{
  "type": "Feature",
  "properties": {
    "gn:admin1_code":"57.0",
    "gn:admin2_code":"19.0",
    "gn:asciiname":"Pypliai",
    "gn:country_code":"LT",
    "gn:dem":79,
    "gn:feature_class":"P",
    "gn:feature_code":"PPL",
    "gn:name":"Pypliai",
    "gn:population":0,
    "gn:timezone":"Europe/Vilnius",
    "iso:country":"LT",
    "name:und_x_variant":[
        "Pypli\u0173",
        "Piple",
        "Pypliai"
    ],
    "wof:name":"Pypliai",
    "wof:placetype":"locality"
},
  "geometry": {"coordinates":[23.7719,54.91472],"type":"Point"}
}