{
  "type": "Feature",
  "properties": {
    "gn:admin1_code":"59.0",
    "gn:admin2_code":"84.0",
    "gn:asciiname":"Skaistgiriai",
    "gn:country_code":"LT",
    "gn:dem":52,
    "gn:feature_class":"P",
    "gn:feature_code":"PPL",
    "gn:name":"Skaistgiriai",
    "gn:population":0,
    "gn:timezone":"Europe/Vilnius",
    "iso:country":"LT",
    "name:lit_x_preferred":[
        "Skaistgiriai"
    ],
    "name:und_x_variant":[
        "Skaysgiry",
        "Skaizgiris",
        "Skaisgirio",
        "Skaisgiri\u0173",
        "Skaisgiriai"
    ],
    "wof:name":"Skaistgiriai",
    "wof:placetype":"locality"
},
  "geometry": {"coordinates":[23.08919,54.89104],"type":"Point"}
}