{
  "type": "Feature",
  "properties": {
    "gn:admin1_code":"60",
    "gn:admin2_code":"36.0",
    "gn:asciiname":"Dreiviskiai",
    "gn:country_code":"LT",
    "gn:dem":51,
    "gn:feature_class":"P",
    "gn:feature_code":"PPL",
    "gn:name":"Dreivi\u0161kiai",
    "gn:population":0,
    "gn:timezone":"Europe/Vilnius",
    "iso:country":"LT",
    "name:lit_x_preferred":[
        "Dreivi\u0161kiai"
    ],
    "wof:name":"Dreiviskiai",
    "wof:placetype":"locality"
},
  "geometry": {"coordinates":[24.78122,56.31538000000001],"type":"Point"}
}