{
  "type": "Feature",
  "properties": {
    "gn:admin1_code":"64",
    "gn:admin2_code":"45.0",
    "gn:asciiname":"Kazakavas",
    "gn:country_code":"LT",
    "gn:dem":176,
    "gn:feature_class":"P",
    "gn:feature_code":"PPL",
    "gn:name":"Kazakavas",
    "gn:population":0,
    "gn:timezone":"Europe/Vilnius",
    "iso:country":"LT",
    "name:lit_x_preferred":[
        "Kazakavas"
    ],
    "wof:name":"Kazakavas",
    "wof:placetype":"locality"
},
  "geometry": {"coordinates":[26.4306,55.32092],"type":"Point"}
}