{
  "type": "Feature",
  "properties": {
    "gn:admin1_code":"65",
    "gn:admin2_code":"79.0",
    "gn:asciiname":"Jurezeris",
    "gn:country_code":"LT",
    "gn:dem":162,
    "gn:feature_class":"P",
    "gn:feature_code":"PPL",
    "gn:name":"Jure\u017eeris",
    "gn:population":0,
    "gn:timezone":"Europe/Vilnius",
    "iso:country":"LT",
    "name:lit_x_preferred":[
        "Jure\u017eeris"
    ],
    "wof:name":"Jurezeris",
    "wof:placetype":"locality"
},
  "geometry": {"coordinates":[24.61512,54.6443],"type":"Point"}
}