{
  "type": "Feature",
  "properties": {
    "gn:admin1_code":"65.0",
    "gn:admin2_code":"81.0",
    "gn:asciiname":"Kraupenai",
    "gn:country_code":"LT",
    "gn:dem":81,
    "gn:feature_class":"P",
    "gn:feature_code":"PPL",
    "gn:name":"Kraup\u0117nai",
    "gn:population":0,
    "gn:timezone":"Europe/Vilnius",
    "iso:country":"LT",
    "name:und_x_variant":[
        "Kroupyany",
        "Kraup\u0117nai"
    ],
    "wof:name":"Kraupenai",
    "wof:placetype":"locality"
},
  "geometry": {"coordinates":[24.72401,55.43026999999999],"type":"Point"}
}