{
  "type": "Feature",
  "properties": {
    "gn:admin1_code":"60",
    "gn:admin2_code":"27.0",
    "gn:asciiname":"Rainaiciai",
    "gn:country_code":"LT",
    "gn:dem":77,
    "gn:feature_class":"P",
    "gn:feature_code":"PPL",
    "gn:name":"Rainai\u010diai",
    "gn:population":0,
    "gn:timezone":"Europe/Vilnius",
    "iso:country":"LT",
    "name:lit_x_preferred":[
        "Rainai\u010diai"
    ],
    "wof:name":"Rainaiciai",
    "wof:placetype":"locality"
},
  "geometry": {"coordinates":[24.42813,55.40321],"type":"Point"}
}