{
  "type": "Feature",
  "properties": {
    "gn:admin1_code":"63.0",
    "gn:admin2_code":"61.0",
    "gn:asciiname":"Daubariai",
    "gn:country_code":"LT",
    "gn:dem":60,
    "gn:feature_class":"P",
    "gn:feature_code":"PPL",
    "gn:name":"Daubariai",
    "gn:population":0,
    "gn:timezone":"Europe/Vilnius",
    "iso:country":"LT",
    "name:lit_x_preferred":[
        "Daubariai"
    ],
    "wof:name":"Daubariai",
    "wof:placetype":"locality"
},
  "geometry": {"coordinates":[22.30983,56.28609],"type":"Point"}
}