{
  "type": "Feature",
  "properties": {
    "gn:admin1_code":"64",
    "gn:admin2_code":"34.0",
    "gn:asciiname":"Zizdra",
    "gn:country_code":"LT",
    "gn:dem":132,
    "gn:feature_class":"P",
    "gn:feature_code":"PPL",
    "gn:name":"Zizdra",
    "gn:population":0,
    "gn:timezone":"Europe/Vilnius",
    "iso:country":"LT",
    "name:lit_x_preferred":[
        "Zizdra"
    ],
    "wof:name":"Zizdra",
    "wof:placetype":"locality"
},
  "geometry": {"coordinates":[25.01503,55.34575],"type":"Point"}
}