{
  "type": "Feature",
  "properties": {
    "gn:admin1_code":"0.0",
    "gn:asciiname":"Pleikiskiai",
    "gn:cc2":"LT",
    "gn:country_code":"LT",
    "gn:dem":9,
    "gn:feature_class":"P",
    "gn:feature_code":"PPL",
    "gn:name":"Pleiki\u0161kiai",
    "gn:population":0,
    "gn:timezone":"Europe/Vilnius",
    "iso:country":"LT",
    "name:und_x_variant":[
        "Plyaykishken",
        "Pleiki\u0161ki\u0173",
        "Pleiki\u0161kiai"
    ],
    "wof:name":"Pleikiskiai",
    "wof:placetype":"locality"
},
  "geometry": {"coordinates":[21.73333,55.21666999999999],"type":"Point"}
}