{
  "type": "Feature",
  "properties": {
    "gn:admin1_code":"62",
    "gn:admin2_code":"77.0",
    "gn:asciiname":"Dvarvieciai",
    "gn:country_code":"LT",
    "gn:dem":17,
    "gn:feature_class":"P",
    "gn:feature_code":"PPL",
    "gn:name":"Dvarvie\u010diai",
    "gn:population":0,
    "gn:timezone":"Europe/Vilnius",
    "iso:country":"LT",
    "name:lit_x_preferred":[
        "Dvarvie\u010diai"
    ],
    "wof:name":"Dvarvieciai",
    "wof:placetype":"locality"
},
  "geometry": {"coordinates":[22.22392,55.21713],"type":"Point"}
}