{
  "type": "Feature",
  "properties": {
    "gn:admin1_code":"60.0",
    "gn:admin2_code":"27.0",
    "gn:asciiname":"Klepsiai",
    "gn:country_code":"LT",
    "gn:dem":61,
    "gn:feature_class":"P",
    "gn:feature_code":"PPL",
    "gn:name":"Klep\u0161iai",
    "gn:population":0,
    "gn:timezone":"Europe/Vilnius",
    "iso:country":"LT",
    "name:und_x_variant":[
        "Klepshi",
        "Klep\u0161iai"
    ],
    "wof:name":"Klepsiai",
    "wof:placetype":"locality"
},
  "geometry": {"coordinates":[24.48084,55.6362],"type":"Point"}
}