{
  "type": "Feature",
  "properties": {
    "gn:admin1_code":"61.0",
    "gn:admin2_code":"71.0",
    "gn:asciiname":"Asteikiai",
    "gn:country_code":"LT",
    "gn:dem":74,
    "gn:feature_class":"P",
    "gn:feature_code":"PPL",
    "gn:name":"Asteikiai",
    "gn:population":0,
    "gn:timezone":"Europe/Vilnius",
    "iso:country":"LT",
    "name:und_x_variant":[
        "Ostreykyay",
        "Asteikiai"
    ],
    "wof:name":"Asteikiai",
    "wof:placetype":"locality"
},
  "geometry": {"coordinates":[23.93093,55.6918],"type":"Point"}
}