{
  "type": "Feature",
  "properties": {
    "gn:admin1_code":"64",
    "gn:admin2_code":"82.0",
    "gn:asciiname":"Kureisiskes",
    "gn:country_code":"LT",
    "gn:dem":132,
    "gn:feature_class":"P",
    "gn:feature_code":"PPL",
    "gn:name":"Kurei\u0161i\u0161k\u0117s",
    "gn:population":0,
    "gn:timezone":"Europe/Vilnius",
    "iso:country":"LT",
    "name:lit_x_preferred":[
        "Kurei\u0161i\u0161k\u0117s"
    ],
    "wof:name":"Kureisiskes",
    "wof:placetype":"locality"
},
  "geometry": {"coordinates":[25.60008,55.60469000000001],"type":"Point"}
}