{
  "type": "Feature",
  "properties": {
    "gn:admin1_code":"59",
    "gn:admin2_code":"84.0",
    "gn:asciiname":"Stumbriske",
    "gn:country_code":"LT",
    "gn:dem":63,
    "gn:feature_class":"P",
    "gn:feature_code":"PPL",
    "gn:name":"Stumbri\u0161k\u0117",
    "gn:population":0,
    "gn:timezone":"Europe/Vilnius",
    "iso:country":"LT",
    "name:lit_x_preferred":[
        "Stumbri\u0161k\u0117"
    ],
    "wof:name":"Stumbriske",
    "wof:placetype":"locality"
},
  "geometry": {"coordinates":[23.14861,54.97633],"type":"Point"}
}