{
  "type": "Feature",
  "properties": {
    "gn:admin1_code":"60.0",
    "gn:admin2_code":"73.0",
    "gn:asciiname":"Laibgaliai",
    "gn:country_code":"LT",
    "gn:dem":132,
    "gn:feature_class":"P",
    "gn:feature_code":"PPL",
    "gn:name":"Laibgaliai",
    "gn:population":0,
    "gn:timezone":"Europe/Vilnius",
    "iso:country":"LT",
    "name:lit_x_preferred":[
        "Laibgaliai"
    ],
    "wof:name":"Laibgaliai",
    "wof:placetype":"locality"
},
  "geometry": {"coordinates":[25.63127,55.90938000000001],"type":"Point"}
}