{
  "type": "Feature",
  "properties": {
    "gn:admin1_code":"64",
    "gn:admin2_code":"34.0",
    "gn:asciiname":"Kiskeliai",
    "gn:country_code":"LT",
    "gn:dem":156,
    "gn:feature_class":"P",
    "gn:feature_code":"PPL",
    "gn:name":"Ki\u0161keliai",
    "gn:population":0,
    "gn:timezone":"Europe/Vilnius",
    "iso:country":"LT",
    "name:lit_x_preferred":[
        "Ki\u0161keliai"
    ],
    "wof:name":"Kiskeliai",
    "wof:placetype":"locality"
},
  "geometry": {"coordinates":[25.16622000000001,55.49244],"type":"Point"}
}