{
  "type": "Feature",
  "properties": {
    "gn:admin1_code":"56",
    "gn:admin2_code":"59.0",
    "gn:asciiname":"Juozapavas",
    "gn:country_code":"LT",
    "gn:dem":149,
    "gn:feature_class":"P",
    "gn:feature_code":"PPL",
    "gn:name":"Juozapavas",
    "gn:population":0,
    "gn:timezone":"Europe/Vilnius",
    "iso:country":"LT",
    "name:lit_x_preferred":[
        "Juozapavas"
    ],
    "wof:name":"Juozapavas",
    "wof:placetype":"locality"
},
  "geometry": {"coordinates":[23.47318,54.18326],"type":"Point"}
}