{
  "type": "Feature",
  "properties": {
    "gn:admin1_code":"60",
    "gn:admin2_code":"67.0",
    "gn:asciiname":"Svirpliskis",
    "gn:country_code":"LT",
    "gn:dem":39,
    "gn:feature_class":"P",
    "gn:feature_code":"PPL",
    "gn:name":"Svirpli\u0161kis",
    "gn:population":0,
    "gn:timezone":"Europe/Vilnius",
    "iso:country":"LT",
    "name:lit_x_preferred":[
        "Svirpli\u0161kis"
    ],
    "wof:name":"Svirpliskis",
    "wof:placetype":"locality"
},
  "geometry": {"coordinates":[24.31881,56.07771999999999],"type":"Point"}
}