{
  "type": "Feature",
  "properties": {
    "gn:admin1_code":"62.0",
    "gn:admin2_code":"77.0",
    "gn:asciiname":"Stirbaiciai",
    "gn:country_code":"LT",
    "gn:dem":32,
    "gn:feature_class":"P",
    "gn:feature_code":"PPL",
    "gn:name":"Stirbai\u010diai",
    "gn:population":0,
    "gn:timezone":"Europe/Vilnius",
    "iso:country":"LT",
    "name:und_x_variant":[
        "Styrbaytse",
        "Stirbai\u010diai"
    ],
    "wof:name":"Stirbaiciai",
    "wof:placetype":"locality"
},
  "geometry": {"coordinates":[22.53024,55.24717],"type":"Point"}
}