{
  "type": "Feature",
  "properties": {
    "gn:admin1_code":"60.0",
    "gn:admin2_code":"36.0",
    "gn:asciiname":"Kratiskiai",
    "gn:country_code":"LT",
    "gn:dem":57,
    "gn:feature_class":"P",
    "gn:feature_code":"PPL",
    "gn:name":"Krati\u0161kiai",
    "gn:population":0,
    "gn:timezone":"Europe/Vilnius",
    "iso:country":"LT",
    "name:eng_x_preferred":[
        "Krati\u0161kiai"
    ],
    "name:rus_x_preferred":[
        "\u041a\u0440\u0430\u0442\u0438\u0448\u043a\u044f\u0439"
    ],
    "name:und_x_variant":[
        "Kratishkiai",
        "Kratishkyay",
        "Krati\u0161ki\u0173"
    ],
    "wof:name":"Kratiskiai",
    "wof:placetype":"locality"
},
  "geometry": {"coordinates":[24.71648,56.10522],"type":"Point"}
}