{
  "type": "Feature",
  "properties": {
    "gn:admin1_code":"56",
    "gn:admin2_code":"11.0",
    "gn:asciiname":"Burbiskes",
    "gn:country_code":"LT",
    "gn:dem":102,
    "gn:feature_class":"P",
    "gn:feature_code":"PPL",
    "gn:name":"Burbi\u0161k\u0117s",
    "gn:population":0,
    "gn:timezone":"Europe/Vilnius",
    "iso:country":"LT",
    "name:lit_x_preferred":[
        "Burbi\u0161k\u0117s"
    ],
    "wof:name":"Burbiskes",
    "wof:placetype":"locality"
},
  "geometry": {"coordinates":[23.93444,54.34714],"type":"Point"}
}