{
  "type": "Feature",
  "properties": {
    "gn:admin1_code":"57",
    "gn:admin2_code":"19.0",
    "gn:asciiname":"Vincentavas",
    "gn:country_code":"LT",
    "gn:dem":64,
    "gn:feature_class":"P",
    "gn:feature_code":"PPL",
    "gn:name":"Vincentavas",
    "gn:population":0,
    "gn:timezone":"Europe/Vilnius",
    "iso:country":"LT",
    "name:lit_x_preferred":[
        "Vincentavas"
    ],
    "wof:name":"Vincentavas",
    "wof:placetype":"locality"
},
  "geometry": {"coordinates":[23.51328,54.97628],"type":"Point"}
}