{
  "type": "Feature",
  "properties": {
    "gn:admin1_code":"65",
    "gn:admin2_code":"79.0",
    "gn:asciiname":"Dembniakai",
    "gn:country_code":"LT",
    "gn:dem":169,
    "gn:feature_class":"P",
    "gn:feature_code":"PPL",
    "gn:name":"Dembniakai",
    "gn:population":0,
    "gn:timezone":"Europe/Vilnius",
    "iso:country":"LT",
    "name:lit_x_preferred":[
        "Dembniakai"
    ],
    "wof:name":"Dembniakai",
    "wof:placetype":"locality"
},
  "geometry": {"coordinates":[24.75275,54.58711],"type":"Point"}
}