{
  "type": "Feature",
  "properties": {
    "gn:admin1_code":"63.0",
    "gn:admin2_code":"78.0",
    "gn:asciiname":"Kirsiai",
    "gn:country_code":"LT",
    "gn:dem":118,
    "gn:feature_class":"P",
    "gn:feature_code":"PPL",
    "gn:name":"Kir\u0161iai",
    "gn:population":0,
    "gn:timezone":"Europe/Vilnius",
    "iso:country":"LT",
    "name:und_x_variant":[
        "Kirshyay",
        "Kir\u0161iai"
    ],
    "wof:name":"Kirsiai",
    "wof:placetype":"locality"
},
  "geometry": {"coordinates":[22.45215,55.99902],"type":"Point"}
}