{
  "type": "Feature",
  "properties": {
    "gn:admin1_code":"64",
    "gn:admin2_code":"82.0",
    "gn:asciiname":"Biliakiemis",
    "gn:country_code":"LT",
    "gn:dem":166,
    "gn:feature_class":"P",
    "gn:feature_code":"PPL",
    "gn:name":"Biliakiemis",
    "gn:population":0,
    "gn:timezone":"Europe/Vilnius",
    "iso:country":"LT",
    "name:lit_x_preferred":[
        "Biliakiemis"
    ],
    "wof:name":"Biliakiemis",
    "wof:placetype":"locality"
},
  "geometry": {"coordinates":[25.6857,55.46366999999999],"type":"Point"}
}