{
  "type": "Feature",
  "properties": {
    "gn:admin1_code":"62",
    "gn:admin2_code":"87.0",
    "gn:asciiname":"Rudiske",
    "gn:country_code":"LT",
    "gn:dem":154,
    "gn:feature_class":"P",
    "gn:feature_code":"PPL",
    "gn:name":"Rudi\u0161k\u0117",
    "gn:population":0,
    "gn:timezone":"Europe/Vilnius",
    "iso:country":"LT",
    "name:lit_x_preferred":[
        "Rudi\u0161k\u0117"
    ],
    "wof:name":"Rudiske",
    "wof:placetype":"locality"
},
  "geometry": {"coordinates":[22.29828,55.5568],"type":"Point"}
}