{
  "type": "Feature",
  "properties": {
    "gn:admin1_code":"0.0",
    "gn:asciiname":"Aluotos",
    "gn:country_code":"LT",
    "gn:dem":95,
    "gn:feature_class":"P",
    "gn:feature_code":"PPL",
    "gn:name":"Aluotos",
    "gn:population":0,
    "gn:timezone":"Europe/Vilnius",
    "iso:country":"LT",
    "name:lit_x_preferred":[
        "Aluotos"
    ],
    "wof:name":"Aluotos",
    "wof:placetype":"locality"
},
  "geometry": {"coordinates":[25.27989,55.72133],"type":"Point"}
}