{
  "type": "Feature",
  "properties": {
    "gn:admin1_code":"64",
    "gn:admin2_code":"82.0",
    "gn:asciiname":"Kruopiskis",
    "gn:country_code":"LT",
    "gn:dem":155,
    "gn:feature_class":"P",
    "gn:feature_code":"PPL",
    "gn:name":"Kruopi\u0161kis",
    "gn:population":0,
    "gn:timezone":"Europe/Vilnius",
    "iso:country":"LT",
    "name:lit_x_preferred":[
        "Kruopi\u0161kis"
    ],
    "wof:name":"Kruopiskis",
    "wof:placetype":"locality"
},
  "geometry": {"coordinates":[25.63884,55.57244],"type":"Point"}
}