{
  "type": "Feature",
  "properties": {
    "gn:admin1_code":"60",
    "gn:admin2_code":"67.0",
    "gn:asciiname":"Dumbliuneliai",
    "gn:country_code":"LT",
    "gn:dem":51,
    "gn:feature_class":"P",
    "gn:feature_code":"PPL",
    "gn:name":"Dumbli\u016bn\u0117liai",
    "gn:population":0,
    "gn:timezone":"Europe/Vilnius",
    "iso:country":"LT",
    "name:lit_x_preferred":[
        "Dumbli\u016bn\u0117liai"
    ],
    "wof:name":"Dumbliuneliai",
    "wof:placetype":"locality"
},
  "geometry": {"coordinates":[24.50398,55.91359],"type":"Point"}
}