{
  "type": "Feature",
  "properties": {
    "gn:admin1_code":"65.0",
    "gn:admin2_code":"86.0",
    "gn:asciiname":"Mezionys",
    "gn:country_code":"LT",
    "gn:dem":180,
    "gn:feature_class":"P",
    "gn:feature_code":"PPL",
    "gn:name":"M\u0117\u017eionys",
    "gn:population":0,
    "gn:timezone":"Europe/Vilnius",
    "iso:country":"LT",
    "name:eng_x_preferred":[
        "Me\u017eionys"
    ],
    "name:lit_x_preferred":[
        "M\u0117\u017eionys"
    ],
    "name:rus_x_preferred":[
        "\u041c\u0435\u0436\u0435\u043d\u0438\u0441"
    ],
    "name:und_x_variant":[
        "Me\u0161konys",
        "Mezhany",
        "Me\u017eionys"
    ],
    "wof:name":"Mezionys",
    "wof:placetype":"locality"
},
  "geometry": {"coordinates":[26.05643,55.1018],"type":"Point"}
}