{
  "type": "Feature",
  "properties": {
    "gn:admin1_code":"63",
    "gn:admin2_code":"61.0",
    "gn:asciiname":"Kuslenai",
    "gn:country_code":"LT",
    "gn:dem":69,
    "gn:feature_class":"P",
    "gn:feature_code":"PPL",
    "gn:name":"Ku\u0161l\u0117nai",
    "gn:population":0,
    "gn:timezone":"Europe/Vilnius",
    "iso:country":"LT",
    "name:lit_x_preferred":[
        "Ku\u0161l\u0117nai"
    ],
    "wof:name":"Kuslenai",
    "wof:placetype":"locality"
},
  "geometry": {"coordinates":[22.25411,56.35693000000001],"type":"Point"}
}