{
  "type": "Feature",
  "properties": {
    "gn:admin1_code":"65.0",
    "gn:admin2_code":"81.0",
    "gn:asciiname":"Varzos",
    "gn:country_code":"LT",
    "gn:dem":82,
    "gn:feature_class":"P",
    "gn:feature_code":"PPL",
    "gn:name":"Var\u017eos",
    "gn:population":0,
    "gn:timezone":"Europe/Vilnius",
    "iso:country":"LT",
    "name:und_x_variant":[
        "Var\u017eos Pirmosios",
        "Var\u017eos",
        "Varzhos",
        "Var\u017e\u0173",
        "Vai\u017eu",
        "Vorzhi",
        "Var\u017eos I"
    ],
    "wof:name":"Varzos",
    "wof:placetype":"locality"
},
  "geometry": {"coordinates":[24.68571,55.33324],"type":"Point"}
}