{
  "type": "Feature",
  "properties": {
    "gn:admin1_code":"64",
    "gn:admin2_code":"62.0",
    "gn:asciiname":"Vysnialaukis",
    "gn:country_code":"LT",
    "gn:dem":174,
    "gn:feature_class":"P",
    "gn:feature_code":"PPL",
    "gn:name":"Vysnialaukis",
    "gn:population":0,
    "gn:timezone":"Europe/Vilnius",
    "iso:country":"LT",
    "name:lit_x_preferred":[
        "Vysnialaukis"
    ],
    "wof:name":"Vysnialaukis",
    "wof:placetype":"locality"
},
  "geometry": {"coordinates":[25.60768,55.36252],"type":"Point"}
}