{
  "type": "Feature",
  "properties": {
    "gn:admin1_code":"61",
    "gn:admin2_code":"54.0",
    "gn:asciiname":"Pavezupis",
    "gn:country_code":"LT",
    "gn:dem":135,
    "gn:feature_class":"P",
    "gn:feature_code":"PPL",
    "gn:name":"Pav\u0117\u017eupis",
    "gn:population":0,
    "gn:timezone":"Europe/Vilnius",
    "iso:country":"LT",
    "name:lit_x_preferred":[
        "Pav\u0117\u017eupis"
    ],
    "wof:name":"Pavezupis",
    "wof:placetype":"locality"
},
  "geometry": {"coordinates":[22.95133,55.76129],"type":"Point"}
}