{
  "type": "Feature",
  "properties": {
    "gn:admin1_code":"57.0",
    "gn:admin2_code":"53.0",
    "gn:asciiname":"Siukstuliskiai",
    "gn:country_code":"LT",
    "gn:dem":48,
    "gn:feature_class":"P",
    "gn:feature_code":"PPL",
    "gn:name":"\u0160iuk\u0161tuli\u0161kiai",
    "gn:population":0,
    "gn:timezone":"Europe/Vilnius",
    "iso:country":"LT",
    "name:und_x_variant":[
        "Shyukshtulishkyay",
        "Shukshtolishkyay",
        "Shukshtolishki",
        "\u0160iuk\u0161tuli\u0161kiai"
    ],
    "wof:name":"Siukstuliskiai",
    "wof:placetype":"locality"
},
  "geometry": {"coordinates":[23.86134,55.29753],"type":"Point"}
}