{
  "type": "Feature",
  "properties": {
    "gn:admin1_code":"65",
    "gn:admin2_code":"81.0",
    "gn:asciiname":"Laukeliai",
    "gn:country_code":"LT",
    "gn:dem":128,
    "gn:feature_class":"P",
    "gn:feature_code":"PPL",
    "gn:name":"Laukeliai",
    "gn:population":0,
    "gn:timezone":"Europe/Vilnius",
    "iso:country":"LT",
    "name:lit_x_preferred":[
        "Laukeliai"
    ],
    "wof:name":"Laukeliai",
    "wof:placetype":"locality"
},
  "geometry": {"coordinates":[25.06574,55.25739],"type":"Point"}
}