{
  "type": "Feature",
  "properties": {
    "gn:admin1_code":"63.0",
    "gn:admin2_code":"78.0",
    "gn:asciiname":"Pasruoje",
    "gn:country_code":"LT",
    "gn:dem":121,
    "gn:feature_class":"P",
    "gn:feature_code":"PPL",
    "gn:name":"Pasruoj\u0117",
    "gn:population":0,
    "gn:timezone":"Europe/Vilnius",
    "iso:country":"LT",
    "name:lit_x_preferred":[
        "Pasruoj\u0117"
    ],
    "name:und_x_variant":[
        "Posrui",
        "Pasruoye"
    ],
    "wof:name":"Pasruoje",
    "wof:placetype":"locality"
},
  "geometry": {"coordinates":[22.09564,56.08466],"type":"Point"}
}