{
  "type": "Feature",
  "properties": {
    "gn:admin1_code":"61",
    "gn:admin2_code":"29.0",
    "gn:asciiname":"Tarvydziai",
    "gn:country_code":"LT",
    "gn:dem":108,
    "gn:feature_class":"P",
    "gn:feature_code":"PPL",
    "gn:name":"Tarvyd\u017eiai",
    "gn:population":0,
    "gn:timezone":"Europe/Vilnius",
    "iso:country":"LT",
    "name:lit_x_preferred":[
        "Tarvyd\u017eiai"
    ],
    "wof:name":"Tarvydziai",
    "wof:placetype":"locality"
},
  "geometry": {"coordinates":[22.75095,56.06396],"type":"Point"}
}