{
  "type": "Feature",
  "properties": {
    "gn:admin1_code":"61.0",
    "gn:admin2_code":"71.0",
    "gn:asciiname":"Jokubiskiai",
    "gn:country_code":"LT",
    "gn:dem":126,
    "gn:feature_class":"P",
    "gn:feature_code":"PPL",
    "gn:name":"Jok\u016bbi\u0161kiai",
    "gn:population":0,
    "gn:timezone":"Europe/Vilnius",
    "iso:country":"LT",
    "name:und_x_variant":[
        "Yakubishkyay",
        "Jok\u016bbi\u0161kiai"
    ],
    "wof:name":"Jokubiskiai",
    "wof:placetype":"locality"
},
  "geometry": {"coordinates":[23.4686,55.69064],"type":"Point"}
}