{
  "type": "Feature",
  "properties": {
    "gn:admin1_code":"0.0",
    "gn:asciiname":"Rauskas",
    "gn:cc2":"LT",
    "gn:country_code":"LT",
    "gn:dem":92,
    "gn:feature_class":"P",
    "gn:feature_code":"PPL",
    "gn:name":"Rau\u0161kas",
    "gn:population":0,
    "gn:timezone":"Europe/Vilnius",
    "iso:country":"LT",
    "name:und_x_variant":[
        "Ravshkyay",
        "Rau\u0161kas"
    ],
    "wof:name":"Rauskas",
    "wof:placetype":"locality"
},
  "geometry": {"coordinates":[22.11667000000001,55.41667],"type":"Point"}
}