{
  "type": "Feature",
  "properties": {
    "gn:admin1_code":"57.0",
    "gn:admin2_code":"49.0",
    "gn:asciiname":"Sekionys",
    "gn:country_code":"LT",
    "gn:dem":52,
    "gn:feature_class":"P",
    "gn:feature_code":"PPL",
    "gn:name":"Sekionys",
    "gn:population":0,
    "gn:timezone":"Europe/Vilnius",
    "iso:country":"LT",
    "name:und_x_variant":[
        "Sekio",
        "Sekany",
        "Sekioni\u0173",
        "Sekionys"
    ],
    "wof:name":"Sekionys",
    "wof:placetype":"locality"
},
  "geometry": {"coordinates":[24.09318,54.69817],"type":"Point"}
}