{
  "type": "Feature",
  "properties": {
    "gn:admin1_code":"60",
    "gn:admin2_code":"36.0",
    "gn:asciiname":"Valantiskis",
    "gn:country_code":"LT",
    "gn:dem":53,
    "gn:feature_class":"P",
    "gn:feature_code":"PPL",
    "gn:name":"Valanti\u0161kis",
    "gn:population":0,
    "gn:timezone":"Europe/Vilnius",
    "iso:country":"LT",
    "name:lit_x_preferred":[
        "Valanti\u0161kis"
    ],
    "wof:name":"Valantiskis",
    "wof:placetype":"locality"
},
  "geometry": {"coordinates":[24.7173,56.18999],"type":"Point"}
}