{
  "type": "Feature",
  "properties": {
    "gn:admin1_code":"64",
    "gn:admin2_code":"62.0",
    "gn:asciiname":"Pakamanys",
    "gn:country_code":"LT",
    "gn:dem":157,
    "gn:feature_class":"P",
    "gn:feature_code":"PPL",
    "gn:name":"Pakamanys",
    "gn:population":0,
    "gn:timezone":"Europe/Vilnius",
    "iso:country":"LT",
    "name:lit_x_preferred":[
        "Pakamanys"
    ],
    "wof:name":"Pakamanys",
    "wof:placetype":"locality"
},
  "geometry": {"coordinates":[25.59938,55.09766],"type":"Point"}
}