{
  "type": "Feature",
  "properties": {
    "gn:admin1_code":"64",
    "gn:admin2_code":"43.0",
    "gn:asciiname":"Repka",
    "gn:country_code":"LT",
    "gn:dem":165,
    "gn:feature_class":"P",
    "gn:feature_code":"PPL",
    "gn:name":"R\u0117pka",
    "gn:population":0,
    "gn:timezone":"Europe/Vilnius",
    "iso:country":"LT",
    "name:lit_x_preferred":[
        "R\u0117pka"
    ],
    "wof:name":"Repka",
    "wof:placetype":"locality"
},
  "geometry": {"coordinates":[26.30418,55.69708000000001],"type":"Point"}
}