{
  "type": "Feature",
  "properties": {
    "gn:admin1_code":"60.0",
    "gn:admin2_code":"67.0",
    "gn:asciiname":"Gegabrasta",
    "gn:country_code":"LT",
    "gn:dem":40,
    "gn:feature_class":"P",
    "gn:feature_code":"PPL",
    "gn:name":"Gegabrasta",
    "gn:population":0,
    "gn:timezone":"Europe/Vilnius",
    "iso:country":"LT",
    "name:und_x_variant":[
        "Gegobrastos",
        "Gegabrasta",
        "Gegobrasta"
    ],
    "wof:name":"Gegabrasta",
    "wof:placetype":"locality"
},
  "geometry": {"coordinates":[24.30378,55.9677],"type":"Point"}
}