{
  "type": "Feature",
  "properties": {
    "gn:admin1_code":"57",
    "gn:admin2_code":"69.0",
    "gn:asciiname":"Sutrukas",
    "gn:country_code":"LT",
    "gn:dem":186,
    "gn:feature_class":"P",
    "gn:feature_code":"PPL",
    "gn:name":"Sutrukas",
    "gn:population":0,
    "gn:timezone":"Europe/Vilnius",
    "iso:country":"LT",
    "name:lit_x_preferred":[
        "Sutrukas"
    ],
    "wof:name":"Sutrukas",
    "wof:placetype":"locality"
},
  "geometry": {"coordinates":[24.42385,54.59307],"type":"Point"}
}