{
  "type": "Feature",
  "properties": {
    "gn:admin1_code":"58.0",
    "gn:admin2_code":"21.0",
    "gn:asciiname":"Kapstatai",
    "gn:country_code":"LT",
    "gn:dem":115,
    "gn:feature_class":"P",
    "gn:feature_code":"PPL",
    "gn:name":"Kapstatai",
    "gn:population":0,
    "gn:timezone":"Europe/Vilnius",
    "iso:country":"LT",
    "name:und_x_variant":[
        "Kapstot\u0173",
        "Kapstatay",
        "Kapstatai"
    ],
    "wof:name":"Kapstatai",
    "wof:placetype":"locality"
},
  "geometry": {"coordinates":[21.75447,55.70408000000001],"type":"Point"}
}