{
  "type": "Feature",
  "properties": {
    "gn:admin1_code":"61.0",
    "gn:admin2_code":"54.0",
    "gn:asciiname":"Paalksniai",
    "gn:country_code":"LT",
    "gn:dem":166,
    "gn:feature_class":"P",
    "gn:feature_code":"PPL",
    "gn:name":"Paalksniai",
    "gn:population":0,
    "gn:timezone":"Europe/Vilnius",
    "iso:country":"LT",
    "name:und_x_variant":[
        "Poal\u2019ksne",
        "Paalksniai"
    ],
    "wof:name":"Paalksniai",
    "wof:placetype":"locality"
},
  "geometry": {"coordinates":[22.55991,55.63567],"type":"Point"}
}