{
  "type": "Feature",
  "properties": {
    "gn:admin1_code":"59.0",
    "gn:admin2_code":"84.0",
    "gn:asciiname":"Ramoniskiai",
    "gn:country_code":"LT",
    "gn:dem":37,
    "gn:feature_class":"P",
    "gn:feature_code":"PPL",
    "gn:name":"Ramoni\u0161kiai",
    "gn:population":0,
    "gn:timezone":"Europe/Vilnius",
    "iso:country":"LT",
    "name:und_x_variant":[
        "Romanishki",
        "Ramoni\u0161kiai"
    ],
    "wof:name":"Ramoniskiai",
    "wof:placetype":"locality"
},
  "geometry": {"coordinates":[22.59961,55.04883],"type":"Point"}
}