{
  "type": "Feature",
  "properties": {
    "gn:admin1_code":"60",
    "gn:admin2_code":"73.0",
    "gn:asciiname":"Miskonys",
    "gn:country_code":"LT",
    "gn:dem":90,
    "gn:feature_class":"P",
    "gn:feature_code":"PPL",
    "gn:name":"Mi\u0161konys",
    "gn:population":0,
    "gn:timezone":"Europe/Vilnius",
    "iso:country":"LT",
    "name:lit_x_preferred":[
        "Mi\u0161konys"
    ],
    "wof:name":"Miskonys",
    "wof:placetype":"locality"
},
  "geometry": {"coordinates":[25.31534,55.86955],"type":"Point"}
}