{
  "type": "Feature",
  "properties": {
    "gn:admin1_code":"58",
    "gn:admin2_code":"21.0",
    "gn:asciiname":"Klemiske I",
    "gn:country_code":"LT",
    "gn:dem":17,
    "gn:feature_class":"P",
    "gn:feature_code":"PPL",
    "gn:name":"Klemisk\u0117 I",
    "gn:population":0,
    "gn:timezone":"Europe/Vilnius",
    "iso:country":"LT",
    "name:lit_x_preferred":[
        "Klemisk\u0117 I"
    ],
    "wof:name":"Klemiske I",
    "wof:placetype":"locality"
},
  "geometry": {"coordinates":[21.20478,55.72276],"type":"Point"}
}