{
  "type": "Feature",
  "properties": {
    "gn:admin1_code":"56",
    "gn:admin2_code":"11.0",
    "gn:asciiname":"Ziukai",
    "gn:country_code":"LT",
    "gn:dem":140,
    "gn:feature_class":"P",
    "gn:feature_code":"PPL",
    "gn:name":"\u017di\u016bkai",
    "gn:population":0,
    "gn:timezone":"Europe/Vilnius",
    "iso:country":"LT",
    "name:lit_x_preferred":[
        "\u017di\u016bkai"
    ],
    "wof:name":"Ziukai",
    "wof:placetype":"locality"
},
  "geometry": {"coordinates":[24.10587,54.4427],"type":"Point"}
}