{
  "type": "Feature",
  "properties": {
    "gn:admin1_code":"65",
    "gn:admin2_code":"79.0",
    "gn:asciiname":"Svirneliai",
    "gn:country_code":"LT",
    "gn:dem":143,
    "gn:feature_class":"P",
    "gn:feature_code":"PPL",
    "gn:name":"Svirneliai",
    "gn:population":0,
    "gn:timezone":"Europe/Vilnius",
    "iso:country":"LT",
    "name:lit_x_preferred":[
        "Svirneliai"
    ],
    "wof:name":"Svirneliai",
    "wof:placetype":"locality"
},
  "geometry": {"coordinates":[24.43151,54.47654],"type":"Point"}
}