{
  "type": "Feature",
  "properties": {
    "gn:admin1_code":"59.0",
    "gn:admin2_code":"84.0",
    "gn:asciiname":"Zemoji Panemune",
    "gn:country_code":"LT",
    "gn:dem":56,
    "gn:feature_class":"P",
    "gn:feature_code":"PPL",
    "gn:name":"\u017demoji Panemun\u0117",
    "gn:population":0,
    "gn:timezone":"Europe/Vilnius",
    "iso:country":"LT",
    "name:ceb_x_preferred":[
        "\u017demoji Panemun\u0117"
    ],
    "name:est_x_preferred":[
        "\u017demoji Panemun\u0117"
    ],
    "name:fin_x_preferred":[
        "\u017demoji Panemun\u0117"
    ],
    "name:lit_x_preferred":[
        "\u017demoji Panemun\u0117"
    ],
    "name:nld_x_preferred":[
        "\u017demoji Panemun\u0117"
    ],
    "name:pol_x_preferred":[
        "Poniemu\u0144"
    ],
    "name:swe_x_preferred":[
        "\u017demoji Panemun\u0117"
    ],
    "name:und_x_variant":[
        "Panemun\u0117s \u017demosios"
    ],
    "wof:name":"Zemoji Panemune",
    "wof:placetype":"locality"
},
  "geometry": {"coordinates":[23.46911,55.04535],"type":"Point"}
}