{
  "type": "Feature",
  "properties": {
    "gn:admin1_code":"62",
    "gn:admin2_code":"63.0",
    "gn:asciiname":"Zemuciai",
    "gn:country_code":"LT",
    "gn:dem":39,
    "gn:feature_class":"P",
    "gn:feature_code":"PPL",
    "gn:name":"\u017demu\u010diai",
    "gn:population":0,
    "gn:timezone":"Europe/Vilnius",
    "iso:country":"LT",
    "name:lit_x_preferred":[
        "\u017demu\u010diai"
    ],
    "wof:name":"Zemuciai",
    "wof:placetype":"locality"
},
  "geometry": {"coordinates":[21.97487000000001,55.23984],"type":"Point"}
}