{
  "type": "Feature",
  "properties": {
    "gn:admin1_code":"59",
    "gn:admin2_code":"18.0",
    "gn:asciiname":"Buriskiai",
    "gn:country_code":"LT",
    "gn:dem":111,
    "gn:feature_class":"P",
    "gn:feature_code":"PPL",
    "gn:name":"B\u016bri\u0161kiai",
    "gn:population":0,
    "gn:timezone":"Europe/Vilnius",
    "iso:country":"LT",
    "name:lit_x_preferred":[
        "B\u016bri\u0161kiai"
    ],
    "wof:name":"Buriskiai",
    "wof:placetype":"locality"
},
  "geometry": {"coordinates":[23.40516,54.42419],"type":"Point"}
}