{
  "type": "Feature",
  "properties": {
    "gn:admin1_code":"60.0",
    "gn:admin2_code":"27.0",
    "gn:asciiname":"Vilkiskis",
    "gn:country_code":"LT",
    "gn:dem":48,
    "gn:feature_class":"P",
    "gn:feature_code":"PPL",
    "gn:name":"Vilki\u0161kis",
    "gn:population":0,
    "gn:timezone":"Europe/Vilnius",
    "iso:country":"LT",
    "name:und_x_variant":[
        "Vil\u2019kishki",
        "Vilki\u0161kis"
    ],
    "wof:name":"Vilkiskis",
    "wof:placetype":"locality"
},
  "geometry": {"coordinates":[24.20348,55.77834],"type":"Point"}
}