{
  "type": "Feature",
  "properties": {
    "gn:admin1_code":"64",
    "gn:admin2_code":"34.0",
    "gn:asciiname":"Petkunai",
    "gn:country_code":"LT",
    "gn:dem":85,
    "gn:feature_class":"P",
    "gn:feature_code":"PPL",
    "gn:name":"Petk\u016bnai",
    "gn:population":0,
    "gn:timezone":"Europe/Vilnius",
    "iso:country":"LT",
    "name:lit_x_preferred":[
        "Petk\u016bnai"
    ],
    "wof:name":"Petkunai",
    "wof:placetype":"locality"
},
  "geometry": {"coordinates":[24.78339,55.65798],"type":"Point"}
}