{
  "type": "Feature",
  "properties": {
    "gn:admin1_code":"58",
    "gn:admin2_code":"75.0",
    "gn:asciiname":"Girsinai",
    "gn:country_code":"LT",
    "gn:dem":59,
    "gn:feature_class":"P",
    "gn:feature_code":"PPL",
    "gn:name":"Gir\u0161inai",
    "gn:population":0,
    "gn:timezone":"Europe/Vilnius",
    "iso:country":"LT",
    "name:lit_x_preferred":[
        "Gir\u0161inai"
    ],
    "wof:name":"Girsinai",
    "wof:placetype":"locality"
},
  "geometry": {"coordinates":[21.62345,56.18086],"type":"Point"}
}