{
  "type": "Feature",
  "properties": {
    "gn:admin1_code":"57.0",
    "gn:admin2_code":"72.0",
    "gn:asciiname":"Molavenai",
    "gn:country_code":"LT",
    "gn:dem":107,
    "gn:feature_class":"P",
    "gn:feature_code":"PPL",
    "gn:name":"Molav\u0117nai",
    "gn:population":0,
    "gn:timezone":"Europe/Vilnius",
    "iso:country":"LT",
    "name:lit_x_preferred":[
        "Molav\u0117nai"
    ],
    "name:und_x_variant":[
        "Malovenay"
    ],
    "wof:name":"Molavenai",
    "wof:placetype":"locality"
},
  "geometry": {"coordinates":[22.87964,55.45557],"type":"Point"}
}