{
  "type": "Feature",
  "properties": {
    "gn:admin1_code":"64",
    "gn:admin2_code":"34.0",
    "gn:asciiname":"Naujadalis",
    "gn:country_code":"LT",
    "gn:dem":80,
    "gn:feature_class":"P",
    "gn:feature_code":"PPL",
    "gn:name":"Naujadalis",
    "gn:population":0,
    "gn:timezone":"Europe/Vilnius",
    "iso:country":"LT",
    "name:lit_x_preferred":[
        "Naujadalis"
    ],
    "wof:name":"Naujadalis",
    "wof:placetype":"locality"
},
  "geometry": {"coordinates":[24.7591,55.53142],"type":"Point"}
}