{
  "type": "Feature",
  "properties": {
    "gn:admin1_code":"61.0",
    "gn:admin2_code":"29.0",
    "gn:asciiname":"Paezeriai",
    "gn:country_code":"LT",
    "gn:dem":119,
    "gn:feature_class":"P",
    "gn:feature_code":"PPL",
    "gn:name":"Pae\u017eeriai",
    "gn:population":0,
    "gn:timezone":"Europe/Vilnius",
    "iso:country":"LT",
    "name:lit_x_preferred":[
        "Pae\u017eeriai"
    ],
    "name:und_x_variant":[
        "Fol\u2019vark Poyeziory",
        "Dvaras Pae\u017eeriai"
    ],
    "wof:name":"Paezeriai",
    "wof:placetype":"locality"
},
  "geometry": {"coordinates":[22.80318,55.95834],"type":"Point"}
}