{
  "type": "Feature",
  "properties": {
    "gn:admin1_code":"60.0",
    "gn:admin2_code":"67.0",
    "gn:asciiname":"Mikenai",
    "gn:country_code":"LT",
    "gn:dem":55,
    "gn:feature_class":"P",
    "gn:feature_code":"PPL",
    "gn:name":"Mik\u0117nai",
    "gn:population":0,
    "gn:timezone":"Europe/Vilnius",
    "iso:country":"LT",
    "name:und_x_variant":[
        "Mikyany",
        "Mik\u0117nai"
    ],
    "wof:name":"Mikenai",
    "wof:placetype":"locality"
},
  "geometry": {"coordinates":[24.56851,55.92242],"type":"Point"}
}