{
  "type": "Feature",
  "properties": {
    "gn:admin1_code":"64",
    "gn:admin2_code":"34.0",
    "gn:asciiname":"Pagrizai",
    "gn:country_code":"LT",
    "gn:dem":144,
    "gn:feature_class":"P",
    "gn:feature_code":"PPL",
    "gn:name":"Pagri\u017eai",
    "gn:population":0,
    "gn:timezone":"Europe/Vilnius",
    "iso:country":"LT",
    "name:lit_x_preferred":[
        "Pagri\u017eai"
    ],
    "wof:name":"Pagrizai",
    "wof:placetype":"locality"
},
  "geometry": {"coordinates":[25.31741,55.44342],"type":"Point"}
}