{
  "type": "Feature",
  "properties": {
    "gn:admin1_code":"61.0",
    "gn:admin2_code":"71.0",
    "gn:asciiname":"Daukantai",
    "gn:country_code":"LT",
    "gn:dem":80,
    "gn:feature_class":"P",
    "gn:feature_code":"PPL",
    "gn:name":"Daukantai",
    "gn:population":0,
    "gn:timezone":"Europe/Vilnius",
    "iso:country":"LT",
    "name:und_x_variant":[
        "Rokonay",
        "Rokoniai"
    ],
    "wof:name":"Daukantai",
    "wof:placetype":"locality"
},
  "geometry": {"coordinates":[23.90869,55.71686999999999],"type":"Point"}
}