{
  "type": "Feature",
  "properties": {
    "gn:admin1_code":"64",
    "gn:admin2_code":"82.0",
    "gn:asciiname":"Norvaisiai",
    "gn:country_code":"LT",
    "gn:dem":160,
    "gn:feature_class":"P",
    "gn:feature_code":"PPL",
    "gn:name":"Norvai\u0161iai",
    "gn:population":0,
    "gn:timezone":"Europe/Vilnius",
    "iso:country":"LT",
    "name:lit_x_preferred":[
        "Norvai\u0161iai"
    ],
    "wof:name":"Norvaisiai",
    "wof:placetype":"locality"
},
  "geometry": {"coordinates":[25.6836,55.55691],"type":"Point"}
}