{
  "type": "Feature",
  "properties": {
    "gn:gn_country":"LT",
    "gn:gn_fcode":"PPL",
    "gn:gn_pop":7321,
    "gn:population":7321,
    "iso:country":"LT",
    "name:eng_x_preferred":[
        "\u0160irvintos"
    ],
    "name:rus_x_preferred":[
        "\u0428\u0438\u0440\u0432\u0438\u043d\u0442\u043e\u0441"
    ],
    "name:unk_x_variant":[
        "Szyrwinty"
    ],
    "qs_pg:aaroncc":"LT",
    "qs_pg:gn_country":"LT",
    "qs_pg:gn_fcode":"PPL",
    "qs_pg:gn_pop":7321,
    "qs_pg:name":"\u0160 Irvintos",
    "qs_pg:name_adm0":"Lietuva",
    "qs_pg:name_adm1":"Vilniaus Apskritis",
    "qs_pg:photos_9k":1,
    "qs_pg:photos_9r":1,
    "qs_pg:photos_all":1,
    "qs_pg:photos_sr":0,
    "qs_pg:pop_sr":5,
    "qs_pg:qs_pg_placetype":"locality",
    "qs_pg:qs_pg_placetype_gp":"Town",
    "qs_pg:woe_adm0":23424875,
    "woe:adm0_id":23424875,
    "woe:name_adm0":"Lietuva",
    "woe:name_adm1":"Vilniaus Apskritis",
    "woe:placetype":"Town",
    "wof:name":"\u0160 Irvintos",
    "wof:placetype":"locality",
    "wof:population":7321
},
  "geometry": {"coordinates":[24.95,55.05],"type":"Point"}
}