{
  "type": "Feature",
  "properties": {
    "gn:admin1_code":"61",
    "gn:admin2_code":"54.0",
    "gn:asciiname":"Varlakojai",
    "gn:country_code":"LT",
    "gn:dem":143,
    "gn:feature_class":"P",
    "gn:feature_code":"PPL",
    "gn:name":"Varlakojai",
    "gn:population":0,
    "gn:timezone":"Europe/Vilnius",
    "iso:country":"LT",
    "name:lit_x_preferred":[
        "Varlakojai"
    ],
    "wof:name":"Varlakojai",
    "wof:placetype":"locality"
},
  "geometry": {"coordinates":[22.66249,55.61865],"type":"Point"}
}