{
  "type": "Feature",
  "properties": {
    "gn:admin1_code":"60",
    "gn:admin2_code":"27.0",
    "gn:asciiname":"Pruseliai",
    "gn:country_code":"LT",
    "gn:dem":62,
    "gn:feature_class":"P",
    "gn:feature_code":"PPL",
    "gn:name":"Pr\u016bseliai",
    "gn:population":0,
    "gn:timezone":"Europe/Vilnius",
    "iso:country":"LT",
    "name:lit_x_preferred":[
        "Pr\u016bseliai"
    ],
    "wof:name":"Pruseliai",
    "wof:placetype":"locality"
},
  "geometry": {"coordinates":[24.68803,55.87317],"type":"Point"}
}