{
  "type": "Feature",
  "properties": {
    "gn:admin1_code":"57",
    "gn:admin2_code":"49.0",
    "gn:asciiname":"Muldiskes",
    "gn:country_code":"LT",
    "gn:dem":95,
    "gn:feature_class":"P",
    "gn:feature_code":"PPL",
    "gn:name":"Muldi\u0161k\u0117s",
    "gn:population":0,
    "gn:timezone":"Europe/Vilnius",
    "iso:country":"LT",
    "name:lit_x_preferred":[
        "Muldi\u0161k\u0117s"
    ],
    "wof:name":"Muldiskes",
    "wof:placetype":"locality"
},
  "geometry": {"coordinates":[24.39987,54.91041],"type":"Point"}
}