{
  "type": "Feature",
  "properties": {
    "gn:admin1_code":"63.0",
    "gn:admin2_code":"78.0",
    "gn:asciiname":"Juciai",
    "gn:country_code":"LT",
    "gn:dem":119,
    "gn:feature_class":"P",
    "gn:feature_code":"PPL",
    "gn:name":"Juciai",
    "gn:population":0,
    "gn:timezone":"Europe/Vilnius",
    "iso:country":"LT",
    "name:und_x_variant":[
        "Yuchay",
        "Juciai"
    ],
    "wof:name":"Juciai",
    "wof:placetype":"locality"
},
  "geometry": {"coordinates":[22.49137,55.92156],"type":"Point"}
}