{
  "type": "Feature",
  "properties": {
    "gn:admin1_code":"59.0",
    "gn:admin2_code":"84.0",
    "gn:asciiname":"Prancai",
    "gn:country_code":"LT",
    "gn:dem":61,
    "gn:feature_class":"P",
    "gn:feature_code":"PPL",
    "gn:name":"Prancai",
    "gn:population":0,
    "gn:timezone":"Europe/Vilnius",
    "iso:country":"LT",
    "name:und_x_variant":[
        "Prantsyay",
        "Prantse",
        "Prancai"
    ],
    "wof:name":"Prancai",
    "wof:placetype":"locality"
},
  "geometry": {"coordinates":[23.14912,55.00748000000001],"type":"Point"}
}