{
  "type": "Feature",
  "properties": {
    "gn:admin1_code":"64.0",
    "gn:admin2_code":"62.0",
    "gn:asciiname":"Avilciai",
    "gn:country_code":"LT",
    "gn:dem":151,
    "gn:feature_class":"P",
    "gn:feature_code":"PPL",
    "gn:name":"Avil\u010diai",
    "gn:population":0,
    "gn:timezone":"Europe/Vilnius",
    "iso:country":"LT",
    "name:eng_x_preferred":[
        "Aviliai"
    ],
    "name:lit_x_preferred":[
        "Avil\u010diai"
    ],
    "name:rus_x_preferred":[
        "\u0410\u0432\u0438\u043b\u044c\u0447\u044f\u0439"
    ],
    "name:und_x_variant":[
        "Avil\u010diai",
        "Avil\u2019chyay",
        "Avili\u0173",
        "Al\u2019vil\u2019tsy",
        "Aviliai"
    ],
    "wof:name":"Avilciai",
    "wof:placetype":"locality"
},
  "geometry": {"coordinates":[25.3464,55.2923],"type":"Point"}
}