{
  "type": "Feature",
  "properties": {
    "gn:admin1_code":"64",
    "gn:admin2_code":"43.0",
    "gn:asciiname":"Pempes",
    "gn:country_code":"LT",
    "gn:dem":161,
    "gn:feature_class":"P",
    "gn:feature_code":"PPL",
    "gn:name":"Pemp\u0117s",
    "gn:population":0,
    "gn:timezone":"Europe/Vilnius",
    "iso:country":"LT",
    "name:lit_x_preferred":[
        "Pemp\u0117s"
    ],
    "wof:name":"Pempes",
    "wof:placetype":"locality"
},
  "geometry": {"coordinates":[25.90878,55.71113],"type":"Point"}
}