{
  "type": "Feature",
  "properties": {
    "gn:admin1_code":"65.0",
    "gn:admin2_code":"13.0",
    "gn:asciiname":"Glitiskes",
    "gn:country_code":"LT",
    "gn:dem":138,
    "gn:feature_class":"P",
    "gn:feature_code":"PPL",
    "gn:name":"Gliti\u0161k\u0117s",
    "gn:population":0,
    "gn:timezone":"Europe/Vilnius",
    "iso:country":"LT",
    "name:und_x_variant":[
        "Gliti\u0161k\u0117s"
    ],
    "wof:name":"Glitiskes",
    "wof:placetype":"locality"
},
  "geometry": {"coordinates":[25.2301,54.98147],"type":"Point"}
}