{
  "type": "Feature",
  "properties": {
    "gn:admin1_code":"65.0",
    "gn:admin2_code":"13.0",
    "gn:asciiname":"Glitiskes",
    "gn:country_code":"LT",
    "gn:dem":138,
    "gn:feature_class":"P",
    "gn:feature_code":"PPL",
    "gn:name":"Gliti\u0161k\u0117s",
    "gn:population":0,
    "gn:timezone":"Europe/Vilnius",
    "iso:country":"LT",
    "name:ceb_x_preferred":[
        "Gliti\u0161k\u0117s"
    ],
    "name:fra_x_preferred":[
        "Gliti\u0161k\u0117s"
    ],
    "name:lit_x_preferred":[
        "Gliti\u0161k\u0117s"
    ],
    "name:nld_x_preferred":[
        "Gliti\u0161k\u0117s"
    ],
    "name:pol_x_preferred":[
        "Glinciszki"
    ],
    "name:rus_x_preferred":[
        "\u0413\u043b\u0438\u0442\u0438\u0448\u043a\u0435\u0441"
    ],
    "name:swe_x_preferred":[
        "Gliti\u0161k\u0117s"
    ],
    "wof:name":"Glitiskes",
    "wof:placetype":"locality"
},
  "geometry": {"coordinates":[25.2301,54.98147],"type":"Point"}
}