{
  "type": "Feature",
  "properties": {
    "gn:admin1_code":"57.0",
    "gn:admin2_code":"46.0",
    "gn:asciiname":"Zeimeliai",
    "gn:country_code":"LT",
    "gn:dem":87,
    "gn:feature_class":"P",
    "gn:feature_code":"PPL",
    "gn:name":"\u017deimeliai",
    "gn:population":0,
    "gn:timezone":"Europe/Vilnius",
    "iso:country":"LT",
    "name:lit_x_preferred":[
        "\u017deimeliai"
    ],
    "name:und_x_variant":[
        "Zheymelis",
        "\u017deimelis"
    ],
    "wof:name":"Zeimeliai",
    "wof:placetype":"locality"
},
  "geometry": {"coordinates":[24.32165,55.17341],"type":"Point"}
}