{
  "type": "Feature",
  "properties": {
    "gn:admin1_code":"0.0",
    "gn:asciiname":"Vencloviskiai",
    "gn:country_code":"LT",
    "gn:dem":88,
    "gn:feature_class":"P",
    "gn:feature_code":"PPL",
    "gn:name":"Venclovi\u0161kiai",
    "gn:population":0,
    "gn:timezone":"Europe/Vilnius",
    "iso:country":"LT",
    "name:und_x_variant":[
        "Ventslavishki",
        "Venclovi\u0161kiai"
    ],
    "wof:name":"Vencloviskiai",
    "wof:placetype":"locality"
},
  "geometry": {"coordinates":[23.60438,55.16171],"type":"Point"}
}