{
  "type": "Feature",
  "properties": {
    "gn:admin1_code":"60",
    "gn:admin2_code":"67.0",
    "gn:asciiname":"Dagilyne",
    "gn:country_code":"LT",
    "gn:dem":39,
    "gn:feature_class":"P",
    "gn:feature_code":"PPL",
    "gn:name":"Dagilyn\u0117",
    "gn:population":0,
    "gn:timezone":"Europe/Vilnius",
    "iso:country":"LT",
    "name:lit_x_preferred":[
        "Dagilyn\u0117"
    ],
    "wof:name":"Dagilyne",
    "wof:placetype":"locality"
},
  "geometry": {"coordinates":[24.50192,56.13609],"type":"Point"}
}