{
  "type": "Feature",
  "properties": {
    "gn:admin1_code":"64.0",
    "gn:admin2_code":"43.0",
    "gn:asciiname":"Dideja",
    "gn:country_code":"LT",
    "gn:dem":146,
    "gn:feature_class":"P",
    "gn:feature_code":"PPL",
    "gn:name":"Did\u0117ja",
    "gn:population":0,
    "gn:timezone":"Europe/Vilnius",
    "iso:country":"LT",
    "name:und_x_variant":[
        "Dideya",
        "Did\u0117jo",
        "Did\u0117ja"
    ],
    "wof:name":"Dideja",
    "wof:placetype":"locality"
},
  "geometry": {"coordinates":[26.0372,55.84573],"type":"Point"}
}