{
  "type": "Feature",
  "properties": {
    "gn:admin1_code":"59.0",
    "gn:admin2_code":"18.0",
    "gn:asciiname":"Kulinge",
    "gn:country_code":"LT",
    "gn:dem":111,
    "gn:feature_class":"P",
    "gn:feature_code":"PPL",
    "gn:name":"K\u016bling\u0117",
    "gn:population":0,
    "gn:timezone":"Europe/Vilnius",
    "iso:country":"LT",
    "name:lit_x_preferred":[
        "K\u016bling\u0117"
    ],
    "name:und_x_variant":[
        "Kulinga",
        "Kuling\u0117"
    ],
    "wof:name":"Kulinge",
    "wof:placetype":"locality"
},
  "geometry": {"coordinates":[23.62477,54.57103000000001],"type":"Point"}
}