{
  "type": "Feature",
  "properties": {
    "gn:admin1_code":"65",
    "gn:admin2_code":"89.0",
    "gn:asciiname":"Smelianka",
    "gn:country_code":"LT",
    "gn:dem":78,
    "gn:feature_class":"P",
    "gn:feature_code":"PPL",
    "gn:name":"Sm\u0117lianka",
    "gn:population":0,
    "gn:timezone":"Europe/Vilnius",
    "iso:country":"LT",
    "name:lit_x_preferred":[
        "Sm\u0117lianka"
    ],
    "wof:name":"Smelianka",
    "wof:placetype":"locality"
},
  "geometry": {"coordinates":[24.58488,54.98313],"type":"Point"}
}