{
  "type": "Feature",
  "properties": {
    "gn:admin1_code":"57",
    "gn:admin2_code":"19.0",
    "gn:asciiname":"Karkazai",
    "gn:country_code":"LT",
    "gn:dem":66,
    "gn:feature_class":"P",
    "gn:feature_code":"PPL",
    "gn:name":"Karka\u017eai",
    "gn:population":0,
    "gn:timezone":"Europe/Vilnius",
    "iso:country":"LT",
    "name:lit_x_preferred":[
        "Karka\u017eai"
    ],
    "wof:name":"Karkazai",
    "wof:placetype":"locality"
},
  "geometry": {"coordinates":[23.9216,54.84424],"type":"Point"}
}