{
  "type": "Feature",
  "properties": {
    "gn:admin1_code":"64",
    "gn:admin2_code":"45.0",
    "gn:asciiname":"Amineniske",
    "gn:country_code":"LT",
    "gn:dem":174,
    "gn:feature_class":"P",
    "gn:feature_code":"PPL",
    "gn:name":"Amin\u0117ni\u0161k\u0117",
    "gn:population":0,
    "gn:timezone":"Europe/Vilnius",
    "iso:country":"LT",
    "name:lit_x_preferred":[
        "Amin\u0117ni\u0161k\u0117"
    ],
    "wof:name":"Amineniske",
    "wof:placetype":"locality"
},
  "geometry": {"coordinates":[26.04503,55.48221],"type":"Point"}
}