{
  "type": "Feature",
  "properties": {
    "gn:admin1_code":"57.0",
    "gn:admin2_code":"69.0",
    "gn:asciiname":"Asminta",
    "gn:country_code":"LT",
    "gn:dem":98,
    "gn:feature_class":"P",
    "gn:feature_code":"PPL",
    "gn:name":"A\u0161minta",
    "gn:population":0,
    "gn:timezone":"Europe/Vilnius",
    "iso:country":"LT",
    "name:und_x_variant":[
        "Oshminta",
        "A\u0161mintos",
        "A\u0161minta"
    ],
    "wof:name":"Asminta",
    "wof:placetype":"locality"
},
  "geometry": {"coordinates":[24.00094,54.68323],"type":"Point"}
}