{
  "type": "Feature",
  "properties": {
    "gn:admin1_code":"62.0",
    "gn:admin2_code":"94.0",
    "gn:asciiname":"Balneliskiai",
    "gn:country_code":"LT",
    "gn:dem":36,
    "gn:feature_class":"P",
    "gn:feature_code":"PPL",
    "gn:name":"Balneli\u0161kiai",
    "gn:population":0,
    "gn:timezone":"Europe/Vilnius",
    "iso:country":"LT",
    "name:und_x_variant":[
        "Bal\u2019nelishki",
        "Balneli\u0161kiai"
    ],
    "wof:name":"Balneliskiai",
    "wof:placetype":"locality"
},
  "geometry": {"coordinates":[22.64715,55.21867],"type":"Point"}
}