{
  "type": "Feature",
  "properties": {
    "gn:admin1_code":"65.0",
    "gn:admin2_code":"13.0",
    "gn:asciiname":"Dusinenai",
    "gn:country_code":"LT",
    "gn:dem":152,
    "gn:feature_class":"P",
    "gn:feature_code":"PPL",
    "gn:name":"Dusin\u0117nai",
    "gn:population":0,
    "gn:timezone":"Europe/Vilnius",
    "iso:country":"LT",
    "name:lit_x_preferred":[
        "Dusin\u0117nai"
    ],
    "wof:name":"Dusinenai",
    "wof:placetype":"locality"
},
  "geometry": {"coordinates":[25.27715,54.565],"type":"Point"}
}