{
  "type": "Feature",
  "properties": {
    "iso:country":"LT",
    "name:bel_x_variant":[
        "\u0410\u043d\u0442\u043e\u043a\u0430\u043b\u044c"
    ],
    "name:dan_x_preferred":[
        "Antakalnis"
    ],
    "name:deu_x_preferred":[
        "Antakalnis"
    ],
    "name:dut_x_preferred":[
        "Antakalnis"
    ],
    "name:eng_x_preferred":[
        "Antakalnis"
    ],
    "name:fre_x_preferred":[
        "Antakalnis"
    ],
    "name:ger_x_preferred":[
        "Antakalnis"
    ],
    "name:lav_x_preferred":[
        "Antakalnis"
    ],
    "name:lit_x_preferred":[
        "Antakalnis"
    ],
    "name:pol_x_preferred":[
        "Antokol"
    ],
    "name:rus_x_preferred":[
        "\u0410\u043d\u0442\u0430\u043a\u0430\u043b\u044c\u043d\u0438\u0441"
    ],
    "name:und_x_preferred":[
        "Antakalnis"
    ],
    "name:unk_x_variant":[
        "Antokol",
        "Antakalnis"
    ],
    "qs:gn_adm0_cc":"LT",
    "qs:gn_fcode":"PPL",
    "qs:gn_local":593116,
    "qs:gn_namadm1":"00",
    "qs:gn_name":"Antakalnis",
    "qs:local_max":12571,
    "qs:local_sum":23762,
    "qs:localhoods":20,
    "qs:name":"Antakalnis",
    "qs:name_adm0":"Lietuva",
    "qs:name_adm1":"Vilniaus Apskritis",
    "qs:name_adm2":"Vilniaus Miesto Savivaldybe",
    "qs:name_lau":"Vilnius",
    "qs:name_local":"Vilnius",
    "qs:photo_max":40,
    "qs:photo_sum":299,
    "qs:placetype":"Suburb",
    "qs:quad_count":62,
    "qs:woe_adm0":23424875,
    "qs:woe_adm1":55848083,
    "qs:woe_adm2":2346097,
    "qs:woe_lau":56044000,
    "qs:woe_local":479616,
    "qs:woe_ver":"7.10.0",
    "wd:population":47400,
    "wd:wordcount":322,
    "wof:lang":[
        "unk"
    ],
    "wof:name":"Antakalnis",
    "wof:placetype":"neighbourhood",
    "wof:population":47400
},
  "geometry": {"coordinates":[25.312009,54.705407],"type":"Point"}
}