{
  "type": "Feature",
  "properties": {
    "gn:admin1_code":"61.0",
    "gn:admin2_code":"29.0",
    "gn:asciiname":"Girkantai",
    "gn:country_code":"LT",
    "gn:dem":127,
    "gn:feature_class":"P",
    "gn:feature_code":"PPL",
    "gn:name":"Girkantai",
    "gn:population":0,
    "gn:timezone":"Europe/Vilnius",
    "iso:country":"LT",
    "name:und_x_variant":[
        "Girkontay",
        "Girkantai"
    ],
    "wof:name":"Girkantai",
    "wof:placetype":"locality"
},
  "geometry": {"coordinates":[22.64888,55.99406],"type":"Point"}
}