{
  "type": "Feature",
  "properties": {
    "gn:admin1_code":"61",
    "gn:admin2_code":"71.0",
    "gn:asciiname":"Eibariskiai",
    "gn:country_code":"LT",
    "gn:dem":120,
    "gn:feature_class":"P",
    "gn:feature_code":"PPL",
    "gn:name":"Eibari\u0161kiai",
    "gn:population":0,
    "gn:timezone":"Europe/Vilnius",
    "iso:country":"LT",
    "name:lit_x_preferred":[
        "Eibari\u0161kiai"
    ],
    "wof:name":"Eibariskiai",
    "wof:placetype":"locality"
},
  "geometry": {"coordinates":[23.54443,55.8282],"type":"Point"}
}