{
  "type": "Feature",
  "properties": {
    "gn:admin1_code":"65.0",
    "gn:admin2_code":"42.0",
    "gn:asciiname":"Vindziuliai",
    "gn:country_code":"LT",
    "gn:dem":115,
    "gn:feature_class":"P",
    "gn:feature_code":"PPL",
    "gn:name":"Vind\u017eiuliai",
    "gn:population":0,
    "gn:timezone":"Europe/Vilnius",
    "iso:country":"LT",
    "name:und_x_variant":[
        "Vindzyuli",
        "Vindziuli\u0173",
        "Vind\u017eiuliai"
    ],
    "wof:name":"Vindziuliai",
    "wof:placetype":"locality"
},
  "geometry": {"coordinates":[24.60894,54.71049],"type":"Point"}
}