{
  "type": "Feature",
  "properties": {
    "gn:admin1_code":"56",
    "gn:admin2_code":"38.0",
    "gn:asciiname":"Sokonys",
    "gn:country_code":"LT",
    "gn:dem":135,
    "gn:feature_class":"P",
    "gn:feature_code":"PPL",
    "gn:name":"Sokonys",
    "gn:population":0,
    "gn:timezone":"Europe/Vilnius",
    "iso:country":"LT",
    "name:lit_x_preferred":[
        "Sokonys"
    ],
    "wof:name":"Sokonys",
    "wof:placetype":"locality"
},
  "geometry": {"coordinates":[24.41162000000001,54.32323],"type":"Point"}
}