{
  "type": "Feature",
  "properties": {
    "gn:admin1_code":"57",
    "gn:admin2_code":"69.0",
    "gn:asciiname":"Zarijos",
    "gn:country_code":"LT",
    "gn:dem":95,
    "gn:feature_class":"P",
    "gn:feature_code":"PPL",
    "gn:name":"\u017darijos",
    "gn:population":0,
    "gn:timezone":"Europe/Vilnius",
    "iso:country":"LT",
    "name:lit_x_preferred":[
        "\u017darijos"
    ],
    "wof:name":"Zarijos",
    "wof:placetype":"locality"
},
  "geometry": {"coordinates":[24.00002000000001,54.65021],"type":"Point"}
}