{
  "type": "Feature",
  "properties": {
    "gn:admin1_code":"61.0",
    "gn:admin2_code":"71.0",
    "gn:asciiname":"Menaiciai",
    "gn:country_code":"LT",
    "gn:dem":112,
    "gn:feature_class":"P",
    "gn:feature_code":"PPL",
    "gn:name":"M\u0117nai\u010diai",
    "gn:population":0,
    "gn:timezone":"Europe/Vilnius",
    "iso:country":"LT",
    "name:ceb_x_preferred":[
        "Minai\u010diai"
    ],
    "name:lit_x_preferred":[
        "Minai\u010diai"
    ],
    "name:swe_x_preferred":[
        "Minai\u010diai"
    ],
    "name:und_x_variant":[
        "M\u0117nai\u010diai",
        "Minaytsi",
        "Minai\u010di\u0173"
    ],
    "wof:name":"Menaiciai",
    "wof:placetype":"locality"
},
  "geometry": {"coordinates":[23.55322,55.62987],"type":"Point"}
}