{
  "type": "Feature",
  "properties": {
    "gn:admin1_code":"61",
    "gn:admin2_code":"47.0",
    "gn:asciiname":"Paberziai",
    "gn:country_code":"LT",
    "gn:dem":45,
    "gn:feature_class":"P",
    "gn:feature_code":"PPL",
    "gn:name":"Paber\u017eiai",
    "gn:population":0,
    "gn:timezone":"Europe/Vilnius",
    "iso:country":"LT",
    "name:lit_x_preferred":[
        "Paber\u017eiai"
    ],
    "wof:name":"Paberziai",
    "wof:placetype":"locality"
},
  "geometry": {"coordinates":[23.52625,56.30537],"type":"Point"}
}