{
  "type": "Feature",
  "properties": {
    "gn:admin1_code":"56",
    "gn:admin2_code":"59.0",
    "gn:asciiname":"Valanciunai",
    "gn:country_code":"LT",
    "gn:dem":117,
    "gn:feature_class":"P",
    "gn:feature_code":"PPL",
    "gn:name":"Valan\u010di\u016bnai",
    "gn:population":0,
    "gn:timezone":"Europe/Vilnius",
    "iso:country":"LT",
    "name:lit_x_preferred":[
        "Valan\u010di\u016bnai"
    ],
    "wof:name":"Valanciunai",
    "wof:placetype":"locality"
},
  "geometry": {"coordinates":[23.80732,54.02654],"type":"Point"}
}