{
  "type": "Feature",
  "properties": {
    "gn:admin1_code":"62",
    "gn:admin2_code":"87.0",
    "gn:asciiname":"Padievaitis",
    "gn:country_code":"LT",
    "gn:dem":96,
    "gn:feature_class":"P",
    "gn:feature_code":"PPL",
    "gn:name":"Padievaitis",
    "gn:population":0,
    "gn:timezone":"Europe/Vilnius",
    "iso:country":"LT",
    "name:lit_x_preferred":[
        "Padievaitis"
    ],
    "wof:name":"Padievaitis",
    "wof:placetype":"locality"
},
  "geometry": {"coordinates":[22.00172,55.52685],"type":"Point"}
}