{
  "type": "Feature",
  "properties": {
    "gn:admin1_code":"59",
    "gn:admin2_code":"84.0",
    "gn:asciiname":"Suopiai",
    "gn:country_code":"LT",
    "gn:dem":58,
    "gn:feature_class":"P",
    "gn:feature_code":"PPL",
    "gn:name":"Suopiai",
    "gn:population":0,
    "gn:timezone":"Europe/Vilnius",
    "iso:country":"LT",
    "name:lit_x_preferred":[
        "Suopiai"
    ],
    "wof:name":"Suopiai",
    "wof:placetype":"locality"
},
  "geometry": {"coordinates":[23.26878,54.94163],"type":"Point"}
}