{
  "type": "Feature",
  "properties": {
    "gn:admin1_code":"58.0",
    "gn:admin2_code":"88.0",
    "gn:asciiname":"Grynaiciai",
    "gn:country_code":"LT",
    "gn:dem":21,
    "gn:feature_class":"P",
    "gn:feature_code":"PPL",
    "gn:name":"Grynai\u010diai",
    "gn:population":0,
    "gn:timezone":"Europe/Vilnius",
    "iso:country":"LT",
    "name:und_x_variant":[
        "Grineydzhey",
        "Grynai\u010diai"
    ],
    "wof:name":"Grynaiciai",
    "wof:placetype":"locality"
},
  "geometry": {"coordinates":[21.50112,55.50662],"type":"Point"}
}