{
  "type": "Feature",
  "properties": {
    "gn:admin1_code":"64",
    "gn:admin2_code":"62.0",
    "gn:asciiname":"Juodiskes",
    "gn:country_code":"LT",
    "gn:dem":152,
    "gn:feature_class":"P",
    "gn:feature_code":"PPL",
    "gn:name":"Juodi\u0161k\u0117s",
    "gn:population":0,
    "gn:timezone":"Europe/Vilnius",
    "iso:country":"LT",
    "name:lit_x_preferred":[
        "Juodi\u0161k\u0117s"
    ],
    "wof:name":"Juodiskes",
    "wof:placetype":"locality"
},
  "geometry": {"coordinates":[25.47366,55.23044],"type":"Point"}
}