{
  "type": "Feature",
  "properties": {
    "gn:admin1_code":"57",
    "gn:admin2_code":"69.0",
    "gn:asciiname":"Giraitiskes",
    "gn:country_code":"LT",
    "gn:dem":80,
    "gn:feature_class":"P",
    "gn:feature_code":"PPL",
    "gn:name":"Giraiti\u0161k\u0117s",
    "gn:population":0,
    "gn:timezone":"Europe/Vilnius",
    "iso:country":"LT",
    "name:lit_x_preferred":[
        "Giraiti\u0161k\u0117s"
    ],
    "wof:name":"Giraitiskes",
    "wof:placetype":"locality"
},
  "geometry": {"coordinates":[23.97969,54.60144],"type":"Point"}
}