{
  "type": "Feature",
  "properties": {
    "gn:admin1_code":"60.0",
    "gn:admin2_code":"27.0",
    "gn:asciiname":"Vadokliai",
    "gn:country_code":"LT",
    "gn:dem":75,
    "gn:feature_class":"P",
    "gn:feature_code":"PPL",
    "gn:name":"Vadokliai",
    "gn:population":0,
    "gn:timezone":"Europe/Vilnius",
    "iso:country":"LT",
    "name:ceb_x_preferred":[
        "Vadokliai"
    ],
    "name:est_x_preferred":[
        "Vadokliai"
    ],
    "name:lit_x_preferred":[
        "Vadokliai"
    ],
    "name:nld_x_preferred":[
        "Vadokliai"
    ],
    "name:pol_x_preferred":[
        "Wodakle"
    ],
    "name:swe_x_preferred":[
        "Vadokliai"
    ],
    "name:und_x_variant":[
        "Wodakle",
        "Vadoklyay",
        "Vadoklia",
        "Vadokli\u0173",
        "Vadokliai"
    ],
    "wof:name":"Vadokliai",
    "wof:placetype":"locality"
},
  "geometry": {"coordinates":[24.46358,55.49681],"type":"Point"}
}