{
  "type": "Feature",
  "properties": {
    "gn:admin1_code":"60",
    "gn:admin2_code":"36.0",
    "gn:asciiname":"Putriai",
    "gn:country_code":"LT",
    "gn:dem":32,
    "gn:feature_class":"P",
    "gn:feature_code":"PPL",
    "gn:name":"Putriai",
    "gn:population":0,
    "gn:timezone":"Europe/Vilnius",
    "iso:country":"LT",
    "name:lit_x_preferred":[
        "Putriai"
    ],
    "wof:name":"Putriai",
    "wof:placetype":"locality"
},
  "geometry": {"coordinates":[24.51577,56.26527],"type":"Point"}
}