{
  "type": "Feature",
  "properties": {
    "gn:admin1_code":"59",
    "gn:admin2_code":"39.0",
    "gn:asciiname":"Teiberiai",
    "gn:country_code":"LT",
    "gn:dem":53,
    "gn:feature_class":"P",
    "gn:feature_code":"PPL",
    "gn:name":"Teiberiai",
    "gn:population":0,
    "gn:timezone":"Europe/Vilnius",
    "iso:country":"LT",
    "name:lit_x_preferred":[
        "Teiberiai"
    ],
    "wof:name":"Teiberiai",
    "wof:placetype":"locality"
},
  "geometry": {"coordinates":[23.02816,54.71011],"type":"Point"}
}