{
  "type": "Feature",
  "properties": {
    "gn:admin1_code":"64.0",
    "gn:admin2_code":"82.0",
    "gn:asciiname":"Stalnioniskis",
    "gn:country_code":"LT",
    "gn:dem":113,
    "gn:feature_class":"P",
    "gn:feature_code":"PPL",
    "gn:name":"Stalnioni\u0161kis",
    "gn:population":0,
    "gn:timezone":"Europe/Vilnius",
    "iso:country":"LT",
    "name:und_x_variant":[
        "Stalnioni\u0161ki\u0173",
        "Stal\u2019yanishki",
        "Stalnioni\u0161kis"
    ],
    "wof:name":"Stalnioniskis",
    "wof:placetype":"locality"
},
  "geometry": {"coordinates":[25.44065,55.5956],"type":"Point"}
}