{
  "type": "Feature",
  "properties": {
    "gn:admin1_code":"65",
    "gn:admin2_code":"13.0",
    "gn:asciiname":"Valkaguliai",
    "gn:country_code":"LT",
    "gn:dem":260,
    "gn:feature_class":"P",
    "gn:feature_code":"PPL",
    "gn:name":"Valkaguliai",
    "gn:population":0,
    "gn:timezone":"Europe/Vilnius",
    "iso:country":"LT",
    "name:lit_x_preferred":[
        "Valkaguliai"
    ],
    "wof:name":"Valkaguliai",
    "wof:placetype":"locality"
},
  "geometry": {"coordinates":[25.58713,54.53095],"type":"Point"}
}