{
  "type": "Feature",
  "properties": {
    "gn:admin1_code":"56.0",
    "gn:admin2_code":"11.0",
    "gn:asciiname":"Ostampas",
    "gn:country_code":"LT",
    "gn:dem":101,
    "gn:feature_class":"P",
    "gn:feature_code":"PPL",
    "gn:name":"Ostampas",
    "gn:population":0,
    "gn:timezone":"Europe/Vilnius",
    "iso:country":"LT",
    "name:lit_x_preferred":[
        "Ostampas"
    ],
    "name:und_x_variant":[
        "Ostemp\u0173",
        "Ostemp",
        "Ostempai",
        "Astampas"
    ],
    "wof:name":"Ostampas",
    "wof:placetype":"locality"
},
  "geometry": {"coordinates":[23.66543,54.42511],"type":"Point"}
}