{
  "type": "Feature",
  "properties": {
    "gn:admin1_code":"60.0",
    "gn:admin2_code":"27.0",
    "gn:asciiname":"Paezeris",
    "gn:country_code":"LT",
    "gn:dem":56,
    "gn:feature_class":"P",
    "gn:feature_code":"PPL",
    "gn:name":"Pae\u017eeris",
    "gn:population":0,
    "gn:timezone":"Europe/Vilnius",
    "iso:country":"LT",
    "name:lit_x_preferred":[
        "Pae\u017eeris"
    ],
    "wof:name":"Paezeris",
    "wof:placetype":"locality"
},
  "geometry": {"coordinates":[24.20249,55.5061],"type":"Point"}
}