{
  "type": "Feature",
  "properties": {
    "gn:admin1_code":"60",
    "gn:admin2_code":"73.0",
    "gn:asciiname":"Gabriskis",
    "gn:country_code":"LT",
    "gn:dem":129,
    "gn:feature_class":"P",
    "gn:feature_code":"PPL",
    "gn:name":"Gabri\u0161kis",
    "gn:population":0,
    "gn:timezone":"Europe/Vilnius",
    "iso:country":"LT",
    "name:lit_x_preferred":[
        "Gabri\u0161kis"
    ],
    "wof:name":"Gabriskis",
    "wof:placetype":"locality"
},
  "geometry": {"coordinates":[25.55936,55.94201999999999],"type":"Point"}
}