{
  "type": "Feature",
  "properties": {
    "gn:admin1_code":"57.0",
    "gn:admin2_code":"46.0",
    "gn:asciiname":"Sviloneliai",
    "gn:country_code":"LT",
    "gn:dem":54,
    "gn:feature_class":"P",
    "gn:feature_code":"PPL",
    "gn:name":"Svilon\u0117liai",
    "gn:population":0,
    "gn:timezone":"Europe/Vilnius",
    "iso:country":"LT",
    "name:lit_x_preferred":[
        "Svilon\u0117liai"
    ],
    "name:und_x_variant":[
        "Svilaynelyay",
        "Svilain\u0117liai"
    ],
    "wof:name":"Sviloneliai",
    "wof:placetype":"locality"
},
  "geometry": {"coordinates":[24.12754,55.00821],"type":"Point"}
}