{
  "type": "Feature",
  "properties": {
    "gn:admin1_code":"61",
    "gn:admin2_code":"54.0",
    "gn:asciiname":"Juodiske",
    "gn:country_code":"LT",
    "gn:dem":137,
    "gn:feature_class":"P",
    "gn:feature_code":"PPL",
    "gn:name":"Juodi\u0161k\u0117",
    "gn:population":0,
    "gn:timezone":"Europe/Vilnius",
    "iso:country":"LT",
    "name:lit_x_preferred":[
        "Juodi\u0161k\u0117"
    ],
    "wof:name":"Juodiske",
    "wof:placetype":"locality"
},
  "geometry": {"coordinates":[22.9818,55.52916],"type":"Point"}
}