{
  "type": "Feature",
  "properties": {
    "gn:admin1_code":"65.0",
    "gn:admin2_code":"79.0",
    "gn:asciiname":"Senasis Tarpupis",
    "gn:country_code":"LT",
    "gn:dem":142,
    "gn:feature_class":"P",
    "gn:feature_code":"PPL",
    "gn:name":"Senasis Tarpupis",
    "gn:population":0,
    "gn:timezone":"Europe/Vilnius",
    "iso:country":"LT",
    "name:lit_x_preferred":[
        "Senasis Tarpupis"
    ],
    "name:und_x_variant":[
        "Senieji Tarpupiai",
        "Seneiy Tarpupyay",
        "Senai Tarpupai",
        "Mezhdurech\u2019ye Staroye"
    ],
    "wof:name":"Senasis Tarpupis",
    "wof:placetype":"locality"
},
  "geometry": {"coordinates":[24.98531,54.555],"type":"Point"}
}