{
  "type": "Feature",
  "properties": {
    "gn:admin1_code":"60",
    "gn:admin2_code":"27.0",
    "gn:asciiname":"Butkunai",
    "gn:country_code":"LT",
    "gn:dem":63,
    "gn:feature_class":"P",
    "gn:feature_code":"PPL",
    "gn:name":"Butk\u016bnai",
    "gn:population":0,
    "gn:timezone":"Europe/Vilnius",
    "iso:country":"LT",
    "name:lit_x_preferred":[
        "Butk\u016bnai"
    ],
    "wof:name":"Butkunai",
    "wof:placetype":"locality"
},
  "geometry": {"coordinates":[24.46865,55.6004],"type":"Point"}
}