{
  "type": "Feature",
  "properties": {
    "gn:admin1_code":"64",
    "gn:admin2_code":"43.0",
    "gn:asciiname":"Galiniskes I",
    "gn:country_code":"LT",
    "gn:dem":162,
    "gn:feature_class":"P",
    "gn:feature_code":"PPL",
    "gn:name":"Galini\u0161k\u0117s I",
    "gn:population":0,
    "gn:timezone":"Europe/Vilnius",
    "iso:country":"LT",
    "name:lit_x_preferred":[
        "Galini\u0161k\u0117s I"
    ],
    "wof:name":"Galiniskes I",
    "wof:placetype":"locality"
},
  "geometry": {"coordinates":[26.31381,55.68492],"type":"Point"}
}