{
  "type": "Feature",
  "properties": {
    "gn:admin1_code":"63.0",
    "gn:admin2_code":"61.0",
    "gn:asciiname":"Lelaiciai",
    "gn:country_code":"LT",
    "gn:dem":64,
    "gn:feature_class":"P",
    "gn:feature_code":"PPL",
    "gn:name":"L\u0117lai\u010diai",
    "gn:population":0,
    "gn:timezone":"Europe/Vilnius",
    "iso:country":"LT",
    "name:lit_x_preferred":[
        "L\u0117lai\u010diai"
    ],
    "name:lit_x_variant":[
        "Lelai\u010diai"
    ],
    "wof:name":"Lelaiciai",
    "wof:placetype":"locality"
},
  "geometry": {"coordinates":[22.45355,56.23956999999999],"type":"Point"}
}