{
  "type": "Feature",
  "properties": {
    "gn:admin1_code":"61",
    "gn:admin2_code":"29.0",
    "gn:asciiname":"Paluksciai",
    "gn:country_code":"LT",
    "gn:dem":97,
    "gn:feature_class":"P",
    "gn:feature_code":"PPL",
    "gn:name":"Pal\u016bks\u010diai",
    "gn:population":0,
    "gn:timezone":"Europe/Vilnius",
    "iso:country":"LT",
    "name:lit_x_preferred":[
        "Pal\u016bks\u010diai"
    ],
    "wof:name":"Paluksciai",
    "wof:placetype":"locality"
},
  "geometry": {"coordinates":[22.97314,56.05457],"type":"Point"}
}