{
  "type": "Feature",
  "properties": {
    "gn:admin1_code":"0.0",
    "gn:asciiname":"Vizbarai",
    "gn:cc2":"LT",
    "gn:country_code":"LT",
    "gn:dem":69,
    "gn:feature_class":"P",
    "gn:feature_code":"PPL",
    "gn:name":"Vizbarai",
    "gn:population":0,
    "gn:timezone":"Europe/Vilnius",
    "iso:country":"LT",
    "name:und_x_variant":[
        "Vizbaray",
        "Vizbar\u0173",
        "Vizbarai"
    ],
    "wof:name":"Vizbarai",
    "wof:placetype":"locality"
},
  "geometry": {"coordinates":[22.05,55.36666999999999],"type":"Point"}
}