{
  "type": "Feature",
  "properties": {
    "gn:admin1_code":"65",
    "gn:admin2_code":"13.0",
    "gn:asciiname":"Lapeikiai",
    "gn:country_code":"LT",
    "gn:dem":152,
    "gn:feature_class":"P",
    "gn:feature_code":"PPL",
    "gn:name":"Lapeikiai",
    "gn:population":0,
    "gn:timezone":"Europe/Vilnius",
    "iso:country":"LT",
    "name:lit_x_preferred":[
        "Lapeikiai"
    ],
    "wof:name":"Lapeikiai",
    "wof:placetype":"locality"
},
  "geometry": {"coordinates":[25.49942,54.93916],"type":"Point"}
}