{
  "type": "Feature",
  "properties": {
    "gn:admin1_code":"59.0",
    "gn:admin2_code":"84.0",
    "gn:asciiname":"Tervydoniai",
    "gn:country_code":"LT",
    "gn:dem":59,
    "gn:feature_class":"P",
    "gn:feature_code":"PPL",
    "gn:name":"Tervydoniai",
    "gn:population":0,
    "gn:timezone":"Europe/Vilnius",
    "iso:country":"LT",
    "name:und_x_variant":[
        "Tervidany",
        "Tervidonay",
        "Tervydoniai"
    ],
    "wof:name":"Tervydoniai",
    "wof:placetype":"locality"
},
  "geometry": {"coordinates":[23.45639,55.02835],"type":"Point"}
}