{
  "type": "Feature",
  "properties": {
    "gn:admin1_code":"65",
    "gn:admin2_code":"85.0",
    "gn:asciiname":"Ozionys",
    "gn:country_code":"LT",
    "gn:dem":201,
    "gn:feature_class":"P",
    "gn:feature_code":"PPL",
    "gn:name":"O\u017eionys",
    "gn:population":0,
    "gn:timezone":"Europe/Vilnius",
    "iso:country":"LT",
    "name:lit_x_preferred":[
        "O\u017eionys"
    ],
    "wof:name":"Ozionys",
    "wof:placetype":"locality"
},
  "geometry": {"coordinates":[25.50747,54.47365],"type":"Point"}
}