{
  "type": "Feature",
  "properties": {
    "gn:admin1_code":"62.0",
    "gn:admin2_code":"87.0",
    "gn:asciiname":"Paskarbiskiai",
    "gn:country_code":"LT",
    "gn:dem":89,
    "gn:feature_class":"P",
    "gn:feature_code":"PPL",
    "gn:name":"Paskarbi\u0161kiai",
    "gn:population":0,
    "gn:timezone":"Europe/Vilnius",
    "iso:country":"LT",
    "name:und_x_variant":[
        "Paskarbishek",
        "Paskarbishkyay",
        "Paskarbi\u0161kiai"
    ],
    "wof:name":"Paskarbiskiai",
    "wof:placetype":"locality"
},
  "geometry": {"coordinates":[22.00849,55.49249],"type":"Point"}
}