{
  "type": "Feature",
  "properties": {
    "gn:admin1_code":"60",
    "gn:admin2_code":"67.0",
    "gn:asciiname":"Jurgeniskiai",
    "gn:country_code":"LT",
    "gn:dem":42,
    "gn:feature_class":"P",
    "gn:feature_code":"PPL",
    "gn:name":"Jurgeni\u0161kiai",
    "gn:population":0,
    "gn:timezone":"Europe/Vilnius",
    "iso:country":"LT",
    "name:lit_x_preferred":[
        "Jurgeni\u0161kiai"
    ],
    "wof:name":"Jurgeniskiai",
    "wof:placetype":"locality"
},
  "geometry": {"coordinates":[24.26302,56.02518000000001],"type":"Point"}
}