{
  "type": "Feature",
  "properties": {
    "gn:admin1_code":"65",
    "gn:admin2_code":"13.0",
    "gn:asciiname":"Mantusiai",
    "gn:country_code":"LT",
    "gn:dem":243,
    "gn:feature_class":"P",
    "gn:feature_code":"PPL",
    "gn:name":"Mantu\u0161iai",
    "gn:population":0,
    "gn:timezone":"Europe/Vilnius",
    "iso:country":"LT",
    "name:lit_x_preferred":[
        "Mantu\u0161iai"
    ],
    "wof:name":"Mantusiai",
    "wof:placetype":"locality"
},
  "geometry": {"coordinates":[25.51794,54.54829],"type":"Point"}
}