{
  "type": "Feature",
  "properties": {
    "gn:admin1_code":"65",
    "gn:admin2_code":"13.0",
    "gn:asciiname":"Pavyzulionele",
    "gn:country_code":"LT",
    "gn:dem":177,
    "gn:feature_class":"P",
    "gn:feature_code":"PPL",
    "gn:name":"Pavyzulion\u0117l\u0117",
    "gn:population":0,
    "gn:timezone":"Europe/Vilnius",
    "iso:country":"LT",
    "name:lit_x_preferred":[
        "Pavyzulion\u0117l\u0117"
    ],
    "wof:name":"Pavyzulionele",
    "wof:placetype":"locality"
},
  "geometry": {"coordinates":[25.30365,54.94886999999999],"type":"Point"}
}