{
  "type": "Feature",
  "properties": {
    "gn:admin1_code":"62.0",
    "gn:admin2_code":"63.0",
    "gn:asciiname":"Vezininkai",
    "gn:country_code":"LT",
    "gn:dem":10,
    "gn:feature_class":"P",
    "gn:feature_code":"PPL",
    "gn:name":"V\u0117\u017eininkai",
    "gn:population":0,
    "gn:timezone":"Europe/Vilnius",
    "iso:country":"LT",
    "name:und_x_variant":[
        "Vezhninkyay",
        "Vezheningken",
        "V\u0117\u017eininkai"
    ],
    "wof:name":"Vezininkai",
    "wof:placetype":"locality"
},
  "geometry": {"coordinates":[22.16335,55.06988000000001],"type":"Point"}
}