{
  "type": "Feature",
  "properties": {
    "iso:country":"LT",
    "name:lit_x_preferred":[
        "\u0104\u017euolijai"
    ],
    "wof:name":"Azuolijai",
    "wof:placetype":"neighbourhood"
},
  "geometry": {"coordinates":[25.25056880487536,54.61639957628092],"type":"Point"}
}