{
  "type": "Feature",
  "properties": {
    "gn:admin1_code":"0.0",
    "gn:asciiname":"Dubuliai",
    "gn:cc2":"LT",
    "gn:country_code":"LT",
    "gn:dem":58,
    "gn:feature_class":"P",
    "gn:feature_code":"PPL",
    "gn:name":"Dubuliai",
    "gn:population":0,
    "gn:timezone":"Europe/Vilnius",
    "iso:country":"LT",
    "name:und_x_variant":[
        "Dobuli",
        "Dubuliai"
    ],
    "wof:name":"Dubuliai",
    "wof:placetype":"locality"
},
  "geometry": {"coordinates":[24.25,55.61666999999999],"type":"Point"}
}