{
  "type": "Feature",
  "properties": {
    "gn:admin1_code":"64",
    "gn:admin2_code":"34.0",
    "gn:asciiname":"Liepagiriai",
    "gn:country_code":"LT",
    "gn:dem":113,
    "gn:feature_class":"P",
    "gn:feature_code":"PPL",
    "gn:name":"Liepagiriai",
    "gn:population":0,
    "gn:timezone":"Europe/Vilnius",
    "iso:country":"LT",
    "name:lit_x_preferred":[
        "Liepagiriai"
    ],
    "wof:name":"Liepagiriai",
    "wof:placetype":"locality"
},
  "geometry": {"coordinates":[25.45135,55.65018000000001],"type":"Point"}
}