{
  "type": "Feature",
  "properties": {
    "gn:admin1_code":"57.0",
    "gn:admin2_code":"72.0",
    "gn:asciiname":"Pramedziava",
    "gn:country_code":"LT",
    "gn:dem":87,
    "gn:feature_class":"P",
    "gn:feature_code":"PPL",
    "gn:name":"Pramed\u017eiava",
    "gn:population":0,
    "gn:timezone":"Europe/Vilnius",
    "iso:country":"LT",
    "name:deu_x_historical":[
        "Promiatschew",
        "Promiaczew"
    ],
    "name:deu_x_preferred":[
        "Promiatschew"
    ],
    "name:deu_x_variant":[
        "Promiaczew"
    ],
    "name:lit_x_preferred":[
        "Pramed\u017eiava"
    ],
    "wof:name":"Pramedziava",
    "wof:placetype":"locality"
},
  "geometry": {"coordinates":[23.21821,55.26156],"type":"Point"}
}