{
  "type": "Feature",
  "properties": {
    "gn:admin1_code":"64",
    "gn:admin2_code":"62.0",
    "gn:asciiname":"Strizauciske",
    "gn:country_code":"LT",
    "gn:dem":151,
    "gn:feature_class":"P",
    "gn:feature_code":"PPL",
    "gn:name":"Stri\u017eau\u010di\u0161k\u0117",
    "gn:population":0,
    "gn:timezone":"Europe/Vilnius",
    "iso:country":"LT",
    "name:lit_x_preferred":[
        "Stri\u017eau\u010di\u0161k\u0117"
    ],
    "wof:name":"Strizauciske",
    "wof:placetype":"locality"
},
  "geometry": {"coordinates":[25.59101,55.24484],"type":"Point"}
}