{
  "type": "Feature",
  "properties": {
    "gn:admin1_code":"64",
    "gn:admin2_code":"34.0",
    "gn:asciiname":"Daugeliskiai",
    "gn:country_code":"LT",
    "gn:dem":103,
    "gn:feature_class":"P",
    "gn:feature_code":"PPL",
    "gn:name":"Daug\u0117li\u0161kiai",
    "gn:population":0,
    "gn:timezone":"Europe/Vilnius",
    "iso:country":"LT",
    "name:lit_x_preferred":[
        "Daug\u0117li\u0161kiai"
    ],
    "wof:name":"Daugeliskiai",
    "wof:placetype":"locality"
},
  "geometry": {"coordinates":[24.95936,55.60451],"type":"Point"}
}