{
  "type": "Feature",
  "properties": {
    "gn:admin1_code":"0.0",
    "gn:asciiname":"Gaveikenai",
    "gn:country_code":"LT",
    "gn:dem":158,
    "gn:feature_class":"P",
    "gn:feature_code":"PPL",
    "gn:name":"Gaveik\u0117nai",
    "gn:population":0,
    "gn:timezone":"Europe/Vilnius",
    "iso:country":"LT",
    "name:und_x_variant":[
        "Gaveykyany",
        "Gawejkiany",
        "Gaveik\u0117nai"
    ],
    "wof:name":"Gaveikenai",
    "wof:placetype":"locality"
},
  "geometry": {"coordinates":[26.10772,55.34618],"type":"Point"}
}