{
  "type": "Feature",
  "properties": {
    "gn:admin1_code":"60",
    "gn:admin2_code":"73.0",
    "gn:asciiname":"Margenai",
    "gn:country_code":"LT",
    "gn:dem":102,
    "gn:feature_class":"P",
    "gn:feature_code":"PPL",
    "gn:name":"Marg\u0117nai",
    "gn:population":0,
    "gn:timezone":"Europe/Vilnius",
    "iso:country":"LT",
    "name:lit_x_preferred":[
        "Marg\u0117nai"
    ],
    "wof:name":"Margenai",
    "wof:placetype":"locality"
},
  "geometry": {"coordinates":[25.76218,55.82549],"type":"Point"}
}