{
  "type": "Feature",
  "properties": {
    "gn:admin1_code":"62",
    "gn:admin2_code":"94.0",
    "gn:asciiname":"Adomaitiske",
    "gn:country_code":"LT",
    "gn:dem":66,
    "gn:feature_class":"P",
    "gn:feature_code":"PPL",
    "gn:name":"Adomaiti\u0161k\u0117",
    "gn:population":0,
    "gn:timezone":"Europe/Vilnius",
    "iso:country":"LT",
    "name:lit_x_preferred":[
        "Adomaiti\u0161k\u0117"
    ],
    "wof:name":"Adomaitiske",
    "wof:placetype":"locality"
},
  "geometry": {"coordinates":[23.21623,55.11519000000001],"type":"Point"}
}