{
  "type": "Feature",
  "properties": {
    "gn:admin1_code":"64",
    "gn:admin2_code":"82.0",
    "gn:asciiname":"Tautiskis",
    "gn:country_code":"LT",
    "gn:dem":192,
    "gn:feature_class":"P",
    "gn:feature_code":"PPL",
    "gn:name":"Tauti\u0161kis",
    "gn:population":0,
    "gn:timezone":"Europe/Vilnius",
    "iso:country":"LT",
    "name:lit_x_preferred":[
        "Tauti\u0161kis"
    ],
    "wof:name":"Tautiskis",
    "wof:placetype":"locality"
},
  "geometry": {"coordinates":[25.89272,55.41391],"type":"Point"}
}