{
  "type": "Feature",
  "properties": {
    "gn:admin1_code":"65",
    "gn:admin2_code":"81.0",
    "gn:asciiname":"Apusynai",
    "gn:country_code":"LT",
    "gn:dem":89,
    "gn:feature_class":"P",
    "gn:feature_code":"PPL",
    "gn:name":"Apu\u0161ynai",
    "gn:population":0,
    "gn:timezone":"Europe/Vilnius",
    "iso:country":"LT",
    "name:lit_x_preferred":[
        "Apu\u0161ynai"
    ],
    "wof:name":"Apusynai",
    "wof:placetype":"locality"
},
  "geometry": {"coordinates":[24.62387,55.10423],"type":"Point"}
}