{
  "type": "Feature",
  "properties": {
    "gn:admin1_code":"65.0",
    "gn:admin2_code":"42.0",
    "gn:asciiname":"Jagelonys",
    "gn:country_code":"LT",
    "gn:dem":134,
    "gn:feature_class":"P",
    "gn:feature_code":"PPL",
    "gn:name":"Jag\u0117lonys",
    "gn:population":0,
    "gn:timezone":"Europe/Vilnius",
    "iso:country":"LT",
    "name:und_x_variant":[
        "Yagelonis",
        "Jag\u0117lonys"
    ],
    "wof:name":"Jagelonys",
    "wof:placetype":"locality"
},
  "geometry": {"coordinates":[24.56744,54.72805],"type":"Point"}
}