{
  "type": "Feature",
  "properties": {
    "gn:admin1_code":"65",
    "gn:admin2_code":"13.0",
    "gn:asciiname":"Zameckavas",
    "gn:country_code":"LT",
    "gn:dem":142,
    "gn:feature_class":"P",
    "gn:feature_code":"PPL",
    "gn:name":"Zame\u010dkavas",
    "gn:population":0,
    "gn:timezone":"Europe/Vilnius",
    "iso:country":"LT",
    "name:lit_x_preferred":[
        "Zame\u010dkavas"
    ],
    "wof:name":"Zameckavas",
    "wof:placetype":"locality"
},
  "geometry": {"coordinates":[25.39128,54.80943000000001],"type":"Point"}
}