{
  "type": "Feature",
  "properties": {
    "gn:admin1_code":"56",
    "gn:admin2_code":"11.0",
    "gn:asciiname":"Mikalavas",
    "gn:country_code":"LT",
    "gn:dem":173,
    "gn:feature_class":"P",
    "gn:feature_code":"PPL",
    "gn:name":"Mikalavas",
    "gn:population":0,
    "gn:timezone":"Europe/Vilnius",
    "iso:country":"LT",
    "name:lit_x_preferred":[
        "Mikalavas"
    ],
    "wof:name":"Mikalavas",
    "wof:placetype":"locality"
},
  "geometry": {"coordinates":[24.19286,54.39931],"type":"Point"}
}