{
  "type": "Feature",
  "properties": {
    "gn:admin1_code":"61",
    "gn:admin2_code":"54.0",
    "gn:asciiname":"Senlioliai",
    "gn:country_code":"LT",
    "gn:dem":150,
    "gn:feature_class":"P",
    "gn:feature_code":"PPL",
    "gn:name":"Senlioliai",
    "gn:population":0,
    "gn:timezone":"Europe/Vilnius",
    "iso:country":"LT",
    "name:lit_x_preferred":[
        "Senlioliai"
    ],
    "wof:name":"Senlioliai",
    "wof:placetype":"locality"
},
  "geometry": {"coordinates":[22.91651,55.56522],"type":"Point"}
}