{
  "type": "Feature",
  "properties": {
    "gn:admin1_code":"63",
    "gn:admin2_code":"61.0",
    "gn:asciiname":"Rimoliai",
    "gn:country_code":"LT",
    "gn:dem":124,
    "gn:feature_class":"P",
    "gn:feature_code":"PPL",
    "gn:name":"Rimoliai",
    "gn:population":0,
    "gn:timezone":"Europe/Vilnius",
    "iso:country":"LT",
    "name:lit_x_preferred":[
        "Rimoliai"
    ],
    "wof:name":"Rimoliai",
    "wof:placetype":"locality"
},
  "geometry": {"coordinates":[22.0726,56.19172],"type":"Point"}
}