{
  "type": "Feature",
  "properties": {
    "gn:admin1_code":"64",
    "gn:admin2_code":"62.0",
    "gn:asciiname":"Ulycele",
    "gn:country_code":"LT",
    "gn:dem":164,
    "gn:feature_class":"P",
    "gn:feature_code":"PPL",
    "gn:name":"\u016aly\u010d\u0117l\u0117",
    "gn:population":0,
    "gn:timezone":"Europe/Vilnius",
    "iso:country":"LT",
    "name:lit_x_preferred":[
        "\u016aly\u010d\u0117l\u0117"
    ],
    "wof:name":"Ulycele",
    "wof:placetype":"locality"
},
  "geometry": {"coordinates":[25.35148,55.17527],"type":"Point"}
}