{
  "type": "Feature",
  "properties": {
    "gn:admin1_code":"60",
    "gn:admin2_code":"73.0",
    "gn:asciiname":"Kazliskelis",
    "gn:country_code":"LT",
    "gn:dem":89,
    "gn:feature_class":"P",
    "gn:feature_code":"PPL",
    "gn:name":"Kazli\u0161k\u0117lis",
    "gn:population":0,
    "gn:timezone":"Europe/Vilnius",
    "iso:country":"LT",
    "name:lit_x_preferred":[
        "Kazli\u0161k\u0117lis"
    ],
    "wof:name":"Kazliskelis",
    "wof:placetype":"locality"
},
  "geometry": {"coordinates":[25.37311,56.01736],"type":"Point"}
}