{
  "type": "Feature",
  "properties": {
    "gn:admin1_code":"65",
    "gn:admin2_code":"86.0",
    "gn:asciiname":"Naujiniske",
    "gn:country_code":"LT",
    "gn:dem":159,
    "gn:feature_class":"P",
    "gn:feature_code":"PPL",
    "gn:name":"Naujini\u0161k\u0117",
    "gn:population":0,
    "gn:timezone":"Europe/Vilnius",
    "iso:country":"LT",
    "name:lit_x_preferred":[
        "Naujini\u0161k\u0117"
    ],
    "wof:name":"Naujiniske",
    "wof:placetype":"locality"
},
  "geometry": {"coordinates":[25.85766,54.95965],"type":"Point"}
}