{
  "type": "Feature",
  "properties": {
    "gn:admin1_code":"56.0",
    "gn:admin2_code":"11.0",
    "gn:asciiname":"Bukauciskes II",
    "gn:country_code":"LT",
    "gn:dem":132,
    "gn:feature_class":"P",
    "gn:feature_code":"PPL",
    "gn:name":"Bukau\u010di\u0161k\u0117s II",
    "gn:population":0,
    "gn:timezone":"Europe/Vilnius",
    "iso:country":"LT",
    "name:lit_x_preferred":[
        "Bukau\u010di\u0161k\u0117s II"
    ],
    "name:und_x_variant":[
        "Bukau\u010di\u0161k\u0117s Antrieji",
        "Bykovchishki",
        "Buki\u0161k\u0117s",
        "Bukauchishkes",
        "Bukau\u010di\u0161k\u0117s"
    ],
    "wof:name":"Bukauciskes II",
    "wof:placetype":"locality"
},
  "geometry": {"coordinates":[24.36811,54.31842],"type":"Point"}
}