{
  "type": "Feature",
  "properties": {
    "gn:admin1_code":"61",
    "gn:admin2_code":"71.0",
    "gn:asciiname":"Kaciuskiai",
    "gn:country_code":"LT",
    "gn:dem":108,
    "gn:feature_class":"P",
    "gn:feature_code":"PPL",
    "gn:name":"Ka\u010diu\u0161kiai",
    "gn:population":0,
    "gn:timezone":"Europe/Vilnius",
    "iso:country":"LT",
    "name:lit_x_preferred":[
        "Ka\u010diu\u0161kiai"
    ],
    "wof:name":"Kaciuskiai",
    "wof:placetype":"locality"
},
  "geometry": {"coordinates":[23.61079,55.57803000000001],"type":"Point"}
}