{
  "type": "Feature",
  "properties": {
    "gn:admin1_code":"64",
    "gn:admin2_code":"82.0",
    "gn:asciiname":"Zebriskes",
    "gn:country_code":"LT",
    "gn:dem":195,
    "gn:feature_class":"P",
    "gn:feature_code":"PPL",
    "gn:name":"\u017debri\u0161k\u0117s",
    "gn:population":0,
    "gn:timezone":"Europe/Vilnius",
    "iso:country":"LT",
    "name:lit_x_preferred":[
        "\u017debri\u0161k\u0117s"
    ],
    "wof:name":"Zebriskes",
    "wof:placetype":"locality"
},
  "geometry": {"coordinates":[25.75544,55.4565],"type":"Point"}
}