{
  "type": "Feature",
  "properties": {
    "gn:admin1_code":"60.0",
    "gn:admin2_code":"36.0",
    "gn:asciiname":"Nausedziai",
    "gn:country_code":"LT",
    "gn:dem":46,
    "gn:feature_class":"P",
    "gn:feature_code":"PPL",
    "gn:name":"Naus\u0117d\u017eiai",
    "gn:population":0,
    "gn:timezone":"Europe/Vilnius",
    "iso:country":"LT",
    "name:und_x_variant":[
        "Naus\u0117d\u017ei\u0173",
        "Nausedzhyay",
        "Naus\u0117d\u017eiai"
    ],
    "wof:name":"Nausedziai",
    "wof:placetype":"locality"
},
  "geometry": {"coordinates":[24.77368,56.36475],"type":"Point"}
}