{
  "type": "Feature",
  "properties": {
    "gn:admin1_code":"64",
    "gn:admin2_code":"43.0",
    "gn:asciiname":"Siratava",
    "gn:country_code":"LT",
    "gn:dem":116,
    "gn:feature_class":"P",
    "gn:feature_code":"PPL",
    "gn:name":"Siratava",
    "gn:population":0,
    "gn:timezone":"Europe/Vilnius",
    "iso:country":"LT",
    "name:lit_x_preferred":[
        "Siratava"
    ],
    "wof:name":"Siratava",
    "wof:placetype":"locality"
},
  "geometry": {"coordinates":[25.78097,55.69545],"type":"Point"}
}