{
  "type": "Feature",
  "properties": {
    "gn:admin1_code":"59.0",
    "gn:admin2_code":"84.0",
    "gn:asciiname":"Zvirgzdaiciai",
    "gn:country_code":"LT",
    "gn:dem":43,
    "gn:feature_class":"P",
    "gn:feature_code":"PPL",
    "gn:name":"\u017dvirg\u017edai\u010diai",
    "gn:population":0,
    "gn:timezone":"Europe/Vilnius",
    "iso:country":"LT",
    "name:und_x_variant":[
        "Zhvirgzhdaychyay",
        "\u017dvirg\u017edai\u010di\u0173",
        "Zhvirgzhdaitse",
        "\u017dvirg\u017edai\u010diai"
    ],
    "wof:name":"Zvirgzdaiciai",
    "wof:placetype":"locality"
},
  "geometry": {"coordinates":[23.03096,54.79508000000001],"type":"Point"}
}