{
  "type": "Feature",
  "properties": {
    "gn:admin1_code":"57.0",
    "gn:admin2_code":"19.0",
    "gn:asciiname":"Jurginiskiai",
    "gn:country_code":"LT",
    "gn:dem":87,
    "gn:feature_class":"P",
    "gn:feature_code":"PPL",
    "gn:name":"Jurgini\u0161kiai",
    "gn:population":0,
    "gn:timezone":"Europe/Vilnius",
    "iso:country":"LT",
    "name:und_x_variant":[
        "Yurgenishki",
        "Jurgoni\u0161ki\u0173",
        "Yurginishkyay",
        "Jurgini\u0161k\u0117s",
        "Jurgini\u0161ki\u0173",
        "Jurgini\u0161kiai"
    ],
    "wof:name":"Jurginiskiai",
    "wof:placetype":"locality"
},
  "geometry": {"coordinates":[23.78058,54.77557],"type":"Point"}
}