{
  "type": "Feature",
  "properties": {
    "gn:admin1_code":"59.0",
    "gn:admin2_code":"39.0",
    "gn:asciiname":"Slabadai",
    "gn:country_code":"LT",
    "gn:dem":42,
    "gn:feature_class":"P",
    "gn:feature_code":"PPL",
    "gn:name":"Slabadai",
    "gn:population":0,
    "gn:timezone":"Europe/Vilnius",
    "iso:country":"LT",
    "name:eng_x_preferred":[
        "Slabadai"
    ],
    "name:rus_x_preferred":[
        "\u0421\u043b\u0430\u0431\u0430\u0434\u0430\u0439"
    ],
    "name:und_x_variant":[
        "Sloboda",
        "Slabaday",
        "Slabados",
        "Slabad\u0173",
        "Slabadai"
    ],
    "wof:name":"Slabadai",
    "wof:placetype":"locality"
},
  "geometry": {"coordinates":[22.98807,54.76291],"type":"Point"}
}