{
  "type": "Feature",
  "properties": {
    "gn:admin1_code":"60.0",
    "gn:admin2_code":"57.0",
    "gn:asciiname":"Darsiskiai",
    "gn:country_code":"LT",
    "gn:dem":65,
    "gn:feature_class":"P",
    "gn:feature_code":"PPL",
    "gn:name":"Dar\u0161i\u0161kiai",
    "gn:population":0,
    "gn:timezone":"Europe/Vilnius",
    "iso:country":"LT",
    "name:und_x_variant":[
        "Darshishkes",
        "Dar\u0161i\u0161kiai"
    ],
    "wof:name":"Darsiskiai",
    "wof:placetype":"locality"
},
  "geometry": {"coordinates":[24.7783,55.90897],"type":"Point"}
}