{
  "type": "Feature",
  "properties": {
    "gn:admin1_code":"60",
    "gn:admin2_code":"67.0",
    "gn:asciiname":"Kuzmiskis",
    "gn:country_code":"LT",
    "gn:dem":42,
    "gn:feature_class":"P",
    "gn:feature_code":"PPL",
    "gn:name":"Ku\u017emi\u0161kis",
    "gn:population":0,
    "gn:timezone":"Europe/Vilnius",
    "iso:country":"LT",
    "name:lit_x_preferred":[
        "Ku\u017emi\u0161kis"
    ],
    "wof:name":"Kuzmiskis",
    "wof:placetype":"locality"
},
  "geometry": {"coordinates":[24.25324,56.2418],"type":"Point"}
}