{
  "type": "Feature",
  "properties": {
    "gn:admin1_code":"57.0",
    "gn:admin2_code":"72.0",
    "gn:asciiname":"Kantroliai",
    "gn:country_code":"LT",
    "gn:dem":101,
    "gn:feature_class":"P",
    "gn:feature_code":"PPL",
    "gn:name":"Kantroliai",
    "gn:population":0,
    "gn:timezone":"Europe/Vilnius",
    "iso:country":"LT",
    "name:und_x_variant":[
        "Ramonai Antrieji",
        "Ramonai"
    ],
    "wof:name":"Kantroliai",
    "wof:placetype":"locality"
},
  "geometry": {"coordinates":[23.11828,55.40199000000001],"type":"Point"}
}