{
  "type": "Feature",
  "properties": {
    "gn:admin1_code":"0.0",
    "gn:asciiname":"Obeline",
    "gn:cc2":"LT",
    "gn:country_code":"LT",
    "gn:dem":134,
    "gn:feature_class":"P",
    "gn:feature_code":"PPL",
    "gn:name":"Obelin\u0117",
    "gn:population":0,
    "gn:timezone":"Europe/Vilnius",
    "iso:country":"LT",
    "name:und_x_variant":[
        "Vobalina",
        "Obelin\u0117"
    ],
    "wof:name":"Obeline",
    "wof:placetype":"locality"
},
  "geometry": {"coordinates":[22.71667,55.61666999999999],"type":"Point"}
}