{
  "type": "Feature",
  "properties": {
    "gn:admin1_code":"61",
    "gn:admin2_code":"54.0",
    "gn:asciiname":"Suvartuva",
    "gn:country_code":"LT",
    "gn:dem":131,
    "gn:feature_class":"P",
    "gn:feature_code":"PPL",
    "gn:name":"Suvartuva",
    "gn:population":0,
    "gn:timezone":"Europe/Vilnius",
    "iso:country":"LT",
    "name:lit_x_preferred":[
        "Suvartuva"
    ],
    "wof:name":"Suvartuva",
    "wof:placetype":"locality"
},
  "geometry": {"coordinates":[22.9895,55.71245],"type":"Point"}
}