{
  "type": "Feature",
  "properties": {
    "gn:admin1_code":"56.0",
    "gn:admin2_code":"38.0",
    "gn:asciiname":"Vazgirdonys",
    "gn:country_code":"LT",
    "gn:dem":139,
    "gn:feature_class":"P",
    "gn:feature_code":"PPL",
    "gn:name":"Vazgirdonys",
    "gn:population":0,
    "gn:timezone":"Europe/Vilnius",
    "iso:country":"LT",
    "name:fas_x_preferred":[
        "\u0648\u0632\u06af\u06cc\u0631\u062f\u0646\u06cc\u0633"
    ],
    "name:lit_x_preferred":[
        "Vazgirdonys"
    ],
    "wof:name":"Vazgirdonys",
    "wof:placetype":"locality"
},
  "geometry": {"coordinates":[24.57083,54.34301],"type":"Point"}
}