{
  "type": "Feature",
  "properties": {
    "gn:admin1_code":"59.0",
    "gn:admin2_code":"84.0",
    "gn:asciiname":"Joginiskiai",
    "gn:country_code":"LT",
    "gn:dem":60,
    "gn:feature_class":"P",
    "gn:feature_code":"PPL",
    "gn:name":"Jogini\u0161kiai",
    "gn:population":0,
    "gn:timezone":"Europe/Vilnius",
    "iso:country":"LT",
    "name:lit_x_preferred":[
        "Jogini\u0161kiai"
    ],
    "name:und_x_variant":[
        "Jogini\u0161kiai Antrieji",
        "Jogini\u0161kiai II"
    ],
    "wof:name":"Joginiskiai",
    "wof:placetype":"locality"
},
  "geometry": {"coordinates":[23.39481,55.06228],"type":"Point"}
}