{
  "type": "Feature",
  "properties": {
    "gn:admin1_code":"65",
    "gn:admin2_code":"81.0",
    "gn:asciiname":"Juodvisine",
    "gn:country_code":"LT",
    "gn:dem":80,
    "gn:feature_class":"P",
    "gn:feature_code":"PPL",
    "gn:name":"Juodvisin\u0117",
    "gn:population":0,
    "gn:timezone":"Europe/Vilnius",
    "iso:country":"LT",
    "name:lit_x_preferred":[
        "Juodvisin\u0117"
    ],
    "wof:name":"Juodvisine",
    "wof:placetype":"locality"
},
  "geometry": {"coordinates":[24.57911,55.3999],"type":"Point"}
}