{
  "type": "Feature",
  "properties": {
    "gn:admin1_code":"64",
    "gn:admin2_code":"43.0",
    "gn:asciiname":"Kunotai",
    "gn:country_code":"LT",
    "gn:dem":173,
    "gn:feature_class":"P",
    "gn:feature_code":"PPL",
    "gn:name":"Kunotai",
    "gn:population":0,
    "gn:timezone":"Europe/Vilnius",
    "iso:country":"LT",
    "name:lit_x_preferred":[
        "Kunotai"
    ],
    "wof:name":"Kunotai",
    "wof:placetype":"locality"
},
  "geometry": {"coordinates":[25.97555,55.69995],"type":"Point"}
}