{
  "type": "Feature",
  "properties": {
    "gn:admin1_code":"58.0",
    "gn:admin2_code":"55.0",
    "gn:asciiname":"Gibisai",
    "gn:country_code":"LT",
    "gn:dem":1,
    "gn:feature_class":"P",
    "gn:feature_code":"PPL",
    "gn:name":"Gibi\u0161ai",
    "gn:population":0,
    "gn:timezone":"Europe/Vilnius",
    "iso:country":"LT",
    "name:und_x_variant":[
        "Gibbishen-Martin",
        "Gibi\u0161ai"
    ],
    "wof:name":"Gibisai",
    "wof:placetype":"locality"
},
  "geometry": {"coordinates":[21.20199,55.6444],"type":"Point"}
}