{
  "type": "Feature",
  "properties": {
    "iso:country":"LT",
    "name:lit_x_preferred":[
        "Lazdyn\u0117liai"
    ],
    "wof:name":"Lazdyneliai",
    "wof:placetype":"neighbourhood"
},
  "geometry": {"coordinates":[25.18917122149279,54.66259442390798],"type":"Point"}
}