{
  "type": "Feature",
  "properties": {
    "gn:admin1_code":"57.0",
    "gn:admin2_code":"53.0",
    "gn:asciiname":"Paberze",
    "gn:country_code":"LT",
    "gn:dem":66,
    "gn:feature_class":"P",
    "gn:feature_code":"PPL",
    "gn:name":"Paber\u017e\u0117",
    "gn:population":0,
    "gn:timezone":"Europe/Vilnius",
    "iso:country":"LT",
    "name:und_x_variant":[
        "Podbzhez\u2019",
        "Paber\u017e\u0117s",
        "Padbzhezyay",
        "Podbrzezie",
        "Paber\u017e\u0117"
    ],
    "wof:name":"Paberze",
    "wof:placetype":"locality"
},
  "geometry": {"coordinates":[23.96838,55.50403000000001],"type":"Point"}
}