{
  "type": "Feature",
  "properties": {
    "gn:admin1_code":"56",
    "gn:admin2_code":"59.0",
    "gn:asciiname":"Bertasiunai",
    "gn:country_code":"LT",
    "gn:dem":114,
    "gn:feature_class":"P",
    "gn:feature_code":"PPL",
    "gn:name":"Berta\u0161i\u016bnai",
    "gn:population":0,
    "gn:timezone":"Europe/Vilnius",
    "iso:country":"LT",
    "name:lit_x_preferred":[
        "Berta\u0161i\u016bnai"
    ],
    "wof:name":"Bertasiunai",
    "wof:placetype":"locality"
},
  "geometry": {"coordinates":[23.77702,54.05778000000001],"type":"Point"}
}