{
  "type": "Feature",
  "properties": {
    "gn:admin1_code":"64.0",
    "gn:admin2_code":"62.0",
    "gn:asciiname":"Bekupe",
    "gn:country_code":"LT",
    "gn:dem":133,
    "gn:feature_class":"P",
    "gn:feature_code":"PPL",
    "gn:name":"Bekup\u0117",
    "gn:population":0,
    "gn:timezone":"Europe/Vilnius",
    "iso:country":"LT",
    "name:lit_x_preferred":[
        "Bekup\u0117"
    ],
    "name:lit_x_variant":[
        "Bekupe"
    ],
    "wof:name":"Bekupe",
    "wof:placetype":"locality"
},
  "geometry": {"coordinates":[25.21123,55.10994],"type":"Point"}
}