{
  "type": "Feature",
  "properties": {
    "gn:admin1_code":"57",
    "gn:admin2_code":"53.0",
    "gn:asciiname":"Pestiniukai",
    "gn:country_code":"LT",
    "gn:dem":93,
    "gn:feature_class":"P",
    "gn:feature_code":"PPL",
    "gn:name":"Pe\u0161tiniukai",
    "gn:population":0,
    "gn:timezone":"Europe/Vilnius",
    "iso:country":"LT",
    "name:lit_x_preferred":[
        "Pe\u0161tiniukai"
    ],
    "wof:name":"Pestiniukai",
    "wof:placetype":"locality"
},
  "geometry": {"coordinates":[23.70357000000001,55.4134],"type":"Point"}
}