{
  "type": "Feature",
  "properties": {
    "gn:admin1_code":"57.0",
    "gn:admin2_code":"19.0",
    "gn:asciiname":"Paneveziukas",
    "gn:country_code":"LT",
    "gn:dem":29,
    "gn:feature_class":"P",
    "gn:feature_code":"PPL",
    "gn:name":"Panev\u0117\u017eiukas",
    "gn:population":0,
    "gn:timezone":"Europe/Vilnius",
    "iso:country":"LT",
    "name:und_x_variant":[
        "Ponevezhik",
        "Panev\u0117\u017eiuko",
        "Panev\u0117\u017eiukas"
    ],
    "wof:name":"Paneveziukas",
    "wof:placetype":"locality"
},
  "geometry": {"coordinates":[23.78732,55.13958],"type":"Point"}
}