{
  "type": "Feature",
  "properties": {
    "gn:admin1_code":"65",
    "gn:admin2_code":"86.0",
    "gn:asciiname":"Merionys II",
    "gn:country_code":"LT",
    "gn:dem":143,
    "gn:feature_class":"P",
    "gn:feature_code":"PPL",
    "gn:name":"Merionys II",
    "gn:population":0,
    "gn:timezone":"Europe/Vilnius",
    "iso:country":"LT",
    "name:lit_x_preferred":[
        "Merionys II"
    ],
    "wof:name":"Merionys II",
    "wof:placetype":"locality"
},
  "geometry": {"coordinates":[25.60326,55.01788000000001],"type":"Point"}
}