{
  "type": "Feature",
  "properties": {
    "gn:admin1_code":"59",
    "gn:admin2_code":"39.0",
    "gn:asciiname":"Naujienele",
    "gn:country_code":"LT",
    "gn:dem":68,
    "gn:feature_class":"P",
    "gn:feature_code":"PPL",
    "gn:name":"Naujien\u0117l\u0117",
    "gn:population":0,
    "gn:timezone":"Europe/Vilnius",
    "iso:country":"LT",
    "name:lit_x_preferred":[
        "Naujien\u0117l\u0117"
    ],
    "wof:name":"Naujienele",
    "wof:placetype":"locality"
},
  "geometry": {"coordinates":[23.2405,54.60292],"type":"Point"}
}