{
  "type": "Feature",
  "properties": {
    "gn:admin1_code":"61",
    "gn:admin2_code":"54.0",
    "gn:asciiname":"Ganyprova",
    "gn:country_code":"LT",
    "gn:dem":169,
    "gn:feature_class":"P",
    "gn:feature_code":"PPL",
    "gn:name":"Ganyprova",
    "gn:population":0,
    "gn:timezone":"Europe/Vilnius",
    "iso:country":"LT",
    "name:lit_x_preferred":[
        "Ganyprova"
    ],
    "wof:name":"Ganyprova",
    "wof:placetype":"locality"
},
  "geometry": {"coordinates":[22.78657,55.62365],"type":"Point"}
}