{
  "type": "Feature",
  "properties": {
    "gn:admin1_code":"63.0",
    "gn:admin2_code":"78.0",
    "gn:asciiname":"Pervainiai",
    "gn:country_code":"LT",
    "gn:dem":127,
    "gn:feature_class":"P",
    "gn:feature_code":"PPL",
    "gn:name":"Pervainiai",
    "gn:population":0,
    "gn:timezone":"Europe/Vilnius",
    "iso:country":"LT",
    "name:und_x_variant":[
        "Pervonyay",
        "Pervainiai"
    ],
    "wof:name":"Pervainiai",
    "wof:placetype":"locality"
},
  "geometry": {"coordinates":[22.51242,55.97373],"type":"Point"}
}