{
  "type": "Feature",
  "properties": {
    "gn:admin1_code":"65.0",
    "gn:admin2_code":"13.0",
    "gn:asciiname":"Nemezis",
    "gn:country_code":"LT",
    "gn:dem":194,
    "gn:feature_class":"P",
    "gn:feature_code":"PPL",
    "gn:name":"Nem\u0117\u017eis",
    "gn:population":0,
    "gn:timezone":"Europe/Vilnius",
    "iso:country":"LT",
    "name:deu_x_preferred":[
        "Nem\u0117\u017eis"
    ],
    "name:hun_x_preferred":[
        "Nem\u0117\u017eis"
    ],
    "name:lit_x_preferred":[
        "Nem\u0117\u017eis"
    ],
    "name:pol_x_preferred":[
        "Niemie\u017c"
    ],
    "name:rus_x_preferred":[
        "\u041d\u044f\u043c\u0435\u0436\u0438\u0441"
    ],
    "name:sco_x_preferred":[
        "Nem\u0117\u017eis"
    ],
    "name:spa_x_preferred":[
        "Nem\u0117\u017eis"
    ],
    "name:tat_x_preferred":[
        "\u041d\u0435\u043c\u0435\u0436"
    ],
    "name:und_x_variant":[
        "Nemezhis",
        "Nem\u0117\u017e\u0117",
        "Okolitsa Nemezh",
        "Nemie\u017eis",
        "Nemie\u017eius",
        "Nem\u0117\u017ea",
        "Nemie\u017c",
        "Nem\u0117\u017eis"
    ],
    "wof:name":"Nemezis",
    "wof:placetype":"locality"
},
  "geometry": {"coordinates":[25.35455,54.63629],"type":"Point"}
}