{
  "type": "Feature",
  "properties": {
    "gn:admin1_code":"65",
    "gn:admin2_code":"81.0",
    "gn:asciiname":"Jusiskis I",
    "gn:country_code":"LT",
    "gn:dem":92,
    "gn:feature_class":"P",
    "gn:feature_code":"PPL",
    "gn:name":"Jusi\u0161kis I",
    "gn:population":0,
    "gn:timezone":"Europe/Vilnius",
    "iso:country":"LT",
    "name:lit_x_preferred":[
        "Jusi\u0161kis I"
    ],
    "wof:name":"Jusiskis I",
    "wof:placetype":"locality"
},
  "geometry": {"coordinates":[24.79251,55.44491],"type":"Point"}
}