{
  "type": "Feature",
  "properties": {
    "gn:admin1_code":"65.0",
    "gn:admin2_code":"81.0",
    "gn:asciiname":"Gailioniai",
    "gn:country_code":"LT",
    "gn:dem":82,
    "gn:feature_class":"P",
    "gn:feature_code":"PPL",
    "gn:name":"Gailioniai",
    "gn:population":0,
    "gn:timezone":"Europe/Vilnius",
    "iso:country":"LT",
    "name:und_x_variant":[
        "Gaylenyay",
        "Gailioniai"
    ],
    "wof:name":"Gailioniai",
    "wof:placetype":"locality"
},
  "geometry": {"coordinates":[24.49132,55.19431],"type":"Point"}
}