{
  "type": "Feature",
  "properties": {
    "gn:admin1_code":"56",
    "gn:admin2_code":"38.0",
    "gn:asciiname":"Zakoriai",
    "gn:country_code":"LT",
    "gn:dem":152,
    "gn:feature_class":"P",
    "gn:feature_code":"PPL",
    "gn:name":"Zakoriai",
    "gn:population":0,
    "gn:timezone":"Europe/Vilnius",
    "iso:country":"LT",
    "name:lit_x_preferred":[
        "Zakoriai"
    ],
    "wof:name":"Zakoriai",
    "wof:placetype":"locality"
},
  "geometry": {"coordinates":[24.6595,54.35758000000001],"type":"Point"}
}