{
  "type": "Feature",
  "properties": {
    "gn:admin1_code":"61.0",
    "gn:admin2_code":"71.0",
    "gn:asciiname":"Dotiskiai",
    "gn:country_code":"LT",
    "gn:dem":72,
    "gn:feature_class":"P",
    "gn:feature_code":"PPL",
    "gn:name":"Doti\u0161kiai",
    "gn:population":0,
    "gn:timezone":"Europe/Vilnius",
    "iso:country":"LT",
    "name:und_x_variant":[
        "Datyshkyay",
        "Doti\u0161kiai"
    ],
    "wof:name":"Dotiskiai",
    "wof:placetype":"locality"
},
  "geometry": {"coordinates":[23.96708,55.7058],"type":"Point"}
}