{
  "type": "Feature",
  "properties": {
    "gn:admin1_code":"64",
    "gn:admin2_code":"34.0",
    "gn:asciiname":"Smulkis",
    "gn:country_code":"LT",
    "gn:dem":155,
    "gn:feature_class":"P",
    "gn:feature_code":"PPL",
    "gn:name":"Smulkis",
    "gn:population":0,
    "gn:timezone":"Europe/Vilnius",
    "iso:country":"LT",
    "name:lit_x_preferred":[
        "Smulkis"
    ],
    "wof:name":"Smulkis",
    "wof:placetype":"locality"
},
  "geometry": {"coordinates":[25.36213,55.45968000000001],"type":"Point"}
}