{
  "type": "Feature",
  "properties": {
    "gn:admin1_code":"58",
    "gn:admin2_code":"21.0",
    "gn:asciiname":"Sausiai",
    "gn:country_code":"LT",
    "gn:dem":50,
    "gn:feature_class":"P",
    "gn:feature_code":"PPL",
    "gn:name":"Sausiai",
    "gn:population":0,
    "gn:timezone":"Europe/Vilnius",
    "iso:country":"LT",
    "name:lit_x_preferred":[
        "Sausiai"
    ],
    "wof:name":"Sausiai",
    "wof:placetype":"locality"
},
  "geometry": {"coordinates":[21.6318,55.5913],"type":"Point"}
}