{
  "type": "Feature",
  "properties": {
    "gn:admin1_code":"65",
    "gn:admin2_code":"89.0",
    "gn:asciiname":"Raudonka",
    "gn:country_code":"LT",
    "gn:dem":98,
    "gn:feature_class":"P",
    "gn:feature_code":"PPL",
    "gn:name":"Raudonka",
    "gn:population":0,
    "gn:timezone":"Europe/Vilnius",
    "iso:country":"LT",
    "name:lit_x_preferred":[
        "Raudonka"
    ],
    "wof:name":"Raudonka",
    "wof:placetype":"locality"
},
  "geometry": {"coordinates":[24.67034,55.04903],"type":"Point"}
}