{
  "type": "Feature",
  "properties": {
    "gn:admin1_code":"56",
    "gn:admin2_code":"59.0",
    "gn:asciiname":"Ancios",
    "gn:country_code":"LT",
    "gn:dem":122,
    "gn:feature_class":"P",
    "gn:feature_code":"PPL",
    "gn:name":"An\u010dios",
    "gn:population":0,
    "gn:timezone":"Europe/Vilnius",
    "iso:country":"LT",
    "name:lit_x_preferred":[
        "An\u010dios"
    ],
    "wof:name":"Ancios",
    "wof:placetype":"locality"
},
  "geometry": {"coordinates":[23.74219,54.07682],"type":"Point"}
}