{
  "type": "Feature",
  "properties": {
    "gn:admin1_code":"65",
    "gn:admin2_code":"13.0",
    "gn:asciiname":"Vyzulionys",
    "gn:country_code":"LT",
    "gn:dem":176,
    "gn:feature_class":"P",
    "gn:feature_code":"PPL",
    "gn:name":"Vy\u017eulionys",
    "gn:population":0,
    "gn:timezone":"Europe/Vilnius",
    "iso:country":"LT",
    "name:lit_x_preferred":[
        "Vy\u017eulionys"
    ],
    "wof:name":"Vyzulionys",
    "wof:placetype":"locality"
},
  "geometry": {"coordinates":[25.29506,54.93982],"type":"Point"}
}