{
  "type": "Feature",
  "properties": {
    "gn:admin1_code":"62.0",
    "gn:admin2_code":"87.0",
    "gn:asciiname":"Kastauniske",
    "gn:country_code":"LT",
    "gn:dem":150,
    "gn:feature_class":"P",
    "gn:feature_code":"PPL",
    "gn:name":"Kastauni\u0161k\u0117",
    "gn:population":0,
    "gn:timezone":"Europe/Vilnius",
    "iso:country":"LT",
    "name:und_x_variant":[
        "Kashtaunay",
        "Kastauni\u0161k\u0117"
    ],
    "wof:name":"Kastauniske",
    "wof:placetype":"locality"
},
  "geometry": {"coordinates":[22.32462,55.52757],"type":"Point"}
}