{
  "type": "Feature",
  "properties": {
    "gn:admin1_code":"65.0",
    "gn:admin2_code":"89.0",
    "gn:asciiname":"Ciobiskis",
    "gn:country_code":"LT",
    "gn:dem":52,
    "gn:feature_class":"P",
    "gn:feature_code":"PPL",
    "gn:name":"\u010ciobi\u0161kis",
    "gn:population":0,
    "gn:timezone":"Europe/Vilnius",
    "iso:country":"LT",
    "name:und_x_variant":[
        "Chebishkis",
        "Chiobishkis",
        "Chuobishkis",
        "Czabiszki",
        "Chabishi",
        "\u010ciobi\u0161ki\u0173",
        "\u010ciobi\u0161kio",
        "Chobashkis",
        "\u010ciubi\u0161kis",
        "\u010ciobi\u0161kis"
    ],
    "wof:name":"Ciobiskis",
    "wof:placetype":"locality"
},
  "geometry": {"coordinates":[24.66016,54.95466999999999],"type":"Point"}
}