{
  "type": "Feature",
  "properties": {
    "gn:admin1_code":"65.0",
    "gn:admin2_code":"81.0",
    "gn:asciiname":"Kreiviai",
    "gn:country_code":"LT",
    "gn:dem":78,
    "gn:feature_class":"P",
    "gn:feature_code":"PPL",
    "gn:name":"Kreiviai",
    "gn:population":0,
    "gn:timezone":"Europe/Vilnius",
    "iso:country":"LT",
    "name:und_x_variant":[
        "Kreivi\u0173",
        "Kreyvyay",
        "Kreiviai"
    ],
    "wof:name":"Kreiviai",
    "wof:placetype":"locality"
},
  "geometry": {"coordinates":[24.62218,55.23705],"type":"Point"}
}