{
  "type": "Feature",
  "properties": {
    "gn:admin1_code":"62",
    "gn:admin2_code":"94.0",
    "gn:asciiname":"Lapgiriai",
    "gn:country_code":"LT",
    "gn:dem":58,
    "gn:feature_class":"P",
    "gn:feature_code":"PPL",
    "gn:name":"Lapgiriai",
    "gn:population":0,
    "gn:timezone":"Europe/Vilnius",
    "iso:country":"LT",
    "name:lit_x_preferred":[
        "Lapgiriai"
    ],
    "wof:name":"Lapgiriai",
    "wof:placetype":"locality"
},
  "geometry": {"coordinates":[22.86649,55.25403000000001],"type":"Point"}
}