{
  "type": "Feature",
  "properties": {
    "gn:admin1_code":"64",
    "gn:admin2_code":"34.0",
    "gn:asciiname":"Viesinteles",
    "gn:country_code":"LT",
    "gn:dem":109,
    "gn:feature_class":"P",
    "gn:feature_code":"PPL",
    "gn:name":"Vie\u0161int\u0117l\u0117s",
    "gn:population":0,
    "gn:timezone":"Europe/Vilnius",
    "iso:country":"LT",
    "name:lit_x_preferred":[
        "Vie\u0161int\u0117l\u0117s"
    ],
    "wof:name":"Viesinteles",
    "wof:placetype":"locality"
},
  "geometry": {"coordinates":[24.98797,55.68234],"type":"Point"}
}