{
  "type": "Feature",
  "properties": {
    "gn:admin1_code":"62.0",
    "gn:admin2_code":"77.0",
    "gn:asciiname":"Dauglaukis",
    "gn:country_code":"LT",
    "gn:dem":19,
    "gn:feature_class":"P",
    "gn:feature_code":"PPL",
    "gn:name":"Dauglaukis",
    "gn:population":0,
    "gn:timezone":"Europe/Vilnius",
    "iso:country":"LT",
    "name:und_x_variant":[
        "Dauglaukis Didysis",
        "Dovkintlavki",
        "Dauglaukis Ma\u017easis",
        "Dauglaukis"
    ],
    "wof:name":"Dauglaukis",
    "wof:placetype":"locality"
},
  "geometry": {"coordinates":[22.21866,55.187],"type":"Point"}
}