{
  "type": "Feature",
  "properties": {
    "gn:admin1_code":"56.0",
    "gn:admin2_code":"11.0",
    "gn:asciiname":"Mikutiskiai",
    "gn:country_code":"LT",
    "gn:dem":111,
    "gn:feature_class":"P",
    "gn:feature_code":"PPL",
    "gn:name":"Mikuti\u0161kiai",
    "gn:population":0,
    "gn:timezone":"Europe/Vilnius",
    "iso:country":"LT",
    "name:und_x_variant":[
        "Mikutishki",
        "Mikutishkyay",
        "Mikuti\u0161kiai"
    ],
    "wof:name":"Mikutiskiai",
    "wof:placetype":"locality"
},
  "geometry": {"coordinates":[24.03436,54.47994],"type":"Point"}
}