{
  "type": "Feature",
  "properties": {
    "gn:admin1_code":"61.0",
    "gn:admin2_code":"71.0",
    "gn:asciiname":"Balandiskis",
    "gn:country_code":"LT",
    "gn:dem":111,
    "gn:feature_class":"P",
    "gn:feature_code":"PPL",
    "gn:name":"Balandi\u0161kis",
    "gn:population":0,
    "gn:timezone":"Europe/Vilnius",
    "iso:country":"LT",
    "name:und_x_variant":[
        "Balandi\u0161kis",
        "Pa\u0161u\u0161vys"
    ],
    "wof:name":"Balandiskis",
    "wof:placetype":"locality"
},
  "geometry": {"coordinates":[23.58297,55.59689],"type":"Point"}
}