{
  "type": "Feature",
  "properties": {
    "gn:admin1_code":"64",
    "gn:admin2_code":"43.0",
    "gn:asciiname":"Dumblyne",
    "gn:country_code":"LT",
    "gn:dem":127,
    "gn:feature_class":"P",
    "gn:feature_code":"PPL",
    "gn:name":"Dumblyn\u0117",
    "gn:population":0,
    "gn:timezone":"Europe/Vilnius",
    "iso:country":"LT",
    "name:lit_x_preferred":[
        "Dumblyn\u0117"
    ],
    "wof:name":"Dumblyne",
    "wof:placetype":"locality"
},
  "geometry": {"coordinates":[25.90225,55.80601],"type":"Point"}
}