{
  "type": "Feature",
  "properties": {
    "gn:admin1_code":"64",
    "gn:admin2_code":"62.0",
    "gn:asciiname":"Krasnogurka",
    "gn:country_code":"LT",
    "gn:dem":194,
    "gn:feature_class":"P",
    "gn:feature_code":"PPL",
    "gn:name":"Krasnogurka",
    "gn:population":0,
    "gn:timezone":"Europe/Vilnius",
    "iso:country":"LT",
    "name:lit_x_preferred":[
        "Krasnogurka"
    ],
    "wof:name":"Krasnogurka",
    "wof:placetype":"locality"
},
  "geometry": {"coordinates":[25.42431,55.12358],"type":"Point"}
}