{
  "type": "Feature",
  "properties": {
    "gn:admin1_code":"57",
    "gn:admin2_code":"46.0",
    "gn:asciiname":"Sabuniskiai",
    "gn:country_code":"LT",
    "gn:dem":85,
    "gn:feature_class":"P",
    "gn:feature_code":"PPL",
    "gn:name":"Sab\u016bni\u0161kiai",
    "gn:population":0,
    "gn:timezone":"Europe/Vilnius",
    "iso:country":"LT",
    "name:lit_x_preferred":[
        "Sab\u016bni\u0161kiai"
    ],
    "wof:name":"Sabuniskiai",
    "wof:placetype":"locality"
},
  "geometry": {"coordinates":[24.12802000000001,55.05838000000001],"type":"Point"}
}