{
  "type": "Feature",
  "properties": {
    "gn:admin1_code":"64",
    "gn:admin2_code":"43.0",
    "gn:asciiname":"Paberze",
    "gn:country_code":"LT",
    "gn:dem":147,
    "gn:feature_class":"P",
    "gn:feature_code":"PPL",
    "gn:name":"Paber\u017e\u0117",
    "gn:population":0,
    "gn:timezone":"Europe/Riga",
    "iso:country":"LT",
    "name:lit_x_preferred":[
        "Paber\u017e\u0117"
    ],
    "wof:name":"Paberze",
    "wof:placetype":"locality"
},
  "geometry": {"coordinates":[26.56869,55.67793],"type":"Point"}
}