{
  "type": "Feature",
  "properties": {
    "gn:admin1_code":"59.0",
    "gn:admin2_code":"58.0",
    "gn:asciiname":"Pliopliai",
    "gn:country_code":"LT",
    "gn:dem":48,
    "gn:feature_class":"P",
    "gn:feature_code":"PPL",
    "gn:name":"Pliopliai",
    "gn:population":0,
    "gn:timezone":"Europe/Vilnius",
    "iso:country":"LT",
    "name:und_x_variant":[
        "Pleple",
        "Pleplyay",
        "Pliopliai"
    ],
    "wof:name":"Pliopliai",
    "wof:placetype":"locality"
},
  "geometry": {"coordinates":[23.32123,54.71455],"type":"Point"}
}