{
  "type": "Feature",
  "properties": {
    "gn:admin1_code":"65",
    "gn:admin2_code":"13.0",
    "gn:asciiname":"Darzeliai",
    "gn:country_code":"LT",
    "gn:dem":184,
    "gn:feature_class":"P",
    "gn:feature_code":"PPL",
    "gn:name":"Dar\u017eeliai",
    "gn:population":0,
    "gn:timezone":"Europe/Vilnius",
    "iso:country":"LT",
    "name:lit_x_preferred":[
        "Dar\u017eeliai"
    ],
    "wof:name":"Darzeliai",
    "wof:placetype":"locality"
},
  "geometry": {"coordinates":[25.66068,54.83438],"type":"Point"}
}