{
  "type": "Feature",
  "properties": {
    "gn:admin1_code":"57.0",
    "gn:admin2_code":"19.0",
    "gn:asciiname":"Pazerai",
    "gn:country_code":"LT",
    "gn:dem":84,
    "gn:feature_class":"P",
    "gn:feature_code":"PPL",
    "gn:name":"Pa\u017e\u0117rai",
    "gn:population":0,
    "gn:timezone":"Europe/Vilnius",
    "iso:country":"LT",
    "name:und_x_variant":[
        "Pa\u017eeriai",
        "Po\u017e\u0117rai",
        "Pazheray",
        "Pa\u017eeri\u0173",
        "Pozhery",
        "Pa\u017e\u0117rai"
    ],
    "wof:name":"Pazerai",
    "wof:placetype":"locality"
},
  "geometry": {"coordinates":[23.73084,54.81565],"type":"Point"}
}