{
  "type": "Feature",
  "properties": {
    "gn:admin1_code":"61",
    "gn:admin2_code":"71.0",
    "gn:asciiname":"Minautuva",
    "gn:country_code":"LT",
    "gn:dem":127,
    "gn:feature_class":"P",
    "gn:feature_code":"PPL",
    "gn:name":"Minautuva",
    "gn:population":0,
    "gn:timezone":"Europe/Vilnius",
    "iso:country":"LT",
    "name:lit_x_preferred":[
        "Minautuva"
    ],
    "wof:name":"Minautuva",
    "wof:placetype":"locality"
},
  "geometry": {"coordinates":[23.32522,55.64191999999999],"type":"Point"}
}