{
  "type": "Feature",
  "properties": {
    "gn:admin1_code":"61",
    "gn:admin2_code":"65.0",
    "gn:asciiname":"Gedziunai",
    "gn:country_code":"LT",
    "gn:dem":44,
    "gn:feature_class":"P",
    "gn:feature_code":"PPL",
    "gn:name":"Ged\u017ei\u016bnai",
    "gn:population":0,
    "gn:timezone":"Europe/Vilnius",
    "iso:country":"LT",
    "name:lit_x_preferred":[
        "Ged\u017ei\u016bnai"
    ],
    "wof:name":"Gedziunai",
    "wof:placetype":"locality"
},
  "geometry": {"coordinates":[24.09604,56.07427],"type":"Point"}
}