{
  "type": "Feature",
  "properties": {
    "gn:admin1_code":"64",
    "gn:admin2_code":"34.0",
    "gn:asciiname":"Meldiskiai",
    "gn:country_code":"LT",
    "gn:dem":93,
    "gn:feature_class":"P",
    "gn:feature_code":"PPL",
    "gn:name":"Meldi\u0161kiai",
    "gn:population":0,
    "gn:timezone":"Europe/Vilnius",
    "iso:country":"LT",
    "name:lit_x_preferred":[
        "Meldi\u0161kiai"
    ],
    "wof:name":"Meldiskiai",
    "wof:placetype":"locality"
},
  "geometry": {"coordinates":[24.91233,55.70745],"type":"Point"}
}