{
  "type": "Feature",
  "properties": {
    "gn:admin1_code":"57",
    "gn:admin2_code":"49.0",
    "gn:asciiname":"Paukstiskes",
    "gn:country_code":"LT",
    "gn:dem":103,
    "gn:feature_class":"P",
    "gn:feature_code":"PPL",
    "gn:name":"Pauk\u0161ti\u0161k\u0117s",
    "gn:population":0,
    "gn:timezone":"Europe/Vilnius",
    "iso:country":"LT",
    "name:lit_x_preferred":[
        "Pauk\u0161ti\u0161k\u0117s"
    ],
    "wof:name":"Paukstiskes",
    "wof:placetype":"locality"
},
  "geometry": {"coordinates":[24.29017,54.67697],"type":"Point"}
}