{
  "type": "Feature",
  "properties": {
    "gn:admin1_code":"59.0",
    "gn:admin2_code":"84.0",
    "gn:asciiname":"Barzdai",
    "gn:country_code":"LT",
    "gn:dem":51,
    "gn:feature_class":"P",
    "gn:feature_code":"PPL",
    "gn:name":"Barzdai",
    "gn:population":0,
    "gn:timezone":"Europe/Vilnius",
    "iso:country":"LT",
    "name:und_x_variant":[
        "Barzdy",
        "Barzd\u0173",
        "Barzday",
        "Barzdai"
    ],
    "wof:name":"Barzdai",
    "wof:placetype":"locality"
},
  "geometry": {"coordinates":[23.19464,54.78039],"type":"Point"}
}