{
  "type": "Feature",
  "properties": {
    "gn:admin1_code":"59.0",
    "gn:admin2_code":"84.0",
    "gn:asciiname":"Barzdai",
    "gn:country_code":"LT",
    "gn:dem":51,
    "gn:feature_class":"P",
    "gn:feature_code":"PPL",
    "gn:name":"Barzdai",
    "gn:population":0,
    "gn:timezone":"Europe/Vilnius",
    "iso:country":"LT",
    "name:ceb_x_preferred":[
        "Barzdai"
    ],
    "name:est_x_preferred":[
        "Barzdai"
    ],
    "name:fin_x_preferred":[
        "Barzdai"
    ],
    "name:lit_x_preferred":[
        "Barzdai"
    ],
    "name:nld_x_preferred":[
        "Barzdai"
    ],
    "name:pol_x_preferred":[
        "Barzdy"
    ],
    "name:swe_x_preferred":[
        "Barzdai"
    ],
    "name:und_x_variant":[
        "Barzd\u0173",
        "Barzday"
    ],
    "wof:name":"Barzdai",
    "wof:placetype":"locality"
},
  "geometry": {"coordinates":[23.19464,54.78039],"type":"Point"}
}