{
  "type": "Feature",
  "properties": {
    "gn:admin1_code":"60.0",
    "gn:admin2_code":"67.0",
    "gn:asciiname":"Smilgeliai",
    "gn:country_code":"LT",
    "gn:dem":44,
    "gn:feature_class":"P",
    "gn:feature_code":"PPL",
    "gn:name":"Smilgeliai",
    "gn:population":0,
    "gn:timezone":"Europe/Vilnius",
    "iso:country":"LT",
    "name:und_x_variant":[
        "Smilgelyay",
        "Smilgeli\u0173",
        "Smilgeliai"
    ],
    "wof:name":"Smilgeliai",
    "wof:placetype":"locality"
},
  "geometry": {"coordinates":[24.31916,55.9382],"type":"Point"}
}