{
  "type": "Feature",
  "properties": {
    "gn:admin1_code":"64",
    "gn:admin2_code":"43.0",
    "gn:asciiname":"Mozureliai",
    "gn:country_code":"LT",
    "gn:dem":155,
    "gn:feature_class":"P",
    "gn:feature_code":"PPL",
    "gn:name":"Moz\u016br\u0117liai",
    "gn:population":0,
    "gn:timezone":"Europe/Vilnius",
    "iso:country":"LT",
    "name:lit_x_preferred":[
        "Moz\u016br\u0117liai"
    ],
    "wof:name":"Mozureliai",
    "wof:placetype":"locality"
},
  "geometry": {"coordinates":[26.07055,55.73402],"type":"Point"}
}