{
  "type": "Feature",
  "properties": {
    "gn:admin1_code":"64",
    "gn:admin2_code":"62.0",
    "gn:asciiname":"Alantele",
    "gn:country_code":"LT",
    "gn:dem":143,
    "gn:feature_class":"P",
    "gn:feature_code":"PPL",
    "gn:name":"Alant\u0117l\u0117",
    "gn:population":0,
    "gn:timezone":"Europe/Vilnius",
    "iso:country":"LT",
    "name:lit_x_preferred":[
        "Alant\u0117l\u0117"
    ],
    "wof:name":"Alantele",
    "wof:placetype":"locality"
},
  "geometry": {"coordinates":[25.2884,55.28678000000001],"type":"Point"}
}