{
  "type": "Feature",
  "properties": {
    "gn:admin1_code":"65",
    "gn:admin2_code":"13.0",
    "gn:asciiname":"Bielazariskes",
    "gn:country_code":"LT",
    "gn:dem":234,
    "gn:feature_class":"P",
    "gn:feature_code":"PPL",
    "gn:name":"Bielazari\u0161k\u0117s",
    "gn:population":0,
    "gn:timezone":"Europe/Vilnius",
    "iso:country":"LT",
    "name:lit_x_preferred":[
        "Bielazari\u0161k\u0117s"
    ],
    "wof:name":"Bielazariskes",
    "wof:placetype":"locality"
},
  "geometry": {"coordinates":[25.58206,54.48449],"type":"Point"}
}