{
  "type": "Feature",
  "properties": {
    "gn:country":"LT",
    "gn:fcode":"PPL",
    "gn:population":2051,
    "iso:country":"LT",
    "name:ara_x_preferred":[
        "\u0625\u064a\u062c\u0631\u0644\u064a\u0633"
    ],
    "name:bel_x_preferred":[
        "\u0413\u043e\u0440\u0430\u0434 \u042d\u0436\u0430\u0440\u044d\u043b\u0456\u0441"
    ],
    "name:bel_x_variant":[
        "\u042d\u0436\u0430\u0440\u044d\u043b\u0456\u0441"
    ],
    "name:cat_x_preferred":[
        "E\u017eer\u0117lis"
    ],
    "name:ceb_x_preferred":[
        "E\u017eer\u0117lis"
    ],
    "name:eng_x_preferred":[
        "E\u017eer\u0117lis"
    ],
    "name:est_x_preferred":[
        "E\u017eer\u0117lis"
    ],
    "name:fas_x_preferred":[
        "\u0627\u0698\u0631\u0644\u06cc\u0633"
    ],
    "name:fin_x_preferred":[
        "E\u017eer\u0117lis"
    ],
    "name:fra_x_preferred":[
        "E\u017eer\u0117lis"
    ],
    "name:hsb_x_preferred":[
        "E\u017eer\u0117lis"
    ],
    "name:ind_x_preferred":[
        "E\u017eer\u0117lis"
    ],
    "name:ita_x_preferred":[
        "E\u017eer\u0117lis"
    ],
    "name:lav_x_preferred":[
        "E\u017eer\u0113le"
    ],
    "name:lit_x_preferred":[
        "E\u017eer\u0117lis"
    ],
    "name:nld_x_preferred":[
        "E\u017eer\u0117lis"
    ],
    "name:pms_x_preferred":[
        "E\u017eer\u0117lis"
    ],
    "name:pol_x_preferred":[
        "A\u017carele"
    ],
    "name:rus_x_preferred":[
        "\u042d\u0436\u0435\u0440\u0435\u043b\u0438\u0441"
    ],
    "name:sgs_x_preferred":[
        "E\u017eerielis"
    ],
    "name:swe_x_preferred":[
        "E\u017eer\u0117lis"
    ],
    "name:tat_x_preferred":[
        "\u042d\u0497\u0435\u0440\u0435\u043b\u0438\u0441"
    ],
    "name:und_x_variant":[
        "Ezherelis"
    ],
    "name:vol_x_preferred":[
        "E\u017eer\u0117lis"
    ],
    "name:zho_x_preferred":[
        "\u57c3\u71b1\u96f7\u5229\u65af"
    ],
    "qs_pg:aaroncc":"LT",
    "qs_pg:gn_country":"LT",
    "qs_pg:gn_fcode":"PPL",
    "qs_pg:gn_pop":2051,
    "qs_pg:name":"E\u017eer\u0117lis",
    "qs_pg:name_adm0":"Lietuva",
    "qs_pg:name_adm1":"Kauno Apskritis",
    "qs_pg:photos_9k":1,
    "qs_pg:photos_9r":1,
    "qs_pg:photos_all":3,
    "qs_pg:photos_sr":0,
    "qs_pg:pop_sr":4,
    "qs_pg:qs_pg_placetype":"locality",
    "qs_pg:qs_pg_placetype_gp":"Town",
    "qs_pg:woe_adm0":23424875,
    "woe:adm0_id":23424875,
    "woe:name_adm0":"Lietuva",
    "woe:name_adm1":"Kauno Apskritis",
    "woe:placetype":"Town",
    "wof:name":"E\u017eer\u0117lis",
    "wof:placetype":"locality",
    "wof:population":2051
},
  "geometry": {"coordinates":[23.61667,54.88333],"type":"Point"}
}