{
  "type": "Feature",
  "properties": {
    "gn:admin1_code":"58.0",
    "gn:admin2_code":"56.0",
    "gn:asciiname":"Ankstakiai",
    "gn:country_code":"LT",
    "gn:dem":20,
    "gn:feature_class":"P",
    "gn:feature_code":"PPL",
    "gn:name":"Ank\u0161takiai",
    "gn:population":0,
    "gn:timezone":"Europe/Vilnius",
    "iso:country":"LT",
    "name:und_x_variant":[
        "Ankshtakey",
        "Ank\u0161takiai"
    ],
    "wof:name":"Ankstakiai",
    "wof:placetype":"locality"
},
  "geometry": {"coordinates":[21.21864,55.92749],"type":"Point"}
}