{
  "type": "Feature",
  "properties": {
    "gn:admin1_code":"56",
    "gn:admin2_code":"59.0",
    "gn:asciiname":"Grauzai",
    "gn:country_code":"LT",
    "gn:dem":121,
    "gn:feature_class":"P",
    "gn:feature_code":"PPL",
    "gn:name":"Grau\u017eai",
    "gn:population":0,
    "gn:timezone":"Europe/Vilnius",
    "iso:country":"LT",
    "name:lit_x_preferred":[
        "Grau\u017eai"
    ],
    "wof:name":"Grauzai",
    "wof:placetype":"locality"
},
  "geometry": {"coordinates":[23.73666,54.26771],"type":"Point"}
}