{
  "type": "Feature",
  "properties": {
    "gn:admin1_code":"59",
    "gn:admin2_code":"39.0",
    "gn:asciiname":"Omentiskiai",
    "gn:country_code":"LT",
    "gn:dem":55,
    "gn:feature_class":"P",
    "gn:feature_code":"PPL",
    "gn:name":"Omenti\u0161kiai",
    "gn:population":0,
    "gn:timezone":"Europe/Vilnius",
    "iso:country":"LT",
    "name:lit_x_preferred":[
        "Omenti\u0161kiai"
    ],
    "wof:name":"Omentiskiai",
    "wof:placetype":"locality"
},
  "geometry": {"coordinates":[23.17778,54.68666],"type":"Point"}
}