{
  "type": "Feature",
  "properties": {
    "gn:admin1_code":"57.0",
    "gn:admin2_code":"53.0",
    "gn:asciiname":"Paliepiai",
    "gn:country_code":"LT",
    "gn:dem":44,
    "gn:feature_class":"P",
    "gn:feature_code":"PPL",
    "gn:name":"Paliepiai",
    "gn:population":0,
    "gn:timezone":"Europe/Vilnius",
    "iso:country":"LT",
    "name:ceb_x_preferred":[
        "Paliepiai"
    ],
    "name:fin_x_preferred":[
        "Paliepiai"
    ],
    "name:lit_x_preferred":[
        "Paliepiai"
    ],
    "name:swe_x_preferred":[
        "Paliepiai"
    ],
    "name:und_x_variant":[
        "Polepe",
        "Palepyay",
        "Paliepiai"
    ],
    "wof:name":"Paliepiai",
    "wof:placetype":"locality"
},
  "geometry": {"coordinates":[23.84763,55.1898],"type":"Point"}
}