{
  "type": "Feature",
  "properties": {
    "gn:admin1_code":"61",
    "gn:admin2_code":"29.0",
    "gn:asciiname":"Maniusiai",
    "gn:country_code":"LT",
    "gn:dem":110,
    "gn:feature_class":"P",
    "gn:feature_code":"PPL",
    "gn:name":"Mani\u016b\u0161iai",
    "gn:population":0,
    "gn:timezone":"Europe/Vilnius",
    "iso:country":"LT",
    "name:lit_x_preferred":[
        "Mani\u016b\u0161iai"
    ],
    "wof:name":"Maniusiai",
    "wof:placetype":"locality"
},
  "geometry": {"coordinates":[23.22731,56.04058000000001],"type":"Point"}
}