{
  "type": "Feature",
  "properties": {
    "gn:admin1_code":"57",
    "gn:admin2_code":"49.0",
    "gn:asciiname":"Gliebiskis",
    "gn:country_code":"LT",
    "gn:dem":81,
    "gn:feature_class":"P",
    "gn:feature_code":"PPL",
    "gn:name":"Gliebi\u0161kis",
    "gn:population":0,
    "gn:timezone":"Europe/Vilnius",
    "iso:country":"LT",
    "name:lit_x_preferred":[
        "Gliebi\u0161kis"
    ],
    "wof:name":"Gliebiskis",
    "wof:placetype":"locality"
},
  "geometry": {"coordinates":[24.22145,54.7347],"type":"Point"}
}