{
  "type": "Feature",
  "properties": {
    "gn:admin1_code":"60",
    "gn:admin2_code":"36.0",
    "gn:asciiname":"Kemenai",
    "gn:country_code":"LT",
    "gn:dem":71,
    "gn:feature_class":"P",
    "gn:feature_code":"PPL",
    "gn:name":"Kem\u0117nai",
    "gn:population":0,
    "gn:timezone":"Europe/Vilnius",
    "iso:country":"LT",
    "name:lit_x_preferred":[
        "Kem\u0117nai"
    ],
    "wof:name":"Kemenai",
    "wof:placetype":"locality"
},
  "geometry": {"coordinates":[24.92085,56.08873000000001],"type":"Point"}
}