{
  "type": "Feature",
  "properties": {
    "gn:admin1_code":"64",
    "gn:admin2_code":"34.0",
    "gn:asciiname":"Juodeglynis",
    "gn:country_code":"LT",
    "gn:dem":115,
    "gn:feature_class":"P",
    "gn:feature_code":"PPL",
    "gn:name":"Juodeglynis",
    "gn:population":0,
    "gn:timezone":"Europe/Vilnius",
    "iso:country":"LT",
    "name:lit_x_preferred":[
        "Juodeglynis"
    ],
    "wof:name":"Juodeglynis",
    "wof:placetype":"locality"
},
  "geometry": {"coordinates":[25.2277,55.69499],"type":"Point"}
}