{
  "type": "Feature",
  "properties": {
    "gn:admin1_code":"61",
    "gn:admin2_code":"54.0",
    "gn:asciiname":"Malioriske",
    "gn:country_code":"LT",
    "gn:dem":130,
    "gn:feature_class":"P",
    "gn:feature_code":"PPL",
    "gn:name":"Maliori\u0161k\u0117",
    "gn:population":0,
    "gn:timezone":"Europe/Vilnius",
    "iso:country":"LT",
    "name:lit_x_preferred":[
        "Maliori\u0161k\u0117"
    ],
    "wof:name":"Malioriske",
    "wof:placetype":"locality"
},
  "geometry": {"coordinates":[22.90202,55.64721],"type":"Point"}
}