{
  "type": "Feature",
  "properties": {
    "gn:admin1_code":"56.0",
    "gn:admin2_code":"11.0",
    "gn:asciiname":"Pagile",
    "gn:country_code":"LT",
    "gn:dem":154,
    "gn:feature_class":"P",
    "gn:feature_code":"PPL",
    "gn:name":"Pagil\u0117",
    "gn:population":0,
    "gn:timezone":"Europe/Vilnius",
    "iso:country":"LT",
    "name:lit_x_preferred":[
        "Pagil\u0117"
    ],
    "wof:name":"Pagile",
    "wof:placetype":"locality"
},
  "geometry": {"coordinates":[24.29622,54.38486],"type":"Point"}
}