{
  "type": "Feature",
  "properties": {
    "gn:admin1_code":"59",
    "gn:admin2_code":"18.0",
    "gn:asciiname":"Steponiskes",
    "gn:country_code":"LT",
    "gn:dem":66,
    "gn:feature_class":"P",
    "gn:feature_code":"PPL",
    "gn:name":"Steponi\u0161k\u0117s",
    "gn:population":0,
    "gn:timezone":"Europe/Vilnius",
    "iso:country":"LT",
    "name:lit_x_preferred":[
        "Steponi\u0161k\u0117s"
    ],
    "wof:name":"Steponiskes",
    "wof:placetype":"locality"
},
  "geometry": {"coordinates":[23.39672,54.57134],"type":"Point"}
}