{
  "type": "Feature",
  "properties": {
    "gn:admin1_code":"56.0",
    "gn:admin2_code":"38.0",
    "gn:asciiname":"Degsnes",
    "gn:country_code":"LT",
    "gn:dem":126,
    "gn:feature_class":"P",
    "gn:feature_code":"PPL",
    "gn:name":"Degsn\u0117s",
    "gn:population":0,
    "gn:timezone":"Europe/Vilnius",
    "iso:country":"LT",
    "name:lit_x_preferred":[
        "Degsn\u0117s"
    ],
    "name:pol_x_preferred":[
        "Deksznia"
    ],
    "name:und_x_variant":[
        "Degsn\u0117s"
    ],
    "wof:name":"Degsnes",
    "wof:placetype":"locality"
},
  "geometry": {"coordinates":[24.79639,54.36854],"type":"Point"}
}