{
  "type": "Feature",
  "properties": {
    "gn:admin1_code":"60",
    "gn:admin2_code":"36.0",
    "gn:asciiname":"Vileisiskiai",
    "gn:country_code":"LT",
    "gn:dem":68,
    "gn:feature_class":"P",
    "gn:feature_code":"PPL",
    "gn:name":"Vilei\u0161i\u0161kiai",
    "gn:population":0,
    "gn:timezone":"Europe/Vilnius",
    "iso:country":"LT",
    "name:lit_x_preferred":[
        "Vilei\u0161i\u0161kiai"
    ],
    "wof:name":"Vileisiskiai",
    "wof:placetype":"locality"
},
  "geometry": {"coordinates":[24.88558,56.01645],"type":"Point"}
}