{
  "type": "Feature",
  "properties": {
    "gn:admin1_code":"65",
    "gn:admin2_code":"86.0",
    "gn:asciiname":"Kasciukai",
    "gn:country_code":"LT",
    "gn:dem":173,
    "gn:feature_class":"P",
    "gn:feature_code":"PPL",
    "gn:name":"Kas\u010diukai",
    "gn:population":0,
    "gn:timezone":"Europe/Vilnius",
    "iso:country":"LT",
    "name:lit_x_preferred":[
        "Kas\u010diukai"
    ],
    "wof:name":"Kasciukai",
    "wof:placetype":"locality"
},
  "geometry": {"coordinates":[26.09109,55.07435],"type":"Point"}
}