{
  "type": "Feature",
  "properties": {
    "gn:admin1_code":"59.0",
    "gn:admin2_code":"58.0",
    "gn:asciiname":"Grigaliunai",
    "gn:country_code":"LT",
    "gn:dem":78,
    "gn:feature_class":"P",
    "gn:feature_code":"PPL",
    "gn:name":"Grigali\u016bnai",
    "gn:population":0,
    "gn:timezone":"Europe/Vilnius",
    "iso:country":"LT",
    "name:und_x_variant":[
        "Grigalyuny",
        "Grigali\u016bn\u0173",
        "Grigali\u016bnai"
    ],
    "wof:name":"Grigaliunai",
    "wof:placetype":"locality"
},
  "geometry": {"coordinates":[23.6361,54.70027],"type":"Point"}
}