{
  "type": "Feature",
  "properties": {
    "gn:admin1_code":"58.0",
    "gn:admin2_code":"25.0",
    "gn:asciiname":"Nemirseta",
    "gn:country_code":"LT",
    "gn:dem":6,
    "gn:feature_class":"P",
    "gn:feature_code":"PPL",
    "gn:name":"Nemirseta",
    "gn:population":0,
    "gn:timezone":"Europe/Vilnius",
    "iso:country":"LT",
    "name:deu_x_preferred":[
        "Nimmersatt"
    ],
    "name:deu_x_variant":[
        "Nemirseta"
    ],
    "name:lit_x_preferred":[
        "Nemerzat\u0117"
    ],
    "name:lit_x_variant":[
        "Nemirseta"
    ],
    "name:ron_x_preferred":[
        "Nemirseta"
    ],
    "name:und_x_variant":[
        "N\u0117mer\u017eata",
        "Nemerzhara",
        "Nemer\u017eet\u00e0",
        "Nemirseta",
        "Nimmersatt",
        "Nemerzat\u0117"
    ],
    "wof:name":"Nemirseta",
    "wof:placetype":"locality"
},
  "geometry": {"coordinates":[21.08167000000001,55.87848],"type":"Point"}
}