{
  "type": "Feature",
  "properties": {
    "gn:admin1_code":"63.0",
    "gn:admin2_code":"68.0",
    "gn:asciiname":"Pakutuvenai",
    "gn:country_code":"LT",
    "gn:dem":71,
    "gn:feature_class":"P",
    "gn:feature_code":"PPL",
    "gn:name":"Pakutuv\u0117nai",
    "gn:population":0,
    "gn:timezone":"Europe/Vilnius",
    "iso:country":"LT",
    "name:und_x_variant":[
        "Pakutuven\u0173",
        "Pakutavenay",
        "Pakutav\u0117n\u0173",
        "Pakutuv\u0117nai"
    ],
    "wof:name":"Pakutuvenai",
    "wof:placetype":"locality"
},
  "geometry": {"coordinates":[21.66868,55.91446],"type":"Point"}
}