{
  "type": "Feature",
  "properties": {
    "gn:admin1_code":"62.0",
    "gn:admin2_code":"94.0",
    "gn:asciiname":"Vertimai",
    "gn:country_code":"LT",
    "gn:dem":33,
    "gn:feature_class":"P",
    "gn:feature_code":"PPL",
    "gn:name":"Vertimai",
    "gn:population":0,
    "gn:timezone":"Europe/Vilnius",
    "iso:country":"LT",
    "name:und_x_variant":[
        "Vertimay",
        "Vertim\u0173",
        "Vertymy",
        "Vertimai"
    ],
    "wof:name":"Vertimai",
    "wof:placetype":"locality"
},
  "geometry": {"coordinates":[22.64401,55.17118000000001],"type":"Point"}
}