{
  "type": "Feature",
  "properties": {
    "gn:admin1_code":"61",
    "gn:admin2_code":"32.0",
    "gn:asciiname":"Paeglesiai",
    "gn:country_code":"LT",
    "gn:dem":75,
    "gn:feature_class":"P",
    "gn:feature_code":"PPL",
    "gn:name":"Paeglesiai",
    "gn:population":0,
    "gn:timezone":"Europe/Vilnius",
    "iso:country":"LT",
    "name:lit_x_preferred":[
        "Paeglesiai"
    ],
    "wof:name":"Paeglesiai",
    "wof:placetype":"locality"
},
  "geometry": {"coordinates":[22.72115,56.1876],"type":"Point"}
}