{
  "type": "Feature",
  "properties": {
    "gn:admin1_code":"57.0",
    "gn:admin2_code":"69.0",
    "gn:asciiname":"Ciudiskiai",
    "gn:country_code":"LT",
    "gn:dem":78,
    "gn:feature_class":"P",
    "gn:feature_code":"PPL",
    "gn:name":"\u010ciudi\u0161kiai",
    "gn:population":0,
    "gn:timezone":"Europe/Vilnius",
    "iso:country":"LT",
    "name:lit_x_preferred":[
        "\u010ciudi\u0161kiai"
    ],
    "wof:name":"Ciudiskiai",
    "wof:placetype":"locality"
},
  "geometry": {"coordinates":[23.9047,54.69319],"type":"Point"}
}