{
  "type": "Feature",
  "properties": {
    "gn:admin1_code":"56.0",
    "gn:admin2_code":"11.0",
    "gn:asciiname":"Verebiejai",
    "gn:country_code":"LT",
    "gn:dem":93,
    "gn:feature_class":"P",
    "gn:feature_code":"PPL",
    "gn:name":"Verebiejai",
    "gn:population":0,
    "gn:timezone":"Europe/Vilnius",
    "iso:country":"LT",
    "name:eng_x_preferred":[
        "Verebiejai"
    ],
    "name:rus_x_preferred":[
        "\u0412\u0435\u0440\u0435\u0431\u0430\u044f\u0439"
    ],
    "wof:name":"Verebiejai",
    "wof:placetype":"locality"
},
  "geometry": {"coordinates":[23.70015,54.4574],"type":"Point"}
}