{
  "type": "Feature",
  "properties": {
    "gn:admin1_code":"64",
    "gn:admin2_code":"62.0",
    "gn:asciiname":"Gerciukai",
    "gn:country_code":"LT",
    "gn:dem":134,
    "gn:feature_class":"P",
    "gn:feature_code":"PPL",
    "gn:name":"Ger\u010diukai",
    "gn:population":0,
    "gn:timezone":"Europe/Vilnius",
    "iso:country":"LT",
    "name:lit_x_preferred":[
        "Ger\u010diukai"
    ],
    "wof:name":"Gerciukai",
    "wof:placetype":"locality"
},
  "geometry": {"coordinates":[25.18334,55.1133],"type":"Point"}
}