{
  "type": "Feature",
  "properties": {
    "gn:admin1_code":"59.0",
    "gn:admin2_code":"18.0",
    "gn:asciiname":"Simuliai",
    "gn:country_code":"LT",
    "gn:dem":86,
    "gn:feature_class":"P",
    "gn:feature_code":"PPL",
    "gn:name":"\u0160imuliai",
    "gn:population":0,
    "gn:timezone":"Europe/Vilnius",
    "iso:country":"LT",
    "name:lit_x_preferred":[
        "\u0160imuliai"
    ],
    "wof:name":"Simuliai",
    "wof:placetype":"locality"
},
  "geometry": {"coordinates":[23.39303,54.46485],"type":"Point"}
}