{
  "type": "Feature",
  "properties": {
    "gn:admin1_code":"64",
    "gn:admin2_code":"34.0",
    "gn:asciiname":"Krivinskai",
    "gn:country_code":"LT",
    "gn:dem":104,
    "gn:feature_class":"P",
    "gn:feature_code":"PPL",
    "gn:name":"Krivinskai",
    "gn:population":0,
    "gn:timezone":"Europe/Vilnius",
    "iso:country":"LT",
    "name:lit_x_preferred":[
        "Krivinskai"
    ],
    "wof:name":"Krivinskai",
    "wof:placetype":"locality"
},
  "geometry": {"coordinates":[25.04689,55.55518000000001],"type":"Point"}
}