{
  "type": "Feature",
  "properties": {
    "gn:admin1_code":"59",
    "gn:admin2_code":"48.0",
    "gn:asciiname":"Naujienele I",
    "gn:country_code":"LT",
    "gn:dem":120,
    "gn:feature_class":"P",
    "gn:feature_code":"PPL",
    "gn:name":"Naujien\u0117l\u0117 I",
    "gn:population":0,
    "gn:timezone":"Europe/Vilnius",
    "iso:country":"LT",
    "name:lit_x_preferred":[
        "Naujien\u0117l\u0117 I"
    ],
    "wof:name":"Naujienele I",
    "wof:placetype":"locality"
},
  "geometry": {"coordinates":[23.14137,54.46934],"type":"Point"}
}