{
  "type": "Feature",
  "properties": {
    "gn:admin1_code":"57.0",
    "gn:admin2_code":"53.0",
    "gn:asciiname":"Jaksiai",
    "gn:country_code":"LT",
    "gn:dem":76,
    "gn:feature_class":"P",
    "gn:feature_code":"PPL",
    "gn:name":"Jak\u0161iai",
    "gn:population":0,
    "gn:timezone":"Europe/Vilnius",
    "iso:country":"LT",
    "name:und_x_variant":[
        "Yakshi",
        "Yakshay",
        "Yakshyay",
        "Jak\u0161iai"
    ],
    "wof:name":"Jaksiai",
    "wof:placetype":"locality"
},
  "geometry": {"coordinates":[23.68404,55.23915],"type":"Point"}
}