{
  "type": "Feature",
  "properties": {
    "gn:admin1_code":"59",
    "gn:admin2_code":"18.0",
    "gn:asciiname":"Skesbaliai",
    "gn:country_code":"LT",
    "gn:dem":101,
    "gn:feature_class":"P",
    "gn:feature_code":"PPL",
    "gn:name":"Skesbaliai",
    "gn:population":0,
    "gn:timezone":"Europe/Vilnius",
    "iso:country":"LT",
    "name:lit_x_preferred":[
        "Skesbaliai"
    ],
    "wof:name":"Skesbaliai",
    "wof:placetype":"locality"
},
  "geometry": {"coordinates":[23.69133,54.53751],"type":"Point"}
}