{
  "type": "Feature",
  "properties": {
    "gn:admin1_code":"61",
    "gn:admin2_code":"29.0",
    "gn:asciiname":"Vaisnoriai",
    "gn:country_code":"LT",
    "gn:dem":106,
    "gn:feature_class":"P",
    "gn:feature_code":"PPL",
    "gn:name":"Vai\u0161noriai",
    "gn:population":0,
    "gn:timezone":"Europe/Vilnius",
    "iso:country":"LT",
    "name:lit_x_preferred":[
        "Vai\u0161noriai"
    ],
    "wof:name":"Vaisnoriai",
    "wof:placetype":"locality"
},
  "geometry": {"coordinates":[23.12023,55.94761],"type":"Point"}
}