{
  "type": "Feature",
  "properties": {
    "gn:admin1_code":"65",
    "gn:admin2_code":"13.0",
    "gn:asciiname":"Pupiniskes",
    "gn:country_code":"LT",
    "gn:dem":156,
    "gn:feature_class":"P",
    "gn:feature_code":"PPL",
    "gn:name":"Pupini\u0161k\u0117s",
    "gn:population":0,
    "gn:timezone":"Europe/Vilnius",
    "iso:country":"LT",
    "name:lit_x_preferred":[
        "Pupini\u0161k\u0117s"
    ],
    "wof:name":"Pupiniskes",
    "wof:placetype":"locality"
},
  "geometry": {"coordinates":[25.44484,54.91874],"type":"Point"}
}