{
  "type": "Feature",
  "properties": {
    "gn:admin1_code":"57",
    "gn:admin2_code":"12.0",
    "gn:asciiname":"Paverkniai",
    "gn:country_code":"LT",
    "gn:dem":59,
    "gn:feature_class":"P",
    "gn:feature_code":"PPL",
    "gn:name":"Paverkniai",
    "gn:population":0,
    "gn:timezone":"Europe/Vilnius",
    "iso:country":"LT",
    "name:lit_x_preferred":[
        "Paverkniai"
    ],
    "wof:name":"Paverkniai",
    "wof:placetype":"locality"
},
  "geometry": {"coordinates":[24.09032,54.59703],"type":"Point"}
}