{
  "type": "Feature",
  "properties": {
    "gn:admin1_code":"65",
    "gn:admin2_code":"89.0",
    "gn:asciiname":"Valiukiskiai",
    "gn:country_code":"LT",
    "gn:dem":58,
    "gn:feature_class":"P",
    "gn:feature_code":"PPL",
    "gn:name":"Valiuki\u0161kiai",
    "gn:population":0,
    "gn:timezone":"Europe/Vilnius",
    "iso:country":"LT",
    "name:lit_x_preferred":[
        "Valiuki\u0161kiai"
    ],
    "wof:name":"Valiukiskiai",
    "wof:placetype":"locality"
},
  "geometry": {"coordinates":[24.81098,54.89798],"type":"Point"}
}