{
  "type": "Feature",
  "properties": {
    "gn:admin1_code":"63.0",
    "gn:admin2_code":"78.0",
    "gn:asciiname":"Godeliai",
    "gn:country_code":"LT",
    "gn:dem":168,
    "gn:feature_class":"P",
    "gn:feature_code":"PPL",
    "gn:name":"Godeliai",
    "gn:population":0,
    "gn:timezone":"Europe/Vilnius",
    "iso:country":"LT",
    "name:und_x_variant":[
        "Gudelyay",
        "Godeliai"
    ],
    "wof:name":"Godeliai",
    "wof:placetype":"locality"
},
  "geometry": {"coordinates":[22.37455,55.70895],"type":"Point"}
}