{
  "type": "Feature",
  "properties": {
    "gn:admin1_code":"61.0",
    "gn:admin2_code":"47.0",
    "gn:asciiname":"Darginiai",
    "gn:country_code":"LT",
    "gn:dem":50,
    "gn:feature_class":"P",
    "gn:feature_code":"PPL",
    "gn:name":"Darginiai",
    "gn:population":0,
    "gn:timezone":"Europe/Vilnius",
    "iso:country":"LT",
    "name:und_x_variant":[
        "Darginyay",
        "Dargyany",
        "Darginiai"
    ],
    "wof:name":"Darginiai",
    "wof:placetype":"locality"
},
  "geometry": {"coordinates":[23.8252,56.2427],"type":"Point"}
}