{
  "type": "Feature",
  "properties": {
    "gn:admin1_code":"58",
    "gn:admin2_code":"21.0",
    "gn:asciiname":"Sernai",
    "gn:country_code":"LT",
    "gn:dem":9,
    "gn:feature_class":"P",
    "gn:feature_code":"PPL",
    "gn:name":"\u0160ernai",
    "gn:population":0,
    "gn:timezone":"Europe/Vilnius",
    "iso:country":"LT",
    "name:lit_x_preferred":[
        "\u0160ernai"
    ],
    "wof:name":"Sernai",
    "wof:placetype":"locality"
},
  "geometry": {"coordinates":[21.31132,55.63892],"type":"Point"}
}