{
  "type": "Feature",
  "properties": {
    "gn:admin1_code":"57.0",
    "gn:admin2_code":"46.0",
    "gn:asciiname":"Narauninkiskiai",
    "gn:country_code":"LT",
    "gn:dem":84,
    "gn:feature_class":"P",
    "gn:feature_code":"PPL",
    "gn:name":"Narauninki\u0161kiai",
    "gn:population":0,
    "gn:timezone":"Europe/Vilnius",
    "iso:country":"LT",
    "name:und_x_variant":[
        "Narauninkishkyay",
        "Narauninki\u0161kiai"
    ],
    "wof:name":"Narauninkiskiai",
    "wof:placetype":"locality"
},
  "geometry": {"coordinates":[24.29888,55.16983000000001],"type":"Point"}
}