{
  "type": "Feature",
  "properties": {
    "gn:admin1_code":"61.0",
    "gn:admin2_code":"65.0",
    "gn:asciiname":"Jasaiciai",
    "gn:country_code":"LT",
    "gn:dem":83,
    "gn:feature_class":"P",
    "gn:feature_code":"PPL",
    "gn:name":"Jasai\u010diai",
    "gn:population":0,
    "gn:timezone":"Europe/Vilnius",
    "iso:country":"LT",
    "name:und_x_variant":[
        "Yasaychyay",
        "Jasai\u010diai"
    ],
    "wof:name":"Jasaiciai",
    "wof:placetype":"locality"
},
  "geometry": {"coordinates":[23.75148,55.92339000000001],"type":"Point"}
}