{
  "type": "Feature",
  "properties": {
    "gn:admin1_code":"60",
    "gn:admin2_code":"27.0",
    "gn:asciiname":"Kutronys",
    "gn:country_code":"LT",
    "gn:dem":71,
    "gn:feature_class":"P",
    "gn:feature_code":"PPL",
    "gn:name":"Kutronys",
    "gn:population":0,
    "gn:timezone":"Europe/Vilnius",
    "iso:country":"LT",
    "name:lit_x_preferred":[
        "Kutronys"
    ],
    "wof:name":"Kutronys",
    "wof:placetype":"locality"
},
  "geometry": {"coordinates":[24.46616,55.5096],"type":"Point"}
}