{
  "type": "Feature",
  "properties": {
    "gn:admin1_code":"65",
    "gn:admin2_code":"86.0",
    "gn:asciiname":"Pasvente",
    "gn:country_code":"LT",
    "gn:dem":180,
    "gn:feature_class":"P",
    "gn:feature_code":"PPL",
    "gn:name":"Pa\u0161vent\u0117",
    "gn:population":0,
    "gn:timezone":"Europe/Vilnius",
    "iso:country":"LT",
    "name:lit_x_preferred":[
        "Pa\u0161vent\u0117"
    ],
    "wof:name":"Pasvente",
    "wof:placetype":"locality"
},
  "geometry": {"coordinates":[26.34354,55.21833],"type":"Point"}
}