{
  "type": "Feature",
  "properties": {
    "gn:admin1_code":"65.0",
    "gn:admin2_code":"13.0",
    "gn:asciiname":"Nemencinele",
    "gn:country_code":"LT",
    "gn:dem":158,
    "gn:feature_class":"P",
    "gn:feature_code":"PPL",
    "gn:name":"Nemen\u010din\u0117l\u0117",
    "gn:population":0,
    "gn:timezone":"Europe/Vilnius",
    "iso:country":"LT",
    "name:lit_x_preferred":[
        "Nemen\u010din\u0117l\u0117"
    ],
    "name:lit_x_variant":[
        "Nemen\u010dinel\u0117"
    ],
    "wof:name":"Nemencinele",
    "wof:placetype":"locality"
},
  "geometry": {"coordinates":[25.28946,54.85895],"type":"Point"}
}