{
  "type": "Feature",
  "properties": {
    "gn:admin1_code":"60",
    "gn:admin2_code":"73.0",
    "gn:asciiname":"Petresiunai",
    "gn:country_code":"LT",
    "gn:dem":115,
    "gn:feature_class":"P",
    "gn:feature_code":"PPL",
    "gn:name":"Petre\u0161i\u016bnai",
    "gn:population":0,
    "gn:timezone":"Europe/Vilnius",
    "iso:country":"LT",
    "name:lit_x_preferred":[
        "Petre\u0161i\u016bnai"
    ],
    "wof:name":"Petresiunai",
    "wof:placetype":"locality"
},
  "geometry": {"coordinates":[25.71639,55.84018],"type":"Point"}
}