{
  "type": "Feature",
  "properties": {
    "gn:admin1_code":"56.0",
    "gn:admin2_code":"38.0",
    "gn:asciiname":"Barciai",
    "gn:country_code":"LT",
    "gn:dem":160,
    "gn:feature_class":"P",
    "gn:feature_code":"PPL",
    "gn:name":"Bar\u010diai",
    "gn:population":0,
    "gn:timezone":"Europe/Vilnius",
    "iso:country":"LT",
    "name:eng_x_preferred":[
        "Bar\u010diai"
    ],
    "name:rus_x_preferred":[
        "\u0411\u0430\u0440\u0447\u044f\u0439"
    ],
    "name:und_x_variant":[
        "Bortele",
        "Barchyay",
        "Barteliai",
        "Bartelyay",
        "Borteli"
    ],
    "wof:name":"Barciai",
    "wof:placetype":"locality"
},
  "geometry": {"coordinates":[24.66909,54.18802],"type":"Point"}
}