{
  "type": "Feature",
  "properties": {
    "gn:admin1_code":"64",
    "gn:admin2_code":"62.0",
    "gn:asciiname":"Smilgiai",
    "gn:country_code":"LT",
    "gn:dem":159,
    "gn:feature_class":"P",
    "gn:feature_code":"PPL",
    "gn:name":"Smilgiai",
    "gn:population":0,
    "gn:timezone":"Europe/Vilnius",
    "iso:country":"LT",
    "name:ceb_x_preferred":[
        "Smilgiai"
    ],
    "name:deu_x_preferred":[
        "Smilgiai"
    ],
    "name:est_x_preferred":[
        "Smilgiai"
    ],
    "name:lit_x_preferred":[
        "Smilgiai"
    ],
    "name:nld_x_preferred":[
        "Smilgiai"
    ],
    "name:pol_x_preferred":[
        "Smilgie"
    ],
    "name:swe_x_preferred":[
        "Smilgiai"
    ],
    "wof:name":"Smilgiai",
    "wof:placetype":"locality"
},
  "geometry": {"coordinates":[25.37972,55.25828000000001],"type":"Point"}
}