{
  "type": "Feature",
  "properties": {
    "gn:admin1_code":"57.0",
    "gn:admin2_code":"46.0",
    "gn:asciiname":"Trakai",
    "gn:country_code":"LT",
    "gn:dem":71,
    "gn:feature_class":"P",
    "gn:feature_code":"PPL",
    "gn:name":"Trakai",
    "gn:population":0,
    "gn:timezone":"Europe/Vilnius",
    "iso:country":"LT",
    "name:und_x_variant":[
        "Trakay",
        "Trakai"
    ],
    "wof:name":"Trakai",
    "wof:placetype":"locality"
},
  "geometry": {"coordinates":[24.17577,55.1161],"type":"Point"}
}