{
  "type": "Feature",
  "properties": {
    "gn:admin1_code":"56.0",
    "gn:admin2_code":"15.0",
    "gn:asciiname":"Neravai",
    "gn:country_code":"LT",
    "gn:dem":109,
    "gn:feature_class":"P",
    "gn:feature_code":"PPL",
    "gn:name":"Neravai",
    "gn:population":0,
    "gn:timezone":"Europe/Vilnius",
    "iso:country":"LT",
    "name:eng_x_preferred":[
        "Neravai"
    ],
    "name:rus_x_preferred":[
        "\u041d\u0430\u0440\u0430\u0432\u0430\u0439"
    ],
    "name:und_x_variant":[
        "Naravai"
    ],
    "wof:name":"Neravai",
    "wof:placetype":"locality"
},
  "geometry": {"coordinates":[24.02998,54.0383],"type":"Point"}
}