{
  "type": "Feature",
  "properties": {
    "gn:admin1_code":"57",
    "gn:admin2_code":"49.0",
    "gn:asciiname":"Uztakai",
    "gn:country_code":"LT",
    "gn:dem":82,
    "gn:feature_class":"P",
    "gn:feature_code":"PPL",
    "gn:name":"U\u017etakai",
    "gn:population":0,
    "gn:timezone":"Europe/Vilnius",
    "iso:country":"LT",
    "name:lit_x_preferred":[
        "U\u017etakai"
    ],
    "wof:name":"Uztakai",
    "wof:placetype":"locality"
},
  "geometry": {"coordinates":[24.22539,54.88974],"type":"Point"}
}