{
  "type": "Feature",
  "properties": {
    "gn:admin1_code":"56",
    "gn:admin2_code":"38.0",
    "gn:asciiname":"Dubaklonis",
    "gn:country_code":"LT",
    "gn:dem":134,
    "gn:feature_class":"P",
    "gn:feature_code":"PPL",
    "gn:name":"Dubaklonis",
    "gn:population":0,
    "gn:timezone":"Europe/Vilnius",
    "iso:country":"LT",
    "name:lit_x_preferred":[
        "Dubaklonis"
    ],
    "wof:name":"Dubaklonis",
    "wof:placetype":"locality"
},
  "geometry": {"coordinates":[24.36311,54.23736],"type":"Point"}
}