{
  "type": "Feature",
  "properties": {
    "gn:admin1_code":"65.0",
    "gn:admin2_code":"86.0",
    "gn:asciiname":"Stanislavavas",
    "gn:country_code":"LT",
    "gn:dem":218,
    "gn:feature_class":"P",
    "gn:feature_code":"PPL",
    "gn:name":"Stanislavavas",
    "gn:population":0,
    "gn:timezone":"Europe/Vilnius",
    "iso:country":"LT",
    "name:lit_x_preferred":[
        "Stanislavavas"
    ],
    "wof:name":"Stanislavavas",
    "wof:placetype":"locality"
},
  "geometry": {"coordinates":[26.27554,55.18861],"type":"Point"}
}