{
  "type": "Feature",
  "properties": {
    "gn:admin1_code":"58",
    "gn:admin2_code":"88.0",
    "gn:asciiname":"Kalininkai",
    "gn:country_code":"LT",
    "gn:dem":50,
    "gn:feature_class":"P",
    "gn:feature_code":"PPL",
    "gn:name":"Kalininkai",
    "gn:population":0,
    "gn:timezone":"Europe/Vilnius",
    "iso:country":"LT",
    "name:lit_x_preferred":[
        "Kalininkai"
    ],
    "wof:name":"Kalininkai",
    "wof:placetype":"locality"
},
  "geometry": {"coordinates":[21.78028,55.32435],"type":"Point"}
}