{
  "type": "Feature",
  "properties": {
    "gn:admin1_code":"63",
    "gn:admin2_code":"78.0",
    "gn:asciiname":"Padvarninkai",
    "gn:country_code":"LT",
    "gn:dem":121,
    "gn:feature_class":"P",
    "gn:feature_code":"PPL",
    "gn:name":"Padvarninkai",
    "gn:population":0,
    "gn:timezone":"Europe/Vilnius",
    "iso:country":"LT",
    "name:lit_x_preferred":[
        "Padvarninkai"
    ],
    "wof:name":"Padvarninkai",
    "wof:placetype":"locality"
},
  "geometry": {"coordinates":[22.57053,55.93772],"type":"Point"}
}