{
  "type": "Feature",
  "properties": {
    "gn:admin1_code":"64",
    "gn:admin2_code":"43.0",
    "gn:asciiname":"Smalveles",
    "gn:country_code":"LT",
    "gn:dem":159,
    "gn:feature_class":"P",
    "gn:feature_code":"PPL",
    "gn:name":"Smalvel\u0117s",
    "gn:population":0,
    "gn:timezone":"Europe/Vilnius",
    "iso:country":"LT",
    "name:lit_x_preferred":[
        "Smalvel\u0117s"
    ],
    "wof:name":"Smalveles",
    "wof:placetype":"locality"
},
  "geometry": {"coordinates":[26.42231,55.68257],"type":"Point"}
}