{
  "type": "Feature",
  "properties": {
    "gn:admin1_code":"60",
    "gn:admin2_code":"57.0",
    "gn:asciiname":"Vasalava",
    "gn:country_code":"LT",
    "gn:dem":89,
    "gn:feature_class":"P",
    "gn:feature_code":"PPL",
    "gn:name":"Vasalava",
    "gn:population":0,
    "gn:timezone":"Europe/Vilnius",
    "iso:country":"LT",
    "name:lit_x_preferred":[
        "Vasalava"
    ],
    "wof:name":"Vasalava",
    "wof:placetype":"locality"
},
  "geometry": {"coordinates":[24.87307,55.80741],"type":"Point"}
}