{
  "type": "Feature",
  "properties": {
    "gn:admin1_code":"0.0",
    "gn:asciiname":"Zubiskiai",
    "gn:cc2":"LT",
    "gn:country_code":"LT",
    "gn:dem":47,
    "gn:feature_class":"P",
    "gn:feature_code":"PPL",
    "gn:name":"Zubi\u0161kiai",
    "gn:population":0,
    "gn:timezone":"Europe/Vilnius",
    "iso:country":"LT",
    "name:und_x_variant":[
        "Zubi\u0161ki\u0173",
        "Zubishkyay",
        "Zubi\u0161kiai"
    ],
    "wof:name":"Zubiskiai",
    "wof:placetype":"locality"
},
  "geometry": {"coordinates":[24.26667,55.66667],"type":"Point"}
}