{
  "type": "Feature",
  "properties": {
    "gn:admin1_code":"60",
    "gn:admin2_code":"36.0",
    "gn:asciiname":"Jaunuciai",
    "gn:country_code":"LT",
    "gn:dem":65,
    "gn:feature_class":"P",
    "gn:feature_code":"PPL",
    "gn:name":"Jaunu\u010diai",
    "gn:population":0,
    "gn:timezone":"Europe/Vilnius",
    "iso:country":"LT",
    "name:lit_x_preferred":[
        "Jaunu\u010diai"
    ],
    "wof:name":"Jaunuciai",
    "wof:placetype":"locality"
},
  "geometry": {"coordinates":[24.86269,56.04043000000001],"type":"Point"}
}