{
  "type": "Feature",
  "properties": {
    "gn:admin1_code":"64.0",
    "gn:admin2_code":"82.0",
    "gn:asciiname":"Dusyniai",
    "gn:country_code":"LT",
    "gn:dem":130,
    "gn:feature_class":"P",
    "gn:feature_code":"PPL",
    "gn:name":"Dusyniai",
    "gn:population":0,
    "gn:timezone":"Europe/Vilnius",
    "iso:country":"LT",
    "name:lit_x_preferred":[
        "Dusyniai"
    ],
    "name:und_x_variant":[
        "Dusini\u0173",
        "Dusini",
        "Dusinyay",
        "Dusiniai"
    ],
    "wof:name":"Dusyniai",
    "wof:placetype":"locality"
},
  "geometry": {"coordinates":[25.45303,55.56335],"type":"Point"}
}