{
  "type": "Feature",
  "properties": {
    "gn:admin1_code":"57.0",
    "gn:admin2_code":"53.0",
    "gn:asciiname":"Dilgiai",
    "gn:country_code":"LT",
    "gn:dem":46,
    "gn:feature_class":"P",
    "gn:feature_code":"PPL",
    "gn:name":"Dilgiai",
    "gn:population":0,
    "gn:timezone":"Europe/Vilnius",
    "iso:country":"LT",
    "name:und_x_variant":[
        "Dylgi",
        "Dilgiai"
    ],
    "wof:name":"Dilgiai",
    "wof:placetype":"locality"
},
  "geometry": {"coordinates":[24.05474,55.29232],"type":"Point"}
}