{
  "type": "Feature",
  "properties": {
    "gn:admin1_code":"59.0",
    "gn:admin2_code":"84.0",
    "gn:asciiname":"Zalvederiai",
    "gn:country_code":"LT",
    "gn:dem":51,
    "gn:feature_class":"P",
    "gn:feature_code":"PPL",
    "gn:name":"\u017dalv\u0117deriai",
    "gn:population":0,
    "gn:timezone":"Europe/Vilnius",
    "iso:country":"LT",
    "name:lit_x_preferred":[
        "\u017dalv\u0117deriai"
    ],
    "name:und_x_variant":[
        "\u017dalia\u0161arkiai"
    ],
    "wof:name":"Zalvederiai",
    "wof:placetype":"locality"
},
  "geometry": {"coordinates":[23.09772,54.79435],"type":"Point"}
}