{
  "type": "Feature",
  "properties": {
    "gn:admin1_code":"56",
    "gn:admin2_code":"59.0",
    "gn:asciiname":"Bevirsiai",
    "gn:country_code":"LT",
    "gn:dem":170,
    "gn:feature_class":"P",
    "gn:feature_code":"PPL",
    "gn:name":"Bevir\u0161iai",
    "gn:population":0,
    "gn:timezone":"Europe/Vilnius",
    "iso:country":"LT",
    "name:lit_x_preferred":[
        "Bevir\u0161iai"
    ],
    "wof:name":"Bevirsiai",
    "wof:placetype":"locality"
},
  "geometry": {"coordinates":[23.44449,54.27276],"type":"Point"}
}