{
  "type": "Feature",
  "properties": {
    "gn:admin1_code":"64",
    "gn:admin2_code":"45.0",
    "gn:asciiname":"Sabaliske",
    "gn:country_code":"LT",
    "gn:dem":189,
    "gn:feature_class":"P",
    "gn:feature_code":"PPL",
    "gn:name":"Sabali\u0161k\u0117",
    "gn:population":0,
    "gn:timezone":"Europe/Vilnius",
    "iso:country":"LT",
    "name:lit_x_preferred":[
        "Sabali\u0161k\u0117"
    ],
    "wof:name":"Sabaliske",
    "wof:placetype":"locality"
},
  "geometry": {"coordinates":[26.19231,55.28806],"type":"Point"}
}