{
  "type": "Feature",
  "properties": {
    "gn:admin1_code":"65",
    "gn:admin2_code":"81.0",
    "gn:asciiname":"Naceliskiai II",
    "gn:country_code":"LT",
    "gn:dem":91,
    "gn:feature_class":"P",
    "gn:feature_code":"PPL",
    "gn:name":"Naceli\u0161kiai II",
    "gn:population":0,
    "gn:timezone":"Europe/Vilnius",
    "iso:country":"LT",
    "name:lit_x_preferred":[
        "Naceli\u0161kiai II"
    ],
    "wof:name":"Naceliskiai II",
    "wof:placetype":"locality"
},
  "geometry": {"coordinates":[24.7199,55.18244],"type":"Point"}
}