{
  "type": "Feature",
  "properties": {
    "gn:admin1_code":"57",
    "gn:admin2_code":"49.0",
    "gn:asciiname":"Bartaiciai",
    "gn:country_code":"LT",
    "gn:dem":105,
    "gn:feature_class":"P",
    "gn:feature_code":"PPL",
    "gn:name":"Bartai\u010diai",
    "gn:population":0,
    "gn:timezone":"Europe/Vilnius",
    "iso:country":"LT",
    "name:lit_x_preferred":[
        "Bartai\u010diai"
    ],
    "wof:name":"Bartaiciai",
    "wof:placetype":"locality"
},
  "geometry": {"coordinates":[24.49309,54.86633000000001],"type":"Point"}
}