{
  "type": "Feature",
  "properties": {
    "gn:admin1_code":"65",
    "gn:admin2_code":"89.0",
    "gn:asciiname":"Markunai",
    "gn:country_code":"LT",
    "gn:dem":100,
    "gn:feature_class":"P",
    "gn:feature_code":"PPL",
    "gn:name":"Mark\u016bnai",
    "gn:population":0,
    "gn:timezone":"Europe/Vilnius",
    "iso:country":"LT",
    "name:lit_x_preferred":[
        "Mark\u016bnai"
    ],
    "wof:name":"Markunai",
    "wof:placetype":"locality"
},
  "geometry": {"coordinates":[24.72105,55.00383000000001],"type":"Point"}
}