{
  "type": "Feature",
  "properties": {
    "gn:admin1_code":"65",
    "gn:admin2_code":"81.0",
    "gn:asciiname":"Musia",
    "gn:country_code":"LT",
    "gn:dem":72,
    "gn:feature_class":"P",
    "gn:feature_code":"PPL",
    "gn:name":"M\u016b\u0161ia",
    "gn:population":0,
    "gn:timezone":"Europe/Vilnius",
    "iso:country":"LT",
    "name:lit_x_preferred":[
        "M\u016b\u0161ia"
    ],
    "wof:name":"Musia",
    "wof:placetype":"locality"
},
  "geometry": {"coordinates":[24.85314,55.29778],"type":"Point"}
}