{
  "type": "Feature",
  "properties": {
    "gn:admin1_code":"63",
    "gn:admin2_code":"61.0",
    "gn:asciiname":"Gudiske",
    "gn:country_code":"LT",
    "gn:dem":87,
    "gn:feature_class":"P",
    "gn:feature_code":"PPL",
    "gn:name":"Gudi\u0161k\u0117",
    "gn:population":0,
    "gn:timezone":"Europe/Vilnius",
    "iso:country":"LT",
    "name:lit_x_preferred":[
        "Gudi\u0161k\u0117"
    ],
    "wof:name":"Gudiske",
    "wof:placetype":"locality"
},
  "geometry": {"coordinates":[22.15513,56.27083],"type":"Point"}
}