{
  "type": "Feature",
  "properties": {
    "gn:admin1_code":"60",
    "gn:admin2_code":"73.0",
    "gn:asciiname":"Keruciai",
    "gn:country_code":"LT",
    "gn:dem":119,
    "gn:feature_class":"P",
    "gn:feature_code":"PPL",
    "gn:name":"Keru\u010diai",
    "gn:population":0,
    "gn:timezone":"Europe/Vilnius",
    "iso:country":"LT",
    "name:lit_x_preferred":[
        "Keru\u010diai"
    ],
    "wof:name":"Keruciai",
    "wof:placetype":"locality"
},
  "geometry": {"coordinates":[25.69969,55.78073000000001],"type":"Point"}
}