{
  "type": "Feature",
  "properties": {
    "gn:admin1_code":"60.0",
    "gn:admin2_code":"57.0",
    "gn:asciiname":"Puozas",
    "gn:country_code":"LT",
    "gn:dem":106,
    "gn:feature_class":"P",
    "gn:feature_code":"PPL",
    "gn:name":"Puo\u017eas",
    "gn:population":0,
    "gn:timezone":"Europe/Vilnius",
    "iso:country":"LT",
    "name:und_x_variant":[
        "Puozhas",
        "Pozhi",
        "Puo\u017eas"
    ],
    "wof:name":"Puozas",
    "wof:placetype":"locality"
},
  "geometry": {"coordinates":[25.16383,55.80979],"type":"Point"}
}