{
  "type": "Feature",
  "properties": {
    "gn:admin1_code":"60",
    "gn:admin2_code":"57.0",
    "gn:asciiname":"Linkiskiai",
    "gn:country_code":"LT",
    "gn:dem":112,
    "gn:feature_class":"P",
    "gn:feature_code":"PPL",
    "gn:name":"Linki\u0161kiai",
    "gn:population":0,
    "gn:timezone":"Europe/Vilnius",
    "iso:country":"LT",
    "name:lit_x_preferred":[
        "Linki\u0161kiai"
    ],
    "wof:name":"Linkiskiai",
    "wof:placetype":"locality"
},
  "geometry": {"coordinates":[25.02855,55.73309],"type":"Point"}
}