{
  "type": "Feature",
  "properties": {
    "iso:country":"LT",
    "qs_pg:aaroncc":"LT",
    "qs_pg:name":"Vistycio Seniunija",
    "qs_pg:name_adm0":"Lietuva",
    "qs_pg:name_adm1":"Marijampol\u00ecs Apskritis",
    "qs_pg:photos":27,
    "qs_pg:photos_1k":5,
    "qs_pg:photos_9k":1,
    "qs_pg:photos_9r":3,
    "qs_pg:photos_all":140,
    "qs_pg:photos_sr":2,
    "qs_pg:pop_sr":0,
    "qs_pg:qs_pg_placetype":"localadmin",
    "qs_pg:qs_pg_placetype_gp":"LocalAdmin",
    "qs_pg:woe_adm0":23424875,
    "woe:adm0_id":23424875,
    "woe:name_adm0":"Lietuva",
    "woe:name_adm1":"Marijampol\u00ecs Apskritis",
    "woe:placetype":"LocalAdmin",
    "wof:name":"Vistycio Seniunija",
    "wof:placetype":"localadmin"
},
  "geometry": {"coordinates":[22.766246,54.410087],"type":"Point"}
}