{
  "type": "Feature",
  "properties": {
    "gn:admin1_code":"62",
    "gn:admin2_code":"94.0",
    "gn:asciiname":"Pilis II",
    "gn:country_code":"LT",
    "gn:dem":56,
    "gn:feature_class":"P",
    "gn:feature_code":"PPL",
    "gn:name":"Pilis II",
    "gn:population":0,
    "gn:timezone":"Europe/Vilnius",
    "iso:country":"LT",
    "name:lit_x_preferred":[
        "Pilis II"
    ],
    "wof:name":"Pilis II",
    "wof:placetype":"locality"
},
  "geometry": {"coordinates":[22.99929,55.10996],"type":"Point"}
}