{
  "type": "Feature",
  "properties": {
    "gn:admin1_code":"59.0",
    "gn:admin2_code":"84.0",
    "gn:asciiname":"Geciai",
    "gn:country_code":"LT",
    "gn:dem":35,
    "gn:feature_class":"P",
    "gn:feature_code":"PPL",
    "gn:name":"Ge\u010diai",
    "gn:population":0,
    "gn:timezone":"Europe/Vilnius",
    "iso:country":"LT",
    "name:und_x_variant":[
        "Getse",
        "Ge\u010diai"
    ],
    "wof:name":"Geciai",
    "wof:placetype":"locality"
},
  "geometry": {"coordinates":[22.76671,55.02018],"type":"Point"}
}