{
  "type": "Feature",
  "properties": {
    "gn:admin1_code":"64",
    "gn:admin2_code":"45.0",
    "gn:asciiname":"Pakiaunys",
    "gn:country_code":"LT",
    "gn:dem":151,
    "gn:feature_class":"P",
    "gn:feature_code":"PPL",
    "gn:name":"Pakiaunys",
    "gn:population":0,
    "gn:timezone":"Europe/Vilnius",
    "iso:country":"LT",
    "name:lit_x_preferred":[
        "Pakiaunys"
    ],
    "wof:name":"Pakiaunys",
    "wof:placetype":"locality"
},
  "geometry": {"coordinates":[25.89431,55.30849],"type":"Point"}
}