{
  "type": "Feature",
  "properties": {
    "gn:admin1_code":"60",
    "gn:admin2_code":"73.0",
    "gn:asciiname":"Kuliai",
    "gn:country_code":"LT",
    "gn:dem":153,
    "gn:feature_class":"P",
    "gn:feature_code":"PPL",
    "gn:name":"Kuliai",
    "gn:population":0,
    "gn:timezone":"Europe/Vilnius",
    "iso:country":"LT",
    "name:ceb_x_preferred":[
        "Kuliai"
    ],
    "name:ces_x_preferred":[
        "Kuliai"
    ],
    "name:est_x_preferred":[
        "Kuliai"
    ],
    "name:fra_x_preferred":[
        "Kuliai"
    ],
    "name:lit_x_preferred":[
        "Kuliai"
    ],
    "name:nld_x_preferred":[
        "Kuliai"
    ],
    "name:pol_x_preferred":[
        "Kule"
    ],
    "name:swe_x_preferred":[
        "Kuliai"
    ],
    "wof:name":"Kuliai",
    "wof:placetype":"locality"
},
  "geometry": {"coordinates":[25.63854,55.81223000000001],"type":"Point"}
}