{
  "type": "Feature",
  "properties": {
    "gn:admin1_code":"56.0",
    "gn:admin2_code":"11.0",
    "gn:asciiname":"Lydekininkai",
    "gn:country_code":"LT",
    "gn:dem":143,
    "gn:feature_class":"P",
    "gn:feature_code":"PPL",
    "gn:name":"Lydekininkai",
    "gn:population":0,
    "gn:timezone":"Europe/Vilnius",
    "iso:country":"LT",
    "name:und_x_variant":[
        "Ledyakine",
        "Lydekininkai"
    ],
    "wof:name":"Lydekininkai",
    "wof:placetype":"locality"
},
  "geometry": {"coordinates":[24.11615,54.25331],"type":"Point"}
}