{
  "type": "Feature",
  "properties": {
    "gn:admin1_code":"65",
    "gn:admin2_code":"89.0",
    "gn:asciiname":"Pusilgiskiai",
    "gn:country_code":"LT",
    "gn:dem":107,
    "gn:feature_class":"P",
    "gn:feature_code":"PPL",
    "gn:name":"Pusilgi\u0161kiai",
    "gn:population":0,
    "gn:timezone":"Europe/Vilnius",
    "iso:country":"LT",
    "name:lit_x_preferred":[
        "Pusilgi\u0161kiai"
    ],
    "wof:name":"Pusilgiskiai",
    "wof:placetype":"locality"
},
  "geometry": {"coordinates":[24.68981,55.02775],"type":"Point"}
}