{
  "type": "Feature",
  "properties": {
    "iso:country":"LT",
    "wof:name":"Babiniai",
    "wof:placetype":"neighbourhood"
},
  "geometry": {"coordinates":[25.35356568287028,54.7753438354132],"type":"Point"}
}