{
  "type": "Feature",
  "properties": {
    "gn:admin1_code":"60.0",
    "gn:admin2_code":"27.0",
    "gn:asciiname":"Jasvilonys",
    "gn:country_code":"LT",
    "gn:dem":74,
    "gn:feature_class":"P",
    "gn:feature_code":"PPL",
    "gn:name":"Jasvilonys",
    "gn:population":0,
    "gn:timezone":"Europe/Vilnius",
    "iso:country":"LT",
    "name:lit_x_preferred":[
        "Jasvilonys"
    ],
    "name:und_x_variant":[
        "Yasvilantsy",
        "Jasvylonys"
    ],
    "wof:name":"Jasvilonys",
    "wof:placetype":"locality"
},
  "geometry": {"coordinates":[24.7094,55.71703],"type":"Point"}
}