{
  "type": "Feature",
  "properties": {
    "gn:admin1_code":"60.0",
    "gn:admin2_code":"27.0",
    "gn:asciiname":"Uzuraisciai",
    "gn:country_code":"LT",
    "gn:dem":79,
    "gn:feature_class":"P",
    "gn:feature_code":"PPL",
    "gn:name":"U\u017eurais\u010diai",
    "gn:population":0,
    "gn:timezone":"Europe/Vilnius",
    "iso:country":"LT",
    "name:und_x_variant":[
        "U\u017eurais\u010di\u0173",
        "Uzhuroystse",
        "Uzhuralegyay",
        "U\u017eurais\u010diai"
    ],
    "wof:name":"Uzuraisciai",
    "wof:placetype":"locality"
},
  "geometry": {"coordinates":[24.45798,55.42159],"type":"Point"}
}