{
  "type": "Feature",
  "properties": {
    "gn:admin1_code":"0.0",
    "gn:asciiname":"Juodsimiai",
    "gn:cc2":"LT",
    "gn:country_code":"LT",
    "gn:dem":63,
    "gn:feature_class":"P",
    "gn:feature_code":"PPL",
    "gn:name":"Juod\u0161imiai",
    "gn:population":0,
    "gn:timezone":"Europe/Vilnius",
    "iso:country":"LT",
    "name:und_x_variant":[
        "Iochima",
        "Juod\u0161imiai"
    ],
    "wof:name":"Juodsimiai",
    "wof:placetype":"locality"
},
  "geometry": {"coordinates":[24.28333,55.35],"type":"Point"}
}