{
  "type": "Feature",
  "properties": {
    "gn:admin1_code":"60",
    "gn:admin2_code":"67.0",
    "gn:asciiname":"Puigiskiai",
    "gn:country_code":"LT",
    "gn:dem":35,
    "gn:feature_class":"P",
    "gn:feature_code":"PPL",
    "gn:name":"Puigi\u0161kiai",
    "gn:population":0,
    "gn:timezone":"Europe/Vilnius",
    "iso:country":"LT",
    "name:lit_x_preferred":[
        "Puigi\u0161kiai"
    ],
    "wof:name":"Puigiskiai",
    "wof:placetype":"locality"
},
  "geometry": {"coordinates":[24.45385,56.19342],"type":"Point"}
}