{
  "type": "Feature",
  "properties": {
    "gn:admin1_code":"61.0",
    "gn:admin2_code":"54.0",
    "gn:asciiname":"Kerkasiai",
    "gn:country_code":"LT",
    "gn:dem":142,
    "gn:feature_class":"P",
    "gn:feature_code":"PPL",
    "gn:name":"Kerkasiai",
    "gn:population":0,
    "gn:timezone":"Europe/Vilnius",
    "iso:country":"LT",
    "name:und_x_variant":[
        "Kerkosay",
        "Kerkasiai"
    ],
    "wof:name":"Kerkasiai",
    "wof:placetype":"locality"
},
  "geometry": {"coordinates":[22.88841,55.50821],"type":"Point"}
}