{
  "type": "Feature",
  "properties": {
    "gn:admin1_code":"64",
    "gn:admin2_code":"34.0",
    "gn:asciiname":"Peciuliai",
    "gn:country_code":"LT",
    "gn:dem":139,
    "gn:feature_class":"P",
    "gn:feature_code":"PPL",
    "gn:name":"Pe\u010diuliai",
    "gn:population":0,
    "gn:timezone":"Europe/Vilnius",
    "iso:country":"LT",
    "name:lit_x_preferred":[
        "Pe\u010diuliai"
    ],
    "wof:name":"Peciuliai",
    "wof:placetype":"locality"
},
  "geometry": {"coordinates":[25.19234,55.49393000000001],"type":"Point"}
}