{
  "type": "Feature",
  "properties": {
    "gn:admin1_code":"57",
    "gn:admin2_code":"19.0",
    "gn:asciiname":"Purvaiciai",
    "gn:country_code":"LT",
    "gn:dem":72,
    "gn:feature_class":"P",
    "gn:feature_code":"PPL",
    "gn:name":"Purvai\u010diai",
    "gn:population":0,
    "gn:timezone":"Europe/Vilnius",
    "iso:country":"LT",
    "name:lit_x_preferred":[
        "Purvai\u010diai"
    ],
    "wof:name":"Purvaiciai",
    "wof:placetype":"locality"
},
  "geometry": {"coordinates":[23.53778,55.16568],"type":"Point"}
}