{
  "type": "Feature",
  "properties": {
    "gn:admin1_code":"57",
    "gn:admin2_code":"49.0",
    "gn:asciiname":"Sutartiskes",
    "gn:country_code":"LT",
    "gn:dem":153,
    "gn:feature_class":"P",
    "gn:feature_code":"PPL",
    "gn:name":"Sutarti\u0161k\u0117s",
    "gn:population":0,
    "gn:timezone":"Europe/Vilnius",
    "iso:country":"LT",
    "name:lit_x_preferred":[
        "Sutarti\u0161k\u0117s"
    ],
    "wof:name":"Sutartiskes",
    "wof:placetype":"locality"
},
  "geometry": {"coordinates":[24.43097,54.72003],"type":"Point"}
}