{
  "type": "Feature",
  "properties": {
    "gn:admin1_code":"65",
    "gn:admin2_code":"81.0",
    "gn:asciiname":"Knyzlaukis",
    "gn:country_code":"LT",
    "gn:dem":87,
    "gn:feature_class":"P",
    "gn:feature_code":"PPL",
    "gn:name":"Knyzlaukis",
    "gn:population":0,
    "gn:timezone":"Europe/Vilnius",
    "iso:country":"LT",
    "name:lit_x_preferred":[
        "Knyzlaukis"
    ],
    "wof:name":"Knyzlaukis",
    "wof:placetype":"locality"
},
  "geometry": {"coordinates":[24.62911,55.13938],"type":"Point"}
}