{
  "type": "Feature",
  "properties": {
    "gn:admin1_code":"65",
    "gn:admin2_code":"79.0",
    "gn:asciiname":"Grabniokai",
    "gn:country_code":"LT",
    "gn:dem":168,
    "gn:feature_class":"P",
    "gn:feature_code":"PPL",
    "gn:name":"Grabniokai",
    "gn:population":0,
    "gn:timezone":"Europe/Vilnius",
    "iso:country":"LT",
    "name:lit_x_preferred":[
        "Grabniokai"
    ],
    "wof:name":"Grabniokai",
    "wof:placetype":"locality"
},
  "geometry": {"coordinates":[24.60416,54.57481],"type":"Point"}
}