{
  "type": "Feature",
  "properties": {
    "gn:admin1_code":"60",
    "gn:admin2_code":"27.0",
    "gn:asciiname":"Trakiskiai",
    "gn:country_code":"LT",
    "gn:dem":47,
    "gn:feature_class":"P",
    "gn:feature_code":"PPL",
    "gn:name":"Traki\u0161kiai",
    "gn:population":0,
    "gn:timezone":"Europe/Vilnius",
    "iso:country":"LT",
    "name:lit_x_preferred":[
        "Traki\u0161kiai"
    ],
    "wof:name":"Trakiskiai",
    "wof:placetype":"locality"
},
  "geometry": {"coordinates":[24.24887,55.69668000000001],"type":"Point"}
}