{
  "type": "Feature",
  "properties": {
    "gn:admin1_code":"56",
    "gn:admin2_code":"11.0",
    "gn:asciiname":"Darbalaukis",
    "gn:country_code":"LT",
    "gn:dem":147,
    "gn:feature_class":"P",
    "gn:feature_code":"PPL",
    "gn:name":"Darbalaukis",
    "gn:population":0,
    "gn:timezone":"Europe/Vilnius",
    "iso:country":"LT",
    "name:lit_x_preferred":[
        "Darbalaukis"
    ],
    "wof:name":"Darbalaukis",
    "wof:placetype":"locality"
},
  "geometry": {"coordinates":[24.3247,54.48431],"type":"Point"}
}