{
  "type": "Feature",
  "properties": {
    "gn:admin1_code":"56",
    "gn:admin2_code":"11.0",
    "gn:asciiname":"Panemuninkeliai",
    "gn:country_code":"LT",
    "gn:dem":69,
    "gn:feature_class":"P",
    "gn:feature_code":"PPL",
    "gn:name":"Panemunink\u0117liai",
    "gn:population":0,
    "gn:timezone":"Europe/Vilnius",
    "iso:country":"LT",
    "name:lit_x_preferred":[
        "Panemunink\u0117liai"
    ],
    "wof:name":"Panemuninkeliai",
    "wof:placetype":"locality"
},
  "geometry": {"coordinates":[24.06931,54.43111999999999],"type":"Point"}
}