{
  "type": "Feature",
  "properties": {
    "gn:admin1_code":"64",
    "gn:admin2_code":"62.0",
    "gn:asciiname":"Surguske",
    "gn:country_code":"LT",
    "gn:dem":161,
    "gn:feature_class":"P",
    "gn:feature_code":"PPL",
    "gn:name":"Surgu\u0161k\u0117",
    "gn:population":0,
    "gn:timezone":"Europe/Vilnius",
    "iso:country":"LT",
    "name:lit_x_preferred":[
        "Surgu\u0161k\u0117"
    ],
    "wof:name":"Surguske",
    "wof:placetype":"locality"
},
  "geometry": {"coordinates":[25.4786,55.17311],"type":"Point"}
}