{
  "type": "Feature",
  "properties": {
    "iso:country":"LT",
    "wof:name":"Piromontas",
    "wof:placetype":"neighbourhood"
},
  "geometry": {"coordinates":[25.28678937363689,54.69339491606934],"type":"Point"}
}