{
  "type": "Feature",
  "properties": {
    "gn:admin1_code":"64",
    "gn:admin2_code":"45.0",
    "gn:asciiname":"Pajuodupis",
    "gn:country_code":"LT",
    "gn:dem":130,
    "gn:feature_class":"P",
    "gn:feature_code":"PPL",
    "gn:name":"Pajuodupis",
    "gn:population":0,
    "gn:timezone":"Europe/Minsk",
    "iso:country":"LT",
    "name:lit_x_preferred":[
        "Pajuodupis"
    ],
    "wof:name":"Pajuodupis",
    "wof:placetype":"locality"
},
  "geometry": {"coordinates":[26.76983,55.26158],"type":"Point"}
}