{
  "type": "Feature",
  "properties": {
    "gn:admin1_code":"61.0",
    "gn:admin2_code":"29.0",
    "gn:asciiname":"Tamosiunai",
    "gn:country_code":"LT",
    "gn:dem":95,
    "gn:feature_class":"P",
    "gn:feature_code":"PPL",
    "gn:name":"Tamo\u0161i\u016bnai",
    "gn:population":0,
    "gn:timezone":"Europe/Vilnius",
    "iso:country":"LT",
    "name:und_x_variant":[
        "Tamoshyunay",
        "Tamo\u0161i\u016bnai"
    ],
    "wof:name":"Tamosiunai",
    "wof:placetype":"locality"
},
  "geometry": {"coordinates":[23.39014,56.09458000000001],"type":"Point"}
}