{
  "type": "Feature",
  "properties": {
    "gn:admin1_code":"57.0",
    "gn:admin2_code":"53.0",
    "gn:asciiname":"Ramygolka",
    "gn:country_code":"LT",
    "gn:dem":67,
    "gn:feature_class":"P",
    "gn:feature_code":"PPL",
    "gn:name":"Ramygolka",
    "gn:population":0,
    "gn:timezone":"Europe/Vilnius",
    "iso:country":"LT",
    "name:lit_x_preferred":[
        "Ramygolka"
    ],
    "name:und_x_variant":[
        "Remigola",
        "Ramigolka",
        "\u0160ven\u010dgalis"
    ],
    "wof:name":"Ramygolka",
    "wof:placetype":"locality"
},
  "geometry": {"coordinates":[24.333,55.43359],"type":"Point"}
}