{
  "type": "Feature",
  "properties": {
    "gn:admin1_code":"64",
    "gn:admin2_code":"45.0",
    "gn:asciiname":"Smilginiske",
    "gn:country_code":"LT",
    "gn:dem":153,
    "gn:feature_class":"P",
    "gn:feature_code":"PPL",
    "gn:name":"Smilgini\u0161k\u0117",
    "gn:population":0,
    "gn:timezone":"Europe/Vilnius",
    "iso:country":"LT",
    "name:lit_x_preferred":[
        "Smilgini\u0161k\u0117"
    ],
    "wof:name":"Smilginiske",
    "wof:placetype":"locality"
},
  "geometry": {"coordinates":[26.53786,55.42396],"type":"Point"}
}