{
  "type": "Feature",
  "properties": {
    "gn:admin1_code":"61.0",
    "gn:admin2_code":"65.0",
    "gn:asciiname":"Spilgiai",
    "gn:country_code":"LT",
    "gn:dem":54,
    "gn:feature_class":"P",
    "gn:feature_code":"PPL",
    "gn:name":"Spilgiai",
    "gn:population":0,
    "gn:timezone":"Europe/Vilnius",
    "iso:country":"LT",
    "name:und_x_variant":[
        "Spil\u2019gyay",
        "Spilgiai"
    ],
    "wof:name":"Spilgiai",
    "wof:placetype":"locality"
},
  "geometry": {"coordinates":[24.07418,55.93514],"type":"Point"}
}