{
  "type": "Feature",
  "properties": {
    "gn:admin1_code":"60",
    "gn:admin2_code":"73.0",
    "gn:asciiname":"Dundiskiai",
    "gn:country_code":"LT",
    "gn:dem":144,
    "gn:feature_class":"P",
    "gn:feature_code":"PPL",
    "gn:name":"Dundi\u0161kiai",
    "gn:population":0,
    "gn:timezone":"Europe/Vilnius",
    "iso:country":"LT",
    "name:lit_x_preferred":[
        "Dundi\u0161kiai"
    ],
    "wof:name":"Dundiskiai",
    "wof:placetype":"locality"
},
  "geometry": {"coordinates":[25.92839,55.94111],"type":"Point"}
}