{
  "type": "Feature",
  "properties": {
    "gn:admin1_code":"57.0",
    "gn:admin2_code":"19.0",
    "gn:asciiname":"Vilkenai",
    "gn:country_code":"LT",
    "gn:dem":37,
    "gn:feature_class":"P",
    "gn:feature_code":"PPL",
    "gn:name":"Vilk\u0117nai",
    "gn:population":0,
    "gn:timezone":"Europe/Vilnius",
    "iso:country":"LT",
    "name:und_x_variant":[
        "Pacheveukas",
        "Vil\u2019chatov",
        "Vilk\u0117nai"
    ],
    "wof:name":"Vilkenai",
    "wof:placetype":"locality"
},
  "geometry": {"coordinates":[23.79851,55.13199],"type":"Point"}
}