{
  "type": "Feature",
  "properties": {
    "gn:admin1_code":"65",
    "gn:admin2_code":"13.0",
    "gn:asciiname":"Kuleliskes",
    "gn:country_code":"LT",
    "gn:dem":194,
    "gn:feature_class":"P",
    "gn:feature_code":"PPL",
    "gn:name":"Kuleli\u0161k\u0117s",
    "gn:population":0,
    "gn:timezone":"Europe/Vilnius",
    "iso:country":"LT",
    "name:lit_x_preferred":[
        "Kuleli\u0161k\u0117s"
    ],
    "wof:name":"Kuleliskes",
    "wof:placetype":"locality"
},
  "geometry": {"coordinates":[25.68677000000001,54.71852],"type":"Point"}
}