{
  "type": "Feature",
  "properties": {
    "gn:admin1_code":"60",
    "gn:admin2_code":"27.0",
    "gn:asciiname":"Siurpes",
    "gn:country_code":"LT",
    "gn:dem":60,
    "gn:feature_class":"P",
    "gn:feature_code":"PPL",
    "gn:name":"\u0160iurp\u0117s",
    "gn:population":0,
    "gn:timezone":"Europe/Vilnius",
    "iso:country":"LT",
    "name:lit_x_preferred":[
        "\u0160iurp\u0117s"
    ],
    "wof:name":"Siurpes",
    "wof:placetype":"locality"
},
  "geometry": {"coordinates":[24.50813,55.68969],"type":"Point"}
}