{
  "type": "Feature",
  "properties": {
    "gn:admin1_code":"65",
    "gn:admin2_code":"81.0",
    "gn:asciiname":"Dembrovica",
    "gn:country_code":"LT",
    "gn:dem":145,
    "gn:feature_class":"P",
    "gn:feature_code":"PPL",
    "gn:name":"Dembrovica",
    "gn:population":0,
    "gn:timezone":"Europe/Vilnius",
    "iso:country":"LT",
    "name:lit_x_preferred":[
        "Dembrovica"
    ],
    "wof:name":"Dembrovica",
    "wof:placetype":"locality"
},
  "geometry": {"coordinates":[24.9898,55.19857],"type":"Point"}
}