{
  "type": "Feature",
  "properties": {
    "gn:admin1_code":"60",
    "gn:admin2_code":"36.0",
    "gn:asciiname":"Medikiai",
    "gn:country_code":"LT",
    "gn:dem":76,
    "gn:feature_class":"P",
    "gn:feature_code":"PPL",
    "gn:name":"Medikiai",
    "gn:population":0,
    "gn:timezone":"Europe/Vilnius",
    "iso:country":"LT",
    "name:lit_x_preferred":[
        "Medikiai"
    ],
    "wof:name":"Medikiai",
    "wof:placetype":"locality"
},
  "geometry": {"coordinates":[25.17174,56.13032],"type":"Point"}
}