{
  "type": "Feature",
  "properties": {
    "gn:admin1_code":"57",
    "gn:admin2_code":"72.0",
    "gn:asciiname":"Jagucioniai",
    "gn:country_code":"LT",
    "gn:dem":110,
    "gn:feature_class":"P",
    "gn:feature_code":"PPL",
    "gn:name":"Jagu\u010dioniai",
    "gn:population":0,
    "gn:timezone":"Europe/Vilnius",
    "iso:country":"LT",
    "name:lit_x_preferred":[
        "Jagu\u010dioniai"
    ],
    "wof:name":"Jagucioniai",
    "wof:placetype":"locality"
},
  "geometry": {"coordinates":[23.44116,55.34556],"type":"Point"}
}