{
  "type": "Feature",
  "properties": {
    "gn:admin1_code":"57.0",
    "gn:admin2_code":"69.0",
    "gn:asciiname":"Verbyliskes",
    "gn:country_code":"LT",
    "gn:dem":68,
    "gn:feature_class":"P",
    "gn:feature_code":"PPL",
    "gn:name":"Verbyli\u0161k\u0117s",
    "gn:population":0,
    "gn:timezone":"Europe/Vilnius",
    "iso:country":"LT",
    "name:und_x_variant":[
        "Verbelishki",
        "Verbyli\u0161k\u0117s"
    ],
    "wof:name":"Verbyliskes",
    "wof:placetype":"locality"
},
  "geometry": {"coordinates":[24.17044,54.5752],"type":"Point"}
}