{
  "type": "Feature",
  "properties": {
    "gn:admin1_code":"65",
    "gn:admin2_code":"81.0",
    "gn:asciiname":"Gavenonys",
    "gn:country_code":"LT",
    "gn:dem":77,
    "gn:feature_class":"P",
    "gn:feature_code":"PPL",
    "gn:name":"Gav\u0117nonys",
    "gn:population":0,
    "gn:timezone":"Europe/Vilnius",
    "iso:country":"LT",
    "name:lit_x_preferred":[
        "Gav\u0117nonys"
    ],
    "wof:name":"Gavenonys",
    "wof:placetype":"locality"
},
  "geometry": {"coordinates":[24.5892,55.12549],"type":"Point"}
}