{
  "type": "Feature",
  "properties": {
    "gn:admin1_code":"56.0",
    "gn:admin2_code":"38.0",
    "gn:asciiname":"Kursiai",
    "gn:country_code":"LT",
    "gn:dem":155,
    "gn:feature_class":"P",
    "gn:feature_code":"PPL",
    "gn:name":"Kur\u0161iai",
    "gn:population":0,
    "gn:timezone":"Europe/Vilnius",
    "iso:country":"LT",
    "name:und_x_variant":[
        "Kurshi",
        "Kur\u0161iai"
    ],
    "wof:name":"Kursiai",
    "wof:placetype":"locality"
},
  "geometry": {"coordinates":[24.90972,54.32455],"type":"Point"}
}