{
  "type": "Feature",
  "properties": {
    "gn:admin1_code":"57.0",
    "gn:asciiname":"Rukai",
    "gn:cc2":"LT",
    "gn:country_code":"LT",
    "gn:dem":91,
    "gn:feature_class":"P",
    "gn:feature_code":"PPL",
    "gn:name":"Rukai",
    "gn:population":0,
    "gn:timezone":"Europe/Vilnius",
    "iso:country":"LT",
    "name:und_x_variant":[
        "Ruki",
        "R\u016bk\u0173",
        "Rukai"
    ],
    "wof:name":"Rukai",
    "wof:placetype":"locality"
},
  "geometry": {"coordinates":[23.7448,55.4642],"type":"Point"}
}