{
  "type": "Feature",
  "properties": {
    "gn:admin1_code":"57.0",
    "gn:admin2_code":"46.0",
    "gn:asciiname":"Turzenai",
    "gn:country_code":"LT",
    "gn:dem":60,
    "gn:feature_class":"P",
    "gn:feature_code":"PPL",
    "gn:name":"Tur\u017e\u0117nai",
    "gn:population":0,
    "gn:timezone":"Europe/Vilnius",
    "iso:country":"LT",
    "name:lit_x_preferred":[
        "Tur\u017e\u0117nai"
    ],
    "wof:name":"Turzenai",
    "wof:placetype":"locality"
},
  "geometry": {"coordinates":[24.09288,54.98301],"type":"Point"}
}