{
  "type": "Feature",
  "properties": {
    "gn:admin1_code":"60",
    "gn:admin2_code":"67.0",
    "gn:asciiname":"Balsiai",
    "gn:country_code":"LT",
    "gn:dem":34,
    "gn:feature_class":"P",
    "gn:feature_code":"PPL",
    "gn:name":"Balsiai",
    "gn:population":0,
    "gn:timezone":"Europe/Vilnius",
    "iso:country":"LT",
    "name:lit_x_preferred":[
        "Balsiai"
    ],
    "wof:name":"Balsiai",
    "wof:placetype":"locality"
},
  "geometry": {"coordinates":[24.35357,56.03495],"type":"Point"}
}