{
  "type": "Feature",
  "properties": {
    "gn:admin1_code":"57",
    "gn:admin2_code":"72.0",
    "gn:asciiname":"Fliorencija",
    "gn:country_code":"LT",
    "gn:dem":110,
    "gn:feature_class":"P",
    "gn:feature_code":"PPL",
    "gn:name":"Fliorencija",
    "gn:population":0,
    "gn:timezone":"Europe/Vilnius",
    "iso:country":"LT",
    "name:lit_x_preferred":[
        "Fliorencija"
    ],
    "wof:name":"Fliorencija",
    "wof:placetype":"locality"
},
  "geometry": {"coordinates":[23.26998,55.42698000000001],"type":"Point"}
}