{
  "type": "Feature",
  "properties": {
    "gn:admin1_code":"58.0",
    "gn:admin2_code":"21.0",
    "gn:asciiname":"Vytauciai",
    "gn:country_code":"LT",
    "gn:dem":34,
    "gn:feature_class":"P",
    "gn:feature_code":"PPL",
    "gn:name":"Vytau\u010diai",
    "gn:population":0,
    "gn:timezone":"Europe/Vilnius",
    "iso:country":"LT",
    "name:und_x_variant":[
        "Vytauchay",
        "Vytau\u010diai"
    ],
    "wof:name":"Vytauciai",
    "wof:placetype":"locality"
},
  "geometry": {"coordinates":[21.28333,55.80586],"type":"Point"}
}