{
  "type": "Feature",
  "properties": {
    "gn:admin1_code":"60",
    "gn:admin2_code":"73.0",
    "gn:asciiname":"Vebris!kiai",
    "gn:country_code":"LT",
    "gn:dem":98,
    "gn:feature_class":"P",
    "gn:feature_code":"PPL",
    "gn:name":"V\u0117bris!kiai",
    "gn:population":0,
    "gn:timezone":"Europe/Vilnius",
    "iso:country":"LT",
    "name:lit_x_preferred":[
        "V\u0117bris!kiai"
    ],
    "wof:name":"Vebris!kiai",
    "wof:placetype":"locality"
},
  "geometry": {"coordinates":[25.40377,55.89695],"type":"Point"}
}