{
  "type": "Feature",
  "properties": {
    "gn:admin1_code":"65",
    "gn:admin2_code":"86.0",
    "gn:asciiname":"Dalia",
    "gn:country_code":"LT",
    "gn:dem":135,
    "gn:feature_class":"P",
    "gn:feature_code":"PPL",
    "gn:name":"Dalia",
    "gn:population":0,
    "gn:timezone":"Europe/Vilnius",
    "iso:country":"LT",
    "name:ara_x_preferred":[
        "\u062f\u0627\u0644\u064a\u0627"
    ],
    "name:deu_x_preferred":[
        "Dalia"
    ],
    "name:glg_x_preferred":[
        "Dalia"
    ],
    "name:heb_x_preferred":[
        "\u05d3\u05dc\u05d9\u05d4"
    ],
    "name:ita_x_preferred":[
        "Dalia"
    ],
    "name:lit_x_preferred":[
        "Dalia"
    ],
    "name:pol_x_preferred":[
        "Dalia"
    ],
    "name:spa_x_preferred":[
        "Dalia"
    ],
    "wof:name":"Dalia",
    "wof:placetype":"locality"
},
  "geometry": {"coordinates":[25.6693,54.92265],"type":"Point"}
}