{
  "type": "Feature",
  "properties": {
    "gn:admin1_code":"65",
    "gn:admin2_code":"13.0",
    "gn:asciiname":"Prapuolai",
    "gn:country_code":"LT",
    "gn:dem":165,
    "gn:feature_class":"P",
    "gn:feature_code":"PPL",
    "gn:name":"Prapuolai",
    "gn:population":0,
    "gn:timezone":"Europe/Vilnius",
    "iso:country":"LT",
    "name:lit_x_preferred":[
        "Prapuolai"
    ],
    "wof:name":"Prapuolai",
    "wof:placetype":"locality"
},
  "geometry": {"coordinates":[25.07748,54.74809000000001],"type":"Point"}
}