{
  "type": "Feature",
  "properties": {
    "gn:admin1_code":"62",
    "gn:admin2_code":"94.0",
    "gn:asciiname":"Antkalniai",
    "gn:country_code":"LT",
    "gn:dem":32,
    "gn:feature_class":"P",
    "gn:feature_code":"PPL",
    "gn:name":"Antkalniai",
    "gn:population":0,
    "gn:timezone":"Europe/Vilnius",
    "iso:country":"LT",
    "name:lit_x_preferred":[
        "Antkalniai"
    ],
    "wof:name":"Antkalniai",
    "wof:placetype":"locality"
},
  "geometry": {"coordinates":[22.66951,55.13592],"type":"Point"}
}