{
  "type": "Feature",
  "properties": {
    "gn:admin1_code":"62.0",
    "gn:admin2_code":"77.0",
    "gn:asciiname":"Daujoteliai",
    "gn:country_code":"LT",
    "gn:dem":134,
    "gn:feature_class":"P",
    "gn:feature_code":"PPL",
    "gn:name":"Daujot\u0117liai",
    "gn:population":0,
    "gn:timezone":"Europe/Vilnius",
    "iso:country":"LT",
    "name:und_x_variant":[
        "Dovyatelyay",
        "Daujot\u0117liai"
    ],
    "wof:name":"Daujoteliai",
    "wof:placetype":"locality"
},
  "geometry": {"coordinates":[22.67591,55.44657],"type":"Point"}
}