{
  "type": "Feature",
  "properties": {
    "gn:admin1_code":"57",
    "gn:admin2_code":"69.0",
    "gn:asciiname":"Liepalotas",
    "gn:country_code":"LT",
    "gn:dem":104,
    "gn:feature_class":"P",
    "gn:feature_code":"PPL",
    "gn:name":"Liepalotas",
    "gn:population":0,
    "gn:timezone":"Europe/Vilnius",
    "iso:country":"LT",
    "name:lit_x_preferred":[
        "Liepalotas"
    ],
    "wof:name":"Liepalotas",
    "wof:placetype":"locality"
},
  "geometry": {"coordinates":[23.94669,54.67587],"type":"Point"}
}