{
  "type": "Feature",
  "properties": {
    "gn:admin1_code":"64",
    "gn:admin2_code":"34.0",
    "gn:asciiname":"Riboskiskis",
    "gn:country_code":"LT",
    "gn:dem":91,
    "gn:feature_class":"P",
    "gn:feature_code":"PPL",
    "gn:name":"Riboski\u0161kis",
    "gn:population":0,
    "gn:timezone":"Europe/Vilnius",
    "iso:country":"LT",
    "name:lit_x_preferred":[
        "Riboski\u0161kis"
    ],
    "wof:name":"Riboskiskis",
    "wof:placetype":"locality"
},
  "geometry": {"coordinates":[24.90817,55.44698],"type":"Point"}
}