{
  "type": "Feature",
  "properties": {
    "gn:admin1_code":"57",
    "gn:admin2_code":"69.0",
    "gn:asciiname":"Paskrynupys",
    "gn:country_code":"LT",
    "gn:dem":108,
    "gn:feature_class":"P",
    "gn:feature_code":"PPL",
    "gn:name":"Paskrynupys",
    "gn:population":0,
    "gn:timezone":"Europe/Vilnius",
    "iso:country":"LT",
    "name:lit_x_preferred":[
        "Paskrynupys"
    ],
    "wof:name":"Paskrynupys",
    "wof:placetype":"locality"
},
  "geometry": {"coordinates":[23.7071,54.61389000000001],"type":"Point"}
}