{
  "type": "Feature",
  "properties": {
    "gn:admin1_code":"60",
    "gn:admin2_code":"27.0",
    "gn:asciiname":"Vareikiai I",
    "gn:country_code":"LT",
    "gn:dem":84,
    "gn:feature_class":"P",
    "gn:feature_code":"PPL",
    "gn:name":"Vareikiai I",
    "gn:population":0,
    "gn:timezone":"Europe/Vilnius",
    "iso:country":"LT",
    "name:lit_x_preferred":[
        "Vareikiai I"
    ],
    "wof:name":"Vareikiai I",
    "wof:placetype":"locality"
},
  "geometry": {"coordinates":[24.63843,55.73381],"type":"Point"}
}