{
  "type": "Feature",
  "properties": {
    "gn:admin1_code":"62.0",
    "gn:admin2_code":"94.0",
    "gn:asciiname":"Balandziai",
    "gn:country_code":"LT",
    "gn:dem":41,
    "gn:feature_class":"P",
    "gn:feature_code":"PPL",
    "gn:name":"Baland\u017eiai",
    "gn:population":0,
    "gn:timezone":"Europe/Vilnius",
    "iso:country":"LT",
    "name:und_x_variant":[
        "Balandze",
        "Baland\u017eiai"
    ],
    "wof:name":"Balandziai",
    "wof:placetype":"locality"
},
  "geometry": {"coordinates":[22.69225,55.25676],"type":"Point"}
}