{
  "type": "Feature",
  "properties": {
    "gn:admin1_code":"58",
    "gn:admin2_code":"88.0",
    "gn:asciiname":"Naustremeniai",
    "gn:country_code":"LT",
    "gn:dem":18,
    "gn:feature_class":"P",
    "gn:feature_code":"PPL",
    "gn:name":"Naustremeniai",
    "gn:population":0,
    "gn:timezone":"Europe/Vilnius",
    "iso:country":"LT",
    "name:lit_x_preferred":[
        "Naustremeniai"
    ],
    "wof:name":"Naustremeniai",
    "wof:placetype":"locality"
},
  "geometry": {"coordinates":[21.75127,55.25147],"type":"Point"}
}