{
  "type": "Feature",
  "properties": {
    "gn:admin1_code":"64",
    "gn:admin2_code":"43.0",
    "gn:asciiname":"Kizirniskes",
    "gn:country_code":"LT",
    "gn:dem":133,
    "gn:feature_class":"P",
    "gn:feature_code":"PPL",
    "gn:name":"Kizirni\u0161k\u0117s",
    "gn:population":0,
    "gn:timezone":"Europe/Vilnius",
    "iso:country":"LT",
    "name:lit_x_preferred":[
        "Kizirni\u0161k\u0117s"
    ],
    "wof:name":"Kizirniskes",
    "wof:placetype":"locality"
},
  "geometry": {"coordinates":[26.31156,55.73271999999999],"type":"Point"}
}