{
  "type": "Feature",
  "properties": {
    "gn:admin1_code":"65.0",
    "gn:admin2_code":"85.0",
    "gn:asciiname":"Sadziunai",
    "gn:country_code":"LT",
    "gn:dem":166,
    "gn:feature_class":"P",
    "gn:feature_code":"PPL",
    "gn:name":"\u0160ad\u017ei\u016bnai",
    "gn:population":0,
    "gn:timezone":"Europe/Vilnius",
    "iso:country":"LT",
    "name:lit_x_preferred":[
        "\u0160ad\u017ei\u016bnai"
    ],
    "name:lit_x_variant":[
        "\u0160ad\u017eiunai"
    ],
    "wof:name":"Sadziunai",
    "wof:placetype":"locality"
},
  "geometry": {"coordinates":[25.69313,54.16434],"type":"Point"}
}