{
  "type": "Feature",
  "properties": {
    "gn:admin1_code":"59.0",
    "gn:admin2_code":"18.0",
    "gn:asciiname":"Gyviskiai",
    "gn:country_code":"LT",
    "gn:dem":99,
    "gn:feature_class":"P",
    "gn:feature_code":"PPL",
    "gn:name":"Gyvi\u0161kiai",
    "gn:population":0,
    "gn:timezone":"Europe/Vilnius",
    "iso:country":"LT",
    "name:lit_x_preferred":[
        "Gyvi\u0161kiai"
    ],
    "wof:name":"Gyviskiai",
    "wof:placetype":"locality"
},
  "geometry": {"coordinates":[23.47767,54.4775],"type":"Point"}
}