{
  "type": "Feature",
  "properties": {
    "gn:admin1_code":"58.0",
    "gn:admin2_code":"88.0",
    "gn:asciiname":"Zagatai",
    "gn:country_code":"LT",
    "gn:dem":22,
    "gn:feature_class":"P",
    "gn:feature_code":"PPL",
    "gn:name":"\u017dagatai",
    "gn:population":0,
    "gn:timezone":"Europe/Vilnius",
    "iso:country":"LT",
    "name:und_x_variant":[
        "Zhagaychey",
        "Zhagatay",
        "\u017dagatai"
    ],
    "wof:name":"Zagatai",
    "wof:placetype":"locality"
},
  "geometry": {"coordinates":[21.58236,55.40875],"type":"Point"}
}