{
  "type": "Feature",
  "properties": {
    "gn:admin1_code":"59.0",
    "gn:admin2_code":"39.0",
    "gn:asciiname":"Darzininkai",
    "gn:country_code":"LT",
    "gn:dem":45,
    "gn:feature_class":"P",
    "gn:feature_code":"PPL",
    "gn:name":"Dar\u017eininkai",
    "gn:population":0,
    "gn:timezone":"Europe/Vilnius",
    "iso:country":"LT",
    "name:und_x_variant":[
        "Darzhininkay",
        "Dar\u017eininkai"
    ],
    "wof:name":"Darzininkai",
    "wof:placetype":"locality"
},
  "geometry": {"coordinates":[22.91314,54.74871],"type":"Point"}
}