{
  "type": "Feature",
  "properties": {
    "gn:admin1_code":"64.0",
    "gn:admin2_code":"43.0",
    "gn:asciiname":"Bacioniskis",
    "gn:country_code":"LT",
    "gn:dem":140,
    "gn:feature_class":"P",
    "gn:feature_code":"PPL",
    "gn:name":"Bacioni\u0161kis",
    "gn:population":0,
    "gn:timezone":"Europe/Vilnius",
    "iso:country":"LT",
    "name:lit_x_preferred":[
        "Bacioni\u0161kis"
    ],
    "name:lit_x_variant":[
        "Ba\u010doni\u0161kis"
    ],
    "wof:name":"Bacioniskis",
    "wof:placetype":"locality"
},
  "geometry": {"coordinates":[26.20517000000001,55.74263000000001],"type":"Point"}
}