{
  "type": "Feature",
  "properties": {
    "gn:admin1_code":"58",
    "gn:admin2_code":"75.0",
    "gn:asciiname":"Kalvaiciai",
    "gn:country_code":"LT",
    "gn:dem":90,
    "gn:feature_class":"P",
    "gn:feature_code":"PPL",
    "gn:name":"Kalvai\u010diai",
    "gn:population":0,
    "gn:timezone":"Europe/Vilnius",
    "iso:country":"LT",
    "name:lit_x_preferred":[
        "Kalvai\u010diai"
    ],
    "wof:name":"Kalvaiciai",
    "wof:placetype":"locality"
},
  "geometry": {"coordinates":[21.83327,56.31186],"type":"Point"}
}