{
  "type": "Feature",
  "properties": {
    "gn:admin1_code":"58.0",
    "gn:admin2_code":"88.0",
    "gn:asciiname":"Vytuliai",
    "gn:country_code":"LT",
    "gn:dem":2,
    "gn:feature_class":"P",
    "gn:feature_code":"PPL",
    "gn:name":"Vytuliai",
    "gn:population":0,
    "gn:timezone":"Europe/Vilnius",
    "iso:country":"LT",
    "name:lit_x_preferred":[
        "Vytuliai"
    ],
    "name:und_x_variant":[
        "Veyteley",
        "Vitulyay",
        "Vyt\u016bliai"
    ],
    "wof:name":"Vytuliai",
    "wof:placetype":"locality"
},
  "geometry": {"coordinates":[21.43756,55.42195],"type":"Point"}
}