{
  "type": "Feature",
  "properties": {
    "gn:admin1_code":"59",
    "gn:admin2_code":"18.0",
    "gn:asciiname":"Danieliskiai",
    "gn:country_code":"LT",
    "gn:dem":84,
    "gn:feature_class":"P",
    "gn:feature_code":"PPL",
    "gn:name":"Danieli\u0161kiai",
    "gn:population":0,
    "gn:timezone":"Europe/Vilnius",
    "iso:country":"LT",
    "name:lit_x_preferred":[
        "Danieli\u0161kiai"
    ],
    "wof:name":"Danieliskiai",
    "wof:placetype":"locality"
},
  "geometry": {"coordinates":[23.42917000000001,54.49051],"type":"Point"}
}