{
  "type": "Feature",
  "properties": {
    "gn:admin1_code":"65",
    "gn:admin2_code":"13.0",
    "gn:asciiname":"Kralikiskes",
    "gn:country_code":"LT",
    "gn:dem":139,
    "gn:feature_class":"P",
    "gn:feature_code":"PPL",
    "gn:name":"Kraliki\u0161k\u0117s",
    "gn:population":0,
    "gn:timezone":"Europe/Vilnius",
    "iso:country":"LT",
    "name:lit_x_preferred":[
        "Kraliki\u0161k\u0117s"
    ],
    "wof:name":"Kralikiskes",
    "wof:placetype":"locality"
},
  "geometry": {"coordinates":[25.24721,54.94525],"type":"Point"}
}