{
  "type": "Feature",
  "properties": {
    "gn:admin1_code":"65",
    "gn:admin2_code":"13.0",
    "gn:asciiname":"Seskuciai",
    "gn:country_code":"LT",
    "gn:dem":144,
    "gn:feature_class":"P",
    "gn:feature_code":"PPL",
    "gn:name":"\u0160e\u0161ku\u010diai",
    "gn:population":0,
    "gn:timezone":"Europe/Vilnius",
    "iso:country":"LT",
    "name:lit_x_preferred":[
        "\u0160e\u0161ku\u010diai"
    ],
    "wof:name":"Seskuciai",
    "wof:placetype":"locality"
},
  "geometry": {"coordinates":[25.46937,54.75927],"type":"Point"}
}