{
  "type": "Feature",
  "properties": {
    "gn:admin1_code":"65",
    "gn:admin2_code":"41.0",
    "gn:asciiname":"Peciukai",
    "gn:country_code":"LT",
    "gn:dem":102,
    "gn:feature_class":"P",
    "gn:feature_code":"PPL",
    "gn:name":"Pe\u010diukai",
    "gn:population":0,
    "gn:timezone":"Europe/Vilnius",
    "iso:country":"LT",
    "name:lit_x_preferred":[
        "Pe\u010diukai"
    ],
    "wof:name":"Peciukai",
    "wof:placetype":"locality"
},
  "geometry": {"coordinates":[25.377,54.78169000000001],"type":"Point"}
}