{
  "type": "Feature",
  "properties": {
    "gn:admin1_code":"0.0",
    "gn:asciiname":"Uzbiciai",
    "gn:cc2":"LT",
    "gn:country_code":"LT",
    "gn:dem":16,
    "gn:feature_class":"P",
    "gn:feature_code":"PPL",
    "gn:name":"U\u017ebi\u010diai",
    "gn:population":0,
    "gn:timezone":"Europe/Vilnius",
    "iso:country":"LT",
    "name:und_x_variant":[
        "Bittenen-Uzhbichen",
        "U\u017ebi\u010diai"
    ],
    "wof:name":"Uzbiciai",
    "wof:placetype":"locality"
},
  "geometry": {"coordinates":[22.04444,55.08139],"type":"Point"}
}