{
  "type": "Feature",
  "properties": {
    "gn:admin1_code":"64",
    "gn:admin2_code":"43.0",
    "gn:asciiname":"Yliske",
    "gn:country_code":"LT",
    "gn:dem":143,
    "gn:feature_class":"P",
    "gn:feature_code":"PPL",
    "gn:name":"Yli\u0161k\u0117",
    "gn:population":0,
    "gn:timezone":"Europe/Vilnius",
    "iso:country":"LT",
    "name:lit_x_preferred":[
        "Yli\u0161k\u0117"
    ],
    "wof:name":"Yliske",
    "wof:placetype":"locality"
},
  "geometry": {"coordinates":[26.48402,55.61753],"type":"Point"}
}