{
  "type": "Feature",
  "properties": {
    "gn:admin1_code":"56",
    "gn:admin2_code":"15.0",
    "gn:asciiname":"Drapaliai",
    "gn:country_code":"LT",
    "gn:dem":130,
    "gn:feature_class":"P",
    "gn:feature_code":"PPL",
    "gn:name":"Drapaliai",
    "gn:population":0,
    "gn:timezone":"Europe/Vilnius",
    "iso:country":"LT",
    "name:lit_x_preferred":[
        "Drapaliai"
    ],
    "wof:name":"Drapaliai",
    "wof:placetype":"locality"
},
  "geometry": {"coordinates":[23.9216,54.17206],"type":"Point"}
}