{
  "type": "Feature",
  "properties": {
    "gn:admin1_code":"61.0",
    "gn:admin2_code":"65.0",
    "gn:asciiname":"Kaireliai",
    "gn:country_code":"LT",
    "gn:dem":45,
    "gn:feature_class":"P",
    "gn:feature_code":"PPL",
    "gn:name":"Kaireliai",
    "gn:population":0,
    "gn:timezone":"Europe/Vilnius",
    "iso:country":"LT",
    "name:und_x_variant":[
        "Kayryalyay",
        "Kaireli\u0173",
        "Kayrelyay",
        "Kaireliai"
    ],
    "wof:name":"Kaireliai",
    "wof:placetype":"locality"
},
  "geometry": {"coordinates":[23.94304,56.26229],"type":"Point"}
}