{
  "type": "Feature",
  "properties": {
    "gn:admin1_code":"60",
    "gn:admin2_code":"73.0",
    "gn:asciiname":"Lydziunai",
    "gn:country_code":"LT",
    "gn:dem":93,
    "gn:feature_class":"P",
    "gn:feature_code":"PPL",
    "gn:name":"Lyd\u017ei\u016bnai",
    "gn:population":0,
    "gn:timezone":"Europe/Vilnius",
    "iso:country":"LT",
    "name:lit_x_preferred":[
        "Lyd\u017ei\u016bnai"
    ],
    "wof:name":"Lydziunai",
    "wof:placetype":"locality"
},
  "geometry": {"coordinates":[25.28131,55.96998000000001],"type":"Point"}
}