{
  "type": "Feature",
  "properties": {
    "gn:admin1_code":"64.0",
    "gn:admin2_code":"43.0",
    "gn:asciiname":"Salakas",
    "gn:country_code":"LT",
    "gn:dem":161,
    "gn:feature_class":"P",
    "gn:feature_code":"PPL",
    "gn:name":"Salakas",
    "gn:population":0,
    "gn:timezone":"Europe/Vilnius",
    "iso:country":"LT",
    "name:eng_x_preferred":[
        "Salakas"
    ],
    "name:fra_x_preferred":[
        "Salakas"
    ],
    "name:heb_x_preferred":[
        "\u05e1\u05dc\u05e7\u05d0\u05e1"
    ],
    "name:ita_x_preferred":[
        "Salakas"
    ],
    "name:lit_x_preferred":[
        "Salakas"
    ],
    "name:pol_x_preferred":[
        "So\u0142oki"
    ],
    "name:rus_x_preferred":[
        "\u0421\u0430\u043b\u0430\u043a\u0430\u0441"
    ],
    "name:und_x_variant":[
        "So\u0142oki",
        "Salako",
        "Salakas"
    ],
    "wof:name":"Salakas",
    "wof:placetype":"locality"
},
  "geometry": {"coordinates":[26.13299,55.57972],"type":"Point"}
}