{
  "type": "Feature",
  "properties": {
    "gn:admin1_code":"63.0",
    "gn:admin2_code":"68.0",
    "gn:asciiname":"Rotinenai",
    "gn:country_code":"LT",
    "gn:dem":140,
    "gn:feature_class":"P",
    "gn:feature_code":"PPL",
    "gn:name":"Rotin\u0117nai",
    "gn:population":0,
    "gn:timezone":"Europe/Vilnius",
    "iso:country":"LT",
    "name:und_x_variant":[
        "Rotyniany",
        "Rotinenay",
        "Rotin\u0117n\u0173",
        "Rotin\u0117nai"
    ],
    "wof:name":"Rotinenai",
    "wof:placetype":"locality"
},
  "geometry": {"coordinates":[22.03145,56.08071999999999],"type":"Point"}
}