{
  "type": "Feature",
  "properties": {
    "gn:admin1_code":"64",
    "gn:admin2_code":"82.0",
    "gn:asciiname":"Bikeliai",
    "gn:country_code":"LT",
    "gn:dem":163,
    "gn:feature_class":"P",
    "gn:feature_code":"PPL",
    "gn:name":"Bikeliai",
    "gn:population":0,
    "gn:timezone":"Europe/Vilnius",
    "iso:country":"LT",
    "name:lit_x_preferred":[
        "Bikeliai"
    ],
    "wof:name":"Bikeliai",
    "wof:placetype":"locality"
},
  "geometry": {"coordinates":[25.72767,55.3736],"type":"Point"}
}