{
  "type": "Feature",
  "properties": {
    "gn:admin1_code":"64",
    "gn:admin2_code":"43.0",
    "gn:asciiname":"Gilyne",
    "gn:country_code":"LT",
    "gn:dem":153,
    "gn:feature_class":"P",
    "gn:feature_code":"PPL",
    "gn:name":"Gilyn\u0117",
    "gn:population":0,
    "gn:timezone":"Europe/Vilnius",
    "iso:country":"LT",
    "name:lit_x_preferred":[
        "Gilyn\u0117"
    ],
    "wof:name":"Gilyne",
    "wof:placetype":"locality"
},
  "geometry": {"coordinates":[26.42625,55.67111],"type":"Point"}
}