{
  "type": "Feature",
  "properties": {
    "gn:admin1_code":"61.0",
    "gn:admin2_code":"29.0",
    "gn:asciiname":"Gibaiciai",
    "gn:country_code":"LT",
    "gn:dem":90,
    "gn:feature_class":"P",
    "gn:feature_code":"PPL",
    "gn:name":"Gibai\u010diai",
    "gn:population":0,
    "gn:timezone":"Europe/Vilnius",
    "iso:country":"LT",
    "name:und_x_variant":[
        "Gibaychyay",
        "Gibai\u010diai"
    ],
    "wof:name":"Gibaiciai",
    "wof:placetype":"locality"
},
  "geometry": {"coordinates":[23.48354,56.04041],"type":"Point"}
}