{
  "type": "Feature",
  "properties": {
    "gn:admin1_code":"60",
    "gn:admin2_code":"73.0",
    "gn:asciiname":"Dauliunai",
    "gn:country_code":"LT",
    "gn:dem":133,
    "gn:feature_class":"P",
    "gn:feature_code":"PPL",
    "gn:name":"Dauli\u016bnai",
    "gn:population":0,
    "gn:timezone":"Europe/Vilnius",
    "iso:country":"LT",
    "name:lit_x_preferred":[
        "Dauli\u016bnai"
    ],
    "wof:name":"Dauliunai",
    "wof:placetype":"locality"
},
  "geometry": {"coordinates":[25.62429,55.75996],"type":"Point"}
}