{
  "type": "Feature",
  "properties": {
    "gn:admin1_code":"61",
    "gn:admin2_code":"54.0",
    "gn:asciiname":"Kiaunariskiai",
    "gn:country_code":"LT",
    "gn:dem":169,
    "gn:feature_class":"P",
    "gn:feature_code":"PPL",
    "gn:name":"Kiaunari\u0161kiai",
    "gn:population":0,
    "gn:timezone":"Europe/Vilnius",
    "iso:country":"LT",
    "name:lit_x_preferred":[
        "Kiaunari\u0161kiai"
    ],
    "wof:name":"Kiaunariskiai",
    "wof:placetype":"locality"
},
  "geometry": {"coordinates":[22.76111,55.59378],"type":"Point"}
}