{
  "type": "Feature",
  "properties": {
    "gn:admin1_code":"64",
    "gn:admin2_code":"62.0",
    "gn:asciiname":"Padvarys",
    "gn:country_code":"LT",
    "gn:dem":178,
    "gn:feature_class":"P",
    "gn:feature_code":"PPL",
    "gn:name":"Padvarys",
    "gn:population":0,
    "gn:timezone":"Europe/Vilnius",
    "iso:country":"LT",
    "name:lit_x_preferred":[
        "Padvarys"
    ],
    "wof:name":"Padvarys",
    "wof:placetype":"locality"
},
  "geometry": {"coordinates":[25.33741,55.15362],"type":"Point"}
}