{
  "type": "Feature",
  "properties": {
    "gn:admin1_code":"56.0",
    "gn:admin2_code":"11.0",
    "gn:asciiname":"Barkuniskis",
    "gn:country_code":"LT",
    "gn:dem":74,
    "gn:feature_class":"P",
    "gn:feature_code":"PPL",
    "gn:name":"Bark\u016bni\u0161kis",
    "gn:population":0,
    "gn:timezone":"Europe/Vilnius",
    "iso:country":"LT",
    "name:lit_x_preferred":[
        "Bark\u016bni\u0161kis"
    ],
    "wof:name":"Barkuniskis",
    "wof:placetype":"locality"
},
  "geometry": {"coordinates":[23.91755,54.45151],"type":"Point"}
}