{
  "type": "Feature",
  "properties": {
    "gn:admin1_code":"56",
    "gn:admin2_code":"59.0",
    "gn:asciiname":"Maisymai",
    "gn:country_code":"LT",
    "gn:dem":143,
    "gn:feature_class":"P",
    "gn:feature_code":"PPL",
    "gn:name":"Mai\u0161ymai",
    "gn:population":0,
    "gn:timezone":"Europe/Vilnius",
    "iso:country":"LT",
    "name:lit_x_preferred":[
        "Mai\u0161ymai"
    ],
    "wof:name":"Maisymai",
    "wof:placetype":"locality"
},
  "geometry": {"coordinates":[23.45627,54.30266999999999],"type":"Point"}
}