{
  "type": "Feature",
  "properties": {
    "gn:admin1_code":"61",
    "gn:admin2_code":"65.0",
    "gn:asciiname":"Gatauteliai",
    "gn:country_code":"LT",
    "gn:dem":52,
    "gn:feature_class":"P",
    "gn:feature_code":"PPL",
    "gn:name":"Gataut\u0117liai",
    "gn:population":0,
    "gn:timezone":"Europe/Vilnius",
    "iso:country":"LT",
    "name:lit_x_preferred":[
        "Gataut\u0117liai"
    ],
    "wof:name":"Gatauteliai",
    "wof:placetype":"locality"
},
  "geometry": {"coordinates":[23.95497,56.1775],"type":"Point"}
}