{
  "type": "Feature",
  "properties": {
    "gn:admin1_code":"58.0",
    "gn:admin2_code":"21.0",
    "gn:asciiname":"Ginduliai",
    "gn:country_code":"LT",
    "gn:dem":18,
    "gn:feature_class":"P",
    "gn:feature_code":"PPL",
    "gn:name":"Ginduliai",
    "gn:population":0,
    "gn:timezone":"Europe/Vilnius",
    "iso:country":"LT",
    "name:und_x_variant":[
        "Kruken-Gerge",
        "Ginduliai"
    ],
    "wof:name":"Ginduliai",
    "wof:placetype":"locality"
},
  "geometry": {"coordinates":[21.19665,55.72961],"type":"Point"}
}