{
  "type": "Feature",
  "properties": {
    "gn:admin1_code":"64.0",
    "gn:admin2_code":"82.0",
    "gn:asciiname":"Kirdeikiai",
    "gn:country_code":"LT",
    "gn:dem":154,
    "gn:feature_class":"P",
    "gn:feature_code":"PPL",
    "gn:name":"Kirdeikiai",
    "gn:population":0,
    "gn:timezone":"Europe/Vilnius",
    "iso:country":"LT",
    "name:eng_x_preferred":[
        "Kirdeikiai"
    ],
    "name:rus_x_preferred":[
        "\u041a\u0438\u0440\u0434\u0435\u0439\u043a\u044f\u0439"
    ],
    "name:und_x_variant":[
        "Kirdeykyay",
        "Kirdeiki\u0173"
    ],
    "wof:name":"Kirdeikiai",
    "wof:placetype":"locality"
},
  "geometry": {"coordinates":[25.93919,55.37645],"type":"Point"}
}