{
  "type": "Feature",
  "properties": {
    "gn:admin1_code":"65.0",
    "gn:admin2_code":"89.0",
    "gn:asciiname":"Mesliukai",
    "gn:country_code":"LT",
    "gn:dem":138,
    "gn:feature_class":"P",
    "gn:feature_code":"PPL",
    "gn:name":"Me\u0161liukai",
    "gn:population":0,
    "gn:timezone":"Europe/Vilnius",
    "iso:country":"LT",
    "name:lit_x_preferred":[
        "Me\u0161liukai"
    ],
    "wof:name":"Mesliukai",
    "wof:placetype":"locality"
},
  "geometry": {"coordinates":[25.04205,54.90572],"type":"Point"}
}