{
  "type": "Feature",
  "properties": {
    "gn:admin1_code":"60",
    "gn:admin2_code":"73.0",
    "gn:asciiname":"Buteniskis",
    "gn:country_code":"LT",
    "gn:dem":103,
    "gn:feature_class":"P",
    "gn:feature_code":"PPL",
    "gn:name":"But\u0117ni\u0161kis",
    "gn:population":0,
    "gn:timezone":"Europe/Vilnius",
    "iso:country":"LT",
    "name:lit_x_preferred":[
        "But\u0117ni\u0161kis"
    ],
    "wof:name":"Buteniskis",
    "wof:placetype":"locality"
},
  "geometry": {"coordinates":[25.54683,56.08538000000001],"type":"Point"}
}