{
  "type": "Feature",
  "properties": {
    "gn:admin1_code":"64.0",
    "gn:admin2_code":"62.0",
    "gn:asciiname":"Grauziniai",
    "gn:country_code":"LT",
    "gn:dem":153,
    "gn:feature_class":"P",
    "gn:feature_code":"PPL",
    "gn:name":"Grau\u017einiai",
    "gn:population":0,
    "gn:timezone":"Europe/Vilnius",
    "iso:country":"LT",
    "name:lit_x_preferred":[
        "Grau\u017einiai"
    ],
    "wof:name":"Grauziniai",
    "wof:placetype":"locality"
},
  "geometry": {"coordinates":[25.60719,55.08746],"type":"Point"}
}