{
  "type": "Feature",
  "properties": {
    "gn:admin1_code":"63.0",
    "gn:admin2_code":"61.0",
    "gn:asciiname":"Ketunai",
    "gn:country_code":"LT",
    "gn:dem":112,
    "gn:feature_class":"P",
    "gn:feature_code":"PPL",
    "gn:name":"Ket\u016bnai",
    "gn:population":0,
    "gn:timezone":"Europe/Vilnius",
    "iso:country":"LT",
    "name:und_x_variant":[
        "Ket\u016bn\u0173",
        "Kietuny",
        "Ketunyay",
        "Ket\u016bnai"
    ],
    "wof:name":"Ketunai",
    "wof:placetype":"locality"
},
  "geometry": {"coordinates":[22.18099,56.16996],"type":"Point"}
}