{
  "type": "Feature",
  "properties": {
    "gn:admin1_code":"63.0",
    "gn:admin2_code":"68.0",
    "gn:asciiname":"Deguciai",
    "gn:country_code":"LT",
    "gn:dem":125,
    "gn:feature_class":"P",
    "gn:feature_code":"PPL",
    "gn:name":"Degu\u010diai",
    "gn:population":0,
    "gn:timezone":"Europe/Vilnius",
    "iso:country":"LT",
    "name:lit_x_preferred":[
        "Degu\u010diai"
    ],
    "wof:name":"Deguciai",
    "wof:placetype":"locality"
},
  "geometry": {"coordinates":[22.04476,56.10486],"type":"Point"}
}