{
  "type": "Feature",
  "properties": {
    "gn:admin1_code":"56.0",
    "gn:admin2_code":"59.0",
    "gn:asciiname":"Sestokai",
    "gn:country_code":"LT",
    "gn:dem":121,
    "gn:feature_class":"P",
    "gn:feature_code":"PPL",
    "gn:name":"\u0160e\u0161tokai",
    "gn:population":0,
    "gn:timezone":"Europe/Vilnius",
    "iso:country":"LT",
    "name:ceb_x_preferred":[
        "\u0160e\u0161tokai"
    ],
    "name:deu_x_preferred":[
        "\u0160e\u0161tokai"
    ],
    "name:eng_x_preferred":[
        "\u0160e\u0161tokai"
    ],
    "name:est_x_preferred":[
        "\u0160e\u0161tokai"
    ],
    "name:fin_x_preferred":[
        "\u0160e\u0161tokai"
    ],
    "name:ita_x_preferred":[
        "\u0160e\u0161tokai"
    ],
    "name:lit_x_preferred":[
        "\u0160e\u0161tokai"
    ],
    "name:nld_x_preferred":[
        "\u0160e\u0161tokai"
    ],
    "name:pol_x_preferred":[
        "Szostak\u00f3w"
    ],
    "name:rus_x_preferred":[
        "\u0428\u0435\u0448\u0442\u043e\u043a\u0430\u0439"
    ],
    "name:swe_x_preferred":[
        "\u0160e\u0161tokai"
    ],
    "name:und_x_variant":[
        "Shostakov",
        "Shostakuv",
        "Sheshtokay",
        "Shestakov-Ostatni",
        "\u0160e\u0161tok\u0173",
        "Szostak\u00f3w",
        "\u0160e\u0161tokai"
    ],
    "wof:name":"Sestokai",
    "wof:placetype":"locality"
},
  "geometry": {"coordinates":[23.44545,54.35842],"type":"Point"}
}