{
  "type": "Feature",
  "properties": {
    "gn:admin1_code":"65",
    "gn:admin2_code":"89.0",
    "gn:asciiname":"Degsniai",
    "gn:country_code":"LT",
    "gn:dem":134,
    "gn:feature_class":"P",
    "gn:feature_code":"PPL",
    "gn:name":"Degsniai",
    "gn:population":0,
    "gn:timezone":"Europe/Vilnius",
    "iso:country":"LT",
    "name:lit_x_preferred":[
        "Degsniai"
    ],
    "wof:name":"Degsniai",
    "wof:placetype":"locality"
},
  "geometry": {"coordinates":[25.15992,55.12494],"type":"Point"}
}