{
  "type": "Feature",
  "properties": {
    "gn:admin1_code":"65",
    "gn:admin2_code":"42.0",
    "gn:asciiname":"Bukiskes",
    "gn:country_code":"LT",
    "gn:dem":142,
    "gn:feature_class":"P",
    "gn:feature_code":"PPL",
    "gn:name":"Buki\u0161k\u0117s",
    "gn:population":0,
    "gn:timezone":"Europe/Vilnius",
    "iso:country":"LT",
    "name:lit_x_preferred":[
        "Buki\u0161k\u0117s"
    ],
    "wof:name":"Bukiskes",
    "wof:placetype":"locality"
},
  "geometry": {"coordinates":[24.81649,54.73264],"type":"Point"}
}