{
  "type": "Feature",
  "properties": {
    "gn:admin1_code":"64",
    "gn:admin2_code":"45.0",
    "gn:asciiname":"Vastakiske",
    "gn:country_code":"LT",
    "gn:dem":155,
    "gn:feature_class":"P",
    "gn:feature_code":"PPL",
    "gn:name":"Vastaki\u0161k\u0117",
    "gn:population":0,
    "gn:timezone":"Europe/Vilnius",
    "iso:country":"LT",
    "name:lit_x_preferred":[
        "Vastaki\u0161k\u0117"
    ],
    "wof:name":"Vastakiske",
    "wof:placetype":"locality"
},
  "geometry": {"coordinates":[26.38863,55.34645],"type":"Point"}
}