{
  "type": "Feature",
  "properties": {
    "gn:admin1_code":"62.0",
    "gn:admin2_code":"94.0",
    "gn:asciiname":"Vadzgirys",
    "gn:country_code":"LT",
    "gn:dem":60,
    "gn:feature_class":"P",
    "gn:feature_code":"PPL",
    "gn:name":"Vad\u017egirys",
    "gn:population":0,
    "gn:timezone":"Europe/Vilnius",
    "iso:country":"LT",
    "name:eng_x_preferred":[
        "Vad\u017egirys"
    ],
    "name:rus_x_preferred":[
        "\u0412\u0430\u0434\u0436\u0433\u0438\u0440\u0438\u0441"
    ],
    "name:und_x_variant":[
        "Vodzhgiry",
        "Vad\u017egirio",
        "Vadzhgiris",
        "Vad\u017egiris"
    ],
    "wof:name":"Vadzgirys",
    "wof:placetype":"locality"
},
  "geometry": {"coordinates":[22.9203,55.25464],"type":"Point"}
}