{
  "type": "Feature",
  "properties": {
    "gn:admin1_code":"57",
    "gn:admin2_code":"19.0",
    "gn:asciiname":"Aukstkalniai",
    "gn:country_code":"LT",
    "gn:dem":84,
    "gn:feature_class":"P",
    "gn:feature_code":"PPL",
    "gn:name":"Auk\u0161tkalniai",
    "gn:population":0,
    "gn:timezone":"Europe/Vilnius",
    "iso:country":"LT",
    "name:lit_x_preferred":[
        "Auk\u0161tkalniai"
    ],
    "wof:name":"Aukstkalniai",
    "wof:placetype":"locality"
},
  "geometry": {"coordinates":[23.54551,55.05701],"type":"Point"}
}