{
  "type": "Feature",
  "properties": {
    "gn:admin1_code":"61.0",
    "gn:admin2_code":"47.0",
    "gn:asciiname":"Dameliai",
    "gn:country_code":"LT",
    "gn:dem":77,
    "gn:feature_class":"P",
    "gn:feature_code":"PPL",
    "gn:name":"Dameliai",
    "gn:population":0,
    "gn:timezone":"Europe/Vilnius",
    "iso:country":"LT",
    "name:und_x_variant":[
        "Dameli\u0173",
        "Damyalyay",
        "Damelyay",
        "Dameliai"
    ],
    "wof:name":"Dameliai",
    "wof:placetype":"locality"
},
  "geometry": {"coordinates":[23.25799,56.26935],"type":"Point"}
}