{
  "type": "Feature",
  "properties": {
    "gn:admin1_code":"60",
    "gn:admin2_code":"73.0",
    "gn:asciiname":"Mieleikiai",
    "gn:country_code":"LT",
    "gn:dem":138,
    "gn:feature_class":"P",
    "gn:feature_code":"PPL",
    "gn:name":"Mieleikiai",
    "gn:population":0,
    "gn:timezone":"Europe/Vilnius",
    "iso:country":"LT",
    "name:lit_x_preferred":[
        "Mieleikiai"
    ],
    "wof:name":"Mieleikiai",
    "wof:placetype":"locality"
},
  "geometry": {"coordinates":[25.60558,55.78048],"type":"Point"}
}