{
  "type": "Feature",
  "properties": {
    "gn:admin1_code":"65",
    "gn:admin2_code":"79.0",
    "gn:asciiname":"Uzilgiai",
    "gn:country_code":"LT",
    "gn:dem":155,
    "gn:feature_class":"P",
    "gn:feature_code":"PPL",
    "gn:name":"U\u017eilgiai",
    "gn:population":0,
    "gn:timezone":"Europe/Vilnius",
    "iso:country":"LT",
    "name:lit_x_preferred":[
        "U\u017eilgiai"
    ],
    "wof:name":"Uzilgiai",
    "wof:placetype":"locality"
},
  "geometry": {"coordinates":[24.7458,54.62513000000001],"type":"Point"}
}