{
  "type": "Feature",
  "properties": {
    "gn:admin1_code":"58",
    "gn:admin2_code":"21.0",
    "gn:asciiname":"Svepeliai",
    "gn:country_code":"LT",
    "gn:dem":13,
    "gn:feature_class":"P",
    "gn:feature_code":"PPL",
    "gn:name":"\u0160vepeliai",
    "gn:population":0,
    "gn:timezone":"Europe/Vilnius",
    "iso:country":"LT",
    "name:lit_x_preferred":[
        "\u0160vepeliai"
    ],
    "wof:name":"Svepeliai",
    "wof:placetype":"locality"
},
  "geometry": {"coordinates":[21.24659,55.68601999999999],"type":"Point"}
}