{
  "type": "Feature",
  "properties": {
    "gn:admin1_code":"59.0",
    "gn:admin2_code":"48.0",
    "gn:asciiname":"Aguonis",
    "gn:country_code":"LT",
    "gn:dem":140,
    "gn:feature_class":"P",
    "gn:feature_code":"PPL",
    "gn:name":"Aguonis",
    "gn:population":0,
    "gn:timezone":"Europe/Vilnius",
    "iso:country":"LT",
    "name:lit_x_preferred":[
        "Aguonis"
    ],
    "name:und_x_variant":[
        "Aguoni\u0161kiai"
    ],
    "wof:name":"Aguonis",
    "wof:placetype":"locality"
},
  "geometry": {"coordinates":[23.11771,54.36074],"type":"Point"}
}