{
  "type": "Feature",
  "properties": {
    "gn:admin1_code":"65",
    "gn:admin2_code":"79.0",
    "gn:asciiname":"Vanagai",
    "gn:country_code":"LT",
    "gn:dem":160,
    "gn:feature_class":"P",
    "gn:feature_code":"PPL",
    "gn:name":"Vanagai",
    "gn:population":0,
    "gn:timezone":"Europe/Vilnius",
    "iso:country":"LT",
    "name:lit_x_preferred":[
        "Vanagai"
    ],
    "wof:name":"Vanagai",
    "wof:placetype":"locality"
},
  "geometry": {"coordinates":[24.55438,54.53583],"type":"Point"}
}