{
  "type": "Feature",
  "properties": {
    "gn:admin1_code":"64",
    "gn:admin2_code":"43.0",
    "gn:asciiname":"Merkialaukiai",
    "gn:country_code":"LT",
    "gn:dem":115,
    "gn:feature_class":"P",
    "gn:feature_code":"PPL",
    "gn:name":"Merkialaukiai",
    "gn:population":0,
    "gn:timezone":"Europe/Vilnius",
    "iso:country":"LT",
    "name:lit_x_preferred":[
        "Merkialaukiai"
    ],
    "wof:name":"Merkialaukiai",
    "wof:placetype":"locality"
},
  "geometry": {"coordinates":[25.91624,55.83228],"type":"Point"}
}