{
  "type": "Feature",
  "properties": {
    "gn:admin1_code":"60.0",
    "gn:admin2_code":"27.0",
    "gn:asciiname":"Kairiai",
    "gn:country_code":"LT",
    "gn:dem":52,
    "gn:feature_class":"P",
    "gn:feature_code":"PPL",
    "gn:name":"Kairiai",
    "gn:population":0,
    "gn:timezone":"Europe/Vilnius",
    "iso:country":"LT",
    "name:und_x_variant":[
        "Keyry",
        "Kairiai"
    ],
    "wof:name":"Kairiai",
    "wof:placetype":"locality"
},
  "geometry": {"coordinates":[24.1192,55.7849],"type":"Point"}
}