{
  "type": "Feature",
  "properties": {
    "gn:admin1_code":"57.0",
    "gn:admin2_code":"72.0",
    "gn:asciiname":"Vailabai",
    "gn:country_code":"LT",
    "gn:dem":68,
    "gn:feature_class":"P",
    "gn:feature_code":"PPL",
    "gn:name":"Vailabai",
    "gn:population":0,
    "gn:timezone":"Europe/Vilnius",
    "iso:country":"LT",
    "name:und_x_variant":[
        "Vaylabay",
        "Vailab\u0173",
        "Vailabai"
    ],
    "wof:name":"Vailabai",
    "wof:placetype":"locality"
},
  "geometry": {"coordinates":[22.82416,55.3759],"type":"Point"}
}