{
  "type": "Feature",
  "properties": {
    "gn:admin1_code":"64",
    "gn:admin2_code":"62.0",
    "gn:asciiname":"Sodenai",
    "gn:country_code":"LT",
    "gn:dem":142,
    "gn:feature_class":"P",
    "gn:feature_code":"PPL",
    "gn:name":"Sod\u0117nai",
    "gn:population":0,
    "gn:timezone":"Europe/Vilnius",
    "iso:country":"LT",
    "name:lit_x_preferred":[
        "Sod\u0117nai"
    ],
    "wof:name":"Sodenai",
    "wof:placetype":"locality"
},
  "geometry": {"coordinates":[25.31467,55.22936],"type":"Point"}
}