{
  "type": "Feature",
  "properties": {
    "gn:admin1_code":"60",
    "gn:admin2_code":"67.0",
    "gn:asciiname":"Uzusienis II",
    "gn:country_code":"LT",
    "gn:dem":54,
    "gn:feature_class":"P",
    "gn:feature_code":"PPL",
    "gn:name":"U\u017eusienis II",
    "gn:population":0,
    "gn:timezone":"Europe/Vilnius",
    "iso:country":"LT",
    "name:lit_x_preferred":[
        "U\u017eusienis II"
    ],
    "wof:name":"Uzusienis II",
    "wof:placetype":"locality"
},
  "geometry": {"coordinates":[24.63911,56.06971],"type":"Point"}
}