{
  "type": "Feature",
  "properties": {
    "gn:admin1_code":"65",
    "gn:admin2_code":"42.0",
    "gn:asciiname":"Malavole",
    "gn:country_code":"LT",
    "gn:dem":107,
    "gn:feature_class":"P",
    "gn:feature_code":"PPL",
    "gn:name":"Malavol\u0117",
    "gn:population":0,
    "gn:timezone":"Europe/Vilnius",
    "iso:country":"LT",
    "name:lit_x_preferred":[
        "Malavol\u0117"
    ],
    "wof:name":"Malavole",
    "wof:placetype":"locality"
},
  "geometry": {"coordinates":[24.93227000000001,54.79885],"type":"Point"}
}