{
  "type": "Feature",
  "properties": {
    "gn:admin1_code":"62.0",
    "gn:admin2_code":"94.0",
    "gn:asciiname":"Terespolis",
    "gn:country_code":"LT",
    "gn:dem":66,
    "gn:feature_class":"P",
    "gn:feature_code":"PPL",
    "gn:name":"Terespolis",
    "gn:population":0,
    "gn:timezone":"Europe/Vilnius",
    "iso:country":"LT",
    "name:und_x_variant":[
        "Terespol\u2019",
        "B\u016bdos"
    ],
    "wof:name":"Terespolis",
    "wof:placetype":"locality"
},
  "geometry": {"coordinates":[23.25202,55.12514],"type":"Point"}
}