{
  "type": "Feature",
  "properties": {
    "gn:admin1_code":"62.0",
    "gn:admin2_code":"94.0",
    "gn:asciiname":"Ruksniai",
    "gn:country_code":"LT",
    "gn:dem":38,
    "gn:feature_class":"P",
    "gn:feature_code":"PPL",
    "gn:name":"Ruk\u0161niai",
    "gn:population":0,
    "gn:timezone":"Europe/Vilnius",
    "iso:country":"LT",
    "name:und_x_variant":[
        "Rukshni",
        "Ruk\u0161niai"
    ],
    "wof:name":"Ruksniai",
    "wof:placetype":"locality"
},
  "geometry": {"coordinates":[22.70784,55.12772],"type":"Point"}
}