{
  "type": "Feature",
  "properties": {
    "gn:admin1_code":"58.0",
    "gn:admin2_code":"56.0",
    "gn:asciiname":"Slaveitai",
    "gn:country_code":"LT",
    "gn:dem":39,
    "gn:feature_class":"P",
    "gn:feature_code":"PPL",
    "gn:name":"\u0160laveitai",
    "gn:population":0,
    "gn:timezone":"Europe/Vilnius",
    "iso:country":"LT",
    "name:lit_x_preferred":[
        "\u0160laveitai"
    ],
    "wof:name":"Slaveitai",
    "wof:placetype":"locality"
},
  "geometry": {"coordinates":[21.33625,56.03923],"type":"Point"}
}