{
  "type": "Feature",
  "properties": {
    "gn:admin1_code":"65.0",
    "gn:admin2_code":"13.0",
    "gn:asciiname":"Dukeliai",
    "gn:country_code":"LT",
    "gn:dem":210,
    "gn:feature_class":"P",
    "gn:feature_code":"PPL",
    "gn:name":"Dukeliai",
    "gn:population":0,
    "gn:timezone":"Europe/Vilnius",
    "iso:country":"LT",
    "name:und_x_variant":[
        "Dukele",
        "Dukeliai"
    ],
    "wof:name":"Dukeliai",
    "wof:placetype":"locality"
},
  "geometry": {"coordinates":[25.43023,54.59625],"type":"Point"}
}