{
  "type": "Feature",
  "properties": {
    "iso:country":"LT",
    "wof:name":"Centras",
    "wof:placetype":"neighbourhood"
},
  "geometry": {"coordinates":[25.26561779316019,54.68721021962617],"type":"Point"}
}