{
  "type": "Feature",
  "properties": {
    "gn:admin1_code":"62.0",
    "gn:admin2_code":"63.0",
    "gn:asciiname":"Ropkojai",
    "gn:country_code":"LT",
    "gn:dem":41,
    "gn:feature_class":"P",
    "gn:feature_code":"PPL",
    "gn:name":"Ropkojai",
    "gn:population":0,
    "gn:timezone":"Europe/Vilnius",
    "iso:country":"LT",
    "name:deu_x_preferred":[
        "Robkojen"
    ],
    "name:und_x_variant":[
        "Ropkoyay",
        "Ropkojai",
        "Robkojen"
    ],
    "wof:name":"Ropkojai",
    "wof:placetype":"locality"
},
  "geometry": {"coordinates":[21.9996,55.22946999999999],"type":"Point"}
}