{
  "type": "Feature",
  "properties": {
    "gn:admin1_code":"58.0",
    "gn:admin2_code":"21.0",
    "gn:asciiname":"Budvieciai",
    "gn:country_code":"LT",
    "gn:dem":6,
    "gn:feature_class":"P",
    "gn:feature_code":"PPL",
    "gn:name":"B\u016bdvie\u010diai",
    "gn:population":0,
    "gn:timezone":"Europe/Vilnius",
    "iso:country":"LT",
    "name:und_x_variant":[
        "Budv\u2019ete",
        "B\u016bdvie\u010diai"
    ],
    "wof:name":"Budvieciai",
    "wof:placetype":"locality"
},
  "geometry": {"coordinates":[21.36376,55.57166],"type":"Point"}
}