{
  "type": "Feature",
  "properties": {
    "gn:admin1_code":"64",
    "gn:admin2_code":"43.0",
    "gn:asciiname":"Burniai",
    "gn:country_code":"LT",
    "gn:dem":147,
    "gn:feature_class":"P",
    "gn:feature_code":"PPL",
    "gn:name":"Burniai",
    "gn:population":0,
    "gn:timezone":"Europe/Vilnius",
    "iso:country":"LT",
    "name:lit_x_preferred":[
        "Burniai"
    ],
    "wof:name":"Burniai",
    "wof:placetype":"locality"
},
  "geometry": {"coordinates":[26.55822,55.64423000000001],"type":"Point"}
}