{
  "type": "Feature",
  "properties": {
    "gn:admin1_code":"65",
    "gn:admin2_code":"13.0",
    "gn:asciiname":"Mikaline",
    "gn:country_code":"LT",
    "gn:dem":190,
    "gn:feature_class":"P",
    "gn:feature_code":"PPL",
    "gn:name":"Mikalin\u0117",
    "gn:population":0,
    "gn:timezone":"Europe/Vilnius",
    "iso:country":"LT",
    "name:lit_x_preferred":[
        "Mikalin\u0117"
    ],
    "wof:name":"Mikaline",
    "wof:placetype":"locality"
},
  "geometry": {"coordinates":[25.38465,54.56173],"type":"Point"}
}