{
  "type": "Feature",
  "properties": {
    "gn:admin1_code":"56.0",
    "gn:admin2_code":"59.0",
    "gn:asciiname":"Rudamina",
    "gn:country_code":"LT",
    "gn:dem":161,
    "gn:feature_class":"P",
    "gn:feature_code":"PPL",
    "gn:name":"Rudamina",
    "gn:population":0,
    "gn:timezone":"Europe/Vilnius",
    "iso:country":"LT",
    "name:eng_x_preferred":[
        "Rudamina"
    ],
    "name:est_x_preferred":[
        "Rudamina"
    ],
    "name:heb_x_preferred":[
        "\u05e8\u05d5\u05d3\u05de\u05d9\u05df"
    ],
    "name:lit_x_preferred":[
        "Rudamina"
    ],
    "name:nld_x_preferred":[
        "Rudamina"
    ],
    "name:pol_x_preferred":[
        "Urdomin"
    ],
    "name:rus_x_preferred":[
        "\u0420\u0443\u0434\u0430\u043c\u0438\u043d\u0430"
    ],
    "name:und_x_variant":[
        "Rudomin",
        "Rudaminos",
        "Urdomin",
        "Rudamina"
    ],
    "wof:name":"Rudamina",
    "wof:placetype":"locality"
},
  "geometry": {"coordinates":[23.45068,54.2886],"type":"Point"}
}