{
  "type": "Feature",
  "properties": {
    "gn:admin1_code":"64",
    "gn:admin2_code":"34.0",
    "gn:asciiname":"Zalioji",
    "gn:country_code":"LT",
    "gn:dem":86,
    "gn:feature_class":"P",
    "gn:feature_code":"PPL",
    "gn:name":"\u017dalioji",
    "gn:population":0,
    "gn:timezone":"Europe/Vilnius",
    "iso:country":"LT",
    "name:lit_x_preferred":[
        "\u017dalioji"
    ],
    "wof:name":"Zalioji",
    "wof:placetype":"locality"
},
  "geometry": {"coordinates":[25.42563,55.62409],"type":"Point"}
}