{
  "type": "Feature",
  "properties": {
    "gn:admin1_code":"56.0",
    "gn:admin2_code":"38.0",
    "gn:asciiname":"Gudakiemis",
    "gn:country_code":"LT",
    "gn:dem":125,
    "gn:feature_class":"P",
    "gn:feature_code":"PPL",
    "gn:name":"Gudakiemis",
    "gn:population":0,
    "gn:timezone":"Europe/Vilnius",
    "iso:country":"LT",
    "name:ceb_x_preferred":[
        "Gudakiemis"
    ],
    "name:eng_x_preferred":[
        "Gudakiemis"
    ],
    "name:lit_x_preferred":[
        "Gudakiemis"
    ],
    "name:rus_x_preferred":[
        "\u0413\u0443\u0434\u0430\u043a\u0435\u043c\u0438\u0441"
    ],
    "name:swe_x_preferred":[
        "Gudakiemis"
    ],
    "name:und_x_variant":[
        "Russkaya-Ves\u2019",
        "Gudakiemio",
        "Gudakiemis"
    ],
    "wof:name":"Gudakiemis",
    "wof:placetype":"locality"
},
  "geometry": {"coordinates":[24.2475,54.20582],"type":"Point"}
}