{
  "type": "Feature",
  "properties": {
    "gn:admin1_code":"65",
    "gn:admin2_code":"86.0",
    "gn:asciiname":"Kulbokiske",
    "gn:country_code":"LT",
    "gn:dem":171,
    "gn:feature_class":"P",
    "gn:feature_code":"PPL",
    "gn:name":"Kulboki\u0161k\u0117",
    "gn:population":0,
    "gn:timezone":"Europe/Vilnius",
    "iso:country":"LT",
    "name:lit_x_preferred":[
        "Kulboki\u0161k\u0117"
    ],
    "wof:name":"Kulbokiske",
    "wof:placetype":"locality"
},
  "geometry": {"coordinates":[26.15492,55.00791],"type":"Point"}
}