{
  "type": "Feature",
  "properties": {
    "gn:admin1_code":"57",
    "gn:admin2_code":"69.0",
    "gn:asciiname":"Jiezno Kolonijos",
    "gn:country_code":"LT",
    "gn:dem":111,
    "gn:feature_class":"P",
    "gn:feature_code":"PPL",
    "gn:name":"Jiezno Kolonijos",
    "gn:population":0,
    "gn:timezone":"Europe/Vilnius",
    "iso:country":"LT",
    "name:lit_x_preferred":[
        "Jiezno Kolonijos"
    ],
    "wof:name":"Jiezno Kolonijos",
    "wof:placetype":"locality"
},
  "geometry": {"coordinates":[24.17107,54.60592],"type":"Point"}
}