{
  "type": "Feature",
  "properties": {
    "gn:admin1_code":"58.0",
    "gn:admin2_code":"55.0",
    "gn:asciiname":"Kopgalis",
    "gn:country_code":"LT",
    "gn:dem":0,
    "gn:feature_class":"P",
    "gn:feature_code":"PPL",
    "gn:name":"Kopgalis",
    "gn:population":0,
    "gn:timezone":"Europe/Vilnius",
    "iso:country":"LT",
    "name:lit_x_preferred":[
        "Kopgalis"
    ],
    "wof:name":"Kopgalis",
    "wof:placetype":"locality"
},
  "geometry": {"coordinates":[21.10374,55.71478000000001],"type":"Point"}
}