{
  "type": "Feature",
  "properties": {
    "gn:admin1_code":"62.0",
    "gn:admin2_code":"87.0",
    "gn:asciiname":"Sodale",
    "gn:country_code":"LT",
    "gn:dem":106,
    "gn:feature_class":"P",
    "gn:feature_code":"PPL",
    "gn:name":"Sodal\u0117",
    "gn:population":0,
    "gn:timezone":"Europe/Vilnius",
    "iso:country":"LT",
    "name:und_x_variant":[
        "D\u017eiugin\u0117liai",
        "Sodal\u0117"
    ],
    "wof:name":"Sodale",
    "wof:placetype":"locality"
},
  "geometry": {"coordinates":[21.98121,55.53806],"type":"Point"}
}