{
  "type": "Feature",
  "properties": {
    "gn:admin1_code":"60",
    "gn:admin2_code":"73.0",
    "gn:asciiname":"Vanagyne",
    "gn:country_code":"LT",
    "gn:dem":126,
    "gn:feature_class":"P",
    "gn:feature_code":"PPL",
    "gn:name":"Vanagyn\u0117",
    "gn:population":0,
    "gn:timezone":"Europe/Vilnius",
    "iso:country":"LT",
    "name:lit_x_preferred":[
        "Vanagyn\u0117"
    ],
    "wof:name":"Vanagyne",
    "wof:placetype":"locality"
},
  "geometry": {"coordinates":[25.75415,56.0464],"type":"Point"}
}