{
  "type": "Feature",
  "properties": {
    "gn:admin1_code":"63.0",
    "gn:admin2_code":"61.0",
    "gn:asciiname":"Maigai",
    "gn:country_code":"LT",
    "gn:dem":68,
    "gn:feature_class":"P",
    "gn:feature_code":"PPL",
    "gn:name":"Maigai",
    "gn:population":0,
    "gn:timezone":"Europe/Vilnius",
    "iso:country":"LT",
    "name:und_x_variant":[
        "Maygay",
        "Maig\u0173",
        "Maigai"
    ],
    "wof:name":"Maigai",
    "wof:placetype":"locality"
},
  "geometry": {"coordinates":[22.45525,56.27405],"type":"Point"}
}