{
  "type": "Feature",
  "properties": {
    "gn:admin1_code":"65",
    "gn:admin2_code":"89.0",
    "gn:asciiname":"Nukovscizna",
    "gn:country_code":"LT",
    "gn:dem":131,
    "gn:feature_class":"P",
    "gn:feature_code":"PPL",
    "gn:name":"Nukov\u0161\u010dizna",
    "gn:population":0,
    "gn:timezone":"Europe/Vilnius",
    "iso:country":"LT",
    "name:lit_x_preferred":[
        "Nukov\u0161\u010dizna"
    ],
    "wof:name":"Nukovscizna",
    "wof:placetype":"locality"
},
  "geometry": {"coordinates":[25.0453,54.96199],"type":"Point"}
}