{
  "type": "Feature",
  "properties": {
    "gn:admin1_code":"64",
    "gn:admin2_code":"45.0",
    "gn:asciiname":"Gaveikiske",
    "gn:country_code":"LT",
    "gn:dem":183,
    "gn:feature_class":"P",
    "gn:feature_code":"PPL",
    "gn:name":"Gaveiki\u0161k\u0117",
    "gn:population":0,
    "gn:timezone":"Europe/Vilnius",
    "iso:country":"LT",
    "name:lit_x_preferred":[
        "Gaveiki\u0161k\u0117"
    ],
    "wof:name":"Gaveikiske",
    "wof:placetype":"locality"
},
  "geometry": {"coordinates":[26.32535,55.40814],"type":"Point"}
}