{
  "type": "Feature",
  "properties": {
    "gn:admin1_code":"59",
    "gn:admin2_code":"48.0",
    "gn:asciiname":"Krijobaliai",
    "gn:country_code":"LT",
    "gn:dem":177,
    "gn:feature_class":"P",
    "gn:feature_code":"PPL",
    "gn:name":"Krijobaliai",
    "gn:population":0,
    "gn:timezone":"Europe/Vilnius",
    "iso:country":"LT",
    "name:lit_x_preferred":[
        "Krijobaliai"
    ],
    "wof:name":"Krijobaliai",
    "wof:placetype":"locality"
},
  "geometry": {"coordinates":[23.04854,54.44613],"type":"Point"}
}