{
  "type": "Feature",
  "properties": {
    "gn:admin1_code":"62.0",
    "gn:admin2_code":"94.0",
    "gn:asciiname":"Seredzius",
    "gn:country_code":"LT",
    "gn:dem":61,
    "gn:feature_class":"P",
    "gn:feature_code":"PPL",
    "gn:name":"Sered\u017eius",
    "gn:population":0,
    "gn:timezone":"Europe/Vilnius",
    "iso:country":"LT",
    "name:ceb_x_preferred":[
        "Sered\u017eius"
    ],
    "name:est_x_preferred":[
        "Sered\u017eius"
    ],
    "name:fas_x_preferred":[
        "\u0633\u0631\u0698\u06cc\u0648\u0633"
    ],
    "name:fra_x_preferred":[
        "Sered\u017eius"
    ],
    "name:lit_x_preferred":[
        "Sered\u017eius"
    ],
    "name:pol_x_preferred":[
        "\u015aredniki"
    ],
    "name:swe_x_preferred":[
        "Sered\u017eius"
    ],
    "name:und_x_variant":[
        "Sredniki",
        "Srednike",
        "Sered\u017eia\u016bs",
        "Seredzhus",
        "Seredzhyus"
    ],
    "wof:name":"Seredzius",
    "wof:placetype":"locality"
},
  "geometry": {"coordinates":[23.41559,55.08228],"type":"Point"}
}