{
  "type": "Feature",
  "properties": {
    "gn:admin1_code":"65.0",
    "gn:admin2_code":"81.0",
    "gn:asciiname":"Jurgelionys",
    "gn:country_code":"LT",
    "gn:dem":82,
    "gn:feature_class":"P",
    "gn:feature_code":"PPL",
    "gn:name":"Jurgelionys",
    "gn:population":0,
    "gn:timezone":"Europe/Vilnius",
    "iso:country":"LT",
    "name:und_x_variant":[
        "Yurgelyantse",
        "Jurgelion\u0173",
        "Yurgelionis",
        "Jurgelioni\u0173",
        "Jurgelionys"
    ],
    "wof:name":"Jurgelionys",
    "wof:placetype":"locality"
},
  "geometry": {"coordinates":[24.60615,55.35979],"type":"Point"}
}