{
  "type": "Feature",
  "properties": {
    "gn:admin1_code":"60.0",
    "gn:admin2_code":"36.0",
    "gn:asciiname":"Nariskiai",
    "gn:country_code":"LT",
    "gn:dem":58,
    "gn:feature_class":"P",
    "gn:feature_code":"PPL",
    "gn:name":"Nari\u0161kiai",
    "gn:population":0,
    "gn:timezone":"Europe/Vilnius",
    "iso:country":"LT",
    "name:und_x_variant":[
        "Naryshki",
        "Nari\u0161kiai"
    ],
    "wof:name":"Nariskiai",
    "wof:placetype":"locality"
},
  "geometry": {"coordinates":[24.68057,55.99502],"type":"Point"}
}