{
  "type": "Feature",
  "properties": {
    "gn:admin1_code":"63",
    "gn:admin2_code":"78.0",
    "gn:asciiname":"Sledai",
    "gn:country_code":"LT",
    "gn:dem":127,
    "gn:feature_class":"P",
    "gn:feature_code":"PPL",
    "gn:name":"Sl\u0117dai",
    "gn:population":0,
    "gn:timezone":"Europe/Vilnius",
    "iso:country":"LT",
    "name:lit_x_preferred":[
        "Sl\u0117dai"
    ],
    "wof:name":"Sledai",
    "wof:placetype":"locality"
},
  "geometry": {"coordinates":[22.08482,56.07336],"type":"Point"}
}