{
  "type": "Feature",
  "properties": {
    "gn:admin1_code":"57",
    "gn:admin2_code":"49.0",
    "gn:asciiname":"Pavuolis",
    "gn:country_code":"LT",
    "gn:dem":75,
    "gn:feature_class":"P",
    "gn:feature_code":"PPL",
    "gn:name":"Pavuolis",
    "gn:population":0,
    "gn:timezone":"Europe/Vilnius",
    "iso:country":"LT",
    "name:lit_x_preferred":[
        "Pavuolis"
    ],
    "wof:name":"Pavuolis",
    "wof:placetype":"locality"
},
  "geometry": {"coordinates":[24.33158,54.82189],"type":"Point"}
}