{
  "type": "Feature",
  "properties": {
    "gn:admin1_code":"65.0",
    "gn:admin2_code":"79.0",
    "gn:asciiname":"Gudakiemis",
    "gn:country_code":"LT",
    "gn:dem":144,
    "gn:feature_class":"P",
    "gn:feature_code":"PPL",
    "gn:name":"Gudakiemis",
    "gn:population":0,
    "gn:timezone":"Europe/Vilnius",
    "iso:country":"LT",
    "name:ceb_x_preferred":[
        "Gudakiemis"
    ],
    "name:lit_x_preferred":[
        "Gudakiemis"
    ],
    "name:swe_x_preferred":[
        "Gudakiemis"
    ],
    "name:und_x_variant":[
        "Gudakemyay",
        "Gudakiemio"
    ],
    "wof:name":"Gudakiemis",
    "wof:placetype":"locality"
},
  "geometry": {"coordinates":[24.7236,54.48003000000001],"type":"Point"}
}