{
  "type": "Feature",
  "properties": {
    "gn:admin1_code":"65.0",
    "gn:admin2_code":"85.0",
    "gn:asciiname":"Malakonys",
    "gn:country_code":"LT",
    "gn:dem":193,
    "gn:feature_class":"P",
    "gn:feature_code":"PPL",
    "gn:name":"Malakonys",
    "gn:population":0,
    "gn:timezone":"Europe/Vilnius",
    "iso:country":"LT",
    "name:und_x_variant":[
        "Malakhovtsy",
        "Malakonis",
        "Malakonys"
    ],
    "wof:name":"Malakonys",
    "wof:placetype":"locality"
},
  "geometry": {"coordinates":[25.4884,54.42892],"type":"Point"}
}