{
  "type": "Feature",
  "properties": {
    "gn:admin1_code":"65.0",
    "gn:admin2_code":"81.0",
    "gn:asciiname":"Belazariskiai",
    "gn:country_code":"LT",
    "gn:dem":93,
    "gn:feature_class":"P",
    "gn:feature_code":"PPL",
    "gn:name":"Belazari\u0161kiai",
    "gn:population":0,
    "gn:timezone":"Europe/Vilnius",
    "iso:country":"LT",
    "name:lit_x_preferred":[
        "Belazari\u0161kiai"
    ],
    "name:und_x_variant":[
        "Baltazarishkyay",
        "Bielazari\u0161kiai"
    ],
    "wof:name":"Belazariskiai",
    "wof:placetype":"locality"
},
  "geometry": {"coordinates":[24.47848,55.26261],"type":"Point"}
}