{
  "type": "Feature",
  "properties": {
    "gn:admin1_code":"62.0",
    "gn:admin2_code":"87.0",
    "gn:asciiname":"Tubines I",
    "gn:country_code":"LT",
    "gn:dem":139,
    "gn:feature_class":"P",
    "gn:feature_code":"PPL",
    "gn:name":"T\u016bbin\u0117s I",
    "gn:population":0,
    "gn:timezone":"Europe/Vilnius",
    "iso:country":"LT",
    "name:und_x_variant":[
        "T\u016bbin\u0117s I",
        "Tubyn\u0117s",
        "T\u016bbin\u0117s"
    ],
    "wof:name":"Tubines I",
    "wof:placetype":"locality"
},
  "geometry": {"coordinates":[22.26079,55.5267],"type":"Point"}
}