{
  "type": "Feature",
  "properties": {
    "gn:admin1_code":"61",
    "gn:admin2_code":"29.0",
    "gn:asciiname":"Oliesinas",
    "gn:country_code":"LT",
    "gn:dem":102,
    "gn:feature_class":"P",
    "gn:feature_code":"PPL",
    "gn:name":"Oliesinas",
    "gn:population":0,
    "gn:timezone":"Europe/Vilnius",
    "iso:country":"LT",
    "name:lit_x_preferred":[
        "Oliesinas"
    ],
    "wof:name":"Oliesinas",
    "wof:placetype":"locality"
},
  "geometry": {"coordinates":[22.90027000000001,56.00708],"type":"Point"}
}