{
  "type": "Feature",
  "properties": {
    "gn:admin1_code":"56",
    "gn:admin2_code":"38.0",
    "gn:asciiname":"Kirklionys",
    "gn:country_code":"LT",
    "gn:dem":126,
    "gn:feature_class":"P",
    "gn:feature_code":"PPL",
    "gn:name":"Kirklionys",
    "gn:population":0,
    "gn:timezone":"Europe/Vilnius",
    "iso:country":"LT",
    "name:lit_x_preferred":[
        "Kirklionys"
    ],
    "wof:name":"Kirklionys",
    "wof:placetype":"locality"
},
  "geometry": {"coordinates":[24.51773,54.34],"type":"Point"}
}