{
  "type": "Feature",
  "properties": {
    "gn:admin1_code":"56",
    "gn:admin2_code":"11.0",
    "gn:asciiname":"Aniskis",
    "gn:country_code":"LT",
    "gn:dem":90,
    "gn:feature_class":"P",
    "gn:feature_code":"PPL",
    "gn:name":"Ani\u0161kis",
    "gn:population":0,
    "gn:timezone":"Europe/Vilnius",
    "iso:country":"LT",
    "name:lit_x_preferred":[
        "Ani\u0161kis"
    ],
    "wof:name":"Aniskis",
    "wof:placetype":"locality"
},
  "geometry": {"coordinates":[23.87607,54.41451],"type":"Point"}
}