{
  "type": "Feature",
  "properties": {
    "gn:admin1_code":"60",
    "gn:admin2_code":"27.0",
    "gn:asciiname":"Algirdava",
    "gn:country_code":"LT",
    "gn:dem":55,
    "gn:feature_class":"P",
    "gn:feature_code":"PPL",
    "gn:name":"Algirdava",
    "gn:population":0,
    "gn:timezone":"Europe/Vilnius",
    "iso:country":"LT",
    "name:lit_x_preferred":[
        "Algirdava"
    ],
    "wof:name":"Algirdava",
    "wof:placetype":"locality"
},
  "geometry": {"coordinates":[24.08403,55.68819000000001],"type":"Point"}
}