{
  "type": "Feature",
  "properties": {
    "gn:admin1_code":"63.0",
    "gn:admin2_code":"61.0",
    "gn:asciiname":"Rekeciai",
    "gn:country_code":"LT",
    "gn:dem":74,
    "gn:feature_class":"P",
    "gn:feature_code":"PPL",
    "gn:name":"Reke\u010diai",
    "gn:population":0,
    "gn:timezone":"Europe/Vilnius",
    "iso:country":"LT",
    "name:lit_x_preferred":[
        "Reke\u010diai"
    ],
    "name:und_x_variant":[
        "Rekechyay",
        "Reke\u010di\u0173"
    ],
    "wof:name":"Rekeciai",
    "wof:placetype":"locality"
},
  "geometry": {"coordinates":[22.52745,56.26868],"type":"Point"}
}