{
  "type": "Feature",
  "properties": {
    "iso:country":"LT",
    "wof:name":"Didieji Pupojai",
    "wof:placetype":"neighbourhood"
},
  "geometry": {"coordinates":[25.39015818480235,54.71644688737106],"type":"Point"}
}