{
  "type": "Feature",
  "properties": {
    "gn:admin1_code":"58",
    "gn:admin2_code":"75.0",
    "gn:asciiname":"Palsiai",
    "gn:country_code":"LT",
    "gn:dem":41,
    "gn:feature_class":"P",
    "gn:feature_code":"PPL",
    "gn:name":"Pal\u0161iai",
    "gn:population":0,
    "gn:timezone":"Europe/Vilnius",
    "iso:country":"LT",
    "name:lit_x_preferred":[
        "Pal\u0161iai"
    ],
    "wof:name":"Palsiai",
    "wof:placetype":"locality"
},
  "geometry": {"coordinates":[21.523,56.11545],"type":"Point"}
}