{
  "type": "Feature",
  "properties": {
    "gn:admin1_code":"62.0",
    "gn:admin2_code":"63.0",
    "gn:asciiname":"Mikytai",
    "gn:country_code":"LT",
    "gn:dem":14,
    "gn:feature_class":"P",
    "gn:feature_code":"PPL",
    "gn:name":"Mikytai",
    "gn:population":0,
    "gn:timezone":"Europe/Vilnius",
    "iso:country":"LT",
    "name:und_x_variant":[
        "Mikitay",
        "Mikytai"
    ],
    "wof:name":"Mikytai",
    "wof:placetype":"locality"
},
  "geometry": {"coordinates":[21.95062,55.1236],"type":"Point"}
}