{
  "type": "Feature",
  "properties": {
    "gn:admin1_code":"64",
    "gn:admin2_code":"82.0",
    "gn:asciiname":"Blusiskes",
    "gn:country_code":"LT",
    "gn:dem":192,
    "gn:feature_class":"P",
    "gn:feature_code":"PPL",
    "gn:name":"Blusi\u0161k\u0117s",
    "gn:population":0,
    "gn:timezone":"Europe/Vilnius",
    "iso:country":"LT",
    "name:lit_x_preferred":[
        "Blusi\u0161k\u0117s"
    ],
    "wof:name":"Blusiskes",
    "wof:placetype":"locality"
},
  "geometry": {"coordinates":[25.89354,55.54919],"type":"Point"}
}