{
  "type": "Feature",
  "properties": {
    "gn:admin1_code":"56.0",
    "gn:admin2_code":"11.0",
    "gn:asciiname":"Makniunai",
    "gn:country_code":"LT",
    "gn:dem":131,
    "gn:feature_class":"P",
    "gn:feature_code":"PPL",
    "gn:name":"Makni\u016bnai",
    "gn:population":0,
    "gn:timezone":"Europe/Vilnius",
    "iso:country":"LT",
    "name:lit_x_preferred":[
        "Makni\u016bnai"
    ],
    "wof:name":"Makniunai",
    "wof:placetype":"locality"
},
  "geometry": {"coordinates":[24.08413,54.24316999999999],"type":"Point"}
}