{
  "type": "Feature",
  "properties": {
    "gn:admin1_code":"60",
    "gn:admin2_code":"27.0",
    "gn:asciiname":"Marimpolis",
    "gn:country_code":"LT",
    "gn:dem":52,
    "gn:feature_class":"P",
    "gn:feature_code":"PPL",
    "gn:name":"Marimpolis",
    "gn:population":0,
    "gn:timezone":"Europe/Vilnius",
    "iso:country":"LT",
    "name:lit_x_preferred":[
        "Marimpolis"
    ],
    "wof:name":"Marimpolis",
    "wof:placetype":"locality"
},
  "geometry": {"coordinates":[24.25869,55.6593],"type":"Point"}
}