{
  "type": "Feature",
  "properties": {
    "gn:admin1_code":"57.0",
    "gn:admin2_code":"19.0",
    "gn:asciiname":"Urneziai",
    "gn:country_code":"LT",
    "gn:dem":43,
    "gn:feature_class":"P",
    "gn:feature_code":"PPL",
    "gn:name":"Urn\u0117\u017eiai",
    "gn:population":0,
    "gn:timezone":"Europe/Vilnius",
    "iso:country":"LT",
    "name:und_x_variant":[
        "Urnyazhyay",
        "Urnyazhe",
        "Urn\u0117\u017eiai"
    ],
    "wof:name":"Urneziai",
    "wof:placetype":"locality"
},
  "geometry": {"coordinates":[23.84077000000001,55.14127],"type":"Point"}
}