{
  "type": "Feature",
  "properties": {
    "gn:admin1_code":"60.0",
    "gn:admin2_code":"27.0",
    "gn:asciiname":"Pasiliai I",
    "gn:country_code":"LT",
    "gn:dem":58,
    "gn:feature_class":"P",
    "gn:feature_code":"PPL",
    "gn:name":"Pa\u0161iliai I",
    "gn:population":0,
    "gn:timezone":"Europe/Vilnius",
    "iso:country":"LT",
    "name:lit_x_preferred":[
        "Pa\u0161iliai I"
    ],
    "name:und_x_variant":[
        "Poshile",
        "Pa\u0161iliai"
    ],
    "wof:name":"Pasiliai I",
    "wof:placetype":"locality"
},
  "geometry": {"coordinates":[24.34714,55.63842],"type":"Point"}
}