{
  "type": "Feature",
  "properties": {
    "gn:admin1_code":"60.0",
    "gn:admin2_code":"73.0",
    "gn:asciiname":"Apascia",
    "gn:country_code":"LT",
    "gn:dem":85,
    "gn:feature_class":"P",
    "gn:feature_code":"PPL",
    "gn:name":"Apa\u0161\u010dia",
    "gn:population":0,
    "gn:timezone":"Europe/Vilnius",
    "iso:country":"LT",
    "name:und_x_variant":[
        "Apas\u010diai",
        "Apa\u0161\u010dia"
    ],
    "wof:name":"Apascia",
    "wof:placetype":"locality"
},
  "geometry": {"coordinates":[25.18503,56.04416],"type":"Point"}
}