{
  "type": "Feature",
  "properties": {
    "gn:admin1_code":"58",
    "gn:admin2_code":"75.0",
    "gn:asciiname":"Drupiai",
    "gn:country_code":"LT",
    "gn:dem":74,
    "gn:feature_class":"P",
    "gn:feature_code":"PPL",
    "gn:name":"Drupiai",
    "gn:population":0,
    "gn:timezone":"Europe/Vilnius",
    "iso:country":"LT",
    "name:lit_x_preferred":[
        "Drupiai"
    ],
    "wof:name":"Drupiai",
    "wof:placetype":"locality"
},
  "geometry": {"coordinates":[21.6822,56.20923000000001],"type":"Point"}
}