{
  "type": "Feature",
  "properties": {
    "gn:admin1_code":"61",
    "gn:admin2_code":"29.0",
    "gn:asciiname":"Silkalnis",
    "gn:country_code":"LT",
    "gn:dem":99,
    "gn:feature_class":"P",
    "gn:feature_code":"PPL",
    "gn:name":"\u0160ilkalnis",
    "gn:population":0,
    "gn:timezone":"Europe/Vilnius",
    "iso:country":"LT",
    "name:lit_x_preferred":[
        "\u0160ilkalnis"
    ],
    "wof:name":"Silkalnis",
    "wof:placetype":"locality"
},
  "geometry": {"coordinates":[22.91231,55.87431],"type":"Point"}
}