{
  "type": "Feature",
  "properties": {
    "gn:admin1_code":"58.0",
    "gn:admin2_code":"21.0",
    "gn:asciiname":"Bruzdeilynas",
    "gn:country_code":"LT",
    "gn:dem":12,
    "gn:feature_class":"P",
    "gn:feature_code":"PPL",
    "gn:name":"Bruzdeilynas",
    "gn:population":0,
    "gn:timezone":"Europe/Vilnius",
    "iso:country":"LT",
    "name:und_x_variant":[
        "Bruzdeilynai",
        "Brusdaylinen",
        "Bruzdeilynas"
    ],
    "wof:name":"Bruzdeilynas",
    "wof:placetype":"locality"
},
  "geometry": {"coordinates":[21.11551,55.84944],"type":"Point"}
}