{
  "type": "Feature",
  "properties": {
    "gn:admin1_code":"60.0",
    "gn:admin2_code":"36.0",
    "gn:asciiname":"Mazoji Panemune",
    "gn:country_code":"LT",
    "gn:dem":31,
    "gn:feature_class":"P",
    "gn:feature_code":"PPL",
    "gn:name":"Ma\u017eoji Panemun\u0117",
    "gn:population":0,
    "gn:timezone":"Europe/Riga",
    "iso:country":"LT",
    "name:und_x_variant":[
        "Mazh-Panyamune",
        "Ma\u017eoji Panemun\u0117"
    ],
    "wof:name":"Mazoji Panemune",
    "wof:placetype":"locality"
},
  "geometry": {"coordinates":[24.59212,56.33279],"type":"Point"}
}