{
  "type": "Feature",
  "properties": {
    "gn:admin1_code":"60",
    "gn:admin2_code":"73.0",
    "gn:asciiname":"Gojiskis",
    "gn:country_code":"LT",
    "gn:dem":156,
    "gn:feature_class":"P",
    "gn:feature_code":"PPL",
    "gn:name":"Goji\u0161kis",
    "gn:population":0,
    "gn:timezone":"Europe/Vilnius",
    "iso:country":"LT",
    "name:lit_x_preferred":[
        "Goji\u0161kis"
    ],
    "wof:name":"Gojiskis",
    "wof:placetype":"locality"
},
  "geometry": {"coordinates":[25.85698,55.93356],"type":"Point"}
}