{
  "type": "Feature",
  "properties": {
    "gn:admin1_code":"65",
    "gn:admin2_code":"89.0",
    "gn:asciiname":"Lydekupe",
    "gn:country_code":"LT",
    "gn:dem":106,
    "gn:feature_class":"P",
    "gn:feature_code":"PPL",
    "gn:name":"Lydekup\u0117",
    "gn:population":0,
    "gn:timezone":"Europe/Vilnius",
    "iso:country":"LT",
    "name:lit_x_preferred":[
        "Lydekup\u0117"
    ],
    "wof:name":"Lydekupe",
    "wof:placetype":"locality"
},
  "geometry": {"coordinates":[24.84733,54.9864],"type":"Point"}
}