{
  "type": "Feature",
  "properties": {
    "gn:admin1_code":"65",
    "gn:admin2_code":"13.0",
    "gn:asciiname":"Pagailasiai",
    "gn:country_code":"LT",
    "gn:dem":168,
    "gn:feature_class":"P",
    "gn:feature_code":"PPL",
    "gn:name":"Pagaila\u0161iai",
    "gn:population":0,
    "gn:timezone":"Europe/Vilnius",
    "iso:country":"LT",
    "name:lit_x_preferred":[
        "Pagaila\u0161iai"
    ],
    "wof:name":"Pagailasiai",
    "wof:placetype":"locality"
},
  "geometry": {"coordinates":[25.20593,54.82958000000001],"type":"Point"}
}