{
  "type": "Feature",
  "properties": {
    "gn:admin1_code":"61.0",
    "gn:admin2_code":"65.0",
    "gn:asciiname":"Triskoniai",
    "gn:country_code":"LT",
    "gn:dem":61,
    "gn:feature_class":"P",
    "gn:feature_code":"PPL",
    "gn:name":"Tri\u0161koniai",
    "gn:population":0,
    "gn:timezone":"Europe/Vilnius",
    "iso:country":"LT",
    "name:und_x_variant":[
        "Trishkonis",
        "Trishkonyay",
        "Tri\u0161koniai"
    ],
    "wof:name":"Triskoniai",
    "wof:placetype":"locality"
},
  "geometry": {"coordinates":[23.87097,56.08583],"type":"Point"}
}