{
  "type": "Feature",
  "properties": {
    "gn:admin1_code":"56.0",
    "gn:admin2_code":"59.0",
    "gn:asciiname":"Sadziunai",
    "gn:country_code":"LT",
    "gn:dem":127,
    "gn:feature_class":"P",
    "gn:feature_code":"PPL",
    "gn:name":"\u0160ad\u017ei\u016bnai",
    "gn:population":0,
    "gn:timezone":"Europe/Vilnius",
    "iso:country":"LT",
    "name:lit_x_preferred":[
        "\u0160ad\u017ei\u016bnai"
    ],
    "name:lit_x_variant":[
        "Sad\u017ei\u016bnai"
    ],
    "wof:name":"Sadziunai",
    "wof:placetype":"locality"
},
  "geometry": {"coordinates":[23.77654,54.10377],"type":"Point"}
}