{
  "type": "Feature",
  "properties": {
    "gn:admin1_code":"58.0",
    "gn:admin2_code":"88.0",
    "gn:asciiname":"Lamsociai",
    "gn:country_code":"LT",
    "gn:dem":5,
    "gn:feature_class":"P",
    "gn:feature_code":"PPL",
    "gn:name":"Lamso\u010diai",
    "gn:population":0,
    "gn:timezone":"Europe/Vilnius",
    "iso:country":"LT",
    "name:und_x_variant":[
        "Lamsochyay",
        "Lampsaten",
        "Lamso\u010diai"
    ],
    "wof:name":"Lamsociai",
    "wof:placetype":"locality"
},
  "geometry": {"coordinates":[21.34771,55.47665],"type":"Point"}
}