{
  "type": "Feature",
  "properties": {
    "gn:admin1_code":"59.0",
    "gn:admin2_code":"48.0",
    "gn:asciiname":"Jurgezeriai",
    "gn:country_code":"LT",
    "gn:dem":117,
    "gn:feature_class":"P",
    "gn:feature_code":"PPL",
    "gn:name":"Jurge\u017eeriai",
    "gn:population":0,
    "gn:timezone":"Europe/Vilnius",
    "iso:country":"LT",
    "name:und_x_variant":[
        "Yurgezery",
        "Jurge\u017eeri\u0173",
        "Jurge\u017eeriai"
    ],
    "wof:name":"Jurgezeriai",
    "wof:placetype":"locality"
},
  "geometry": {"coordinates":[23.16921,54.41229000000001],"type":"Point"}
}