{
  "type": "Feature",
  "properties": {
    "gn:admin1_code":"65.0",
    "gn:admin2_code":"81.0",
    "gn:asciiname":"Padbariskiai",
    "gn:country_code":"LT",
    "gn:dem":70,
    "gn:feature_class":"P",
    "gn:feature_code":"PPL",
    "gn:name":"Padbari\u0161kiai",
    "gn:population":0,
    "gn:timezone":"Europe/Vilnius",
    "iso:country":"LT",
    "name:lit_x_preferred":[
        "Padbari\u0161kiai"
    ],
    "name:und_x_variant":[
        "Podborishki",
        "Pabari\u0161kiai"
    ],
    "wof:name":"Padbariskiai",
    "wof:placetype":"locality"
},
  "geometry": {"coordinates":[24.79917,55.28232],"type":"Point"}
}