{
  "type": "Feature",
  "properties": {
    "gn:admin1_code":"65",
    "gn:admin2_code":"13.0",
    "gn:asciiname":"Dailidiskes",
    "gn:country_code":"LT",
    "gn:dem":163,
    "gn:feature_class":"P",
    "gn:feature_code":"PPL",
    "gn:name":"Dailidi\u0161k\u0117s",
    "gn:population":0,
    "gn:timezone":"Europe/Vilnius",
    "iso:country":"LT",
    "name:lit_x_preferred":[
        "Dailidi\u0161k\u0117s"
    ],
    "wof:name":"Dailidiskes",
    "wof:placetype":"locality"
},
  "geometry": {"coordinates":[25.38235,54.90451],"type":"Point"}
}