{
  "type": "Feature",
  "properties": {
    "gn:admin1_code":"65",
    "gn:admin2_code":"13.0",
    "gn:asciiname":"Siaurukai",
    "gn:country_code":"LT",
    "gn:dem":194,
    "gn:feature_class":"P",
    "gn:feature_code":"PPL",
    "gn:name":"Siaurukai",
    "gn:population":0,
    "gn:timezone":"Europe/Vilnius",
    "iso:country":"LT",
    "name:lit_x_preferred":[
        "Siaurukai"
    ],
    "wof:name":"Siaurukai",
    "wof:placetype":"locality"
},
  "geometry": {"coordinates":[25.44153,54.99794],"type":"Point"}
}