{
  "type": "Feature",
  "properties": {
    "gn:admin1_code":"57.0",
    "gn:admin2_code":"69.0",
    "gn:asciiname":"Leskava",
    "gn:country_code":"LT",
    "gn:dem":85,
    "gn:feature_class":"P",
    "gn:feature_code":"PPL",
    "gn:name":"Leskava",
    "gn:population":0,
    "gn:timezone":"Europe/Vilnius",
    "iso:country":"LT",
    "name:und_x_variant":[
        "Lyaskovo",
        "Leskava"
    ],
    "wof:name":"Leskava",
    "wof:placetype":"locality"
},
  "geometry": {"coordinates":[23.70706,54.71125],"type":"Point"}
}