{
  "type": "Feature",
  "properties": {
    "gn:admin1_code":"60",
    "gn:admin2_code":"67.0",
    "gn:asciiname":"Adampolis",
    "gn:country_code":"LT",
    "gn:dem":33,
    "gn:feature_class":"P",
    "gn:feature_code":"PPL",
    "gn:name":"Adampolis",
    "gn:population":0,
    "gn:timezone":"Europe/Vilnius",
    "iso:country":"LT",
    "name:lit_x_preferred":[
        "Adampolis"
    ],
    "wof:name":"Adampolis",
    "wof:placetype":"locality"
},
  "geometry": {"coordinates":[24.45135,56.08197],"type":"Point"}
}