{
  "type": "Feature",
  "properties": {
    "gn:admin1_code":"64.0",
    "gn:admin2_code":"43.0",
    "gn:asciiname":"Baibiai",
    "gn:country_code":"LT",
    "gn:dem":175,
    "gn:feature_class":"P",
    "gn:feature_code":"PPL",
    "gn:name":"Baibiai",
    "gn:population":0,
    "gn:timezone":"Europe/Vilnius",
    "iso:country":"LT",
    "name:und_x_variant":[
        "Baybyay",
        "Beybyay",
        "Baibiai"
    ],
    "wof:name":"Baibiai",
    "wof:placetype":"locality"
},
  "geometry": {"coordinates":[25.95876,55.62687],"type":"Point"}
}