{
  "type": "Feature",
  "properties": {
    "gn:admin1_code":"61.0",
    "gn:admin2_code":"71.0",
    "gn:asciiname":"Pamiskalniai",
    "gn:country_code":"LT",
    "gn:dem":131,
    "gn:feature_class":"P",
    "gn:feature_code":"PPL",
    "gn:name":"Pami\u0161kalniai",
    "gn:population":0,
    "gn:timezone":"Europe/Vilnius",
    "iso:country":"LT",
    "name:und_x_variant":[
        "Pomishkal\u2019ni",
        "Pomishkal\u2019ne",
        "Pami\u0161kalniai"
    ],
    "wof:name":"Pamiskalniai",
    "wof:placetype":"locality"
},
  "geometry": {"coordinates":[23.43883,55.66526],"type":"Point"}
}