{
  "type": "Feature",
  "properties": {
    "gn:admin1_code":"65",
    "gn:admin2_code":"85.0",
    "gn:asciiname":"Vinciapolis",
    "gn:country_code":"LT",
    "gn:dem":220,
    "gn:feature_class":"P",
    "gn:feature_code":"PPL",
    "gn:name":"Vinciapolis",
    "gn:population":0,
    "gn:timezone":"Europe/Vilnius",
    "iso:country":"LT",
    "name:lit_x_preferred":[
        "Vinciapolis"
    ],
    "wof:name":"Vinciapolis",
    "wof:placetype":"locality"
},
  "geometry": {"coordinates":[25.5304,54.32424],"type":"Point"}
}