{
  "type": "Feature",
  "properties": {
    "gn:admin1_code":"62.0",
    "gn:admin2_code":"87.0",
    "gn:asciiname":"Radiske",
    "gn:country_code":"LT",
    "gn:dem":171,
    "gn:feature_class":"P",
    "gn:feature_code":"PPL",
    "gn:name":"Radi\u0161k\u0117",
    "gn:population":0,
    "gn:timezone":"Europe/Vilnius",
    "iso:country":"LT",
    "name:und_x_variant":[
        "Rodyshkyay",
        "Radi\u0161k\u0117"
    ],
    "wof:name":"Radiske",
    "wof:placetype":"locality"
},
  "geometry": {"coordinates":[22.46673,55.59196],"type":"Point"}
}