{
  "type": "Feature",
  "properties": {
    "iso:country":"LT",
    "wof:name":"Riovonys",
    "wof:placetype":"neighbourhood"
},
  "geometry": {"coordinates":[25.2374653131749,54.65041335252511],"type":"Point"}
}