{
  "type": "Feature",
  "properties": {
    "gn:admin1_code":"59",
    "gn:admin2_code":"48.0",
    "gn:asciiname":"Saltieji Saltiniai",
    "gn:country_code":"LT",
    "gn:dem":122,
    "gn:feature_class":"P",
    "gn:feature_code":"PPL",
    "gn:name":"\u0160altieji \u0160altiniai",
    "gn:population":0,
    "gn:timezone":"Europe/Vilnius",
    "iso:country":"LT",
    "name:lit_x_preferred":[
        "\u0160altieji \u0160altiniai"
    ],
    "wof:name":"Saltieji Saltiniai",
    "wof:placetype":"locality"
},
  "geometry": {"coordinates":[23.16885,54.44168000000001],"type":"Point"}
}