{
  "type": "Feature",
  "properties": {
    "gn:admin1_code":"65",
    "gn:admin2_code":"13.0",
    "gn:asciiname":"Lazanka",
    "gn:country_code":"LT",
    "gn:dem":222,
    "gn:feature_class":"P",
    "gn:feature_code":"PPL",
    "gn:name":"Lazanka",
    "gn:population":0,
    "gn:timezone":"Europe/Vilnius",
    "iso:country":"LT",
    "name:lit_x_preferred":[
        "Lazanka"
    ],
    "wof:name":"Lazanka",
    "wof:placetype":"locality"
},
  "geometry": {"coordinates":[25.5285,54.49598],"type":"Point"}
}