{
  "type": "Feature",
  "properties": {
    "gn:country":"LT",
    "gn:fcode":"PPL",
    "gn:population":0,
    "iso:country":"LT",
    "name:und_x_variant":[
        "Vindyuny"
    ],
    "qs_pg:aaroncc":"LT",
    "qs_pg:gn_country":"LT",
    "qs_pg:gn_fcode":"PPL",
    "qs_pg:gn_pop":0,
    "qs_pg:name":"Vind\u017ei\u016bnai",
    "qs_pg:name_adm0":"Lietuva",
    "qs_pg:name_adm1":"Vilniaus Apskritis",
    "qs_pg:photos":11,
    "qs_pg:photos_1k":2,
    "qs_pg:photos_9k":1,
    "qs_pg:photos_9r":1,
    "qs_pg:photos_all":11,
    "qs_pg:photos_sr":1,
    "qs_pg:pop_sr":0,
    "qs_pg:qs_pg_placetype":"locality",
    "qs_pg:qs_pg_placetype_gp":"Town",
    "qs_pg:woe_adm0":23424875,
    "woe:adm0_id":23424875,
    "woe:name_adm0":"Lietuva",
    "woe:name_adm1":"Vilniaus Apskritis",
    "woe:placetype":"Town",
    "wof:name":"Vind\u017ei\u016bnai",
    "wof:placetype":"locality"
},
  "geometry": {"coordinates":[25.71667,54.56667],"type":"Point"}
}