{
  "type": "Feature",
  "properties": {
    "gn:admin1_code":"62.0",
    "gn:admin2_code":"63.0",
    "gn:asciiname":"Bardinai",
    "gn:country_code":"LT",
    "gn:dem":31,
    "gn:feature_class":"P",
    "gn:feature_code":"PPL",
    "gn:name":"Bardinai",
    "gn:population":0,
    "gn:timezone":"Europe/Vilnius",
    "iso:country":"LT",
    "name:und_x_variant":[
        "Bardenen",
        "Bardinai"
    ],
    "wof:name":"Bardinai",
    "wof:placetype":"locality"
},
  "geometry": {"coordinates":[22.02122,55.09654000000001],"type":"Point"}
}