{
  "type": "Feature",
  "properties": {
    "gn:admin1_code":"57.0",
    "gn:admin2_code":"72.0",
    "gn:asciiname":"Gintauciai",
    "gn:country_code":"LT",
    "gn:dem":118,
    "gn:feature_class":"P",
    "gn:feature_code":"PPL",
    "gn:name":"Gintau\u010diai",
    "gn:population":0,
    "gn:timezone":"Europe/Vilnius",
    "iso:country":"LT",
    "name:lit_x_preferred":[
        "Gintau\u010diai"
    ],
    "wof:name":"Gintauciai",
    "wof:placetype":"locality"
},
  "geometry": {"coordinates":[23.32402,55.48803],"type":"Point"}
}