{
  "type": "Feature",
  "properties": {
    "gn:admin1_code":"64",
    "gn:admin2_code":"45.0",
    "gn:asciiname":"Mieleskiai",
    "gn:country_code":"LT",
    "gn:dem":154,
    "gn:feature_class":"P",
    "gn:feature_code":"PPL",
    "gn:name":"Miele\u0161kiai",
    "gn:population":0,
    "gn:timezone":"Europe/Vilnius",
    "iso:country":"LT",
    "name:lit_x_preferred":[
        "Miele\u0161kiai"
    ],
    "wof:name":"Mieleskiai",
    "wof:placetype":"locality"
},
  "geometry": {"coordinates":[26.50782,55.38458000000001],"type":"Point"}
}