{
  "type": "Feature",
  "properties": {
    "gn:admin1_code":"0.0",
    "gn:asciiname":"Sriubiai",
    "gn:cc2":"LT",
    "gn:country_code":"LT",
    "gn:dem":61,
    "gn:feature_class":"P",
    "gn:feature_code":"PPL",
    "gn:name":"Sriubiai",
    "gn:population":0,
    "gn:timezone":"Europe/Vilnius",
    "iso:country":"LT",
    "name:und_x_variant":[
        "Sruby",
        "Sriubiai"
    ],
    "wof:name":"Sriubiai",
    "wof:placetype":"locality"
},
  "geometry": {"coordinates":[24.26667,55.33333],"type":"Point"}
}