{
  "type": "Feature",
  "properties": {
    "gn:admin1_code":"56",
    "gn:admin2_code":"59.0",
    "gn:asciiname":"Kelmaiciai",
    "gn:country_code":"LT",
    "gn:dem":193,
    "gn:feature_class":"P",
    "gn:feature_code":"PPL",
    "gn:name":"Kelmai\u010diai",
    "gn:population":0,
    "gn:timezone":"Europe/Vilnius",
    "iso:country":"LT",
    "name:lit_x_preferred":[
        "Kelmai\u010diai"
    ],
    "wof:name":"Kelmaiciai",
    "wof:placetype":"locality"
},
  "geometry": {"coordinates":[23.39893,54.26714000000001],"type":"Point"}
}