{
  "type": "Feature",
  "properties": {
    "gn:admin1_code":"61",
    "gn:admin2_code":"71.0",
    "gn:asciiname":"Baroniskiai",
    "gn:country_code":"LT",
    "gn:dem":124,
    "gn:feature_class":"P",
    "gn:feature_code":"PPL",
    "gn:name":"Baroni\u0161kiai",
    "gn:population":0,
    "gn:timezone":"Europe/Vilnius",
    "iso:country":"LT",
    "name:lit_x_preferred":[
        "Baroni\u0161kiai"
    ],
    "wof:name":"Baroniskiai",
    "wof:placetype":"locality"
},
  "geometry": {"coordinates":[23.43921,55.80264],"type":"Point"}
}