{
  "type": "Feature",
  "properties": {
    "gn:admin1_code":"58.0",
    "gn:admin2_code":"75.0",
    "gn:asciiname":"Raudoniai",
    "gn:country_code":"LT",
    "gn:dem":94,
    "gn:feature_class":"P",
    "gn:feature_code":"PPL",
    "gn:name":"Raudoniai",
    "gn:population":0,
    "gn:timezone":"Europe/Vilnius",
    "iso:country":"LT",
    "name:lit_x_preferred":[
        "Raudoniai"
    ],
    "wof:name":"Raudoniai",
    "wof:placetype":"locality"
},
  "geometry": {"coordinates":[21.87317,56.22926999999999],"type":"Point"}
}