{
  "type": "Feature",
  "properties": {
    "gn:admin1_code":"59.0",
    "gn:admin2_code":"39.0",
    "gn:asciiname":"Vaiclaukis",
    "gn:country_code":"LT",
    "gn:dem":64,
    "gn:feature_class":"P",
    "gn:feature_code":"PPL",
    "gn:name":"Vai\u010dlaukis",
    "gn:population":0,
    "gn:timezone":"Europe/Vilnius",
    "iso:country":"LT",
    "name:und_x_variant":[
        "Veychlavka",
        "Vai\u010dlaukio",
        "Vaychlaukis",
        "Vai\u010diulaukis",
        "Vai\u010dlaukis"
    ],
    "wof:name":"Vaiclaukis",
    "wof:placetype":"locality"
},
  "geometry": {"coordinates":[22.98594,54.60997],"type":"Point"}
}