{
  "type": "Feature",
  "properties": {
    "gn:admin1_code":"65.0",
    "gn:admin2_code":"85.0",
    "gn:asciiname":"Rudninkai",
    "gn:country_code":"LT",
    "gn:dem":136,
    "gn:feature_class":"P",
    "gn:feature_code":"PPL",
    "gn:name":"R\u016bdninkai",
    "gn:population":0,
    "gn:timezone":"Europe/Vilnius",
    "iso:country":"LT",
    "name:eng_x_preferred":[
        "R\u016bdninkai"
    ],
    "name:rus_x_preferred":[
        "\u0420\u0443\u0434\u043d\u0438\u043d\u043a\u0430\u0439"
    ],
    "name:und_x_variant":[
        "Rudininkai",
        "Rudniki",
        "Rudninkay",
        "R\u016bdninkai"
    ],
    "wof:name":"Rudninkai",
    "wof:placetype":"locality"
},
  "geometry": {"coordinates":[25.15119,54.4371],"type":"Point"}
}