{
  "type": "Feature",
  "properties": {
    "gn:admin1_code":"61",
    "gn:admin2_code":"47.0",
    "gn:asciiname":"Vaiduokliai",
    "gn:country_code":"LT",
    "gn:dem":43,
    "gn:feature_class":"P",
    "gn:feature_code":"PPL",
    "gn:name":"Vaiduokliai",
    "gn:population":0,
    "gn:timezone":"Europe/Vilnius",
    "iso:country":"LT",
    "name:lit_x_preferred":[
        "Vaiduokliai"
    ],
    "wof:name":"Vaiduokliai",
    "wof:placetype":"locality"
},
  "geometry": {"coordinates":[23.84769,56.31061],"type":"Point"}
}