{
  "type": "Feature",
  "properties": {
    "gn:admin1_code":"56",
    "gn:admin2_code":"11.0",
    "gn:asciiname":"Geistariskes",
    "gn:country_code":"LT",
    "gn:dem":98,
    "gn:feature_class":"P",
    "gn:feature_code":"PPL",
    "gn:name":"Geistari\u0161k\u0117s",
    "gn:population":0,
    "gn:timezone":"Europe/Vilnius",
    "iso:country":"LT",
    "name:lit_x_preferred":[
        "Geistari\u0161k\u0117s"
    ],
    "wof:name":"Geistariskes",
    "wof:placetype":"locality"
},
  "geometry": {"coordinates":[23.95744,54.33805],"type":"Point"}
}