{
  "type": "Feature",
  "properties": {
    "gn:admin1_code":"60",
    "gn:admin2_code":"73.0",
    "gn:asciiname":"Tarnava",
    "gn:country_code":"LT",
    "gn:dem":115,
    "gn:feature_class":"P",
    "gn:feature_code":"PPL",
    "gn:name":"Tarnava",
    "gn:population":0,
    "gn:timezone":"Europe/Vilnius",
    "iso:country":"LT",
    "name:bul_x_preferred":[
        "\u0422\u044a\u0440\u043d\u0430\u0432\u0430"
    ],
    "name:ceb_x_preferred":[
        "Tarnava"
    ],
    "name:fra_x_preferred":[
        "Tarnava"
    ],
    "name:ita_x_preferred":[
        "Tarnava"
    ],
    "name:lit_x_preferred":[
        "Tarnava"
    ],
    "name:rus_x_preferred":[
        "\u0422\u044b\u0440\u043d\u0430\u0432\u0430"
    ],
    "name:srp_x_preferred":[
        "\u0422\u0430\u0440\u043d\u0430\u0432\u0430"
    ],
    "name:swe_x_preferred":[
        "Tarnava"
    ],
    "wof:name":"Tarnava",
    "wof:placetype":"locality"
},
  "geometry": {"coordinates":[25.72012,55.77716],"type":"Point"}
}