{
  "type": "Feature",
  "properties": {
    "gn:admin1_code":"60",
    "gn:admin2_code":"36.0",
    "gn:asciiname":"Runikiai",
    "gn:country_code":"LT",
    "gn:dem":44,
    "gn:feature_class":"P",
    "gn:feature_code":"PPL",
    "gn:name":"Runikiai",
    "gn:population":0,
    "gn:timezone":"Europe/Vilnius",
    "iso:country":"LT",
    "name:lit_x_preferred":[
        "Runikiai"
    ],
    "wof:name":"Runikiai",
    "wof:placetype":"locality"
},
  "geometry": {"coordinates":[24.66793,56.36195],"type":"Point"}
}