{
  "type": "Feature",
  "properties": {
    "gn:admin1_code":"57",
    "gn:admin2_code":"46.0",
    "gn:asciiname":"Dovydonys",
    "gn:country_code":"LT",
    "gn:dem":84,
    "gn:feature_class":"P",
    "gn:feature_code":"PPL",
    "gn:name":"Dovydonys",
    "gn:population":0,
    "gn:timezone":"Europe/Vilnius",
    "iso:country":"LT",
    "name:lit_x_preferred":[
        "Dovydonys"
    ],
    "wof:name":"Dovydonys",
    "wof:placetype":"locality"
},
  "geometry": {"coordinates":[24.34113,55.22182],"type":"Point"}
}