{
  "type": "Feature",
  "properties": {
    "gn:gn_country":"LT",
    "gn:gn_fcode":"PPL",
    "gn:gn_pop":0,
    "iso:country":"LT",
    "name:eng_x_preferred":[
        "Skriaud\u017eiai"
    ],
    "name:fin_x_preferred":[
        "Skriaud\u017eiai"
    ],
    "name:lit_x_preferred":[
        "Skriaud\u017eiai"
    ],
    "name:sgs_x_preferred":[
        "Skriaud\u0113"
    ],
    "name:unk_x_variant":[
        "Skriaud\u017ei\u0173"
    ],
    "qs_pg:aaroncc":"LT",
    "qs_pg:gn_country":"LT",
    "qs_pg:gn_fcode":"PPL",
    "qs_pg:gn_pop":0,
    "qs_pg:name":"Skriaud\u017eiai",
    "qs_pg:name_adm0":"Lietuva",
    "qs_pg:name_adm1":"Kauno Apskritis",
    "qs_pg:photos":2,
    "qs_pg:photos_1k":1,
    "qs_pg:photos_9k":1,
    "qs_pg:photos_9r":1,
    "qs_pg:photos_all":2,
    "qs_pg:photos_sr":1,
    "qs_pg:pop_sr":0,
    "qs_pg:qs_pg_placetype":"locality",
    "qs_pg:qs_pg_placetype_gp":"Town",
    "qs_pg:woe_adm0":23424875,
    "woe:adm0_id":23424875,
    "woe:name_adm0":"Lietuva",
    "woe:name_adm1":"Kauno Apskritis",
    "woe:placetype":"Town",
    "wof:name":"Skriaud\u017eiai",
    "wof:placetype":"locality"
},
  "geometry": {"coordinates":[23.65,54.73333],"type":"Point"}
}