{
  "type": "Feature",
  "properties": {
    "gn:admin1_code":"64",
    "gn:admin2_code":"34.0",
    "gn:asciiname":"Rakutenai",
    "gn:country_code":"LT",
    "gn:dem":88,
    "gn:feature_class":"P",
    "gn:feature_code":"PPL",
    "gn:name":"Rakut\u0117nai",
    "gn:population":0,
    "gn:timezone":"Europe/Vilnius",
    "iso:country":"LT",
    "name:lit_x_preferred":[
        "Rakut\u0117nai"
    ],
    "wof:name":"Rakutenai",
    "wof:placetype":"locality"
},
  "geometry": {"coordinates":[24.84386,55.6805],"type":"Point"}
}