{
  "type": "Feature",
  "properties": {
    "gn:admin1_code":"56",
    "gn:admin2_code":"38.0",
    "gn:asciiname":"Burokaraistele",
    "gn:country_code":"LT",
    "gn:dem":110,
    "gn:feature_class":"P",
    "gn:feature_code":"PPL",
    "gn:name":"Burokaraist\u0117l\u0117",
    "gn:population":0,
    "gn:timezone":"Europe/Vilnius",
    "iso:country":"LT",
    "name:lit_x_preferred":[
        "Burokaraist\u0117l\u0117"
    ],
    "wof:name":"Burokaraistele",
    "wof:placetype":"locality"
},
  "geometry": {"coordinates":[24.3428,54.20135],"type":"Point"}
}