{
  "type": "Feature",
  "properties": {
    "gn:admin1_code":"65",
    "gn:admin2_code":"13.0",
    "gn:asciiname":"Dedoniskes",
    "gn:country_code":"LT",
    "gn:dem":158,
    "gn:feature_class":"P",
    "gn:feature_code":"PPL",
    "gn:name":"D\u0117doni\u0161k\u0117s",
    "gn:population":0,
    "gn:timezone":"Europe/Vilnius",
    "iso:country":"LT",
    "name:lit_x_preferred":[
        "D\u0117doni\u0161k\u0117s"
    ],
    "wof:name":"Dedoniskes",
    "wof:placetype":"locality"
},
  "geometry": {"coordinates":[25.57171,54.70198000000001],"type":"Point"}
}