{
  "type": "Feature",
  "properties": {
    "gn:admin1_code":"59",
    "gn:admin2_code":"58.0",
    "gn:asciiname":"Audiejiske",
    "gn:country_code":"LT",
    "gn:dem":46,
    "gn:feature_class":"P",
    "gn:feature_code":"PPL",
    "gn:name":"Audieji\u0161k\u0117",
    "gn:population":0,
    "gn:timezone":"Europe/Vilnius",
    "iso:country":"LT",
    "name:lit_x_preferred":[
        "Audieji\u0161k\u0117"
    ],
    "wof:name":"Audiejiske",
    "wof:placetype":"locality"
},
  "geometry": {"coordinates":[23.2989,54.7631],"type":"Point"}
}