{
  "type": "Feature",
  "properties": {
    "gn:admin1_code":"65.0",
    "gn:admin2_code":"13.0",
    "gn:asciiname":"Skleriskes",
    "gn:country_code":"LT",
    "gn:dem":146,
    "gn:feature_class":"P",
    "gn:feature_code":"PPL",
    "gn:name":"Skl\u0117ri\u0161k\u0117s",
    "gn:population":0,
    "gn:timezone":"Europe/Vilnius",
    "iso:country":"LT",
    "name:lit_x_preferred":[
        "Skl\u0117ri\u0161k\u0117s"
    ],
    "name:und_x_variant":[
        "Sklerishki",
        "Skl\u0117ri\u0161kis"
    ],
    "wof:name":"Skleriskes",
    "wof:placetype":"locality"
},
  "geometry": {"coordinates":[25.57666,54.91293],"type":"Point"}
}