{
  "type": "Feature",
  "properties": {
    "gn:admin1_code":"64",
    "gn:admin2_code":"34.0",
    "gn:asciiname":"Ertejai",
    "gn:country_code":"LT",
    "gn:dem":116,
    "gn:feature_class":"P",
    "gn:feature_code":"PPL",
    "gn:name":"Ert\u0117jai",
    "gn:population":0,
    "gn:timezone":"Europe/Vilnius",
    "iso:country":"LT",
    "name:lit_x_preferred":[
        "Ert\u0117jai"
    ],
    "wof:name":"Ertejai",
    "wof:placetype":"locality"
},
  "geometry": {"coordinates":[25.25761,55.68861999999999],"type":"Point"}
}