{
  "type": "Feature",
  "properties": {
    "gn:admin1_code":"64",
    "gn:admin2_code":"45.0",
    "gn:asciiname":"Galalaukiai",
    "gn:country_code":"LT",
    "gn:dem":135,
    "gn:feature_class":"P",
    "gn:feature_code":"PPL",
    "gn:name":"Galalaukiai",
    "gn:population":0,
    "gn:timezone":"Europe/Vilnius",
    "iso:country":"LT",
    "name:bel_x_preferred":[
        "\u0413\u0430\u043b\u0430\u043b\u0430\u045e\u043a\u0435\u0439"
    ],
    "name:lit_x_preferred":[
        "Galalaukiai"
    ],
    "name:pol_x_preferred":[
        "Ko\u0144cepole"
    ],
    "wof:name":"Galalaukiai",
    "wof:placetype":"locality"
},
  "geometry": {"coordinates":[26.72388,55.31642],"type":"Point"}
}