{
  "type": "Feature",
  "properties": {
    "gn:admin1_code":"62",
    "gn:admin2_code":"87.0",
    "gn:asciiname":"Uzsienis",
    "gn:country_code":"LT",
    "gn:dem":125,
    "gn:feature_class":"P",
    "gn:feature_code":"PPL",
    "gn:name":"U\u017esienis",
    "gn:population":0,
    "gn:timezone":"Europe/Vilnius",
    "iso:country":"LT",
    "name:lit_x_preferred":[
        "U\u017esienis"
    ],
    "wof:name":"Uzsienis",
    "wof:placetype":"locality"
},
  "geometry": {"coordinates":[22.05972,55.53706],"type":"Point"}
}