{
  "type": "Feature",
  "properties": {
    "gn:admin1_code":"64.0",
    "gn:admin2_code":"45.0",
    "gn:asciiname":"Sileikiske",
    "gn:country_code":"LT",
    "gn:dem":200,
    "gn:feature_class":"P",
    "gn:feature_code":"PPL",
    "gn:name":"\u0160ileiki\u0161k\u0117",
    "gn:population":0,
    "gn:timezone":"Europe/Vilnius",
    "iso:country":"LT",
    "name:lit_x_preferred":[
        "\u0160ileiki\u0161k\u0117"
    ],
    "name:lit_x_variant":[
        "Salaki\u0161kiai"
    ],
    "wof:name":"Sileikiske",
    "wof:placetype":"locality"
},
  "geometry": {"coordinates":[26.2872,55.24415],"type":"Point"}
}