{
  "type": "Feature",
  "properties": {
    "gn:admin1_code":"58.0",
    "gn:admin2_code":"56.0",
    "gn:asciiname":"Kulupenai",
    "gn:country_code":"LT",
    "gn:dem":57,
    "gn:feature_class":"P",
    "gn:feature_code":"PPL",
    "gn:name":"K\u016blup\u0117nai",
    "gn:population":0,
    "gn:timezone":"Europe/Vilnius",
    "iso:country":"LT",
    "name:eng_x_preferred":[
        "K\u016blup\u0117nai"
    ],
    "name:rus_x_preferred":[
        "\u041a\u0443\u043b\u0443\u043f\u0435\u043d\u0430\u0439"
    ],
    "name:und_x_variant":[
        "Kulupenay"
    ],
    "wof:name":"Kulupenai",
    "wof:placetype":"locality"
},
  "geometry": {"coordinates":[21.48152,55.9593],"type":"Point"}
}