{
  "type": "Feature",
  "properties": {
    "gn:admin1_code":"61.0",
    "gn:admin2_code":"29.0",
    "gn:asciiname":"Mikailaiciai",
    "gn:country_code":"LT",
    "gn:dem":110,
    "gn:feature_class":"P",
    "gn:feature_code":"PPL",
    "gn:name":"Mikailai\u010diai",
    "gn:population":0,
    "gn:timezone":"Europe/Vilnius",
    "iso:country":"LT",
    "name:und_x_variant":[
        "Mikolaychyay",
        "Mikailai\u010diai"
    ],
    "wof:name":"Mikailaiciai",
    "wof:placetype":"locality"
},
  "geometry": {"coordinates":[23.43764,55.95915],"type":"Point"}
}