{
  "type": "Feature",
  "properties": {
    "gn:admin1_code":"64",
    "gn:admin2_code":"34.0",
    "gn:asciiname":"Vildiskiai",
    "gn:country_code":"LT",
    "gn:dem":145,
    "gn:feature_class":"P",
    "gn:feature_code":"PPL",
    "gn:name":"Vildi\u0161kiai",
    "gn:population":0,
    "gn:timezone":"Europe/Vilnius",
    "iso:country":"LT",
    "name:lit_x_preferred":[
        "Vildi\u0161kiai"
    ],
    "wof:name":"Vildiskiai",
    "wof:placetype":"locality"
},
  "geometry": {"coordinates":[25.22556,55.41485],"type":"Point"}
}