{
  "type": "Feature",
  "properties": {
    "gn:admin1_code":"64",
    "gn:admin2_code":"82.0",
    "gn:asciiname":"Slekiskes",
    "gn:country_code":"LT",
    "gn:dem":200,
    "gn:feature_class":"P",
    "gn:feature_code":"PPL",
    "gn:name":"\u0160leki\u0161k\u0117s",
    "gn:population":0,
    "gn:timezone":"Europe/Vilnius",
    "iso:country":"LT",
    "name:lit_x_preferred":[
        "\u0160leki\u0161k\u0117s"
    ],
    "wof:name":"Slekiskes",
    "wof:placetype":"locality"
},
  "geometry": {"coordinates":[25.83711,55.55127],"type":"Point"}
}