{
  "type": "Feature",
  "properties": {
    "gn:admin1_code":"63.0",
    "gn:admin2_code":"68.0",
    "gn:asciiname":"Endriuskaiciai",
    "gn:country_code":"LT",
    "gn:dem":146,
    "gn:feature_class":"P",
    "gn:feature_code":"PPL",
    "gn:name":"Endriu\u0161kai\u010diai",
    "gn:population":0,
    "gn:timezone":"Europe/Vilnius",
    "iso:country":"LT",
    "name:und_x_variant":[
        "Andrushkaychey",
        "Endriu\u0161kai\u010diai"
    ],
    "wof:name":"Endriuskaiciai",
    "wof:placetype":"locality"
},
  "geometry": {"coordinates":[21.91471,55.9993],"type":"Point"}
}