{
  "type": "Feature",
  "properties": {
    "gn:admin1_code":"65",
    "gn:admin2_code":"86.0",
    "gn:asciiname":"Raudonalaukis",
    "gn:country_code":"LT",
    "gn:dem":201,
    "gn:feature_class":"P",
    "gn:feature_code":"PPL",
    "gn:name":"Raudonalaukis",
    "gn:population":0,
    "gn:timezone":"Europe/Vilnius",
    "iso:country":"LT",
    "name:lit_x_preferred":[
        "Raudonalaukis"
    ],
    "wof:name":"Raudonalaukis",
    "wof:placetype":"locality"
},
  "geometry": {"coordinates":[26.18516,55.18261],"type":"Point"}
}