{
  "type": "Feature",
  "properties": {
    "gn:admin1_code":"60",
    "gn:admin2_code":"67.0",
    "gn:asciiname":"Sindriuniskis",
    "gn:country_code":"LT",
    "gn:dem":41,
    "gn:feature_class":"P",
    "gn:feature_code":"PPL",
    "gn:name":"Sindri\u016bni\u0161kis",
    "gn:population":0,
    "gn:timezone":"Europe/Vilnius",
    "iso:country":"LT",
    "name:lit_x_preferred":[
        "Sindri\u016bni\u0161kis"
    ],
    "wof:name":"Sindriuniskis",
    "wof:placetype":"locality"
},
  "geometry": {"coordinates":[24.26174,56.08213000000001],"type":"Point"}
}