{
  "type": "Feature",
  "properties": {
    "gn:admin1_code":"60.0",
    "gn:admin2_code":"36.0",
    "gn:asciiname":"Stackunai",
    "gn:country_code":"LT",
    "gn:dem":57,
    "gn:feature_class":"P",
    "gn:feature_code":"PPL",
    "gn:name":"Sta\u010dk\u016bnai",
    "gn:population":0,
    "gn:timezone":"Europe/Vilnius",
    "iso:country":"LT",
    "name:und_x_variant":[
        "Stochkunay",
        "Stachkunay",
        "Stochkunai",
        "Sta\u010dk\u016bnai"
    ],
    "wof:name":"Stackunai",
    "wof:placetype":"locality"
},
  "geometry": {"coordinates":[24.81697,56.22595],"type":"Point"}
}