{
  "type": "Feature",
  "properties": {
    "gn:admin1_code":"65",
    "gn:admin2_code":"81.0",
    "gn:asciiname":"Smiltyne",
    "gn:country_code":"LT",
    "gn:dem":59,
    "gn:feature_class":"P",
    "gn:feature_code":"PPL",
    "gn:name":"Smiltyn\u0117",
    "gn:population":0,
    "gn:timezone":"Europe/Vilnius",
    "iso:country":"LT",
    "name:lit_x_preferred":[
        "Smiltyn\u0117"
    ],
    "wof:name":"Smiltyne",
    "wof:placetype":"locality"
},
  "geometry": {"coordinates":[24.87431,55.30429],"type":"Point"}
}