{
  "type": "Feature",
  "properties": {
    "gn:admin1_code":"65",
    "gn:admin2_code":"13.0",
    "gn:asciiname":"Juozapine",
    "gn:country_code":"LT",
    "gn:dem":269,
    "gn:feature_class":"P",
    "gn:feature_code":"PPL",
    "gn:name":"Juozapin\u0117",
    "gn:population":0,
    "gn:timezone":"Europe/Vilnius",
    "iso:country":"LT",
    "name:lit_x_preferred":[
        "Juozapin\u0117"
    ],
    "wof:name":"Juozapine",
    "wof:placetype":"locality"
},
  "geometry": {"coordinates":[25.62249,54.5311],"type":"Point"}
}