{
  "type": "Feature",
  "properties": {
    "gn:admin1_code":"60.0",
    "gn:admin2_code":"73.0",
    "gn:asciiname":"Rudeliai",
    "gn:country_code":"LT",
    "gn:dem":151,
    "gn:feature_class":"P",
    "gn:feature_code":"PPL",
    "gn:name":"Rudeliai",
    "gn:population":0,
    "gn:timezone":"Europe/Vilnius",
    "iso:country":"LT",
    "name:und_x_variant":[
        "Rudeli\u0173",
        "Rudelyay",
        "Rudeliai"
    ],
    "wof:name":"Rudeliai",
    "wof:placetype":"locality"
},
  "geometry": {"coordinates":[25.68167,55.91458000000001],"type":"Point"}
}