{
  "type": "Feature",
  "properties": {
    "gn:admin1_code":"59",
    "gn:admin2_code":"48.0",
    "gn:asciiname":"Pasesupys",
    "gn:country_code":"LT",
    "gn:dem":108,
    "gn:feature_class":"P",
    "gn:feature_code":"PPL",
    "gn:name":"Pa\u0161e\u0161upys",
    "gn:population":0,
    "gn:timezone":"Europe/Vilnius",
    "iso:country":"LT",
    "name:lit_x_preferred":[
        "Pa\u0161e\u0161upys"
    ],
    "wof:name":"Pasesupys",
    "wof:placetype":"locality"
},
  "geometry": {"coordinates":[23.27342,54.41761999999999],"type":"Point"}
}