{
  "type": "Feature",
  "properties": {
    "gn:admin1_code":"62.0",
    "gn:admin2_code":"87.0",
    "gn:asciiname":"Rubinavas",
    "gn:country_code":"LT",
    "gn:dem":95,
    "gn:feature_class":"P",
    "gn:feature_code":"PPL",
    "gn:name":"Rubinavas",
    "gn:population":0,
    "gn:timezone":"Europe/Vilnius",
    "iso:country":"LT",
    "name:lit_x_preferred":[
        "Rubinavas"
    ],
    "name:und_x_variant":[
        "Rubinovo",
        "Rubinai"
    ],
    "wof:name":"Rubinavas",
    "wof:placetype":"locality"
},
  "geometry": {"coordinates":[22.1275,55.48146],"type":"Point"}
}