{
  "type": "Feature",
  "properties": {
    "gn:admin1_code":"57.0",
    "gn:admin2_code":"53.0",
    "gn:asciiname":"Aristava",
    "gn:country_code":"LT",
    "gn:dem":51,
    "gn:feature_class":"P",
    "gn:feature_code":"PPL",
    "gn:name":"Aristava",
    "gn:population":0,
    "gn:timezone":"Europe/Vilnius",
    "iso:country":"LT",
    "name:und_x_variant":[
        "Arvystai",
        "Aristava",
        "Luk\u0161iakaimis",
        "Lukshakaymis"
    ],
    "wof:name":"Aristava",
    "wof:placetype":"locality"
},
  "geometry": {"coordinates":[24.08338,55.29244],"type":"Point"}
}