{
  "type": "Feature",
  "properties": {
    "gn:admin1_code":"61.0",
    "gn:admin2_code":"54.0",
    "gn:asciiname":"Toluciai",
    "gn:country_code":"LT",
    "gn:dem":124,
    "gn:feature_class":"P",
    "gn:feature_code":"PPL",
    "gn:name":"Tolu\u010diai",
    "gn:population":0,
    "gn:timezone":"Europe/Vilnius",
    "iso:country":"LT",
    "name:und_x_variant":[
        "Tolutsi",
        "Toluchyay",
        "Tolu\u010diai"
    ],
    "wof:name":"Toluciai",
    "wof:placetype":"locality"
},
  "geometry": {"coordinates":[23.19815,55.63108],"type":"Point"}
}