{
  "type": "Feature",
  "properties": {
    "gn:admin1_code":"60",
    "gn:admin2_code":"36.0",
    "gn:asciiname":"Upes Seta",
    "gn:country_code":"LT",
    "gn:dem":60,
    "gn:feature_class":"P",
    "gn:feature_code":"PPL",
    "gn:name":"Up\u0117s S\u0117ta",
    "gn:population":0,
    "gn:timezone":"Europe/Riga",
    "iso:country":"LT",
    "name:lit_x_preferred":[
        "Up\u0117s S\u0117ta"
    ],
    "wof:name":"Upes Seta",
    "wof:placetype":"locality"
},
  "geometry": {"coordinates":[24.96774,56.33975],"type":"Point"}
}