{
  "type": "Feature",
  "properties": {
    "gn:admin1_code":"59",
    "gn:admin2_code":"48.0",
    "gn:asciiname":"Ivantiskiai",
    "gn:country_code":"LT",
    "gn:dem":107,
    "gn:feature_class":"P",
    "gn:feature_code":"PPL",
    "gn:name":"Ivanti\u0161kiai",
    "gn:population":0,
    "gn:timezone":"Europe/Vilnius",
    "iso:country":"LT",
    "name:lit_x_preferred":[
        "Ivanti\u0161kiai"
    ],
    "wof:name":"Ivantiskiai",
    "wof:placetype":"locality"
},
  "geometry": {"coordinates":[23.30908,54.40051],"type":"Point"}
}