{
  "type": "Feature",
  "properties": {
    "gn:admin1_code":"59",
    "gn:admin2_code":"84.0",
    "gn:asciiname":"Zygmantiske",
    "gn:country_code":"LT",
    "gn:dem":60,
    "gn:feature_class":"P",
    "gn:feature_code":"PPL",
    "gn:name":"Zygmanti\u0161k\u0117",
    "gn:population":0,
    "gn:timezone":"Europe/Vilnius",
    "iso:country":"LT",
    "name:lit_x_preferred":[
        "Zygmanti\u0161k\u0117"
    ],
    "wof:name":"Zygmantiske",
    "wof:placetype":"locality"
},
  "geometry": {"coordinates":[23.33337,55.00301999999999],"type":"Point"}
}