{
  "type": "Feature",
  "properties": {
    "gn:gn_country":"LT",
    "gn:gn_fcode":"PPLL",
    "gn:gn_pop":20,
    "gn:population":20,
    "iso:country":"LT",
    "name:deu_x_preferred":[
        "Neustubbern"
    ],
    "name:lit_x_preferred":[
        "Naustubriai"
    ],
    "qs_pg:aaroncc":"LT",
    "qs_pg:gn_country":"LT",
    "qs_pg:gn_fcode":"PPLL",
    "qs_pg:gn_pop":20,
    "qs_pg:name":"Naustubriai",
    "qs_pg:photos_9r":0,
    "qs_pg:photos_sr":0,
    "qs_pg:pop_sr":1,
    "qs_pg:qs_pg_placetype":"locality",
    "wof:name":"Naustubriai",
    "wof:placetype":"locality",
    "wof:population":20
},
  "geometry": {"coordinates":[21.82958,55.24199],"type":"Point"}
}