{
  "type": "Feature",
  "properties": {
    "gn:admin1_code":"58.0",
    "gn:admin2_code":"88.0",
    "gn:asciiname":"Inkakliai",
    "gn:country_code":"LT",
    "gn:dem":28,
    "gn:feature_class":"P",
    "gn:feature_code":"PPL",
    "gn:name":"Inkakliai",
    "gn:population":0,
    "gn:timezone":"Europe/Vilnius",
    "iso:country":"LT",
    "name:und_x_variant":[
        "Inkalyay",
        "Inkakli",
        "Inkakliai"
    ],
    "wof:name":"Inkakliai",
    "wof:placetype":"locality"
},
  "geometry": {"coordinates":[21.58049,55.48135],"type":"Point"}
}