{
  "type": "Feature",
  "properties": {
    "gn:admin1_code":"62.0",
    "gn:admin2_code":"87.0",
    "gn:asciiname":"Pempes",
    "gn:country_code":"LT",
    "gn:dem":170,
    "gn:feature_class":"P",
    "gn:feature_code":"PPL",
    "gn:name":"Pemp\u0117s",
    "gn:population":0,
    "gn:timezone":"Europe/Vilnius",
    "iso:country":"LT",
    "name:und_x_variant":[
        "Pempo",
        "Pemp\u0117s"
    ],
    "wof:name":"Pempes",
    "wof:placetype":"locality"
},
  "geometry": {"coordinates":[22.41785,55.59708000000001],"type":"Point"}
}