{
  "type": "Feature",
  "properties": {
    "gn:admin1_code":"57.0",
    "gn:admin2_code":"53.0",
    "gn:asciiname":"Vincgalys",
    "gn:country_code":"LT",
    "gn:dem":63,
    "gn:feature_class":"P",
    "gn:feature_code":"PPL",
    "gn:name":"Vincgalys",
    "gn:population":0,
    "gn:timezone":"Europe/Vilnius",
    "iso:country":"LT",
    "name:und_x_variant":[
        "Ventsgol\u2019",
        "Ventsgolyay",
        "Vincgalys"
    ],
    "wof:name":"Vincgalys",
    "wof:placetype":"locality"
},
  "geometry": {"coordinates":[23.92767000000001,55.40334],"type":"Point"}
}