{
  "type": "Feature",
  "properties": {
    "gn:admin1_code":"59.0",
    "gn:admin2_code":"39.0",
    "gn:asciiname":"Stirniskiai",
    "gn:country_code":"LT",
    "gn:dem":59,
    "gn:feature_class":"P",
    "gn:feature_code":"PPL",
    "gn:name":"Stirni\u0161kiai",
    "gn:population":0,
    "gn:timezone":"Europe/Vilnius",
    "iso:country":"LT",
    "name:und_x_variant":[
        "Sternishki",
        "Stirni\u0161kiai"
    ],
    "wof:name":"Stirniskiai",
    "wof:placetype":"locality"
},
  "geometry": {"coordinates":[23.1503,54.6464],"type":"Point"}
}