{
  "type": "Feature",
  "properties": {
    "gn:admin1_code":"61",
    "gn:admin2_code":"47.0",
    "gn:asciiname":"Bargavones",
    "gn:country_code":"LT",
    "gn:dem":85,
    "gn:feature_class":"P",
    "gn:feature_code":"PPL",
    "gn:name":"Bargavon\u0117s",
    "gn:population":0,
    "gn:timezone":"Europe/Vilnius",
    "iso:country":"LT",
    "name:lit_x_preferred":[
        "Bargavon\u0117s"
    ],
    "wof:name":"Bargavones",
    "wof:placetype":"locality"
},
  "geometry": {"coordinates":[23.41544,56.17276999999999],"type":"Point"}
}