{
  "type": "Feature",
  "properties": {
    "gn:admin1_code":"60",
    "gn:admin2_code":"27.0",
    "gn:asciiname":"Janaliskiai",
    "gn:country_code":"LT",
    "gn:dem":41,
    "gn:feature_class":"P",
    "gn:feature_code":"PPL",
    "gn:name":"Janali\u0161kiai",
    "gn:population":0,
    "gn:timezone":"Europe/Vilnius",
    "iso:country":"LT",
    "name:lit_x_preferred":[
        "Janali\u0161kiai"
    ],
    "wof:name":"Janaliskiai",
    "wof:placetype":"locality"
},
  "geometry": {"coordinates":[24.2804,55.82448],"type":"Point"}
}