{
  "type": "Feature",
  "properties": {
    "gn:admin1_code":"58.0",
    "gn:admin2_code":"88.0",
    "gn:asciiname":"Buikiske",
    "gn:country_code":"LT",
    "gn:dem":58,
    "gn:feature_class":"P",
    "gn:feature_code":"PPL",
    "gn:name":"Buiki\u0161k\u0117",
    "gn:population":0,
    "gn:timezone":"Europe/Vilnius",
    "iso:country":"LT",
    "name:und_x_variant":[
        "Buykishke",
        "Buykishki",
        "Buiki\u0161k\u0117"
    ],
    "wof:name":"Buikiske",
    "wof:placetype":"locality"
},
  "geometry": {"coordinates":[21.81698,55.32232],"type":"Point"}
}