{
  "type": "Feature",
  "properties": {
    "gn:admin1_code":"61",
    "gn:admin2_code":"54.0",
    "gn:asciiname":"Paspastis",
    "gn:country_code":"LT",
    "gn:dem":182,
    "gn:feature_class":"P",
    "gn:feature_code":"PPL",
    "gn:name":"Pasp\u0105stis",
    "gn:population":0,
    "gn:timezone":"Europe/Vilnius",
    "iso:country":"LT",
    "name:lit_x_preferred":[
        "Pasp\u0105stis"
    ],
    "wof:name":"Paspastis",
    "wof:placetype":"locality"
},
  "geometry": {"coordinates":[22.5368,55.67788],"type":"Point"}
}