{
  "type": "Feature",
  "properties": {
    "gn:admin1_code":"62.0",
    "gn:admin2_code":"87.0",
    "gn:asciiname":"Romes Laukas",
    "gn:country_code":"LT",
    "gn:dem":98,
    "gn:feature_class":"P",
    "gn:feature_code":"PPL",
    "gn:name":"Rom\u0117s Laukas",
    "gn:population":0,
    "gn:timezone":"Europe/Vilnius",
    "iso:country":"LT",
    "name:lit_x_preferred":[
        "Rom\u0117s Laukas"
    ],
    "name:und_x_variant":[
        "Romes Lauk\u0117s"
    ],
    "wof:name":"Romes Laukas",
    "wof:placetype":"locality"
},
  "geometry": {"coordinates":[22.28054,55.4295],"type":"Point"}
}