{
  "type": "Feature",
  "properties": {
    "gn:admin1_code":"65.0",
    "gn:admin2_code":"89.0",
    "gn:asciiname":"Levaniskis I",
    "gn:country_code":"LT",
    "gn:dem":126,
    "gn:feature_class":"P",
    "gn:feature_code":"PPL",
    "gn:name":"Levani\u0161kis I",
    "gn:population":0,
    "gn:timezone":"Europe/Vilnius",
    "iso:country":"LT",
    "name:lit_x_preferred":[
        "Levani\u0161kis I"
    ],
    "name:und_x_variant":[
        "Levanishkis",
        "Levani\u0161kis"
    ],
    "wof:name":"Levaniskis I",
    "wof:placetype":"locality"
},
  "geometry": {"coordinates":[24.98397000000001,55.11111],"type":"Point"}
}