{
  "type": "Feature",
  "properties": {
    "gn:admin1_code":"62.0",
    "gn:admin2_code":"94.0",
    "gn:asciiname":"Pazerai",
    "gn:country_code":"LT",
    "gn:dem":46,
    "gn:feature_class":"P",
    "gn:feature_code":"PPL",
    "gn:name":"Pa\u017e\u0117rai",
    "gn:population":0,
    "gn:timezone":"Europe/Vilnius",
    "iso:country":"LT",
    "name:und_x_variant":[
        "Pozhery",
        "Pa\u017eeri\u0173",
        "Pa\u017e\u0117rai"
    ],
    "wof:name":"Pazerai",
    "wof:placetype":"locality"
},
  "geometry": {"coordinates":[22.88838,55.16859],"type":"Point"}
}