{
  "type": "Feature",
  "properties": {
    "gn:admin1_code":"57.0",
    "gn:admin2_code":"49.0",
    "gn:asciiname":"Senkonys",
    "gn:country_code":"LT",
    "gn:dem":113,
    "gn:feature_class":"P",
    "gn:feature_code":"PPL",
    "gn:name":"Senkonys",
    "gn:population":0,
    "gn:timezone":"Europe/Vilnius",
    "iso:country":"LT",
    "name:und_x_variant":[
        "Senkany",
        "Senkonys"
    ],
    "wof:name":"Senkonys",
    "wof:placetype":"locality"
},
  "geometry": {"coordinates":[24.62546,54.88527],"type":"Point"}
}