{
  "type": "Feature",
  "properties": {
    "gn:admin1_code":"63.0",
    "gn:admin2_code":"78.0",
    "gn:asciiname":"Rudupiai",
    "gn:country_code":"LT",
    "gn:dem":144,
    "gn:feature_class":"P",
    "gn:feature_code":"PPL",
    "gn:name":"R\u016bdupiai",
    "gn:population":0,
    "gn:timezone":"Europe/Vilnius",
    "iso:country":"LT",
    "name:und_x_variant":[
        "R\u016bdupi\u0173",
        "Rudupyay",
        "R\u016bdupiai"
    ],
    "wof:name":"Rudupiai",
    "wof:placetype":"locality"
},
  "geometry": {"coordinates":[22.41857000000001,55.91598000000001],"type":"Point"}
}