{
  "type": "Feature",
  "properties": {
    "gn:admin1_code":"59",
    "gn:admin2_code":"39.0",
    "gn:asciiname":"Stolaukelis",
    "gn:country_code":"LT",
    "gn:dem":92,
    "gn:feature_class":"P",
    "gn:feature_code":"PPL",
    "gn:name":"Stolauk\u0117lis",
    "gn:population":0,
    "gn:timezone":"Europe/Vilnius",
    "iso:country":"LT",
    "name:lit_x_preferred":[
        "Stolauk\u0117lis"
    ],
    "wof:name":"Stolaukelis",
    "wof:placetype":"locality"
},
  "geometry": {"coordinates":[22.92307000000001,54.57093],"type":"Point"}
}