{
  "type": "Feature",
  "properties": {
    "iso:country":"LT",
    "name:lit_x_preferred":[
        "Ma\u017eieji Gulbinai"
    ],
    "wof:name":"Mazieji Gulbinai",
    "wof:placetype":"neighbourhood"
},
  "geometry": {"coordinates":[25.30418440192046,54.78422089898004],"type":"Point"}
}