{
  "type": "Feature",
  "properties": {
    "gn:admin1_code":"64",
    "gn:admin2_code":"45.0",
    "gn:asciiname":"Budninkai",
    "gn:country_code":"LT",
    "gn:dem":237,
    "gn:feature_class":"P",
    "gn:feature_code":"PPL",
    "gn:name":"B\u016bdninkai",
    "gn:population":0,
    "gn:timezone":"Europe/Vilnius",
    "iso:country":"LT",
    "name:lit_x_preferred":[
        "B\u016bdninkai"
    ],
    "wof:name":"Budninkai",
    "wof:placetype":"locality"
},
  "geometry": {"coordinates":[26.28111,55.31066],"type":"Point"}
}