{
  "type": "Feature",
  "properties": {
    "gn:admin1_code":"57.0",
    "gn:admin2_code":"53.0",
    "gn:asciiname":"Skirgailine",
    "gn:country_code":"LT",
    "gn:dem":102,
    "gn:feature_class":"P",
    "gn:feature_code":"PPL",
    "gn:name":"Skirgailin\u0117",
    "gn:population":0,
    "gn:timezone":"Europe/Vilnius",
    "iso:country":"LT",
    "name:lit_x_preferred":[
        "Skirgailin\u0117"
    ],
    "wof:name":"Skirgailine",
    "wof:placetype":"locality"
},
  "geometry": {"coordinates":[23.57662,55.40963000000001],"type":"Point"}
}