{
  "type": "Feature",
  "properties": {
    "gn:admin1_code":"65.0",
    "gn:admin2_code":"42.0",
    "gn:asciiname":"Beizionys",
    "gn:country_code":"LT",
    "gn:dem":194,
    "gn:feature_class":"P",
    "gn:feature_code":"PPL",
    "gn:name":"Bei\u017eionys",
    "gn:population":0,
    "gn:timezone":"Europe/Vilnius",
    "iso:country":"LT",
    "name:eng_x_preferred":[
        "Bei\u017eionys"
    ],
    "name:rus_x_preferred":[
        "\u0411\u0435\u0439\u0436\u0435\u043d\u0438\u0441"
    ],
    "name:und_x_variant":[
        "Bei\u017eoni\u0173",
        "Bei\u017eonys",
        "Beizhonis",
        "Beyzhenis",
        "Bei\u017eionys"
    ],
    "wof:name":"Beizionys",
    "wof:placetype":"locality"
},
  "geometry": {"coordinates":[24.48496,54.6828],"type":"Point"}
}