{
  "type": "Feature",
  "properties": {
    "gn:admin1_code":"60",
    "gn:admin2_code":"67.0",
    "gn:asciiname":"Ragujai",
    "gn:country_code":"LT",
    "gn:dem":34,
    "gn:feature_class":"P",
    "gn:feature_code":"PPL",
    "gn:name":"Ragujai",
    "gn:population":0,
    "gn:timezone":"Europe/Vilnius",
    "iso:country":"LT",
    "name:lit_x_preferred":[
        "Ragujai"
    ],
    "wof:name":"Ragujai",
    "wof:placetype":"locality"
},
  "geometry": {"coordinates":[24.45414,56.05998],"type":"Point"}
}