{
  "type": "Feature",
  "properties": {
    "gn:admin1_code":"65",
    "gn:admin2_code":"81.0",
    "gn:asciiname":"Minderiskiai",
    "gn:country_code":"LT",
    "gn:dem":84,
    "gn:feature_class":"P",
    "gn:feature_code":"PPL",
    "gn:name":"Minderi\u0161kiai",
    "gn:population":0,
    "gn:timezone":"Europe/Vilnius",
    "iso:country":"LT",
    "name:lit_x_preferred":[
        "Minderi\u0161kiai"
    ],
    "wof:name":"Minderiskiai",
    "wof:placetype":"locality"
},
  "geometry": {"coordinates":[24.59513,55.09204],"type":"Point"}
}