{
  "type": "Feature",
  "properties": {
    "gn:admin1_code":"65",
    "gn:admin2_code":"85.0",
    "gn:asciiname":"Dabrai",
    "gn:country_code":"LT",
    "gn:dem":171,
    "gn:feature_class":"P",
    "gn:feature_code":"PPL",
    "gn:name":"Dabrai",
    "gn:population":0,
    "gn:timezone":"Europe/Vilnius",
    "iso:country":"LT",
    "name:lit_x_preferred":[
        "Dabrai"
    ],
    "wof:name":"Dabrai",
    "wof:placetype":"locality"
},
  "geometry": {"coordinates":[24.83561,54.18084],"type":"Point"}
}