{
  "type": "Feature",
  "properties": {
    "gn:admin1_code":"57",
    "gn:admin2_code":"69.0",
    "gn:asciiname":"Utos Sruoga",
    "gn:country_code":"LT",
    "gn:dem":102,
    "gn:feature_class":"P",
    "gn:feature_code":"PPL",
    "gn:name":"\u016atos Sruoga",
    "gn:population":0,
    "gn:timezone":"Europe/Vilnius",
    "iso:country":"LT",
    "name:lit_x_preferred":[
        "\u016atos Sruoga"
    ],
    "wof:name":"Utos Sruoga",
    "wof:placetype":"locality"
},
  "geometry": {"coordinates":[23.75302000000001,54.59268],"type":"Point"}
}