{
  "type": "Feature",
  "properties": {
    "gn:admin1_code":"65",
    "gn:admin2_code":"81.0",
    "gn:asciiname":"Miliunai",
    "gn:country_code":"LT",
    "gn:dem":80,
    "gn:feature_class":"P",
    "gn:feature_code":"PPL",
    "gn:name":"Mili\u016bnai",
    "gn:population":0,
    "gn:timezone":"Europe/Vilnius",
    "iso:country":"LT",
    "name:lit_x_preferred":[
        "Mili\u016bnai"
    ],
    "wof:name":"Miliunai",
    "wof:placetype":"locality"
},
  "geometry": {"coordinates":[24.56169,55.32921],"type":"Point"}
}