{
  "type": "Feature",
  "properties": {
    "gn:admin1_code":"65.0",
    "gn:admin2_code":"79.0",
    "gn:asciiname":"Skleriai",
    "gn:country_code":"LT",
    "gn:dem":147,
    "gn:feature_class":"P",
    "gn:feature_code":"PPL",
    "gn:name":"\u0160kl\u0117riai",
    "gn:population":0,
    "gn:timezone":"Europe/Vilnius",
    "iso:country":"LT",
    "name:lit_x_preferred":[
        "\u0160kl\u0117riai"
    ],
    "name:lit_x_variant":[
        "\u0160kleriai"
    ],
    "wof:name":"Skleriai",
    "wof:placetype":"locality"
},
  "geometry": {"coordinates":[24.87396,54.56485],"type":"Point"}
}