{
  "type": "Feature",
  "properties": {
    "gn:admin1_code":"62.0",
    "gn:admin2_code":"94.0",
    "gn:asciiname":"Zvirblaukys",
    "gn:country_code":"LT",
    "gn:dem":55,
    "gn:feature_class":"P",
    "gn:feature_code":"PPL",
    "gn:name":"\u017dvirblaukys",
    "gn:population":0,
    "gn:timezone":"Europe/Vilnius",
    "iso:country":"LT",
    "name:und_x_variant":[
        "Zhvirblavka",
        "\u017dvirblaukys"
    ],
    "wof:name":"Zvirblaukys",
    "wof:placetype":"locality"
},
  "geometry": {"coordinates":[22.90217,55.26921],"type":"Point"}
}