{
  "type": "Feature",
  "properties": {
    "gn:admin1_code":"60",
    "gn:admin2_code":"57.0",
    "gn:asciiname":"Plundakai",
    "gn:country_code":"LT",
    "gn:dem":97,
    "gn:feature_class":"P",
    "gn:feature_code":"PPL",
    "gn:name":"Plundakai",
    "gn:population":0,
    "gn:timezone":"Europe/Vilnius",
    "iso:country":"LT",
    "name:lit_x_preferred":[
        "Plundakai"
    ],
    "wof:name":"Plundakai",
    "wof:placetype":"locality"
},
  "geometry": {"coordinates":[25.04122000000001,55.84015],"type":"Point"}
}