{
  "type": "Feature",
  "properties": {
    "gn:admin1_code":"64",
    "gn:admin2_code":"43.0",
    "gn:asciiname":"Kiviskes",
    "gn:country_code":"LT",
    "gn:dem":161,
    "gn:feature_class":"P",
    "gn:feature_code":"PPL",
    "gn:name":"Kivi\u0161k\u0117s",
    "gn:population":0,
    "gn:timezone":"Europe/Vilnius",
    "iso:country":"LT",
    "name:lit_x_preferred":[
        "Kivi\u0161k\u0117s"
    ],
    "wof:name":"Kiviskes",
    "wof:placetype":"locality"
},
  "geometry": {"coordinates":[26.18076,55.78961],"type":"Point"}
}