{
  "type": "Feature",
  "properties": {
    "gn:admin1_code":"65.0",
    "gn:admin2_code":"89.0",
    "gn:asciiname":"Virsuliai",
    "gn:country_code":"LT",
    "gn:dem":128,
    "gn:feature_class":"P",
    "gn:feature_code":"PPL",
    "gn:name":"Vir\u0161uliai",
    "gn:population":0,
    "gn:timezone":"Europe/Vilnius",
    "iso:country":"LT",
    "name:lit_x_preferred":[
        "Vir\u0161uliai"
    ],
    "wof:name":"Virsuliai",
    "wof:placetype":"locality"
},
  "geometry": {"coordinates":[25.02757,54.94216],"type":"Point"}
}