{
  "type": "Feature",
  "properties": {
    "gn:admin1_code":"65",
    "gn:admin2_code":"13.0",
    "gn:asciiname":"Skrabine",
    "gn:country_code":"LT",
    "gn:dem":210,
    "gn:feature_class":"P",
    "gn:feature_code":"PPL",
    "gn:name":"Skrabin\u0117",
    "gn:population":0,
    "gn:timezone":"Europe/Vilnius",
    "iso:country":"LT",
    "name:lit_x_preferred":[
        "Skrabin\u0117"
    ],
    "wof:name":"Skrabine",
    "wof:placetype":"locality"
},
  "geometry": {"coordinates":[25.41457,54.60805],"type":"Point"}
}