{
  "type": "Feature",
  "properties": {
    "gn:admin1_code":"61.0",
    "gn:admin2_code":"54.0",
    "gn:asciiname":"Spirgiai",
    "gn:country_code":"LT",
    "gn:dem":153,
    "gn:feature_class":"P",
    "gn:feature_code":"PPL",
    "gn:name":"Spirgiai",
    "gn:population":0,
    "gn:timezone":"Europe/Vilnius",
    "iso:country":"LT",
    "name:und_x_variant":[
        "Spirgyay",
        "Spirgiai"
    ],
    "wof:name":"Spirgiai",
    "wof:placetype":"locality"
},
  "geometry": {"coordinates":[22.60487,55.65709],"type":"Point"}
}