{
  "type": "Feature",
  "properties": {
    "gn:admin1_code":"60.0",
    "gn:admin2_code":"36.0",
    "gn:asciiname":"Mockunai",
    "gn:country_code":"LT",
    "gn:dem":62,
    "gn:feature_class":"P",
    "gn:feature_code":"PPL",
    "gn:name":"Mock\u016bnai",
    "gn:population":0,
    "gn:timezone":"Europe/Vilnius",
    "iso:country":"LT",
    "name:und_x_variant":[
        "Motskunay",
        "Mock\u016bnai"
    ],
    "wof:name":"Mockunai",
    "wof:placetype":"locality"
},
  "geometry": {"coordinates":[24.73861,56.00558],"type":"Point"}
}