{
  "type": "Feature",
  "properties": {
    "gn:admin1_code":"59.0",
    "gn:admin2_code":"48.0",
    "gn:asciiname":"Tarprubeziai",
    "gn:country_code":"LT",
    "gn:dem":139,
    "gn:feature_class":"P",
    "gn:feature_code":"PPL",
    "gn:name":"Tarprube\u017eiai",
    "gn:population":0,
    "gn:timezone":"Europe/Vilnius",
    "iso:country":"LT",
    "name:lit_x_preferred":[
        "Tarprube\u017eiai"
    ],
    "wof:name":"Tarprubeziai",
    "wof:placetype":"locality"
},
  "geometry": {"coordinates":[23.12938,54.45392],"type":"Point"}
}