{
  "type": "Feature",
  "properties": {
    "gn:admin1_code":"56.0",
    "gn:admin2_code":"11.0",
    "gn:asciiname":"Sarkiskiai",
    "gn:country_code":"LT",
    "gn:dem":149,
    "gn:feature_class":"P",
    "gn:feature_code":"PPL",
    "gn:name":"\u0160arki\u0161kiai",
    "gn:population":0,
    "gn:timezone":"Europe/Vilnius",
    "iso:country":"LT",
    "name:lit_x_preferred":[
        "\u0160arki\u0161kiai"
    ],
    "wof:name":"Sarkiskiai",
    "wof:placetype":"locality"
},
  "geometry": {"coordinates":[23.58174,54.35284],"type":"Point"}
}