{
  "type": "Feature",
  "properties": {
    "gn:admin1_code":"59",
    "gn:admin2_code":"39.0",
    "gn:asciiname":"Dotamai",
    "gn:country_code":"LT",
    "gn:dem":184,
    "gn:feature_class":"P",
    "gn:feature_code":"PPL",
    "gn:name":"Dotamai",
    "gn:population":0,
    "gn:timezone":"Europe/Vilnius",
    "iso:country":"LT",
    "name:lit_x_preferred":[
        "Dotamai"
    ],
    "wof:name":"Dotamai",
    "wof:placetype":"locality"
},
  "geometry": {"coordinates":[22.96375,54.45307],"type":"Point"}
}