{
  "type": "Feature",
  "properties": {
    "gn:admin1_code":"59.0",
    "gn:admin2_code":"39.0",
    "gn:asciiname":"Navininkai",
    "gn:country_code":"LT",
    "gn:dem":58,
    "gn:feature_class":"P",
    "gn:feature_code":"PPL",
    "gn:name":"Navininkai",
    "gn:population":0,
    "gn:timezone":"Europe/Vilnius",
    "iso:country":"LT",
    "name:und_x_variant":[
        "Novinikay",
        "Navininkai"
    ],
    "wof:name":"Navininkai",
    "wof:placetype":"locality"
},
  "geometry": {"coordinates":[23.06122,54.69059],"type":"Point"}
}