{
  "type": "Feature",
  "properties": {
    "gn:admin1_code":"60.0",
    "gn:admin2_code":"27.0",
    "gn:asciiname":"Radviliskiai",
    "gn:country_code":"LT",
    "gn:dem":52,
    "gn:feature_class":"P",
    "gn:feature_code":"PPL",
    "gn:name":"Radvili\u0161kiai",
    "gn:population":0,
    "gn:timezone":"Europe/Vilnius",
    "iso:country":"LT",
    "name:lit_x_preferred":[
        "Radvili\u0161kiai"
    ],
    "name:und_x_variant":[
        "Radvilishki",
        "Radvilishkis",
        "Radvili\u0161kis"
    ],
    "wof:name":"Radviliskiai",
    "wof:placetype":"locality"
},
  "geometry": {"coordinates":[24.14822,55.47605],"type":"Point"}
}