{
  "type": "Feature",
  "properties": {
    "gn:admin1_code":"64.0",
    "gn:admin2_code":"62.0",
    "gn:asciiname":"Pusne",
    "gn:country_code":"LT",
    "gn:dem":143,
    "gn:feature_class":"P",
    "gn:feature_code":"PPL",
    "gn:name":"Pusn\u0117",
    "gn:population":0,
    "gn:timezone":"Europe/Vilnius",
    "iso:country":"LT",
    "name:eng_x_preferred":[
        "Pusn\u0117"
    ],
    "name:rus_x_preferred":[
        "\u041f\u0443\u0441\u043d\u0435"
    ],
    "name:und_x_variant":[
        "Pusn\u0117s"
    ],
    "wof:name":"Pusne",
    "wof:placetype":"locality"
},
  "geometry": {"coordinates":[25.1884,55.15],"type":"Point"}
}