{
  "type": "Feature",
  "properties": {
    "gn:admin1_code":"62.0",
    "gn:admin2_code":"77.0",
    "gn:asciiname":"Trumpininkai",
    "gn:country_code":"LT",
    "gn:dem":46,
    "gn:feature_class":"P",
    "gn:feature_code":"PPL",
    "gn:name":"Trumpininkai",
    "gn:population":0,
    "gn:timezone":"Europe/Vilnius",
    "iso:country":"LT",
    "name:und_x_variant":[
        "Trumpeniki",
        "Trumpininkay",
        "Trumpininkai"
    ],
    "wof:name":"Trumpininkai",
    "wof:placetype":"locality"
},
  "geometry": {"coordinates":[21.91826,55.28179],"type":"Point"}
}