{
  "type": "Feature",
  "properties": {
    "gn:admin1_code":"58.0",
    "gn:admin2_code":"88.0",
    "gn:asciiname":"Vileikiai",
    "gn:country_code":"LT",
    "gn:dem":14,
    "gn:feature_class":"P",
    "gn:feature_code":"PPL",
    "gn:name":"Vileikiai",
    "gn:population":0,
    "gn:timezone":"Europe/Vilnius",
    "iso:country":"LT",
    "name:und_x_variant":[
        "Vileikai",
        "Vileykyay",
        "Villyayken",
        "Vileikiai"
    ],
    "wof:name":"Vileikiai",
    "wof:placetype":"locality"
},
  "geometry": {"coordinates":[21.5127,55.2929],"type":"Point"}
}