{
  "type": "Feature",
  "properties": {
    "gn:admin1_code":"65.0",
    "gn:admin2_code":"85.0",
    "gn:asciiname":"Zaltunai",
    "gn:country_code":"LT",
    "gn:dem":203,
    "gn:feature_class":"P",
    "gn:feature_code":"PPL",
    "gn:name":"\u017dalt\u016bnai",
    "gn:population":0,
    "gn:timezone":"Europe/Vilnius",
    "iso:country":"LT",
    "name:und_x_variant":[
        "Zholtuny",
        "\u017dalt\u016bnai"
    ],
    "wof:name":"Zaltunai",
    "wof:placetype":"locality"
},
  "geometry": {"coordinates":[25.56263,54.40043000000001],"type":"Point"}
}