{
  "type": "Feature",
  "properties": {
    "gn:admin1_code":"58.0",
    "gn:admin2_code":"21.0",
    "gn:asciiname":"Rusinai",
    "gn:country_code":"LT",
    "gn:dem":72,
    "gn:feature_class":"P",
    "gn:feature_code":"PPL",
    "gn:name":"Rusinai",
    "gn:population":0,
    "gn:timezone":"Europe/Vilnius",
    "iso:country":"LT",
    "name:und_x_variant":[
        "Rusinay",
        "Rusinai"
    ],
    "wof:name":"Rusinai",
    "wof:placetype":"locality"
},
  "geometry": {"coordinates":[21.59684,55.66362],"type":"Point"}
}