{
  "type": "Feature",
  "properties": {
    "gn:admin1_code":"62",
    "gn:admin2_code":"77.0",
    "gn:asciiname":"Vylusciai",
    "gn:country_code":"LT",
    "gn:dem":48,
    "gn:feature_class":"P",
    "gn:feature_code":"PPL",
    "gn:name":"Vyl\u016bsciai",
    "gn:population":0,
    "gn:timezone":"Europe/Vilnius",
    "iso:country":"LT",
    "name:lit_x_preferred":[
        "Vyl\u016bsciai"
    ],
    "wof:name":"Vylusciai",
    "wof:placetype":"locality"
},
  "geometry": {"coordinates":[22.01588,55.29998000000001],"type":"Point"}
}