{
  "type": "Feature",
  "properties": {
    "gn:admin1_code":"59.0",
    "gn:admin2_code":"84.0",
    "gn:asciiname":"Dievaiciai",
    "gn:country_code":"LT",
    "gn:dem":35,
    "gn:feature_class":"P",
    "gn:feature_code":"PPL",
    "gn:name":"Dievai\u010diai",
    "gn:population":0,
    "gn:timezone":"Europe/Vilnius",
    "iso:country":"LT",
    "name:und_x_variant":[
        "Devaytse",
        "Dievai\u010diai"
    ],
    "wof:name":"Dievaiciai",
    "wof:placetype":"locality"
},
  "geometry": {"coordinates":[22.71392,55.02076],"type":"Point"}
}