{
  "type": "Feature",
  "properties": {
    "gn:admin1_code":"63.0",
    "gn:admin2_code":"78.0",
    "gn:asciiname":"Vydmantai",
    "gn:country_code":"LT",
    "gn:dem":175,
    "gn:feature_class":"P",
    "gn:feature_code":"PPL",
    "gn:name":"Vydmantai",
    "gn:population":0,
    "gn:timezone":"Europe/Vilnius",
    "iso:country":"LT",
    "name:und_x_variant":[
        "Vidiritis",
        "Vydmantai"
    ],
    "wof:name":"Vydmantai",
    "wof:placetype":"locality"
},
  "geometry": {"coordinates":[22.27189,55.75441],"type":"Point"}
}