{
  "type": "Feature",
  "properties": {
    "gn:admin1_code":"0.0",
    "gn:asciiname":"Babaline",
    "gn:country_code":"LT",
    "gn:dem":97,
    "gn:feature_class":"P",
    "gn:feature_code":"PPL",
    "gn:name":"Babalin\u0117",
    "gn:population":0,
    "gn:timezone":"Europe/Vilnius",
    "iso:country":"LT",
    "wof:name":"Babaline",
    "wof:placetype":"locality"
},
  "geometry": {"coordinates":[23.43333,54.51667],"type":"Point"}
}