{
  "type": "Feature",
  "properties": {
    "gn:admin1_code":"64",
    "gn:admin2_code":"43.0",
    "gn:asciiname":"Slaveniskis",
    "gn:country_code":"LT",
    "gn:dem":163,
    "gn:feature_class":"P",
    "gn:feature_code":"PPL",
    "gn:name":"Slav\u0117ni\u0161kis",
    "gn:population":0,
    "gn:timezone":"Europe/Vilnius",
    "iso:country":"LT",
    "name:lit_x_preferred":[
        "Slav\u0117ni\u0161kis"
    ],
    "wof:name":"Slaveniskis",
    "wof:placetype":"locality"
},
  "geometry": {"coordinates":[26.03725,55.88874000000001],"type":"Point"}
}