{
  "type": "Feature",
  "properties": {
    "gn:admin1_code":"57.0",
    "gn:admin2_code":"53.0",
    "gn:asciiname":"Cereliai",
    "gn:country_code":"LT",
    "gn:dem":68,
    "gn:feature_class":"P",
    "gn:feature_code":"PPL",
    "gn:name":"\u010cereliai",
    "gn:population":0,
    "gn:timezone":"Europe/Vilnius",
    "iso:country":"LT",
    "name:und_x_variant":[
        "Chereli",
        "\u010cereliai"
    ],
    "wof:name":"Cereliai",
    "wof:placetype":"locality"
},
  "geometry": {"coordinates":[24.32394,55.36744],"type":"Point"}
}