{
  "type": "Feature",
  "properties": {
    "gn:admin1_code":"58",
    "gn:admin2_code":"75.0",
    "gn:asciiname":"Trumplauke",
    "gn:country_code":"LT",
    "gn:dem":87,
    "gn:feature_class":"P",
    "gn:feature_code":"PPL",
    "gn:name":"Trumplauk\u0117",
    "gn:population":0,
    "gn:timezone":"Europe/Vilnius",
    "iso:country":"LT",
    "name:lit_x_preferred":[
        "Trumplauk\u0117"
    ],
    "wof:name":"Trumplauke",
    "wof:placetype":"locality"
},
  "geometry": {"coordinates":[21.8125,56.21847],"type":"Point"}
}