{
  "type": "Feature",
  "properties": {
    "gn:admin1_code":"65",
    "gn:admin2_code":"42.0",
    "gn:asciiname":"Jona",
    "gn:country_code":"LT",
    "gn:dem":125,
    "gn:feature_class":"P",
    "gn:feature_code":"PPL",
    "gn:name":"Jona",
    "gn:population":0,
    "gn:timezone":"Europe/Vilnius",
    "iso:country":"LT",
    "name:ara_x_preferred":[
        "\u064a\u0648\u0646\u0627"
    ],
    "name:ceb_x_preferred":[
        "Jona"
    ],
    "name:deu_x_preferred":[
        "Jona"
    ],
    "name:fra_x_preferred":[
        "Jona"
    ],
    "name:ita_x_preferred":[
        "Jona"
    ],
    "name:kaz_x_preferred":[
        "\u0419\u043e\u043d\u0430"
    ],
    "name:lat_x_preferred":[
        "Iohanna"
    ],
    "name:lit_x_preferred":[
        "Jona"
    ],
    "name:nld_x_preferred":[
        "Jona"
    ],
    "name:nor_x_preferred":[
        "Jona"
    ],
    "name:pms_x_preferred":[
        "Jona"
    ],
    "name:por_x_preferred":[
        "Jona"
    ],
    "name:roh_x_preferred":[
        "Jona"
    ],
    "name:rus_x_preferred":[
        "\u0419\u043e\u043d\u0430"
    ],
    "name:spa_x_preferred":[
        "Jona"
    ],
    "name:swe_x_preferred":[
        "Jona"
    ],
    "name:uzb_x_preferred":[
        "Jona"
    ],
    "wof:name":"Jona",
    "wof:placetype":"locality"
},
  "geometry": {"coordinates":[24.76712,54.83366],"type":"Point"}
}