{
  "type": "Feature",
  "properties": {
    "gn:admin1_code":"60",
    "gn:admin2_code":"67.0",
    "gn:asciiname":"Ozkyciai",
    "gn:country_code":"LT",
    "gn:dem":46,
    "gn:feature_class":"P",
    "gn:feature_code":"PPL",
    "gn:name":"O\u017eky\u010diai",
    "gn:population":0,
    "gn:timezone":"Europe/Vilnius",
    "iso:country":"LT",
    "name:lit_x_preferred":[
        "O\u017eky\u010diai"
    ],
    "wof:name":"Ozkyciai",
    "wof:placetype":"locality"
},
  "geometry": {"coordinates":[24.21771,55.89255],"type":"Point"}
}