{
  "type": "Feature",
  "properties": {
    "gn:admin1_code":"58.0",
    "gn:admin2_code":"56.0",
    "gn:asciiname":"Budriai",
    "gn:country_code":"LT",
    "gn:dem":65,
    "gn:feature_class":"P",
    "gn:feature_code":"PPL",
    "gn:name":"Budriai",
    "gn:population":0,
    "gn:timezone":"Europe/Vilnius",
    "iso:country":"LT",
    "name:und_x_variant":[
        "Budryay",
        "Budri\u0173",
        "Budriai"
    ],
    "wof:name":"Budriai",
    "wof:placetype":"locality"
},
  "geometry": {"coordinates":[21.45255,55.87673],"type":"Point"}
}