{
  "type": "Feature",
  "properties": {
    "gn:admin1_code":"64",
    "gn:admin2_code":"82.0",
    "gn:asciiname":"Bedziai",
    "gn:country_code":"LT",
    "gn:dem":105,
    "gn:feature_class":"P",
    "gn:feature_code":"PPL",
    "gn:name":"B\u0117d\u017eiai",
    "gn:population":0,
    "gn:timezone":"Europe/Vilnius",
    "iso:country":"LT",
    "name:lit_x_preferred":[
        "B\u0117d\u017eiai"
    ],
    "wof:name":"Bedziai",
    "wof:placetype":"locality"
},
  "geometry": {"coordinates":[25.45908,55.60143000000001],"type":"Point"}
}