{
  "type": "Feature",
  "properties": {
    "gn:admin1_code":"59.0",
    "gn:admin2_code":"39.0",
    "gn:asciiname":"Sausbaliai",
    "gn:country_code":"LT",
    "gn:dem":46,
    "gn:feature_class":"P",
    "gn:feature_code":"PPL",
    "gn:name":"Sausbaliai",
    "gn:population":0,
    "gn:timezone":"Europe/Vilnius",
    "iso:country":"LT",
    "name:lit_x_preferred":[
        "Sausbaliai"
    ],
    "name:lit_x_variant":[
        "Sausballai"
    ],
    "wof:name":"Sausbaliai",
    "wof:placetype":"locality"
},
  "geometry": {"coordinates":[23.21963,54.70077],"type":"Point"}
}