{
  "type": "Feature",
  "properties": {
    "gn:admin1_code":"56.0",
    "gn:admin2_code":"11.0",
    "gn:asciiname":"Janauka",
    "gn:country_code":"LT",
    "gn:dem":141,
    "gn:feature_class":"P",
    "gn:feature_code":"PPL",
    "gn:name":"Janauka",
    "gn:population":0,
    "gn:timezone":"Europe/Vilnius",
    "iso:country":"LT",
    "name:lit_x_preferred":[
        "Janauka"
    ],
    "name:und_x_variant":[
        "Yanovka",
        "Joni\u0161k\u0117s"
    ],
    "wof:name":"Janauka",
    "wof:placetype":"locality"
},
  "geometry": {"coordinates":[24.31026,54.49433000000001],"type":"Point"}
}