{
  "type": "Feature",
  "properties": {
    "gn:admin1_code":"61.0",
    "gn:admin2_code":"71.0",
    "gn:asciiname":"Prasciunai",
    "gn:country_code":"LT",
    "gn:dem":75,
    "gn:feature_class":"P",
    "gn:feature_code":"PPL",
    "gn:name":"Pra\u0161\u010di\u016bnai",
    "gn:population":0,
    "gn:timezone":"Europe/Vilnius",
    "iso:country":"LT",
    "name:und_x_variant":[
        "Prashunay",
        "Pra\u0161\u010di\u016bnai"
    ],
    "wof:name":"Prasciunai",
    "wof:placetype":"locality"
},
  "geometry": {"coordinates":[23.94329,55.6746],"type":"Point"}
}