{
  "type": "Feature",
  "properties": {
    "gn:admin1_code":"65.0",
    "gn:admin2_code":"42.0",
    "gn:asciiname":"Zikaronys",
    "gn:country_code":"LT",
    "gn:dem":143,
    "gn:feature_class":"P",
    "gn:feature_code":"PPL",
    "gn:name":"\u017dikaronys",
    "gn:population":0,
    "gn:timezone":"Europe/Vilnius",
    "iso:country":"LT",
    "name:und_x_variant":[
        "Lingiai",
        "Zhukharony",
        "\u017dikaronys"
    ],
    "wof:name":"Zikaronys",
    "wof:placetype":"locality"
},
  "geometry": {"coordinates":[24.53379,54.71345],"type":"Point"}
}