{
  "type": "Feature",
  "properties": {
    "gn:admin1_code":"64",
    "gn:admin2_code":"43.0",
    "gn:asciiname":"Liminaselis",
    "gn:country_code":"LT",
    "gn:dem":157,
    "gn:feature_class":"P",
    "gn:feature_code":"PPL",
    "gn:name":"Liminas\u0117lis",
    "gn:population":0,
    "gn:timezone":"Europe/Vilnius",
    "iso:country":"LT",
    "name:lit_x_preferred":[
        "Liminas\u0117lis"
    ],
    "wof:name":"Liminaselis",
    "wof:placetype":"locality"
},
  "geometry": {"coordinates":[26.10726,55.67479],"type":"Point"}
}