{
  "type": "Feature",
  "properties": {
    "gn:admin1_code":"57.0",
    "gn:admin2_code":"49.0",
    "gn:asciiname":"Palomene",
    "gn:country_code":"LT",
    "gn:dem":75,
    "gn:feature_class":"P",
    "gn:feature_code":"PPL",
    "gn:name":"Palomen\u0117",
    "gn:population":0,
    "gn:timezone":"Europe/Vilnius",
    "iso:country":"LT",
    "name:und_x_variant":[
        "Polomeny",
        "Palomenis",
        "Palomen\u0117"
    ],
    "wof:name":"Palomene",
    "wof:placetype":"locality"
},
  "geometry": {"coordinates":[24.46296,54.93659],"type":"Point"}
}