{
  "type": "Feature",
  "properties": {
    "gn:admin1_code":"60",
    "gn:admin2_code":"73.0",
    "gn:asciiname":"Zeliunai",
    "gn:country_code":"LT",
    "gn:dem":151,
    "gn:feature_class":"P",
    "gn:feature_code":"PPL",
    "gn:name":"\u017deli\u016bnai",
    "gn:population":0,
    "gn:timezone":"Europe/Vilnius",
    "iso:country":"LT",
    "name:lit_x_preferred":[
        "\u017deli\u016bnai"
    ],
    "wof:name":"Zeliunai",
    "wof:placetype":"locality"
},
  "geometry": {"coordinates":[25.94234,55.90821999999999],"type":"Point"}
}