{
  "type": "Feature",
  "properties": {
    "gn:admin1_code":"56",
    "gn:admin2_code":"11.0",
    "gn:asciiname":"Dirmiskes",
    "gn:country_code":"LT",
    "gn:dem":139,
    "gn:feature_class":"P",
    "gn:feature_code":"PPL",
    "gn:name":"Dirmi\u0161k\u0117s",
    "gn:population":0,
    "gn:timezone":"Europe/Vilnius",
    "iso:country":"LT",
    "name:lit_x_preferred":[
        "Dirmi\u0161k\u0117s"
    ],
    "wof:name":"Dirmiskes",
    "wof:placetype":"locality"
},
  "geometry": {"coordinates":[23.94763,54.27735],"type":"Point"}
}