{
  "type": "Feature",
  "properties": {
    "gn:admin1_code":"60.0",
    "gn:admin2_code":"73.0",
    "gn:asciiname":"Rasciunai",
    "gn:country_code":"LT",
    "gn:dem":77,
    "gn:feature_class":"P",
    "gn:feature_code":"PPL",
    "gn:name":"Ra\u0161\u010di\u016bnai",
    "gn:population":0,
    "gn:timezone":"Europe/Vilnius",
    "iso:country":"LT",
    "name:und_x_variant":[
        "Ra\u0161\u010di\u016bn\u0173",
        "Rashchyunay",
        "Ra\u0161\u010di\u016bnai"
    ],
    "wof:name":"Rasciunai",
    "wof:placetype":"locality"
},
  "geometry": {"coordinates":[25.16087000000001,56.09543000000001],"type":"Point"}
}