{
  "type": "Feature",
  "properties": {
    "gn:admin1_code":"59",
    "gn:admin2_code":"84.0",
    "gn:asciiname":"Vidusilis",
    "gn:country_code":"LT",
    "gn:dem":59,
    "gn:feature_class":"P",
    "gn:feature_code":"PPL",
    "gn:name":"Vidu\u0161ilis",
    "gn:population":0,
    "gn:timezone":"Europe/Vilnius",
    "iso:country":"LT",
    "name:lit_x_preferred":[
        "Vidu\u0161ilis"
    ],
    "wof:name":"Vidusilis",
    "wof:placetype":"locality"
},
  "geometry": {"coordinates":[23.32033,54.95394],"type":"Point"}
}