{
  "type": "Feature",
  "properties": {
    "gn:admin1_code":"62.0",
    "gn:admin2_code":"63.0",
    "gn:asciiname":"Minjotai",
    "gn:country_code":"LT",
    "gn:dem":30,
    "gn:feature_class":"P",
    "gn:feature_code":"PPL",
    "gn:name":"Minjotai",
    "gn:population":0,
    "gn:timezone":"Europe/Vilnius",
    "iso:country":"LT",
    "name:und_x_variant":[
        "Vil\u2019pin",
        "Minyotay",
        "Minjotai"
    ],
    "wof:name":"Minjotai",
    "wof:placetype":"locality"
},
  "geometry": {"coordinates":[21.90586,55.2646],"type":"Point"}
}