{
  "type": "Feature",
  "properties": {
    "gn:admin1_code":"60",
    "gn:admin2_code":"36.0",
    "gn:asciiname":"Triskai",
    "gn:country_code":"LT",
    "gn:dem":43,
    "gn:feature_class":"P",
    "gn:feature_code":"PPL",
    "gn:name":"Tri\u0161kai",
    "gn:population":0,
    "gn:timezone":"Europe/Vilnius",
    "iso:country":"LT",
    "name:lit_x_preferred":[
        "Tri\u0161kai"
    ],
    "wof:name":"Triskai",
    "wof:placetype":"locality"
},
  "geometry": {"coordinates":[24.59915,56.25286],"type":"Point"}
}