{
  "type": "Feature",
  "properties": {
    "gn:admin1_code":"64",
    "gn:admin2_code":"43.0",
    "gn:asciiname":"Dulkiske",
    "gn:country_code":"LT",
    "gn:dem":146,
    "gn:feature_class":"P",
    "gn:feature_code":"PPL",
    "gn:name":"Dulki\u0161k\u0117",
    "gn:population":0,
    "gn:timezone":"Europe/Vilnius",
    "iso:country":"LT",
    "name:lit_x_preferred":[
        "Dulki\u0161k\u0117"
    ],
    "wof:name":"Dulkiske",
    "wof:placetype":"locality"
},
  "geometry": {"coordinates":[26.43063,55.67638],"type":"Point"}
}