{
  "type": "Feature",
  "properties": {
    "gn:admin1_code":"58.0",
    "gn:admin2_code":"21.0",
    "gn:asciiname":"Trepkalniai",
    "gn:country_code":"LT",
    "gn:dem":58,
    "gn:feature_class":"P",
    "gn:feature_code":"PPL",
    "gn:name":"Trepkalniai",
    "gn:population":0,
    "gn:timezone":"Europe/Vilnius",
    "iso:country":"LT",
    "name:lit_x_preferred":[
        "Trepkalniai"
    ],
    "name:und_x_variant":[
        "Trepikalne",
        "Trepkalnis"
    ],
    "wof:name":"Trepkalniai",
    "wof:placetype":"locality"
},
  "geometry": {"coordinates":[21.59682,55.60986],"type":"Point"}
}