{
  "type": "Feature",
  "properties": {
    "gn:admin1_code":"56.0",
    "gn:admin2_code":"38.0",
    "gn:asciiname":"Kibysiai",
    "gn:country_code":"LT",
    "gn:dem":131,
    "gn:feature_class":"P",
    "gn:feature_code":"PPL",
    "gn:name":"Kiby\u0161iai",
    "gn:population":0,
    "gn:timezone":"Europe/Vilnius",
    "iso:country":"LT",
    "name:ceb_x_preferred":[
        "Kiby\u0161iai"
    ],
    "name:lit_x_preferred":[
        "Kiby\u0161iai"
    ],
    "name:swe_x_preferred":[
        "Kiby\u0161iai"
    ],
    "name:und_x_variant":[
        "Kibishi",
        "Kibishyay",
        "Kiby\u0161iai"
    ],
    "wof:name":"Kibysiai",
    "wof:placetype":"locality"
},
  "geometry": {"coordinates":[24.07656,54.15035],"type":"Point"}
}