{
  "type": "Feature",
  "properties": {
    "gn:admin1_code":"61.0",
    "gn:admin2_code":"54.0",
    "gn:asciiname":"Kletiske",
    "gn:country_code":"LT",
    "gn:dem":156,
    "gn:feature_class":"P",
    "gn:feature_code":"PPL",
    "gn:name":"Kleti\u0161k\u0117",
    "gn:population":0,
    "gn:timezone":"Europe/Vilnius",
    "iso:country":"LT",
    "name:und_x_variant":[
        "Kletishke",
        "Kliati\u0161k\u0117s",
        "Kleti\u0161k\u0117"
    ],
    "wof:name":"Kletiske",
    "wof:placetype":"locality"
},
  "geometry": {"coordinates":[22.65841,55.66152],"type":"Point"}
}