{
  "type": "Feature",
  "properties": {
    "gn:admin1_code":"57.0",
    "gn:admin2_code":"53.0",
    "gn:asciiname":"Paskardziai",
    "gn:country_code":"LT",
    "gn:dem":79,
    "gn:feature_class":"P",
    "gn:feature_code":"PPL",
    "gn:name":"Paskard\u017eiai",
    "gn:population":0,
    "gn:timezone":"Europe/Vilnius",
    "iso:country":"LT",
    "name:und_x_variant":[
        "Poskordze",
        "Paskardzhyay",
        "Paskard\u017eiai"
    ],
    "wof:name":"Paskardziai",
    "wof:placetype":"locality"
},
  "geometry": {"coordinates":[23.64863,55.34004],"type":"Point"}
}