{
  "type": "Feature",
  "properties": {
    "gn:admin1_code":"60",
    "gn:admin2_code":"27.0",
    "gn:asciiname":"Bygailiai",
    "gn:country_code":"LT",
    "gn:dem":70,
    "gn:feature_class":"P",
    "gn:feature_code":"PPL",
    "gn:name":"Bygailiai",
    "gn:population":0,
    "gn:timezone":"Europe/Vilnius",
    "iso:country":"LT",
    "name:lit_x_preferred":[
        "Bygailiai"
    ],
    "wof:name":"Bygailiai",
    "wof:placetype":"locality"
},
  "geometry": {"coordinates":[24.67223,55.77697],"type":"Point"}
}