{
  "type": "Feature",
  "properties": {
    "gn:admin1_code":"57.0",
    "gn:admin2_code":"19.0",
    "gn:asciiname":"Altoniskiai",
    "gn:country_code":"LT",
    "gn:dem":61,
    "gn:feature_class":"P",
    "gn:feature_code":"PPL",
    "gn:name":"Altoni\u0161kiai",
    "gn:population":0,
    "gn:timezone":"Europe/Vilnius",
    "iso:country":"LT",
    "name:lit_x_preferred":[
        "Altoni\u0161kiai"
    ],
    "wof:name":"Altoniskiai",
    "wof:placetype":"locality"
},
  "geometry": {"coordinates":[23.58807,54.94677],"type":"Point"}
}