{
  "type": "Feature",
  "properties": {
    "gn:admin1_code":"61",
    "gn:admin2_code":"47.0",
    "gn:asciiname":"Veiksiai",
    "gn:country_code":"LT",
    "gn:dem":44,
    "gn:feature_class":"P",
    "gn:feature_code":"PPL",
    "gn:name":"Veik\u0161iai",
    "gn:population":0,
    "gn:timezone":"Europe/Vilnius",
    "iso:country":"LT",
    "name:lit_x_preferred":[
        "Veik\u0161iai"
    ],
    "wof:name":"Veiksiai",
    "wof:placetype":"locality"
},
  "geometry": {"coordinates":[23.90065,56.28484],"type":"Point"}
}