{
  "type": "Feature",
  "properties": {
    "gn:admin1_code":"64",
    "gn:admin2_code":"62.0",
    "gn:asciiname":"Butkaucizna",
    "gn:country_code":"LT",
    "gn:dem":166,
    "gn:feature_class":"P",
    "gn:feature_code":"PPL",
    "gn:name":"Butkau\u010dizna",
    "gn:population":0,
    "gn:timezone":"Europe/Vilnius",
    "iso:country":"LT",
    "name:lit_x_preferred":[
        "Butkau\u010dizna"
    ],
    "wof:name":"Butkaucizna",
    "wof:placetype":"locality"
},
  "geometry": {"coordinates":[25.5123,55.12568],"type":"Point"}
}