{
  "type": "Feature",
  "properties": {
    "gn:admin1_code":"64",
    "gn:admin2_code":"43.0",
    "gn:asciiname":"Vitkuskes",
    "gn:country_code":"LT",
    "gn:dem":153,
    "gn:feature_class":"P",
    "gn:feature_code":"PPL",
    "gn:name":"Vitku\u0161k\u0117s",
    "gn:population":0,
    "gn:timezone":"Europe/Vilnius",
    "iso:country":"LT",
    "name:lit_x_preferred":[
        "Vitku\u0161k\u0117s"
    ],
    "wof:name":"Vitkuskes",
    "wof:placetype":"locality"
},
  "geometry": {"coordinates":[26.07537,55.63331],"type":"Point"}
}