{
  "type": "Feature",
  "properties": {
    "gn:admin1_code":"61",
    "gn:admin2_code":"65.0",
    "gn:asciiname":"Eibutoniai",
    "gn:country_code":"LT",
    "gn:dem":74,
    "gn:feature_class":"P",
    "gn:feature_code":"PPL",
    "gn:name":"Eibutoniai",
    "gn:population":0,
    "gn:timezone":"Europe/Vilnius",
    "iso:country":"LT",
    "name:lit_x_preferred":[
        "Eibutoniai"
    ],
    "wof:name":"Eibutoniai",
    "wof:placetype":"locality"
},
  "geometry": {"coordinates":[23.82104,55.92309],"type":"Point"}
}