{
  "type": "Feature",
  "properties": {
    "gn:admin1_code":"57",
    "gn:admin2_code":"69.0",
    "gn:asciiname":"Kudirkos",
    "gn:country_code":"LT",
    "gn:dem":83,
    "gn:feature_class":"P",
    "gn:feature_code":"PPL",
    "gn:name":"Kudirkos",
    "gn:population":0,
    "gn:timezone":"Europe/Vilnius",
    "iso:country":"LT",
    "name:lit_x_preferred":[
        "Kudirkos"
    ],
    "wof:name":"Kudirkos",
    "wof:placetype":"locality"
},
  "geometry": {"coordinates":[23.99313,54.7392],"type":"Point"}
}