{
  "type": "Feature",
  "properties": {
    "gn:admin1_code":"59",
    "gn:admin2_code":"58.0",
    "gn:asciiname":"Endziuliai",
    "gn:country_code":"LT",
    "gn:dem":58,
    "gn:feature_class":"P",
    "gn:feature_code":"PPL",
    "gn:name":"Endziuliai",
    "gn:population":0,
    "gn:timezone":"Europe/Vilnius",
    "iso:country":"LT",
    "name:lit_x_preferred":[
        "Endziuliai"
    ],
    "wof:name":"Endziuliai",
    "wof:placetype":"locality"
},
  "geometry": {"coordinates":[23.3553,54.8043],"type":"Point"}
}