{
  "type": "Feature",
  "properties": {
    "gn:admin1_code":"60.0",
    "gn:admin2_code":"73.0",
    "gn:asciiname":"Onuskis",
    "gn:country_code":"LT",
    "gn:dem":118,
    "gn:feature_class":"P",
    "gn:feature_code":"PPL",
    "gn:name":"Onu\u0161kis",
    "gn:population":0,
    "gn:timezone":"Europe/Vilnius",
    "iso:country":"LT",
    "name:eng_x_preferred":[
        "Onu\u0161kis"
    ],
    "name:rus_x_preferred":[
        "\u041e\u043d\u0443\u0448\u043a\u0438\u0441"
    ],
    "name:und_x_variant":[
        "Ganu\u0161i\u0161ki",
        "Onu\u0161i\u0161k\u0117s",
        "Ganushishki",
        "Onushkis",
        "Onu\u0161k\u0117s",
        "Oni\u0161kis",
        "Myasto Ganushishki",
        "Onu\u0161kio",
        "Onu\u0161kis"
    ],
    "wof:name":"Onuskis",
    "wof:placetype":"locality"
},
  "geometry": {"coordinates":[25.53016,56.12881],"type":"Point"}
}