{
  "type": "Feature",
  "properties": {
    "gn:admin1_code":"58.0",
    "gn:admin2_code":"88.0",
    "gn:asciiname":"Miestaliai",
    "gn:country_code":"LT",
    "gn:dem":4,
    "gn:feature_class":"P",
    "gn:feature_code":"PPL",
    "gn:name":"Miestaliai",
    "gn:population":0,
    "gn:timezone":"Europe/Vilnius",
    "iso:country":"LT",
    "name:lit_x_preferred":[
        "Miestaliai"
    ],
    "wof:name":"Miestaliai",
    "wof:placetype":"locality"
},
  "geometry": {"coordinates":[21.49248,55.42685],"type":"Point"}
}