{
  "type": "Feature",
  "properties": {
    "gn:admin1_code":"59",
    "gn:admin2_code":"18.0",
    "gn:asciiname":"Sala",
    "gn:country_code":"LT",
    "gn:dem":98,
    "gn:feature_class":"P",
    "gn:feature_code":"PPL",
    "gn:name":"Sala",
    "gn:population":0,
    "gn:timezone":"Europe/Vilnius",
    "iso:country":"LT",
    "name:lit_x_preferred":[
        "Sala"
    ],
    "wof:name":"Sala",
    "wof:placetype":"locality"
},
  "geometry": {"coordinates":[23.6672,54.56484],"type":"Point"}
}