{
  "type": "Feature",
  "properties": {
    "gn:admin1_code":"62.0",
    "gn:admin2_code":"87.0",
    "gn:asciiname":"Pagrybis",
    "gn:country_code":"LT",
    "gn:dem":159,
    "gn:feature_class":"P",
    "gn:feature_code":"PPL",
    "gn:name":"Pagrybis",
    "gn:population":0,
    "gn:timezone":"Europe/Vilnius",
    "iso:country":"LT",
    "name:und_x_variant":[
        "Pogribyay",
        "Pagrybis"
    ],
    "wof:name":"Pagrybis",
    "wof:placetype":"locality"
},
  "geometry": {"coordinates":[22.437,55.52176],"type":"Point"}
}