{
  "type": "Feature",
  "properties": {
    "gn:admin1_code":"60",
    "gn:admin2_code":"27.0",
    "gn:asciiname":"Simuliskis",
    "gn:country_code":"LT",
    "gn:dem":70,
    "gn:feature_class":"P",
    "gn:feature_code":"PPL",
    "gn:name":"Simuli\u0161kis",
    "gn:population":0,
    "gn:timezone":"Europe/Vilnius",
    "iso:country":"LT",
    "name:lit_x_preferred":[
        "Simuli\u0161kis"
    ],
    "wof:name":"Simuliskis",
    "wof:placetype":"locality"
},
  "geometry": {"coordinates":[24.56237,55.64109000000001],"type":"Point"}
}