{
  "type": "Feature",
  "properties": {
    "gn:admin1_code":"57",
    "gn:admin2_code":"69.0",
    "gn:asciiname":"Kukiskes",
    "gn:country_code":"LT",
    "gn:dem":70,
    "gn:feature_class":"P",
    "gn:feature_code":"PPL",
    "gn:name":"Kuki\u0161k\u0117s",
    "gn:population":0,
    "gn:timezone":"Europe/Vilnius",
    "iso:country":"LT",
    "name:lit_x_preferred":[
        "Kuki\u0161k\u0117s"
    ],
    "wof:name":"Kukiskes",
    "wof:placetype":"locality"
},
  "geometry": {"coordinates":[24.1342,54.5816],"type":"Point"}
}