{
  "type": "Feature",
  "properties": {
    "gn:admin1_code":"62.0",
    "gn:admin2_code":"77.0",
    "gn:asciiname":"Pagramantis",
    "gn:country_code":"LT",
    "gn:dem":43,
    "gn:feature_class":"P",
    "gn:feature_code":"PPL",
    "gn:name":"Pagramantis",
    "gn:population":0,
    "gn:timezone":"Europe/Vilnius",
    "iso:country":"LT",
    "name:eng_x_preferred":[
        "Pagramantis"
    ],
    "name:rus_x_preferred":[
        "\u041f\u0430\u0433\u0440\u0430\u043c\u0430\u043d\u0442\u0438\u0441"
    ],
    "wof:name":"Pagramantis",
    "wof:placetype":"locality"
},
  "geometry": {"coordinates":[22.23192,55.36595],"type":"Point"}
}