{
  "type": "Feature",
  "properties": {
    "gn:admin1_code":"59",
    "gn:admin2_code":"84.0",
    "gn:asciiname":"Asmoniskiai",
    "gn:country_code":"LT",
    "gn:dem":42,
    "gn:feature_class":"P",
    "gn:feature_code":"PPL",
    "gn:name":"A\u0161moni\u0161kiai",
    "gn:population":0,
    "gn:timezone":"Europe/Vilnius",
    "iso:country":"LT",
    "name:lit_x_preferred":[
        "A\u0161moni\u0161kiai"
    ],
    "wof:name":"Asmoniskiai",
    "wof:placetype":"locality"
},
  "geometry": {"coordinates":[22.96532,54.80747],"type":"Point"}
}