{
  "type": "Feature",
  "properties": {
    "gn:admin1_code":"58",
    "gn:admin2_code":"21.0",
    "gn:asciiname":"Klausmyliai",
    "gn:country_code":"LT",
    "gn:dem":25,
    "gn:feature_class":"P",
    "gn:feature_code":"PPL",
    "gn:name":"Klausmyliai",
    "gn:population":0,
    "gn:timezone":"Europe/Vilnius",
    "iso:country":"LT",
    "name:lit_x_preferred":[
        "Klausmyliai"
    ],
    "wof:name":"Klausmyliai",
    "wof:placetype":"locality"
},
  "geometry": {"coordinates":[21.21393,55.7108],"type":"Point"}
}