{
  "type": "Feature",
  "properties": {
    "gn:admin1_code":"56",
    "gn:admin2_code":"38.0",
    "gn:asciiname":"Palkabalis",
    "gn:country_code":"LT",
    "gn:dem":141,
    "gn:feature_class":"P",
    "gn:feature_code":"PPL",
    "gn:name":"Palkabalis",
    "gn:population":0,
    "gn:timezone":"Europe/Vilnius",
    "iso:country":"LT",
    "name:lit_x_preferred":[
        "Palkabalis"
    ],
    "wof:name":"Palkabalis",
    "wof:placetype":"locality"
},
  "geometry": {"coordinates":[24.60745,54.14011],"type":"Point"}
}