{
  "type": "Feature",
  "properties": {
    "gn:admin1_code":"65",
    "gn:admin2_code":"86.0",
    "gn:asciiname":"Misiunai",
    "gn:country_code":"LT",
    "gn:dem":197,
    "gn:feature_class":"P",
    "gn:feature_code":"PPL",
    "gn:name":"Misi\u016bnai",
    "gn:population":0,
    "gn:timezone":"Europe/Vilnius",
    "iso:country":"LT",
    "name:lit_x_preferred":[
        "Misi\u016bnai"
    ],
    "wof:name":"Misiunai",
    "wof:placetype":"locality"
},
  "geometry": {"coordinates":[26.16388,55.19265],"type":"Point"}
}