{
  "type": "Feature",
  "properties": {
    "gn:admin1_code":"59.0",
    "gn:admin2_code":"18.0",
    "gn:asciiname":"Liuliskis",
    "gn:country_code":"LT",
    "gn:dem":93,
    "gn:feature_class":"P",
    "gn:feature_code":"PPL",
    "gn:name":"Li\u016bli\u0161kis",
    "gn:population":0,
    "gn:timezone":"Europe/Vilnius",
    "iso:country":"LT",
    "name:lit_x_preferred":[
        "Li\u016bli\u0161kis"
    ],
    "wof:name":"Liuliskis",
    "wof:placetype":"locality"
},
  "geometry": {"coordinates":[23.55704,54.48163],"type":"Point"}
}