{
  "type": "Feature",
  "properties": {
    "gn:admin1_code":"65",
    "gn:admin2_code":"79.0",
    "gn:asciiname":"Petkeniskes",
    "gn:country_code":"LT",
    "gn:dem":168,
    "gn:feature_class":"P",
    "gn:feature_code":"PPL",
    "gn:name":"Petk\u0117ni\u0161k\u0117s",
    "gn:population":0,
    "gn:timezone":"Europe/Vilnius",
    "iso:country":"LT",
    "name:lit_x_preferred":[
        "Petk\u0117ni\u0161k\u0117s"
    ],
    "wof:name":"Petkeniskes",
    "wof:placetype":"locality"
},
  "geometry": {"coordinates":[24.82495,54.65554],"type":"Point"}
}