{
  "type": "Feature",
  "properties": {
    "gn:admin1_code":"65",
    "gn:admin2_code":"13.0",
    "gn:asciiname":"Kuprioniskes",
    "gn:country_code":"LT",
    "gn:dem":204,
    "gn:feature_class":"P",
    "gn:feature_code":"PPL",
    "gn:name":"Kuprioni\u0161k\u0117s",
    "gn:population":0,
    "gn:timezone":"Europe/Vilnius",
    "iso:country":"LT",
    "name:lit_x_preferred":[
        "Kuprioni\u0161k\u0117s"
    ],
    "wof:name":"Kuprioniskes",
    "wof:placetype":"locality"
},
  "geometry": {"coordinates":[25.32992,54.63593],"type":"Point"}
}