{
  "type": "Feature",
  "properties": {
    "gn:admin1_code":"61",
    "gn:admin2_code":"29.0",
    "gn:asciiname":"Noreikiai",
    "gn:country_code":"LT",
    "gn:dem":107,
    "gn:feature_class":"P",
    "gn:feature_code":"PPL",
    "gn:name":"Noreikiai",
    "gn:population":0,
    "gn:timezone":"Europe/Vilnius",
    "iso:country":"LT",
    "name:lit_x_preferred":[
        "Noreikiai"
    ],
    "wof:name":"Noreikiai",
    "wof:placetype":"locality"
},
  "geometry": {"coordinates":[23.23456,55.97022],"type":"Point"}
}