{
  "type": "Feature",
  "properties": {
    "gn:admin1_code":"64.0",
    "gn:admin2_code":"34.0",
    "gn:asciiname":"Kurkleliai",
    "gn:country_code":"LT",
    "gn:dem":100,
    "gn:feature_class":"P",
    "gn:feature_code":"PPL",
    "gn:name":"Kurkleliai",
    "gn:population":0,
    "gn:timezone":"Europe/Vilnius",
    "iso:country":"LT",
    "name:und_x_variant":[
        "Kurklelyay",
        "Kurkleliai"
    ],
    "wof:name":"Kurkleliai",
    "wof:placetype":"locality"
},
  "geometry": {"coordinates":[25.10968,55.43843],"type":"Point"}
}