{
  "type": "Feature",
  "properties": {
    "gn:admin1_code":"61",
    "gn:admin2_code":"65.0",
    "gn:asciiname":"Papusai",
    "gn:country_code":"LT",
    "gn:dem":51,
    "gn:feature_class":"P",
    "gn:feature_code":"PPL",
    "gn:name":"Papu\u0161ai",
    "gn:population":0,
    "gn:timezone":"Europe/Vilnius",
    "iso:country":"LT",
    "name:lit_x_preferred":[
        "Papu\u0161ai"
    ],
    "wof:name":"Papusai",
    "wof:placetype":"locality"
},
  "geometry": {"coordinates":[24.09381,56.13399],"type":"Point"}
}