{
  "type": "Feature",
  "properties": {
    "gn:admin1_code":"60",
    "gn:admin2_code":"73.0",
    "gn:asciiname":"Razrivka",
    "gn:country_code":"LT",
    "gn:dem":162,
    "gn:feature_class":"P",
    "gn:feature_code":"PPL",
    "gn:name":"Razrivka",
    "gn:population":0,
    "gn:timezone":"Europe/Vilnius",
    "iso:country":"LT",
    "name:lit_x_preferred":[
        "Razrivka"
    ],
    "wof:name":"Razrivka",
    "wof:placetype":"locality"
},
  "geometry": {"coordinates":[25.90273,55.92836],"type":"Point"}
}