{
  "type": "Feature",
  "properties": {
    "gn:admin1_code":"0.0",
    "gn:asciiname":"Pakauskiai",
    "gn:country_code":"LT",
    "gn:dem":186,
    "gn:feature_class":"P",
    "gn:feature_code":"PPL",
    "gn:name":"Pakauskiai",
    "gn:population":0,
    "gn:timezone":"Europe/Vilnius",
    "iso:country":"LT",
    "name:lit_x_preferred":[
        "Pakauskiai"
    ],
    "name:und_x_variant":[
        "Pokal\u2019nishki",
        "Pakulni\u0161k\u0117s"
    ],
    "wof:name":"Pakauskiai",
    "wof:placetype":"locality"
},
  "geometry": {"coordinates":[22.36806,55.87969],"type":"Point"}
}