{
  "type": "Feature",
  "properties": {
    "gn:admin1_code":"65.0",
    "gn:admin2_code":"89.0",
    "gn:asciiname":"Gelvonai",
    "gn:country_code":"LT",
    "gn:dem":119,
    "gn:feature_class":"P",
    "gn:feature_code":"PPL",
    "gn:name":"Gelvonai",
    "gn:population":0,
    "gn:timezone":"Europe/Vilnius",
    "iso:country":"LT",
    "name:ceb_x_preferred":[
        "Gelvonai"
    ],
    "name:eng_x_preferred":[
        "Gelvonai"
    ],
    "name:est_x_preferred":[
        "Gelvonai"
    ],
    "name:lit_x_preferred":[
        "Gelvonai"
    ],
    "name:nld_x_preferred":[
        "Gelvonai"
    ],
    "name:pol_x_preferred":[
        "Gie\u0142wany"
    ],
    "name:rus_x_preferred":[
        "\u0413\u0435\u043b\u0432\u043e\u043d\u0430\u0439"
    ],
    "name:swe_x_preferred":[
        "Gelvonai"
    ],
    "name:und_x_variant":[
        "Gelvonys",
        "Gelvony",
        "Gelvoni\u0173",
        "Gelvonis",
        "Gelvonay"
    ],
    "wof:name":"Gelvonai",
    "wof:placetype":"locality"
},
  "geometry": {"coordinates":[24.69337,55.06495],"type":"Point"}
}