{
  "type": "Feature",
  "properties": {
    "gn:admin1_code":"64",
    "gn:admin2_code":"62.0",
    "gn:asciiname":"Giraite I",
    "gn:country_code":"LT",
    "gn:dem":161,
    "gn:feature_class":"P",
    "gn:feature_code":"PPL",
    "gn:name":"Girait\u0117 I",
    "gn:population":0,
    "gn:timezone":"Europe/Vilnius",
    "iso:country":"LT",
    "name:lit_x_preferred":[
        "Girait\u0117 I"
    ],
    "wof:name":"Giraite I",
    "wof:placetype":"locality"
},
  "geometry": {"coordinates":[25.68839,55.12491],"type":"Point"}
}