{
  "type": "Feature",
  "properties": {
    "gn:admin1_code":"65",
    "gn:admin2_code":"89.0",
    "gn:asciiname":"Kantrimiskis",
    "gn:country_code":"LT",
    "gn:dem":119,
    "gn:feature_class":"P",
    "gn:feature_code":"PPL",
    "gn:name":"Kantrimi\u0161kis",
    "gn:population":0,
    "gn:timezone":"Europe/Vilnius",
    "iso:country":"LT",
    "name:lit_x_preferred":[
        "Kantrimi\u0161kis"
    ],
    "wof:name":"Kantrimiskis",
    "wof:placetype":"locality"
},
  "geometry": {"coordinates":[24.98168,54.99227],"type":"Point"}
}