{
  "type": "Feature",
  "properties": {
    "gn:admin1_code":"65",
    "gn:admin2_code":"13.0",
    "gn:asciiname":"Pranciskonys",
    "gn:country_code":"LT",
    "gn:dem":153,
    "gn:feature_class":"P",
    "gn:feature_code":"PPL",
    "gn:name":"Pranci\u0161konys",
    "gn:population":0,
    "gn:timezone":"Europe/Vilnius",
    "iso:country":"LT",
    "name:lit_x_preferred":[
        "Pranci\u0161konys"
    ],
    "wof:name":"Pranciskonys",
    "wof:placetype":"locality"
},
  "geometry": {"coordinates":[25.30334,54.87758],"type":"Point"}
}