{
  "type": "Feature",
  "properties": {
    "gn:admin1_code":"56.0",
    "gn:admin2_code":"11.0",
    "gn:asciiname":"Cibiliekai",
    "gn:country_code":"LT",
    "gn:dem":74,
    "gn:feature_class":"P",
    "gn:feature_code":"PPL",
    "gn:name":"Cibiliekai",
    "gn:population":0,
    "gn:timezone":"Europe/Vilnius",
    "iso:country":"LT",
    "name:lit_x_preferred":[
        "Cibiliekai"
    ],
    "wof:name":"Cibiliekai",
    "wof:placetype":"locality"
},
  "geometry": {"coordinates":[23.81474,54.44568],"type":"Point"}
}