{
  "type": "Feature",
  "properties": {
    "gn:admin1_code":"60.0",
    "gn:admin2_code":"73.0",
    "gn:asciiname":"Cedasai",
    "gn:country_code":"LT",
    "gn:dem":88,
    "gn:feature_class":"P",
    "gn:feature_code":"PPL",
    "gn:name":"\u010cedasai",
    "gn:population":0,
    "gn:timezone":"Europe/Vilnius",
    "iso:country":"LT",
    "name:ceb_x_preferred":[
        "\u010cedasai"
    ],
    "name:eng_x_preferred":[
        "\u010cedasai"
    ],
    "name:est_x_preferred":[
        "\u010cedasai"
    ],
    "name:ita_x_preferred":[
        "\u010cedasai"
    ],
    "name:lit_x_preferred":[
        "\u010cedasai"
    ],
    "name:nld_x_preferred":[
        "\u010cedasai"
    ],
    "name:pol_x_preferred":[
        "Czadosy"
    ],
    "name:rus_x_preferred":[
        "\u0427\u044f\u0434\u0430\u0441\u0430\u0439"
    ],
    "name:swe_x_preferred":[
        "\u010cedasai"
    ],
    "name:und_x_variant":[
        "Czadosy",
        "\u010cedas\u0173",
        "Chedasay",
        "\u010cedasai"
    ],
    "wof:name":"Cedasai",
    "wof:placetype":"locality"
},
  "geometry": {"coordinates":[25.41574,56.10202],"type":"Point"}
}