{
  "type": "Feature",
  "properties": {
    "gn:admin1_code":"61",
    "gn:admin2_code":"65.0",
    "gn:asciiname":"Vainaroniai",
    "gn:country_code":"LT",
    "gn:dem":46,
    "gn:feature_class":"P",
    "gn:feature_code":"PPL",
    "gn:name":"Vainaroniai",
    "gn:population":0,
    "gn:timezone":"Europe/Vilnius",
    "iso:country":"LT",
    "name:lit_x_preferred":[
        "Vainaroniai"
    ],
    "wof:name":"Vainaroniai",
    "wof:placetype":"locality"
},
  "geometry": {"coordinates":[24.16473,56.16289],"type":"Point"}
}