{
  "type": "Feature",
  "properties": {
    "gn:admin1_code":"60",
    "gn:admin2_code":"73.0",
    "gn:asciiname":"Ramonaiciai",
    "gn:country_code":"LT",
    "gn:dem":149,
    "gn:feature_class":"P",
    "gn:feature_code":"PPL",
    "gn:name":"Ramonai\u010diai",
    "gn:population":0,
    "gn:timezone":"Europe/Vilnius",
    "iso:country":"LT",
    "name:lit_x_preferred":[
        "Ramonai\u010diai"
    ],
    "wof:name":"Ramonaiciai",
    "wof:placetype":"locality"
},
  "geometry": {"coordinates":[25.567,55.82955],"type":"Point"}
}