{
  "type": "Feature",
  "properties": {
    "gn:admin1_code":"60",
    "gn:admin2_code":"27.0",
    "gn:asciiname":"Kaukiskiai",
    "gn:country_code":"LT",
    "gn:dem":48,
    "gn:feature_class":"P",
    "gn:feature_code":"PPL",
    "gn:name":"Kauki\u0161kiai",
    "gn:population":0,
    "gn:timezone":"Europe/Vilnius",
    "iso:country":"LT",
    "name:lit_x_preferred":[
        "Kauki\u0161kiai"
    ],
    "wof:name":"Kaukiskiai",
    "wof:placetype":"locality"
},
  "geometry": {"coordinates":[24.38098,55.86099],"type":"Point"}
}