{
  "type": "Feature",
  "properties": {
    "gn:admin1_code":"60",
    "gn:admin2_code":"27.0",
    "gn:asciiname":"Kleveckine",
    "gn:country_code":"LT",
    "gn:dem":44,
    "gn:feature_class":"P",
    "gn:feature_code":"PPL",
    "gn:name":"Kleve\u010dkin\u0117",
    "gn:population":0,
    "gn:timezone":"Europe/Vilnius",
    "iso:country":"LT",
    "name:lit_x_preferred":[
        "Kleve\u010dkin\u0117"
    ],
    "wof:name":"Kleveckine",
    "wof:placetype":"locality"
},
  "geometry": {"coordinates":[24.27774,55.76991],"type":"Point"}
}