{
  "type": "Feature",
  "properties": {
    "gn:admin1_code":"64",
    "gn:admin2_code":"45.0",
    "gn:asciiname":"Azuolyne",
    "gn:country_code":"LT",
    "gn:dem":167,
    "gn:feature_class":"P",
    "gn:feature_code":"PPL",
    "gn:name":"\u0104\u017euolyn\u0117",
    "gn:population":0,
    "gn:timezone":"Europe/Vilnius",
    "iso:country":"LT",
    "name:lit_x_preferred":[
        "\u0104\u017euolyn\u0117"
    ],
    "wof:name":"Azuolyne",
    "wof:placetype":"locality"
},
  "geometry": {"coordinates":[26.35737,55.56285],"type":"Point"}
}