{
  "type": "Feature",
  "properties": {
    "gn:admin1_code":"65.0",
    "gn:admin2_code":"89.0",
    "gn:asciiname":"Musninkai",
    "gn:country_code":"LT",
    "gn:dem":109,
    "gn:feature_class":"P",
    "gn:feature_code":"PPL",
    "gn:name":"Musninkai",
    "gn:population":0,
    "gn:timezone":"Europe/Vilnius",
    "iso:country":"LT",
    "name:eng_x_preferred":[
        "Musninkai"
    ],
    "name:rus_x_preferred":[
        "\u041c\u0443\u0441\u043d\u0438\u043d\u043a\u0430\u0439"
    ],
    "name:und_x_variant":[
        "Mu\u015bniki",
        "Musnink\u0173",
        "Musnik\u0173",
        "Musninkay",
        "Musninkai"
    ],
    "wof:name":"Musninkai",
    "wof:placetype":"locality"
},
  "geometry": {"coordinates":[24.83943,54.94758],"type":"Point"}
}