{
  "type": "Feature",
  "properties": {
    "gn:admin1_code":"65",
    "gn:admin2_code":"79.0",
    "gn:asciiname":"Darbutiskes",
    "gn:country_code":"LT",
    "gn:dem":132,
    "gn:feature_class":"P",
    "gn:feature_code":"PPL",
    "gn:name":"Darbuti\u0161k\u0117s",
    "gn:population":0,
    "gn:timezone":"Europe/Vilnius",
    "iso:country":"LT",
    "name:lit_x_preferred":[
        "Darbuti\u0161k\u0117s"
    ],
    "wof:name":"Darbutiskes",
    "wof:placetype":"locality"
},
  "geometry": {"coordinates":[24.44734,54.55966],"type":"Point"}
}