{
  "type": "Feature",
  "properties": {
    "gn:admin1_code":"59",
    "gn:admin2_code":"39.0",
    "gn:asciiname":"Medininkai",
    "gn:country_code":"LT",
    "gn:dem":51,
    "gn:feature_class":"P",
    "gn:feature_code":"PPL",
    "gn:name":"Medininkai",
    "gn:population":0,
    "gn:timezone":"Europe/Vilnius",
    "iso:country":"LT",
    "name:afr_x_preferred":[
        "Medininkai"
    ],
    "name:bel_x_preferred":[
        "\u041c\u044f\u0434\u0437\u0456\u043d\u0456\u043d\u043a\u0430\u0439"
    ],
    "name:cat_x_preferred":[
        "Medininkai"
    ],
    "name:ceb_x_preferred":[
        "Medininkai"
    ],
    "name:deu_x_preferred":[
        "Medininkai"
    ],
    "name:fra_x_preferred":[
        "Medininkai"
    ],
    "name:lit_x_preferred":[
        "Medininkai"
    ],
    "name:nld_x_preferred":[
        "Medininkai"
    ],
    "name:pol_x_preferred":[
        "Miedniki Kr\u00f3lewskie"
    ],
    "name:ron_x_preferred":[
        "Medininkai"
    ],
    "name:rus_x_preferred":[
        "\u041c\u044f\u0434\u0438\u043d\u0438\u043d\u043a\u0430\u0439"
    ],
    "name:ukr_x_preferred":[
        "\u041c\u044f\u0434\u0456\u043d\u0456\u043d\u043a\u0430\u0439"
    ],
    "wof:name":"Medininkai",
    "wof:placetype":"locality"
},
  "geometry": {"coordinates":[22.83241,54.66316],"type":"Point"}
}