{
  "type": "Feature",
  "properties": {
    "gn:admin1_code":"0.0",
    "gn:asciiname":"Jungiris",
    "gn:cc2":"LT",
    "gn:country_code":"LT",
    "gn:dem":166,
    "gn:feature_class":"P",
    "gn:feature_code":"PPL",
    "gn:name":"Jungiris",
    "gn:population":0,
    "gn:timezone":"Europe/Vilnius",
    "iso:country":"LT",
    "name:und_x_variant":[
        "Yungiri",
        "Jungiris"
    ],
    "wof:name":"Jungiris",
    "wof:placetype":"locality"
},
  "geometry": {"coordinates":[22.61667000000001,55.73333],"type":"Point"}
}