{
  "type": "Feature",
  "properties": {
    "gn:admin1_code":"61.0",
    "gn:admin2_code":"65.0",
    "gn:asciiname":"Poskieciai",
    "gn:country_code":"LT",
    "gn:dem":71,
    "gn:feature_class":"P",
    "gn:feature_code":"PPL",
    "gn:name":"Po\u0161kie\u010diai",
    "gn:population":0,
    "gn:timezone":"Europe/Vilnius",
    "iso:country":"LT",
    "name:und_x_variant":[
        "Pashkanchyay",
        "Po\u0161kie\u010diai"
    ],
    "wof:name":"Poskieciai",
    "wof:placetype":"locality"
},
  "geometry": {"coordinates":[23.76543,55.96385],"type":"Point"}
}