{
  "type": "Feature",
  "properties": {
    "gn:admin1_code":"57",
    "gn:admin2_code":"49.0",
    "gn:asciiname":"Bagdoniskes",
    "gn:country_code":"LT",
    "gn:dem":86,
    "gn:feature_class":"P",
    "gn:feature_code":"PPL",
    "gn:name":"Bagdoni\u0161k\u0117s",
    "gn:population":0,
    "gn:timezone":"Europe/Vilnius",
    "iso:country":"LT",
    "name:lit_x_preferred":[
        "Bagdoni\u0161k\u0117s"
    ],
    "wof:name":"Bagdoniskes",
    "wof:placetype":"locality"
},
  "geometry": {"coordinates":[24.45047000000001,54.95009],"type":"Point"}
}