{
  "type": "Feature",
  "properties": {
    "gn:admin1_code":"0.0",
    "gn:asciiname":"Gesviai",
    "gn:cc2":"LT",
    "gn:country_code":"LT",
    "gn:dem":56,
    "gn:feature_class":"P",
    "gn:feature_code":"PPL",
    "gn:name":"Gesviai",
    "gn:population":0,
    "gn:timezone":"Europe/Vilnius",
    "iso:country":"LT",
    "name:und_x_variant":[
        "Ges\u2019vi",
        "Gesviai"
    ],
    "wof:name":"Gesviai",
    "wof:placetype":"locality"
},
  "geometry": {"coordinates":[24.05,55.88333000000001],"type":"Point"}
}