{
  "type": "Feature",
  "properties": {
    "gn:admin1_code":"64",
    "gn:admin2_code":"43.0",
    "gn:asciiname":"Kloviskiai",
    "gn:country_code":"LT",
    "gn:dem":163,
    "gn:feature_class":"P",
    "gn:feature_code":"PPL",
    "gn:name":"Klovi\u0161kiai",
    "gn:population":0,
    "gn:timezone":"Europe/Vilnius",
    "iso:country":"LT",
    "name:lit_x_preferred":[
        "Klovi\u0161kiai"
    ],
    "wof:name":"Kloviskiai",
    "wof:placetype":"locality"
},
  "geometry": {"coordinates":[25.95032,55.60083],"type":"Point"}
}