{
  "type": "Feature",
  "properties": {
    "gn:admin1_code":"57",
    "gn:admin2_code":"12.0",
    "gn:asciiname":"Sutupis",
    "gn:country_code":"LT",
    "gn:dem":94,
    "gn:feature_class":"P",
    "gn:feature_code":"PPL",
    "gn:name":"S\u016btupis",
    "gn:population":0,
    "gn:timezone":"Europe/Vilnius",
    "iso:country":"LT",
    "name:lit_x_preferred":[
        "S\u016btupis"
    ],
    "wof:name":"Sutupis",
    "wof:placetype":"locality"
},
  "geometry": {"coordinates":[23.91997000000001,54.53525],"type":"Point"}
}