{
  "type": "Feature",
  "properties": {
    "gn:admin1_code":"0.0",
    "gn:asciiname":"Gintautai",
    "gn:cc2":"LT",
    "gn:country_code":"LT",
    "gn:dem":103,
    "gn:feature_class":"P",
    "gn:feature_code":"PPL",
    "gn:name":"Gintautai",
    "gn:population":0,
    "gn:timezone":"Europe/Vilnius",
    "iso:country":"LT",
    "name:und_x_variant":[
        "Gintauty",
        "Gintautai"
    ],
    "wof:name":"Gintautai",
    "wof:placetype":"locality"
},
  "geometry": {"coordinates":[23.21667,54.46666999999999],"type":"Point"}
}