{
  "type": "Feature",
  "properties": {
    "gn:admin1_code":"57.0",
    "gn:admin2_code":"72.0",
    "gn:asciiname":"Paliepiai",
    "gn:country_code":"LT",
    "gn:dem":111,
    "gn:feature_class":"P",
    "gn:feature_code":"PPL",
    "gn:name":"Paliepiai",
    "gn:population":0,
    "gn:timezone":"Europe/Vilnius",
    "iso:country":"LT",
    "name:ceb_x_preferred":[
        "Paliepiai"
    ],
    "name:eng_x_preferred":[
        "Paliepiai"
    ],
    "name:fin_x_preferred":[
        "Paliepiai"
    ],
    "name:lit_x_preferred":[
        "Paliepiai"
    ],
    "name:rus_x_preferred":[
        "\u041f\u0430\u043b\u0435\u043f\u044f\u0439"
    ],
    "name:swe_x_preferred":[
        "Paliepiai"
    ],
    "name:und_x_variant":[
        "Polepi",
        "Paliepi\u0173",
        "Palipi\u0173",
        "Paliepiai"
    ],
    "wof:name":"Paliepiai",
    "wof:placetype":"locality"
},
  "geometry": {"coordinates":[23.54422000000001,55.34949],"type":"Point"}
}