{
  "type": "Feature",
  "properties": {
    "gn:admin1_code":"65",
    "gn:admin2_code":"85.0",
    "gn:asciiname":"Narkuskes",
    "gn:country_code":"LT",
    "gn:dem":163,
    "gn:feature_class":"P",
    "gn:feature_code":"PPL",
    "gn:name":"Narku\u0161k\u0117s",
    "gn:population":0,
    "gn:timezone":"Europe/Vilnius",
    "iso:country":"LT",
    "name:lit_x_preferred":[
        "Narku\u0161k\u0117s"
    ],
    "wof:name":"Narkuskes",
    "wof:placetype":"locality"
},
  "geometry": {"coordinates":[25.18086,54.22042],"type":"Point"}
}