{
  "type": "Feature",
  "properties": {
    "gn:admin1_code":"63",
    "gn:admin2_code":"78.0",
    "gn:asciiname":"Siliskes",
    "gn:country_code":"LT",
    "gn:dem":122,
    "gn:feature_class":"P",
    "gn:feature_code":"PPL",
    "gn:name":"\u0160ili\u0161k\u0117s",
    "gn:population":0,
    "gn:timezone":"Europe/Vilnius",
    "iso:country":"LT",
    "name:lit_x_preferred":[
        "\u0160ili\u0161k\u0117s"
    ],
    "wof:name":"Siliskes",
    "wof:placetype":"locality"
},
  "geometry": {"coordinates":[22.24863,56.08557],"type":"Point"}
}