{
  "type": "Feature",
  "properties": {
    "gn:admin1_code":"62",
    "gn:admin2_code":"87.0",
    "gn:asciiname":"Pepliske",
    "gn:country_code":"LT",
    "gn:dem":125,
    "gn:feature_class":"P",
    "gn:feature_code":"PPL",
    "gn:name":"P\u0117plisk\u0117",
    "gn:population":0,
    "gn:timezone":"Europe/Vilnius",
    "iso:country":"LT",
    "name:lit_x_preferred":[
        "P\u0117plisk\u0117"
    ],
    "wof:name":"Pepliske",
    "wof:placetype":"locality"
},
  "geometry": {"coordinates":[22.07635,55.51927],"type":"Point"}
}