{
  "type": "Feature",
  "properties": {
    "gn:admin1_code":"57.0",
    "gn:admin2_code":"53.0",
    "gn:asciiname":"Serbinai",
    "gn:country_code":"LT",
    "gn:dem":45,
    "gn:feature_class":"P",
    "gn:feature_code":"PPL",
    "gn:name":"Serbinai",
    "gn:population":0,
    "gn:timezone":"Europe/Vilnius",
    "iso:country":"LT",
    "name:und_x_variant":[
        "Serbiny",
        "Serb\u0117ntai",
        "Syarbinay",
        "Serbinay",
        "Serbinai"
    ],
    "wof:name":"Serbinai",
    "wof:placetype":"locality"
},
  "geometry": {"coordinates":[23.94338,55.20106],"type":"Point"}
}