{
  "type": "Feature",
  "properties": {
    "gn:admin1_code":"57",
    "gn:admin2_code":"49.0",
    "gn:asciiname":"Jursiskes",
    "gn:country_code":"LT",
    "gn:dem":97,
    "gn:feature_class":"P",
    "gn:feature_code":"PPL",
    "gn:name":"Jur\u0161i\u0161k\u0117s",
    "gn:population":0,
    "gn:timezone":"Europe/Vilnius",
    "iso:country":"LT",
    "name:lit_x_preferred":[
        "Jur\u0161i\u0161k\u0117s"
    ],
    "wof:name":"Jursiskes",
    "wof:placetype":"locality"
},
  "geometry": {"coordinates":[24.60213,54.88374],"type":"Point"}
}