{
  "type": "Feature",
  "properties": {
    "gn:admin1_code":"60.0",
    "gn:admin2_code":"73.0",
    "gn:asciiname":"Nevieriai",
    "gn:country_code":"LT",
    "gn:dem":105,
    "gn:feature_class":"P",
    "gn:feature_code":"PPL",
    "gn:name":"Nevieriai",
    "gn:population":0,
    "gn:timezone":"Europe/Vilnius",
    "iso:country":"LT",
    "name:und_x_variant":[
        "Neviyeni",
        "Neveriai",
        "Nevieriai"
    ],
    "wof:name":"Nevieriai",
    "wof:placetype":"locality"
},
  "geometry": {"coordinates":[25.41313,55.85032],"type":"Point"}
}