{
  "type": "Feature",
  "properties": {
    "gn:admin1_code":"0.0",
    "gn:asciiname":"Svendrai",
    "gn:cc2":"LT",
    "gn:country_code":"LT",
    "gn:dem":71,
    "gn:feature_class":"P",
    "gn:feature_code":"PPL",
    "gn:name":"\u0160vendrai",
    "gn:population":0,
    "gn:timezone":"Europe/Vilnius",
    "iso:country":"LT",
    "name:und_x_variant":[
        "Shavendra",
        "\u0160vendrai"
    ],
    "wof:name":"Svendrai",
    "wof:placetype":"locality"
},
  "geometry": {"coordinates":[22.91667,55.35],"type":"Point"}
}