{
  "type": "Feature",
  "properties": {
    "gn:admin1_code":"65",
    "gn:admin2_code":"79.0",
    "gn:asciiname":"Obeliai",
    "gn:country_code":"LT",
    "gn:dem":168,
    "gn:feature_class":"P",
    "gn:feature_code":"PPL",
    "gn:name":"Obeliai",
    "gn:population":0,
    "gn:timezone":"Europe/Vilnius",
    "iso:country":"LT",
    "name:lit_x_preferred":[
        "Obeliai"
    ],
    "wof:name":"Obeliai",
    "wof:placetype":"locality"
},
  "geometry": {"coordinates":[24.77222,54.55938],"type":"Point"}
}