{
  "type": "Feature",
  "properties": {
    "gn:admin1_code":"65",
    "gn:admin2_code":"79.0",
    "gn:asciiname":"Obeliai",
    "gn:country_code":"LT",
    "gn:dem":168,
    "gn:feature_class":"P",
    "gn:feature_code":"PPL",
    "gn:name":"Obeliai",
    "gn:population":0,
    "gn:timezone":"Europe/Vilnius",
    "iso:country":"LT",
    "name:afr_x_preferred":[
        "Obeliai"
    ],
    "name:ara_x_preferred":[
        "\u0623\u0648\u0628\u064a\u0644\u064a\u0627\u064a"
    ],
    "name:bel_x_preferred":[
        "\u0410\u0431\u044f\u043b\u0435\u0439"
    ],
    "name:cat_x_preferred":[
        "Obeliai"
    ],
    "name:ceb_x_preferred":[
        "Obeliai"
    ],
    "name:deu_x_preferred":[
        "Obeliai"
    ],
    "name:ell_x_preferred":[
        "\u039f\u03bc\u03c0\u03ad\u03bb\u03b9\u03b1\u03ca"
    ],
    "name:est_x_preferred":[
        "Obeliai"
    ],
    "name:fas_x_preferred":[
        "\u0627\u0648\u0628\u0644\u06cc\u0627\u06cc"
    ],
    "name:fin_x_preferred":[
        "Obeliai"
    ],
    "name:fra_x_preferred":[
        "Obeliai"
    ],
    "name:heb_x_preferred":[
        "\u05d0\u05d5\u05d1\u05dc\u05d0\u05d9"
    ],
    "name:hsb_x_preferred":[
        "Obeliai"
    ],
    "name:ind_x_preferred":[
        "Obeliai"
    ],
    "name:ita_x_preferred":[
        "Obeliai"
    ],
    "name:lav_x_preferred":[
        "Obe\u013ci"
    ],
    "name:lit_x_preferred":[
        "Obeliai"
    ],
    "name:pms_x_preferred":[
        "Obeliai"
    ],
    "name:pol_x_preferred":[
        "Abele"
    ],
    "name:rus_x_preferred":[
        "\u041e\u0431\u044f\u043b\u044f\u0439"
    ],
    "name:swe_x_preferred":[
        "Obeliai"
    ],
    "name:ukr_x_preferred":[
        "\u041e\u0431\u0435\u043b\u044f\u0439"
    ],
    "name:vol_x_preferred":[
        "Obeliai"
    ],
    "name:yid_x_preferred":[
        "\u05d0\u05d1\u05e2\u05dc"
    ],
    "name:zho_x_preferred":[
        "\u5967\u8c9d\u5229\u827e"
    ],
    "wof:name":"Obeliai",
    "wof:placetype":"locality"
},
  "geometry": {"coordinates":[24.77222,54.55938],"type":"Point"}
}