{
  "type": "Feature",
  "properties": {
    "gn:admin1_code":"0.0",
    "gn:asciiname":"Geruciai",
    "gn:cc2":"LT",
    "gn:country_code":"LT",
    "gn:dem":36,
    "gn:feature_class":"P",
    "gn:feature_code":"PPL",
    "gn:name":"Geru\u010diai",
    "gn:population":0,
    "gn:timezone":"Europe/Vilnius",
    "iso:country":"LT",
    "name:und_x_variant":[
        "Gyaruchyay",
        "Geru\u010diai"
    ],
    "wof:name":"Geruciai",
    "wof:placetype":"locality"
},
  "geometry": {"coordinates":[23.98839,56.32389000000001],"type":"Point"}
}