{
  "type": "Feature",
  "properties": {
    "gn:admin1_code":"57.0",
    "gn:admin2_code":"49.0",
    "gn:asciiname":"Zydeikiskes",
    "gn:country_code":"LT",
    "gn:dem":102,
    "gn:feature_class":"P",
    "gn:feature_code":"PPL",
    "gn:name":"\u017dydeiki\u0161k\u0117s",
    "gn:population":0,
    "gn:timezone":"Europe/Vilnius",
    "iso:country":"LT",
    "name:und_x_variant":[
        "Zhidaykishki",
        "\u017dydeiki\u0161kiai",
        "\u017dydeiki\u0161ki\u0173",
        "\u017dydeiki\u0161k\u0117s"
    ],
    "wof:name":"Zydeikiskes",
    "wof:placetype":"locality"
},
  "geometry": {"coordinates":[24.33756,54.79521999999999],"type":"Point"}
}