{
  "type": "Feature",
  "properties": {
    "gn:admin1_code":"60.0",
    "gn:admin2_code":"36.0",
    "gn:asciiname":"Uzusiliai",
    "gn:country_code":"LT",
    "gn:dem":55,
    "gn:feature_class":"P",
    "gn:feature_code":"PPL",
    "gn:name":"U\u017eu\u0161iliai",
    "gn:population":0,
    "gn:timezone":"Europe/Vilnius",
    "iso:country":"LT",
    "name:und_x_variant":[
        "Uzhushilyay",
        "U\u017eu\u0161ili\u0173",
        "U\u017eu\u0161iliai"
    ],
    "wof:name":"Uzusiliai",
    "wof:placetype":"locality"
},
  "geometry": {"coordinates":[24.74685,56.29439],"type":"Point"}
}