{
  "type": "Feature",
  "properties": {
    "gn:admin1_code":"62",
    "gn:admin2_code":"77.0",
    "gn:asciiname":"Uzpelkiai",
    "gn:country_code":"LT",
    "gn:dem":36,
    "gn:feature_class":"P",
    "gn:feature_code":"PPL",
    "gn:name":"U\u017epelkiai",
    "gn:population":0,
    "gn:timezone":"Europe/Vilnius",
    "iso:country":"LT",
    "name:lit_x_preferred":[
        "U\u017epelkiai"
    ],
    "wof:name":"Uzpelkiai",
    "wof:placetype":"locality"
},
  "geometry": {"coordinates":[21.97157,55.25979],"type":"Point"}
}