{
  "type": "Feature",
  "properties": {
    "gn:admin1_code":"57.0",
    "gn:admin2_code":"72.0",
    "gn:asciiname":"Baltkarciai",
    "gn:country_code":"LT",
    "gn:dem":101,
    "gn:feature_class":"P",
    "gn:feature_code":"PPL",
    "gn:name":"Baltkar\u010diai",
    "gn:population":0,
    "gn:timezone":"Europe/Vilnius",
    "iso:country":"LT",
    "name:lit_x_preferred":[
        "Baltkar\u010diai"
    ],
    "wof:name":"Baltkarciai",
    "wof:placetype":"locality"
},
  "geometry": {"coordinates":[23.11671,55.51995],"type":"Point"}
}