{
  "type": "Feature",
  "properties": {
    "gn:admin1_code":"58.0",
    "gn:admin2_code":"23.0",
    "gn:asciiname":"Skruzdyne",
    "gn:country_code":"LT",
    "gn:dem":5,
    "gn:feature_class":"P",
    "gn:feature_code":"PPL",
    "gn:name":"Skruzdyn\u0117",
    "gn:population":0,
    "gn:timezone":"Europe/Vilnius",
    "iso:country":"LT",
    "name:lit_x_preferred":[
        "Skruzdyn\u0117"
    ],
    "name:und_x_variant":[
        "Neringa",
        "Skruzdinas",
        "Skruzdynas"
    ],
    "wof:name":"Skruzdyne",
    "wof:placetype":"locality"
},
  "geometry": {"coordinates":[21.01227,55.31278],"type":"Point"}
}