{
  "type": "Feature",
  "properties": {
    "gn:admin1_code":"62.0",
    "gn:admin2_code":"87.0",
    "gn:asciiname":"Uzjuris",
    "gn:country_code":"LT",
    "gn:dem":69,
    "gn:feature_class":"P",
    "gn:feature_code":"PPL",
    "gn:name":"U\u017ej\u016bris",
    "gn:population":0,
    "gn:timezone":"Europe/Vilnius",
    "iso:country":"LT",
    "name:eng_x_preferred":[
        "U\u017ej\u016bris"
    ],
    "name:rus_x_preferred":[
        "\u041f\u0430\u044e\u0440\u0438\u0441"
    ],
    "name:und_x_variant":[
        "Zayury"
    ],
    "wof:name":"Uzjuris",
    "wof:placetype":"locality"
},
  "geometry": {"coordinates":[22.02201,55.44245],"type":"Point"}
}