{
  "type": "Feature",
  "properties": {
    "gn:admin1_code":"64",
    "gn:admin2_code":"34.0",
    "gn:asciiname":"Jasonys II",
    "gn:country_code":"LT",
    "gn:dem":96,
    "gn:feature_class":"P",
    "gn:feature_code":"PPL",
    "gn:name":"Jasonys II",
    "gn:population":0,
    "gn:timezone":"Europe/Vilnius",
    "iso:country":"LT",
    "name:lit_x_preferred":[
        "Jasonys II"
    ],
    "wof:name":"Jasonys II",
    "wof:placetype":"locality"
},
  "geometry": {"coordinates":[24.88872000000001,55.44199],"type":"Point"}
}