{
  "type": "Feature",
  "properties": {
    "gn:admin1_code":"60.0",
    "gn:admin2_code":"27.0",
    "gn:asciiname":"Smilgiai",
    "gn:country_code":"LT",
    "gn:dem":66,
    "gn:feature_class":"P",
    "gn:feature_code":"PPL",
    "gn:name":"Smilgiai",
    "gn:population":0,
    "gn:timezone":"Europe/Vilnius",
    "iso:country":"LT",
    "name:ceb_x_preferred":[
        "Smilgiai"
    ],
    "name:deu_x_preferred":[
        "Smilgiai"
    ],
    "name:eng_x_preferred":[
        "Smilgiai"
    ],
    "name:est_x_preferred":[
        "Smilgiai"
    ],
    "name:lit_x_preferred":[
        "Smilgiai"
    ],
    "name:nld_x_preferred":[
        "Smilgiai"
    ],
    "name:pol_x_preferred":[
        "Smilgie"
    ],
    "name:rus_x_preferred":[
        "\u0421\u043c\u0438\u043b\u044c\u0433\u044f\u0439"
    ],
    "name:swe_x_preferred":[
        "Smilgiai"
    ],
    "name:und_x_variant":[
        "Smilgyay",
        "Smilgis",
        "Smilgi\u0173"
    ],
    "wof:name":"Smilgiai",
    "wof:placetype":"locality"
},
  "geometry": {"coordinates":[24.01491,55.80374000000001],"type":"Point"}
}