{
  "type": "Feature",
  "properties": {
    "gn:admin1_code":"59",
    "gn:admin2_code":"84.0",
    "gn:asciiname":"Kepstai",
    "gn:country_code":"LT",
    "gn:dem":39,
    "gn:feature_class":"P",
    "gn:feature_code":"PPL",
    "gn:name":"K\u0117p\u0161tai",
    "gn:population":0,
    "gn:timezone":"Europe/Vilnius",
    "iso:country":"LT",
    "name:lit_x_preferred":[
        "K\u0117p\u0161tai"
    ],
    "wof:name":"Kepstai",
    "wof:placetype":"locality"
},
  "geometry": {"coordinates":[22.87505,55.03239],"type":"Point"}
}