{
  "type": "Feature",
  "properties": {
    "gn:admin1_code":"58.0",
    "gn:admin2_code":"56.0",
    "gn:asciiname":"Imbare",
    "gn:country_code":"LT",
    "gn:dem":65,
    "gn:feature_class":"P",
    "gn:feature_code":"PPL",
    "gn:name":"Imbar\u0117",
    "gn:population":0,
    "gn:timezone":"Europe/Vilnius",
    "iso:country":"LT",
    "name:und_x_variant":[
        "Inbory",
        "Imbar\u0117s",
        "Imbar\u0117"
    ],
    "wof:name":"Imbare",
    "wof:placetype":"locality"
},
  "geometry": {"coordinates":[21.58514,56.023],"type":"Point"}
}