{
  "type": "Feature",
  "properties": {
    "gn:admin1_code":"57.0",
    "gn:admin2_code":"12.0",
    "gn:asciiname":"Kampiskiai",
    "gn:country_code":"LT",
    "gn:dem":47,
    "gn:feature_class":"P",
    "gn:feature_code":"PPL",
    "gn:name":"Kampi\u0161kiai",
    "gn:population":0,
    "gn:timezone":"Europe/Vilnius",
    "iso:country":"LT",
    "name:lit_x_preferred":[
        "Kampi\u0161kiai"
    ],
    "wof:name":"Kampiskiai",
    "wof:placetype":"locality"
},
  "geometry": {"coordinates":[24.06047,54.61291],"type":"Point"}
}