{
  "type": "Feature",
  "properties": {
    "gn:admin1_code":"57",
    "gn:admin2_code":"49.0",
    "gn:asciiname":"Sakniai",
    "gn:country_code":"LT",
    "gn:dem":87,
    "gn:feature_class":"P",
    "gn:feature_code":"PPL",
    "gn:name":"\u0160akniai",
    "gn:population":0,
    "gn:timezone":"Europe/Vilnius",
    "iso:country":"LT",
    "name:lit_x_preferred":[
        "\u0160akniai"
    ],
    "wof:name":"Sakniai",
    "wof:placetype":"locality"
},
  "geometry": {"coordinates":[24.47519,54.88544],"type":"Point"}
}