{
  "type": "Feature",
  "properties": {
    "gn:admin1_code":"61",
    "gn:admin2_code":"54.0",
    "gn:asciiname":"Pliuskaiciai",
    "gn:country_code":"LT",
    "gn:dem":150,
    "gn:feature_class":"P",
    "gn:feature_code":"PPL",
    "gn:name":"Pliu\u0161kai\u010diai",
    "gn:population":0,
    "gn:timezone":"Europe/Vilnius",
    "iso:country":"LT",
    "name:lit_x_preferred":[
        "Pliu\u0161kai\u010diai"
    ],
    "wof:name":"Pliuskaiciai",
    "wof:placetype":"locality"
},
  "geometry": {"coordinates":[22.82027,55.64894],"type":"Point"}
}