{
  "type": "Feature",
  "properties": {
    "gn:admin1_code":"57.0",
    "gn:admin2_code":"53.0",
    "gn:asciiname":"Gudziunu Gelezinkelio Stotis",
    "gn:country_code":"LT",
    "gn:dem":90,
    "gn:feature_class":"P",
    "gn:feature_code":"PPL",
    "gn:name":"Gud\u017ei\u016bn\u0173 Gele\u017einkelio Stotis",
    "gn:population":0,
    "gn:timezone":"Europe/Vilnius",
    "iso:country":"LT",
    "name:lit_x_preferred":[
        "Gud\u017ei\u016bn\u0173 Gele\u017einkelio Stotis"
    ],
    "name:lit_x_variant":[
        "Gele\u017einkelio Stotis Gud\u017ei\u016bnai",
        "Gud\u017ei\u016bnai"
    ],
    "name:und_x_variant":[
        "Gudzhunay",
        "Gudzyuny",
        "Mikelmonto Gud\u017ei\u016bn\u0173",
        "Stotis Gud\u017ei\u016bnai"
    ],
    "wof:name":"Gudziunu Gelezinkelio Stotis",
    "wof:placetype":"locality"
},
  "geometry": {"coordinates":[23.79174,55.52539],"type":"Point"}
}