{
  "type": "Feature",
  "properties": {
    "gn:admin1_code":"64",
    "gn:admin2_code":"30.0",
    "gn:asciiname":"Tiltelis",
    "gn:country_code":"LT",
    "gn:dem":169,
    "gn:feature_class":"P",
    "gn:feature_code":"PPL",
    "gn:name":"Tiltelis",
    "gn:population":0,
    "gn:timezone":"Europe/Vilnius",
    "iso:country":"LT",
    "name:lit_x_preferred":[
        "Tiltelis"
    ],
    "wof:name":"Tiltelis",
    "wof:placetype":"locality"
},
  "geometry": {"coordinates":[26.41999,55.56394],"type":"Point"}
}