{
  "type": "Feature",
  "properties": {
    "gn:admin1_code":"65",
    "gn:admin2_code":"81.0",
    "gn:asciiname":"Libisonys",
    "gn:country_code":"LT",
    "gn:dem":81,
    "gn:feature_class":"P",
    "gn:feature_code":"PPL",
    "gn:name":"Libi\u0161onys",
    "gn:population":0,
    "gn:timezone":"Europe/Vilnius",
    "iso:country":"LT",
    "name:lit_x_preferred":[
        "Libi\u0161onys"
    ],
    "wof:name":"Libisonys",
    "wof:placetype":"locality"
},
  "geometry": {"coordinates":[24.61241,55.34922],"type":"Point"}
}