{
  "type": "Feature",
  "properties": {
    "gn:admin1_code":"60.0",
    "gn:admin2_code":"27.0",
    "gn:asciiname":"Joskildai",
    "gn:country_code":"LT",
    "gn:dem":64,
    "gn:feature_class":"P",
    "gn:feature_code":"PPL",
    "gn:name":"Joskildai",
    "gn:population":0,
    "gn:timezone":"Europe/Vilnius",
    "iso:country":"LT",
    "name:und_x_variant":[
        "Yaskildy",
        "Joskildai"
    ],
    "wof:name":"Joskildai",
    "wof:placetype":"locality"
},
  "geometry": {"coordinates":[24.34502,55.59214],"type":"Point"}
}