{
  "type": "Feature",
  "properties": {
    "gn:admin1_code":"57",
    "gn:admin2_code":"69.0",
    "gn:asciiname":"Dankstyte",
    "gn:country_code":"LT",
    "gn:dem":75,
    "gn:feature_class":"P",
    "gn:feature_code":"PPL",
    "gn:name":"Dankstyt\u0117",
    "gn:population":0,
    "gn:timezone":"Europe/Vilnius",
    "iso:country":"LT",
    "name:lit_x_preferred":[
        "Dankstyt\u0117"
    ],
    "wof:name":"Dankstyte",
    "wof:placetype":"locality"
},
  "geometry": {"coordinates":[24.02876,54.77323000000001],"type":"Point"}
}