{
  "type": "Feature",
  "properties": {
    "gn:admin1_code":"56.0",
    "gn:admin2_code":"11.0",
    "gn:asciiname":"Pociuniskes",
    "gn:country_code":"LT",
    "gn:dem":136,
    "gn:feature_class":"P",
    "gn:feature_code":"PPL",
    "gn:name":"Poci\u016bni\u0161k\u0117s",
    "gn:population":0,
    "gn:timezone":"Europe/Vilnius",
    "iso:country":"LT",
    "name:und_x_variant":[
        "Patsunishki",
        "Poci\u016bni\u0161k\u0117s"
    ],
    "wof:name":"Pociuniskes",
    "wof:placetype":"locality"
},
  "geometry": {"coordinates":[24.26951,54.29264000000001],"type":"Point"}
}