{
  "type": "Feature",
  "properties": {
    "gn:admin1_code":"61.0",
    "gn:admin2_code":"71.0",
    "gn:asciiname":"Beinorava",
    "gn:country_code":"LT",
    "gn:dem":68,
    "gn:feature_class":"P",
    "gn:feature_code":"PPL",
    "gn:name":"Beinorava",
    "gn:population":0,
    "gn:timezone":"Europe/Vilnius",
    "iso:country":"LT",
    "name:lit_x_preferred":[
        "Beinorava"
    ],
    "name:und_x_variant":[
        "Beynaravas",
        "Beinorai"
    ],
    "wof:name":"Beinorava",
    "wof:placetype":"locality"
},
  "geometry": {"coordinates":[23.99657,55.73477],"type":"Point"}
}