{
  "type": "Feature",
  "properties": {
    "gn:admin1_code":"64",
    "gn:admin2_code":"82.0",
    "gn:asciiname":"Brinkliskes",
    "gn:country_code":"LT",
    "gn:dem":176,
    "gn:feature_class":"P",
    "gn:feature_code":"PPL",
    "gn:name":"Brinkli\u0161k\u0117s",
    "gn:population":0,
    "gn:timezone":"Europe/Vilnius",
    "iso:country":"LT",
    "name:lit_x_preferred":[
        "Brinkli\u0161k\u0117s"
    ],
    "wof:name":"Brinkliskes",
    "wof:placetype":"locality"
},
  "geometry": {"coordinates":[25.92341,55.5197],"type":"Point"}
}