{
  "type": "Feature",
  "properties": {
    "gn:admin1_code":"56",
    "gn:admin2_code":"11.0",
    "gn:asciiname":"Raizava",
    "gn:country_code":"LT",
    "gn:dem":122,
    "gn:feature_class":"P",
    "gn:feature_code":"PPL",
    "gn:name":"Rai\u017eava",
    "gn:population":0,
    "gn:timezone":"Europe/Vilnius",
    "iso:country":"LT",
    "name:lit_x_preferred":[
        "Rai\u017eava"
    ],
    "wof:name":"Raizava",
    "wof:placetype":"locality"
},
  "geometry": {"coordinates":[24.19743,54.4926],"type":"Point"}
}