{
  "type": "Feature",
  "properties": {
    "gn:admin1_code":"64",
    "gn:admin2_code":"43.0",
    "gn:asciiname":"Avizine",
    "gn:country_code":"LT",
    "gn:dem":181,
    "gn:feature_class":"P",
    "gn:feature_code":"PPL",
    "gn:name":"Avi\u017ein\u0117",
    "gn:population":0,
    "gn:timezone":"Europe/Vilnius",
    "iso:country":"LT",
    "name:lit_x_preferred":[
        "Avi\u017ein\u0117"
    ],
    "wof:name":"Avizine",
    "wof:placetype":"locality"
},
  "geometry": {"coordinates":[26.33741,55.66365],"type":"Point"}
}