{
  "type": "Feature",
  "properties": {
    "gn:admin1_code":"57",
    "gn:admin2_code":"19.0",
    "gn:asciiname":"Roku Misko Kelmynas",
    "gn:country_code":"LT",
    "gn:dem":62,
    "gn:feature_class":"P",
    "gn:feature_code":"PPL",
    "gn:name":"Rok\u0173 Mi\u0161ko Kelmynas",
    "gn:population":0,
    "gn:timezone":"Europe/Vilnius",
    "iso:country":"LT",
    "name:lit_x_preferred":[
        "Rok\u0173 Mi\u0161ko Kelmynas"
    ],
    "wof:name":"Roku Misko Kelmynas",
    "wof:placetype":"locality"
},
  "geometry": {"coordinates":[24.00155,54.83128000000001],"type":"Point"}
}