{
  "type": "Feature",
  "properties": {
    "gn:admin1_code":"57",
    "gn:admin2_code":"69.0",
    "gn:asciiname":"Apusotas",
    "gn:country_code":"LT",
    "gn:dem":96,
    "gn:feature_class":"P",
    "gn:feature_code":"PPL",
    "gn:name":"Apu\u0161otas",
    "gn:population":0,
    "gn:timezone":"Europe/Vilnius",
    "iso:country":"LT",
    "name:lit_x_preferred":[
        "Apu\u0161otas"
    ],
    "wof:name":"Apusotas",
    "wof:placetype":"locality"
},
  "geometry": {"coordinates":[24.14587,54.62668000000001],"type":"Point"}
}