{
  "type": "Feature",
  "properties": {
    "gn:admin1_code":"57",
    "gn:admin2_code":"72.0",
    "gn:asciiname":"Uzsieniai",
    "gn:country_code":"LT",
    "gn:dem":151,
    "gn:feature_class":"P",
    "gn:feature_code":"PPL",
    "gn:name":"U\u017esieniai",
    "gn:population":0,
    "gn:timezone":"Europe/Vilnius",
    "iso:country":"LT",
    "name:lit_x_preferred":[
        "U\u017esieniai"
    ],
    "wof:name":"Uzsieniai",
    "wof:placetype":"locality"
},
  "geometry": {"coordinates":[22.69978,55.48071],"type":"Point"}
}