{
  "type": "Feature",
  "properties": {
    "gn:admin1_code":"57.0",
    "gn:admin2_code":"49.0",
    "gn:asciiname":"Cineikiai",
    "gn:country_code":"LT",
    "gn:dem":117,
    "gn:feature_class":"P",
    "gn:feature_code":"PPL",
    "gn:name":"Cineikiai",
    "gn:population":0,
    "gn:timezone":"Europe/Vilnius",
    "iso:country":"LT",
    "name:und_x_variant":[
        "Sineikiai",
        "Tsineyki",
        "Cineikiai"
    ],
    "wof:name":"Cineikiai",
    "wof:placetype":"locality"
},
  "geometry": {"coordinates":[24.63263,54.85004],"type":"Point"}
}