{
  "type": "Feature",
  "properties": {
    "gn:admin1_code":"61",
    "gn:admin2_code":"47.0",
    "gn:asciiname":"Nartauciai",
    "gn:country_code":"LT",
    "gn:dem":45,
    "gn:feature_class":"P",
    "gn:feature_code":"PPL",
    "gn:name":"Nartau\u010diai",
    "gn:population":0,
    "gn:timezone":"Europe/Vilnius",
    "iso:country":"LT",
    "name:lit_x_preferred":[
        "Nartau\u010diai"
    ],
    "wof:name":"Nartauciai",
    "wof:placetype":"locality"
},
  "geometry": {"coordinates":[23.54633,56.3027],"type":"Point"}
}