{
  "type": "Feature",
  "properties": {
    "gn:admin1_code":"61.0",
    "gn:admin2_code":"65.0",
    "gn:asciiname":"Daugsigaliai",
    "gn:country_code":"LT",
    "gn:dem":61,
    "gn:feature_class":"P",
    "gn:feature_code":"PPL",
    "gn:name":"Daug\u0161igaliai",
    "gn:population":0,
    "gn:timezone":"Europe/Vilnius",
    "iso:country":"LT",
    "name:lit_x_preferred":[
        "Daug\u0161igaliai"
    ],
    "name:und_x_variant":[
        "Daukshigalyay",
        "Daukshigolyay",
        "Dauk\u0161igaliai"
    ],
    "wof:name":"Daugsigaliai",
    "wof:placetype":"locality"
},
  "geometry": {"coordinates":[23.79596,56.02318],"type":"Point"}
}