{
  "type": "Feature",
  "properties": {
    "gn:admin1_code":"58.0",
    "gn:admin2_code":"88.0",
    "gn:asciiname":"Gedikai",
    "gn:country_code":"LT",
    "gn:dem":44,
    "gn:feature_class":"P",
    "gn:feature_code":"PPL",
    "gn:name":"Gedikai",
    "gn:population":0,
    "gn:timezone":"Europe/Vilnius",
    "iso:country":"LT",
    "name:und_x_variant":[
        "Gedyki",
        "Gyadikay",
        "Gedikai"
    ],
    "wof:name":"Gedikai",
    "wof:placetype":"locality"
},
  "geometry": {"coordinates":[21.68778,55.48871],"type":"Point"}
}