{
  "type": "Feature",
  "properties": {
    "gn:admin1_code":"64",
    "gn:admin2_code":"43.0",
    "gn:asciiname":"Paliese",
    "gn:country_code":"LT",
    "gn:dem":160,
    "gn:feature_class":"P",
    "gn:feature_code":"PPL",
    "gn:name":"Palies\u0117",
    "gn:population":0,
    "gn:timezone":"Europe/Vilnius",
    "iso:country":"LT",
    "name:lit_x_preferred":[
        "Palies\u0117"
    ],
    "wof:name":"Paliese",
    "wof:placetype":"locality"
},
  "geometry": {"coordinates":[25.99836,55.81836],"type":"Point"}
}