{
  "type": "Feature",
  "properties": {
    "gn:admin1_code":"63.0",
    "gn:admin2_code":"74.0",
    "gn:asciiname":"Laurynaiciai",
    "gn:country_code":"LT",
    "gn:dem":113,
    "gn:feature_class":"P",
    "gn:feature_code":"PPL",
    "gn:name":"Laurynai\u010diai",
    "gn:population":0,
    "gn:timezone":"Europe/Vilnius",
    "iso:country":"LT",
    "name:und_x_variant":[
        "Laurinaychyay",
        "Laurynai\u010diai"
    ],
    "wof:name":"Laurynaiciai",
    "wof:placetype":"locality"
},
  "geometry": {"coordinates":[22.06349,55.79219000000001],"type":"Point"}
}