{
  "type": "Feature",
  "properties": {
    "gn:admin1_code":"65",
    "gn:admin2_code":"13.0",
    "gn:asciiname":"Kalniskes",
    "gn:country_code":"LT",
    "gn:dem":198,
    "gn:feature_class":"P",
    "gn:feature_code":"PPL",
    "gn:name":"Kalni\u0161k\u0117s",
    "gn:population":0,
    "gn:timezone":"Europe/Vilnius",
    "iso:country":"LT",
    "name:lit_x_preferred":[
        "Kalni\u0161k\u0117s"
    ],
    "wof:name":"Kalniskes",
    "wof:placetype":"locality"
},
  "geometry": {"coordinates":[25.4875,54.6369],"type":"Point"}
}