{
  "type": "Feature",
  "properties": {
    "gn:admin1_code":"61",
    "gn:admin2_code":"47.0",
    "gn:asciiname":"Katiliskes",
    "gn:country_code":"LT",
    "gn:dem":73,
    "gn:feature_class":"P",
    "gn:feature_code":"PPL",
    "gn:name":"Katili\u0161k\u0117s",
    "gn:population":0,
    "gn:timezone":"Europe/Vilnius",
    "iso:country":"LT",
    "name:lit_x_preferred":[
        "Katili\u0161k\u0117s"
    ],
    "wof:name":"Katiliskes",
    "wof:placetype":"locality"
},
  "geometry": {"coordinates":[23.27777,56.33131],"type":"Point"}
}