{
  "type": "Feature",
  "properties": {
    "gn:admin1_code":"65.0",
    "gn:admin2_code":"81.0",
    "gn:asciiname":"Lelikoniai",
    "gn:country_code":"LT",
    "gn:dem":138,
    "gn:feature_class":"P",
    "gn:feature_code":"PPL",
    "gn:name":"Lelikoniai",
    "gn:population":0,
    "gn:timezone":"Europe/Vilnius",
    "iso:country":"LT",
    "name:lit_x_preferred":[
        "Lelikoniai"
    ],
    "name:und_x_variant":[
        "Lelikoni\u0173",
        "Lelekan\u2019tse",
        "Lelikonys"
    ],
    "wof:name":"Lelikoniai",
    "wof:placetype":"locality"
},
  "geometry": {"coordinates":[25.13947000000001,55.15519000000001],"type":"Point"}
}