{
  "type": "Feature",
  "properties": {
    "gn:admin1_code":"65",
    "gn:admin2_code":"85.0",
    "gn:asciiname":"Asciukiskes",
    "gn:country_code":"LT",
    "gn:dem":223,
    "gn:feature_class":"P",
    "gn:feature_code":"PPL",
    "gn:name":"As\u010diuki\u0161k\u0117s",
    "gn:population":0,
    "gn:timezone":"Europe/Vilnius",
    "iso:country":"LT",
    "name:lit_x_preferred":[
        "As\u010diuki\u0161k\u0117s"
    ],
    "wof:name":"Asciukiskes",
    "wof:placetype":"locality"
},
  "geometry": {"coordinates":[25.57532,54.45106],"type":"Point"}
}