{
  "type": "Feature",
  "properties": {
    "gn:admin1_code":"0.0",
    "gn:asciiname":"Tyruliai",
    "gn:country_code":"LT",
    "gn:dem":122,
    "gn:feature_class":"P",
    "gn:feature_code":"PPL",
    "gn:name":"Tyruliai",
    "gn:population":0,
    "gn:timezone":"Europe/Vilnius",
    "iso:country":"LT",
    "name:est_x_preferred":[
        "Tyruliai"
    ],
    "name:fas_x_preferred":[
        "\u062a\u06cc\u0631\u0648\u0644\u06cc\u0627\u06cc"
    ],
    "name:lit_x_preferred":[
        "Tyruliai"
    ],
    "name:pol_x_preferred":[
        "Tyrolki"
    ],
    "name:rus_x_preferred":[
        "\u0422\u0438\u0440\u0443\u043b\u044f\u0439"
    ],
    "name:swe_x_preferred":[
        "Tyruliai"
    ],
    "wof:name":"Tyruliai",
    "wof:placetype":"locality"
},
  "geometry": {"coordinates":[23.35,55.78333000000001],"type":"Point"}
}