{
  "type": "Feature",
  "properties": {
    "gn:admin1_code":"65.0",
    "gn:admin2_code":"81.0",
    "gn:asciiname":"Inkilai",
    "gn:country_code":"LT",
    "gn:dem":131,
    "gn:feature_class":"P",
    "gn:feature_code":"PPL",
    "gn:name":"Inkilai",
    "gn:population":0,
    "gn:timezone":"Europe/Vilnius",
    "iso:country":"LT",
    "name:und_x_variant":[
        "Inkilay",
        "Inkilai"
    ],
    "wof:name":"Inkilai",
    "wof:placetype":"locality"
},
  "geometry": {"coordinates":[24.87358,55.23291999999999],"type":"Point"}
}