{
  "type": "Feature",
  "properties": {
    "gn:admin1_code":"64",
    "gn:admin2_code":"43.0",
    "gn:asciiname":"Pratkunai",
    "gn:country_code":"LT",
    "gn:dem":219,
    "gn:feature_class":"P",
    "gn:feature_code":"PPL",
    "gn:name":"Pratk\u016bnai",
    "gn:population":0,
    "gn:timezone":"Europe/Vilnius",
    "iso:country":"LT",
    "name:lit_x_preferred":[
        "Pratk\u016bnai"
    ],
    "wof:name":"Pratkunai",
    "wof:placetype":"locality"
},
  "geometry": {"coordinates":[26.09125,55.53408],"type":"Point"}
}