{
  "type": "Feature",
  "properties": {
    "gn:admin1_code":"64.0",
    "gn:admin2_code":"45.0",
    "gn:asciiname":"Mazenai",
    "gn:country_code":"LT",
    "gn:dem":161,
    "gn:feature_class":"P",
    "gn:feature_code":"PPL",
    "gn:name":"Ma\u017e\u0117nai",
    "gn:population":0,
    "gn:timezone":"Europe/Vilnius",
    "iso:country":"LT",
    "name:eng_x_preferred":[
        "Ma\u017e\u0117nai"
    ],
    "name:rus_x_preferred":[
        "\u041c\u0430\u0436\u0435\u043d\u0430\u0439"
    ],
    "name:und_x_variant":[
        "Mazhany"
    ],
    "wof:name":"Mazenai",
    "wof:placetype":"locality"
},
  "geometry": {"coordinates":[26.40064000000001,55.44545],"type":"Point"}
}