{
  "type": "Feature",
  "properties": {
    "gn:admin1_code":"60",
    "gn:admin2_code":"57.0",
    "gn:asciiname":"Laibiskiai",
    "gn:country_code":"LT",
    "gn:dem":91,
    "gn:feature_class":"P",
    "gn:feature_code":"PPL",
    "gn:name":"Laibi\u0161kiai",
    "gn:population":0,
    "gn:timezone":"Europe/Vilnius",
    "iso:country":"LT",
    "name:lit_x_preferred":[
        "Laibi\u0161kiai"
    ],
    "wof:name":"Laibiskiai",
    "wof:placetype":"locality"
},
  "geometry": {"coordinates":[25.2253,55.8812],"type":"Point"}
}