{
  "type": "Feature",
  "properties": {
    "gn:admin1_code":"65",
    "gn:admin2_code":"13.0",
    "gn:asciiname":"Maziuliai",
    "gn:country_code":"LT",
    "gn:dem":153,
    "gn:feature_class":"P",
    "gn:feature_code":"PPL",
    "gn:name":"Ma\u017eiuliai",
    "gn:population":0,
    "gn:timezone":"Europe/Vilnius",
    "iso:country":"LT",
    "name:lit_x_preferred":[
        "Ma\u017eiuliai"
    ],
    "wof:name":"Maziuliai",
    "wof:placetype":"locality"
},
  "geometry": {"coordinates":[25.60986,54.73007],"type":"Point"}
}