{
  "type": "Feature",
  "properties": {
    "gn:admin1_code":"64",
    "gn:admin2_code":"62.0",
    "gn:asciiname":"Rapejai",
    "gn:country_code":"LT",
    "gn:dem":162,
    "gn:feature_class":"P",
    "gn:feature_code":"PPL",
    "gn:name":"Rap\u0117jai",
    "gn:population":0,
    "gn:timezone":"Europe/Vilnius",
    "iso:country":"LT",
    "name:lit_x_preferred":[
        "Rap\u0117jai"
    ],
    "wof:name":"Rapejai",
    "wof:placetype":"locality"
},
  "geometry": {"coordinates":[25.70645,55.12999],"type":"Point"}
}