{
  "type": "Feature",
  "properties": {
    "gn:admin1_code":"61.0",
    "gn:admin2_code":"54.0",
    "gn:asciiname":"Paplusciai",
    "gn:country_code":"LT",
    "gn:dem":139,
    "gn:feature_class":"P",
    "gn:feature_code":"PPL",
    "gn:name":"Papl\u016bs\u010diai",
    "gn:population":0,
    "gn:timezone":"Europe/Vilnius",
    "iso:country":"LT",
    "name:lit_x_preferred":[
        "Papl\u016bs\u010diai"
    ],
    "name:und_x_variant":[
        "Paplu\u0161\u010diai"
    ],
    "wof:name":"Paplusciai",
    "wof:placetype":"locality"
},
  "geometry": {"coordinates":[22.66537000000001,55.55108000000001],"type":"Point"}
}