{
  "type": "Feature",
  "properties": {
    "gn:admin1_code":"65",
    "gn:admin2_code":"86.0",
    "gn:asciiname":"Toleikos",
    "gn:country_code":"LT",
    "gn:dem":200,
    "gn:feature_class":"P",
    "gn:feature_code":"PPL",
    "gn:name":"Toleikos",
    "gn:population":0,
    "gn:timezone":"Europe/Vilnius",
    "iso:country":"LT",
    "name:lit_x_preferred":[
        "Toleikos"
    ],
    "wof:name":"Toleikos",
    "wof:placetype":"locality"
},
  "geometry": {"coordinates":[26.20688,55.05205],"type":"Point"}
}