{
  "type": "Feature",
  "properties": {
    "gn:admin1_code":"60",
    "gn:admin2_code":"36.0",
    "gn:asciiname":"Rindaugiskiai",
    "gn:country_code":"LT",
    "gn:dem":49,
    "gn:feature_class":"P",
    "gn:feature_code":"PPL",
    "gn:name":"Rindaugi\u0161kiai",
    "gn:population":0,
    "gn:timezone":"Europe/Vilnius",
    "iso:country":"LT",
    "name:lit_x_preferred":[
        "Rindaugi\u0161kiai"
    ],
    "wof:name":"Rindaugiskiai",
    "wof:placetype":"locality"
},
  "geometry": {"coordinates":[24.69256,56.3203],"type":"Point"}
}