{
  "type": "Feature",
  "properties": {
    "gn:admin1_code":"0.0",
    "gn:asciiname":"Kacaiciai",
    "gn:cc2":"LT",
    "gn:country_code":"LT",
    "gn:dem":53,
    "gn:feature_class":"P",
    "gn:feature_code":"PPL",
    "gn:name":"Ka\u010dai\u010diai",
    "gn:population":0,
    "gn:timezone":"Europe/Vilnius",
    "iso:country":"LT",
    "name:und_x_variant":[
        "Kachaychey",
        "Ka\u010dai\u010diai"
    ],
    "wof:name":"Kacaiciai",
    "wof:placetype":"locality"
},
  "geometry": {"coordinates":[21.41667,55.86666999999999],"type":"Point"}
}