{
  "type": "Feature",
  "properties": {
    "gn:admin1_code":"61",
    "gn:admin2_code":"29.0",
    "gn:asciiname":"Tulkinciai",
    "gn:country_code":"LT",
    "gn:dem":97,
    "gn:feature_class":"P",
    "gn:feature_code":"PPL",
    "gn:name":"Tulkin\u010diai",
    "gn:population":0,
    "gn:timezone":"Europe/Vilnius",
    "iso:country":"LT",
    "name:lit_x_preferred":[
        "Tulkin\u010diai"
    ],
    "wof:name":"Tulkinciai",
    "wof:placetype":"locality"
},
  "geometry": {"coordinates":[22.8177,56.03131],"type":"Point"}
}