{
  "type": "Feature",
  "properties": {
    "gn:admin1_code":"61",
    "gn:admin2_code":"65.0",
    "gn:asciiname":"Rauklaukis",
    "gn:country_code":"LT",
    "gn:dem":58,
    "gn:feature_class":"P",
    "gn:feature_code":"PPL",
    "gn:name":"Rauklaukis",
    "gn:population":0,
    "gn:timezone":"Europe/Vilnius",
    "iso:country":"LT",
    "name:lit_x_preferred":[
        "Rauklaukis"
    ],
    "wof:name":"Rauklaukis",
    "wof:placetype":"locality"
},
  "geometry": {"coordinates":[23.95593,56.10411],"type":"Point"}
}