{
  "type": "Feature",
  "properties": {
    "gn:admin1_code":"65.0",
    "gn:admin2_code":"86.0",
    "gn:asciiname":"Simaniske",
    "gn:country_code":"LT",
    "gn:dem":183,
    "gn:feature_class":"P",
    "gn:feature_code":"PPL",
    "gn:name":"Simani\u0161k\u0117",
    "gn:population":0,
    "gn:timezone":"Europe/Vilnius",
    "iso:country":"LT",
    "name:lit_x_preferred":[
        "Simani\u0161k\u0117"
    ],
    "name:und_x_variant":[
        "Symonishki",
        "\u0160imoni\u0161k\u0117"
    ],
    "wof:name":"Simaniske",
    "wof:placetype":"locality"
},
  "geometry": {"coordinates":[26.14637,55.04465],"type":"Point"}
}