{
  "type": "Feature",
  "properties": {
    "gn:admin1_code":"60.0",
    "gn:admin2_code":"36.0",
    "gn:asciiname":"Skrebiskiai",
    "gn:country_code":"LT",
    "gn:dem":78,
    "gn:feature_class":"P",
    "gn:feature_code":"PPL",
    "gn:name":"Skrebi\u0161kiai",
    "gn:population":0,
    "gn:timezone":"Europe/Vilnius",
    "iso:country":"LT",
    "name:und_x_variant":[
        "Skrebi\u0161kiai",
        "Skrebi\u0161ki\u0173",
        "Skrebishkyay",
        "Skrebi\u0161kis"
    ],
    "wof:name":"Skrebiskiai",
    "wof:placetype":"locality"
},
  "geometry": {"coordinates":[25.04309,56.14596],"type":"Point"}
}