{
  "type": "Feature",
  "properties": {
    "gn:admin1_code":"63.0",
    "gn:admin2_code":"74.0",
    "gn:asciiname":"Pyvorai",
    "gn:country_code":"LT",
    "gn:dem":125,
    "gn:feature_class":"P",
    "gn:feature_code":"PPL",
    "gn:name":"Pyvorai",
    "gn:population":0,
    "gn:timezone":"Europe/Vilnius",
    "iso:country":"LT",
    "name:und_x_variant":[
        "Pivoray",
        "Pivor\u0173",
        "Pyvoriai",
        "Pyvorai"
    ],
    "wof:name":"Pyvorai",
    "wof:placetype":"locality"
},
  "geometry": {"coordinates":[21.83986,55.77257],"type":"Point"}
}