{
  "type": "Feature",
  "properties": {
    "gn:admin1_code":"62.0",
    "gn:admin2_code":"77.0",
    "gn:asciiname":"Nosaiciai",
    "gn:country_code":"LT",
    "gn:dem":90,
    "gn:feature_class":"P",
    "gn:feature_code":"PPL",
    "gn:name":"Nosai\u010diai",
    "gn:population":0,
    "gn:timezone":"Europe/Vilnius",
    "iso:country":"LT",
    "name:und_x_variant":[
        "Nosaychyay",
        "Nosai\u010diai"
    ],
    "wof:name":"Nosaiciai",
    "wof:placetype":"locality"
},
  "geometry": {"coordinates":[22.59374,55.39554],"type":"Point"}
}