{
  "type": "Feature",
  "properties": {
    "gn:admin1_code":"58.0",
    "gn:admin2_code":"21.0",
    "gn:asciiname":"Vanagai",
    "gn:country_code":"LT",
    "gn:dem":13,
    "gn:feature_class":"P",
    "gn:feature_code":"PPL",
    "gn:name":"Vanagai",
    "gn:population":0,
    "gn:timezone":"Europe/Vilnius",
    "iso:country":"LT",
    "name:und_x_variant":[
        "Vanag\u0173",
        "Vanagey",
        "Wannaggen",
        "Vanagai"
    ],
    "wof:name":"Vanagai",
    "wof:placetype":"locality"
},
  "geometry": {"coordinates":[21.41657,55.56855],"type":"Point"}
}