{
  "type": "Feature",
  "properties": {
    "gn:admin1_code":"60",
    "gn:admin2_code":"36.0",
    "gn:asciiname":"Spalviskiai",
    "gn:country_code":"LT",
    "gn:dem":45,
    "gn:feature_class":"P",
    "gn:feature_code":"PPL",
    "gn:name":"Spalvi\u0161kiai",
    "gn:population":0,
    "gn:timezone":"Europe/Vilnius",
    "iso:country":"LT",
    "name:lit_x_preferred":[
        "Spalvi\u0161kiai"
    ],
    "wof:name":"Spalviskiai",
    "wof:placetype":"locality"
},
  "geometry": {"coordinates":[24.58018,56.15153000000001],"type":"Point"}
}