{
  "type": "Feature",
  "properties": {
    "gn:admin1_code":"57",
    "gn:admin2_code":"49.0",
    "gn:asciiname":"Armanai",
    "gn:country_code":"LT",
    "gn:dem":113,
    "gn:feature_class":"P",
    "gn:feature_code":"PPL",
    "gn:name":"Armanai",
    "gn:population":0,
    "gn:timezone":"Europe/Vilnius",
    "iso:country":"LT",
    "name:lit_x_preferred":[
        "Armanai"
    ],
    "wof:name":"Armanai",
    "wof:placetype":"locality"
},
  "geometry": {"coordinates":[24.28715,54.78683],"type":"Point"}
}