{
  "type": "Feature",
  "properties": {
    "gn:admin1_code":"65",
    "gn:admin2_code":"81.0",
    "gn:asciiname":"Deferencija",
    "gn:country_code":"LT",
    "gn:dem":146,
    "gn:feature_class":"P",
    "gn:feature_code":"PPL",
    "gn:name":"Deferencija",
    "gn:population":0,
    "gn:timezone":"Europe/Vilnius",
    "iso:country":"LT",
    "name:lit_x_preferred":[
        "Deferencija"
    ],
    "wof:name":"Deferencija",
    "wof:placetype":"locality"
},
  "geometry": {"coordinates":[25.0695,55.17251],"type":"Point"}
}