{
  "type": "Feature",
  "properties": {
    "gn:admin1_code":"57",
    "gn:admin2_code":"49.0",
    "gn:asciiname":"Bekstonys",
    "gn:country_code":"LT",
    "gn:dem":98,
    "gn:feature_class":"P",
    "gn:feature_code":"PPL",
    "gn:name":"Bek\u0161tonys",
    "gn:population":0,
    "gn:timezone":"Europe/Vilnius",
    "iso:country":"LT",
    "name:lit_x_preferred":[
        "Bek\u0161tonys"
    ],
    "wof:name":"Bekstonys",
    "wof:placetype":"locality"
},
  "geometry": {"coordinates":[24.74154,54.87706],"type":"Point"}
}