{
  "type": "Feature",
  "properties": {
    "gn:admin1_code":"56",
    "gn:admin2_code":"38.0",
    "gn:asciiname":"Jablanavas",
    "gn:country_code":"LT",
    "gn:dem":100,
    "gn:feature_class":"P",
    "gn:feature_code":"PPL",
    "gn:name":"Jablanavas",
    "gn:population":0,
    "gn:timezone":"Europe/Vilnius",
    "iso:country":"LT",
    "name:lit_x_preferred":[
        "Jablanavas"
    ],
    "wof:name":"Jablanavas",
    "wof:placetype":"locality"
},
  "geometry": {"coordinates":[24.23758,54.13262],"type":"Point"}
}