{
  "type": "Feature",
  "properties": {
    "gn:admin1_code":"56",
    "gn:admin2_code":"59.0",
    "gn:asciiname":"Vaickuniske",
    "gn:country_code":"LT",
    "gn:dem":121,
    "gn:feature_class":"P",
    "gn:feature_code":"PPL",
    "gn:name":"Vaick\u016bnisk\u0117",
    "gn:population":0,
    "gn:timezone":"Europe/Vilnius",
    "iso:country":"LT",
    "name:lit_x_preferred":[
        "Vaick\u016bnisk\u0117"
    ],
    "wof:name":"Vaickuniske",
    "wof:placetype":"locality"
},
  "geometry": {"coordinates":[23.76069,54.26926],"type":"Point"}
}