{
  "type": "Feature",
  "properties": {
    "gn:admin1_code":"65",
    "gn:admin2_code":"86.0",
    "gn:asciiname":"Zickeliai",
    "gn:country_code":"LT",
    "gn:dem":168,
    "gn:feature_class":"P",
    "gn:feature_code":"PPL",
    "gn:name":"\u017di\u010dkeliai",
    "gn:population":0,
    "gn:timezone":"Europe/Vilnius",
    "iso:country":"LT",
    "name:lit_x_preferred":[
        "\u017di\u010dkeliai"
    ],
    "wof:name":"Zickeliai",
    "wof:placetype":"locality"
},
  "geometry": {"coordinates":[25.6974,55.24826],"type":"Point"}
}