{
  "type": "Feature",
  "properties": {
    "gn:admin1_code":"63",
    "gn:admin2_code":"74.0",
    "gn:asciiname":"Grazciai",
    "gn:country_code":"LT",
    "gn:dem":119,
    "gn:feature_class":"P",
    "gn:feature_code":"PPL",
    "gn:name":"Gr\u0105\u017e\u010diai",
    "gn:population":0,
    "gn:timezone":"Europe/Vilnius",
    "iso:country":"LT",
    "name:lit_x_preferred":[
        "Gr\u0105\u017e\u010diai"
    ],
    "wof:name":"Grazciai",
    "wof:placetype":"locality"
},
  "geometry": {"coordinates":[22.11259,55.8421],"type":"Point"}
}