{
  "type": "Feature",
  "properties": {
    "gn:admin1_code":"56",
    "gn:admin2_code":"11.0",
    "gn:asciiname":"Zemaiteliai",
    "gn:country_code":"LT",
    "gn:dem":186,
    "gn:feature_class":"P",
    "gn:feature_code":"PPL",
    "gn:name":"\u017demait\u0117liai",
    "gn:population":0,
    "gn:timezone":"Europe/Vilnius",
    "iso:country":"LT",
    "name:lit_x_preferred":[
        "\u017demait\u0117liai"
    ],
    "wof:name":"Zemaiteliai",
    "wof:placetype":"locality"
},
  "geometry": {"coordinates":[24.19784,54.42765],"type":"Point"}
}