{
  "type": "Feature",
  "properties": {
    "gn:admin1_code":"57.0",
    "gn:admin2_code":"19.0",
    "gn:asciiname":"Puikoniai",
    "gn:country_code":"LT",
    "gn:dem":64,
    "gn:feature_class":"P",
    "gn:feature_code":"PPL",
    "gn:name":"Puikoniai",
    "gn:population":0,
    "gn:timezone":"Europe/Vilnius",
    "iso:country":"LT",
    "name:und_x_variant":[
        "Puykonyay",
        "Puykaynyay",
        "Puikoniai",
        "Puikainiai"
    ],
    "wof:name":"Puikoniai",
    "wof:placetype":"locality"
},
  "geometry": {"coordinates":[24.03565,55.09378],"type":"Point"}
}