{
  "type": "Feature",
  "properties": {
    "gn:admin1_code":"57",
    "gn:admin2_code":"72.0",
    "gn:asciiname":"Sakalai",
    "gn:country_code":"LT",
    "gn:dem":105,
    "gn:feature_class":"P",
    "gn:feature_code":"PPL",
    "gn:name":"Sakalai",
    "gn:population":0,
    "gn:timezone":"Europe/Vilnius",
    "iso:country":"LT",
    "name:lit_x_preferred":[
        "Sakalai"
    ],
    "wof:name":"Sakalai",
    "wof:placetype":"locality"
},
  "geometry": {"coordinates":[23.53853,55.45948000000001],"type":"Point"}
}