{
  "type": "Feature",
  "properties": {
    "gn:admin1_code":"64",
    "gn:admin2_code":"82.0",
    "gn:asciiname":"Kemesys",
    "gn:country_code":"LT",
    "gn:dem":197,
    "gn:feature_class":"P",
    "gn:feature_code":"PPL",
    "gn:name":"Keme\u0161ys",
    "gn:population":0,
    "gn:timezone":"Europe/Vilnius",
    "iso:country":"LT",
    "name:lit_x_preferred":[
        "Keme\u0161ys"
    ],
    "wof:name":"Kemesys",
    "wof:placetype":"locality"
},
  "geometry": {"coordinates":[25.8423,55.3854],"type":"Point"}
}