{
  "type": "Feature",
  "properties": {
    "gn:admin1_code":"60",
    "gn:admin2_code":"36.0",
    "gn:asciiname":"Jukniskiai",
    "gn:country_code":"LT",
    "gn:dem":42,
    "gn:feature_class":"P",
    "gn:feature_code":"PPL",
    "gn:name":"Jukni\u0161kiai",
    "gn:population":0,
    "gn:timezone":"Europe/Vilnius",
    "iso:country":"LT",
    "name:lit_x_preferred":[
        "Jukni\u0161kiai"
    ],
    "wof:name":"Jukniskiai",
    "wof:placetype":"locality"
},
  "geometry": {"coordinates":[24.61634,56.2696],"type":"Point"}
}