{
  "type": "Feature",
  "properties": {
    "gn:admin1_code":"65.0",
    "gn:admin2_code":"13.0",
    "gn:asciiname":"Parudaminys",
    "gn:country_code":"LT",
    "gn:dem":143,
    "gn:feature_class":"P",
    "gn:feature_code":"PPL",
    "gn:name":"Parudaminys",
    "gn:population":0,
    "gn:timezone":"Europe/Vilnius",
    "iso:country":"LT",
    "name:eng_x_preferred":[
        "Parudaminys"
    ],
    "name:rus_x_preferred":[
        "\u041f\u0430\u0440\u0443\u0434\u0430\u043c\u0438\u043d\u0438\u0441"
    ],
    "name:und_x_variant":[
        "Porudamino",
        "Parudamanas",
        "Porudomino",
        "Parudaminis"
    ],
    "wof:name":"Parudaminys",
    "wof:placetype":"locality"
},
  "geometry": {"coordinates":[25.26792,54.52256],"type":"Point"}
}