{
  "type": "Feature",
  "properties": {
    "gn:admin1_code":"63.0",
    "gn:admin2_code":"78.0",
    "gn:asciiname":"Tarvydai",
    "gn:country_code":"LT",
    "gn:dem":169,
    "gn:feature_class":"P",
    "gn:feature_code":"PPL",
    "gn:name":"Tarvydai",
    "gn:population":0,
    "gn:timezone":"Europe/Vilnius",
    "iso:country":"LT",
    "name:und_x_variant":[
        "Tarviday",
        "Tarvydai"
    ],
    "wof:name":"Tarvydai",
    "wof:placetype":"locality"
},
  "geometry": {"coordinates":[22.30294,55.81143],"type":"Point"}
}