{
  "type": "Feature",
  "properties": {
    "gn:admin1_code":"65",
    "gn:admin2_code":"13.0",
    "gn:asciiname":"Paraudondvariai",
    "gn:country_code":"LT",
    "gn:dem":153,
    "gn:feature_class":"P",
    "gn:feature_code":"PPL",
    "gn:name":"Paraudondvariai",
    "gn:population":0,
    "gn:timezone":"Europe/Vilnius",
    "iso:country":"LT",
    "name:lit_x_preferred":[
        "Paraudondvariai"
    ],
    "wof:name":"Paraudondvariai",
    "wof:placetype":"locality"
},
  "geometry": {"coordinates":[25.26592,54.82926],"type":"Point"}
}