{
  "type": "Feature",
  "properties": {
    "gn:admin1_code":"65",
    "gn:admin2_code":"81.0",
    "gn:asciiname":"Naujasodis",
    "gn:country_code":"LT",
    "gn:dem":80,
    "gn:feature_class":"P",
    "gn:feature_code":"PPL",
    "gn:name":"Naujasodis",
    "gn:population":0,
    "gn:timezone":"Europe/Vilnius",
    "iso:country":"LT",
    "name:lit_x_preferred":[
        "Naujasodis"
    ],
    "wof:name":"Naujasodis",
    "wof:placetype":"locality"
},
  "geometry": {"coordinates":[24.55327,55.44836],"type":"Point"}
}