{
  "type": "Feature",
  "properties": {
    "gn:admin1_code":"64",
    "gn:admin2_code":"43.0",
    "gn:asciiname":"Terteliai",
    "gn:country_code":"LT",
    "gn:dem":167,
    "gn:feature_class":"P",
    "gn:feature_code":"PPL",
    "gn:name":"Terteliai",
    "gn:population":0,
    "gn:timezone":"Europe/Vilnius",
    "iso:country":"LT",
    "name:lit_x_preferred":[
        "Terteliai"
    ],
    "wof:name":"Terteliai",
    "wof:placetype":"locality"
},
  "geometry": {"coordinates":[26.16076,55.83205],"type":"Point"}
}