{
  "type": "Feature",
  "properties": {
    "gn:admin1_code":"57.0",
    "gn:admin2_code":"49.0",
    "gn:asciiname":"Skudeniai",
    "gn:country_code":"LT",
    "gn:dem":134,
    "gn:feature_class":"P",
    "gn:feature_code":"PPL",
    "gn:name":"Skudeniai",
    "gn:population":0,
    "gn:timezone":"Europe/Vilnius",
    "iso:country":"LT",
    "name:und_x_variant":[
        "Shkudyany",
        "Skudeniai"
    ],
    "wof:name":"Skudeniai",
    "wof:placetype":"locality"
},
  "geometry": {"coordinates":[24.46263,54.77401999999999],"type":"Point"}
}