{
  "type": "Feature",
  "properties": {
    "gn:admin1_code":"57.0",
    "gn:admin2_code":"53.0",
    "gn:asciiname":"Zilionys",
    "gn:country_code":"LT",
    "gn:dem":67,
    "gn:feature_class":"P",
    "gn:feature_code":"PPL",
    "gn:name":"\u017dilionys",
    "gn:population":0,
    "gn:timezone":"Europe/Vilnius",
    "iso:country":"LT",
    "name:und_x_variant":[
        "Zhilyantse",
        "\u017dilionys"
    ],
    "wof:name":"Zilionys",
    "wof:placetype":"locality"
},
  "geometry": {"coordinates":[24.31728,55.37779000000001],"type":"Point"}
}