{
  "type": "Feature",
  "properties": {
    "gn:admin1_code":"65",
    "gn:admin2_code":"89.0",
    "gn:asciiname":"Babriskis",
    "gn:country_code":"LT",
    "gn:dem":91,
    "gn:feature_class":"P",
    "gn:feature_code":"PPL",
    "gn:name":"Babri\u0161kis",
    "gn:population":0,
    "gn:timezone":"Europe/Vilnius",
    "iso:country":"LT",
    "name:lit_x_preferred":[
        "Babri\u0161kis"
    ],
    "wof:name":"Babriskis",
    "wof:placetype":"locality"
},
  "geometry": {"coordinates":[24.58844,54.99083],"type":"Point"}
}