{
  "type": "Feature",
  "properties": {
    "gn:admin1_code":"58.0",
    "gn:admin2_code":"56.0",
    "gn:asciiname":"Kalnalis",
    "gn:country_code":"LT",
    "gn:dem":66,
    "gn:feature_class":"P",
    "gn:feature_code":"PPL",
    "gn:name":"Kalnalis",
    "gn:population":0,
    "gn:timezone":"Europe/Vilnius",
    "iso:country":"LT",
    "name:und_x_variant":[
        "Kalnelio",
        "Kalnieli",
        "Kalnalis"
    ],
    "wof:name":"Kalnalis",
    "wof:placetype":"locality"
},
  "geometry": {"coordinates":[21.53893,56.01407],"type":"Point"}
}