{
  "type": "Feature",
  "properties": {
    "gn:admin1_code":"65",
    "gn:admin2_code":"13.0",
    "gn:asciiname":"Berzyte",
    "gn:country_code":"LT",
    "gn:dem":255,
    "gn:feature_class":"P",
    "gn:feature_code":"PPL",
    "gn:name":"Berzyt\u0117",
    "gn:population":0,
    "gn:timezone":"Europe/Vilnius",
    "iso:country":"LT",
    "name:lit_x_preferred":[
        "Berzyt\u0117"
    ],
    "wof:name":"Berzyte",
    "wof:placetype":"locality"
},
  "geometry": {"coordinates":[25.60867,54.49466],"type":"Point"}
}