{
  "type": "Feature",
  "properties": {
    "gn:admin1_code":"60.0",
    "gn:admin2_code":"73.0",
    "gn:asciiname":"Azusiliai",
    "gn:country_code":"LT",
    "gn:dem":133,
    "gn:feature_class":"P",
    "gn:feature_code":"PPL",
    "gn:name":"A\u017eu\u0161iliai",
    "gn:population":0,
    "gn:timezone":"Europe/Vilnius",
    "iso:country":"LT",
    "name:lit_x_preferred":[
        "A\u017eu\u0161iliai"
    ],
    "wof:name":"Azusiliai",
    "wof:placetype":"locality"
},
  "geometry": {"coordinates":[26.00885,55.95848],"type":"Point"}
}