{
  "type": "Feature",
  "properties": {
    "gn:admin1_code":"60.0",
    "gn:admin2_code":"67.0",
    "gn:asciiname":"Vienzindziai",
    "gn:country_code":"LT",
    "gn:dem":64,
    "gn:feature_class":"P",
    "gn:feature_code":"PPL",
    "gn:name":"Vien\u017eind\u017eiai",
    "gn:population":0,
    "gn:timezone":"Europe/Vilnius",
    "iso:country":"LT",
    "name:und_x_variant":[
        "Viyendzhyudzhyay",
        "Venzhindzhyay",
        "Vien\u017eend\u017ei\u0173",
        "Vien\u017eind\u017eiai"
    ],
    "wof:name":"Vienzindziai",
    "wof:placetype":"locality"
},
  "geometry": {"coordinates":[24.13444,56.102],"type":"Point"}
}