{
  "type": "Feature",
  "properties": {
    "gn:admin1_code":"59",
    "gn:admin2_code":"18.0",
    "gn:asciiname":"Kumeciai",
    "gn:country_code":"LT",
    "gn:dem":93,
    "gn:feature_class":"P",
    "gn:feature_code":"PPL",
    "gn:name":"Kume\u010diai",
    "gn:population":0,
    "gn:timezone":"Europe/Vilnius",
    "iso:country":"LT",
    "name:lit_x_preferred":[
        "Kume\u010diai"
    ],
    "wof:name":"Kumeciai",
    "wof:placetype":"locality"
},
  "geometry": {"coordinates":[23.531,54.47581],"type":"Point"}
}