{
  "type": "Feature",
  "properties": {
    "gn:admin1_code":"0.0",
    "gn:asciiname":"Bliudsukiai",
    "gn:cc2":"LT",
    "gn:country_code":"LT",
    "gn:dem":38,
    "gn:feature_class":"P",
    "gn:feature_code":"PPL",
    "gn:name":"Bli\u016bdsukiai",
    "gn:population":0,
    "gn:timezone":"Europe/Vilnius",
    "iso:country":"LT",
    "name:und_x_variant":[
        "Bli\u016bcakiai",
        "Blyutsakey",
        "Bli\u016bdsukiai"
    ],
    "wof:name":"Bliudsukiai",
    "wof:placetype":"locality"
},
  "geometry": {"coordinates":[21.28333,55.86666999999999],"type":"Point"}
}