{
  "type": "Feature",
  "properties": {
    "gn:admin1_code":"61.0",
    "gn:admin2_code":"54.0",
    "gn:asciiname":"Laplegiai",
    "gn:country_code":"LT",
    "gn:dem":157,
    "gn:feature_class":"P",
    "gn:feature_code":"PPL",
    "gn:name":"Lapl\u0117giai",
    "gn:population":0,
    "gn:timezone":"Europe/Vilnius",
    "iso:country":"LT",
    "name:und_x_variant":[
        "Laplega",
        "Laplegyay",
        "Lapl\u0117giai"
    ],
    "wof:name":"Laplegiai",
    "wof:placetype":"locality"
},
  "geometry": {"coordinates":[22.70376,55.53186],"type":"Point"}
}