{
  "type": "Feature",
  "properties": {
    "gn:admin1_code":"56",
    "gn:admin2_code":"59.0",
    "gn:asciiname":"Bilvyciai",
    "gn:country_code":"LT",
    "gn:dem":127,
    "gn:feature_class":"P",
    "gn:feature_code":"PPL",
    "gn:name":"Bilvy\u010diai",
    "gn:population":0,
    "gn:timezone":"Europe/Vilnius",
    "iso:country":"LT",
    "name:lit_x_preferred":[
        "Bilvy\u010diai"
    ],
    "wof:name":"Bilvyciai",
    "wof:placetype":"locality"
},
  "geometry": {"coordinates":[23.33721,54.28965],"type":"Point"}
}