{
  "type": "Feature",
  "properties": {
    "gn:admin1_code":"60",
    "gn:admin2_code":"36.0",
    "gn:asciiname":"Sandariskiai",
    "gn:country_code":"LT",
    "gn:dem":54,
    "gn:feature_class":"P",
    "gn:feature_code":"PPL",
    "gn:name":"Sandari\u0161kiai",
    "gn:population":0,
    "gn:timezone":"Europe/Riga",
    "iso:country":"LT",
    "name:lit_x_preferred":[
        "Sandari\u0161kiai"
    ],
    "wof:name":"Sandariskiai",
    "wof:placetype":"locality"
},
  "geometry": {"coordinates":[24.92059,56.40078000000001],"type":"Point"}
}