{
  "type": "Feature",
  "properties": {
    "gn:admin1_code":"59",
    "gn:admin2_code":"58.0",
    "gn:asciiname":"Maliejiske",
    "gn:country_code":"LT",
    "gn:dem":52,
    "gn:feature_class":"P",
    "gn:feature_code":"PPL",
    "gn:name":"Malieji\u0161k\u0117",
    "gn:population":0,
    "gn:timezone":"Europe/Vilnius",
    "iso:country":"LT",
    "name:lit_x_preferred":[
        "Malieji\u0161k\u0117"
    ],
    "wof:name":"Maliejiske",
    "wof:placetype":"locality"
},
  "geometry": {"coordinates":[23.30317,54.78674],"type":"Point"}
}