{
  "type": "Feature",
  "properties": {
    "gn:admin1_code":"57.0",
    "gn:admin2_code":"53.0",
    "gn:asciiname":"Balsiai",
    "gn:country_code":"LT",
    "gn:dem":87,
    "gn:feature_class":"P",
    "gn:feature_code":"PPL",
    "gn:name":"Balsiai",
    "gn:population":0,
    "gn:timezone":"Europe/Vilnius",
    "iso:country":"LT",
    "name:und_x_variant":[
        "Selki",
        "Balsiai"
    ],
    "wof:name":"Balsiai",
    "wof:placetype":"locality"
},
  "geometry": {"coordinates":[23.79305,55.52065],"type":"Point"}
}