{
  "type": "Feature",
  "properties": {
    "gn:admin1_code":"59",
    "gn:admin2_code":"84.0",
    "gn:asciiname":"Matuliai",
    "gn:country_code":"LT",
    "gn:dem":53,
    "gn:feature_class":"P",
    "gn:feature_code":"PPL",
    "gn:name":"Matuliai",
    "gn:population":0,
    "gn:timezone":"Europe/Vilnius",
    "iso:country":"LT",
    "name:lit_x_preferred":[
        "Matuliai"
    ],
    "wof:name":"Matuliai",
    "wof:placetype":"locality"
},
  "geometry": {"coordinates":[23.01652,54.97185],"type":"Point"}
}