{
  "type": "Feature",
  "properties": {
    "gn:admin1_code":"56.0",
    "gn:admin2_code":"11.0",
    "gn:asciiname":"Norgeliskes",
    "gn:country_code":"LT",
    "gn:dem":157,
    "gn:feature_class":"P",
    "gn:feature_code":"PPL",
    "gn:name":"Norgeli\u0161k\u0117s",
    "gn:population":0,
    "gn:timezone":"Europe/Vilnius",
    "iso:country":"LT",
    "name:lit_x_preferred":[
        "Norgeli\u0161k\u0117s"
    ],
    "wof:name":"Norgeliskes",
    "wof:placetype":"locality"
},
  "geometry": {"coordinates":[24.11903,54.44583000000001],"type":"Point"}
}