{
  "type": "Feature",
  "properties": {
    "gn:admin1_code":"56",
    "gn:admin2_code":"11.0",
    "gn:asciiname":"Perseke",
    "gn:country_code":"LT",
    "gn:dem":82,
    "gn:feature_class":"P",
    "gn:feature_code":"PPL",
    "gn:name":"Per\u0161\u0117k\u0117",
    "gn:population":0,
    "gn:timezone":"Europe/Vilnius",
    "iso:country":"LT",
    "name:lit_x_preferred":[
        "Per\u0161\u0117k\u0117"
    ],
    "wof:name":"Perseke",
    "wof:placetype":"locality"
},
  "geometry": {"coordinates":[23.80174,54.46178000000001],"type":"Point"}
}