{
  "type": "Feature",
  "properties": {
    "gn:admin1_code":"65",
    "gn:admin2_code":"81.0",
    "gn:asciiname":"Domantiskiai",
    "gn:country_code":"LT",
    "gn:dem":76,
    "gn:feature_class":"P",
    "gn:feature_code":"PPL",
    "gn:name":"Domanti\u0161kiai",
    "gn:population":0,
    "gn:timezone":"Europe/Vilnius",
    "iso:country":"LT",
    "name:lit_x_preferred":[
        "Domanti\u0161kiai"
    ],
    "wof:name":"Domantiskiai",
    "wof:placetype":"locality"
},
  "geometry": {"coordinates":[24.56495,55.2979],"type":"Point"}
}