{
  "type": "Feature",
  "properties": {
    "gn:admin1_code":"61.0",
    "gn:admin2_code":"29.0",
    "gn:asciiname":"Daunorai",
    "gn:country_code":"LT",
    "gn:dem":97,
    "gn:feature_class":"P",
    "gn:feature_code":"PPL",
    "gn:name":"Daunorai",
    "gn:population":0,
    "gn:timezone":"Europe/Vilnius",
    "iso:country":"LT",
    "name:und_x_variant":[
        "Davnory",
        "Daunorai"
    ],
    "wof:name":"Daunorai",
    "wof:placetype":"locality"
},
  "geometry": {"coordinates":[23.47974,56.00274],"type":"Point"}
}