{
  "type": "Feature",
  "properties": {
    "gn:admin1_code":"59",
    "gn:admin2_code":"39.0",
    "gn:asciiname":"Moliniskiai",
    "gn:country_code":"LT",
    "gn:dem":95,
    "gn:feature_class":"P",
    "gn:feature_code":"PPL",
    "gn:name":"Molini\u0161kiai",
    "gn:population":0,
    "gn:timezone":"Europe/Vilnius",
    "iso:country":"LT",
    "name:lit_x_preferred":[
        "Molini\u0161kiai"
    ],
    "wof:name":"Moliniskiai",
    "wof:placetype":"locality"
},
  "geometry": {"coordinates":[22.97501,54.5457],"type":"Point"}
}