{
  "type": "Feature",
  "properties": {
    "gn:admin1_code":"64",
    "gn:admin2_code":"34.0",
    "gn:asciiname":"Kileviskiai",
    "gn:country_code":"LT",
    "gn:dem":181,
    "gn:feature_class":"P",
    "gn:feature_code":"PPL",
    "gn:name":"Kil\u0117vi\u0161kiai",
    "gn:population":0,
    "gn:timezone":"Europe/Vilnius",
    "iso:country":"LT",
    "name:lit_x_preferred":[
        "Kil\u0117vi\u0161kiai"
    ],
    "wof:name":"Kileviskiai",
    "wof:placetype":"locality"
},
  "geometry": {"coordinates":[25.40043,55.52629],"type":"Point"}
}