{
  "type": "Feature",
  "properties": {
    "gn:admin1_code":"61",
    "gn:admin2_code":"29.0",
    "gn:asciiname":"Vilkdarze",
    "gn:country_code":"LT",
    "gn:dem":121,
    "gn:feature_class":"P",
    "gn:feature_code":"PPL",
    "gn:name":"Vilkdar\u017e\u0117",
    "gn:population":0,
    "gn:timezone":"Europe/Vilnius",
    "iso:country":"LT",
    "name:lit_x_preferred":[
        "Vilkdar\u017e\u0117"
    ],
    "wof:name":"Vilkdarze",
    "wof:placetype":"locality"
},
  "geometry": {"coordinates":[22.68907,56.01135],"type":"Point"}
}