{
  "type": "Feature",
  "properties": {
    "gn:admin1_code":"65",
    "gn:admin2_code":"85.0",
    "gn:asciiname":"Geloze",
    "gn:country_code":"LT",
    "gn:dem":209,
    "gn:feature_class":"P",
    "gn:feature_code":"PPL",
    "gn:name":"Gelo\u017e\u0117",
    "gn:population":0,
    "gn:timezone":"Europe/Vilnius",
    "iso:country":"LT",
    "name:lit_x_preferred":[
        "Gelo\u017e\u0117"
    ],
    "wof:name":"Geloze",
    "wof:placetype":"locality"
},
  "geometry": {"coordinates":[25.3789,54.43388],"type":"Point"}
}