{
  "type": "Feature",
  "properties": {
    "gn:admin1_code":"64",
    "gn:admin2_code":"34.0",
    "gn:asciiname":"Paazuoliai",
    "gn:country_code":"LT",
    "gn:dem":158,
    "gn:feature_class":"P",
    "gn:feature_code":"PPL",
    "gn:name":"Pa\u0105\u017euoliai",
    "gn:population":0,
    "gn:timezone":"Europe/Vilnius",
    "iso:country":"LT",
    "name:lit_x_preferred":[
        "Pa\u0105\u017euoliai"
    ],
    "wof:name":"Paazuoliai",
    "wof:placetype":"locality"
},
  "geometry": {"coordinates":[25.05778,55.3426],"type":"Point"}
}