{
  "type": "Feature",
  "properties": {
    "gn:admin1_code":"65",
    "gn:admin2_code":"85.0",
    "gn:asciiname":"Gudakampis",
    "gn:country_code":"LT",
    "gn:dem":175,
    "gn:feature_class":"P",
    "gn:feature_code":"PPL",
    "gn:name":"Gudakampis",
    "gn:population":0,
    "gn:timezone":"Europe/Vilnius",
    "iso:country":"LT",
    "name:lit_x_preferred":[
        "Gudakampis"
    ],
    "wof:name":"Gudakampis",
    "wof:placetype":"locality"
},
  "geometry": {"coordinates":[25.15837,54.21365],"type":"Point"}
}