{
  "type": "Feature",
  "properties": {
    "gn:admin1_code":"63.0",
    "gn:admin2_code":"68.0",
    "gn:asciiname":"Purvaiciai",
    "gn:country_code":"LT",
    "gn:dem":115,
    "gn:feature_class":"P",
    "gn:feature_code":"PPL",
    "gn:name":"Purvai\u010diai",
    "gn:population":0,
    "gn:timezone":"Europe/Vilnius",
    "iso:country":"LT",
    "name:und_x_variant":[
        "Purvaychey",
        "Purvai\u010di\u0173",
        "Purvai\u010diai"
    ],
    "wof:name":"Purvaiciai",
    "wof:placetype":"locality"
},
  "geometry": {"coordinates":[21.98111,55.85318],"type":"Point"}
}