{
  "type": "Feature",
  "properties": {
    "gn:admin1_code":"58",
    "gn:admin2_code":"56.0",
    "gn:asciiname":"Klausgalvu Medsedziai",
    "gn:country_code":"LT",
    "gn:dem":62,
    "gn:feature_class":"P",
    "gn:feature_code":"PPL",
    "gn:name":"Klausgalv\u0173 Meds\u0117d\u017eiai",
    "gn:population":0,
    "gn:timezone":"Europe/Vilnius",
    "iso:country":"LT",
    "name:lit_x_preferred":[
        "Klausgalv\u0173 Meds\u0117d\u017eiai"
    ],
    "wof:name":"Klausgalvu Medsedziai",
    "wof:placetype":"locality"
},
  "geometry": {"coordinates":[21.4945,56.01004],"type":"Point"}
}