{
  "type": "Feature",
  "properties": {
    "gn:admin1_code":"60",
    "gn:admin2_code":"73.0",
    "gn:asciiname":"Diliaukiskis",
    "gn:country_code":"LT",
    "gn:dem":157,
    "gn:feature_class":"P",
    "gn:feature_code":"PPL",
    "gn:name":"Diliauki\u0161kis",
    "gn:population":0,
    "gn:timezone":"Europe/Vilnius",
    "iso:country":"LT",
    "name:lit_x_preferred":[
        "Diliauki\u0161kis"
    ],
    "wof:name":"Diliaukiskis",
    "wof:placetype":"locality"
},
  "geometry": {"coordinates":[25.94508,55.90254],"type":"Point"}
}