{
  "type": "Feature",
  "properties": {
    "gn:admin1_code":"63.0",
    "gn:admin2_code":"74.0",
    "gn:asciiname":"Kiliunenai",
    "gn:country_code":"LT",
    "gn:dem":173,
    "gn:feature_class":"P",
    "gn:feature_code":"PPL",
    "gn:name":"Kili\u016bn\u0117nai",
    "gn:population":0,
    "gn:timezone":"Europe/Vilnius",
    "iso:country":"LT",
    "name:und_x_variant":[
        "Kilnenay",
        "Kili\u016bn\u0117nai"
    ],
    "wof:name":"Kiliunenai",
    "wof:placetype":"locality"
},
  "geometry": {"coordinates":[22.14906,55.80031],"type":"Point"}
}