{
  "type": "Feature",
  "properties": {
    "gn:admin1_code":"60.0",
    "gn:admin2_code":"36.0",
    "gn:asciiname":"Miegonys",
    "gn:country_code":"LT",
    "gn:dem":78,
    "gn:feature_class":"P",
    "gn:feature_code":"PPL",
    "gn:name":"Miegonys",
    "gn:population":0,
    "gn:timezone":"Europe/Vilnius",
    "iso:country":"LT",
    "name:und_x_variant":[
        "Miyegonis",
        "Miegoni\u0173",
        "Miegonys"
    ],
    "wof:name":"Miegonys",
    "wof:placetype":"locality"
},
  "geometry": {"coordinates":[25.03484,56.06549],"type":"Point"}
}