{
  "type": "Feature",
  "properties": {
    "gn:admin1_code":"64.0",
    "gn:admin2_code":"62.0",
    "gn:asciiname":"Kijeliai",
    "gn:country_code":"LT",
    "gn:dem":157,
    "gn:feature_class":"P",
    "gn:feature_code":"PPL",
    "gn:name":"Kij\u0117liai",
    "gn:population":0,
    "gn:timezone":"Europe/Vilnius",
    "iso:country":"LT",
    "name:lit_x_preferred":[
        "Kij\u0117liai"
    ],
    "name:und_x_variant":[
        "Kieliai"
    ],
    "wof:name":"Kijeliai",
    "wof:placetype":"locality"
},
  "geometry": {"coordinates":[25.38546,55.23309],"type":"Point"}
}