{
  "type": "Feature",
  "properties": {
    "gn:admin1_code":"65",
    "gn:admin2_code":"81.0",
    "gn:asciiname":"Sleniai",
    "gn:country_code":"LT",
    "gn:dem":68,
    "gn:feature_class":"P",
    "gn:feature_code":"PPL",
    "gn:name":"\u0160leniai",
    "gn:population":0,
    "gn:timezone":"Europe/Vilnius",
    "iso:country":"LT",
    "name:lit_x_preferred":[
        "\u0160leniai"
    ],
    "wof:name":"Sleniai",
    "wof:placetype":"locality"
},
  "geometry": {"coordinates":[24.8129,55.34795],"type":"Point"}
}