{
  "type": "Feature",
  "properties": {
    "gn:admin1_code":"61",
    "gn:admin2_code":"71.0",
    "gn:asciiname":"Noruciai",
    "gn:country_code":"LT",
    "gn:dem":105,
    "gn:feature_class":"P",
    "gn:feature_code":"PPL",
    "gn:name":"Noru\u010diai",
    "gn:population":0,
    "gn:timezone":"Europe/Vilnius",
    "iso:country":"LT",
    "name:lit_x_preferred":[
        "Noru\u010diai"
    ],
    "wof:name":"Noruciai",
    "wof:placetype":"locality"
},
  "geometry": {"coordinates":[23.62752,55.54269],"type":"Point"}
}