{
  "type": "Feature",
  "properties": {
    "gn:admin1_code":"59.0",
    "gn:admin2_code":"58.0",
    "gn:asciiname":"Bebruliske",
    "gn:country_code":"LT",
    "gn:dem":61,
    "gn:feature_class":"P",
    "gn:feature_code":"PPL",
    "gn:name":"Bebruli\u0161k\u0117",
    "gn:population":0,
    "gn:timezone":"Europe/Vilnius",
    "iso:country":"LT",
    "name:und_x_variant":[
        "Bobrolishki",
        "Bebruli\u0161k\u0117s",
        "Bebrulishkis",
        "Bebruli\u0161k\u0117"
    ],
    "wof:name":"Bebruliske",
    "wof:placetype":"locality"
},
  "geometry": {"coordinates":[23.44946,54.69965],"type":"Point"}
}