{
  "type": "Feature",
  "properties": {
    "gn:admin1_code":"58.0",
    "gn:admin2_code":"21.0",
    "gn:asciiname":"Kintrimai",
    "gn:country_code":"LT",
    "gn:dem":108,
    "gn:feature_class":"P",
    "gn:feature_code":"PPL",
    "gn:name":"Kintrimai",
    "gn:population":0,
    "gn:timezone":"Europe/Vilnius",
    "iso:country":"LT",
    "name:und_x_variant":[
        "Kintrimay",
        "Kintrimai"
    ],
    "wof:name":"Kintrimai",
    "wof:placetype":"locality"
},
  "geometry": {"coordinates":[21.73967,55.66843000000001],"type":"Point"}
}