{
  "type": "Feature",
  "properties": {
    "gn:admin1_code":"60.0",
    "gn:admin2_code":"36.0",
    "gn:asciiname":"Butautai",
    "gn:country_code":"LT",
    "gn:dem":39,
    "gn:feature_class":"P",
    "gn:feature_code":"PPL",
    "gn:name":"Butautai",
    "gn:population":0,
    "gn:timezone":"Europe/Vilnius",
    "iso:country":"LT",
    "name:und_x_variant":[
        "Butaut\u0173",
        "Butautay",
        "Butautai"
    ],
    "wof:name":"Butautai",
    "wof:placetype":"locality"
},
  "geometry": {"coordinates":[24.60854,56.29691999999999],"type":"Point"}
}