{
  "type": "Feature",
  "properties": {
    "gn:admin1_code":"65",
    "gn:admin2_code":"86.0",
    "gn:asciiname":"Lygumai I",
    "gn:country_code":"LT",
    "gn:dem":202,
    "gn:feature_class":"P",
    "gn:feature_code":"PPL",
    "gn:name":"Lygumai I",
    "gn:population":0,
    "gn:timezone":"Europe/Vilnius",
    "iso:country":"LT",
    "name:lit_x_preferred":[
        "Lygumai I"
    ],
    "wof:name":"Lygumai I",
    "wof:placetype":"locality"
},
  "geometry": {"coordinates":[26.2004,55.1452],"type":"Point"}
}