{
  "type": "Feature",
  "properties": {
    "gn:admin1_code":"64",
    "gn:admin2_code":"45.0",
    "gn:asciiname":"Miskiniske",
    "gn:country_code":"LT",
    "gn:dem":176,
    "gn:feature_class":"P",
    "gn:feature_code":"PPL",
    "gn:name":"Mi\u0161kini\u0161k\u0117",
    "gn:population":0,
    "gn:timezone":"Europe/Vilnius",
    "iso:country":"LT",
    "name:lit_x_preferred":[
        "Mi\u0161kini\u0161k\u0117"
    ],
    "wof:name":"Miskiniske",
    "wof:placetype":"locality"
},
  "geometry": {"coordinates":[26.02765,55.48599],"type":"Point"}
}