{
  "type": "Feature",
  "properties": {
    "gn:admin1_code":"64",
    "gn:admin2_code":"82.0",
    "gn:asciiname":"Purviniskis",
    "gn:country_code":"LT",
    "gn:dem":179,
    "gn:feature_class":"P",
    "gn:feature_code":"PPL",
    "gn:name":"Purvini\u0161kis",
    "gn:population":0,
    "gn:timezone":"Europe/Vilnius",
    "iso:country":"LT",
    "name:lit_x_preferred":[
        "Purvini\u0161kis"
    ],
    "wof:name":"Purviniskis",
    "wof:placetype":"locality"
},
  "geometry": {"coordinates":[25.70639,55.45316],"type":"Point"}
}