{
  "type": "Feature",
  "properties": {
    "gn:admin1_code":"61.0",
    "gn:admin2_code":"32.0",
    "gn:asciiname":"Minkiai",
    "gn:country_code":"LT",
    "gn:dem":81,
    "gn:feature_class":"P",
    "gn:feature_code":"PPL",
    "gn:name":"Minkiai",
    "gn:population":0,
    "gn:timezone":"Europe/Vilnius",
    "iso:country":"LT",
    "name:und_x_variant":[
        "Minkyay",
        "Minkiai"
    ],
    "wof:name":"Minkiai",
    "wof:placetype":"locality"
},
  "geometry": {"coordinates":[23.08204,56.30919],"type":"Point"}
}