{
  "type": "Feature",
  "properties": {
    "gn:admin1_code":"61",
    "gn:admin2_code":"47.0",
    "gn:asciiname":"Vaizguciai",
    "gn:country_code":"LT",
    "gn:dem":71,
    "gn:feature_class":"P",
    "gn:feature_code":"PPL",
    "gn:name":"Vaizgu\u010diai",
    "gn:population":0,
    "gn:timezone":"Europe/Vilnius",
    "iso:country":"LT",
    "name:lit_x_preferred":[
        "Vaizgu\u010diai"
    ],
    "wof:name":"Vaizguciai",
    "wof:placetype":"locality"
},
  "geometry": {"coordinates":[23.57338,56.16083],"type":"Point"}
}