{
  "type": "Feature",
  "properties": {
    "gn:admin1_code":"64",
    "gn:admin2_code":"34.0",
    "gn:asciiname":"Sirvydai",
    "gn:country_code":"LT",
    "gn:dem":89,
    "gn:feature_class":"P",
    "gn:feature_code":"PPL",
    "gn:name":"Sirvydai",
    "gn:population":0,
    "gn:timezone":"Europe/Vilnius",
    "iso:country":"LT",
    "name:lit_x_preferred":[
        "Sirvydai"
    ],
    "wof:name":"Sirvydai",
    "wof:placetype":"locality"
},
  "geometry": {"coordinates":[24.92788,55.50148000000001],"type":"Point"}
}