{
  "type": "Feature",
  "properties": {
    "gn:admin1_code":"59",
    "gn:admin2_code":"18.0",
    "gn:asciiname":"Raisupys",
    "gn:country_code":"LT",
    "gn:dem":77,
    "gn:feature_class":"P",
    "gn:feature_code":"PPL",
    "gn:name":"Rai\u0161upys",
    "gn:population":0,
    "gn:timezone":"Europe/Vilnius",
    "iso:country":"LT",
    "name:lit_x_preferred":[
        "Rai\u0161upys"
    ],
    "wof:name":"Raisupys",
    "wof:placetype":"locality"
},
  "geometry": {"coordinates":[23.48444,54.60981],"type":"Point"}
}