{
  "type": "Feature",
  "properties": {
    "gn:admin1_code":"57.0",
    "gn:admin2_code":"19.0",
    "gn:asciiname":"Ramonai",
    "gn:country_code":"LT",
    "gn:dem":79,
    "gn:feature_class":"P",
    "gn:feature_code":"PPL",
    "gn:name":"Ramonai",
    "gn:population":0,
    "gn:timezone":"Europe/Vilnius",
    "iso:country":"LT",
    "name:und_x_variant":[
        "Romany",
        "Romenay",
        "Ramonai"
    ],
    "wof:name":"Ramonai",
    "wof:placetype":"locality"
},
  "geometry": {"coordinates":[23.6083,55.12152],"type":"Point"}
}