{
  "type": "Feature",
  "properties": {
    "gn:admin1_code":"58.0",
    "gn:admin2_code":"75.0",
    "gn:asciiname":"Nausedai",
    "gn:country_code":"LT",
    "gn:dem":95,
    "gn:feature_class":"P",
    "gn:feature_code":"PPL",
    "gn:name":"Naus\u0117dai",
    "gn:population":0,
    "gn:timezone":"Europe/Vilnius",
    "iso:country":"LT",
    "name:lit_x_preferred":[
        "Naus\u0117dai"
    ],
    "wof:name":"Nausedai",
    "wof:placetype":"locality"
},
  "geometry": {"coordinates":[21.81699,56.2316],"type":"Point"}
}