{
  "type": "Feature",
  "properties": {
    "gn:admin1_code":"57",
    "gn:admin2_code":"69.0",
    "gn:asciiname":"Buckiemis",
    "gn:country_code":"LT",
    "gn:dem":102,
    "gn:feature_class":"P",
    "gn:feature_code":"PPL",
    "gn:name":"B\u016b\u010dkiemis",
    "gn:population":0,
    "gn:timezone":"Europe/Vilnius",
    "iso:country":"LT",
    "name:lit_x_preferred":[
        "B\u016b\u010dkiemis"
    ],
    "wof:name":"Buckiemis",
    "wof:placetype":"locality"
},
  "geometry": {"coordinates":[24.04487,54.71198],"type":"Point"}
}