{
  "type": "Feature",
  "properties": {
    "gn:admin1_code":"64",
    "gn:admin2_code":"43.0",
    "gn:asciiname":"Murliskes",
    "gn:country_code":"LT",
    "gn:dem":170,
    "gn:feature_class":"P",
    "gn:feature_code":"PPL",
    "gn:name":"Murli\u0161k\u0117s",
    "gn:population":0,
    "gn:timezone":"Europe/Vilnius",
    "iso:country":"LT",
    "name:lit_x_preferred":[
        "Murli\u0161k\u0117s"
    ],
    "wof:name":"Murliskes",
    "wof:placetype":"locality"
},
  "geometry": {"coordinates":[25.92701,55.6202],"type":"Point"}
}