{
  "type": "Feature",
  "properties": {
    "gn:admin1_code":"61",
    "gn:admin2_code":"54.0",
    "gn:asciiname":"Kalnai",
    "gn:country_code":"LT",
    "gn:dem":180,
    "gn:feature_class":"P",
    "gn:feature_code":"PPL",
    "gn:name":"Kalnai",
    "gn:population":0,
    "gn:timezone":"Europe/Vilnius",
    "iso:country":"LT",
    "name:lit_x_preferred":[
        "Kalnai"
    ],
    "wof:name":"Kalnai",
    "wof:placetype":"locality"
},
  "geometry": {"coordinates":[22.86694,55.70101999999999],"type":"Point"}
}