{
  "type": "Feature",
  "properties": {
    "gn:admin1_code":"61.0",
    "gn:admin2_code":"71.0",
    "gn:asciiname":"Ozaiciai",
    "gn:country_code":"LT",
    "gn:dem":78,
    "gn:feature_class":"P",
    "gn:feature_code":"PPL",
    "gn:name":"O\u017eai\u010diai",
    "gn:population":0,
    "gn:timezone":"Europe/Vilnius",
    "iso:country":"LT",
    "name:eng_x_preferred":[
        "O\u017eai\u010diai"
    ],
    "name:rus_x_preferred":[
        "\u041e\u0436\u0430\u0439\u0447\u044f\u0439"
    ],
    "name:und_x_variant":[
        "Ozhaytse",
        "Ozhaychyay"
    ],
    "wof:name":"Ozaiciai",
    "wof:placetype":"locality"
},
  "geometry": {"coordinates":[23.91538,55.63934],"type":"Point"}
}