{
  "type": "Feature",
  "properties": {
    "gn:admin1_code":"60.0",
    "gn:admin2_code":"36.0",
    "gn:asciiname":"Sodeliskiai",
    "gn:country_code":"LT",
    "gn:dem":48,
    "gn:feature_class":"P",
    "gn:feature_code":"PPL",
    "gn:name":"Sodeli\u0161kiai",
    "gn:population":0,
    "gn:timezone":"Europe/Vilnius",
    "iso:country":"LT",
    "name:und_x_variant":[
        "Sodyalishkyay",
        "Sodeli\u0161kiai"
    ],
    "wof:name":"Sodeliskiai",
    "wof:placetype":"locality"
},
  "geometry": {"coordinates":[24.64148,56.28298],"type":"Point"}
}