{
  "type": "Feature",
  "properties": {
    "gn:admin1_code":"64",
    "gn:admin2_code":"62.0",
    "gn:asciiname":"Pagaluone",
    "gn:country_code":"LT",
    "gn:dem":161,
    "gn:feature_class":"P",
    "gn:feature_code":"PPL",
    "gn:name":"Pagaluon\u0117",
    "gn:population":0,
    "gn:timezone":"Europe/Vilnius",
    "iso:country":"LT",
    "name:lit_x_preferred":[
        "Pagaluon\u0117"
    ],
    "wof:name":"Pagaluone",
    "wof:placetype":"locality"
},
  "geometry": {"coordinates":[25.4798,55.15843],"type":"Point"}
}