{
  "type": "Feature",
  "properties": {
    "gn:admin1_code":"61.0",
    "gn:admin2_code":"71.0",
    "gn:asciiname":"Vakarai",
    "gn:country_code":"LT",
    "gn:dem":86,
    "gn:feature_class":"P",
    "gn:feature_code":"PPL",
    "gn:name":"Vakarai",
    "gn:population":0,
    "gn:timezone":"Europe/Vilnius",
    "iso:country":"LT",
    "name:lit_x_preferred":[
        "Vakarai"
    ],
    "name:und_x_variant":[
        "Vertimai"
    ],
    "wof:name":"Vakarai",
    "wof:placetype":"locality"
},
  "geometry": {"coordinates":[23.81718,55.60775],"type":"Point"}
}