{
  "type": "Feature",
  "properties": {
    "gn:admin1_code":"57.0",
    "gn:admin2_code":"72.0",
    "gn:asciiname":"Zbaras",
    "gn:country_code":"LT",
    "gn:dem":138,
    "gn:feature_class":"P",
    "gn:feature_code":"PPL",
    "gn:name":"Zbaras",
    "gn:population":0,
    "gn:timezone":"Europe/Vilnius",
    "iso:country":"LT",
    "name:und_x_variant":[
        "Sboray",
        "Sbory",
        "Zbaras"
    ],
    "wof:name":"Zbaras",
    "wof:placetype":"locality"
},
  "geometry": {"coordinates":[23.23171,55.53479],"type":"Point"}
}