{
  "type": "Feature",
  "properties": {
    "gn:admin1_code":"57",
    "gn:admin2_code":"19.0",
    "gn:asciiname":"Kaciuniske",
    "gn:country_code":"LT",
    "gn:dem":23,
    "gn:feature_class":"P",
    "gn:feature_code":"PPL",
    "gn:name":"Ka\u010di\u016bni\u0161k\u0117",
    "gn:population":0,
    "gn:timezone":"Europe/Vilnius",
    "iso:country":"LT",
    "name:lit_x_preferred":[
        "Ka\u010di\u016bni\u0161k\u0117"
    ],
    "wof:name":"Kaciuniske",
    "wof:placetype":"locality"
},
  "geometry": {"coordinates":[23.79405,55.01316],"type":"Point"}
}