{
  "type": "Feature",
  "properties": {
    "gn:admin1_code":"62",
    "gn:admin2_code":"77.0",
    "gn:asciiname":"Lybiskiai",
    "gn:country_code":"LT",
    "gn:dem":25,
    "gn:feature_class":"P",
    "gn:feature_code":"PPL",
    "gn:name":"Lybi\u0161kiai",
    "gn:population":0,
    "gn:timezone":"Europe/Vilnius",
    "iso:country":"LT",
    "name:lit_x_preferred":[
        "Lybi\u0161kiai"
    ],
    "wof:name":"Lybiskiai",
    "wof:placetype":"locality"
},
  "geometry": {"coordinates":[22.39189,55.22776],"type":"Point"}
}