{
  "type": "Feature",
  "properties": {
    "gn:admin1_code":"0.0",
    "gn:asciiname":"Kekaliske",
    "gn:cc2":"LT",
    "gn:country_code":"LT",
    "gn:dem":21,
    "gn:feature_class":"P",
    "gn:feature_code":"PPL",
    "gn:name":"Kekali\u0161k\u0117",
    "gn:population":0,
    "gn:timezone":"Europe/Vilnius",
    "iso:country":"LT",
    "name:und_x_variant":[
        "Kekalishki",
        "Kekali\u0161k\u0117"
    ],
    "wof:name":"Kekaliske",
    "wof:placetype":"locality"
},
  "geometry": {"coordinates":[21.56667,55.45],"type":"Point"}
}