{
  "type": "Feature",
  "properties": {
    "gn:admin1_code":"59",
    "gn:admin2_code":"18.0",
    "gn:asciiname":"Obsruteliai",
    "gn:country_code":"LT",
    "gn:dem":73,
    "gn:feature_class":"P",
    "gn:feature_code":"PPL",
    "gn:name":"Ob\u0161r\u016bt\u0117liai",
    "gn:population":0,
    "gn:timezone":"Europe/Vilnius",
    "iso:country":"LT",
    "name:lit_x_preferred":[
        "Ob\u0161r\u016bt\u0117liai"
    ],
    "wof:name":"Obsruteliai",
    "wof:placetype":"locality"
},
  "geometry": {"coordinates":[23.30466,54.59271],"type":"Point"}
}