{
  "type": "Feature",
  "properties": {
    "gn:admin1_code":"58.0",
    "gn:admin2_code":"21.0",
    "gn:asciiname":"Vyskupiskiai",
    "gn:country_code":"LT",
    "gn:dem":36,
    "gn:feature_class":"P",
    "gn:feature_code":"PPL",
    "gn:name":"Vyskupi\u0161kiai",
    "gn:population":0,
    "gn:timezone":"Europe/Vilnius",
    "iso:country":"LT",
    "name:und_x_variant":[
        "Viskupishkey",
        "Vyskupi\u0161kiai"
    ],
    "wof:name":"Vyskupiskiai",
    "wof:placetype":"locality"
},
  "geometry": {"coordinates":[21.55982,55.59157],"type":"Point"}
}