{
  "type": "Feature",
  "properties": {
    "gn:admin1_code":"61",
    "gn:admin2_code":"47.0",
    "gn:asciiname":"Nemeiksiai",
    "gn:country_code":"LT",
    "gn:dem":39,
    "gn:feature_class":"P",
    "gn:feature_code":"PPL",
    "gn:name":"Nemeik\u0161iai",
    "gn:population":0,
    "gn:timezone":"Europe/Vilnius",
    "iso:country":"LT",
    "name:lit_x_preferred":[
        "Nemeik\u0161iai"
    ],
    "wof:name":"Nemeiksiai",
    "wof:placetype":"locality"
},
  "geometry": {"coordinates":[23.74521,56.3187],"type":"Point"}
}