{
  "type": "Feature",
  "properties": {
    "gn:admin1_code":"64",
    "gn:admin2_code":"62.0",
    "gn:asciiname":"Rudesele",
    "gn:country_code":"LT",
    "gn:dem":161,
    "gn:feature_class":"P",
    "gn:feature_code":"PPL",
    "gn:name":"Rudes\u0117l\u0117",
    "gn:population":0,
    "gn:timezone":"Europe/Vilnius",
    "iso:country":"LT",
    "name:lit_x_preferred":[
        "Rudes\u0117l\u0117"
    ],
    "wof:name":"Rudesele",
    "wof:placetype":"locality"
},
  "geometry": {"coordinates":[25.49915,55.2035],"type":"Point"}
}