{
  "type": "Feature",
  "properties": {
    "gn:admin1_code":"62.0",
    "gn:admin2_code":"77.0",
    "gn:asciiname":"Skirzeme",
    "gn:country_code":"LT",
    "gn:dem":61,
    "gn:feature_class":"P",
    "gn:feature_code":"PPL",
    "gn:name":"Skir\u017eem\u0117",
    "gn:population":0,
    "gn:timezone":"Europe/Vilnius",
    "iso:country":"LT",
    "name:lit_x_preferred":[
        "Skirzeme"
    ],
    "name:und_x_variant":[
        "Skir\u017eemio",
        "Skirzhyame",
        "Skir\u017eem\u0117s",
        "Skirozemy",
        "Skir\u017eem\u0117"
    ],
    "wof:name":"Skirzeme",
    "wof:placetype":"locality"
},
  "geometry": {"coordinates":[21.91446,55.29456],"type":"Point"}
}