{
  "type": "Feature",
  "properties": {
    "gn:admin1_code":"57",
    "gn:admin2_code":"46.0",
    "gn:asciiname":"Milasiskiai",
    "gn:country_code":"LT",
    "gn:dem":62,
    "gn:feature_class":"P",
    "gn:feature_code":"PPL",
    "gn:name":"Mila\u0161i\u0161kiai",
    "gn:population":0,
    "gn:timezone":"Europe/Vilnius",
    "iso:country":"LT",
    "name:lit_x_preferred":[
        "Mila\u0161i\u0161kiai"
    ],
    "wof:name":"Milasiskiai",
    "wof:placetype":"locality"
},
  "geometry": {"coordinates":[24.02536,55.10681999999999],"type":"Point"}
}