{
  "type": "Feature",
  "properties": {
    "gn:admin1_code":"65",
    "gn:admin2_code":"85.0",
    "gn:asciiname":"Siurksciai",
    "gn:country_code":"LT",
    "gn:dem":174,
    "gn:feature_class":"P",
    "gn:feature_code":"PPL",
    "gn:name":"\u0160i\u016brk\u0161\u010diai",
    "gn:population":0,
    "gn:timezone":"Europe/Vilnius",
    "iso:country":"LT",
    "name:lit_x_preferred":[
        "\u0160i\u016brk\u0161\u010diai"
    ],
    "wof:name":"Siurksciai",
    "wof:placetype":"locality"
},
  "geometry": {"coordinates":[25.70895,54.20901],"type":"Point"}
}