{
  "type": "Feature",
  "properties": {
    "gn:admin1_code":"61",
    "gn:admin2_code":"29.0",
    "gn:asciiname":"Trauleiniai",
    "gn:country_code":"LT",
    "gn:dem":121,
    "gn:feature_class":"P",
    "gn:feature_code":"PPL",
    "gn:name":"Trauleiniai",
    "gn:population":0,
    "gn:timezone":"Europe/Vilnius",
    "iso:country":"LT",
    "name:lit_x_preferred":[
        "Trauleiniai"
    ],
    "wof:name":"Trauleiniai",
    "wof:placetype":"locality"
},
  "geometry": {"coordinates":[22.97463,55.85865],"type":"Point"}
}