{
  "type": "Feature",
  "properties": {
    "gn:admin1_code":"57.0",
    "gn:admin2_code":"69.0",
    "gn:asciiname":"Jakniskes",
    "gn:country_code":"LT",
    "gn:dem":94,
    "gn:feature_class":"P",
    "gn:feature_code":"PPL",
    "gn:name":"Jakni\u0161k\u0117s",
    "gn:population":0,
    "gn:timezone":"Europe/Vilnius",
    "iso:country":"LT",
    "name:lit_x_preferred":[
        "Jakni\u0161k\u0117s"
    ],
    "wof:name":"Jakniskes",
    "wof:placetype":"locality"
},
  "geometry": {"coordinates":[24.18683,54.67482],"type":"Point"}
}