{
  "type": "Feature",
  "properties": {
    "gn:admin1_code":"62",
    "gn:admin2_code":"77.0",
    "gn:asciiname":"Juskiske",
    "gn:country_code":"LT",
    "gn:dem":125,
    "gn:feature_class":"P",
    "gn:feature_code":"PPL",
    "gn:name":"Ju\u0161ki\u0161k\u0117",
    "gn:population":0,
    "gn:timezone":"Europe/Vilnius",
    "iso:country":"LT",
    "name:lit_x_preferred":[
        "Ju\u0161ki\u0161k\u0117"
    ],
    "wof:name":"Juskiske",
    "wof:placetype":"locality"
},
  "geometry": {"coordinates":[22.48875,55.42218],"type":"Point"}
}