{
  "type": "Feature",
  "properties": {
    "gn:admin1_code":"57.0",
    "gn:admin2_code":"49.0",
    "gn:asciiname":"Lomeniai",
    "gn:country_code":"LT",
    "gn:dem":75,
    "gn:feature_class":"P",
    "gn:feature_code":"PPL",
    "gn:name":"Lomeniai",
    "gn:population":0,
    "gn:timezone":"Europe/Vilnius",
    "iso:country":"LT",
    "name:eng_x_preferred":[
        "Lomeniai"
    ],
    "name:rus_x_preferred":[
        "\u041b\u043e\u043c\u0435\u043d\u044f\u0439"
    ],
    "name:und_x_variant":[
        "Lovmyantsy",
        "Lomeniai"
    ],
    "wof:name":"Lomeniai",
    "wof:placetype":"locality"
},
  "geometry": {"coordinates":[24.43621,54.96762],"type":"Point"}
}