{
  "type": "Feature",
  "properties": {
    "gn:admin1_code":"62.0",
    "gn:admin2_code":"87.0",
    "gn:asciiname":"Keberksciai",
    "gn:country_code":"LT",
    "gn:dem":100,
    "gn:feature_class":"P",
    "gn:feature_code":"PPL",
    "gn:name":"Keberk\u0161\u010diai",
    "gn:population":0,
    "gn:timezone":"Europe/Vilnius",
    "iso:country":"LT",
    "name:und_x_variant":[
        "Keberkshty",
        "Keberk\u0161\u010diai"
    ],
    "wof:name":"Keberksciai",
    "wof:placetype":"locality"
},
  "geometry": {"coordinates":[22.07113,55.45533],"type":"Point"}
}