{
  "type": "Feature",
  "properties": {
    "gn:admin1_code":"64",
    "gn:admin2_code":"82.0",
    "gn:asciiname":"Liaumuskos",
    "gn:country_code":"LT",
    "gn:dem":127,
    "gn:feature_class":"P",
    "gn:feature_code":"PPL",
    "gn:name":"Liaumu\u0161kos",
    "gn:population":0,
    "gn:timezone":"Europe/Vilnius",
    "iso:country":"LT",
    "name:lit_x_preferred":[
        "Liaumu\u0161kos"
    ],
    "wof:name":"Liaumuskos",
    "wof:placetype":"locality"
},
  "geometry": {"coordinates":[25.57622000000001,55.46495],"type":"Point"}
}