{
  "type": "Feature",
  "properties": {
    "gn:admin1_code":"64",
    "gn:admin2_code":"34.0",
    "gn:asciiname":"Vosgeliai",
    "gn:country_code":"LT",
    "gn:dem":103,
    "gn:feature_class":"P",
    "gn:feature_code":"PPL",
    "gn:name":"Vosg\u0117liai",
    "gn:population":0,
    "gn:timezone":"Europe/Vilnius",
    "iso:country":"LT",
    "name:lit_x_preferred":[
        "Vosg\u0117liai"
    ],
    "wof:name":"Vosgeliai",
    "wof:placetype":"locality"
},
  "geometry": {"coordinates":[25.18564,55.56996],"type":"Point"}
}