{
  "type": "Feature",
  "properties": {
    "gn:admin1_code":"0.0",
    "gn:asciiname":"Varzos II",
    "gn:cc2":"LT",
    "gn:country_code":"LT",
    "gn:dem":89,
    "gn:feature_class":"P",
    "gn:feature_code":"PPL",
    "gn:name":"Var\u017eos II",
    "gn:population":0,
    "gn:timezone":"Europe/Vilnius",
    "iso:country":"LT",
    "name:und_x_variant":[
        "Novoro\u017edestvenka",
        "Rozhdestvenskaya",
        "Var\u017eos Antrosios",
        "Var\u017eos II"
    ],
    "wof:name":"Varzos II",
    "wof:placetype":"locality"
},
  "geometry": {"coordinates":[24.68333,55.35],"type":"Point"}
}