{
  "type": "Feature",
  "properties": {
    "gn:admin1_code":"64.0",
    "gn:admin2_code":"34.0",
    "gn:asciiname":"Mazeliai",
    "gn:country_code":"LT",
    "gn:dem":88,
    "gn:feature_class":"P",
    "gn:feature_code":"PPL",
    "gn:name":"Ma\u017eeliai",
    "gn:population":0,
    "gn:timezone":"Europe/Vilnius",
    "iso:country":"LT",
    "name:und_x_variant":[
        "Ma\u017eeli\u0173",
        "Mezheli",
        "Mazhelyay",
        "Ma\u017eeliai"
    ],
    "wof:name":"Mazeliai",
    "wof:placetype":"locality"
},
  "geometry": {"coordinates":[24.91319,55.46176],"type":"Point"}
}