{
  "type": "Feature",
  "properties": {
    "gn:admin1_code":"64",
    "gn:admin2_code":"43.0",
    "gn:asciiname":"Rudines",
    "gn:country_code":"LT",
    "gn:dem":150,
    "gn:feature_class":"P",
    "gn:feature_code":"PPL",
    "gn:name":"Rudin\u0117s",
    "gn:population":0,
    "gn:timezone":"Europe/Vilnius",
    "iso:country":"LT",
    "name:lit_x_preferred":[
        "Rudin\u0117s"
    ],
    "wof:name":"Rudines",
    "wof:placetype":"locality"
},
  "geometry": {"coordinates":[26.09141,55.82805],"type":"Point"}
}