{
  "type": "Feature",
  "properties": {
    "gn:admin1_code":"65",
    "gn:admin2_code":"89.0",
    "gn:asciiname":"Oziskes",
    "gn:country_code":"LT",
    "gn:dem":133,
    "gn:feature_class":"P",
    "gn:feature_code":"PPL",
    "gn:name":"O\u017ei\u0161k\u0117s",
    "gn:population":0,
    "gn:timezone":"Europe/Vilnius",
    "iso:country":"LT",
    "name:lit_x_preferred":[
        "O\u017ei\u0161k\u0117s"
    ],
    "wof:name":"Oziskes",
    "wof:placetype":"locality"
},
  "geometry": {"coordinates":[25.12246,54.979],"type":"Point"}
}