{
  "type": "Feature",
  "properties": {
    "gn:admin1_code":"60.0",
    "gn:admin2_code":"36.0",
    "gn:asciiname":"Cypenai",
    "gn:country_code":"LT",
    "gn:dem":68,
    "gn:feature_class":"P",
    "gn:feature_code":"PPL",
    "gn:name":"\u010cyp\u0117nai",
    "gn:population":0,
    "gn:timezone":"Europe/Vilnius",
    "iso:country":"LT",
    "name:und_x_variant":[
        "Chipenay",
        "\u010cyp\u0117n\u0173",
        "\u010cyp\u0117nai"
    ],
    "wof:name":"Cypenai",
    "wof:placetype":"locality"
},
  "geometry": {"coordinates":[24.85582,55.98014000000001],"type":"Point"}
}