{
  "type": "Feature",
  "properties": {
    "gn:admin1_code":"58",
    "gn:admin2_code":"88.0",
    "gn:asciiname":"Rugaliai",
    "gn:country_code":"LT",
    "gn:dem":1,
    "gn:feature_class":"P",
    "gn:feature_code":"PPL",
    "gn:name":"R\u016bgaliai",
    "gn:population":0,
    "gn:timezone":"Europe/Vilnius",
    "iso:country":"LT",
    "name:lit_x_preferred":[
        "R\u016bgaliai"
    ],
    "wof:name":"Rugaliai",
    "wof:placetype":"locality"
},
  "geometry": {"coordinates":[21.32727,55.39309],"type":"Point"}
}