{
  "type": "Feature",
  "properties": {
    "gn:admin1_code":"64",
    "gn:admin2_code":"62.0",
    "gn:asciiname":"Vitiskes",
    "gn:country_code":"LT",
    "gn:dem":172,
    "gn:feature_class":"P",
    "gn:feature_code":"PPL",
    "gn:name":"Viti\u0161k\u0117s",
    "gn:population":0,
    "gn:timezone":"Europe/Vilnius",
    "iso:country":"LT",
    "name:lit_x_preferred":[
        "Viti\u0161k\u0117s"
    ],
    "wof:name":"Vitiskes",
    "wof:placetype":"locality"
},
  "geometry": {"coordinates":[25.49473,55.18574],"type":"Point"}
}