{
  "type": "Feature",
  "properties": {
    "gn:admin1_code":"57",
    "gn:admin2_code":"72.0",
    "gn:asciiname":"Plausiniai",
    "gn:country_code":"LT",
    "gn:dem":104,
    "gn:feature_class":"P",
    "gn:feature_code":"PPL",
    "gn:name":"Plau\u0161iniai",
    "gn:population":0,
    "gn:timezone":"Europe/Vilnius",
    "iso:country":"LT",
    "name:lit_x_preferred":[
        "Plau\u0161iniai"
    ],
    "wof:name":"Plausiniai",
    "wof:placetype":"locality"
},
  "geometry": {"coordinates":[23.2474,55.27999000000001],"type":"Point"}
}