{
  "type": "Feature",
  "properties": {
    "gn:admin1_code":"56.0",
    "gn:admin2_code":"59.0",
    "gn:asciiname":"Roliai",
    "gn:country_code":"LT",
    "gn:dem":130,
    "gn:feature_class":"P",
    "gn:feature_code":"PPL",
    "gn:name":"Roliai",
    "gn:population":0,
    "gn:timezone":"Europe/Vilnius",
    "iso:country":"LT",
    "name:und_x_variant":[
        "Ralle",
        "Roliai"
    ],
    "wof:name":"Roliai",
    "wof:placetype":"locality"
},
  "geometry": {"coordinates":[23.53551,54.31965],"type":"Point"}
}