{
  "type": "Feature",
  "properties": {
    "gn:admin1_code":"56.0",
    "gn:admin2_code":"59.0",
    "gn:asciiname":"Makauciske",
    "gn:country_code":"LT",
    "gn:dem":115,
    "gn:feature_class":"P",
    "gn:feature_code":"PPL",
    "gn:name":"Makau\u010di\u0161k\u0117",
    "gn:population":0,
    "gn:timezone":"Europe/Vilnius",
    "iso:country":"LT",
    "name:und_x_variant":[
        "Makau\u010di\u0161k\u0117",
        "Makau\u010di\u0161k\u0117s",
        "Stumbrin\u0117"
    ],
    "wof:name":"Makauciske",
    "wof:placetype":"locality"
},
  "geometry": {"coordinates":[23.48204,54.36866],"type":"Point"}
}