{
  "type": "Feature",
  "properties": {
    "gn:admin1_code":"64",
    "gn:admin2_code":"82.0",
    "gn:asciiname":"Vyziai",
    "gn:country_code":"LT",
    "gn:dem":169,
    "gn:feature_class":"P",
    "gn:feature_code":"PPL",
    "gn:name":"Vy\u017eiai",
    "gn:population":0,
    "gn:timezone":"Europe/Vilnius",
    "iso:country":"LT",
    "name:lit_x_preferred":[
        "Vy\u017eiai"
    ],
    "wof:name":"Vyziai",
    "wof:placetype":"locality"
},
  "geometry": {"coordinates":[25.99486,55.42175],"type":"Point"}
}