{
  "type": "Feature",
  "properties": {
    "gn:admin1_code":"64",
    "gn:admin2_code":"34.0",
    "gn:asciiname":"Krasteliai",
    "gn:country_code":"LT",
    "gn:dem":135,
    "gn:feature_class":"P",
    "gn:feature_code":"PPL",
    "gn:name":"Kra\u0161teliai",
    "gn:population":0,
    "gn:timezone":"Europe/Vilnius",
    "iso:country":"LT",
    "name:lit_x_preferred":[
        "Kra\u0161teliai"
    ],
    "wof:name":"Krasteliai",
    "wof:placetype":"locality"
},
  "geometry": {"coordinates":[25.42677,55.7054],"type":"Point"}
}