{
  "type": "Feature",
  "properties": {
    "gn:admin1_code":"64",
    "gn:admin2_code":"82.0",
    "gn:asciiname":"Plausai",
    "gn:country_code":"LT",
    "gn:dem":102,
    "gn:feature_class":"P",
    "gn:feature_code":"PPL",
    "gn:name":"Plau\u0161ai",
    "gn:population":0,
    "gn:timezone":"Europe/Vilnius",
    "iso:country":"LT",
    "name:lit_x_preferred":[
        "Plau\u0161ai"
    ],
    "wof:name":"Plausai",
    "wof:placetype":"locality"
},
  "geometry": {"coordinates":[25.4993,55.57315],"type":"Point"}
}