{
  "type": "Feature",
  "properties": {
    "gn:admin1_code":"57.0",
    "gn:admin2_code":"46.0",
    "gn:asciiname":"Stasenai",
    "gn:country_code":"LT",
    "gn:dem":37,
    "gn:feature_class":"P",
    "gn:feature_code":"PPL",
    "gn:name":"Sta\u0161\u0117nai",
    "gn:population":0,
    "gn:timezone":"Europe/Vilnius",
    "iso:country":"LT",
    "name:und_x_variant":[
        "Stashenyay",
        "Sta\u0161\u0117nai"
    ],
    "wof:name":"Stasenai",
    "wof:placetype":"locality"
},
  "geometry": {"coordinates":[24.20695,55.05587],"type":"Point"}
}