{
  "type": "Feature",
  "properties": {
    "gn:admin1_code":"64",
    "gn:admin2_code":"45.0",
    "gn:asciiname":"Dikiske",
    "gn:country_code":"LT",
    "gn:dem":156,
    "gn:feature_class":"P",
    "gn:feature_code":"PPL",
    "gn:name":"Diki\u0161k\u0117",
    "gn:population":0,
    "gn:timezone":"Europe/Vilnius",
    "iso:country":"LT",
    "name:lit_x_preferred":[
        "Diki\u0161k\u0117"
    ],
    "wof:name":"Dikiske",
    "wof:placetype":"locality"
},
  "geometry": {"coordinates":[26.45832,55.4229],"type":"Point"}
}