{
  "type": "Feature",
  "properties": {
    "gn:admin1_code":"61",
    "gn:admin2_code":"29.0",
    "gn:asciiname":"Jokubaiciai",
    "gn:country_code":"LT",
    "gn:dem":100,
    "gn:feature_class":"P",
    "gn:feature_code":"PPL",
    "gn:name":"Jok\u016bbai\u010diai",
    "gn:population":0,
    "gn:timezone":"Europe/Vilnius",
    "iso:country":"LT",
    "name:lit_x_preferred":[
        "Jok\u016bbai\u010diai"
    ],
    "wof:name":"Jokubaiciai",
    "wof:placetype":"locality"
},
  "geometry": {"coordinates":[23.2186,56.11646999999999],"type":"Point"}
}