{
  "type": "Feature",
  "properties": {
    "gn:admin1_code":"61",
    "gn:admin2_code":"29.0",
    "gn:asciiname":"Dapkunai",
    "gn:country_code":"LT",
    "gn:dem":88,
    "gn:feature_class":"P",
    "gn:feature_code":"PPL",
    "gn:name":"Dapk\u016bnai",
    "gn:population":0,
    "gn:timezone":"Europe/Vilnius",
    "iso:country":"LT",
    "name:lit_x_preferred":[
        "Dapk\u016bnai"
    ],
    "wof:name":"Dapkunai",
    "wof:placetype":"locality"
},
  "geometry": {"coordinates":[23.46654,56.05898000000001],"type":"Point"}
}