{
  "type": "Feature",
  "properties": {
    "gn:admin1_code":"58",
    "gn:admin2_code":"88.0",
    "gn:asciiname":"Bliudsukiai",
    "gn:country_code":"LT",
    "gn:dem":44,
    "gn:feature_class":"P",
    "gn:feature_code":"PPL",
    "gn:name":"Bli\u016bdsukiai",
    "gn:population":0,
    "gn:timezone":"Europe/Vilnius",
    "iso:country":"LT",
    "name:lit_x_preferred":[
        "Bli\u016bdsukiai"
    ],
    "wof:name":"Bliudsukiai",
    "wof:placetype":"locality"
},
  "geometry": {"coordinates":[21.71213,55.46619000000001],"type":"Point"}
}