{
  "type": "Feature",
  "properties": {
    "gn:admin1_code":"63",
    "gn:admin2_code":"78.0",
    "gn:asciiname":"Jausyciai",
    "gn:country_code":"LT",
    "gn:dem":172,
    "gn:feature_class":"P",
    "gn:feature_code":"PPL",
    "gn:name":"Jau\u0161y\u010diai",
    "gn:population":0,
    "gn:timezone":"Europe/Vilnius",
    "iso:country":"LT",
    "name:lit_x_preferred":[
        "Jau\u0161y\u010diai"
    ],
    "wof:name":"Jausyciai",
    "wof:placetype":"locality"
},
  "geometry": {"coordinates":[22.2422,55.75538],"type":"Point"}
}