{
  "type": "Feature",
  "properties": {
    "gn:admin1_code":"64",
    "gn:admin2_code":"45.0",
    "gn:asciiname":"Kukutenai",
    "gn:country_code":"LT",
    "gn:dem":153,
    "gn:feature_class":"P",
    "gn:feature_code":"PPL",
    "gn:name":"Kukut\u0117nai",
    "gn:population":0,
    "gn:timezone":"Europe/Vilnius",
    "iso:country":"LT",
    "name:lit_x_preferred":[
        "Kukut\u0117nai"
    ],
    "wof:name":"Kukutenai",
    "wof:placetype":"locality"
},
  "geometry": {"coordinates":[26.5335,55.5614],"type":"Point"}
}