{
  "type": "Feature",
  "properties": {
    "gn:admin1_code":"64",
    "gn:admin2_code":"82.0",
    "gn:asciiname":"Kauliniskis",
    "gn:country_code":"LT",
    "gn:dem":104,
    "gn:feature_class":"P",
    "gn:feature_code":"PPL",
    "gn:name":"Kaulini\u0161kis",
    "gn:population":0,
    "gn:timezone":"Europe/Vilnius",
    "iso:country":"LT",
    "name:lit_x_preferred":[
        "Kaulini\u0161kis"
    ],
    "wof:name":"Kauliniskis",
    "wof:placetype":"locality"
},
  "geometry": {"coordinates":[25.5637,55.5173],"type":"Point"}
}