{
  "type": "Feature",
  "properties": {
    "gn:admin1_code":"60",
    "gn:admin2_code":"73.0",
    "gn:asciiname":"Parokiske",
    "gn:country_code":"LT",
    "gn:dem":128,
    "gn:feature_class":"P",
    "gn:feature_code":"PPL",
    "gn:name":"Paroki\u0161k\u0117",
    "gn:population":0,
    "gn:timezone":"Europe/Vilnius",
    "iso:country":"LT",
    "name:lit_x_preferred":[
        "Paroki\u0161k\u0117"
    ],
    "wof:name":"Parokiske",
    "wof:placetype":"locality"
},
  "geometry": {"coordinates":[25.5791,55.94523],"type":"Point"}
}