{
  "type": "Feature",
  "properties": {
    "gn:admin1_code":"59",
    "gn:admin2_code":"39.0",
    "gn:asciiname":"Ciziskiai",
    "gn:country_code":"LT",
    "gn:dem":174,
    "gn:feature_class":"P",
    "gn:feature_code":"PPL",
    "gn:name":"\u010ci\u017ei\u0161kiai",
    "gn:population":0,
    "gn:timezone":"Europe/Kaliningrad",
    "iso:country":"LT",
    "name:lit_x_preferred":[
        "\u010ci\u017ei\u0161kiai"
    ],
    "wof:name":"Ciziskiai",
    "wof:placetype":"locality"
},
  "geometry": {"coordinates":[22.7607,54.40983000000001],"type":"Point"}
}