{
  "type": "Feature",
  "properties": {
    "gn:admin1_code":"61",
    "gn:admin2_code":"32.0",
    "gn:asciiname":"Saltiskiai",
    "gn:country_code":"LT",
    "gn:dem":82,
    "gn:feature_class":"P",
    "gn:feature_code":"PPL",
    "gn:name":"\u0160alti\u0161kiai",
    "gn:population":0,
    "gn:timezone":"Europe/Vilnius",
    "iso:country":"LT",
    "name:lit_x_preferred":[
        "\u0160alti\u0161kiai"
    ],
    "wof:name":"Saltiskiai",
    "wof:placetype":"locality"
},
  "geometry": {"coordinates":[22.81966,56.18129],"type":"Point"}
}