{
  "type": "Feature",
  "properties": {
    "gn:admin1_code":"59",
    "gn:admin2_code":"39.0",
    "gn:asciiname":"Visciakaimis",
    "gn:country_code":"LT",
    "gn:dem":55,
    "gn:feature_class":"P",
    "gn:feature_code":"PPL",
    "gn:name":"Vi\u0161\u010diakaimis",
    "gn:population":0,
    "gn:timezone":"Europe/Vilnius",
    "iso:country":"LT",
    "name:lit_x_preferred":[
        "Vi\u0161\u010diakaimis"
    ],
    "wof:name":"Visciakaimis",
    "wof:placetype":"locality"
},
  "geometry": {"coordinates":[22.99836,54.65807],"type":"Point"}
}