{
  "type": "Feature",
  "properties": {
    "gn:admin1_code":"60.0",
    "gn:admin2_code":"57.0",
    "gn:asciiname":"Kinderiai",
    "gn:country_code":"LT",
    "gn:dem":120,
    "gn:feature_class":"P",
    "gn:feature_code":"PPL",
    "gn:name":"Kinderiai",
    "gn:population":0,
    "gn:timezone":"Europe/Vilnius",
    "iso:country":"LT",
    "name:und_x_variant":[
        "Kinderi\u0173",
        "Kinderyay",
        "Kinderiai"
    ],
    "wof:name":"Kinderiai",
    "wof:placetype":"locality"
},
  "geometry": {"coordinates":[25.09801,55.77595],"type":"Point"}
}