{
  "type": "Feature",
  "properties": {
    "gn:admin1_code":"57.0",
    "gn:admin2_code":"53.0",
    "gn:asciiname":"Dauksiai",
    "gn:country_code":"LT",
    "gn:dem":51,
    "gn:feature_class":"P",
    "gn:feature_code":"PPL",
    "gn:name":"Dauk\u0161iai",
    "gn:population":0,
    "gn:timezone":"Europe/Vilnius",
    "iso:country":"LT",
    "name:und_x_variant":[
        "Dauk\u0161iai"
    ],
    "wof:name":"Dauksiai",
    "wof:placetype":"locality"
},
  "geometry": {"coordinates":[23.91578,55.33599],"type":"Point"}
}