{
  "type": "Feature",
  "properties": {
    "gn:admin1_code":"56",
    "gn:admin2_code":"11.0",
    "gn:asciiname":"Bernotiskes",
    "gn:country_code":"LT",
    "gn:dem":79,
    "gn:feature_class":"P",
    "gn:feature_code":"PPL",
    "gn:name":"Bernoti\u0161k\u0117s",
    "gn:population":0,
    "gn:timezone":"Europe/Vilnius",
    "iso:country":"LT",
    "name:lit_x_preferred":[
        "Bernoti\u0161k\u0117s"
    ],
    "wof:name":"Bernotiskes",
    "wof:placetype":"locality"
},
  "geometry": {"coordinates":[23.845,54.42106999999999],"type":"Point"}
}