{
  "type": "Feature",
  "properties": {
    "gn:admin1_code":"65.0",
    "gn:admin2_code":"13.0",
    "gn:asciiname":"Juodsiliai",
    "gn:country_code":"LT",
    "gn:dem":159,
    "gn:feature_class":"P",
    "gn:feature_code":"PPL",
    "gn:name":"Juod\u0161iliai",
    "gn:population":0,
    "gn:timezone":"Europe/Vilnius",
    "iso:country":"LT",
    "name:eng_x_preferred":[
        "Juod\u0161iliai"
    ],
    "name:rus_x_preferred":[
        "\u042e\u043e\u0434\u0448\u0438\u043b\u044f\u0439"
    ],
    "name:und_x_variant":[
        "Juoda\u0161iliai",
        "Yuodshilyay",
        "Chernyy Bor"
    ],
    "wof:name":"Juodsiliai",
    "wof:placetype":"locality"
},
  "geometry": {"coordinates":[25.26138,54.58316],"type":"Point"}
}