{
  "type": "Feature",
  "properties": {
    "gn:admin1_code":"59",
    "gn:admin2_code":"18.0",
    "gn:asciiname":"Marciukinis",
    "gn:country_code":"LT",
    "gn:dem":101,
    "gn:feature_class":"P",
    "gn:feature_code":"PPL",
    "gn:name":"Mar\u010diukinis",
    "gn:population":0,
    "gn:timezone":"Europe/Vilnius",
    "iso:country":"LT",
    "name:lit_x_preferred":[
        "Mar\u010diukinis"
    ],
    "wof:name":"Marciukinis",
    "wof:placetype":"locality"
},
  "geometry": {"coordinates":[23.41509,54.51852],"type":"Point"}
}