{
  "type": "Feature",
  "properties": {
    "gn:admin1_code":"62.0",
    "gn:admin2_code":"77.0",
    "gn:asciiname":"Trumpiskiai",
    "gn:country_code":"LT",
    "gn:dem":54,
    "gn:feature_class":"P",
    "gn:feature_code":"PPL",
    "gn:name":"Trumpi\u0161kiai",
    "gn:population":0,
    "gn:timezone":"Europe/Vilnius",
    "iso:country":"LT",
    "name:und_x_variant":[
        "Trumpishkyay",
        "Trumpi\u0161kiai"
    ],
    "wof:name":"Trumpiskiai",
    "wof:placetype":"locality"
},
  "geometry": {"coordinates":[22.03567,55.33188000000001],"type":"Point"}
}