{
  "type": "Feature",
  "properties": {
    "gn:admin1_code":"60",
    "gn:admin2_code":"73.0",
    "gn:asciiname":"Puriuskiai",
    "gn:country_code":"LT",
    "gn:dem":114,
    "gn:feature_class":"P",
    "gn:feature_code":"PPL",
    "gn:name":"Puriu\u0161kiai",
    "gn:population":0,
    "gn:timezone":"Europe/Vilnius",
    "iso:country":"LT",
    "name:lit_x_preferred":[
        "Puriu\u0161kiai"
    ],
    "wof:name":"Puriuskiai",
    "wof:placetype":"locality"
},
  "geometry": {"coordinates":[25.65399,55.84501],"type":"Point"}
}