{
  "type": "Feature",
  "properties": {
    "gn:admin1_code":"57.0",
    "gn:asciiname":"Pagiriai",
    "gn:cc2":"LT",
    "gn:country_code":"LT",
    "gn:dem":77,
    "gn:feature_class":"P",
    "gn:feature_code":"PPL",
    "gn:name":"Pagiriai",
    "gn:population":0,
    "gn:timezone":"Europe/Vilnius",
    "iso:country":"LT",
    "name:eng_x_preferred":[
        "Pagiriai"
    ],
    "name:est_x_preferred":[
        "Pagiriai"
    ],
    "name:lit_x_preferred":[
        "Pagiriai"
    ],
    "name:nld_x_preferred":[
        "Pagiriai"
    ],
    "name:pol_x_preferred":[
        "Pogiry"
    ],
    "name:rus_x_preferred":[
        "\u041f\u0430\u0433\u0438\u0440\u0438\u0441"
    ],
    "name:und_x_variant":[
        "Pogiry",
        "Pagiris",
        "Pagiri\u0173",
        "Pagiryay",
        "Pagirys",
        "Pagiryai",
        "Pagiriai"
    ],
    "wof:name":"Pagiriai",
    "wof:placetype":"locality"
},
  "geometry": {"coordinates":[24.398,55.362],"type":"Point"}
}