{
  "type": "Feature",
  "properties": {
    "gn:admin1_code":"56.0",
    "gn:admin2_code":"11.0",
    "gn:asciiname":"Giluiciai",
    "gn:country_code":"LT",
    "gn:dem":94,
    "gn:feature_class":"P",
    "gn:feature_code":"PPL",
    "gn:name":"Gilui\u010diai",
    "gn:population":0,
    "gn:timezone":"Europe/Vilnius",
    "iso:country":"LT",
    "name:und_x_variant":[
        "Giluytse",
        "Giluychay",
        "Gilui\u010diai"
    ],
    "wof:name":"Giluiciai",
    "wof:placetype":"locality"
},
  "geometry": {"coordinates":[23.6027,54.38542],"type":"Point"}
}