{
  "type": "Feature",
  "properties": {
    "gn:admin1_code":"60",
    "gn:admin2_code":"73.0",
    "gn:asciiname":"Rimgaudiskis",
    "gn:country_code":"LT",
    "gn:dem":98,
    "gn:feature_class":"P",
    "gn:feature_code":"PPL",
    "gn:name":"Rimgaudi\u0161kis",
    "gn:population":0,
    "gn:timezone":"Europe/Vilnius",
    "iso:country":"LT",
    "name:lit_x_preferred":[
        "Rimgaudi\u0161kis"
    ],
    "wof:name":"Rimgaudiskis",
    "wof:placetype":"locality"
},
  "geometry": {"coordinates":[25.33938,55.99922],"type":"Point"}
}