{
  "type": "Feature",
  "properties": {
    "gn:admin1_code":"64",
    "gn:admin2_code":"34.0",
    "gn:asciiname":"Surdegis",
    "gn:country_code":"LT",
    "gn:dem":169,
    "gn:feature_class":"P",
    "gn:feature_code":"PPL",
    "gn:name":"Surdegis",
    "gn:population":0,
    "gn:timezone":"Europe/Vilnius",
    "iso:country":"LT",
    "name:ceb_x_preferred":[
        "Surdegis"
    ],
    "name:est_x_preferred":[
        "Surdegis"
    ],
    "name:ita_x_preferred":[
        "Surdegis"
    ],
    "name:lit_x_preferred":[
        "Surdegis"
    ],
    "name:nld_x_preferred":[
        "Surdegis"
    ],
    "name:pol_x_preferred":[
        "Surdegi"
    ],
    "name:swe_x_preferred":[
        "Surdegis"
    ],
    "wof:name":"Surdegis",
    "wof:placetype":"locality"
},
  "geometry": {"coordinates":[25.38352,55.53645],"type":"Point"}
}