{
  "type": "Feature",
  "properties": {
    "gn:admin1_code":"58.0",
    "gn:admin2_code":"56.0",
    "gn:asciiname":"Gargzdele",
    "gn:country_code":"LT",
    "gn:dem":65,
    "gn:feature_class":"P",
    "gn:feature_code":"PPL",
    "gn:name":"Garg\u017edel\u0117",
    "gn:population":0,
    "gn:timezone":"Europe/Vilnius",
    "iso:country":"LT",
    "name:und_x_variant":[
        "Garg\u017edel\u0117",
        "Gedgaud\u017eiai",
        "Garg\u017edei\u0117"
    ],
    "wof:name":"Gargzdele",
    "wof:placetype":"locality"
},
  "geometry": {"coordinates":[21.59664,56.05218000000001],"type":"Point"}
}