{
  "type": "Feature",
  "properties": {
    "gn:admin1_code":"64.0",
    "gn:admin2_code":"43.0",
    "gn:asciiname":"Rusteikiai",
    "gn:country_code":"LT",
    "gn:dem":164,
    "gn:feature_class":"P",
    "gn:feature_code":"PPL",
    "gn:name":"R\u016bsteikiai",
    "gn:population":0,
    "gn:timezone":"Europe/Vilnius",
    "iso:country":"LT",
    "name:und_x_variant":[
        "Rusteiki\u0173",
        "Rusteykyay",
        "R\u016bsteikiai"
    ],
    "wof:name":"Rusteikiai",
    "wof:placetype":"locality"
},
  "geometry": {"coordinates":[26.27115,55.64697],"type":"Point"}
}