{
  "type": "Feature",
  "properties": {
    "gn:admin1_code":"61.0",
    "gn:admin2_code":"54.0",
    "gn:asciiname":"Pakarcemis",
    "gn:country_code":"LT",
    "gn:dem":141,
    "gn:feature_class":"P",
    "gn:feature_code":"PPL",
    "gn:name":"Pakar\u010demis",
    "gn:population":0,
    "gn:timezone":"Europe/Vilnius",
    "iso:country":"LT",
    "name:und_x_variant":[
        "Pakarchame",
        "Pakar\u010demis"
    ],
    "wof:name":"Pakarcemis",
    "wof:placetype":"locality"
},
  "geometry": {"coordinates":[22.86727,55.65714000000001],"type":"Point"}
}