{
  "type": "Feature",
  "properties": {
    "gn:admin1_code":"59",
    "gn:admin2_code":"39.0",
    "gn:asciiname":"Zagrenai",
    "gn:country_code":"LT",
    "gn:dem":43,
    "gn:feature_class":"P",
    "gn:feature_code":"PPL",
    "gn:name":"\u017dagr\u0117nai",
    "gn:population":0,
    "gn:timezone":"Europe/Vilnius",
    "iso:country":"LT",
    "name:lit_x_preferred":[
        "\u017dagr\u0117nai"
    ],
    "wof:name":"Zagrenai",
    "wof:placetype":"locality"
},
  "geometry": {"coordinates":[22.75581,54.67059],"type":"Point"}
}