{
  "type": "Feature",
  "properties": {
    "gn:admin1_code":"64",
    "gn:admin2_code":"82.0",
    "gn:asciiname":"Vygeliai",
    "gn:country_code":"LT",
    "gn:dem":134,
    "gn:feature_class":"P",
    "gn:feature_code":"PPL",
    "gn:name":"Vyg\u0117liai",
    "gn:population":0,
    "gn:timezone":"Europe/Vilnius",
    "iso:country":"LT",
    "name:lit_x_preferred":[
        "Vyg\u0117liai"
    ],
    "wof:name":"Vygeliai",
    "wof:placetype":"locality"
},
  "geometry": {"coordinates":[25.55472,55.7263],"type":"Point"}
}