{
  "type": "Feature",
  "properties": {
    "gn:admin1_code":"60",
    "gn:admin2_code":"57.0",
    "gn:asciiname":"Uogsilys",
    "gn:country_code":"LT",
    "gn:dem":102,
    "gn:feature_class":"P",
    "gn:feature_code":"PPL",
    "gn:name":"Uog\u0161ilys",
    "gn:population":0,
    "gn:timezone":"Europe/Vilnius",
    "iso:country":"LT",
    "name:lit_x_preferred":[
        "Uog\u0161ilys"
    ],
    "wof:name":"Uogsilys",
    "wof:placetype":"locality"
},
  "geometry": {"coordinates":[25.13918,55.72763000000001],"type":"Point"}
}