{
  "type": "Feature",
  "properties": {
    "gn:admin1_code":"61.0",
    "gn:admin2_code":"71.0",
    "gn:asciiname":"Birietiskiai",
    "gn:country_code":"LT",
    "gn:dem":130,
    "gn:feature_class":"P",
    "gn:feature_code":"PPL",
    "gn:name":"Birieti\u0161kiai",
    "gn:population":0,
    "gn:timezone":"Europe/Vilnius",
    "iso:country":"LT",
    "name:und_x_variant":[
        "Bershtyshkyay",
        "Birieti\u0161kiai"
    ],
    "wof:name":"Birietiskiai",
    "wof:placetype":"locality"
},
  "geometry": {"coordinates":[23.36775,55.71719],"type":"Point"}
}