{
  "type": "Feature",
  "properties": {
    "gn:admin1_code":"65.0",
    "gn:admin2_code":"89.0",
    "gn:asciiname":"Lesciunai",
    "gn:country_code":"LT",
    "gn:dem":103,
    "gn:feature_class":"P",
    "gn:feature_code":"PPL",
    "gn:name":"Les\u010di\u016bnai",
    "gn:population":0,
    "gn:timezone":"Europe/Vilnius",
    "iso:country":"LT",
    "name:und_x_variant":[
        "Leschyunay",
        "Les\u010di\u016bnai"
    ],
    "wof:name":"Lesciunai",
    "wof:placetype":"locality"
},
  "geometry": {"coordinates":[24.68919,55.01678],"type":"Point"}
}