{
  "type": "Feature",
  "properties": {
    "gn:admin1_code":"59",
    "gn:admin2_code":"84.0",
    "gn:asciiname":"Pliorisiai",
    "gn:country_code":"LT",
    "gn:dem":35,
    "gn:feature_class":"P",
    "gn:feature_code":"PPL",
    "gn:name":"Pliori\u0161iai",
    "gn:population":0,
    "gn:timezone":"Europe/Vilnius",
    "iso:country":"LT",
    "name:lit_x_preferred":[
        "Pliori\u0161iai"
    ],
    "wof:name":"Pliorisiai",
    "wof:placetype":"locality"
},
  "geometry": {"coordinates":[22.85224,54.92462],"type":"Point"}
}