{
  "type": "Feature",
  "properties": {
    "gn:admin1_code":"62",
    "gn:admin2_code":"77.0",
    "gn:asciiname":"Ceikiske",
    "gn:country_code":"LT",
    "gn:dem":24,
    "gn:feature_class":"P",
    "gn:feature_code":"PPL",
    "gn:name":"Ceiki\u0161k\u0117",
    "gn:population":0,
    "gn:timezone":"Europe/Vilnius",
    "iso:country":"LT",
    "name:lit_x_preferred":[
        "Ceiki\u0161k\u0117"
    ],
    "wof:name":"Ceikiske",
    "wof:placetype":"locality"
},
  "geometry": {"coordinates":[22.22555,55.23446],"type":"Point"}
}