{
  "type": "Feature",
  "properties": {
    "gn:admin1_code":"65",
    "gn:admin2_code":"86.0",
    "gn:asciiname":"Juodynelis",
    "gn:country_code":"LT",
    "gn:dem":149,
    "gn:feature_class":"P",
    "gn:feature_code":"PPL",
    "gn:name":"Juodyn\u0117lis",
    "gn:population":0,
    "gn:timezone":"Europe/Vilnius",
    "iso:country":"LT",
    "name:lit_x_preferred":[
        "Juodyn\u0117lis"
    ],
    "wof:name":"Juodynelis",
    "wof:placetype":"locality"
},
  "geometry": {"coordinates":[25.924,55.20721999999999],"type":"Point"}
}