{
  "type": "Feature",
  "properties": {
    "gn:admin1_code":"56",
    "gn:admin2_code":"59.0",
    "gn:asciiname":"Buciniske",
    "gn:country_code":"LT",
    "gn:dem":80,
    "gn:feature_class":"P",
    "gn:feature_code":"PPL",
    "gn:name":"Bucini\u0161k\u0117",
    "gn:population":0,
    "gn:timezone":"Europe/Vilnius",
    "iso:country":"LT",
    "name:lit_x_preferred":[
        "Bucini\u0161k\u0117"
    ],
    "wof:name":"Buciniske",
    "wof:placetype":"locality"
},
  "geometry": {"coordinates":[23.96054,54.23604],"type":"Point"}
}