{
  "type": "Feature",
  "properties": {
    "gn:admin1_code":"60",
    "gn:admin2_code":"27.0",
    "gn:asciiname":"Putauskai",
    "gn:country_code":"LT",
    "gn:dem":65,
    "gn:feature_class":"P",
    "gn:feature_code":"PPL",
    "gn:name":"Putauskai",
    "gn:population":0,
    "gn:timezone":"Europe/Vilnius",
    "iso:country":"LT",
    "name:lit_x_preferred":[
        "Putauskai"
    ],
    "wof:name":"Putauskai",
    "wof:placetype":"locality"
},
  "geometry": {"coordinates":[24.61023,55.88523000000001],"type":"Point"}
}