{
  "type": "Feature",
  "properties": {
    "gn:admin1_code":"62",
    "gn:admin2_code":"87.0",
    "gn:asciiname":"Jaunodava",
    "gn:country_code":"LT",
    "gn:dem":165,
    "gn:feature_class":"P",
    "gn:feature_code":"PPL",
    "gn:name":"Jaunodava",
    "gn:population":0,
    "gn:timezone":"Europe/Vilnius",
    "iso:country":"LT",
    "name:lit_x_preferred":[
        "Jaunodava"
    ],
    "wof:name":"Jaunodava",
    "wof:placetype":"locality"
},
  "geometry": {"coordinates":[22.47203,55.61424],"type":"Point"}
}