{
  "type": "Feature",
  "properties": {
    "gn:admin1_code":"58.0",
    "gn:admin2_code":"75.0",
    "gn:asciiname":"Gonaiciai",
    "gn:country_code":"LT",
    "gn:dem":70,
    "gn:feature_class":"P",
    "gn:feature_code":"PPL",
    "gn:name":"Gonai\u010diai",
    "gn:population":0,
    "gn:timezone":"Europe/Vilnius",
    "iso:country":"LT",
    "name:und_x_variant":[
        "Gonaychyay",
        "Gonai\u010diai"
    ],
    "wof:name":"Gonaiciai",
    "wof:placetype":"locality"
},
  "geometry": {"coordinates":[21.79448,56.2721],"type":"Point"}
}