{
  "type": "Feature",
  "properties": {
    "gn:admin1_code":"65.0",
    "gn:admin2_code":"79.0",
    "gn:asciiname":"Zuklijai",
    "gn:country_code":"LT",
    "gn:dem":153,
    "gn:feature_class":"P",
    "gn:feature_code":"PPL",
    "gn:name":"\u017duklijai",
    "gn:population":0,
    "gn:timezone":"Europe/Vilnius",
    "iso:country":"LT",
    "name:und_x_variant":[
        "Zhukleya",
        "\u017dukl\u0117j\u0173",
        "\u017duklija",
        "\u017duklijai",
        "\u017dukl\u0117jai"
    ],
    "wof:name":"Zuklijai",
    "wof:placetype":"locality"
},
  "geometry": {"coordinates":[24.69683,54.51145],"type":"Point"}
}