{
  "type": "Feature",
  "properties": {
    "gn:admin1_code":"63",
    "gn:admin2_code":"68.0",
    "gn:asciiname":"Vilkai",
    "gn:country_code":"LT",
    "gn:dem":168,
    "gn:feature_class":"P",
    "gn:feature_code":"PPL",
    "gn:name":"Vilkai",
    "gn:population":0,
    "gn:timezone":"Europe/Vilnius",
    "iso:country":"LT",
    "name:lit_x_preferred":[
        "Vilkai"
    ],
    "wof:name":"Vilkai",
    "wof:placetype":"locality"
},
  "geometry": {"coordinates":[21.96144,56.04301],"type":"Point"}
}