{
  "type": "Feature",
  "properties": {
    "gn:admin1_code":"62.0",
    "gn:admin2_code":"94.0",
    "gn:asciiname":"Vajotai",
    "gn:country_code":"LT",
    "gn:dem":38,
    "gn:feature_class":"P",
    "gn:feature_code":"PPL",
    "gn:name":"Vajotai",
    "gn:population":0,
    "gn:timezone":"Europe/Vilnius",
    "iso:country":"LT",
    "name:lit_x_preferred":[
        "Vajotai"
    ],
    "wof:name":"Vajotai",
    "wof:placetype":"locality"
},
  "geometry": {"coordinates":[22.70898,55.13857],"type":"Point"}
}