{
  "type": "Feature",
  "properties": {
    "gn:admin1_code":"65.0",
    "gn:admin2_code":"13.0",
    "gn:asciiname":"Suzionys",
    "gn:country_code":"LT",
    "gn:dem":172,
    "gn:feature_class":"P",
    "gn:feature_code":"PPL",
    "gn:name":"Su\u017eionys",
    "gn:population":0,
    "gn:timezone":"Europe/Vilnius",
    "iso:country":"LT",
    "name:und_x_variant":[
        "Suzhenis",
        "Su\u017eany",
        "Su\u017eonys",
        "Suzhany",
        "Su\u017eionys"
    ],
    "wof:name":"Suzionys",
    "wof:placetype":"locality"
},
  "geometry": {"coordinates":[25.50921,54.98996999999999],"type":"Point"}
}