{
  "type": "Feature",
  "properties": {
    "gn:admin1_code":"64",
    "gn:admin2_code":"45.0",
    "gn:asciiname":"Zuikos",
    "gn:country_code":"LT",
    "gn:dem":207,
    "gn:feature_class":"P",
    "gn:feature_code":"PPL",
    "gn:name":"Zuikos",
    "gn:population":0,
    "gn:timezone":"Europe/Vilnius",
    "iso:country":"LT",
    "name:lit_x_preferred":[
        "Zuikos"
    ],
    "wof:name":"Zuikos",
    "wof:placetype":"locality"
},
  "geometry": {"coordinates":[26.19111,55.29886],"type":"Point"}
}