{
  "type": "Feature",
  "properties": {
    "gn:admin1_code":"64",
    "gn:admin2_code":"62.0",
    "gn:asciiname":"Bulaucizna",
    "gn:country_code":"LT",
    "gn:dem":161,
    "gn:feature_class":"P",
    "gn:feature_code":"PPL",
    "gn:name":"Bulau\u010dizna",
    "gn:population":0,
    "gn:timezone":"Europe/Vilnius",
    "iso:country":"LT",
    "name:lit_x_preferred":[
        "Bulau\u010dizna"
    ],
    "wof:name":"Bulaucizna",
    "wof:placetype":"locality"
},
  "geometry": {"coordinates":[25.62127000000001,55.13119],"type":"Point"}
}