{
  "type": "Feature",
  "properties": {
    "gn:admin1_code":"64",
    "gn:admin2_code":"62.0",
    "gn:asciiname":"Piesiskes",
    "gn:country_code":"LT",
    "gn:dem":130,
    "gn:feature_class":"P",
    "gn:feature_code":"PPL",
    "gn:name":"Pie\u0161i\u0161k\u0117s",
    "gn:population":0,
    "gn:timezone":"Europe/Vilnius",
    "iso:country":"LT",
    "name:lit_x_preferred":[
        "Pie\u0161i\u0161k\u0117s"
    ],
    "wof:name":"Piesiskes",
    "wof:placetype":"locality"
},
  "geometry": {"coordinates":[25.3738,55.34189],"type":"Point"}
}