{
  "type": "Feature",
  "properties": {
    "gn:admin1_code":"62",
    "gn:admin2_code":"77.0",
    "gn:asciiname":"Pakalpokiai",
    "gn:country_code":"LT",
    "gn:dem":31,
    "gn:feature_class":"P",
    "gn:feature_code":"PPL",
    "gn:name":"Pakalpokiai",
    "gn:population":0,
    "gn:timezone":"Europe/Vilnius",
    "iso:country":"LT",
    "name:lit_x_preferred":[
        "Pakalpokiai"
    ],
    "wof:name":"Pakalpokiai",
    "wof:placetype":"locality"
},
  "geometry": {"coordinates":[22.23122,55.25317],"type":"Point"}
}