{
  "type": "Feature",
  "properties": {
    "gn:admin1_code":"64.0",
    "gn:admin2_code":"82.0",
    "gn:asciiname":"Narkunai",
    "gn:country_code":"LT",
    "gn:dem":126,
    "gn:feature_class":"P",
    "gn:feature_code":"PPL",
    "gn:name":"Nark\u016bnai",
    "gn:population":0,
    "gn:timezone":"Europe/Vilnius",
    "iso:country":"LT",
    "name:und_x_variant":[
        "Nark\u016bn\u0173",
        "Narkunay",
        "Nark\u016bnai"
    ],
    "wof:name":"Narkunai",
    "wof:placetype":"locality"
},
  "geometry": {"coordinates":[25.56349,55.46765],"type":"Point"}
}