{
  "type": "Feature",
  "properties": {
    "gn:admin1_code":"56",
    "gn:admin2_code":"38.0",
    "gn:asciiname":"Puisys",
    "gn:country_code":"LT",
    "gn:dem":152,
    "gn:feature_class":"P",
    "gn:feature_code":"PPL",
    "gn:name":"Pui\u0161ys",
    "gn:population":0,
    "gn:timezone":"Europe/Vilnius",
    "iso:country":"LT",
    "name:lit_x_preferred":[
        "Pui\u0161ys"
    ],
    "wof:name":"Puisys",
    "wof:placetype":"locality"
},
  "geometry": {"coordinates":[24.77396,54.13396],"type":"Point"}
}