{
  "type": "Feature",
  "properties": {
    "gn:admin1_code":"64",
    "gn:admin2_code":"62.0",
    "gn:asciiname":"Jauros II",
    "gn:country_code":"LT",
    "gn:dem":150,
    "gn:feature_class":"P",
    "gn:feature_code":"PPL",
    "gn:name":"Jauros II",
    "gn:population":0,
    "gn:timezone":"Europe/Vilnius",
    "iso:country":"LT",
    "name:lit_x_preferred":[
        "Jauros II"
    ],
    "wof:name":"Jauros II",
    "wof:placetype":"locality"
},
  "geometry": {"coordinates":[25.44569,55.19124],"type":"Point"}
}