{
  "type": "Feature",
  "properties": {
    "gn:admin1_code":"61",
    "gn:admin2_code":"71.0",
    "gn:asciiname":"Ramulenai",
    "gn:country_code":"LT",
    "gn:dem":107,
    "gn:feature_class":"P",
    "gn:feature_code":"PPL",
    "gn:name":"Ramul\u0117nai",
    "gn:population":0,
    "gn:timezone":"Europe/Vilnius",
    "iso:country":"LT",
    "name:lit_x_preferred":[
        "Ramul\u0117nai"
    ],
    "wof:name":"Ramulenai",
    "wof:placetype":"locality"
},
  "geometry": {"coordinates":[23.53366,55.87671],"type":"Point"}
}