{
  "type": "Feature",
  "properties": {
    "gn:admin1_code":"62",
    "gn:admin2_code":"87.0",
    "gn:asciiname":"Pajerubynis",
    "gn:country_code":"LT",
    "gn:dem":119,
    "gn:feature_class":"P",
    "gn:feature_code":"PPL",
    "gn:name":"Paj\u0117rubynis",
    "gn:population":0,
    "gn:timezone":"Europe/Vilnius",
    "iso:country":"LT",
    "name:lit_x_preferred":[
        "Paj\u0117rubynis"
    ],
    "wof:name":"Pajerubynis",
    "wof:placetype":"locality"
},
  "geometry": {"coordinates":[22.27502,55.50606],"type":"Point"}
}