{
  "type": "Feature",
  "properties": {
    "gn:admin1_code":"57.0",
    "gn:admin2_code":"19.0",
    "gn:asciiname":"Mastaiciai",
    "gn:country_code":"LT",
    "gn:dem":77,
    "gn:feature_class":"P",
    "gn:feature_code":"PPL",
    "gn:name":"Mastaiciai",
    "gn:population":1339,
    "gn:timezone":"Europe/Vilnius",
    "iso:country":"LT",
    "name:und_x_variant":[
        "Mastai\u010diai"
    ],
    "wof:name":"Mastaiciai",
    "wof:placetype":"locality",
    "wof:population":1339
},
  "geometry": {"coordinates":[23.84462000000001,54.81998000000001],"type":"Point"}
}