{
  "type": "Feature",
  "properties": {
    "gn:admin1_code":"64",
    "gn:admin2_code":"43.0",
    "gn:asciiname":"Krakyne",
    "gn:country_code":"LT",
    "gn:dem":177,
    "gn:feature_class":"P",
    "gn:feature_code":"PPL",
    "gn:name":"Krakyn\u0117",
    "gn:population":0,
    "gn:timezone":"Europe/Vilnius",
    "iso:country":"LT",
    "name:lit_x_preferred":[
        "Krakyn\u0117"
    ],
    "wof:name":"Krakyne",
    "wof:placetype":"locality"
},
  "geometry": {"coordinates":[25.99777000000001,55.69859],"type":"Point"}
}