{
  "type": "Feature",
  "properties": {
    "gn:admin1_code":"64",
    "gn:admin2_code":"34.0",
    "gn:asciiname":"Zudzgalys",
    "gn:country_code":"LT",
    "gn:dem":83,
    "gn:feature_class":"P",
    "gn:feature_code":"PPL",
    "gn:name":"\u017dud\u017egalys",
    "gn:population":0,
    "gn:timezone":"Europe/Vilnius",
    "iso:country":"LT",
    "name:lit_x_preferred":[
        "\u017dud\u017egalys"
    ],
    "wof:name":"Zudzgalys",
    "wof:placetype":"locality"
},
  "geometry": {"coordinates":[24.73941,55.69617],"type":"Point"}
}