{
  "type": "Feature",
  "properties": {
    "gn:admin1_code":"0.0",
    "gn:asciiname":"Venteleriskes",
    "gn:country_code":"LT",
    "gn:dem":170,
    "gn:feature_class":"P",
    "gn:feature_code":"PPL",
    "gn:name":"Venteleri\u0161k\u0117s",
    "gn:population":0,
    "gn:timezone":"Europe/Vilnius",
    "iso:country":"LT",
    "name:lit_x_preferred":[
        "Venteleri\u0161k\u0117s"
    ],
    "wof:name":"Venteleriskes",
    "wof:placetype":"locality"
},
  "geometry": {"coordinates":[26.36177,55.70893],"type":"Point"}
}