{
  "type": "Feature",
  "properties": {
    "gn:admin1_code":"65",
    "gn:admin2_code":"81.0",
    "gn:asciiname":"Dvarniniai",
    "gn:country_code":"LT",
    "gn:dem":124,
    "gn:feature_class":"P",
    "gn:feature_code":"PPL",
    "gn:name":"Dvarniniai",
    "gn:population":0,
    "gn:timezone":"Europe/Vilnius",
    "iso:country":"LT",
    "name:lit_x_preferred":[
        "Dvarniniai"
    ],
    "wof:name":"Dvarniniai",
    "wof:placetype":"locality"
},
  "geometry": {"coordinates":[24.95882000000001,55.17913000000001],"type":"Point"}
}