{
  "type": "Feature",
  "properties": {
    "gn:admin1_code":"59",
    "gn:admin2_code":"39.0",
    "gn:asciiname":"Staugaiciai",
    "gn:country_code":"LT",
    "gn:dem":83,
    "gn:feature_class":"P",
    "gn:feature_code":"PPL",
    "gn:name":"Staugai\u010diai",
    "gn:population":0,
    "gn:timezone":"Europe/Vilnius",
    "iso:country":"LT",
    "name:lit_x_preferred":[
        "Staugai\u010diai"
    ],
    "wof:name":"Staugaiciai",
    "wof:placetype":"locality"
},
  "geometry": {"coordinates":[22.88027,54.6145],"type":"Point"}
}