{
  "type": "Feature",
  "properties": {
    "gn:admin1_code":"64",
    "gn:admin2_code":"62.0",
    "gn:asciiname":"Gaiziunai",
    "gn:country_code":"LT",
    "gn:dem":156,
    "gn:feature_class":"P",
    "gn:feature_code":"PPL",
    "gn:name":"Gai\u017ei\u016bnai",
    "gn:population":0,
    "gn:timezone":"Europe/Vilnius",
    "iso:country":"LT",
    "name:lit_x_preferred":[
        "Gai\u017ei\u016bnai"
    ],
    "wof:name":"Gaiziunai",
    "wof:placetype":"locality"
},
  "geometry": {"coordinates":[25.58127,55.13144000000001],"type":"Point"}
}