{
  "type": "Feature",
  "properties": {
    "gn:admin1_code":"57.0",
    "gn:admin2_code":"49.0",
    "gn:asciiname":"Dauginava",
    "gn:country_code":"LT",
    "gn:dem":140,
    "gn:feature_class":"P",
    "gn:feature_code":"PPL",
    "gn:name":"Dauginava",
    "gn:population":0,
    "gn:timezone":"Europe/Vilnius",
    "iso:country":"LT",
    "name:und_x_variant":[
        "Dolginovo",
        "Dauginava"
    ],
    "wof:name":"Dauginava",
    "wof:placetype":"locality"
},
  "geometry": {"coordinates":[24.49688,54.75883],"type":"Point"}
}