{
  "type": "Feature",
  "properties": {
    "gn:admin1_code":"61.0",
    "gn:admin2_code":"29.0",
    "gn:asciiname":"Ginkunai",
    "gn:country_code":"LT",
    "gn:dem":112,
    "gn:feature_class":"P",
    "gn:feature_code":"PPL",
    "gn:name":"Gink\u016bnai",
    "gn:population":0,
    "gn:timezone":"Europe/Vilnius",
    "iso:country":"LT",
    "name:und_x_variant":[
        "Genkunay",
        "Genk\u016bnai",
        "Gink\u016bnai"
    ],
    "wof:name":"Ginkunai",
    "wof:placetype":"locality"
},
  "geometry": {"coordinates":[23.35597000000001,55.95291],"type":"Point"}
}