{
  "type": "Feature",
  "properties": {
    "gn:admin1_code":"58.0",
    "gn:admin2_code":"21.0",
    "gn:asciiname":"Rudgalviai",
    "gn:country_code":"LT",
    "gn:dem":102,
    "gn:feature_class":"P",
    "gn:feature_code":"PPL",
    "gn:name":"Rudgalviai",
    "gn:population":0,
    "gn:timezone":"Europe/Vilnius",
    "iso:country":"LT",
    "name:und_x_variant":[
        "Rudgalvey",
        "Rudgalviai"
    ],
    "wof:name":"Rudgalviai",
    "wof:placetype":"locality"
},
  "geometry": {"coordinates":[21.64923,55.67252],"type":"Point"}
}