{
  "type": "Feature",
  "properties": {
    "gn:admin1_code":"61",
    "gn:admin2_code":"65.0",
    "gn:asciiname":"Margiai",
    "gn:country_code":"LT",
    "gn:dem":55,
    "gn:feature_class":"P",
    "gn:feature_code":"PPL",
    "gn:name":"Margiai",
    "gn:population":0,
    "gn:timezone":"Europe/Vilnius",
    "iso:country":"LT",
    "name:lit_x_preferred":[
        "Margiai"
    ],
    "wof:name":"Margiai",
    "wof:placetype":"locality"
},
  "geometry": {"coordinates":[23.9567,55.96377],"type":"Point"}
}