{
  "type": "Feature",
  "properties": {
    "gn:admin1_code":"62",
    "gn:admin2_code":"77.0",
    "gn:asciiname":"Steponiskiai",
    "gn:country_code":"LT",
    "gn:dem":26,
    "gn:feature_class":"P",
    "gn:feature_code":"PPL",
    "gn:name":"Steponi\u0161kiai",
    "gn:population":0,
    "gn:timezone":"Europe/Vilnius",
    "iso:country":"LT",
    "name:lit_x_preferred":[
        "Steponi\u0161kiai"
    ],
    "wof:name":"Steponiskiai",
    "wof:placetype":"locality"
},
  "geometry": {"coordinates":[22.04542,55.2131],"type":"Point"}
}