{
  "type": "Feature",
  "properties": {
    "gn:admin1_code":"60.0",
    "gn:admin2_code":"67.0",
    "gn:asciiname":"Krastai",
    "gn:country_code":"LT",
    "gn:dem":43,
    "gn:feature_class":"P",
    "gn:feature_code":"PPL",
    "gn:name":"Kra\u0161tai",
    "gn:population":0,
    "gn:timezone":"Europe/Vilnius",
    "iso:country":"LT",
    "name:und_x_variant":[
        "Krashtay",
        "Kra\u0161tai"
    ],
    "wof:name":"Krastai",
    "wof:placetype":"locality"
},
  "geometry": {"coordinates":[24.54155,56.13211999999999],"type":"Point"}
}