{
  "type": "Feature",
  "properties": {
    "gn:admin1_code":"57",
    "gn:admin2_code":"49.0",
    "gn:asciiname":"Karlauka",
    "gn:country_code":"LT",
    "gn:dem":83,
    "gn:feature_class":"P",
    "gn:feature_code":"PPL",
    "gn:name":"Karlauka",
    "gn:population":0,
    "gn:timezone":"Europe/Vilnius",
    "iso:country":"LT",
    "name:lit_x_preferred":[
        "Karlauka"
    ],
    "wof:name":"Karlauka",
    "wof:placetype":"locality"
},
  "geometry": {"coordinates":[24.41571,54.96601],"type":"Point"}
}