{
  "type": "Feature",
  "properties": {
    "gn:admin1_code":"65",
    "gn:admin2_code":"13.0",
    "gn:asciiname":"Barzdziunai",
    "gn:country_code":"LT",
    "gn:dem":161,
    "gn:feature_class":"P",
    "gn:feature_code":"PPL",
    "gn:name":"Barzd\u017ei\u016bnai",
    "gn:population":0,
    "gn:timezone":"Europe/Vilnius",
    "iso:country":"LT",
    "name:lit_x_preferred":[
        "Barzd\u017ei\u016bnai"
    ],
    "wof:name":"Barzdziunai",
    "wof:placetype":"locality"
},
  "geometry": {"coordinates":[25.53779,54.99452],"type":"Point"}
}