{
  "type": "Feature",
  "properties": {
    "gn:admin1_code":"65",
    "gn:admin2_code":"13.0",
    "gn:asciiname":"Makovscizna",
    "gn:country_code":"LT",
    "gn:dem":177,
    "gn:feature_class":"P",
    "gn:feature_code":"PPL",
    "gn:name":"Makov\u0161\u010dizna",
    "gn:population":0,
    "gn:timezone":"Europe/Vilnius",
    "iso:country":"LT",
    "name:lit_x_preferred":[
        "Makov\u0161\u010dizna"
    ],
    "wof:name":"Makovscizna",
    "wof:placetype":"locality"
},
  "geometry": {"coordinates":[25.66718,54.73773000000001],"type":"Point"}
}