{
  "type": "Feature",
  "properties": {
    "gn:admin1_code":"65",
    "gn:admin2_code":"81.0",
    "gn:asciiname":"Radziunai",
    "gn:country_code":"LT",
    "gn:dem":80,
    "gn:feature_class":"P",
    "gn:feature_code":"PPL",
    "gn:name":"Rad\u017ei\u016bnai",
    "gn:population":0,
    "gn:timezone":"Europe/Vilnius",
    "iso:country":"LT",
    "name:lit_x_preferred":[
        "Rad\u017ei\u016bnai"
    ],
    "wof:name":"Radziunai",
    "wof:placetype":"locality"
},
  "geometry": {"coordinates":[24.76287,55.42128],"type":"Point"}
}