{
  "type": "Feature",
  "properties": {
    "gn:admin1_code":"61",
    "gn:admin2_code":"47.0",
    "gn:asciiname":"Azuolyne",
    "gn:country_code":"LT",
    "gn:dem":63,
    "gn:feature_class":"P",
    "gn:feature_code":"PPL",
    "gn:name":"A\u017euolyn\u0117",
    "gn:population":0,
    "gn:timezone":"Europe/Vilnius",
    "iso:country":"LT",
    "name:lit_x_preferred":[
        "A\u017euolyn\u0117"
    ],
    "wof:name":"Azuolyne",
    "wof:placetype":"locality"
},
  "geometry": {"coordinates":[23.42033,56.25086],"type":"Point"}
}