{
  "type": "Feature",
  "properties": {
    "gn:admin1_code":"65.0",
    "gn:admin2_code":"86.0",
    "gn:asciiname":"Balingradas",
    "gn:country_code":"LT",
    "gn:dem":112,
    "gn:feature_class":"P",
    "gn:feature_code":"PPL",
    "gn:name":"Balingradas",
    "gn:population":0,
    "gn:timezone":"Europe/Vilnius",
    "iso:country":"LT",
    "name:lit_x_preferred":[
        "Balingradas"
    ],
    "name:und_x_variant":[
        "Balingardas",
        "Balangrudok",
        "Balingr\u00f3dek",
        "Bageli\u0161k\u0117s"
    ],
    "wof:name":"Balingradas",
    "wof:placetype":"locality"
},
  "geometry": {"coordinates":[25.70436,54.86809],"type":"Point"}
}