{
  "type": "Feature",
  "properties": {
    "gn:admin1_code":"64",
    "gn:admin2_code":"43.0",
    "gn:asciiname":"Staciunai",
    "gn:country_code":"LT",
    "gn:dem":146,
    "gn:feature_class":"P",
    "gn:feature_code":"PPL",
    "gn:name":"Sta\u010di\u016bnai",
    "gn:population":0,
    "gn:timezone":"Europe/Vilnius",
    "iso:country":"LT",
    "name:lit_x_preferred":[
        "Sta\u010di\u016bnai"
    ],
    "wof:name":"Staciunai",
    "wof:placetype":"locality"
},
  "geometry": {"coordinates":[26.44939,55.64976],"type":"Point"}
}