{
  "type": "Feature",
  "properties": {
    "gn:admin1_code":"64",
    "gn:admin2_code":"62.0",
    "gn:asciiname":"Antatiskes",
    "gn:country_code":"LT",
    "gn:dem":153,
    "gn:feature_class":"P",
    "gn:feature_code":"PPL",
    "gn:name":"Antati\u0161k\u0117s",
    "gn:population":0,
    "gn:timezone":"Europe/Vilnius",
    "iso:country":"LT",
    "name:lit_x_preferred":[
        "Antati\u0161k\u0117s"
    ],
    "wof:name":"Antatiskes",
    "wof:placetype":"locality"
},
  "geometry": {"coordinates":[25.48224,55.24263000000001],"type":"Point"}
}