{
  "type": "Feature",
  "properties": {
    "gn:admin1_code":"57.0",
    "gn:admin2_code":"46.0",
    "gn:asciiname":"Blauzdziai",
    "gn:country_code":"LT",
    "gn:dem":62,
    "gn:feature_class":"P",
    "gn:feature_code":"PPL",
    "gn:name":"Blauzd\u017eiai",
    "gn:population":0,
    "gn:timezone":"Europe/Vilnius",
    "iso:country":"LT",
    "name:und_x_variant":[
        "Blauzdzhyay",
        "Blauzd\u017eiai"
    ],
    "wof:name":"Blauzdziai",
    "wof:placetype":"locality"
},
  "geometry": {"coordinates":[24.14891,55.18545],"type":"Point"}
}