{
  "type": "Feature",
  "properties": {
    "gn:admin1_code":"64",
    "gn:admin2_code":"45.0",
    "gn:asciiname":"Kazliske",
    "gn:country_code":"LT",
    "gn:dem":172,
    "gn:feature_class":"P",
    "gn:feature_code":"PPL",
    "gn:name":"Kazli\u0161k\u0117",
    "gn:population":0,
    "gn:timezone":"Europe/Vilnius",
    "iso:country":"LT",
    "name:lit_x_preferred":[
        "Kazli\u0161k\u0117"
    ],
    "wof:name":"Kazliske",
    "wof:placetype":"locality"
},
  "geometry": {"coordinates":[26.37112,55.23956999999999],"type":"Point"}
}