{
  "type": "Feature",
  "properties": {
    "gn:admin1_code":"64.0",
    "gn:admin2_code":"82.0",
    "gn:asciiname":"Klykiai",
    "gn:country_code":"LT",
    "gn:dem":202,
    "gn:feature_class":"P",
    "gn:feature_code":"PPL",
    "gn:name":"Klykiai",
    "gn:population":0,
    "gn:timezone":"Europe/Vilnius",
    "iso:country":"LT",
    "name:und_x_variant":[
        "Klikyay",
        "Klyki\u0173",
        "Klykiai"
    ],
    "wof:name":"Klykiai",
    "wof:placetype":"locality"
},
  "geometry": {"coordinates":[25.76295,55.47691999999999],"type":"Point"}
}