{
  "type": "Feature",
  "properties": {
    "gn:admin1_code":"64",
    "gn:admin2_code":"43.0",
    "gn:asciiname":"Kukuliskiai",
    "gn:country_code":"LT",
    "gn:dem":157,
    "gn:feature_class":"P",
    "gn:feature_code":"PPL",
    "gn:name":"Kukuli\u0161kiai",
    "gn:population":0,
    "gn:timezone":"Europe/Vilnius",
    "iso:country":"LT",
    "name:lit_x_preferred":[
        "Kukuli\u0161kiai"
    ],
    "wof:name":"Kukuliskiai",
    "wof:placetype":"locality"
},
  "geometry": {"coordinates":[26.19294,55.78309],"type":"Point"}
}