{
  "type": "Feature",
  "properties": {
    "gn:admin1_code":"61.0",
    "gn:admin2_code":"54.0",
    "gn:asciiname":"Kruopainiai",
    "gn:country_code":"LT",
    "gn:dem":168,
    "gn:feature_class":"P",
    "gn:feature_code":"PPL",
    "gn:name":"Kruopainiai",
    "gn:population":0,
    "gn:timezone":"Europe/Vilnius",
    "iso:country":"LT",
    "name:und_x_variant":[
        "Krupayne",
        "Kruopainiai"
    ],
    "wof:name":"Kruopainiai",
    "wof:placetype":"locality"
},
  "geometry": {"coordinates":[22.52587,55.77092],"type":"Point"}
}