{
  "type": "Feature",
  "properties": {
    "gn:admin1_code":"65.0",
    "gn:admin2_code":"79.0",
    "gn:asciiname":"Pilialaukis",
    "gn:country_code":"LT",
    "gn:dem":155,
    "gn:feature_class":"P",
    "gn:feature_code":"PPL",
    "gn:name":"Pilialaukis",
    "gn:population":0,
    "gn:timezone":"Europe/Vilnius",
    "iso:country":"LT",
    "name:und_x_variant":[
        "Piloluaka",
        "Pilialaukis"
    ],
    "wof:name":"Pilialaukis",
    "wof:placetype":"locality"
},
  "geometry": {"coordinates":[25.01602,54.604],"type":"Point"}
}