{
  "type": "Feature",
  "properties": {
    "gn:admin1_code":"59",
    "gn:admin2_code":"84.0",
    "gn:asciiname":"Visinskai",
    "gn:country_code":"LT",
    "gn:dem":45,
    "gn:feature_class":"P",
    "gn:feature_code":"PPL",
    "gn:name":"Vi\u0161inskai",
    "gn:population":0,
    "gn:timezone":"Europe/Vilnius",
    "iso:country":"LT",
    "name:lit_x_preferred":[
        "Vi\u0161inskai"
    ],
    "wof:name":"Visinskai",
    "wof:placetype":"locality"
},
  "geometry": {"coordinates":[22.89475,55.05671],"type":"Point"}
}