{
  "type": "Feature",
  "properties": {
    "gn:admin1_code":"56",
    "gn:admin2_code":"11.0",
    "gn:asciiname":"Olenderne",
    "gn:country_code":"LT",
    "gn:dem":142,
    "gn:feature_class":"P",
    "gn:feature_code":"PPL",
    "gn:name":"Olendern\u0117",
    "gn:population":0,
    "gn:timezone":"Europe/Vilnius",
    "iso:country":"LT",
    "name:lit_x_preferred":[
        "Olendern\u0117"
    ],
    "wof:name":"Olenderne",
    "wof:placetype":"locality"
},
  "geometry": {"coordinates":[24.28384,54.49844],"type":"Point"}
}