{
  "type": "Feature",
  "properties": {
    "gn:admin1_code":"0.0",
    "gn:asciiname":"Pustelninkai",
    "gn:cc2":"LT",
    "gn:country_code":"LT",
    "gn:dem":51,
    "gn:feature_class":"P",
    "gn:feature_code":"PPL",
    "gn:name":"P\u016bstelninkai",
    "gn:population":0,
    "gn:timezone":"Europe/Vilnius",
    "iso:country":"LT",
    "name:und_x_variant":[
        "Pustel'niki",
        "Pustelnikay"
    ],
    "wof:name":"Pustelninkai",
    "wof:placetype":"locality"
},
  "geometry": {"coordinates":[23.85,55.28333000000001],"type":"Point"}
}