{
  "type": "Feature",
  "properties": {
    "gn:admin1_code":"65",
    "gn:admin2_code":"86.0",
    "gn:asciiname":"Gaspariskiai",
    "gn:country_code":"LT",
    "gn:dem":148,
    "gn:feature_class":"P",
    "gn:feature_code":"PPL",
    "gn:name":"Gaspari\u0161kiai",
    "gn:population":0,
    "gn:timezone":"Europe/Vilnius",
    "iso:country":"LT",
    "name:lit_x_preferred":[
        "Gaspari\u0161kiai"
    ],
    "wof:name":"Gaspariskiai",
    "wof:placetype":"locality"
},
  "geometry": {"coordinates":[25.84152000000001,54.95201],"type":"Point"}
}