{
  "type": "Feature",
  "properties": {
    "gn:admin1_code":"65",
    "gn:admin2_code":"42.0",
    "gn:asciiname":"Sodyba",
    "gn:country_code":"LT",
    "gn:dem":124,
    "gn:feature_class":"P",
    "gn:feature_code":"PPL",
    "gn:name":"Sodyba",
    "gn:population":0,
    "gn:timezone":"Europe/Vilnius",
    "iso:country":"LT",
    "name:lit_x_preferred":[
        "Sodyba"
    ],
    "wof:name":"Sodyba",
    "wof:placetype":"locality"
},
  "geometry": {"coordinates":[24.75317,54.82556999999999],"type":"Point"}
}