{
  "type": "Feature",
  "properties": {
    "gn:admin1_code":"65.0",
    "gn:admin2_code":"13.0",
    "gn:asciiname":"Keturiasdesimt Totoriu",
    "gn:country_code":"LT",
    "gn:dem":165,
    "gn:feature_class":"P",
    "gn:feature_code":"PPL",
    "gn:name":"Keturiasde\u0161imt Totori\u0173",
    "gn:population":0,
    "gn:timezone":"Europe/Vilnius",
    "iso:country":"LT",
    "name:und_x_variant":[
        "Totorkaimis",
        "Sorok Tatary",
        "Keturiasde\u0161imt Totori\u0173"
    ],
    "wof:name":"Keturiasdesimt Totoriu",
    "wof:placetype":"locality"
},
  "geometry": {"coordinates":[25.16924,54.56176],"type":"Point"}
}