{
  "type": "Feature",
  "properties": {
    "gn:admin1_code":"62",
    "gn:admin2_code":"63.0",
    "gn:asciiname":"Pleine",
    "gn:country_code":"LT",
    "gn:dem":7,
    "gn:feature_class":"P",
    "gn:feature_code":"PPL",
    "gn:name":"Plein\u0117",
    "gn:population":0,
    "gn:timezone":"Europe/Vilnius",
    "iso:country":"LT",
    "name:lit_x_preferred":[
        "Plein\u0117"
    ],
    "wof:name":"Pleine",
    "wof:placetype":"locality"
},
  "geometry": {"coordinates":[21.74922,55.20802],"type":"Point"}
}