{
  "type": "Feature",
  "properties": {
    "gn:admin1_code":"64.0",
    "gn:admin2_code":"82.0",
    "gn:asciiname":"Spraksiai",
    "gn:country_code":"LT",
    "gn:dem":103,
    "gn:feature_class":"P",
    "gn:feature_code":"PPL",
    "gn:name":"Sprak\u0161iai",
    "gn:population":0,
    "gn:timezone":"Europe/Vilnius",
    "iso:country":"LT",
    "name:und_x_variant":[
        "Sprak\u0161i\u0173",
        "Sprakshyay",
        "Sprak\u0161iai"
    ],
    "wof:name":"Spraksiai",
    "wof:placetype":"locality"
},
  "geometry": {"coordinates":[25.53938,55.56964],"type":"Point"}
}