{
  "type": "Feature",
  "properties": {
    "gn:admin1_code":"61.0",
    "gn:admin2_code":"71.0",
    "gn:asciiname":"Grinkiskis",
    "gn:country_code":"LT",
    "gn:dem":109,
    "gn:feature_class":"P",
    "gn:feature_code":"PPL",
    "gn:name":"Grinki\u0161kis",
    "gn:population":0,
    "gn:timezone":"Europe/Vilnius",
    "iso:country":"LT",
    "name:ceb_x_preferred":[
        "Grinki\u0161kis"
    ],
    "name:deu_x_preferred":[
        "Grinki\u0161kis"
    ],
    "name:eng_x_preferred":[
        "Grinki\u0161kis"
    ],
    "name:est_x_preferred":[
        "Grinki\u0161kis"
    ],
    "name:lit_x_preferred":[
        "Grinki\u0161kis"
    ],
    "name:pol_x_preferred":[
        "Grynkiszki"
    ],
    "name:rus_x_preferred":[
        "\u0413\u0440\u0438\u043d\u043a\u0438\u0448\u043a\u0438\u0441"
    ],
    "name:swe_x_preferred":[
        "Grinki\u0161kis"
    ],
    "name:und_x_variant":[
        "Grinkishki",
        "Grynkiszki",
        "Grinkishkis",
        "Grinki\u0161kio",
        "Grinki\u0161kis"
    ],
    "wof:name":"Grinkiskis",
    "wof:placetype":"locality"
},
  "geometry": {"coordinates":[23.63659,55.55516],"type":"Point"}
}