{
  "type": "Feature",
  "properties": {
    "gn:admin1_code":"61",
    "gn:admin2_code":"65.0",
    "gn:asciiname":"Pagiriai",
    "gn:country_code":"LT",
    "gn:dem":56,
    "gn:feature_class":"P",
    "gn:feature_code":"PPL",
    "gn:name":"Pagiriai",
    "gn:population":0,
    "gn:timezone":"Europe/Vilnius",
    "iso:country":"LT",
    "name:est_x_preferred":[
        "Pagiriai"
    ],
    "name:lit_x_preferred":[
        "Pagiriai"
    ],
    "name:nld_x_preferred":[
        "Pagiriai"
    ],
    "name:pol_x_preferred":[
        "Pogiry"
    ],
    "wof:name":"Pagiriai",
    "wof:placetype":"locality"
},
  "geometry": {"coordinates":[24.02515,56.11945],"type":"Point"}
}