{
  "type": "Feature",
  "properties": {
    "gn:admin1_code":"61",
    "gn:admin2_code":"65.0",
    "gn:asciiname":"Vydziai",
    "gn:country_code":"LT",
    "gn:dem":42,
    "gn:feature_class":"P",
    "gn:feature_code":"PPL",
    "gn:name":"Vyd\u017eiai",
    "gn:population":0,
    "gn:timezone":"Europe/Vilnius",
    "iso:country":"LT",
    "name:lit_x_preferred":[
        "Vyd\u017eiai"
    ],
    "wof:name":"Vydziai",
    "wof:placetype":"locality"
},
  "geometry": {"coordinates":[23.93181,56.2917],"type":"Point"}
}