{
  "type": "Feature",
  "properties": {
    "gn:admin1_code":"60",
    "gn:admin2_code":"36.0",
    "gn:asciiname":"Kirsoniai",
    "gn:country_code":"LT",
    "gn:dem":42,
    "gn:feature_class":"P",
    "gn:feature_code":"PPL",
    "gn:name":"Kir\u0161oniai",
    "gn:population":0,
    "gn:timezone":"Europe/Vilnius",
    "iso:country":"LT",
    "name:lit_x_preferred":[
        "Kir\u0161oniai"
    ],
    "wof:name":"Kirsoniai",
    "wof:placetype":"locality"
},
  "geometry": {"coordinates":[24.61969,56.19317],"type":"Point"}
}