{
  "type": "Feature",
  "properties": {
    "gn:admin1_code":"0.0",
    "gn:asciiname":"Vitrakas",
    "gn:country_code":"LT",
    "gn:dem":48,
    "gn:feature_class":"P",
    "gn:feature_code":"PPL",
    "gn:name":"Vitrakas",
    "gn:population":0,
    "gn:timezone":"Europe/Vilnius",
    "iso:country":"LT",
    "wof:name":"Vitrakas",
    "wof:placetype":"locality"
},
  "geometry": {"coordinates":[23.05,54.91667],"type":"Point"}
}