{
  "type": "Feature",
  "properties": {
    "gn:admin1_code":"59",
    "gn:admin2_code":"18.0",
    "gn:asciiname":"Karciuvka",
    "gn:country_code":"LT",
    "gn:dem":104,
    "gn:feature_class":"P",
    "gn:feature_code":"PPL",
    "gn:name":"Kar\u010diuvka",
    "gn:population":0,
    "gn:timezone":"Europe/Vilnius",
    "iso:country":"LT",
    "name:lit_x_preferred":[
        "Kar\u010diuvka"
    ],
    "wof:name":"Karciuvka",
    "wof:placetype":"locality"
},
  "geometry": {"coordinates":[23.68431,54.59979000000001],"type":"Point"}
}