{
  "type": "Feature",
  "properties": {
    "gn:admin1_code":"65",
    "gn:admin2_code":"42.0",
    "gn:asciiname":"Rinkaucizna",
    "gn:country_code":"LT",
    "gn:dem":174,
    "gn:feature_class":"P",
    "gn:feature_code":"PPL",
    "gn:name":"Rinkau\u010dizna",
    "gn:population":0,
    "gn:timezone":"Europe/Vilnius",
    "iso:country":"LT",
    "name:lit_x_preferred":[
        "Rinkau\u010dizna"
    ],
    "wof:name":"Rinkaucizna",
    "wof:placetype":"locality"
},
  "geometry": {"coordinates":[24.81033,54.71927],"type":"Point"}
}