{
  "type": "Feature",
  "properties": {
    "gn:admin1_code":"64",
    "gn:admin2_code":"62.0",
    "gn:asciiname":"Vengelka",
    "gn:country_code":"LT",
    "gn:dem":166,
    "gn:feature_class":"P",
    "gn:feature_code":"PPL",
    "gn:name":"Vengelka",
    "gn:population":0,
    "gn:timezone":"Europe/Vilnius",
    "iso:country":"LT",
    "name:lit_x_preferred":[
        "Vengelka"
    ],
    "wof:name":"Vengelka",
    "wof:placetype":"locality"
},
  "geometry": {"coordinates":[25.4589,55.16356],"type":"Point"}
}