{
  "type": "Feature",
  "properties": {
    "gn:admin1_code":"58.0",
    "gn:admin2_code":"75.0",
    "gn:asciiname":"Teveliai",
    "gn:country_code":"LT",
    "gn:dem":47,
    "gn:feature_class":"P",
    "gn:feature_code":"PPL",
    "gn:name":"T\u0117veliai",
    "gn:population":0,
    "gn:timezone":"Europe/Vilnius",
    "iso:country":"LT",
    "name:lit_x_preferred":[
        "T\u0117veliai"
    ],
    "wof:name":"Teveliai",
    "wof:placetype":"locality"
},
  "geometry": {"coordinates":[21.58006,56.22321],"type":"Point"}
}