{
  "type": "Feature",
  "properties": {
    "gn:admin1_code":"60.0",
    "gn:admin2_code":"73.0",
    "gn:asciiname":"Konstantinava",
    "gn:country_code":"LT",
    "gn:dem":92,
    "gn:feature_class":"P",
    "gn:feature_code":"PPL",
    "gn:name":"Konstantinava",
    "gn:population":0,
    "gn:timezone":"Europe/Vilnius",
    "iso:country":"LT",
    "name:lit_x_preferred":[
        "Konstantinava"
    ],
    "wof:name":"Konstantinava",
    "wof:placetype":"locality"
},
  "geometry": {"coordinates":[25.35017,56.05498000000001],"type":"Point"}
}