{
  "type": "Feature",
  "properties": {
    "gn:admin1_code":"64",
    "gn:admin2_code":"34.0",
    "gn:asciiname":"Jasiskis",
    "gn:country_code":"LT",
    "gn:dem":158,
    "gn:feature_class":"P",
    "gn:feature_code":"PPL",
    "gn:name":"Ja\u0161i\u0161kis",
    "gn:population":0,
    "gn:timezone":"Europe/Vilnius",
    "iso:country":"LT",
    "name:lit_x_preferred":[
        "Ja\u0161i\u0161kis"
    ],
    "wof:name":"Jasiskis",
    "wof:placetype":"locality"
},
  "geometry": {"coordinates":[25.36427,55.4218],"type":"Point"}
}