{
  "type": "Feature",
  "properties": {
    "gn:admin1_code":"59.0",
    "gn:admin2_code":"84.0",
    "gn:asciiname":"Naujeliskiai",
    "gn:country_code":"LT",
    "gn:dem":60,
    "gn:feature_class":"P",
    "gn:feature_code":"PPL",
    "gn:name":"Naujeli\u0161kiai",
    "gn:population":0,
    "gn:timezone":"Europe/Vilnius",
    "iso:country":"LT",
    "name:und_x_variant":[
        "Kumetse",
        "Naujeli\u0161kiai"
    ],
    "wof:name":"Naujeliskiai",
    "wof:placetype":"locality"
},
  "geometry": {"coordinates":[23.21702,55.06445],"type":"Point"}
}