{
  "type": "Feature",
  "properties": {
    "gn:admin1_code":"64",
    "gn:admin2_code":"82.0",
    "gn:asciiname":"Kloviniai",
    "gn:country_code":"LT",
    "gn:dem":142,
    "gn:feature_class":"P",
    "gn:feature_code":"PPL",
    "gn:name":"Kloviniai",
    "gn:population":0,
    "gn:timezone":"Europe/Vilnius",
    "iso:country":"LT",
    "name:lit_x_preferred":[
        "Kloviniai"
    ],
    "wof:name":"Kloviniai",
    "wof:placetype":"locality"
},
  "geometry": {"coordinates":[25.65373,55.50279000000001],"type":"Point"}
}