{
  "type": "Feature",
  "properties": {
    "gn:admin1_code":"57",
    "gn:admin2_code":"46.0",
    "gn:asciiname":"Kisieliskiai",
    "gn:country_code":"LT",
    "gn:dem":75,
    "gn:feature_class":"P",
    "gn:feature_code":"PPL",
    "gn:name":"Kisieli\u0161kiai",
    "gn:population":0,
    "gn:timezone":"Europe/Vilnius",
    "iso:country":"LT",
    "name:lit_x_preferred":[
        "Kisieli\u0161kiai"
    ],
    "wof:name":"Kisieliskiai",
    "wof:placetype":"locality"
},
  "geometry": {"coordinates":[24.29436,55.03213],"type":"Point"}
}