{
  "type": "Feature",
  "properties": {
    "gn:admin1_code":"58",
    "gn:admin2_code":"56.0",
    "gn:asciiname":"Bargalis",
    "gn:country_code":"LT",
    "gn:dem":52,
    "gn:feature_class":"P",
    "gn:feature_code":"PPL",
    "gn:name":"Bargalis",
    "gn:population":0,
    "gn:timezone":"Europe/Vilnius",
    "iso:country":"LT",
    "name:lit_x_preferred":[
        "Bargalis"
    ],
    "wof:name":"Bargalis",
    "wof:placetype":"locality"
},
  "geometry": {"coordinates":[21.50695,56.05698],"type":"Point"}
}