{
  "type": "Feature",
  "properties": {
    "gn:admin1_code":"64",
    "gn:admin2_code":"82.0",
    "gn:asciiname":"Rugeniskis",
    "gn:country_code":"LT",
    "gn:dem":198,
    "gn:feature_class":"P",
    "gn:feature_code":"PPL",
    "gn:name":"Rugeni\u0161kis",
    "gn:population":0,
    "gn:timezone":"Europe/Vilnius",
    "iso:country":"LT",
    "name:lit_x_preferred":[
        "Rugeni\u0161kis"
    ],
    "wof:name":"Rugeniskis",
    "wof:placetype":"locality"
},
  "geometry": {"coordinates":[25.79179,55.42544],"type":"Point"}
}