{
  "type": "Feature",
  "properties": {
    "gn:admin1_code":"61.0",
    "gn:admin2_code":"71.0",
    "gn:asciiname":"Mankiskiai",
    "gn:country_code":"LT",
    "gn:dem":126,
    "gn:feature_class":"P",
    "gn:feature_code":"PPL",
    "gn:name":"Manki\u0161kiai",
    "gn:population":0,
    "gn:timezone":"Europe/Vilnius",
    "iso:country":"LT",
    "name:und_x_variant":[
        "Manki\u0161ki\u0173",
        "Mankishkyay",
        "Manki\u0161kiai"
    ],
    "wof:name":"Mankiskiai",
    "wof:placetype":"locality"
},
  "geometry": {"coordinates":[23.44634,55.84428000000001],"type":"Point"}
}