{
  "type": "Feature",
  "properties": {
    "gn:admin1_code":"60",
    "gn:admin2_code":"36.0",
    "gn:asciiname":"Putrine",
    "gn:country_code":"LT",
    "gn:dem":53,
    "gn:feature_class":"P",
    "gn:feature_code":"PPL",
    "gn:name":"Putrin\u0117",
    "gn:population":0,
    "gn:timezone":"Europe/Vilnius",
    "iso:country":"LT",
    "name:lit_x_preferred":[
        "Putrin\u0117"
    ],
    "wof:name":"Putrine",
    "wof:placetype":"locality"
},
  "geometry": {"coordinates":[24.90917,56.40544000000001],"type":"Point"}
}