{
  "type": "Feature",
  "properties": {
    "gn:admin1_code":"61.0",
    "gn:admin2_code":"29.0",
    "gn:asciiname":"Mumaiciai",
    "gn:country_code":"LT",
    "gn:dem":110,
    "gn:feature_class":"P",
    "gn:feature_code":"PPL",
    "gn:name":"Mumai\u010diai",
    "gn:population":0,
    "gn:timezone":"Europe/Vilnius",
    "iso:country":"LT",
    "name:und_x_variant":[
        "Mazhaychay",
        "Mumai\u010diai"
    ],
    "wof:name":"Mumaiciai",
    "wof:placetype":"locality"
},
  "geometry": {"coordinates":[23.47506,55.91089],"type":"Point"}
}