{
  "type": "Feature",
  "properties": {
    "gn:admin1_code":"64",
    "gn:admin2_code":"34.0",
    "gn:asciiname":"Kiausai",
    "gn:country_code":"LT",
    "gn:dem":136,
    "gn:feature_class":"P",
    "gn:feature_code":"PPL",
    "gn:name":"Kiau\u0161ai",
    "gn:population":0,
    "gn:timezone":"Europe/Vilnius",
    "iso:country":"LT",
    "name:lit_x_preferred":[
        "Kiau\u0161ai"
    ],
    "wof:name":"Kiausai",
    "wof:placetype":"locality"
},
  "geometry": {"coordinates":[25.21864,55.54241],"type":"Point"}
}