{
  "type": "Feature",
  "properties": {
    "gn:admin1_code":"65",
    "gn:admin2_code":"86.0",
    "gn:asciiname":"Kavaltiske",
    "gn:country_code":"LT",
    "gn:dem":131,
    "gn:feature_class":"P",
    "gn:feature_code":"PPL",
    "gn:name":"Kavalti\u0161k\u0117",
    "gn:population":0,
    "gn:timezone":"Europe/Vilnius",
    "iso:country":"LT",
    "name:lit_x_preferred":[
        "Kavalti\u0161k\u0117"
    ],
    "wof:name":"Kavaltiske",
    "wof:placetype":"locality"
},
  "geometry": {"coordinates":[26.64956,55.20482],"type":"Point"}
}