{
  "type": "Feature",
  "properties": {
    "gn:admin1_code":"64.0",
    "gn:admin2_code":"82.0",
    "gn:asciiname":"Slepeciai",
    "gn:country_code":"LT",
    "gn:dem":182,
    "gn:feature_class":"P",
    "gn:feature_code":"PPL",
    "gn:name":"\u0160lepe\u010diai",
    "gn:population":0,
    "gn:timezone":"Europe/Vilnius",
    "iso:country":"LT",
    "name:lit_x_preferred":[
        "\u0160lepe\u010diai"
    ],
    "wof:name":"Slepeciai",
    "wof:placetype":"locality"
},
  "geometry": {"coordinates":[25.91791,55.58326],"type":"Point"}
}