{
  "type": "Feature",
  "properties": {
    "gn:admin1_code":"65",
    "gn:admin2_code":"13.0",
    "gn:asciiname":"Uosininkai III",
    "gn:country_code":"LT",
    "gn:dem":153,
    "gn:feature_class":"P",
    "gn:feature_code":"PPL",
    "gn:name":"Uosininkai III",
    "gn:population":0,
    "gn:timezone":"Europe/Vilnius",
    "iso:country":"LT",
    "name:lit_x_preferred":[
        "Uosininkai III"
    ],
    "wof:name":"Uosininkai III",
    "wof:placetype":"locality"
},
  "geometry": {"coordinates":[25.60051,54.72071],"type":"Point"}
}