{
  "type": "Feature",
  "properties": {
    "gn:admin1_code":"59.0",
    "gn:admin2_code":"84.0",
    "gn:asciiname":"Bonkiske",
    "gn:country_code":"LT",
    "gn:dem":55,
    "gn:feature_class":"P",
    "gn:feature_code":"PPL",
    "gn:name":"Bonki\u0161k\u0117",
    "gn:population":0,
    "gn:timezone":"Europe/Vilnius",
    "iso:country":"LT",
    "name:und_x_variant":[
        "Bonkishki",
        "Bonki\u0161k\u0117"
    ],
    "wof:name":"Bonkiske",
    "wof:placetype":"locality"
},
  "geometry": {"coordinates":[23.05157,55.07059],"type":"Point"}
}