{
  "type": "Feature",
  "properties": {
    "gn:admin1_code":"61",
    "gn:admin2_code":"54.0",
    "gn:asciiname":"Ringiai",
    "gn:country_code":"LT",
    "gn:dem":185,
    "gn:feature_class":"P",
    "gn:feature_code":"PPL",
    "gn:name":"Ringiai",
    "gn:population":0,
    "gn:timezone":"Europe/Vilnius",
    "iso:country":"LT",
    "name:lit_x_preferred":[
        "Ringiai"
    ],
    "wof:name":"Ringiai",
    "wof:placetype":"locality"
},
  "geometry": {"coordinates":[22.86883,55.69756999999999],"type":"Point"}
}