{
  "type": "Feature",
  "properties": {
    "gn:admin1_code":"64",
    "gn:admin2_code":"62.0",
    "gn:asciiname":"Kunigiskis",
    "gn:country_code":"LT",
    "gn:dem":167,
    "gn:feature_class":"P",
    "gn:feature_code":"PPL",
    "gn:name":"Kunigi\u0161kis",
    "gn:population":0,
    "gn:timezone":"Europe/Vilnius",
    "iso:country":"LT",
    "name:lit_x_preferred":[
        "Kunigi\u0161kis"
    ],
    "wof:name":"Kunigiskis",
    "wof:placetype":"locality"
},
  "geometry": {"coordinates":[25.52079,55.36044],"type":"Point"}
}