{
  "type": "Feature",
  "properties": {
    "gn:admin1_code":"63.0",
    "gn:admin2_code":"78.0",
    "gn:asciiname":"Barstegai",
    "gn:country_code":"LT",
    "gn:dem":168,
    "gn:feature_class":"P",
    "gn:feature_code":"PPL",
    "gn:name":"Barst\u0117gai",
    "gn:population":0,
    "gn:timezone":"Europe/Vilnius",
    "iso:country":"LT",
    "name:und_x_variant":[
        "Borsteygis",
        "Barst\u0117gai"
    ],
    "wof:name":"Barstegai",
    "wof:placetype":"locality"
},
  "geometry": {"coordinates":[22.25731,55.75959],"type":"Point"}
}