{
  "type": "Feature",
  "properties": {
    "gn:admin1_code":"62.0",
    "gn:admin2_code":"87.0",
    "gn:asciiname":"Jucaiciai",
    "gn:country_code":"LT",
    "gn:dem":104,
    "gn:feature_class":"P",
    "gn:feature_code":"PPL",
    "gn:name":"Jucai\u010diai",
    "gn:population":0,
    "gn:timezone":"Europe/Vilnius",
    "iso:country":"LT",
    "name:und_x_variant":[
        "Yutsaychyay",
        "Jucai\u010di\u0173",
        "Jucai\u010diai"
    ],
    "wof:name":"Jucaiciai",
    "wof:placetype":"locality"
},
  "geometry": {"coordinates":[22.1752,55.45196],"type":"Point"}
}