{
  "type": "Feature",
  "properties": {
    "gn:admin1_code":"62.0",
    "gn:admin2_code":"94.0",
    "gn:asciiname":"Pupkaimis",
    "gn:country_code":"LT",
    "gn:dem":51,
    "gn:feature_class":"P",
    "gn:feature_code":"PPL",
    "gn:name":"Pupkaimis",
    "gn:population":0,
    "gn:timezone":"Europe/Vilnius",
    "iso:country":"LT",
    "name:und_x_variant":[
        "Pupkaime",
        "Pupkaymyay",
        "Pupkaimis"
    ],
    "wof:name":"Pupkaimis",
    "wof:placetype":"locality"
},
  "geometry": {"coordinates":[23.1651,55.09564],"type":"Point"}
}