{
  "type": "Feature",
  "properties": {
    "gn:admin1_code":"57",
    "gn:admin2_code":"72.0",
    "gn:asciiname":"Medeksai",
    "gn:country_code":"LT",
    "gn:dem":107,
    "gn:feature_class":"P",
    "gn:feature_code":"PPL",
    "gn:name":"Medek\u0161ai",
    "gn:population":0,
    "gn:timezone":"Europe/Vilnius",
    "iso:country":"LT",
    "name:lit_x_preferred":[
        "Medek\u0161ai"
    ],
    "wof:name":"Medeksai",
    "wof:placetype":"locality"
},
  "geometry": {"coordinates":[23.2112,55.30156],"type":"Point"}
}