{
  "type": "Feature",
  "properties": {
    "gn:admin1_code":"57.0",
    "gn:admin2_code":"53.0",
    "gn:asciiname":"Sviliai",
    "gn:country_code":"LT",
    "gn:dem":57,
    "gn:feature_class":"P",
    "gn:feature_code":"PPL",
    "gn:name":"Sviliai",
    "gn:population":0,
    "gn:timezone":"Europe/Vilnius",
    "iso:country":"LT",
    "name:eng_x_preferred":[
        "Sviliai"
    ],
    "name:rus_x_preferred":[
        "\u0421\u0432\u0438\u043b\u044f\u0439"
    ],
    "name:und_x_variant":[
        "Svili",
        "Svilay",
        "Svilyay",
        "Sviliai"
    ],
    "wof:name":"Sviliai",
    "wof:placetype":"locality"
},
  "geometry": {"coordinates":[23.7955,55.26319],"type":"Point"}
}