{
  "type": "Feature",
  "properties": {
    "gn:admin1_code":"57",
    "gn:admin2_code":"72.0",
    "gn:asciiname":"Skroblyne",
    "gn:country_code":"LT",
    "gn:dem":127,
    "gn:feature_class":"P",
    "gn:feature_code":"PPL",
    "gn:name":"Skroblyn\u0117",
    "gn:population":0,
    "gn:timezone":"Europe/Vilnius",
    "iso:country":"LT",
    "name:lit_x_preferred":[
        "Skroblyn\u0117"
    ],
    "wof:name":"Skroblyne",
    "wof:placetype":"locality"
},
  "geometry": {"coordinates":[22.99889,55.48273],"type":"Point"}
}