{
  "type": "Feature",
  "properties": {
    "gn:admin1_code":"61",
    "gn:admin2_code":"32.0",
    "gn:asciiname":"Kesiai",
    "gn:country_code":"LT",
    "gn:dem":72,
    "gn:feature_class":"P",
    "gn:feature_code":"PPL",
    "gn:name":"Kesiai",
    "gn:population":0,
    "gn:timezone":"Europe/Vilnius",
    "iso:country":"LT",
    "name:lit_x_preferred":[
        "Kesiai"
    ],
    "wof:name":"Kesiai",
    "wof:placetype":"locality"
},
  "geometry": {"coordinates":[22.69876,56.34082],"type":"Point"}
}