{
  "type": "Feature",
  "properties": {
    "gn:admin1_code":"56.0",
    "gn:admin2_code":"11.0",
    "gn:asciiname":"Lelionys",
    "gn:country_code":"LT",
    "gn:dem":184,
    "gn:feature_class":"P",
    "gn:feature_code":"PPL",
    "gn:name":"Lelionys",
    "gn:population":0,
    "gn:timezone":"Europe/Vilnius",
    "iso:country":"LT",
    "name:und_x_variant":[
        "Lelionio",
        "Lelyantsy",
        "Lelionis",
        "Lelionys"
    ],
    "wof:name":"Lelionys",
    "wof:placetype":"locality"
},
  "geometry": {"coordinates":[24.17302,54.4103],"type":"Point"}
}