{
  "type": "Feature",
  "properties": {
    "gn:admin1_code":"62.0",
    "gn:admin2_code":"77.0",
    "gn:asciiname":"Uzbudupis",
    "gn:country_code":"LT",
    "gn:dem":58,
    "gn:feature_class":"P",
    "gn:feature_code":"PPL",
    "gn:name":"U\u017eb\u016bdupis",
    "gn:population":0,
    "gn:timezone":"Europe/Vilnius",
    "iso:country":"LT",
    "name:und_x_variant":[
        "Uzhbudupe",
        "U\u017eb\u016bdupis"
    ],
    "wof:name":"Uzbudupis",
    "wof:placetype":"locality"
},
  "geometry": {"coordinates":[22.26396,55.35182],"type":"Point"}
}