{
  "type": "Feature",
  "properties": {
    "gn:admin1_code":"64",
    "gn:admin2_code":"62.0",
    "gn:asciiname":"Raukuciai",
    "gn:country_code":"LT",
    "gn:dem":165,
    "gn:feature_class":"P",
    "gn:feature_code":"PPL",
    "gn:name":"Rauku\u010diai",
    "gn:population":0,
    "gn:timezone":"Europe/Vilnius",
    "iso:country":"LT",
    "name:lit_x_preferred":[
        "Rauku\u010diai"
    ],
    "wof:name":"Raukuciai",
    "wof:placetype":"locality"
},
  "geometry": {"coordinates":[25.49937000000001,55.18994],"type":"Point"}
}