{
  "type": "Feature",
  "properties": {
    "gn:admin1_code":"65.0",
    "gn:admin2_code":"42.0",
    "gn:asciiname":"Kalniniai Mijaugonys",
    "gn:country_code":"LT",
    "gn:dem":122,
    "gn:feature_class":"P",
    "gn:feature_code":"PPL",
    "gn:name":"Kalniniai Mijaugonys",
    "gn:population":0,
    "gn:timezone":"Europe/Vilnius",
    "iso:country":"LT",
    "name:und_x_variant":[
        "Kalniny",
        "Kalniniai Mijaugonys",
        "Miyaugonis",
        "Mijaugonys",
        "Mijaugoni\u0173",
        "Mijaugonio",
        "Lap\u0117nai"
    ],
    "wof:name":"Kalniniai Mijaugonys",
    "wof:placetype":"locality"
},
  "geometry": {"coordinates":[24.62039,54.79954],"type":"Point"}
}