{
  "type": "Feature",
  "properties": {
    "gn:admin1_code":"62.0",
    "gn:admin2_code":"77.0",
    "gn:asciiname":"Gervieciai",
    "gn:country_code":"LT",
    "gn:dem":59,
    "gn:feature_class":"P",
    "gn:feature_code":"PPL",
    "gn:name":"Gervie\u010diai",
    "gn:population":0,
    "gn:timezone":"Europe/Vilnius",
    "iso:country":"LT",
    "name:und_x_variant":[
        "Gervichyay",
        "Gervie\u010di\u0173",
        "Gervie\u010diai"
    ],
    "wof:name":"Gervieciai",
    "wof:placetype":"locality"
},
  "geometry": {"coordinates":[22.48935,55.34566],"type":"Point"}
}