{
  "type": "Feature",
  "properties": {
    "gn:admin1_code":"57",
    "gn:admin2_code":"53.0",
    "gn:asciiname":"Pamiskes",
    "gn:country_code":"LT",
    "gn:dem":80,
    "gn:feature_class":"P",
    "gn:feature_code":"PPL",
    "gn:name":"Pami\u0161k\u0117s",
    "gn:population":0,
    "gn:timezone":"Europe/Vilnius",
    "iso:country":"LT",
    "name:lit_x_preferred":[
        "Pami\u0161k\u0117s"
    ],
    "wof:name":"Pamiskes",
    "wof:placetype":"locality"
},
  "geometry": {"coordinates":[23.85626,55.48778000000001],"type":"Point"}
}