{
  "type": "Feature",
  "properties": {
    "gn:admin1_code":"64",
    "gn:admin2_code":"45.0",
    "gn:asciiname":"Kuzmiske",
    "gn:country_code":"LT",
    "gn:dem":149,
    "gn:feature_class":"P",
    "gn:feature_code":"PPL",
    "gn:name":"Kuzmi\u0161k\u0117",
    "gn:population":0,
    "gn:timezone":"Europe/Vilnius",
    "iso:country":"LT",
    "name:lit_x_preferred":[
        "Kuzmi\u0161k\u0117"
    ],
    "wof:name":"Kuzmiske",
    "wof:placetype":"locality"
},
  "geometry": {"coordinates":[26.35578,55.51555],"type":"Point"}
}