{
  "type": "Feature",
  "properties": {
    "gn:admin1_code":"56.0",
    "gn:admin2_code":"11.0",
    "gn:asciiname":"Kabines",
    "gn:country_code":"LT",
    "gn:dem":76,
    "gn:feature_class":"P",
    "gn:feature_code":"PPL",
    "gn:name":"Kabin\u0117s",
    "gn:population":0,
    "gn:timezone":"Europe/Vilnius",
    "iso:country":"LT",
    "name:und_x_variant":[
        "Kabiny",
        "Kabin\u0117s"
    ],
    "wof:name":"Kabines",
    "wof:placetype":"locality"
},
  "geometry": {"coordinates":[23.92807,54.43634],"type":"Point"}
}