{
  "type": "Feature",
  "properties": {
    "gn:admin1_code":"59",
    "gn:admin2_code":"18.0",
    "gn:asciiname":"Leiciskiai",
    "gn:country_code":"LT",
    "gn:dem":102,
    "gn:feature_class":"P",
    "gn:feature_code":"PPL",
    "gn:name":"Leici\u0161kiai",
    "gn:population":0,
    "gn:timezone":"Europe/Vilnius",
    "iso:country":"LT",
    "name:lit_x_preferred":[
        "Leici\u0161kiai"
    ],
    "wof:name":"Leiciskiai",
    "wof:placetype":"locality"
},
  "geometry": {"coordinates":[23.67578,54.52775],"type":"Point"}
}