{
  "type": "Feature",
  "properties": {
    "gn:admin1_code":"57",
    "gn:admin2_code":"19.0",
    "gn:asciiname":"Romainiu Kaimele",
    "gn:country_code":"LT",
    "gn:dem":65,
    "gn:feature_class":"P",
    "gn:feature_code":"PPL",
    "gn:name":"Romaini\u0173 Kaimel\u0117",
    "gn:population":0,
    "gn:timezone":"Europe/Vilnius",
    "iso:country":"LT",
    "name:lit_x_preferred":[
        "Romaini\u0173 Kaimel\u0117"
    ],
    "wof:name":"Romainiu Kaimele",
    "wof:placetype":"locality"
},
  "geometry": {"coordinates":[23.80907,54.95206],"type":"Point"}
}