{
  "type": "Feature",
  "properties": {
    "iso:country":"LT",
    "wof:name":"Skansenas",
    "wof:placetype":"neighbourhood"
},
  "geometry": {"coordinates":[25.27843518242175,54.70043835089927],"type":"Point"}
}