{
  "type": "Feature",
  "properties": {
    "gn:admin1_code":"59",
    "gn:admin2_code":"48.0",
    "gn:asciiname":"Ukazupka",
    "gn:country_code":"LT",
    "gn:dem":185,
    "gn:feature_class":"P",
    "gn:feature_code":"PPL",
    "gn:name":"Ukazupka",
    "gn:population":0,
    "gn:timezone":"Europe/Vilnius",
    "iso:country":"LT",
    "name:lit_x_preferred":[
        "Ukazupka"
    ],
    "wof:name":"Ukazupka",
    "wof:placetype":"locality"
},
  "geometry": {"coordinates":[23.0874,54.44244000000001],"type":"Point"}
}