{
  "type": "Feature",
  "properties": {
    "gn:admin1_code":"64",
    "gn:admin2_code":"34.0",
    "gn:asciiname":"Jakunai",
    "gn:country_code":"LT",
    "gn:dem":88,
    "gn:feature_class":"P",
    "gn:feature_code":"PPL",
    "gn:name":"Jak\u016bnai",
    "gn:population":0,
    "gn:timezone":"Europe/Vilnius",
    "iso:country":"LT",
    "name:lit_x_preferred":[
        "Jak\u016bnai"
    ],
    "wof:name":"Jakunai",
    "wof:placetype":"locality"
},
  "geometry": {"coordinates":[24.85061,55.41233],"type":"Point"}
}