{
  "type": "Feature",
  "properties": {
    "gn:admin1_code":"63",
    "gn:admin2_code":"61.0",
    "gn:asciiname":"Palaizupe",
    "gn:country_code":"LT",
    "gn:dem":83,
    "gn:feature_class":"P",
    "gn:feature_code":"PPL",
    "gn:name":"Palai\u017eup\u0117",
    "gn:population":0,
    "gn:timezone":"Europe/Vilnius",
    "iso:country":"LT",
    "name:lit_x_preferred":[
        "Palai\u017eup\u0117"
    ],
    "wof:name":"Palaizupe",
    "wof:placetype":"locality"
},
  "geometry": {"coordinates":[22.53482,56.35412],"type":"Point"}
}