{
  "type": "Feature",
  "properties": {
    "gn:admin1_code":"64",
    "gn:admin2_code":"34.0",
    "gn:asciiname":"Gerkiskiai",
    "gn:country_code":"LT",
    "gn:dem":99,
    "gn:feature_class":"P",
    "gn:feature_code":"PPL",
    "gn:name":"Gerki\u0161kiai",
    "gn:population":0,
    "gn:timezone":"Europe/Vilnius",
    "iso:country":"LT",
    "name:lit_x_preferred":[
        "Gerki\u0161kiai"
    ],
    "wof:name":"Gerkiskiai",
    "wof:placetype":"locality"
},
  "geometry": {"coordinates":[24.9325,55.62594],"type":"Point"}
}