{
  "type": "Feature",
  "properties": {
    "gn:admin1_code":"64",
    "gn:admin2_code":"45.0",
    "gn:asciiname":"Tarosauka",
    "gn:country_code":"LT",
    "gn:dem":177,
    "gn:feature_class":"P",
    "gn:feature_code":"PPL",
    "gn:name":"Tarosauka",
    "gn:population":0,
    "gn:timezone":"Europe/Vilnius",
    "iso:country":"LT",
    "name:lit_x_preferred":[
        "Tarosauka"
    ],
    "wof:name":"Tarosauka",
    "wof:placetype":"locality"
},
  "geometry": {"coordinates":[26.32353,55.23266],"type":"Point"}
}