{
  "type": "Feature",
  "properties": {
    "gn:admin1_code":"64",
    "gn:admin2_code":"82.0",
    "gn:asciiname":"Pilveliai",
    "gn:country_code":"LT",
    "gn:dem":134,
    "gn:feature_class":"P",
    "gn:feature_code":"PPL",
    "gn:name":"Pilveliai",
    "gn:population":0,
    "gn:timezone":"Europe/Vilnius",
    "iso:country":"LT",
    "name:lit_x_preferred":[
        "Pilveliai"
    ],
    "wof:name":"Pilveliai",
    "wof:placetype":"locality"
},
  "geometry": {"coordinates":[25.59099,55.57559000000001],"type":"Point"}
}