{
  "type": "Feature",
  "properties": {
    "gn:admin1_code":"57",
    "gn:admin2_code":"53.0",
    "gn:asciiname":"Aristavele",
    "gn:country_code":"LT",
    "gn:dem":46,
    "gn:feature_class":"P",
    "gn:feature_code":"PPL",
    "gn:name":"Aristav\u0117l\u0117",
    "gn:population":0,
    "gn:timezone":"Europe/Vilnius",
    "iso:country":"LT",
    "name:lit_x_preferred":[
        "Aristav\u0117l\u0117"
    ],
    "wof:name":"Aristavele",
    "wof:placetype":"locality"
},
  "geometry": {"coordinates":[24.06599,55.28982],"type":"Point"}
}