{
  "type": "Feature",
  "properties": {
    "gn:admin1_code":"58.0",
    "gn:admin2_code":"56.0",
    "gn:asciiname":"Zadeikiai",
    "gn:country_code":"LT",
    "gn:dem":45,
    "gn:feature_class":"P",
    "gn:feature_code":"PPL",
    "gn:name":"\u017dadeikiai",
    "gn:population":0,
    "gn:timezone":"Europe/Vilnius",
    "iso:country":"LT",
    "name:lit_x_preferred":[
        "\u017dadeikiai"
    ],
    "name:und_x_variant":[
        "Zhidenkay",
        "\u017dadeikai"
    ],
    "wof:name":"Zadeikiai",
    "wof:placetype":"locality"
},
  "geometry": {"coordinates":[21.43504,55.92491999999999],"type":"Point"}
}