{
  "type": "Feature",
  "properties": {
    "gn:admin1_code":"65",
    "gn:admin2_code":"85.0",
    "gn:asciiname":"Deguskes",
    "gn:country_code":"LT",
    "gn:dem":172,
    "gn:feature_class":"P",
    "gn:feature_code":"PPL",
    "gn:name":"Degu\u0161k\u0117s",
    "gn:population":0,
    "gn:timezone":"Europe/Vilnius",
    "iso:country":"LT",
    "name:lit_x_preferred":[
        "Degu\u0161k\u0117s"
    ],
    "wof:name":"Deguskes",
    "wof:placetype":"locality"
},
  "geometry": {"coordinates":[25.35478,54.44801],"type":"Point"}
}