{
  "type": "Feature",
  "properties": {
    "gn:admin1_code":"62.0",
    "gn:admin2_code":"94.0",
    "gn:asciiname":"Daugeliskiai",
    "gn:country_code":"LT",
    "gn:dem":70,
    "gn:feature_class":"P",
    "gn:feature_code":"PPL",
    "gn:name":"Daugeli\u0161kiai",
    "gn:population":0,
    "gn:timezone":"Europe/Vilnius",
    "iso:country":"LT",
    "name:und_x_variant":[
        "Lesnyye Uvoloki",
        "Daugelishki",
        "Daugeli\u0161kiai"
    ],
    "wof:name":"Daugeliskiai",
    "wof:placetype":"locality"
},
  "geometry": {"coordinates":[23.39784,55.16902],"type":"Point"}
}