{
  "type": "Feature",
  "properties": {
    "gn:admin1_code":"60.0",
    "gn:admin2_code":"67.0",
    "gn:asciiname":"Daujenai",
    "gn:country_code":"LT",
    "gn:dem":67,
    "gn:feature_class":"P",
    "gn:feature_code":"PPL",
    "gn:name":"Dauj\u0117nai",
    "gn:population":0,
    "gn:timezone":"Europe/Vilnius",
    "iso:country":"LT",
    "name:ceb_x_preferred":[
        "Dauj\u0117nai"
    ],
    "name:eng_x_preferred":[
        "Dauj\u0117nai"
    ],
    "name:est_x_preferred":[
        "Dauj\u0117nai"
    ],
    "name:lit_x_preferred":[
        "Dauj\u0117nai"
    ],
    "name:nld_x_preferred":[
        "Dauj\u0117nai"
    ],
    "name:pol_x_preferred":[
        "Dowiany"
    ],
    "name:rus_x_preferred":[
        "\u0414\u0430\u0443\u0435\u043d\u0430\u0439"
    ],
    "name:swe_x_preferred":[
        "Dauj\u0117nai"
    ],
    "name:und_x_variant":[
        "Dauj\u0117n\u0173",
        "Dauyenay"
    ],
    "wof:name":"Daujenai",
    "wof:placetype":"locality"
},
  "geometry": {"coordinates":[24.51735,55.97505],"type":"Point"}
}