{
  "type": "Feature",
  "properties": {
    "gn:admin1_code":"65",
    "gn:admin2_code":"13.0",
    "gn:asciiname":"Slabadka",
    "gn:country_code":"LT",
    "gn:dem":242,
    "gn:feature_class":"P",
    "gn:feature_code":"PPL",
    "gn:name":"Slabadka",
    "gn:population":0,
    "gn:timezone":"Europe/Vilnius",
    "iso:country":"LT",
    "name:lit_x_preferred":[
        "Slabadka"
    ],
    "wof:name":"Slabadka",
    "wof:placetype":"locality"
},
  "geometry": {"coordinates":[25.67879,54.56707],"type":"Point"}
}