{
  "type": "Feature",
  "properties": {
    "gn:admin1_code":"60",
    "gn:admin2_code":"57.0",
    "gn:asciiname":"Kirdiskis",
    "gn:country_code":"LT",
    "gn:dem":86,
    "gn:feature_class":"P",
    "gn:feature_code":"PPL",
    "gn:name":"Kirdi\u0161kis",
    "gn:population":0,
    "gn:timezone":"Europe/Vilnius",
    "iso:country":"LT",
    "name:lit_x_preferred":[
        "Kirdi\u0161kis"
    ],
    "wof:name":"Kirdiskis",
    "wof:placetype":"locality"
},
  "geometry": {"coordinates":[24.83423,55.83088000000001],"type":"Point"}
}