{
  "type": "Feature",
  "properties": {
    "gn:admin1_code":"65",
    "gn:admin2_code":"81.0",
    "gn:asciiname":"Varine",
    "gn:country_code":"LT",
    "gn:dem":81,
    "gn:feature_class":"P",
    "gn:feature_code":"PPL",
    "gn:name":"Varin\u0117",
    "gn:population":0,
    "gn:timezone":"Europe/Vilnius",
    "iso:country":"LT",
    "name:fra_x_preferred":[
        "Varine"
    ],
    "name:lit_x_preferred":[
        "Varin\u0117"
    ],
    "name:ron_x_preferred":[
        "Varine"
    ],
    "name:slv_x_preferred":[
        "Varine"
    ],
    "name:srp_x_preferred":[
        "\u0412\u0430\u0440\u0438\u043d\u0435"
    ],
    "wof:name":"Varine",
    "wof:placetype":"locality"
},
  "geometry": {"coordinates":[24.78754,55.21073000000001],"type":"Point"}
}