{
  "type": "Feature",
  "properties": {
    "gn:admin1_code":"57",
    "gn:admin2_code":"49.0",
    "gn:asciiname":"Piktakiemis",
    "gn:country_code":"LT",
    "gn:dem":141,
    "gn:feature_class":"P",
    "gn:feature_code":"PPL",
    "gn:name":"Piktakiemis",
    "gn:population":0,
    "gn:timezone":"Europe/Vilnius",
    "iso:country":"LT",
    "name:lit_x_preferred":[
        "Piktakiemis"
    ],
    "wof:name":"Piktakiemis",
    "wof:placetype":"locality"
},
  "geometry": {"coordinates":[24.53968,54.74789000000001],"type":"Point"}
}