{
  "type": "Feature",
  "properties": {
    "gn:admin1_code":"59.0",
    "gn:admin2_code":"84.0",
    "gn:asciiname":"Bubleliai",
    "gn:country_code":"LT",
    "gn:dem":40,
    "gn:feature_class":"P",
    "gn:feature_code":"PPL",
    "gn:name":"B\u016bbleliai",
    "gn:population":0,
    "gn:timezone":"Europe/Vilnius",
    "iso:country":"LT",
    "name:lit_x_preferred":[
        "B\u016bbleliai"
    ],
    "name:und_x_variant":[
        "Bublelyay",
        "Bubteli\u0173",
        "Bubleliai"
    ],
    "wof:name":"Bubleliai",
    "wof:placetype":"locality"
},
  "geometry": {"coordinates":[22.91317,54.81021],"type":"Point"}
}