{
  "type": "Feature",
  "properties": {
    "gn:admin1_code":"64",
    "gn:admin2_code":"43.0",
    "gn:asciiname":"Vilkiskes",
    "gn:country_code":"LT",
    "gn:dem":174,
    "gn:feature_class":"P",
    "gn:feature_code":"PPL",
    "gn:name":"Vilki\u0161k\u0117s",
    "gn:population":0,
    "gn:timezone":"Europe/Vilnius",
    "iso:country":"LT",
    "name:lit_x_preferred":[
        "Vilki\u0161k\u0117s"
    ],
    "wof:name":"Vilkiskes",
    "wof:placetype":"locality"
},
  "geometry": {"coordinates":[25.93689,55.68881999999999],"type":"Point"}
}