{
  "type": "Feature",
  "properties": {
    "gn:admin1_code":"64",
    "gn:admin2_code":"43.0",
    "gn:asciiname":"Ilgasilis",
    "gn:country_code":"LT",
    "gn:dem":106,
    "gn:feature_class":"P",
    "gn:feature_code":"PPL",
    "gn:name":"Ilga\u0161ilis",
    "gn:population":0,
    "gn:timezone":"Europe/Vilnius",
    "iso:country":"LT",
    "name:lit_x_preferred":[
        "Ilga\u0161ilis"
    ],
    "wof:name":"Ilgasilis",
    "wof:placetype":"locality"
},
  "geometry": {"coordinates":[25.87711,55.79158],"type":"Point"}
}