{
  "type": "Feature",
  "properties": {
    "gn:admin1_code":"57",
    "gn:admin2_code":"49.0",
    "gn:asciiname":"Grauzai",
    "gn:country_code":"LT",
    "gn:dem":136,
    "gn:feature_class":"P",
    "gn:feature_code":"PPL",
    "gn:name":"Grau\u017eai",
    "gn:population":0,
    "gn:timezone":"Europe/Vilnius",
    "iso:country":"LT",
    "name:lit_x_preferred":[
        "Grau\u017eai"
    ],
    "wof:name":"Grauzai",
    "wof:placetype":"locality"
},
  "geometry": {"coordinates":[24.5047,54.77052],"type":"Point"}
}