{
  "type": "Feature",
  "properties": {
    "iso:country":"LT",
    "name:lit_x_preferred":[
        "Perk\u016bnkiemis"
    ],
    "wof:name":"Perkunkiemis",
    "wof:placetype":"neighbourhood"
},
  "geometry": {"coordinates":[25.21972696196459,54.73874251584609],"type":"Point"}
}