{
  "type": "Feature",
  "properties": {
    "gn:admin1_code":"57",
    "gn:admin2_code":"49.0",
    "gn:asciiname":"Litviniskes",
    "gn:country_code":"LT",
    "gn:dem":54,
    "gn:feature_class":"P",
    "gn:feature_code":"PPL",
    "gn:name":"Litvini\u0161k\u0117s",
    "gn:population":0,
    "gn:timezone":"Europe/Vilnius",
    "iso:country":"LT",
    "name:lit_x_preferred":[
        "Litvini\u0161k\u0117s"
    ],
    "wof:name":"Litviniskes",
    "wof:placetype":"locality"
},
  "geometry": {"coordinates":[24.63329,54.95506999999999],"type":"Point"}
}