{
  "type": "Feature",
  "properties": {
    "gn:admin1_code":"59",
    "gn:admin2_code":"18.0",
    "gn:asciiname":"Santaka",
    "gn:country_code":"LT",
    "gn:dem":99,
    "gn:feature_class":"P",
    "gn:feature_code":"PPL",
    "gn:name":"Santaka",
    "gn:population":0,
    "gn:timezone":"Europe/Vilnius",
    "iso:country":"LT",
    "name:lit_x_preferred":[
        "Santaka"
    ],
    "wof:name":"Santaka",
    "wof:placetype":"locality"
},
  "geometry": {"coordinates":[23.59126,54.58135],"type":"Point"}
}