{
  "type": "Feature",
  "properties": {
    "gn:admin1_code":"60.0",
    "gn:admin2_code":"67.0",
    "gn:asciiname":"Daiciunai",
    "gn:country_code":"LT",
    "gn:dem":41,
    "gn:feature_class":"P",
    "gn:feature_code":"PPL",
    "gn:name":"Dai\u010di\u016bnai",
    "gn:population":0,
    "gn:timezone":"Europe/Vilnius",
    "iso:country":"LT",
    "name:und_x_variant":[
        "Daychyunay",
        "Dai\u010di\u016bnai"
    ],
    "wof:name":"Daiciunai",
    "wof:placetype":"locality"
},
  "geometry": {"coordinates":[24.21918,56.18663000000001],"type":"Point"}
}