{
  "type": "Feature",
  "properties": {
    "gn:admin1_code":"59",
    "gn:admin2_code":"39.0",
    "gn:asciiname":"Paikiai",
    "gn:country_code":"LT",
    "gn:dem":69,
    "gn:feature_class":"P",
    "gn:feature_code":"PPL",
    "gn:name":"Paikiai",
    "gn:population":0,
    "gn:timezone":"Europe/Vilnius",
    "iso:country":"LT",
    "name:lit_x_preferred":[
        "Paikiai"
    ],
    "wof:name":"Paikiai",
    "wof:placetype":"locality"
},
  "geometry": {"coordinates":[23.23099,54.58389],"type":"Point"}
}