{
  "type": "Feature",
  "properties": {
    "gn:admin1_code":"57",
    "gn:admin2_code":"72.0",
    "gn:asciiname":"Burbiskiai",
    "gn:country_code":"LT",
    "gn:dem":96,
    "gn:feature_class":"P",
    "gn:feature_code":"PPL",
    "gn:name":"Burbi\u0161kiai",
    "gn:population":0,
    "gn:timezone":"Europe/Vilnius",
    "iso:country":"LT",
    "name:lit_x_preferred":[
        "Burbi\u0161kiai"
    ],
    "wof:name":"Burbiskiai",
    "wof:placetype":"locality"
},
  "geometry": {"coordinates":[23.34764,55.37066],"type":"Point"}
}