{
  "type": "Feature",
  "properties": {
    "gn:admin1_code":"65",
    "gn:admin2_code":"85.0",
    "gn:asciiname":"Matuizos",
    "gn:country_code":"LT",
    "gn:dem":146,
    "gn:feature_class":"P",
    "gn:feature_code":"PPL",
    "gn:name":"Matuizos",
    "gn:population":0,
    "gn:timezone":"Europe/Vilnius",
    "iso:country":"LT",
    "name:lit_x_preferred":[
        "Matuizos"
    ],
    "wof:name":"Matuizos",
    "wof:placetype":"locality"
},
  "geometry": {"coordinates":[24.87006,54.23257],"type":"Point"}
}