{
  "type": "Feature",
  "properties": {
    "gn:admin1_code":"65",
    "gn:admin2_code":"13.0",
    "gn:asciiname":"Petesa",
    "gn:country_code":"LT",
    "gn:dem":162,
    "gn:feature_class":"P",
    "gn:feature_code":"PPL",
    "gn:name":"Pete\u0161a",
    "gn:population":0,
    "gn:timezone":"Europe/Vilnius",
    "iso:country":"LT",
    "name:lit_x_preferred":[
        "Pete\u0161a"
    ],
    "wof:name":"Petesa",
    "wof:placetype":"locality"
},
  "geometry": {"coordinates":[25.34774,54.56482],"type":"Point"}
}