{
  "type": "Feature",
  "properties": {
    "gn:admin1_code":"63.0",
    "gn:admin2_code":"68.0",
    "gn:asciiname":"Godeliai",
    "gn:country_code":"LT",
    "gn:dem":110,
    "gn:feature_class":"P",
    "gn:feature_code":"PPL",
    "gn:name":"Godeliai",
    "gn:population":0,
    "gn:timezone":"Europe/Vilnius",
    "iso:country":"LT",
    "name:und_x_variant":[
        "Godeli\u0173",
        "Gudeley",
        "Godeliai"
    ],
    "wof:name":"Godeliai",
    "wof:placetype":"locality"
},
  "geometry": {"coordinates":[21.77635,55.98941],"type":"Point"}
}