{
  "type": "Feature",
  "properties": {
    "iso:country":"LT",
    "name:lit_x_preferred":[
        "Dvaryk\u0161\u010diai"
    ],
    "wof:name":"Dvaryksciai",
    "wof:placetype":"neighbourhood"
},
  "geometry": {"coordinates":[25.32672927410383,54.78346196973896],"type":"Point"}
}