{
  "type": "Feature",
  "properties": {
    "gn:admin1_code":"64",
    "gn:admin2_code":"34.0",
    "gn:asciiname":"Kirkiliskiai",
    "gn:country_code":"LT",
    "gn:dem":111,
    "gn:feature_class":"P",
    "gn:feature_code":"PPL",
    "gn:name":"Kirkili\u0161kiai",
    "gn:population":0,
    "gn:timezone":"Europe/Vilnius",
    "iso:country":"LT",
    "name:lit_x_preferred":[
        "Kirkili\u0161kiai"
    ],
    "wof:name":"Kirkiliskiai",
    "wof:placetype":"locality"
},
  "geometry": {"coordinates":[25.08029,55.4507],"type":"Point"}
}