{
  "type": "Feature",
  "properties": {
    "gn:admin1_code":"61",
    "gn:admin2_code":"32.0",
    "gn:asciiname":"Keidai",
    "gn:country_code":"LT",
    "gn:dem":73,
    "gn:feature_class":"P",
    "gn:feature_code":"PPL",
    "gn:name":"Keidai",
    "gn:population":0,
    "gn:timezone":"Europe/Vilnius",
    "iso:country":"LT",
    "name:lit_x_preferred":[
        "Keidai"
    ],
    "wof:name":"Keidai",
    "wof:placetype":"locality"
},
  "geometry": {"coordinates":[22.9518,56.27864],"type":"Point"}
}