{
  "type": "Feature",
  "properties": {
    "gn:admin1_code":"61.0",
    "gn:admin2_code":"71.0",
    "gn:asciiname":"Pypliai",
    "gn:country_code":"LT",
    "gn:dem":104,
    "gn:feature_class":"P",
    "gn:feature_code":"PPL",
    "gn:name":"Pypliai",
    "gn:population":0,
    "gn:timezone":"Europe/Vilnius",
    "iso:country":"LT",
    "name:und_x_variant":[
        "Pili",
        "Piplyay",
        "Pypliai"
    ],
    "wof:name":"Pypliai",
    "wof:placetype":"locality"
},
  "geometry": {"coordinates":[23.63387,55.52381],"type":"Point"}
}