{
  "type": "Feature",
  "properties": {
    "gn:admin1_code":"62.0",
    "gn:admin2_code":"77.0",
    "gn:asciiname":"Ringaliai",
    "gn:country_code":"LT",
    "gn:dem":114,
    "gn:feature_class":"P",
    "gn:feature_code":"PPL",
    "gn:name":"Ringaliai",
    "gn:population":0,
    "gn:timezone":"Europe/Vilnius",
    "iso:country":"LT",
    "name:und_x_variant":[
        "Ringali\u0173",
        "Ringalyay",
        "Ringaliai"
    ],
    "wof:name":"Ringaliai",
    "wof:placetype":"locality"
},
  "geometry": {"coordinates":[22.36203,55.4224],"type":"Point"}
}