{
  "type": "Feature",
  "properties": {
    "gn:admin1_code":"64",
    "gn:admin2_code":"82.0",
    "gn:asciiname":"Alksniskes",
    "gn:country_code":"LT",
    "gn:dem":178,
    "gn:feature_class":"P",
    "gn:feature_code":"PPL",
    "gn:name":"Alksni\u0161k\u0117s",
    "gn:population":0,
    "gn:timezone":"Europe/Vilnius",
    "iso:country":"LT",
    "name:lit_x_preferred":[
        "Alksni\u0161k\u0117s"
    ],
    "wof:name":"Alksniskes",
    "wof:placetype":"locality"
},
  "geometry": {"coordinates":[25.87449,55.47988],"type":"Point"}
}