{
  "type": "Feature",
  "properties": {
    "gn:admin1_code":"61.0",
    "gn:admin2_code":"65.0",
    "gn:asciiname":"Starkoniai",
    "gn:country_code":"LT",
    "gn:dem":60,
    "gn:feature_class":"P",
    "gn:feature_code":"PPL",
    "gn:name":"Starkoniai",
    "gn:population":0,
    "gn:timezone":"Europe/Vilnius",
    "iso:country":"LT",
    "name:und_x_variant":[
        "Starkonyay",
        "Starkoniai"
    ],
    "wof:name":"Starkoniai",
    "wof:placetype":"locality"
},
  "geometry": {"coordinates":[23.77992,56.11125],"type":"Point"}
}