{
  "type": "Feature",
  "properties": {
    "gn:admin1_code":"61",
    "gn:admin2_code":"54.0",
    "gn:asciiname":"Vares",
    "gn:country_code":"LT",
    "gn:dem":119,
    "gn:feature_class":"P",
    "gn:feature_code":"PPL",
    "gn:name":"Var\u0117s",
    "gn:population":0,
    "gn:timezone":"Europe/Vilnius",
    "iso:country":"LT",
    "name:ceb_x_preferred":[
        "Vares"
    ],
    "name:deu_x_preferred":[
        "Vares"
    ],
    "name:fin_x_preferred":[
        "Vares"
    ],
    "name:ita_x_preferred":[
        "Vares"
    ],
    "name:lit_x_preferred":[
        "Var\u0117s"
    ],
    "name:nld_x_preferred":[
        "Vares"
    ],
    "name:swe_x_preferred":[
        "Vares"
    ],
    "wof:name":"Vares",
    "wof:placetype":"locality"
},
  "geometry": {"coordinates":[22.96166,55.62967],"type":"Point"}
}