{
  "type": "Feature",
  "properties": {
    "gn:admin1_code":"64",
    "gn:admin2_code":"34.0",
    "gn:asciiname":"Vajesiai",
    "gn:country_code":"LT",
    "gn:dem":139,
    "gn:feature_class":"P",
    "gn:feature_code":"PPL",
    "gn:name":"Vaj\u0117\u0161iai",
    "gn:population":0,
    "gn:timezone":"Europe/Vilnius",
    "iso:country":"LT",
    "name:lit_x_preferred":[
        "Vaj\u0117\u0161iai"
    ],
    "wof:name":"Vajesiai",
    "wof:placetype":"locality"
},
  "geometry": {"coordinates":[25.23804,55.55339],"type":"Point"}
}