{
  "type": "Feature",
  "properties": {
    "gn:admin1_code":"57",
    "gn:admin2_code":"46.0",
    "gn:asciiname":"Palokis II",
    "gn:country_code":"LT",
    "gn:dem":69,
    "gn:feature_class":"P",
    "gn:feature_code":"PPL",
    "gn:name":"Palokis II",
    "gn:population":0,
    "gn:timezone":"Europe/Vilnius",
    "iso:country":"LT",
    "name:lit_x_preferred":[
        "Palokis II"
    ],
    "wof:name":"Palokis II",
    "wof:placetype":"locality"
},
  "geometry": {"coordinates":[24.37445,55.12608],"type":"Point"}
}