{
  "type": "Feature",
  "properties": {
    "gn:admin1_code":"56.0",
    "gn:admin2_code":"38.0",
    "gn:asciiname":"Jurgiskes",
    "gn:country_code":"LT",
    "gn:dem":146,
    "gn:feature_class":"P",
    "gn:feature_code":"PPL",
    "gn:name":"Jurgi\u0161k\u0117s",
    "gn:population":0,
    "gn:timezone":"Europe/Vilnius",
    "iso:country":"LT",
    "name:und_x_variant":[
        "Jurgi\u0161k\u0117s"
    ],
    "wof:name":"Jurgiskes",
    "wof:placetype":"locality"
},
  "geometry": {"coordinates":[24.73256,54.2664],"type":"Point"}
}