{
  "type": "Feature",
  "properties": {
    "gn:admin1_code":"64",
    "gn:admin2_code":"82.0",
    "gn:asciiname":"Avizieniskis",
    "gn:country_code":"LT",
    "gn:dem":184,
    "gn:feature_class":"P",
    "gn:feature_code":"PPL",
    "gn:name":"Avi\u017eieni\u0161kis",
    "gn:population":0,
    "gn:timezone":"Europe/Vilnius",
    "iso:country":"LT",
    "name:lit_x_preferred":[
        "Avi\u017eieni\u0161kis"
    ],
    "wof:name":"Avizieniskis",
    "wof:placetype":"locality"
},
  "geometry": {"coordinates":[25.78316,55.43338000000001],"type":"Point"}
}