{
  "type": "Feature",
  "properties": {
    "gn:admin1_code":"57",
    "gn:admin2_code":"72.0",
    "gn:asciiname":"Rekosaiciai",
    "gn:country_code":"LT",
    "gn:dem":128,
    "gn:feature_class":"P",
    "gn:feature_code":"PPL",
    "gn:name":"Reko\u0161ai\u010diai",
    "gn:population":0,
    "gn:timezone":"Europe/Vilnius",
    "iso:country":"LT",
    "name:lit_x_preferred":[
        "Reko\u0161ai\u010diai"
    ],
    "wof:name":"Rekosaiciai",
    "wof:placetype":"locality"
},
  "geometry": {"coordinates":[22.70182,55.44738],"type":"Point"}
}