{
  "type": "Feature",
  "properties": {
    "gn:admin1_code":"57",
    "gn:admin2_code":"72.0",
    "gn:asciiname":"Medeksine",
    "gn:country_code":"LT",
    "gn:dem":81,
    "gn:feature_class":"P",
    "gn:feature_code":"PPL",
    "gn:name":"Medek\u0161in\u0117",
    "gn:population":0,
    "gn:timezone":"Europe/Vilnius",
    "iso:country":"LT",
    "name:lit_x_preferred":[
        "Medek\u0161in\u0117"
    ],
    "wof:name":"Medeksine",
    "wof:placetype":"locality"
},
  "geometry": {"coordinates":[22.79403,55.40311],"type":"Point"}
}