{
  "type": "Feature",
  "properties": {
    "iso:country":"LT",
    "name:ceb_x_preferred":[
        "Pa\u0161ilai\u010diai"
    ],
    "name:dan_x_preferred":[
        "Pa\u0161ilai\u010diai"
    ],
    "name:deu_x_preferred":[
        "Pa\u0161ilai\u010diai"
    ],
    "name:eng_x_preferred":[
        "Pa\u0161ilai\u010diai eldership"
    ],
    "name:lit_x_preferred":[
        "Pa\u0161ilai\u010di\u0173 seni\u016bnija"
    ],
    "name:lit_x_variant":[
        "Pa\u0161ilai\u010diai"
    ],
    "name:pol_x_preferred":[
        "Poszy\u0142ajcie"
    ],
    "name:rus_x_preferred":[
        "\u041f\u0430\u0448\u0438\u043b\u0430\u0439\u0447\u044f\u0439"
    ],
    "name:spa_x_preferred":[
        "Distrito municipal de Pa\u0161ilai\u010diai"
    ],
    "name:swe_x_preferred":[
        "Pa\u0161ilai\u010diai"
    ],
    "name:und_x_preferred":[
        "Pasilaiciai"
    ],
    "name:unk_x_variant":[
        "Pasilaiciai"
    ],
    "qs:gn_adm0_cc":"LT",
    "qs:gn_local":593116,
    "qs:local_max":12571,
    "qs:local_sum":23762,
    "qs:localhoods":20,
    "qs:name":"Pasilaiciai",
    "qs:name_adm0":"Lietuva",
    "qs:name_adm1":"Vilniaus Apskritis",
    "qs:name_adm2":"Vilniaus Miesto Savivaldybe",
    "qs:name_lau":"Vilnius",
    "qs:name_local":"Vilnius",
    "qs:photo_max":1,
    "qs:photo_sum":5,
    "qs:placetype":"Suburb",
    "qs:quad_count":5,
    "qs:woe_adm0":23424875,
    "qs:woe_adm1":55848083,
    "qs:woe_adm2":2346097,
    "qs:woe_lau":56044000,
    "qs:woe_local":479616,
    "qs:woe_ver":"7.10.0",
    "wd:wordcount":28,
    "wof:lang":[
        "unk"
    ],
    "wof:name":"Pasilaiciai",
    "wof:placetype":"neighbourhood"
},
  "geometry": {"coordinates":[25.226635,54.729465],"type":"Point"}
}