{
  "type": "Feature",
  "properties": {
    "gn:admin1_code":"63.0",
    "gn:admin2_code":"68.0",
    "gn:asciiname":"Sleckai",
    "gn:country_code":"LT",
    "gn:dem":148,
    "gn:feature_class":"P",
    "gn:feature_code":"PPL",
    "gn:name":"\u0160le\u010dkai",
    "gn:population":0,
    "gn:timezone":"Europe/Vilnius",
    "iso:country":"LT",
    "name:und_x_variant":[
        "Shlyachki",
        "\u0160le\u010dkai"
    ],
    "wof:name":"Sleckai",
    "wof:placetype":"locality"
},
  "geometry": {"coordinates":[21.95638,55.99176],"type":"Point"}
}