{
  "type": "Feature",
  "properties": {
    "gn:admin1_code":"62.0",
    "gn:admin2_code":"87.0",
    "gn:asciiname":"Reistrai",
    "gn:country_code":"LT",
    "gn:dem":159,
    "gn:feature_class":"P",
    "gn:feature_code":"PPL",
    "gn:name":"Reistrai",
    "gn:population":0,
    "gn:timezone":"Europe/Vilnius",
    "iso:country":"LT",
    "name:lit_x_preferred":[
        "Reistrai"
    ],
    "name:und_x_variant":[
        "Reistriai"
    ],
    "wof:name":"Reistrai",
    "wof:placetype":"locality"
},
  "geometry": {"coordinates":[22.30553,55.6633],"type":"Point"}
}