{
  "type": "Feature",
  "properties": {
    "gn:admin1_code":"57.0",
    "gn:admin2_code":"53.0",
    "gn:asciiname":"Piktagalis",
    "gn:country_code":"LT",
    "gn:dem":58,
    "gn:feature_class":"P",
    "gn:feature_code":"PPL",
    "gn:name":"Piktagalis",
    "gn:population":0,
    "gn:timezone":"Europe/Vilnius",
    "iso:country":"LT",
    "name:und_x_variant":[
        "Piktagola",
        "Piktagalis"
    ],
    "wof:name":"Piktagalis",
    "wof:placetype":"locality"
},
  "geometry": {"coordinates":[24.3128,55.44759000000001],"type":"Point"}
}