{
  "type": "Feature",
  "properties": {
    "gn:admin1_code":"59.0",
    "gn:admin2_code":"39.0",
    "gn:asciiname":"Kumeciai II",
    "gn:country_code":"LT",
    "gn:dem":99,
    "gn:feature_class":"P",
    "gn:feature_code":"PPL",
    "gn:name":"Kume\u010diai II",
    "gn:population":0,
    "gn:timezone":"Europe/Vilnius",
    "iso:country":"LT",
    "name:lit_x_preferred":[
        "Kume\u010diai II"
    ],
    "name:und_x_variant":[
        "Kumechyay",
        "Kume\u010diai"
    ],
    "wof:name":"Kumeciai II",
    "wof:placetype":"locality"
},
  "geometry": {"coordinates":[22.90973,54.57289],"type":"Point"}
}