{
  "type": "Feature",
  "properties": {
    "gn:admin1_code":"59.0",
    "gn:admin2_code":"84.0",
    "gn:asciiname":"Suketeliai",
    "gn:country_code":"LT",
    "gn:dem":61,
    "gn:feature_class":"P",
    "gn:feature_code":"PPL",
    "gn:name":"\u0160uk\u0117t\u0117liai",
    "gn:population":0,
    "gn:timezone":"Europe/Vilnius",
    "iso:country":"LT",
    "name:und_x_variant":[
        "Shuksty",
        "\u0160uk\u0117t\u0117liai"
    ],
    "wof:name":"Suketeliai",
    "wof:placetype":"locality"
},
  "geometry": {"coordinates":[23.4438,55.02359000000001],"type":"Point"}
}