{
  "type": "Feature",
  "properties": {
    "gn:admin1_code":"0.0",
    "gn:asciiname":"Draudikiai",
    "gn:cc2":"LT",
    "gn:country_code":"LT",
    "gn:dem":125,
    "gn:feature_class":"P",
    "gn:feature_code":"PPL",
    "gn:name":"Draudikiai",
    "gn:population":0,
    "gn:timezone":"Europe/Vilnius",
    "iso:country":"LT",
    "name:und_x_variant":[
        "Dravdziki",
        "Draudikiai"
    ],
    "wof:name":"Draudikiai",
    "wof:placetype":"locality"
},
  "geometry": {"coordinates":[22.45,55.98333],"type":"Point"}
}