{
  "type": "Feature",
  "properties": {
    "gn:admin1_code":"60.0",
    "gn:admin2_code":"67.0",
    "gn:asciiname":"Paliepiai",
    "gn:country_code":"LT",
    "gn:dem":61,
    "gn:feature_class":"P",
    "gn:feature_code":"PPL",
    "gn:name":"Paliepiai",
    "gn:population":0,
    "gn:timezone":"Europe/Vilnius",
    "iso:country":"LT",
    "name:und_x_variant":[
        "Paliepi\u0173",
        "Palipi\u0173",
        "Paliyepyay",
        "Palepyay",
        "Paliepiai"
    ],
    "wof:name":"Paliepiai",
    "wof:placetype":"locality"
},
  "geometry": {"coordinates":[24.19084,56.12415],"type":"Point"}
}