{
  "type": "Feature",
  "properties": {
    "gn:admin1_code":"64",
    "gn:admin2_code":"34.0",
    "gn:asciiname":"Griezioneles",
    "gn:country_code":"LT",
    "gn:dem":105,
    "gn:feature_class":"P",
    "gn:feature_code":"PPL",
    "gn:name":"Grie\u017eion\u0117l\u0117s",
    "gn:population":0,
    "gn:timezone":"Europe/Vilnius",
    "iso:country":"LT",
    "name:lit_x_preferred":[
        "Grie\u017eion\u0117l\u0117s"
    ],
    "wof:name":"Griezioneles",
    "wof:placetype":"locality"
},
  "geometry": {"coordinates":[25.03588,55.61993],"type":"Point"}
}