{
  "type": "Feature",
  "properties": {
    "gn:admin1_code":"63",
    "gn:admin2_code":"74.0",
    "gn:asciiname":"Palukalnis",
    "gn:country_code":"LT",
    "gn:dem":179,
    "gn:feature_class":"P",
    "gn:feature_code":"PPL",
    "gn:name":"Pal\u016bkalnis",
    "gn:population":0,
    "gn:timezone":"Europe/Vilnius",
    "iso:country":"LT",
    "name:lit_x_preferred":[
        "Pal\u016bkalnis"
    ],
    "wof:name":"Palukalnis",
    "wof:placetype":"locality"
},
  "geometry": {"coordinates":[22.2051,55.76074000000001],"type":"Point"}
}