{
  "type": "Feature",
  "properties": {
    "gn:admin1_code":"60.0",
    "gn:admin2_code":"36.0",
    "gn:asciiname":"Dumbliunai",
    "gn:country_code":"LT",
    "gn:dem":56,
    "gn:feature_class":"P",
    "gn:feature_code":"PPL",
    "gn:name":"Dumbli\u016bnai",
    "gn:population":0,
    "gn:timezone":"Europe/Vilnius",
    "iso:country":"LT",
    "name:und_x_variant":[
        "Dumblyunay",
        "Dumbli\u016bnai"
    ],
    "wof:name":"Dumbliunai",
    "wof:placetype":"locality"
},
  "geometry": {"coordinates":[24.69765,56.01532],"type":"Point"}
}