{
  "type": "Feature",
  "properties": {
    "gn:admin1_code":"63.0",
    "gn:admin2_code":"68.0",
    "gn:asciiname":"Uzpelkiai",
    "gn:country_code":"LT",
    "gn:dem":154,
    "gn:feature_class":"P",
    "gn:feature_code":"PPL",
    "gn:name":"U\u017epelkiai",
    "gn:population":0,
    "gn:timezone":"Europe/Vilnius",
    "iso:country":"LT",
    "name:und_x_variant":[
        "U\u0161pelki\u0173",
        "Uzhpel\u2019kyay",
        "Uszpielki",
        "U\u017epelkiai"
    ],
    "wof:name":"Uzpelkiai",
    "wof:placetype":"locality"
},
  "geometry": {"coordinates":[21.8062,56.07907],"type":"Point"}
}