{
  "type": "Feature",
  "properties": {
    "gn:admin1_code":"60.0",
    "gn:admin2_code":"36.0",
    "gn:asciiname":"Kupriai",
    "gn:country_code":"LT",
    "gn:dem":65,
    "gn:feature_class":"P",
    "gn:feature_code":"PPL",
    "gn:name":"Kupriai",
    "gn:population":0,
    "gn:timezone":"Europe/Vilnius",
    "iso:country":"LT",
    "name:und_x_variant":[
        "Kupryay",
        "Kupriai"
    ],
    "wof:name":"Kupriai",
    "wof:placetype":"locality"
},
  "geometry": {"coordinates":[24.85073,55.99195],"type":"Point"}
}