{
  "type": "Feature",
  "properties": {
    "gn:admin1_code":"62.0",
    "gn:admin2_code":"77.0",
    "gn:asciiname":"Balciske",
    "gn:country_code":"LT",
    "gn:dem":44,
    "gn:feature_class":"P",
    "gn:feature_code":"PPL",
    "gn:name":"Bal\u010di\u0161k\u0117",
    "gn:population":0,
    "gn:timezone":"Europe/Vilnius",
    "iso:country":"LT",
    "name:und_x_variant":[
        "Bal\u2019chishki",
        "Bal\u010di\u0161k\u0117"
    ],
    "wof:name":"Balciske",
    "wof:placetype":"locality"
},
  "geometry": {"coordinates":[22.47637000000001,55.30638],"type":"Point"}
}