{
  "type": "Feature",
  "properties": {
    "gn:admin1_code":"65",
    "gn:admin2_code":"86.0",
    "gn:asciiname":"Petruskos",
    "gn:country_code":"LT",
    "gn:dem":223,
    "gn:feature_class":"P",
    "gn:feature_code":"PPL",
    "gn:name":"Petru\u0161kos",
    "gn:population":0,
    "gn:timezone":"Europe/Vilnius",
    "iso:country":"LT",
    "name:lit_x_preferred":[
        "Petru\u0161kos"
    ],
    "wof:name":"Petruskos",
    "wof:placetype":"locality"
},
  "geometry": {"coordinates":[26.2828,55.20307],"type":"Point"}
}