{
  "type": "Feature",
  "properties": {
    "gn:admin1_code":"65",
    "gn:admin2_code":"81.0",
    "gn:asciiname":"Menturiai",
    "gn:country_code":"LT",
    "gn:dem":79,
    "gn:feature_class":"P",
    "gn:feature_code":"PPL",
    "gn:name":"Menturiai",
    "gn:population":0,
    "gn:timezone":"Europe/Vilnius",
    "iso:country":"LT",
    "name:lit_x_preferred":[
        "Menturiai"
    ],
    "wof:name":"Menturiai",
    "wof:placetype":"locality"
},
  "geometry": {"coordinates":[24.69644,55.47673],"type":"Point"}
}