{
  "type": "Feature",
  "properties": {
    "gn:admin1_code":"64",
    "gn:admin2_code":"34.0",
    "gn:asciiname":"Miliuniskis",
    "gn:country_code":"LT",
    "gn:dem":110,
    "gn:feature_class":"P",
    "gn:feature_code":"PPL",
    "gn:name":"Mili\u016bni\u0161kis",
    "gn:population":0,
    "gn:timezone":"Europe/Vilnius",
    "iso:country":"LT",
    "name:lit_x_preferred":[
        "Mili\u016bni\u0161kis"
    ],
    "wof:name":"Miliuniskis",
    "wof:placetype":"locality"
},
  "geometry": {"coordinates":[25.40724,55.67759],"type":"Point"}
}