{
  "type": "Feature",
  "properties": {
    "gn:admin1_code":"58.0",
    "gn:admin2_code":"75.0",
    "gn:asciiname":"Puodkaliai",
    "gn:country_code":"LT",
    "gn:dem":35,
    "gn:feature_class":"P",
    "gn:feature_code":"PPL",
    "gn:name":"Puodkaliai",
    "gn:population":0,
    "gn:timezone":"Europe/Vilnius",
    "iso:country":"LT",
    "name:lit_x_preferred":[
        "Puodkaliai"
    ],
    "wof:name":"Puodkaliai",
    "wof:placetype":"locality"
},
  "geometry": {"coordinates":[21.53249,56.23573],"type":"Point"}
}