{
  "type": "Feature",
  "properties": {
    "gn:admin1_code":"58",
    "gn:admin2_code":"21.0",
    "gn:asciiname":"Mikai",
    "gn:country_code":"LT",
    "gn:dem":117,
    "gn:feature_class":"P",
    "gn:feature_code":"PPL",
    "gn:name":"Mikai",
    "gn:population":0,
    "gn:timezone":"Europe/Vilnius",
    "iso:country":"LT",
    "name:lit_x_preferred":[
        "Mikai"
    ],
    "wof:name":"Mikai",
    "wof:placetype":"locality"
},
  "geometry": {"coordinates":[21.79363,55.61491],"type":"Point"}
}