{
  "type": "Feature",
  "properties": {
    "gn:admin1_code":"60",
    "gn:admin2_code":"36.0",
    "gn:asciiname":"Devynbalsiai",
    "gn:country_code":"LT",
    "gn:dem":60,
    "gn:feature_class":"P",
    "gn:feature_code":"PPL",
    "gn:name":"Devynbalsiai",
    "gn:population":0,
    "gn:timezone":"Europe/Vilnius",
    "iso:country":"LT",
    "name:lit_x_preferred":[
        "Devynbalsiai"
    ],
    "wof:name":"Devynbalsiai",
    "wof:placetype":"locality"
},
  "geometry": {"coordinates":[24.83659,56.20426],"type":"Point"}
}