{
  "type": "Feature",
  "properties": {
    "gn:admin1_code":"63.0",
    "gn:admin2_code":"68.0",
    "gn:asciiname":"Grumbliai",
    "gn:country_code":"LT",
    "gn:dem":158,
    "gn:feature_class":"P",
    "gn:feature_code":"PPL",
    "gn:name":"Grumbliai",
    "gn:population":0,
    "gn:timezone":"Europe/Vilnius",
    "iso:country":"LT",
    "name:und_x_variant":[
        "Grumbyay",
        "Grumbliai"
    ],
    "wof:name":"Grumbliai",
    "wof:placetype":"locality"
},
  "geometry": {"coordinates":[22.00303,55.97794],"type":"Point"}
}