{
  "type": "Feature",
  "properties": {
    "gn:admin1_code":"61",
    "gn:admin2_code":"71.0",
    "gn:asciiname":"Medeliukai",
    "gn:country_code":"LT",
    "gn:dem":108,
    "gn:feature_class":"P",
    "gn:feature_code":"PPL",
    "gn:name":"Medeliukai",
    "gn:population":0,
    "gn:timezone":"Europe/Vilnius",
    "iso:country":"LT",
    "name:lit_x_preferred":[
        "Medeliukai"
    ],
    "wof:name":"Medeliukai",
    "wof:placetype":"locality"
},
  "geometry": {"coordinates":[23.62847,55.59743],"type":"Point"}
}