{
  "type": "Feature",
  "properties": {
    "gn:admin1_code":"65.0",
    "gn:admin2_code":"81.0",
    "gn:asciiname":"Alionys",
    "gn:country_code":"LT",
    "gn:dem":123,
    "gn:feature_class":"P",
    "gn:feature_code":"PPL",
    "gn:name":"Alionys",
    "gn:population":0,
    "gn:timezone":"Europe/Vilnius",
    "iso:country":"LT",
    "name:und_x_variant":[
        "Alioni\u0173",
        "Alionis",
        "Alionys",
        "Allonys"
    ],
    "wof:name":"Alionys",
    "wof:placetype":"locality"
},
  "geometry": {"coordinates":[24.86542,55.18277],"type":"Point"}
}