{
  "type": "Feature",
  "properties": {
    "gn:admin1_code":"65",
    "gn:admin2_code":"81.0",
    "gn:asciiname":"Geldonka",
    "gn:country_code":"LT",
    "gn:dem":92,
    "gn:feature_class":"P",
    "gn:feature_code":"PPL",
    "gn:name":"Geldonka",
    "gn:population":0,
    "gn:timezone":"Europe/Vilnius",
    "iso:country":"LT",
    "name:lit_x_preferred":[
        "Geldonka"
    ],
    "wof:name":"Geldonka",
    "wof:placetype":"locality"
},
  "geometry": {"coordinates":[24.69124,55.4976],"type":"Point"}
}