{
  "type": "Feature",
  "properties": {
    "gn:admin1_code":"59",
    "gn:admin2_code":"39.0",
    "gn:asciiname":"Jakiskiai",
    "gn:country_code":"LT",
    "gn:dem":143,
    "gn:feature_class":"P",
    "gn:feature_code":"PPL",
    "gn:name":"Jaki\u0161kiai",
    "gn:population":0,
    "gn:timezone":"Europe/Vilnius",
    "iso:country":"LT",
    "name:lit_x_preferred":[
        "Jaki\u0161kiai"
    ],
    "wof:name":"Jakiskiai",
    "wof:placetype":"locality"
},
  "geometry": {"coordinates":[22.91253,54.50805],"type":"Point"}
}