{
  "type": "Feature",
  "properties": {
    "gn:admin1_code":"62.0",
    "gn:admin2_code":"87.0",
    "gn:asciiname":"Nuomininkai",
    "gn:country_code":"LT",
    "gn:dem":133,
    "gn:feature_class":"P",
    "gn:feature_code":"PPL",
    "gn:name":"Nuomininkai",
    "gn:population":0,
    "gn:timezone":"Europe/Vilnius",
    "iso:country":"LT",
    "name:und_x_variant":[
        "Numenikay",
        "Nudmininkai",
        "Nuomininkai"
    ],
    "wof:name":"Nuomininkai",
    "wof:placetype":"locality"
},
  "geometry": {"coordinates":[22.54268,55.5449],"type":"Point"}
}