{
  "type": "Feature",
  "properties": {
    "gn:admin1_code":"65",
    "gn:admin2_code":"13.0",
    "gn:asciiname":"Naujasodziai",
    "gn:country_code":"LT",
    "gn:dem":194,
    "gn:feature_class":"P",
    "gn:feature_code":"PPL",
    "gn:name":"Naujasod\u017eiai",
    "gn:population":0,
    "gn:timezone":"Europe/Vilnius",
    "iso:country":"LT",
    "name:lit_x_preferred":[
        "Naujasod\u017eiai"
    ],
    "wof:name":"Naujasodziai",
    "wof:placetype":"locality"
},
  "geometry": {"coordinates":[25.16511,54.78938],"type":"Point"}
}