{
  "type": "Feature",
  "properties": {
    "gn:admin1_code":"59",
    "gn:admin2_code":"18.0",
    "gn:asciiname":"Sirvydai",
    "gn:country_code":"LT",
    "gn:dem":110,
    "gn:feature_class":"P",
    "gn:feature_code":"PPL",
    "gn:name":"\u0160irvydai",
    "gn:population":0,
    "gn:timezone":"Europe/Vilnius",
    "iso:country":"LT",
    "name:lit_x_preferred":[
        "\u0160irvydai"
    ],
    "wof:name":"Sirvydai",
    "wof:placetype":"locality"
},
  "geometry": {"coordinates":[23.18636,54.49296],"type":"Point"}
}