{
  "type": "Feature",
  "properties": {
    "gn:admin1_code":"57.0",
    "gn:admin2_code":"46.0",
    "gn:asciiname":"Normainiai",
    "gn:country_code":"LT",
    "gn:dem":77,
    "gn:feature_class":"P",
    "gn:feature_code":"PPL",
    "gn:name":"Normainiai",
    "gn:population":0,
    "gn:timezone":"Europe/Vilnius",
    "iso:country":"LT",
    "name:und_x_variant":[
        "Normaini\u0173",
        "Normaynyay",
        "Normainiai"
    ],
    "wof:name":"Normainiai",
    "wof:placetype":"locality"
},
  "geometry": {"coordinates":[24.24164,55.22963000000001],"type":"Point"}
}