{
  "type": "Feature",
  "properties": {
    "gn:admin1_code":"61.0",
    "gn:admin2_code":"47.0",
    "gn:asciiname":"Mielaiciai",
    "gn:country_code":"LT",
    "gn:dem":57,
    "gn:feature_class":"P",
    "gn:feature_code":"PPL",
    "gn:name":"Mielai\u010diai",
    "gn:population":0,
    "gn:timezone":"Europe/Vilnius",
    "iso:country":"LT",
    "name:und_x_variant":[
        "Melai\u010diai",
        "Melaychyay",
        "Mielai\u010diai"
    ],
    "wof:name":"Mielaiciai",
    "wof:placetype":"locality"
},
  "geometry": {"coordinates":[23.6763,56.18484],"type":"Point"}
}