{
  "type": "Feature",
  "properties": {
    "gn:admin1_code":"59.0",
    "gn:admin2_code":"39.0",
    "gn:asciiname":"Daugelaiciai",
    "gn:country_code":"LT",
    "gn:dem":53,
    "gn:feature_class":"P",
    "gn:feature_code":"PPL",
    "gn:name":"Daug\u0117laiciai",
    "gn:population":0,
    "gn:timezone":"Europe/Vilnius",
    "iso:country":"LT",
    "name:lit_x_preferred":[
        "Daug\u0117laiciai"
    ],
    "name:und_x_variant":[
        "Daug\u0117lai\u010di\u0173",
        "Daugelaychyay",
        "Daug\u0117lai\u010diai"
    ],
    "wof:name":"Daugelaiciai",
    "wof:placetype":"locality"
},
  "geometry": {"coordinates":[22.78204,54.63188],"type":"Point"}
}