{
  "type": "Feature",
  "properties": {
    "gn:admin1_code":"60",
    "gn:admin2_code":"36.0",
    "gn:asciiname":"Lapakrita",
    "gn:country_code":"LT",
    "gn:dem":48,
    "gn:feature_class":"P",
    "gn:feature_code":"PPL",
    "gn:name":"Lapakrita",
    "gn:population":0,
    "gn:timezone":"Europe/Vilnius",
    "iso:country":"LT",
    "name:lit_x_preferred":[
        "Lapakrita"
    ],
    "wof:name":"Lapakrita",
    "wof:placetype":"locality"
},
  "geometry": {"coordinates":[24.7941,56.35285],"type":"Point"}
}