{
  "type": "Feature",
  "properties": {
    "gn:admin1_code":"65",
    "gn:admin2_code":"85.0",
    "gn:asciiname":"Senosios Rakliskes",
    "gn:country_code":"LT",
    "gn:dem":140,
    "gn:feature_class":"P",
    "gn:feature_code":"PPL",
    "gn:name":"Senosios Rakli\u0161k\u0117s",
    "gn:population":0,
    "gn:timezone":"Europe/Vilnius",
    "iso:country":"LT",
    "name:lit_x_preferred":[
        "Senosios Rakli\u0161k\u0117s"
    ],
    "wof:name":"Senosios Rakliskes",
    "wof:placetype":"locality"
},
  "geometry": {"coordinates":[25.13436,54.30149],"type":"Point"}
}