{
  "type": "Feature",
  "properties": {
    "gn:admin1_code":"59.0",
    "gn:admin2_code":"84.0",
    "gn:asciiname":"Pusdesriai",
    "gn:country_code":"LT",
    "gn:dem":39,
    "gn:feature_class":"P",
    "gn:feature_code":"PPL",
    "gn:name":"Pusde\u0161riai",
    "gn:population":0,
    "gn:timezone":"Europe/Vilnius",
    "iso:country":"LT",
    "name:und_x_variant":[
        "Puzdeshri",
        "Pusde\u0161ri\u0173",
        "Pusdeshryay",
        "Pusde\u0161riai"
    ],
    "wof:name":"Pusdesriai",
    "wof:placetype":"locality"
},
  "geometry": {"coordinates":[22.87511,54.9319],"type":"Point"}
}