{
  "type": "Feature",
  "properties": {
    "gn:admin1_code":"61.0",
    "gn:admin2_code":"54.0",
    "gn:asciiname":"Bumbuliai",
    "gn:country_code":"LT",
    "gn:dem":154,
    "gn:feature_class":"P",
    "gn:feature_code":"PPL",
    "gn:name":"Bumbuliai",
    "gn:population":0,
    "gn:timezone":"Europe/Vilnius",
    "iso:country":"LT",
    "name:und_x_variant":[
        "Bambulyay",
        "Bumbuliai"
    ],
    "wof:name":"Bumbuliai",
    "wof:placetype":"locality"
},
  "geometry": {"coordinates":[22.74462,55.54779],"type":"Point"}
}