{
  "type": "Feature",
  "properties": {
    "gn:admin1_code":"60.0",
    "gn:admin2_code":"27.0",
    "gn:asciiname":"Vilkapjuviai",
    "gn:country_code":"LT",
    "gn:dem":55,
    "gn:feature_class":"P",
    "gn:feature_code":"PPL",
    "gn:name":"Vilkapj\u016bviai",
    "gn:population":0,
    "gn:timezone":"Europe/Vilnius",
    "iso:country":"LT",
    "name:lit_x_preferred":[
        "Vilkapj\u016bviai"
    ],
    "name:und_x_variant":[
        "Vilkakivyay",
        "Vilkapievi\u0173",
        "Vilkapioviai",
        "Vilkapieviai",
        "Vilkapiuviai"
    ],
    "wof:name":"Vilkapjuviai",
    "wof:placetype":"locality"
},
  "geometry": {"coordinates":[24.46362,55.7994],"type":"Point"}
}