{
  "type": "Feature",
  "properties": {
    "gn:admin1_code":"57",
    "gn:admin2_code":"49.0",
    "gn:asciiname":"Gajaucizna",
    "gn:country_code":"LT",
    "gn:dem":128,
    "gn:feature_class":"P",
    "gn:feature_code":"PPL",
    "gn:name":"Gajau\u010dizna",
    "gn:population":0,
    "gn:timezone":"Europe/Vilnius",
    "iso:country":"LT",
    "name:lit_x_preferred":[
        "Gajau\u010dizna"
    ],
    "wof:name":"Gajaucizna",
    "wof:placetype":"locality"
},
  "geometry": {"coordinates":[24.37896,54.75788000000001],"type":"Point"}
}