{
  "type": "Feature",
  "properties": {
    "gn:admin1_code":"65",
    "gn:admin2_code":"13.0",
    "gn:asciiname":"Berzyte",
    "gn:country_code":"LT",
    "gn:dem":226,
    "gn:feature_class":"P",
    "gn:feature_code":"PPL",
    "gn:name":"Ber\u017eyt\u0117",
    "gn:population":0,
    "gn:timezone":"Europe/Vilnius",
    "iso:country":"LT",
    "name:lit_x_preferred":[
        "Ber\u017eyt\u0117"
    ],
    "wof:name":"Berzyte",
    "wof:placetype":"locality"
},
  "geometry": {"coordinates":[25.71252,54.76744],"type":"Point"}
}