{
  "type": "Feature",
  "properties": {
    "gn:admin1_code":"65",
    "gn:admin2_code":"13.0",
    "gn:asciiname":"Rudyne",
    "gn:country_code":"LT",
    "gn:dem":194,
    "gn:feature_class":"P",
    "gn:feature_code":"PPL",
    "gn:name":"R\u016bdyn\u0117",
    "gn:population":0,
    "gn:timezone":"Europe/Vilnius",
    "iso:country":"LT",
    "name:lit_x_preferred":[
        "R\u016bdyn\u0117"
    ],
    "wof:name":"Rudyne",
    "wof:placetype":"locality"
},
  "geometry": {"coordinates":[25.59059,54.58633],"type":"Point"}
}