{
  "type": "Feature",
  "properties": {
    "gn:admin1_code":"65",
    "gn:admin2_code":"13.0",
    "gn:asciiname":"Sepeciai",
    "gn:country_code":"LT",
    "gn:dem":165,
    "gn:feature_class":"P",
    "gn:feature_code":"PPL",
    "gn:name":"Sepe\u010diai",
    "gn:population":0,
    "gn:timezone":"Europe/Vilnius",
    "iso:country":"LT",
    "name:lit_x_preferred":[
        "Sepe\u010diai"
    ],
    "wof:name":"Sepeciai",
    "wof:placetype":"locality"
},
  "geometry": {"coordinates":[25.26888,54.92799],"type":"Point"}
}