{
  "type": "Feature",
  "properties": {
    "gn:admin1_code":"65",
    "gn:admin2_code":"13.0",
    "gn:asciiname":"Aukstadvaris",
    "gn:country_code":"LT",
    "gn:dem":169,
    "gn:feature_class":"P",
    "gn:feature_code":"PPL",
    "gn:name":"Auk\u0161tadvaris",
    "gn:population":0,
    "gn:timezone":"Europe/Vilnius",
    "iso:country":"LT",
    "name:lit_x_preferred":[
        "Auk\u0161tadvaris"
    ],
    "wof:name":"Aukstadvaris",
    "wof:placetype":"locality"
},
  "geometry": {"coordinates":[25.13868,54.82464],"type":"Point"}
}