{
  "type": "Feature",
  "properties": {
    "gn:admin1_code":"61.0",
    "gn:admin2_code":"29.0",
    "gn:asciiname":"Sauslauke",
    "gn:country_code":"LT",
    "gn:dem":137,
    "gn:feature_class":"P",
    "gn:feature_code":"PPL",
    "gn:name":"Sauslauk\u0117",
    "gn:population":0,
    "gn:timezone":"Europe/Vilnius",
    "iso:country":"LT",
    "name:und_x_variant":[
        "Sauslaukis",
        "Sauslauk\u0117"
    ],
    "wof:name":"Sauslauke",
    "wof:placetype":"locality"
},
  "geometry": {"coordinates":[22.74973,55.95744000000001],"type":"Point"}
}