{
  "type": "Feature",
  "properties": {
    "gn:admin1_code":"56",
    "gn:admin2_code":"38.0",
    "gn:asciiname":"Ulciciai",
    "gn:country_code":"LT",
    "gn:dem":87,
    "gn:feature_class":"P",
    "gn:feature_code":"PPL",
    "gn:name":"Ul\u010di\u010diai",
    "gn:population":0,
    "gn:timezone":"Europe/Vilnius",
    "iso:country":"LT",
    "name:lit_x_preferred":[
        "Ul\u010di\u010diai"
    ],
    "wof:name":"Ulciciai",
    "wof:placetype":"locality"
},
  "geometry": {"coordinates":[24.15381,54.10231],"type":"Point"}
}