{
  "type": "Feature",
  "properties": {
    "gn:admin1_code":"57",
    "gn:admin2_code":"49.0",
    "gn:asciiname":"Vaiduciai",
    "gn:country_code":"LT",
    "gn:dem":50,
    "gn:feature_class":"P",
    "gn:feature_code":"PPL",
    "gn:name":"Vaidu\u010diai",
    "gn:population":0,
    "gn:timezone":"Europe/Vilnius",
    "iso:country":"LT",
    "name:lit_x_preferred":[
        "Vaidu\u010diai"
    ],
    "wof:name":"Vaiduciai",
    "wof:placetype":"locality"
},
  "geometry": {"coordinates":[24.45541,55.01729],"type":"Point"}
}