{
  "type": "Feature",
  "properties": {
    "gn:admin1_code":"56.0",
    "gn:admin2_code":"11.0",
    "gn:asciiname":"Rimenai",
    "gn:country_code":"LT",
    "gn:dem":139,
    "gn:feature_class":"P",
    "gn:feature_code":"PPL",
    "gn:name":"Rim\u0117nai",
    "gn:population":0,
    "gn:timezone":"Europe/Vilnius",
    "iso:country":"LT",
    "name:und_x_variant":[
        "Rym\u0117nai",
        "Rim\u0117n\u0173",
        "Rymyantsy",
        "Rim\u0117nai"
    ],
    "wof:name":"Rimenai",
    "wof:placetype":"locality"
},
  "geometry": {"coordinates":[24.32667,54.32651],"type":"Point"}
}