{
  "type": "Feature",
  "properties": {
    "gn:admin1_code":"56",
    "gn:admin2_code":"38.0",
    "gn:asciiname":"Lankininkai",
    "gn:country_code":"LT",
    "gn:dem":78,
    "gn:feature_class":"P",
    "gn:feature_code":"PPL",
    "gn:name":"Lankininkai",
    "gn:population":0,
    "gn:timezone":"Europe/Vilnius",
    "iso:country":"LT",
    "name:lit_x_preferred":[
        "Lankininkai"
    ],
    "wof:name":"Lankininkai",
    "wof:placetype":"locality"
},
  "geometry": {"coordinates":[24.25577,54.1302],"type":"Point"}
}