{
  "type": "Feature",
  "properties": {
    "gn:admin1_code":"64",
    "gn:admin2_code":"43.0",
    "gn:asciiname":"Gudeliai",
    "gn:country_code":"LT",
    "gn:dem":162,
    "gn:feature_class":"P",
    "gn:feature_code":"PPL",
    "gn:name":"Gudeliai",
    "gn:population":0,
    "gn:timezone":"Europe/Vilnius",
    "iso:country":"LT",
    "name:ceb_x_preferred":[
        "Gudeliai"
    ],
    "name:est_x_preferred":[
        "Gudeliai"
    ],
    "name:lit_x_preferred":[
        "Gudeliai"
    ],
    "name:nld_x_preferred":[
        "Gudeliai"
    ],
    "name:pol_x_preferred":[
        "Gudele"
    ],
    "name:swe_x_preferred":[
        "Gudeliai"
    ],
    "wof:name":"Gudeliai",
    "wof:placetype":"locality"
},
  "geometry": {"coordinates":[26.05012,55.70399999999999],"type":"Point"}
}