{
  "type": "Feature",
  "properties": {
    "gn:admin1_code":"62.0",
    "gn:admin2_code":"87.0",
    "gn:asciiname":"Gineikiai",
    "gn:country_code":"LT",
    "gn:dem":149,
    "gn:feature_class":"P",
    "gn:feature_code":"PPL",
    "gn:name":"Gineikiai",
    "gn:population":0,
    "gn:timezone":"Europe/Vilnius",
    "iso:country":"LT",
    "name:lit_x_preferred":[
        "Gineikiai"
    ],
    "wof:name":"Gineikiai",
    "wof:placetype":"locality"
},
  "geometry": {"coordinates":[22.494,55.53568000000001],"type":"Point"}
}