{
  "type": "Feature",
  "properties": {
    "gn:admin1_code":"57.0",
    "gn:admin2_code":"72.0",
    "gn:asciiname":"Liaubarai",
    "gn:country_code":"LT",
    "gn:dem":131,
    "gn:feature_class":"P",
    "gn:feature_code":"PPL",
    "gn:name":"Liaubarai",
    "gn:population":0,
    "gn:timezone":"Europe/Vilnius",
    "iso:country":"LT",
    "name:und_x_variant":[
        "Levbory",
        "Levboray",
        "Liaubarai"
    ],
    "wof:name":"Liaubarai",
    "wof:placetype":"locality"
},
  "geometry": {"coordinates":[23.48432,55.48153000000001],"type":"Point"}
}