{
  "type": "Feature",
  "properties": {
    "gn:admin1_code":"64",
    "gn:admin2_code":"43.0",
    "gn:asciiname":"Grybiskes",
    "gn:country_code":"LT",
    "gn:dem":168,
    "gn:feature_class":"P",
    "gn:feature_code":"PPL",
    "gn:name":"Grybi\u0161k\u0117s",
    "gn:population":0,
    "gn:timezone":"Europe/Vilnius",
    "iso:country":"LT",
    "name:lit_x_preferred":[
        "Grybi\u0161k\u0117s"
    ],
    "wof:name":"Grybiskes",
    "wof:placetype":"locality"
},
  "geometry": {"coordinates":[26.02825,55.68353000000001],"type":"Point"}
}