{
  "type": "Feature",
  "properties": {
    "gn:admin1_code":"65",
    "gn:admin2_code":"42.0",
    "gn:asciiname":"Eserine",
    "gn:country_code":"LT",
    "gn:dem":120,
    "gn:feature_class":"P",
    "gn:feature_code":"PPL",
    "gn:name":"E\u0161erin\u0117",
    "gn:population":0,
    "gn:timezone":"Europe/Vilnius",
    "iso:country":"LT",
    "name:lit_x_preferred":[
        "E\u0161erin\u0117"
    ],
    "wof:name":"Eserine",
    "wof:placetype":"locality"
},
  "geometry": {"coordinates":[24.88115,54.77464000000001],"type":"Point"}
}