{
  "type": "Feature",
  "properties": {
    "gn:admin1_code":"59.0",
    "gn:admin2_code":"39.0",
    "gn:asciiname":"Geisteriskiai",
    "gn:country_code":"LT",
    "gn:dem":103,
    "gn:feature_class":"P",
    "gn:feature_code":"PPL",
    "gn:name":"Geisteri\u0161kiai",
    "gn:population":0,
    "gn:timezone":"Europe/Vilnius",
    "iso:country":"LT",
    "name:und_x_variant":[
        "Geisteri\u0161ki\u0173",
        "Geystorishki",
        "Geisteri\u0161kiai"
    ],
    "wof:name":"Geisteriskiai",
    "wof:placetype":"locality"
},
  "geometry": {"coordinates":[23.02164,54.53959],"type":"Point"}
}