{
  "type": "Feature",
  "properties": {
    "gn:admin1_code":"62.0",
    "gn:admin2_code":"77.0",
    "gn:asciiname":"Bokseiniai",
    "gn:country_code":"LT",
    "gn:dem":103,
    "gn:feature_class":"P",
    "gn:feature_code":"PPL",
    "gn:name":"Bok\u0161einiai",
    "gn:population":0,
    "gn:timezone":"Europe/Vilnius",
    "iso:country":"LT",
    "name:und_x_variant":[
        "Bokshenai",
        "Bok\u0161einiai"
    ],
    "wof:name":"Bokseiniai",
    "wof:placetype":"locality"
},
  "geometry": {"coordinates":[22.67514,55.41747],"type":"Point"}
}