{
  "type": "Feature",
  "properties": {
    "gn:admin1_code":"59.0",
    "gn:admin2_code":"84.0",
    "gn:asciiname":"Kriaucenai",
    "gn:country_code":"LT",
    "gn:dem":41,
    "gn:feature_class":"P",
    "gn:feature_code":"PPL",
    "gn:name":"Kriau\u010d\u0117nai",
    "gn:population":0,
    "gn:timezone":"Europe/Vilnius",
    "iso:country":"LT",
    "name:und_x_variant":[
        "Kryauchenay",
        "Kriau\u010d\u0117nai"
    ],
    "wof:name":"Kriaucenai",
    "wof:placetype":"locality"
},
  "geometry": {"coordinates":[22.86372,54.97305],"type":"Point"}
}