{
  "type": "Feature",
  "properties": {
    "gn:admin1_code":"65",
    "gn:admin2_code":"13.0",
    "gn:asciiname":"Eiliokiskes",
    "gn:country_code":"LT",
    "gn:dem":167,
    "gn:feature_class":"P",
    "gn:feature_code":"PPL",
    "gn:name":"Eilioki\u0161k\u0117s",
    "gn:population":0,
    "gn:timezone":"Europe/Vilnius",
    "iso:country":"LT",
    "name:lit_x_preferred":[
        "Eilioki\u0161k\u0117s"
    ],
    "wof:name":"Eiliokiskes",
    "wof:placetype":"locality"
},
  "geometry": {"coordinates":[25.14494,54.88961],"type":"Point"}
}