{
  "type": "Feature",
  "properties": {
    "gn:admin1_code":"64",
    "gn:admin2_code":"45.0",
    "gn:asciiname":"Pusynas",
    "gn:country_code":"LT",
    "gn:dem":164,
    "gn:feature_class":"P",
    "gn:feature_code":"PPL",
    "gn:name":"Pu\u0161ynas",
    "gn:population":0,
    "gn:timezone":"Europe/Vilnius",
    "iso:country":"LT",
    "name:lit_x_preferred":[
        "Pu\u0161ynas"
    ],
    "wof:name":"Pusynas",
    "wof:placetype":"locality"
},
  "geometry": {"coordinates":[26.47934,55.55006],"type":"Point"}
}