{
  "type": "Feature",
  "properties": {
    "gn:admin1_code":"61",
    "gn:admin2_code":"71.0",
    "gn:asciiname":"Burbiskis",
    "gn:country_code":"LT",
    "gn:dem":81,
    "gn:feature_class":"P",
    "gn:feature_code":"PPL",
    "gn:name":"Burbi\u0161kis",
    "gn:population":0,
    "gn:timezone":"Europe/Vilnius",
    "iso:country":"LT",
    "name:lit_x_preferred":[
        "Burbi\u0161kis"
    ],
    "wof:name":"Burbiskis",
    "wof:placetype":"locality"
},
  "geometry": {"coordinates":[23.90082,55.78349],"type":"Point"}
}