{
  "type": "Feature",
  "properties": {
    "gn:admin1_code":"64",
    "gn:admin2_code":"62.0",
    "gn:asciiname":"Andrasiunai",
    "gn:country_code":"LT",
    "gn:dem":165,
    "gn:feature_class":"P",
    "gn:feature_code":"PPL",
    "gn:name":"Andra\u0161i\u016bnai",
    "gn:population":0,
    "gn:timezone":"Europe/Vilnius",
    "iso:country":"LT",
    "name:lit_x_preferred":[
        "Andra\u0161i\u016bnai"
    ],
    "wof:name":"Andrasiunai",
    "wof:placetype":"locality"
},
  "geometry": {"coordinates":[25.51246,55.19308],"type":"Point"}
}