{
  "type": "Feature",
  "properties": {
    "gn:admin1_code":"64.0",
    "gn:admin2_code":"43.0",
    "gn:asciiname":"Vedariai",
    "gn:country_code":"LT",
    "gn:dem":167,
    "gn:feature_class":"P",
    "gn:feature_code":"PPL",
    "gn:name":"V\u0117dariai",
    "gn:population":0,
    "gn:timezone":"Europe/Vilnius",
    "iso:country":"LT",
    "name:und_x_variant":[
        "Vedaryay",
        "V\u0117dariai"
    ],
    "wof:name":"Vedariai",
    "wof:placetype":"locality"
},
  "geometry": {"coordinates":[26.03093,55.80779],"type":"Point"}
}