{
  "type": "Feature",
  "properties": {
    "gn:admin1_code":"63",
    "gn:admin2_code":"78.0",
    "gn:asciiname":"Barzdziai",
    "gn:country_code":"LT",
    "gn:dem":150,
    "gn:feature_class":"P",
    "gn:feature_code":"PPL",
    "gn:name":"Barzd\u017eiai",
    "gn:population":0,
    "gn:timezone":"Europe/Vilnius",
    "iso:country":"LT",
    "name:lit_x_preferred":[
        "Barzd\u017eiai"
    ],
    "wof:name":"Barzdziai",
    "wof:placetype":"locality"
},
  "geometry": {"coordinates":[22.44574,55.79964],"type":"Point"}
}