{
  "type": "Feature",
  "properties": {
    "gn:admin1_code":"65",
    "gn:admin2_code":"86.0",
    "gn:asciiname":"Sventa",
    "gn:country_code":"LT",
    "gn:dem":198,
    "gn:feature_class":"P",
    "gn:feature_code":"PPL",
    "gn:name":"\u0160venta",
    "gn:population":0,
    "gn:timezone":"Europe/Vilnius",
    "iso:country":"LT",
    "name:lit_x_preferred":[
        "\u0160venta"
    ],
    "wof:name":"Sventa",
    "wof:placetype":"locality"
},
  "geometry": {"coordinates":[26.20199,55.19079],"type":"Point"}
}