{
  "type": "Feature",
  "properties": {
    "gn:admin1_code":"63",
    "gn:admin2_code":"78.0",
    "gn:asciiname":"Dargvainiai",
    "gn:country_code":"LT",
    "gn:dem":192,
    "gn:feature_class":"P",
    "gn:feature_code":"PPL",
    "gn:name":"Dargvainiai",
    "gn:population":0,
    "gn:timezone":"Europe/Vilnius",
    "iso:country":"LT",
    "name:lit_x_preferred":[
        "Dargvainiai"
    ],
    "wof:name":"Dargvainiai",
    "wof:placetype":"locality"
},
  "geometry": {"coordinates":[22.33446,55.88693000000001],"type":"Point"}
}