{
  "type": "Feature",
  "properties": {
    "gn:admin1_code":"65.0",
    "gn:admin2_code":"13.0",
    "gn:asciiname":"Bagusiai",
    "gn:country_code":"LT",
    "gn:dem":190,
    "gn:feature_class":"P",
    "gn:feature_code":"PPL",
    "gn:name":"Bagu\u0161iai",
    "gn:population":0,
    "gn:timezone":"Europe/Vilnius",
    "iso:country":"LT",
    "name:lit_x_preferred":[
        "Bagu\u0161iai"
    ],
    "wof:name":"Bagusiai",
    "wof:placetype":"locality"
},
  "geometry": {"coordinates":[25.43624,54.5088],"type":"Point"}
}