{
  "type": "Feature",
  "properties": {
    "gn:admin1_code":"65",
    "gn:admin2_code":"86.0",
    "gn:asciiname":"Pastoviskis",
    "gn:country_code":"LT",
    "gn:dem":148,
    "gn:feature_class":"P",
    "gn:feature_code":"PPL",
    "gn:name":"Pastovi\u0161kis",
    "gn:population":0,
    "gn:timezone":"Europe/Vilnius",
    "iso:country":"LT",
    "name:lit_x_preferred":[
        "Pastovi\u0161kis"
    ],
    "wof:name":"Pastoviskis",
    "wof:placetype":"locality"
},
  "geometry": {"coordinates":[25.81185,55.20339],"type":"Point"}
}