{
  "type": "Feature",
  "properties": {
    "gn:admin1_code":"64",
    "gn:admin2_code":"43.0",
    "gn:asciiname":"Kastantinava",
    "gn:country_code":"LT",
    "gn:dem":155,
    "gn:feature_class":"P",
    "gn:feature_code":"PPL",
    "gn:name":"Kastantinava",
    "gn:population":0,
    "gn:timezone":"Europe/Vilnius",
    "iso:country":"LT",
    "name:lit_x_preferred":[
        "Kastantinava"
    ],
    "wof:name":"Kastantinava",
    "wof:placetype":"locality"
},
  "geometry": {"coordinates":[26.09286,55.8691],"type":"Point"}
}