{
  "type": "Feature",
  "properties": {
    "gn:admin1_code":"0.0",
    "gn:asciiname":"Uzpirdziai",
    "gn:cc2":"LT",
    "gn:country_code":"LT",
    "gn:dem":0,
    "gn:feature_class":"P",
    "gn:feature_code":"PPL",
    "gn:name":"U\u017epird\u017eiai",
    "gn:population":0,
    "gn:timezone":"Europe/Vilnius",
    "iso:country":"LT",
    "name:deu_x_preferred":[
        "Uszpirden"
    ],
    "name:und_x_variant":[
        "Uzhpirden",
        "U\u017epird\u017eiai"
    ],
    "wof:name":"Uzpirdziai",
    "wof:placetype":"locality"
},
  "geometry": {"coordinates":[21.78333,55.13333000000001],"type":"Point"}
}