{
  "type": "Feature",
  "properties": {
    "gn:admin1_code":"61",
    "gn:admin2_code":"54.0",
    "gn:asciiname":"Uzmiestis",
    "gn:country_code":"LT",
    "gn:dem":131,
    "gn:feature_class":"P",
    "gn:feature_code":"PPL",
    "gn:name":"U\u017emiestis",
    "gn:population":0,
    "gn:timezone":"Europe/Vilnius",
    "iso:country":"LT",
    "name:lit_x_preferred":[
        "U\u017emiestis"
    ],
    "wof:name":"Uzmiestis",
    "wof:placetype":"locality"
},
  "geometry": {"coordinates":[22.9082,55.63445],"type":"Point"}
}