{
  "type": "Feature",
  "properties": {
    "gn:admin1_code":"64",
    "gn:admin2_code":"62.0",
    "gn:asciiname":"Bendziukai",
    "gn:country_code":"LT",
    "gn:dem":152,
    "gn:feature_class":"P",
    "gn:feature_code":"PPL",
    "gn:name":"Bend\u017eiukai",
    "gn:population":0,
    "gn:timezone":"Europe/Vilnius",
    "iso:country":"LT",
    "name:lit_x_preferred":[
        "Bend\u017eiukai"
    ],
    "wof:name":"Bendziukai",
    "wof:placetype":"locality"
},
  "geometry": {"coordinates":[25.58058,55.08494],"type":"Point"}
}