{
  "type": "Feature",
  "properties": {
    "gn:admin1_code":"63",
    "gn:admin2_code":"61.0",
    "gn:asciiname":"Paezere",
    "gn:country_code":"LT",
    "gn:dem":120,
    "gn:feature_class":"P",
    "gn:feature_code":"PPL",
    "gn:name":"Pae\u017eer\u0117",
    "gn:population":0,
    "gn:timezone":"Europe/Vilnius",
    "iso:country":"LT",
    "name:lit_x_preferred":[
        "Pae\u017eer\u0117"
    ],
    "wof:name":"Paezere",
    "wof:placetype":"locality"
},
  "geometry": {"coordinates":[22.12506,56.15151],"type":"Point"}
}