{
  "type": "Feature",
  "properties": {
    "gn:admin1_code":"59",
    "gn:admin2_code":"48.0",
    "gn:asciiname":"Juodieji Saltiniai",
    "gn:country_code":"LT",
    "gn:dem":119,
    "gn:feature_class":"P",
    "gn:feature_code":"PPL",
    "gn:name":"Juodieji \u0160altiniai",
    "gn:population":0,
    "gn:timezone":"Europe/Vilnius",
    "iso:country":"LT",
    "name:lit_x_preferred":[
        "Juodieji \u0160altiniai"
    ],
    "wof:name":"Juodieji Saltiniai",
    "wof:placetype":"locality"
},
  "geometry": {"coordinates":[23.30562,54.45602],"type":"Point"}
}