{
  "type": "Feature",
  "properties": {
    "gn:admin1_code":"61",
    "gn:admin2_code":"29.0",
    "gn:asciiname":"Paraudziai",
    "gn:country_code":"LT",
    "gn:dem":109,
    "gn:feature_class":"P",
    "gn:feature_code":"PPL",
    "gn:name":"Paraud\u017eiai",
    "gn:population":0,
    "gn:timezone":"Europe/Vilnius",
    "iso:country":"LT",
    "name:lit_x_preferred":[
        "Paraud\u017eiai"
    ],
    "wof:name":"Paraudziai",
    "wof:placetype":"locality"
},
  "geometry": {"coordinates":[22.7216,56.0181],"type":"Point"}
}