{
  "type": "Feature",
  "properties": {
    "gn:admin1_code":"60.0",
    "gn:admin2_code":"36.0",
    "gn:asciiname":"Daukniskiai",
    "gn:country_code":"LT",
    "gn:dem":51,
    "gn:feature_class":"P",
    "gn:feature_code":"PPL",
    "gn:name":"Daukni\u0161kiai",
    "gn:population":0,
    "gn:timezone":"Europe/Vilnius",
    "iso:country":"LT",
    "name:und_x_variant":[
        "Dayknishkyay",
        "Daukni\u0161kiai"
    ],
    "wof:name":"Daukniskiai",
    "wof:placetype":"locality"
},
  "geometry": {"coordinates":[24.7847,56.29691],"type":"Point"}
}