{
  "type": "Feature",
  "properties": {
    "gn:admin1_code":"56.0",
    "gn:admin2_code":"11.0",
    "gn:asciiname":"Miezionys",
    "gn:country_code":"LT",
    "gn:dem":88,
    "gn:feature_class":"P",
    "gn:feature_code":"PPL",
    "gn:name":"Mie\u017eionys",
    "gn:population":0,
    "gn:timezone":"Europe/Vilnius",
    "iso:country":"LT",
    "name:lit_x_preferred":[
        "Mie\u017eionys"
    ],
    "name:und_x_variant":[
        "Mi\u017eoniai"
    ],
    "wof:name":"Miezionys",
    "wof:placetype":"locality"
},
  "geometry": {"coordinates":[23.98895,54.17508],"type":"Point"}
}