{
  "type": "Feature",
  "properties": {
    "gn:admin1_code":"0.0",
    "gn:asciiname":"Degsne",
    "gn:cc2":"LT",
    "gn:country_code":"LT",
    "gn:dem":116,
    "gn:feature_class":"P",
    "gn:feature_code":"PPL",
    "gn:name":"Degsn\u0117",
    "gn:population":0,
    "gn:timezone":"Europe/Vilnius",
    "iso:country":"LT",
    "name:und_x_variant":[
        "Dekshne",
        "Degsn\u0117"
    ],
    "wof:name":"Degsne",
    "wof:placetype":"locality"
},
  "geometry": {"coordinates":[22.65,55.85],"type":"Point"}
}