{
  "type": "Feature",
  "properties": {
    "gn:admin1_code":"65",
    "gn:admin2_code":"42.0",
    "gn:asciiname":"Ausieniskes",
    "gn:country_code":"LT",
    "gn:dem":118,
    "gn:feature_class":"P",
    "gn:feature_code":"PPL",
    "gn:name":"Ausieni\u0161k\u0117s",
    "gn:population":0,
    "gn:timezone":"Europe/Vilnius",
    "iso:country":"LT",
    "name:lit_x_preferred":[
        "Ausieni\u0161k\u0117s"
    ],
    "wof:name":"Ausieniskes",
    "wof:placetype":"locality"
},
  "geometry": {"coordinates":[24.77836,54.78953000000001],"type":"Point"}
}