{
  "type": "Feature",
  "properties": {
    "gn:admin1_code":"57",
    "gn:admin2_code":"69.0",
    "gn:asciiname":"Antapolis",
    "gn:country_code":"LT",
    "gn:dem":197,
    "gn:feature_class":"P",
    "gn:feature_code":"PPL",
    "gn:name":"Antapolis",
    "gn:population":0,
    "gn:timezone":"Europe/Vilnius",
    "iso:country":"LT",
    "name:lit_x_preferred":[
        "Antapolis"
    ],
    "wof:name":"Antapolis",
    "wof:placetype":"locality"
},
  "geometry": {"coordinates":[24.43878,54.59665],"type":"Point"}
}