{
  "type": "Feature",
  "properties": {
    "gn:admin1_code":"60",
    "gn:admin2_code":"67.0",
    "gn:asciiname":"Kupriskis",
    "gn:country_code":"LT",
    "gn:dem":38,
    "gn:feature_class":"P",
    "gn:feature_code":"PPL",
    "gn:name":"Kupri\u0161kis",
    "gn:population":0,
    "gn:timezone":"Europe/Vilnius",
    "iso:country":"LT",
    "name:lit_x_preferred":[
        "Kupri\u0161kis"
    ],
    "wof:name":"Kupriskis",
    "wof:placetype":"locality"
},
  "geometry": {"coordinates":[24.20385,56.23521],"type":"Point"}
}