{
  "type": "Feature",
  "properties": {
    "gn:admin1_code":"63.0",
    "gn:admin2_code":"78.0",
    "gn:asciiname":"Gomaliai",
    "gn:country_code":"LT",
    "gn:dem":158,
    "gn:feature_class":"P",
    "gn:feature_code":"PPL",
    "gn:name":"Gomaliai",
    "gn:population":0,
    "gn:timezone":"Europe/Vilnius",
    "iso:country":"LT",
    "name:und_x_variant":[
        "Gomalyay",
        "Gomaliai"
    ],
    "wof:name":"Gomaliai",
    "wof:placetype":"locality"
},
  "geometry": {"coordinates":[22.38196,55.69201999999999],"type":"Point"}
}