{
  "type": "Feature",
  "properties": {
    "gn:admin1_code":"65",
    "gn:admin2_code":"13.0",
    "gn:asciiname":"Asiukle",
    "gn:country_code":"LT",
    "gn:dem":166,
    "gn:feature_class":"P",
    "gn:feature_code":"PPL",
    "gn:name":"Asi\u016bkl\u0117",
    "gn:population":0,
    "gn:timezone":"Europe/Vilnius",
    "iso:country":"LT",
    "name:lit_x_preferred":[
        "Asi\u016bkl\u0117"
    ],
    "wof:name":"Asiukle",
    "wof:placetype":"locality"
},
  "geometry": {"coordinates":[25.26287,54.84367],"type":"Point"}
}