{
  "type": "Feature",
  "properties": {
    "gn:admin1_code":"57",
    "gn:admin2_code":"19.0",
    "gn:asciiname":"Luksakaimis",
    "gn:country_code":"LT",
    "gn:dem":81,
    "gn:feature_class":"P",
    "gn:feature_code":"PPL",
    "gn:name":"Luk\u0161akaimis",
    "gn:population":0,
    "gn:timezone":"Europe/Vilnius",
    "iso:country":"LT",
    "name:lit_x_preferred":[
        "Luk\u0161akaimis"
    ],
    "wof:name":"Luksakaimis",
    "wof:placetype":"locality"
},
  "geometry": {"coordinates":[23.69758,54.96584],"type":"Point"}
}