{
  "type": "Feature",
  "properties": {
    "gn:admin1_code":"60",
    "gn:admin2_code":"57.0",
    "gn:asciiname":"Berniuniskiai",
    "gn:country_code":"LT",
    "gn:dem":69,
    "gn:feature_class":"P",
    "gn:feature_code":"PPL",
    "gn:name":"Berni\u016bni\u0161kiai",
    "gn:population":0,
    "gn:timezone":"Europe/Vilnius",
    "iso:country":"LT",
    "name:lit_x_preferred":[
        "Berni\u016bni\u0161kiai"
    ],
    "wof:name":"Berniuniskiai",
    "wof:placetype":"locality"
},
  "geometry": {"coordinates":[24.85202,55.93816999999999],"type":"Point"}
}