{
  "type": "Feature",
  "properties": {
    "gn:admin1_code":"60",
    "gn:admin2_code":"27.0",
    "gn:asciiname":"Senamiestis",
    "gn:country_code":"LT",
    "gn:dem":51,
    "gn:feature_class":"P",
    "gn:feature_code":"PPL",
    "gn:name":"Senamiestis",
    "gn:population":0,
    "gn:timezone":"Europe/Vilnius",
    "iso:country":"LT",
    "name:lit_x_preferred":[
        "Senamiestis"
    ],
    "wof:name":"Senamiestis",
    "wof:placetype":"locality"
},
  "geometry": {"coordinates":[24.36388,55.7666],"type":"Point"}
}