{
  "type": "Feature",
  "properties": {
    "gn:admin1_code":"58.0",
    "gn:admin2_code":"88.0",
    "gn:asciiname":"Bartininkai",
    "gn:country_code":"LT",
    "gn:dem":23,
    "gn:feature_class":"P",
    "gn:feature_code":"PPL",
    "gn:name":"Bartininkai",
    "gn:population":0,
    "gn:timezone":"Europe/Vilnius",
    "iso:country":"LT",
    "name:lit_x_preferred":[
        "Bartininkai"
    ],
    "name:und_x_variant":[
        "Bartininkai Pirmieji",
        "Bartininkay",
        "Bartininkai I"
    ],
    "wof:name":"Bartininkai",
    "wof:placetype":"locality"
},
  "geometry": {"coordinates":[21.617,55.40174],"type":"Point"}
}