{
  "type": "Feature",
  "properties": {
    "gn:admin1_code":"62.0",
    "gn:admin2_code":"94.0",
    "gn:asciiname":"Goniunai",
    "gn:country_code":"LT",
    "gn:dem":64,
    "gn:feature_class":"P",
    "gn:feature_code":"PPL",
    "gn:name":"Goni\u016bnai",
    "gn:population":0,
    "gn:timezone":"Europe/Vilnius",
    "iso:country":"LT",
    "name:und_x_variant":[
        "Gaylyuny",
        "Gaylyunay",
        "Goni\u016bnai"
    ],
    "wof:name":"Goniunai",
    "wof:placetype":"locality"
},
  "geometry": {"coordinates":[23.34987000000001,55.10282],"type":"Point"}
}