{
  "type": "Feature",
  "properties": {
    "gn:gn_country":"LT",
    "gn:gn_fcode":"PPL",
    "gn:gn_pop":0,
    "iso:country":"LT",
    "name:unk_x_variant":[
        "Yesiotraki"
    ],
    "qs_pg:aaroncc":"LT",
    "qs_pg:gn_country":"LT",
    "qs_pg:gn_fcode":"PPL",
    "qs_pg:gn_pop":0,
    "qs_pg:name":"Jiestrakis",
    "qs_pg:name_adm0":"Lietuva",
    "qs_pg:name_adm1":"Kauno Apskritis",
    "qs_pg:photos":27,
    "qs_pg:photos_1k":5,
    "qs_pg:photos_9k":1,
    "qs_pg:photos_9r":2,
    "qs_pg:photos_all":27,
    "qs_pg:photos_sr":2,
    "qs_pg:pop_sr":0,
    "qs_pg:qs_pg_placetype":"locality",
    "qs_pg:qs_pg_placetype_gp":"Town",
    "qs_pg:woe_adm0":23424875,
    "woe:adm0_id":23424875,
    "woe:name_adm0":"Lietuva",
    "woe:name_adm1":"Kauno Apskritis",
    "woe:placetype":"Town",
    "wof:name":"Jiestrakis",
    "wof:placetype":"locality"
},
  "geometry": {"coordinates":[23.68333,54.63333],"type":"Point"}
}