{
  "type": "Feature",
  "properties": {
    "gn:admin1_code":"65.0",
    "gn:admin2_code":"79.0",
    "gn:asciiname":"Bakaloriskes",
    "gn:country_code":"LT",
    "gn:dem":144,
    "gn:feature_class":"P",
    "gn:feature_code":"PPL",
    "gn:name":"Bakalori\u0161k\u0117s",
    "gn:population":0,
    "gn:timezone":"Europe/Vilnius",
    "iso:country":"LT",
    "name:lit_x_preferred":[
        "Bakalori\u0161k\u0117s"
    ],
    "name:und_x_variant":[
        "Bakalori\u0161ki\u0173",
        "Bokolorishskiy",
        "Bakalori\u0161kiai"
    ],
    "wof:name":"Bakaloriskes",
    "wof:placetype":"locality"
},
  "geometry": {"coordinates":[24.56224,54.42878],"type":"Point"}
}