{
  "type": "Feature",
  "properties": {
    "gn:admin1_code":"0.0",
    "gn:asciiname":"Gaizuvele-Pastriune",
    "gn:country_code":"LT",
    "gn:dem":50,
    "gn:feature_class":"P",
    "gn:feature_code":"PPL",
    "gn:name":"Gai\u017euv\u0117l\u0117-Pastri\u016bn\u0117",
    "gn:population":0,
    "gn:timezone":"Europe/Vilnius",
    "iso:country":"LT",
    "name:und_x_variant":[
        "Goyzhevka Podstrune",
        "Gai\u017euv\u0117l\u0117-Pastri\u016bn\u0117"
    ],
    "wof:name":"Gaizuvele-Pastriune",
    "wof:placetype":"locality"
},
  "geometry": {"coordinates":[23.7427,55.14849],"type":"Point"}
}