{
  "type": "Feature",
  "properties": {
    "gn:admin1_code":"61.0",
    "gn:admin2_code":"54.0",
    "gn:asciiname":"Zukaiciai",
    "gn:country_code":"LT",
    "gn:dem":166,
    "gn:feature_class":"P",
    "gn:feature_code":"PPL",
    "gn:name":"\u017dukai\u010diai",
    "gn:population":0,
    "gn:timezone":"Europe/Vilnius",
    "iso:country":"LT",
    "name:und_x_variant":[
        "Zhukovshchizna",
        "\u017dukai\u010diai"
    ],
    "wof:name":"Zukaiciai",
    "wof:placetype":"locality"
},
  "geometry": {"coordinates":[22.65739,55.69786],"type":"Point"}
}