{
  "type": "Feature",
  "properties": {
    "gn:admin1_code":"60",
    "gn:admin2_code":"73.0",
    "gn:asciiname":"Siline",
    "gn:country_code":"LT",
    "gn:dem":124,
    "gn:feature_class":"P",
    "gn:feature_code":"PPL",
    "gn:name":"\u0160ilin\u0117",
    "gn:population":0,
    "gn:timezone":"Europe/Vilnius",
    "iso:country":"LT",
    "name:lit_x_preferred":[
        "\u0160ilin\u0117"
    ],
    "wof:name":"Siline",
    "wof:placetype":"locality"
},
  "geometry": {"coordinates":[25.51344,55.77388000000001],"type":"Point"}
}