{
  "type": "Feature",
  "properties": {
    "gn:admin1_code":"60.0",
    "gn:admin2_code":"27.0",
    "gn:asciiname":"Pinigeliai I",
    "gn:country_code":"LT",
    "gn:dem":54,
    "gn:feature_class":"P",
    "gn:feature_code":"PPL",
    "gn:name":"Pinig\u0117liai I",
    "gn:population":0,
    "gn:timezone":"Europe/Vilnius",
    "iso:country":"LT",
    "name:eng_x_preferred":[
        "Pinig\u0117liai"
    ],
    "name:lit_x_preferred":[
        "Pinig\u0117liai I"
    ],
    "name:rus_x_preferred":[
        "\u041f\u0438\u043d\u0438\u0433\u0435\u043b\u044f\u0439"
    ],
    "wof:name":"Pinigeliai I",
    "wof:placetype":"locality"
},
  "geometry": {"coordinates":[24.42144,55.79237],"type":"Point"}
}