{
  "type": "Feature",
  "properties": {
    "gn:admin1_code":"62.0",
    "gn:admin2_code":"87.0",
    "gn:asciiname":"Jokubaiciai",
    "gn:country_code":"LT",
    "gn:dem":110,
    "gn:feature_class":"P",
    "gn:feature_code":"PPL",
    "gn:name":"Jok\u016bbai\u010diai",
    "gn:population":0,
    "gn:timezone":"Europe/Vilnius",
    "iso:country":"LT",
    "name:und_x_variant":[
        "Yakubaychyay",
        "Jok\u016bbai\u010diai"
    ],
    "wof:name":"Jokubaiciai",
    "wof:placetype":"locality"
},
  "geometry": {"coordinates":[22.13164,55.46882],"type":"Point"}
}