{
  "type": "Feature",
  "properties": {
    "gn:admin1_code":"64",
    "gn:admin2_code":"62.0",
    "gn:asciiname":"Bambeniske",
    "gn:country_code":"LT",
    "gn:dem":150,
    "gn:feature_class":"P",
    "gn:feature_code":"PPL",
    "gn:name":"Bamb\u0117ni\u0161k\u0117",
    "gn:population":0,
    "gn:timezone":"Europe/Vilnius",
    "iso:country":"LT",
    "name:lit_x_preferred":[
        "Bamb\u0117ni\u0161k\u0117"
    ],
    "wof:name":"Bambeniske",
    "wof:placetype":"locality"
},
  "geometry": {"coordinates":[25.55722,55.17394],"type":"Point"}
}