{
  "type": "Feature",
  "properties": {
    "gn:admin1_code":"57.0",
    "gn:admin2_code":"53.0",
    "gn:asciiname":"Margininkai",
    "gn:country_code":"LT",
    "gn:dem":83,
    "gn:feature_class":"P",
    "gn:feature_code":"PPL",
    "gn:name":"Margininkai",
    "gn:population":0,
    "gn:timezone":"Europe/Vilnius",
    "iso:country":"LT",
    "name:und_x_variant":[
        "Antomir",
        "Antomiras",
        "Margininkai"
    ],
    "wof:name":"Margininkai",
    "wof:placetype":"locality"
},
  "geometry": {"coordinates":[23.86167,55.52011],"type":"Point"}
}