{
  "type": "Feature",
  "properties": {
    "gn:admin1_code":"60",
    "gn:admin2_code":"73.0",
    "gn:asciiname":"Zyboliai",
    "gn:country_code":"LT",
    "gn:dem":119,
    "gn:feature_class":"P",
    "gn:feature_code":"PPL",
    "gn:name":"Zyboliai",
    "gn:population":0,
    "gn:timezone":"Europe/Vilnius",
    "iso:country":"LT",
    "name:lit_x_preferred":[
        "Zyboliai"
    ],
    "wof:name":"Zyboliai",
    "wof:placetype":"locality"
},
  "geometry": {"coordinates":[25.81968,55.90318000000001],"type":"Point"}
}