{
  "type": "Feature",
  "properties": {
    "gn:admin1_code":"65",
    "gn:admin2_code":"81.0",
    "gn:asciiname":"Gaiciunai",
    "gn:country_code":"LT",
    "gn:dem":114,
    "gn:feature_class":"P",
    "gn:feature_code":"PPL",
    "gn:name":"Gaici\u016bnai",
    "gn:population":0,
    "gn:timezone":"Europe/Vilnius",
    "iso:country":"LT",
    "name:lit_x_preferred":[
        "Gaici\u016bnai"
    ],
    "wof:name":"Gaiciunai",
    "wof:placetype":"locality"
},
  "geometry": {"coordinates":[24.74985,55.1734],"type":"Point"}
}