{
  "type": "Feature",
  "properties": {
    "gn:admin1_code":"64.0",
    "gn:admin2_code":"45.0",
    "gn:asciiname":"Pupiniai",
    "gn:country_code":"LT",
    "gn:dem":153,
    "gn:feature_class":"P",
    "gn:feature_code":"PPL",
    "gn:name":"Pupiniai",
    "gn:population":0,
    "gn:timezone":"Europe/Vilnius",
    "iso:country":"LT",
    "name:lit_x_preferred":[
        "Pupiniai"
    ],
    "wof:name":"Pupiniai",
    "wof:placetype":"locality"
},
  "geometry": {"coordinates":[26.44128,55.42143000000001],"type":"Point"}
}