{
  "type": "Feature",
  "properties": {
    "gn:admin1_code":"62.0",
    "gn:admin2_code":"63.0",
    "gn:asciiname":"Adomiskiai",
    "gn:country_code":"LT",
    "gn:dem":22,
    "gn:feature_class":"P",
    "gn:feature_code":"PPL",
    "gn:name":"Adomi\u0161kiai",
    "gn:population":0,
    "gn:timezone":"Europe/Vilnius",
    "iso:country":"LT",
    "name:und_x_variant":[
        "Adomishken",
        "Adomi\u0161kiai"
    ],
    "wof:name":"Adomiskiai",
    "wof:placetype":"locality"
},
  "geometry": {"coordinates":[22.26442,55.1463],"type":"Point"}
}