{
  "type": "Feature",
  "properties": {
    "gn:admin1_code":"0.0",
    "gn:asciiname":"Allonys",
    "gn:country_code":"LT",
    "gn:dem":122,
    "gn:feature_class":"P",
    "gn:feature_code":"PPL",
    "gn:name":"Allonys",
    "gn:population":0,
    "gn:timezone":"Europe/Vilnius",
    "iso:country":"LT",
    "wof:name":"Allonys",
    "wof:placetype":"locality"
},
  "geometry": {"coordinates":[24.86667000000001,55.18333000000001],"type":"Point"}
}