{
  "type": "Feature",
  "properties": {
    "gn:admin1_code":"59.0",
    "gn:admin2_code":"84.0",
    "gn:asciiname":"Kaimelis",
    "gn:country_code":"LT",
    "gn:dem":30,
    "gn:feature_class":"P",
    "gn:feature_code":"PPL",
    "gn:name":"Kaimelis",
    "gn:population":0,
    "gn:timezone":"Europe/Vilnius",
    "iso:country":"LT",
    "name:und_x_variant":[
        "Kaimelio",
        "Kaymele",
        "Kaimelis"
    ],
    "wof:name":"Kaimelis",
    "wof:placetype":"locality"
},
  "geometry": {"coordinates":[22.80579,55.06578],"type":"Point"}
}