{
  "type": "Feature",
  "properties": {
    "gn:admin1_code":"65",
    "gn:admin2_code":"86.0",
    "gn:asciiname":"Birzija",
    "gn:country_code":"LT",
    "gn:dem":159,
    "gn:feature_class":"P",
    "gn:feature_code":"PPL",
    "gn:name":"Bir\u017eija",
    "gn:population":0,
    "gn:timezone":"Europe/Vilnius",
    "iso:country":"LT",
    "name:lit_x_preferred":[
        "Bir\u017eija"
    ],
    "wof:name":"Birzija",
    "wof:placetype":"locality"
},
  "geometry": {"coordinates":[26.14305,55.27329],"type":"Point"}
}