{
  "type": "Feature",
  "properties": {
    "gn:admin1_code":"57.0",
    "gn:admin2_code":"72.0",
    "gn:asciiname":"Kunigiskiai",
    "gn:country_code":"LT",
    "gn:dem":89,
    "gn:feature_class":"P",
    "gn:feature_code":"PPL",
    "gn:name":"Kunigi\u0161kiai",
    "gn:population":0,
    "gn:timezone":"Europe/Vilnius",
    "iso:country":"LT",
    "name:und_x_variant":[
        "Kungishkyay",
        "Kunigishki",
        "Kunigi\u0161kiai"
    ],
    "wof:name":"Kunigiskiai",
    "wof:placetype":"locality"
},
  "geometry": {"coordinates":[23.47178,55.28064000000001],"type":"Point"}
}