{
  "type": "Feature",
  "properties": {
    "iso:country":"LT",
    "qs_pg:aaroncc":"LT",
    "qs_pg:name":"Plateliu Seniunija",
    "qs_pg:name_adm0":"Lietuva",
    "qs_pg:name_adm1":"Tel\u0161i\u00f9 Apskritis",
    "qs_pg:photos":124,
    "qs_pg:photos_1k":25,
    "qs_pg:photos_9k":1,
    "qs_pg:photos_9r":4,
    "qs_pg:photos_all":182,
    "qs_pg:photos_sr":3,
    "qs_pg:pop_sr":0,
    "qs_pg:qs_pg_placetype":"localadmin",
    "qs_pg:qs_pg_placetype_gp":"LocalAdmin",
    "qs_pg:woe_adm0":23424875,
    "woe:adm0_id":23424875,
    "woe:name_adm0":"Lietuva",
    "woe:name_adm1":"Tel\u0161i\u00f9 Apskritis",
    "woe:placetype":"LocalAdmin",
    "wof:name":"Plateliu Seniunija",
    "wof:placetype":"localadmin"
},
  "geometry": {"coordinates":[21.8135775,56.04678],"type":"Point"}
}