{
  "type": "Feature",
  "properties": {
    "gn:admin1_code":"61.0",
    "gn:admin2_code":"29.0",
    "gn:asciiname":"Laukstuciai",
    "gn:country_code":"LT",
    "gn:dem":100,
    "gn:feature_class":"P",
    "gn:feature_code":"PPL",
    "gn:name":"Laukstu\u010diai",
    "gn:population":0,
    "gn:timezone":"Europe/Vilnius",
    "iso:country":"LT",
    "name:lit_x_preferred":[
        "Laukstu\u010diai"
    ],
    "name:und_x_variant":[
        "Lauk\u0161tu\u010diai"
    ],
    "wof:name":"Laukstuciai",
    "wof:placetype":"locality"
},
  "geometry": {"coordinates":[22.84828,56.02374],"type":"Point"}
}