{
  "type": "Feature",
  "properties": {
    "gn:admin1_code":"64",
    "gn:admin2_code":"45.0",
    "gn:asciiname":"Benesiai",
    "gn:country_code":"LT",
    "gn:dem":151,
    "gn:feature_class":"P",
    "gn:feature_code":"PPL",
    "gn:name":"Ben\u0117\u0161iai",
    "gn:population":0,
    "gn:timezone":"Europe/Vilnius",
    "iso:country":"LT",
    "name:lit_x_preferred":[
        "Ben\u0117\u0161iai"
    ],
    "wof:name":"Benesiai",
    "wof:placetype":"locality"
},
  "geometry": {"coordinates":[26.4724,55.39571],"type":"Point"}
}