{
  "type": "Feature",
  "properties": {
    "gn:admin1_code":"59",
    "gn:admin2_code":"84.0",
    "gn:asciiname":"Skarbudis",
    "gn:country_code":"LT",
    "gn:dem":49,
    "gn:feature_class":"P",
    "gn:feature_code":"PPL",
    "gn:name":"Skarb\u016bdis",
    "gn:population":0,
    "gn:timezone":"Europe/Vilnius",
    "iso:country":"LT",
    "name:lit_x_preferred":[
        "Skarb\u016bdis"
    ],
    "wof:name":"Skarbudis",
    "wof:placetype":"locality"
},
  "geometry": {"coordinates":[23.15819,54.7983],"type":"Point"}
}