{
  "type": "Feature",
  "properties": {
    "gn:admin1_code":"65.0",
    "gn:admin2_code":"81.0",
    "gn:asciiname":"Baravykai",
    "gn:country_code":"LT",
    "gn:dem":77,
    "gn:feature_class":"P",
    "gn:feature_code":"PPL",
    "gn:name":"Baravykai",
    "gn:population":0,
    "gn:timezone":"Europe/Vilnius",
    "iso:country":"LT",
    "name:und_x_variant":[
        "Boroviki",
        "Baravykai"
    ],
    "wof:name":"Baravykai",
    "wof:placetype":"locality"
},
  "geometry": {"coordinates":[24.73698,55.33885],"type":"Point"}
}