{
  "type": "Feature",
  "properties": {
    "gn:admin1_code":"58",
    "gn:admin2_code":"75.0",
    "gn:asciiname":"Baidotai",
    "gn:country_code":"LT",
    "gn:dem":62,
    "gn:feature_class":"P",
    "gn:feature_code":"PPL",
    "gn:name":"Baidotai",
    "gn:population":0,
    "gn:timezone":"Europe/Vilnius",
    "iso:country":"LT",
    "name:lit_x_preferred":[
        "Baidotai"
    ],
    "wof:name":"Baidotai",
    "wof:placetype":"locality"
},
  "geometry": {"coordinates":[21.64094,56.09465],"type":"Point"}
}