{
  "type": "Feature",
  "properties": {
    "gn:admin1_code":"56",
    "gn:admin2_code":"59.0",
    "gn:asciiname":"Okta",
    "gn:country_code":"LT",
    "gn:dem":134,
    "gn:feature_class":"P",
    "gn:feature_code":"PPL",
    "gn:name":"Okta",
    "gn:population":0,
    "gn:timezone":"Europe/Vilnius",
    "iso:country":"LT",
    "name:lit_x_preferred":[
        "Okta"
    ],
    "wof:name":"Okta",
    "wof:placetype":"locality"
},
  "geometry": {"coordinates":[23.8256,54.21312],"type":"Point"}
}