{
  "type": "Feature",
  "properties": {
    "gn:admin1_code":"65",
    "gn:admin2_code":"86.0",
    "gn:asciiname":"Subatiske",
    "gn:country_code":"LT",
    "gn:dem":135,
    "gn:feature_class":"P",
    "gn:feature_code":"PPL",
    "gn:name":"Subati\u0161k\u0117",
    "gn:population":0,
    "gn:timezone":"Europe/Vilnius",
    "iso:country":"LT",
    "name:lit_x_preferred":[
        "Subati\u0161k\u0117"
    ],
    "wof:name":"Subatiske",
    "wof:placetype":"locality"
},
  "geometry": {"coordinates":[26.64884,55.17024],"type":"Point"}
}