{
  "type": "Feature",
  "properties": {
    "gn:admin1_code":"60",
    "gn:admin2_code":"27.0",
    "gn:asciiname":"Ragaine",
    "gn:country_code":"LT",
    "gn:dem":47,
    "gn:feature_class":"P",
    "gn:feature_code":"PPL",
    "gn:name":"Ragain\u0117",
    "gn:population":0,
    "gn:timezone":"Europe/Vilnius",
    "iso:country":"LT",
    "name:lit_x_preferred":[
        "Ragain\u0117"
    ],
    "wof:name":"Ragaine",
    "wof:placetype":"locality"
},
  "geometry": {"coordinates":[24.17621,55.70116],"type":"Point"}
}