{
  "type": "Feature",
  "properties": {
    "gn:admin1_code":"59.0",
    "gn:admin2_code":"58.0",
    "gn:asciiname":"Laukiniske",
    "gn:country_code":"LT",
    "gn:dem":56,
    "gn:feature_class":"P",
    "gn:feature_code":"PPL",
    "gn:name":"Laukini\u0161k\u0117",
    "gn:population":0,
    "gn:timezone":"Europe/Vilnius",
    "iso:country":"LT",
    "name:lit_x_preferred":[
        "Laukini\u0161k\u0117"
    ],
    "wof:name":"Laukiniske",
    "wof:placetype":"locality"
},
  "geometry": {"coordinates":[23.34867,54.82968],"type":"Point"}
}