{
  "type": "Feature",
  "properties": {
    "gn:admin1_code":"65",
    "gn:admin2_code":"13.0",
    "gn:asciiname":"Uzuglobis",
    "gn:country_code":"LT",
    "gn:dem":217,
    "gn:feature_class":"P",
    "gn:feature_code":"PPL",
    "gn:name":"U\u017euglobis",
    "gn:population":0,
    "gn:timezone":"Europe/Vilnius",
    "iso:country":"LT",
    "name:lit_x_preferred":[
        "U\u017euglobis"
    ],
    "wof:name":"Uzuglobis",
    "wof:placetype":"locality"
},
  "geometry": {"coordinates":[25.41838,54.56482],"type":"Point"}
}