{
  "type": "Feature",
  "properties": {
    "gn:admin1_code":"65",
    "gn:admin2_code":"85.0",
    "gn:asciiname":"Jasiunu Gelezinkelio Stotis",
    "gn:country_code":"LT",
    "gn:dem":159,
    "gn:feature_class":"P",
    "gn:feature_code":"PPL",
    "gn:name":"Ja\u0161i\u016bn\u0173 Gele\u017einkelio Stotis",
    "gn:population":0,
    "gn:timezone":"Europe/Vilnius",
    "iso:country":"LT",
    "name:lit_x_preferred":[
        "Ja\u0161i\u016bn\u0173 Gele\u017einkelio Stotis"
    ],
    "name:lit_x_variant":[
        "Gele\u017einkelio Stotis Ja\u0161i\u016bnai"
    ],
    "wof:name":"Jasiunu Gelezinkelio Stotis",
    "wof:placetype":"locality"
},
  "geometry": {"coordinates":[25.28013,54.45253],"type":"Point"}
}