{
  "type": "Feature",
  "properties": {
    "gn:admin1_code":"57",
    "gn:admin2_code":"53.0",
    "gn:asciiname":"Jankunai",
    "gn:country_code":"LT",
    "gn:dem":85,
    "gn:feature_class":"P",
    "gn:feature_code":"PPL",
    "gn:name":"Jank\u016bnai",
    "gn:population":0,
    "gn:timezone":"Europe/Vilnius",
    "iso:country":"LT",
    "name:lit_x_preferred":[
        "Jank\u016bnai"
    ],
    "wof:name":"Jankunai",
    "wof:placetype":"locality"
},
  "geometry": {"coordinates":[23.75305,55.4499],"type":"Point"}
}