{
  "type": "Feature",
  "properties": {
    "gn:admin1_code":"0.0",
    "gn:asciiname":"Barsiai",
    "gn:cc2":"LT",
    "gn:country_code":"LT",
    "gn:dem":115,
    "gn:feature_class":"P",
    "gn:feature_code":"PPL",
    "gn:name":"Bar\u0161iai",
    "gn:population":0,
    "gn:timezone":"Europe/Vilnius",
    "iso:country":"LT",
    "name:und_x_variant":[
        "Puki-Barsze",
        "Barshyay",
        "Bar\u0161i\u0173",
        "Bar\u0161iai"
    ],
    "wof:name":"Barsiai",
    "wof:placetype":"locality"
},
  "geometry": {"coordinates":[21.88333,56.18333000000001],"type":"Point"}
}