{
  "type": "Feature",
  "properties": {
    "gn:admin1_code":"60",
    "gn:admin2_code":"27.0",
    "gn:asciiname":"Kareiviskiai",
    "gn:country_code":"LT",
    "gn:dem":55,
    "gn:feature_class":"P",
    "gn:feature_code":"PPL",
    "gn:name":"Kareivi\u0161kiai",
    "gn:population":0,
    "gn:timezone":"Europe/Vilnius",
    "iso:country":"LT",
    "name:lit_x_preferred":[
        "Kareivi\u0161kiai"
    ],
    "wof:name":"Kareiviskiai",
    "wof:placetype":"locality"
},
  "geometry": {"coordinates":[24.38293,55.83544000000001],"type":"Point"}
}