{
  "type": "Feature",
  "properties": {
    "gn:admin1_code":"60",
    "gn:admin2_code":"57.0",
    "gn:asciiname":"Bajoriskiai",
    "gn:country_code":"LT",
    "gn:dem":87,
    "gn:feature_class":"P",
    "gn:feature_code":"PPL",
    "gn:name":"Bajori\u0161kiai",
    "gn:population":0,
    "gn:timezone":"Europe/Vilnius",
    "iso:country":"LT",
    "name:lit_x_preferred":[
        "Bajori\u0161kiai"
    ],
    "wof:name":"Bajoriskiai",
    "wof:placetype":"locality"
},
  "geometry": {"coordinates":[24.83538,55.77697],"type":"Point"}
}