{
  "type": "Feature",
  "properties": {
    "gn:admin1_code":"61.0",
    "gn:admin2_code":"29.0",
    "gn:asciiname":"Jakstaiciukai",
    "gn:country_code":"LT",
    "gn:dem":119,
    "gn:feature_class":"P",
    "gn:feature_code":"PPL",
    "gn:name":"Jak\u0161tai\u010diukai",
    "gn:population":0,
    "gn:timezone":"Europe/Vilnius",
    "iso:country":"LT",
    "name:lit_x_preferred":[
        "Jak\u0161tai\u010diukai"
    ],
    "wof:name":"Jakstaiciukai",
    "wof:placetype":"locality"
},
  "geometry": {"coordinates":[23.14336,55.88783000000001],"type":"Point"}
}