{
  "type": "Feature",
  "properties": {
    "gn:admin1_code":"61",
    "gn:admin2_code":"54.0",
    "gn:asciiname":"Radiske",
    "gn:country_code":"LT",
    "gn:dem":145,
    "gn:feature_class":"P",
    "gn:feature_code":"PPL",
    "gn:name":"Radi\u0161k\u0117",
    "gn:population":0,
    "gn:timezone":"Europe/Vilnius",
    "iso:country":"LT",
    "name:lit_x_preferred":[
        "Radi\u0161k\u0117"
    ],
    "wof:name":"Radiske",
    "wof:placetype":"locality"
},
  "geometry": {"coordinates":[22.65206,55.64234],"type":"Point"}
}