{
  "type": "Feature",
  "properties": {
    "gn:admin1_code":"64",
    "gn:admin2_code":"62.0",
    "gn:asciiname":"Ozeliskes",
    "gn:country_code":"LT",
    "gn:dem":156,
    "gn:feature_class":"P",
    "gn:feature_code":"PPL",
    "gn:name":"O\u017eeli\u0161k\u0117s",
    "gn:population":0,
    "gn:timezone":"Europe/Vilnius",
    "iso:country":"LT",
    "name:lit_x_preferred":[
        "O\u017eeli\u0161k\u0117s"
    ],
    "wof:name":"Ozeliskes",
    "wof:placetype":"locality"
},
  "geometry": {"coordinates":[25.40255,55.29581],"type":"Point"}
}