{
  "type": "Feature",
  "properties": {
    "gn:admin1_code":"56",
    "gn:admin2_code":"38.0",
    "gn:asciiname":"Aleksandrava",
    "gn:country_code":"LT",
    "gn:dem":137,
    "gn:feature_class":"P",
    "gn:feature_code":"PPL",
    "gn:name":"Aleksandrava",
    "gn:population":0,
    "gn:timezone":"Europe/Vilnius",
    "iso:country":"LT",
    "name:lit_x_preferred":[
        "Aleksandrava"
    ],
    "wof:name":"Aleksandrava",
    "wof:placetype":"locality"
},
  "geometry": {"coordinates":[24.53086,54.33414000000001],"type":"Point"}
}