{
  "type": "Feature",
  "properties": {
    "gn:admin1_code":"62.0",
    "gn:admin2_code":"87.0",
    "gn:asciiname":"Plausiniske",
    "gn:country_code":"LT",
    "gn:dem":124,
    "gn:feature_class":"P",
    "gn:feature_code":"PPL",
    "gn:name":"Plau\u0161ini\u0161k\u0117",
    "gn:population":0,
    "gn:timezone":"Europe/Vilnius",
    "iso:country":"LT",
    "name:lit_x_preferred":[
        "Plau\u0161ini\u0161k\u0117"
    ],
    "name:und_x_variant":[
        "Plau\u0161ini\u0161ke"
    ],
    "wof:name":"Plausiniske",
    "wof:placetype":"locality"
},
  "geometry": {"coordinates":[22.3473,55.50881999999999],"type":"Point"}
}