{
  "type": "Feature",
  "properties": {
    "gn:admin1_code":"58.0",
    "gn:admin2_code":"75.0",
    "gn:asciiname":"Kaukolikai",
    "gn:country_code":"LT",
    "gn:dem":71,
    "gn:feature_class":"P",
    "gn:feature_code":"PPL",
    "gn:name":"Kaukolikai",
    "gn:population":0,
    "gn:timezone":"Europe/Vilnius",
    "iso:country":"LT",
    "name:lit_x_preferred":[
        "Kaukolikai"
    ],
    "name:und_x_variant":[
        "Kaukolik\u0173",
        "Kaukoliki",
        "Kaukolikay",
        "Kaukolikyay"
    ],
    "wof:name":"Kaukolikai",
    "wof:placetype":"locality"
},
  "geometry": {"coordinates":[21.7181,56.23143],"type":"Point"}
}