{
  "type": "Feature",
  "properties": {
    "gn:admin1_code":"62",
    "gn:admin2_code":"77.0",
    "gn:asciiname":"Kalniskiai",
    "gn:country_code":"LT",
    "gn:dem":116,
    "gn:feature_class":"P",
    "gn:feature_code":"PPL",
    "gn:name":"Kalni\u0161kiai",
    "gn:population":0,
    "gn:timezone":"Europe/Vilnius",
    "iso:country":"LT",
    "name:lit_x_preferred":[
        "Kalni\u0161kiai"
    ],
    "wof:name":"Kalniskiai",
    "wof:placetype":"locality"
},
  "geometry": {"coordinates":[22.61887,55.44789],"type":"Point"}
}