{
  "type": "Feature",
  "properties": {
    "gn:admin1_code":"64",
    "gn:admin2_code":"82.0",
    "gn:asciiname":"Aviniskis",
    "gn:country_code":"LT",
    "gn:dem":189,
    "gn:feature_class":"P",
    "gn:feature_code":"PPL",
    "gn:name":"Avini\u0161kis",
    "gn:population":0,
    "gn:timezone":"Europe/Vilnius",
    "iso:country":"LT",
    "name:lit_x_preferred":[
        "Avini\u0161kis"
    ],
    "wof:name":"Aviniskis",
    "wof:placetype":"locality"
},
  "geometry": {"coordinates":[25.75145,55.39974],"type":"Point"}
}