{
  "type": "Feature",
  "properties": {
    "gn:admin1_code":"57",
    "gn:admin2_code":"69.0",
    "gn:asciiname":"Pramieziai",
    "gn:country_code":"LT",
    "gn:dem":102,
    "gn:feature_class":"P",
    "gn:feature_code":"PPL",
    "gn:name":"Pramie\u017eiai",
    "gn:population":0,
    "gn:timezone":"Europe/Vilnius",
    "iso:country":"LT",
    "name:lit_x_preferred":[
        "Pramie\u017eiai"
    ],
    "wof:name":"Pramieziai",
    "wof:placetype":"locality"
},
  "geometry": {"coordinates":[24.28876,54.62472],"type":"Point"}
}