{
  "type": "Feature",
  "properties": {
    "gn:admin1_code":"60.0",
    "gn:admin2_code":"73.0",
    "gn:asciiname":"Bagdoniskis",
    "gn:country_code":"LT",
    "gn:dem":154,
    "gn:feature_class":"P",
    "gn:feature_code":"PPL",
    "gn:name":"Bagdoni\u0161kis",
    "gn:population":0,
    "gn:timezone":"Europe/Vilnius",
    "iso:country":"LT",
    "name:eng_x_preferred":[
        "Bagdoni\u0161kis"
    ],
    "name:rus_x_preferred":[
        "\u0411\u0430\u0433\u0434\u043e\u043d\u0438\u0448\u043a\u0438\u0441"
    ],
    "wof:name":"Bagdoniskis",
    "wof:placetype":"locality"
},
  "geometry": {"coordinates":[25.72426,55.89149000000001],"type":"Point"}
}