{
  "type": "Feature",
  "properties": {
    "gn:admin1_code":"56.0",
    "gn:admin2_code":"11.0",
    "gn:asciiname":"Jurkonys",
    "gn:country_code":"LT",
    "gn:dem":137,
    "gn:feature_class":"P",
    "gn:feature_code":"PPL",
    "gn:name":"Jurkonys",
    "gn:population":0,
    "gn:timezone":"Europe/Vilnius",
    "iso:country":"LT",
    "name:und_x_variant":[
        "Yurkonis",
        "Jurkoni\u0173",
        "Yurkantsy",
        "Jurkonys"
    ],
    "wof:name":"Jurkonys",
    "wof:placetype":"locality"
},
  "geometry": {"coordinates":[24.36734,54.49497],"type":"Point"}
}