{
  "type": "Feature",
  "properties": {
    "gn:admin1_code":"65",
    "gn:admin2_code":"13.0",
    "gn:asciiname":"Sakiskes",
    "gn:country_code":"LT",
    "gn:dem":133,
    "gn:feature_class":"P",
    "gn:feature_code":"PPL",
    "gn:name":"Saki\u0161k\u0117s",
    "gn:population":0,
    "gn:timezone":"Europe/Vilnius",
    "iso:country":"LT",
    "name:lit_x_preferred":[
        "Saki\u0161k\u0117s"
    ],
    "wof:name":"Sakiskes",
    "wof:placetype":"locality"
},
  "geometry": {"coordinates":[25.39883,54.82293000000001],"type":"Point"}
}