{
  "type": "Feature",
  "properties": {
    "gn:admin1_code":"64",
    "gn:admin2_code":"43.0",
    "gn:asciiname":"Petrauciskes",
    "gn:country_code":"LT",
    "gn:dem":162,
    "gn:feature_class":"P",
    "gn:feature_code":"PPL",
    "gn:name":"Petrau\u010di\u0161k\u0117s",
    "gn:population":0,
    "gn:timezone":"Europe/Vilnius",
    "iso:country":"LT",
    "name:lit_x_preferred":[
        "Petrau\u010di\u0161k\u0117s"
    ],
    "wof:name":"Petrauciskes",
    "wof:placetype":"locality"
},
  "geometry": {"coordinates":[25.9895,55.76866999999999],"type":"Point"}
}