{
  "type": "Feature",
  "properties": {
    "gn:admin1_code":"62",
    "gn:admin2_code":"87.0",
    "gn:asciiname":"Zasinalis",
    "gn:country_code":"LT",
    "gn:dem":89,
    "gn:feature_class":"P",
    "gn:feature_code":"PPL",
    "gn:name":"\u017d\u0105sinalis",
    "gn:population":0,
    "gn:timezone":"Europe/Vilnius",
    "iso:country":"LT",
    "name:lit_x_preferred":[
        "\u017d\u0105sinalis"
    ],
    "wof:name":"Zasinalis",
    "wof:placetype":"locality"
},
  "geometry": {"coordinates":[22.07242,55.49429],"type":"Point"}
}