{
  "type": "Feature",
  "properties": {
    "gn:admin1_code":"57.0",
    "gn:admin2_code":"53.0",
    "gn:asciiname":"Goziai",
    "gn:country_code":"LT",
    "gn:dem":75,
    "gn:feature_class":"P",
    "gn:feature_code":"PPL",
    "gn:name":"Go\u017eiai",
    "gn:population":0,
    "gn:timezone":"Europe/Vilnius",
    "iso:country":"LT",
    "name:und_x_variant":[
        "Gozhyay",
        "Go\u017eiai"
    ],
    "wof:name":"Goziai",
    "wof:placetype":"locality"
},
  "geometry": {"coordinates":[23.58198,55.26093],"type":"Point"}
}