{
  "type": "Feature",
  "properties": {
    "gn:admin1_code":"65",
    "gn:admin2_code":"85.0",
    "gn:asciiname":"Liupkiskes",
    "gn:country_code":"LT",
    "gn:dem":170,
    "gn:feature_class":"P",
    "gn:feature_code":"PPL",
    "gn:name":"Liupki\u0161k\u0117s",
    "gn:population":0,
    "gn:timezone":"Europe/Vilnius",
    "iso:country":"LT",
    "name:lit_x_preferred":[
        "Liupki\u0161k\u0117s"
    ],
    "wof:name":"Liupkiskes",
    "wof:placetype":"locality"
},
  "geometry": {"coordinates":[25.01024,54.23491],"type":"Point"}
}