{
  "type": "Feature",
  "properties": {
    "gn:admin1_code":"57",
    "gn:admin2_code":"72.0",
    "gn:asciiname":"Leliusiai",
    "gn:country_code":"LT",
    "gn:dem":87,
    "gn:feature_class":"P",
    "gn:feature_code":"PPL",
    "gn:name":"Leliu\u0161iai",
    "gn:population":0,
    "gn:timezone":"Europe/Vilnius",
    "iso:country":"LT",
    "name:lit_x_preferred":[
        "Leliu\u0161iai"
    ],
    "wof:name":"Leliusiai",
    "wof:placetype":"locality"
},
  "geometry": {"coordinates":[23.46743,55.28765],"type":"Point"}
}