{
  "type": "Feature",
  "properties": {
    "gn:admin1_code":"61",
    "gn:admin2_code":"54.0",
    "gn:asciiname":"Grumbliai",
    "gn:country_code":"LT",
    "gn:dem":164,
    "gn:feature_class":"P",
    "gn:feature_code":"PPL",
    "gn:name":"Grumbliai",
    "gn:population":0,
    "gn:timezone":"Europe/Vilnius",
    "iso:country":"LT",
    "name:lit_x_preferred":[
        "Grumbliai"
    ],
    "wof:name":"Grumbliai",
    "wof:placetype":"locality"
},
  "geometry": {"coordinates":[22.64661,55.5882],"type":"Point"}
}