{
  "type": "Feature",
  "properties": {
    "gn:admin1_code":"64",
    "gn:admin2_code":"45.0",
    "gn:asciiname":"Becionys",
    "gn:country_code":"LT",
    "gn:dem":179,
    "gn:feature_class":"P",
    "gn:feature_code":"PPL",
    "gn:name":"B\u0117\u010dionys",
    "gn:population":0,
    "gn:timezone":"Europe/Vilnius",
    "iso:country":"LT",
    "name:lit_x_preferred":[
        "B\u0117\u010dionys"
    ],
    "wof:name":"Becionys",
    "wof:placetype":"locality"
},
  "geometry": {"coordinates":[26.20515,55.32556],"type":"Point"}
}