{
  "type": "Feature",
  "properties": {
    "gn:admin1_code":"0.0",
    "gn:asciiname":"Kunkojai",
    "gn:country_code":"LT",
    "gn:dem":125,
    "gn:feature_class":"P",
    "gn:feature_code":"PPL",
    "gn:name":"Kunkojai",
    "gn:population":0,
    "gn:timezone":"Europe/Vilnius",
    "iso:country":"LT",
    "wof:name":"Kunkojai",
    "wof:placetype":"locality"
},
  "geometry": {"coordinates":[23.15,55.45],"type":"Point"}
}