{
  "type": "Feature",
  "properties": {
    "gn:admin1_code":"56.0",
    "gn:admin2_code":"38.0",
    "gn:asciiname":"Butvydonys",
    "gn:country_code":"LT",
    "gn:dem":145,
    "gn:feature_class":"P",
    "gn:feature_code":"PPL",
    "gn:name":"Butvydonys",
    "gn:population":0,
    "gn:timezone":"Europe/Vilnius",
    "iso:country":"LT",
    "wof:name":"Butvydonys",
    "wof:placetype":"locality"
},
  "geometry": {"coordinates":[24.82997,54.27676999999999],"type":"Point"}
}