{
  "type": "Feature",
  "properties": {
    "gn:admin1_code":"57.0",
    "gn:admin2_code":"49.0",
    "gn:asciiname":"Kaukine",
    "gn:country_code":"LT",
    "gn:dem":158,
    "gn:feature_class":"P",
    "gn:feature_code":"PPL",
    "gn:name":"Kaukin\u0117",
    "gn:population":0,
    "gn:timezone":"Europe/Vilnius",
    "iso:country":"LT",
    "name:und_x_variant":[
        "Kavkini",
        "Kaukin\u0117"
    ],
    "wof:name":"Kaukine",
    "wof:placetype":"locality"
},
  "geometry": {"coordinates":[24.47647000000001,54.71416],"type":"Point"}
}