{
  "type": "Feature",
  "properties": {
    "gn:admin1_code":"59",
    "gn:admin2_code":"39.0",
    "gn:asciiname":"Bambiniai",
    "gn:country_code":"LT",
    "gn:dem":181,
    "gn:feature_class":"P",
    "gn:feature_code":"PPL",
    "gn:name":"Bambiniai",
    "gn:population":0,
    "gn:timezone":"Europe/Vilnius",
    "iso:country":"LT",
    "name:lit_x_preferred":[
        "Bambiniai"
    ],
    "wof:name":"Bambiniai",
    "wof:placetype":"locality"
},
  "geometry": {"coordinates":[22.90683,54.46533],"type":"Point"}
}