{
  "type": "Feature",
  "properties": {
    "gn:admin1_code":"65",
    "gn:admin2_code":"85.0",
    "gn:asciiname":"Azulomis",
    "gn:country_code":"LT",
    "gn:dem":180,
    "gn:feature_class":"P",
    "gn:feature_code":"PPL",
    "gn:name":"A\u017eulomis",
    "gn:population":0,
    "gn:timezone":"Europe/Vilnius",
    "iso:country":"LT",
    "name:lit_x_preferred":[
        "A\u017eulomis"
    ],
    "wof:name":"Azulomis",
    "wof:placetype":"locality"
},
  "geometry": {"coordinates":[25.37861,54.33643000000001],"type":"Point"}
}