{
  "type": "Feature",
  "properties": {
    "gn:admin1_code":"59",
    "gn:admin2_code":"84.0",
    "gn:asciiname":"Leliokiske",
    "gn:country_code":"LT",
    "gn:dem":49,
    "gn:feature_class":"P",
    "gn:feature_code":"PPL",
    "gn:name":"Lelioki\u0161k\u0117",
    "gn:population":0,
    "gn:timezone":"Europe/Vilnius",
    "iso:country":"LT",
    "name:lit_x_preferred":[
        "Lelioki\u0161k\u0117"
    ],
    "wof:name":"Leliokiske",
    "wof:placetype":"locality"
},
  "geometry": {"coordinates":[23.12166,54.81878],"type":"Point"}
}