{
  "type": "Feature",
  "properties": {
    "gn:admin1_code":"64",
    "gn:admin2_code":"45.0",
    "gn:asciiname":"Popovka",
    "gn:country_code":"LT",
    "gn:dem":135,
    "gn:feature_class":"P",
    "gn:feature_code":"PPL",
    "gn:name":"Popovka",
    "gn:population":0,
    "gn:timezone":"Europe/Vilnius",
    "iso:country":"LT",
    "name:ceb_x_preferred":[
        "Popovka"
    ],
    "name:est_x_preferred":[
        "Popovka"
    ],
    "name:lit_x_preferred":[
        "Popovka"
    ],
    "name:swe_x_preferred":[
        "Popovka"
    ],
    "wof:name":"Popovka",
    "wof:placetype":"locality"
},
  "geometry": {"coordinates":[26.62213,55.31882],"type":"Point"}
}