{
  "type": "Feature",
  "properties": {
    "gn:admin1_code":"64",
    "gn:admin2_code":"62.0",
    "gn:asciiname":"Saraliskiai",
    "gn:country_code":"LT",
    "gn:dem":170,
    "gn:feature_class":"P",
    "gn:feature_code":"PPL",
    "gn:name":"Sarali\u0161kiai",
    "gn:population":0,
    "gn:timezone":"Europe/Vilnius",
    "iso:country":"LT",
    "name:lit_x_preferred":[
        "Sarali\u0161kiai"
    ],
    "wof:name":"Saraliskiai",
    "wof:placetype":"locality"
},
  "geometry": {"coordinates":[25.40813,55.08149],"type":"Point"}
}