{
  "type": "Feature",
  "properties": {
    "gn:admin1_code":"57",
    "gn:admin2_code":"53.0",
    "gn:asciiname":"Pakruostele",
    "gn:country_code":"LT",
    "gn:dem":53,
    "gn:feature_class":"P",
    "gn:feature_code":"PPL",
    "gn:name":"Pakruost\u0117l\u0117",
    "gn:population":0,
    "gn:timezone":"Europe/Vilnius",
    "iso:country":"LT",
    "name:lit_x_preferred":[
        "Pakruost\u0117l\u0117"
    ],
    "wof:name":"Pakruostele",
    "wof:placetype":"locality"
},
  "geometry": {"coordinates":[24.03088,55.43655],"type":"Point"}
}