{
  "type": "Feature",
  "properties": {
    "gn:admin1_code":"64.0",
    "gn:admin2_code":"45.0",
    "gn:asciiname":"Cesulenai",
    "gn:country_code":"LT",
    "gn:dem":159,
    "gn:feature_class":"P",
    "gn:feature_code":"PPL",
    "gn:name":"\u010ce\u0161ul\u0117nai",
    "gn:population":0,
    "gn:timezone":"Europe/Vilnius",
    "iso:country":"LT",
    "name:lit_x_preferred":[
        "\u010ce\u0161ul\u0117nai"
    ],
    "name:und_x_variant":[
        "\u010ce\u0161ulenai",
        "\u010ci\u017ei\u016bnai",
        "Czeszula\u0144ce",
        "Cheshulyan\u2019tse"
    ],
    "wof:name":"Cesulenai",
    "wof:placetype":"locality"
},
  "geometry": {"coordinates":[26.45193,55.36855],"type":"Point"}
}