{
  "type": "Feature",
  "properties": {
    "gn:admin1_code":"58.0",
    "gn:admin2_code":"21.0",
    "gn:asciiname":"Mockaiciai",
    "gn:country_code":"LT",
    "gn:dem":32,
    "gn:feature_class":"P",
    "gn:feature_code":"PPL",
    "gn:name":"Mockai\u010diai",
    "gn:population":0,
    "gn:timezone":"Europe/Vilnius",
    "iso:country":"LT",
    "name:und_x_variant":[
        "Motskaychey",
        "Mockai\u010diai"
    ],
    "wof:name":"Mockaiciai",
    "wof:placetype":"locality"
},
  "geometry": {"coordinates":[21.54222,55.57406999999999],"type":"Point"}
}