{
  "type": "Feature",
  "properties": {
    "gn:admin1_code":"64",
    "gn:admin2_code":"45.0",
    "gn:asciiname":"Barkuske",
    "gn:country_code":"LT",
    "gn:dem":161,
    "gn:feature_class":"P",
    "gn:feature_code":"PPL",
    "gn:name":"Barku\u0161k\u0117",
    "gn:population":0,
    "gn:timezone":"Europe/Vilnius",
    "iso:country":"LT",
    "name:lit_x_preferred":[
        "Barku\u0161k\u0117"
    ],
    "wof:name":"Barkuske",
    "wof:placetype":"locality"
},
  "geometry": {"coordinates":[26.33913,55.24735],"type":"Point"}
}