{
  "type": "Feature",
  "properties": {
    "gn:admin1_code":"65",
    "gn:admin2_code":"86.0",
    "gn:asciiname":"Parase",
    "gn:country_code":"LT",
    "gn:dem":153,
    "gn:feature_class":"P",
    "gn:feature_code":"PPL",
    "gn:name":"Para\u0161\u0117",
    "gn:population":0,
    "gn:timezone":"Europe/Vilnius",
    "iso:country":"LT",
    "name:lit_x_preferred":[
        "Para\u0161\u0117"
    ],
    "wof:name":"Parase",
    "wof:placetype":"locality"
},
  "geometry": {"coordinates":[25.725,55.20903000000001],"type":"Point"}
}