{
  "type": "Feature",
  "properties": {
    "gn:admin1_code":"56.0",
    "gn:admin2_code":"38.0",
    "gn:asciiname":"Papiskiai",
    "gn:country_code":"LT",
    "gn:dem":129,
    "gn:feature_class":"P",
    "gn:feature_code":"PPL",
    "gn:name":"Papi\u0161kiai",
    "gn:population":0,
    "gn:timezone":"Europe/Vilnius",
    "iso:country":"LT",
    "name:und_x_variant":[
        "Papishki",
        "Papi\u0161kiai"
    ],
    "wof:name":"Papiskiai",
    "wof:placetype":"locality"
},
  "geometry": {"coordinates":[24.41088,54.3461],"type":"Point"}
}