{
  "type": "Feature",
  "properties": {
    "gn:admin1_code":"0.0",
    "gn:asciiname":"Pramoneliai",
    "gn:cc2":"LT",
    "gn:country_code":"LT",
    "gn:dem":120,
    "gn:feature_class":"P",
    "gn:feature_code":"PPL",
    "gn:name":"Pramon\u0117liai",
    "gn:population":0,
    "gn:timezone":"Europe/Vilnius",
    "iso:country":"LT",
    "name:und_x_variant":[
        "Promanelyay",
        "Pramon\u0117liai"
    ],
    "wof:name":"Pramoneliai",
    "wof:placetype":"locality"
},
  "geometry": {"coordinates":[23.28333,55.68333000000001],"type":"Point"}
}