{
  "type": "Feature",
  "properties": {
    "gn:admin1_code":"57",
    "gn:admin2_code":"49.0",
    "gn:asciiname":"Karciupis",
    "gn:country_code":"LT",
    "gn:dem":66,
    "gn:feature_class":"P",
    "gn:feature_code":"PPL",
    "gn:name":"Kar\u010diupis",
    "gn:population":0,
    "gn:timezone":"Europe/Vilnius",
    "iso:country":"LT",
    "name:lit_x_preferred":[
        "Kar\u010diupis"
    ],
    "wof:name":"Karciupis",
    "wof:placetype":"locality"
},
  "geometry": {"coordinates":[24.12079,54.91443],"type":"Point"}
}