{
  "type": "Feature",
  "properties": {
    "gn:admin1_code":"58.0",
    "gn:admin2_code":"75.0",
    "gn:asciiname":"Juodeikiai",
    "gn:country_code":"LT",
    "gn:dem":37,
    "gn:feature_class":"P",
    "gn:feature_code":"PPL",
    "gn:name":"Juodeikiai",
    "gn:population":0,
    "gn:timezone":"Europe/Vilnius",
    "iso:country":"LT",
    "name:und_x_variant":[
        "Yudeykyay",
        "Judejki",
        "Juodeiki\u0173",
        "Juodeikiai"
    ],
    "wof:name":"Juodeikiai",
    "wof:placetype":"locality"
},
  "geometry": {"coordinates":[21.27761,56.1457],"type":"Point"}
}