{
  "type": "Feature",
  "properties": {
    "gn:gn_country":"LT",
    "gn:gn_fcode":"PPL",
    "gn:gn_pop":0,
    "iso:country":"LT",
    "name:lit_x_preferred":[
        "Pajstrys"
    ],
    "name:unk_x_variant":[
        "Paystrys"
    ],
    "qs_pg:aaroncc":"LT",
    "qs_pg:gn_country":"LT",
    "qs_pg:gn_fcode":"PPL",
    "qs_pg:gn_pop":0,
    "qs_pg:name":"Pa\u012fstrys",
    "qs_pg:name_adm0":"Lietuva",
    "qs_pg:name_adm1":"Paneve\u017eio Apskritis",
    "qs_pg:photos":31,
    "qs_pg:photos_1k":6,
    "qs_pg:photos_9k":1,
    "qs_pg:photos_9r":2,
    "qs_pg:photos_all":31,
    "qs_pg:photos_sr":2,
    "qs_pg:pop_sr":0,
    "qs_pg:qs_pg_placetype":"locality",
    "qs_pg:qs_pg_placetype_gp":"Town",
    "qs_pg:woe_adm0":23424875,
    "woe:adm0_id":23424875,
    "woe:name_adm0":"Lietuva",
    "woe:name_adm1":"Paneve\u017eio Apskritis",
    "woe:placetype":"Town",
    "wof:name":"Pa\u012fstrys",
    "wof:placetype":"locality"
},
  "geometry": {"coordinates":[24.33333,55.83333],"type":"Point"}
}