{
  "type": "Feature",
  "properties": {
    "gn:admin1_code":"65",
    "gn:admin2_code":"79.0",
    "gn:asciiname":"Zydabrastis",
    "gn:country_code":"LT",
    "gn:dem":144,
    "gn:feature_class":"P",
    "gn:feature_code":"PPL",
    "gn:name":"\u017dydabrastis",
    "gn:population":0,
    "gn:timezone":"Europe/Vilnius",
    "iso:country":"LT",
    "name:lit_x_preferred":[
        "\u017dydabrastis"
    ],
    "wof:name":"Zydabrastis",
    "wof:placetype":"locality"
},
  "geometry": {"coordinates":[24.5538,54.44533000000001],"type":"Point"}
}