{
  "type": "Feature",
  "properties": {
    "gn:admin1_code":"56",
    "gn:admin2_code":"38.0",
    "gn:asciiname":"Naujosios Naniskes",
    "gn:country_code":"LT",
    "gn:dem":148,
    "gn:feature_class":"P",
    "gn:feature_code":"PPL",
    "gn:name":"Naujosios Nanisk\u0117s",
    "gn:population":0,
    "gn:timezone":"Europe/Vilnius",
    "iso:country":"LT",
    "name:lit_x_preferred":[
        "Naujosios Nanisk\u0117s"
    ],
    "wof:name":"Naujosios Naniskes",
    "wof:placetype":"locality"
},
  "geometry": {"coordinates":[24.88124,54.32146],"type":"Point"}
}