{
  "type": "Feature",
  "properties": {
    "gn:admin1_code":"65.0",
    "gn:admin2_code":"13.0",
    "gn:asciiname":"Svedai",
    "gn:country_code":"LT",
    "gn:dem":171,
    "gn:feature_class":"P",
    "gn:feature_code":"PPL",
    "gn:name":"\u0160vedai",
    "gn:population":0,
    "gn:timezone":"Europe/Vilnius",
    "iso:country":"LT",
    "name:lit_x_preferred":[
        "\u0160vedai"
    ],
    "name:lit_x_variant":[
        "Svedai"
    ],
    "wof:name":"Svedai",
    "wof:placetype":"locality"
},
  "geometry": {"coordinates":[25.11638,54.78145],"type":"Point"}
}