{
  "type": "Feature",
  "properties": {
    "gn:admin1_code":"62",
    "gn:admin2_code":"87.0",
    "gn:asciiname":"Pabremenis",
    "gn:country_code":"LT",
    "gn:dem":126,
    "gn:feature_class":"P",
    "gn:feature_code":"PPL",
    "gn:name":"Pabremenis",
    "gn:population":0,
    "gn:timezone":"Europe/Vilnius",
    "iso:country":"LT",
    "name:lit_x_preferred":[
        "Pabremenis"
    ],
    "wof:name":"Pabremenis",
    "wof:placetype":"locality"
},
  "geometry": {"coordinates":[22.34906,55.47036],"type":"Point"}
}