{
  "type": "Feature",
  "properties": {
    "gn:admin1_code":"65",
    "gn:admin2_code":"13.0",
    "gn:asciiname":"Girdziunai",
    "gn:country_code":"LT",
    "gn:dem":128,
    "gn:feature_class":"P",
    "gn:feature_code":"PPL",
    "gn:name":"Gird\u017ei\u016bnai",
    "gn:population":0,
    "gn:timezone":"Europe/Vilnius",
    "iso:country":"LT",
    "name:lit_x_preferred":[
        "Gird\u017ei\u016bnai"
    ],
    "wof:name":"Girdziunai",
    "wof:placetype":"locality"
},
  "geometry": {"coordinates":[25.74114,54.83055],"type":"Point"}
}