{
  "type": "Feature",
  "properties": {
    "gn:admin1_code":"61",
    "gn:admin2_code":"32.0",
    "gn:asciiname":"Dabikinele",
    "gn:country_code":"LT",
    "gn:dem":76,
    "gn:feature_class":"P",
    "gn:feature_code":"PPL",
    "gn:name":"Dabikin\u0117l\u0117",
    "gn:population":0,
    "gn:timezone":"Europe/Vilnius",
    "iso:country":"LT",
    "name:lit_x_preferred":[
        "Dabikin\u0117l\u0117"
    ],
    "wof:name":"Dabikinele",
    "wof:placetype":"locality"
},
  "geometry": {"coordinates":[22.70219,56.23755],"type":"Point"}
}