{
  "type": "Feature",
  "properties": {
    "gn:admin1_code":"64",
    "gn:admin2_code":"45.0",
    "gn:asciiname":"Polianka",
    "gn:country_code":"LT",
    "gn:dem":164,
    "gn:feature_class":"P",
    "gn:feature_code":"PPL",
    "gn:name":"Polianka",
    "gn:population":0,
    "gn:timezone":"Europe/Vilnius",
    "iso:country":"LT",
    "name:cat_x_preferred":[
        "Polianka"
    ],
    "name:ces_x_preferred":[
        "Polianka"
    ],
    "name:deu_x_preferred":[
        "Polianka"
    ],
    "name:epo_x_preferred":[
        "Polianka"
    ],
    "name:eus_x_preferred":[
        "Polianka"
    ],
    "name:fra_x_preferred":[
        "Polianka"
    ],
    "name:hun_x_preferred":[
        "Polianka"
    ],
    "name:ita_x_preferred":[
        "Polianka"
    ],
    "name:lit_x_preferred":[
        "Polianka"
    ],
    "name:msa_x_preferred":[
        "Polianka"
    ],
    "name:nld_x_preferred":[
        "Polianka"
    ],
    "name:pol_x_preferred":[
        "Polianka"
    ],
    "name:ron_x_preferred":[
        "Polianka"
    ],
    "name:slk_x_preferred":[
        "Polianka"
    ],
    "name:spa_x_preferred":[
        "Polianka"
    ],
    "name:srp_x_preferred":[
        "\u041f\u043e\u0459\u0430\u043d\u043a\u0430"
    ],
    "name:war_x_preferred":[
        "Polianka"
    ],
    "wof:name":"Polianka",
    "wof:placetype":"locality"
},
  "geometry": {"coordinates":[26.37794,55.43816999999999],"type":"Point"}
}