{
  "type": "Feature",
  "properties": {
    "gn:admin1_code":"60.0",
    "gn:admin2_code":"36.0",
    "gn:asciiname":"Juostavieciai",
    "gn:country_code":"LT",
    "gn:dem":43,
    "gn:feature_class":"P",
    "gn:feature_code":"PPL",
    "gn:name":"Juostavie\u010diai",
    "gn:population":0,
    "gn:timezone":"Europe/Vilnius",
    "iso:country":"LT",
    "name:und_x_variant":[
        "Yuostavechay",
        "Juostave\u010diai",
        "Juostavie\u010diai"
    ],
    "wof:name":"Juostavieciai",
    "wof:placetype":"locality"
},
  "geometry": {"coordinates":[24.62667,56.3015],"type":"Point"}
}