{
  "type": "Feature",
  "properties": {
    "gn:admin1_code":"62.0",
    "gn:admin2_code":"77.0",
    "gn:asciiname":"Siauriskiai",
    "gn:country_code":"LT",
    "gn:dem":30,
    "gn:feature_class":"P",
    "gn:feature_code":"PPL",
    "gn:name":"\u0160iauri\u0161kiai",
    "gn:population":0,
    "gn:timezone":"Europe/Vilnius",
    "iso:country":"LT",
    "name:und_x_variant":[
        "Shavrishki",
        "\u0160iauri\u0161kiai"
    ],
    "wof:name":"Siauriskiai",
    "wof:placetype":"locality"
},
  "geometry": {"coordinates":[22.43574,55.25886],"type":"Point"}
}