{
  "type": "Feature",
  "properties": {
    "gn:admin1_code":"0.0",
    "gn:asciiname":"Aukstieji Zagmantai",
    "gn:cc2":"LT",
    "gn:country_code":"LT",
    "gn:dem":21,
    "gn:feature_class":"P",
    "gn:feature_code":"PPL",
    "gn:name":"Auk\u0161tieji \u017dagmantai",
    "gn:population":0,
    "gn:timezone":"Europe/Vilnius",
    "iso:country":"LT",
    "name:und_x_variant":[
        "Khokh Zhagmanten",
        "Auk\u0161tieji \u017dagmantai"
    ],
    "wof:name":"Aukstieji Zagmantai",
    "wof:placetype":"locality"
},
  "geometry": {"coordinates":[22.23333,55.11666999999999],"type":"Point"}
}