{
  "type": "Feature",
  "properties": {
    "gn:admin1_code":"64",
    "gn:admin2_code":"34.0",
    "gn:asciiname":"Kelpiskis",
    "gn:country_code":"LT",
    "gn:dem":155,
    "gn:feature_class":"P",
    "gn:feature_code":"PPL",
    "gn:name":"Kelpi\u0161kis",
    "gn:population":0,
    "gn:timezone":"Europe/Vilnius",
    "iso:country":"LT",
    "name:lit_x_preferred":[
        "Kelpi\u0161kis"
    ],
    "wof:name":"Kelpiskis",
    "wof:placetype":"locality"
},
  "geometry": {"coordinates":[25.34385,55.5133],"type":"Point"}
}