{
  "type": "Feature",
  "properties": {
    "gn:admin1_code":"57.0",
    "gn:admin2_code":"72.0",
    "gn:asciiname":"Meistai",
    "gn:country_code":"LT",
    "gn:dem":114,
    "gn:feature_class":"P",
    "gn:feature_code":"PPL",
    "gn:name":"Mei\u0161tai",
    "gn:population":0,
    "gn:timezone":"Europe/Vilnius",
    "iso:country":"LT",
    "name:und_x_variant":[
        "Meyshty",
        "Meyshtay",
        "Mei\u0161tai"
    ],
    "wof:name":"Meistai",
    "wof:placetype":"locality"
},
  "geometry": {"coordinates":[23.20328,55.41585],"type":"Point"}
}