{
  "type": "Feature",
  "properties": {
    "gn:admin1_code":"65",
    "gn:admin2_code":"13.0",
    "gn:asciiname":"Batriskes",
    "gn:country_code":"LT",
    "gn:dem":166,
    "gn:feature_class":"P",
    "gn:feature_code":"PPL",
    "gn:name":"Batri\u0161k\u0117s",
    "gn:population":0,
    "gn:timezone":"Europe/Vilnius",
    "iso:country":"LT",
    "name:lit_x_preferred":[
        "Batri\u0161k\u0117s"
    ],
    "wof:name":"Batriskes",
    "wof:placetype":"locality"
},
  "geometry": {"coordinates":[25.25592,54.91727],"type":"Point"}
}