{
  "type": "Feature",
  "properties": {
    "gn:admin1_code":"62",
    "gn:admin2_code":"77.0",
    "gn:asciiname":"Oplankys",
    "gn:country_code":"LT",
    "gn:dem":16,
    "gn:feature_class":"P",
    "gn:feature_code":"PPL",
    "gn:name":"Oplankys",
    "gn:population":0,
    "gn:timezone":"Europe/Vilnius",
    "iso:country":"LT",
    "name:lit_x_preferred":[
        "Oplankys"
    ],
    "wof:name":"Oplankys",
    "wof:placetype":"locality"
},
  "geometry": {"coordinates":[22.14925,55.17451],"type":"Point"}
}