{
  "type": "Feature",
  "properties": {
    "gn:admin1_code":"65",
    "gn:admin2_code":"86.0",
    "gn:asciiname":"Liedele",
    "gn:country_code":"LT",
    "gn:dem":144,
    "gn:feature_class":"P",
    "gn:feature_code":"PPL",
    "gn:name":"Liedel\u0117",
    "gn:population":0,
    "gn:timezone":"Europe/Vilnius",
    "iso:country":"LT",
    "name:lit_x_preferred":[
        "Liedel\u0117"
    ],
    "wof:name":"Liedele",
    "wof:placetype":"locality"
},
  "geometry": {"coordinates":[25.93628,55.24586],"type":"Point"}
}