{
  "type": "Feature",
  "properties": {
    "gn:admin1_code":"65",
    "gn:admin2_code":"86.0",
    "gn:asciiname":"Jaunadaris",
    "gn:country_code":"LT",
    "gn:dem":135,
    "gn:feature_class":"P",
    "gn:feature_code":"PPL",
    "gn:name":"Jaunadaris",
    "gn:population":0,
    "gn:timezone":"Europe/Vilnius",
    "iso:country":"LT",
    "name:lit_x_preferred":[
        "Jaunadaris"
    ],
    "wof:name":"Jaunadaris",
    "wof:placetype":"locality"
},
  "geometry": {"coordinates":[25.93129,55.08601],"type":"Point"}
}