{
  "type": "Feature",
  "properties": {
    "gn:admin1_code":"61",
    "gn:admin2_code":"29.0",
    "gn:asciiname":"Pakokline",
    "gn:country_code":"LT",
    "gn:dem":121,
    "gn:feature_class":"P",
    "gn:feature_code":"PPL",
    "gn:name":"Pakoklin\u0117",
    "gn:population":0,
    "gn:timezone":"Europe/Vilnius",
    "iso:country":"LT",
    "name:lit_x_preferred":[
        "Pakoklin\u0117"
    ],
    "wof:name":"Pakokline",
    "wof:placetype":"locality"
},
  "geometry": {"coordinates":[22.73696,56.00252],"type":"Point"}
}