{
  "type": "Feature",
  "properties": {
    "gn:admin1_code":"61.0",
    "gn:admin2_code":"54.0",
    "gn:asciiname":"Peldziai",
    "gn:country_code":"LT",
    "gn:dem":127,
    "gn:feature_class":"P",
    "gn:feature_code":"PPL",
    "gn:name":"Peld\u017eiai",
    "gn:population":0,
    "gn:timezone":"Europe/Vilnius",
    "iso:country":"LT",
    "name:und_x_variant":[
        "Pel\u2019dzhyay",
        "Peld\u017eiai"
    ],
    "wof:name":"Peldziai",
    "wof:placetype":"locality"
},
  "geometry": {"coordinates":[23.17758,55.68699],"type":"Point"}
}