{
  "type": "Feature",
  "properties": {
    "gn:admin1_code":"61",
    "gn:admin2_code":"54.0",
    "gn:asciiname":"Pasventupe I",
    "gn:country_code":"LT",
    "gn:dem":128,
    "gn:feature_class":"P",
    "gn:feature_code":"PPL",
    "gn:name":"Pa\u0161ventup\u0117 I",
    "gn:population":0,
    "gn:timezone":"Europe/Vilnius",
    "iso:country":"LT",
    "name:lit_x_preferred":[
        "Pa\u0161ventup\u0117 I"
    ],
    "wof:name":"Pasventupe I",
    "wof:placetype":"locality"
},
  "geometry": {"coordinates":[23.05493,55.77075],"type":"Point"}
}