{
  "type": "Feature",
  "properties": {
    "gn:admin1_code":"59",
    "gn:admin2_code":"48.0",
    "gn:asciiname":"Pagrauziai",
    "gn:country_code":"LT",
    "gn:dem":191,
    "gn:feature_class":"P",
    "gn:feature_code":"PPL",
    "gn:name":"Pagrau\u017eiai",
    "gn:population":0,
    "gn:timezone":"Europe/Vilnius",
    "iso:country":"LT",
    "name:lit_x_preferred":[
        "Pagrau\u017eiai"
    ],
    "wof:name":"Pagrauziai",
    "wof:placetype":"locality"
},
  "geometry": {"coordinates":[23.04137,54.39222],"type":"Point"}
}