{
  "type": "Feature",
  "properties": {
    "gn:admin1_code":"58.0",
    "gn:admin2_code":"88.0",
    "gn:asciiname":"Kelmyniskiai",
    "gn:country_code":"LT",
    "gn:dem":61,
    "gn:feature_class":"P",
    "gn:feature_code":"PPL",
    "gn:name":"Kelmyni\u0161kiai",
    "gn:population":0,
    "gn:timezone":"Europe/Vilnius",
    "iso:country":"LT",
    "wof:name":"Kelmyniskiai",
    "wof:placetype":"locality"
},
  "geometry": {"coordinates":[21.86335,55.37916],"type":"Point"}
}