{
  "type": "Feature",
  "properties": {
    "gn:admin1_code":"61",
    "gn:admin2_code":"54.0",
    "gn:asciiname":"Pakupris",
    "gn:country_code":"LT",
    "gn:dem":122,
    "gn:feature_class":"P",
    "gn:feature_code":"PPL",
    "gn:name":"Pak\u016bpris",
    "gn:population":0,
    "gn:timezone":"Europe/Vilnius",
    "iso:country":"LT",
    "name:lit_x_preferred":[
        "Pak\u016bpris"
    ],
    "wof:name":"Pakupris",
    "wof:placetype":"locality"
},
  "geometry": {"coordinates":[23.0176,55.5215],"type":"Point"}
}