{
  "type": "Feature",
  "properties": {
    "gn:admin1_code":"58",
    "gn:admin2_code":"75.0",
    "gn:asciiname":"Kanyzelis",
    "gn:country_code":"LT",
    "gn:dem":17,
    "gn:feature_class":"P",
    "gn:feature_code":"PPL",
    "gn:name":"Kanyzelis",
    "gn:population":0,
    "gn:timezone":"Europe/Vilnius",
    "iso:country":"LT",
    "name:lit_x_preferred":[
        "Kanyzelis"
    ],
    "wof:name":"Kanyzelis",
    "wof:placetype":"locality"
},
  "geometry": {"coordinates":[21.53168,56.27866],"type":"Point"}
}