{
  "type": "Feature",
  "properties": {
    "gn:admin1_code":"58",
    "gn:admin2_code":"88.0",
    "gn:asciiname":"Dekinteliai",
    "gn:country_code":"LT",
    "gn:dem":15,
    "gn:feature_class":"P",
    "gn:feature_code":"PPL",
    "gn:name":"D\u0117kint\u0117liai",
    "gn:population":0,
    "gn:timezone":"Europe/Vilnius",
    "iso:country":"LT",
    "name:lit_x_preferred":[
        "D\u0117kint\u0117liai"
    ],
    "wof:name":"Dekinteliai",
    "wof:placetype":"locality"
},
  "geometry": {"coordinates":[21.7256,55.27388000000001],"type":"Point"}
}