{
  "type": "Feature",
  "properties": {
    "gn:admin1_code":"62.0",
    "gn:admin2_code":"94.0",
    "gn:asciiname":"Kalveliai",
    "gn:country_code":"LT",
    "gn:dem":13,
    "gn:feature_class":"P",
    "gn:feature_code":"PPL",
    "gn:name":"Kalveliai",
    "gn:population":0,
    "gn:timezone":"Europe/Kaliningrad",
    "iso:country":"LT",
    "name:lit_x_preferred":[
        "Kalveliai"
    ],
    "name:und_x_variant":[
        "Kallwehlen",
        "Kal\u2019velen",
        "Kalv\u0117liai"
    ],
    "wof:name":"Kalveliai",
    "wof:placetype":"locality"
},
  "geometry": {"coordinates":[22.45688,55.05337],"type":"Point"}
}