{
  "type": "Feature",
  "properties": {
    "gn:admin1_code":"57",
    "gn:admin2_code":"46.0",
    "gn:asciiname":"Varnute",
    "gn:country_code":"LT",
    "gn:dem":79,
    "gn:feature_class":"P",
    "gn:feature_code":"PPL",
    "gn:name":"Varnut\u0117",
    "gn:population":0,
    "gn:timezone":"Europe/Vilnius",
    "iso:country":"LT",
    "name:lit_x_preferred":[
        "Varnut\u0117"
    ],
    "wof:name":"Varnute",
    "wof:placetype":"locality"
},
  "geometry": {"coordinates":[24.25882,55.08606999999999],"type":"Point"}
}