{
  "type": "Feature",
  "properties": {
    "gn:admin1_code":"65",
    "gn:admin2_code":"13.0",
    "gn:asciiname":"Maziuleniskes",
    "gn:country_code":"LT",
    "gn:dem":112,
    "gn:feature_class":"P",
    "gn:feature_code":"PPL",
    "gn:name":"Ma\u017eiul\u0117ni\u0161k\u0117s",
    "gn:population":0,
    "gn:timezone":"Europe/Vilnius",
    "iso:country":"LT",
    "name:lit_x_preferred":[
        "Ma\u017eiul\u0117ni\u0161k\u0117s"
    ],
    "wof:name":"Maziuleniskes",
    "wof:placetype":"locality"
},
  "geometry": {"coordinates":[25.60575,54.88542],"type":"Point"}
}