{
  "type": "Feature",
  "properties": {
    "gn:admin1_code":"62.0",
    "gn:admin2_code":"63.0",
    "gn:asciiname":"Sudenai",
    "gn:country_code":"LT",
    "gn:dem":20,
    "gn:feature_class":"P",
    "gn:feature_code":"PPL",
    "gn:name":"S\u016bd\u0117nai",
    "gn:population":0,
    "gn:timezone":"Europe/Vilnius",
    "iso:country":"LT",
    "name:lit_x_preferred":[
        "S\u016bd\u0117nai"
    ],
    "name:und_x_variant":[
        "Shudinen",
        "Suden\u0173",
        "Sudenay",
        "S\u016bdynai"
    ],
    "wof:name":"Sudenai",
    "wof:placetype":"locality"
},
  "geometry": {"coordinates":[21.89091,55.20944],"type":"Point"}
}