{
  "type": "Feature",
  "properties": {
    "gn:admin1_code":"62.0",
    "gn:admin2_code":"63.0",
    "gn:asciiname":"Peteraiciai",
    "gn:country_code":"LT",
    "gn:dem":31,
    "gn:feature_class":"P",
    "gn:feature_code":"PPL",
    "gn:name":"P\u0117terai\u010diai",
    "gn:population":0,
    "gn:timezone":"Europe/Vilnius",
    "iso:country":"LT",
    "name:und_x_variant":[
        "Peteraten",
        "Petyaraychyay",
        "P\u0117terai\u010diai"
    ],
    "wof:name":"Peteraiciai",
    "wof:placetype":"locality"
},
  "geometry": {"coordinates":[21.8855,55.25503000000001],"type":"Point"}
}