{
  "type": "Feature",
  "properties": {
    "gn:admin1_code":"65",
    "gn:admin2_code":"13.0",
    "gn:asciiname":"Salkiskes",
    "gn:country_code":"LT",
    "gn:dem":233,
    "gn:feature_class":"P",
    "gn:feature_code":"PPL",
    "gn:name":"\u0160alki\u0161k\u0117s",
    "gn:population":0,
    "gn:timezone":"Europe/Vilnius",
    "iso:country":"LT",
    "name:lit_x_preferred":[
        "\u0160alki\u0161k\u0117s"
    ],
    "wof:name":"Salkiskes",
    "wof:placetype":"locality"
},
  "geometry": {"coordinates":[25.57137,54.49772],"type":"Point"}
}