{
  "type": "Feature",
  "properties": {
    "gn:admin1_code":"61.0",
    "gn:admin2_code":"29.0",
    "gn:asciiname":"Rimuciai",
    "gn:country_code":"LT",
    "gn:dem":118,
    "gn:feature_class":"P",
    "gn:feature_code":"PPL",
    "gn:name":"Rimu\u010diai",
    "gn:population":0,
    "gn:timezone":"Europe/Vilnius",
    "iso:country":"LT",
    "name:und_x_variant":[
        "Rymuchyay",
        "Rimu\u010diai"
    ],
    "wof:name":"Rimuciai",
    "wof:placetype":"locality"
},
  "geometry": {"coordinates":[23.05845,55.8525],"type":"Point"}
}