{
  "type": "Feature",
  "properties": {
    "gn:admin1_code":"61",
    "gn:admin2_code":"54.0",
    "gn:asciiname":"Knasiai",
    "gn:country_code":"LT",
    "gn:dem":146,
    "gn:feature_class":"P",
    "gn:feature_code":"PPL",
    "gn:name":"Kna\u0161iai",
    "gn:population":0,
    "gn:timezone":"Europe/Vilnius",
    "iso:country":"LT",
    "name:lit_x_preferred":[
        "Kna\u0161iai"
    ],
    "wof:name":"Knasiai",
    "wof:placetype":"locality"
},
  "geometry": {"coordinates":[22.91183,55.6928],"type":"Point"}
}