{
  "type": "Feature",
  "properties": {
    "gn:admin1_code":"64",
    "gn:admin2_code":"34.0",
    "gn:asciiname":"Pilviskiai",
    "gn:country_code":"LT",
    "gn:dem":121,
    "gn:feature_class":"P",
    "gn:feature_code":"PPL",
    "gn:name":"Pilvi\u0161kiai",
    "gn:population":0,
    "gn:timezone":"Europe/Vilnius",
    "iso:country":"LT",
    "name:lit_x_preferred":[
        "Pilvi\u0161kiai"
    ],
    "wof:name":"Pilviskiai",
    "wof:placetype":"locality"
},
  "geometry": {"coordinates":[25.13093,55.44801999999999],"type":"Point"}
}