{
  "type": "Feature",
  "properties": {
    "gn:admin1_code":"57",
    "gn:admin2_code":"49.0",
    "gn:asciiname":"Norkunai",
    "gn:country_code":"LT",
    "gn:dem":95,
    "gn:feature_class":"P",
    "gn:feature_code":"PPL",
    "gn:name":"Nork\u016bnai",
    "gn:population":0,
    "gn:timezone":"Europe/Vilnius",
    "iso:country":"LT",
    "name:lit_x_preferred":[
        "Nork\u016bnai"
    ],
    "wof:name":"Norkunai",
    "wof:placetype":"locality"
},
  "geometry": {"coordinates":[24.19502,54.76759000000001],"type":"Point"}
}