{
  "type": "Feature",
  "properties": {
    "gn:admin1_code":"64.0",
    "gn:admin2_code":"43.0",
    "gn:asciiname":"Smalvos",
    "gn:country_code":"LT",
    "gn:dem":179,
    "gn:feature_class":"P",
    "gn:feature_code":"PPL",
    "gn:name":"Smalvos",
    "gn:population":0,
    "gn:timezone":"Europe/Vilnius",
    "iso:country":"LT",
    "name:eng_x_preferred":[
        "Smalvos"
    ],
    "name:rus_x_preferred":[
        "\u0421\u043c\u0430\u043b\u0432\u043e\u0441"
    ],
    "name:und_x_variant":[
        "Smalvai",
        "Smo\u0142wy",
        "Smolvy"
    ],
    "wof:name":"Smalvos",
    "wof:placetype":"locality"
},
  "geometry": {"coordinates":[26.36196,55.64131],"type":"Point"}
}