{
  "type": "Feature",
  "properties": {
    "gn:admin1_code":"61",
    "gn:admin2_code":"29.0",
    "gn:asciiname":"Papelkiai",
    "gn:country_code":"LT",
    "gn:dem":111,
    "gn:feature_class":"P",
    "gn:feature_code":"PPL",
    "gn:name":"Papelkiai",
    "gn:population":0,
    "gn:timezone":"Europe/Vilnius",
    "iso:country":"LT",
    "name:lit_x_preferred":[
        "Papelkiai"
    ],
    "wof:name":"Papelkiai",
    "wof:placetype":"locality"
},
  "geometry": {"coordinates":[22.89833,55.93137],"type":"Point"}
}