{
  "type": "Feature",
  "properties": {
    "gn:admin1_code":"65.0",
    "gn:admin2_code":"86.0",
    "gn:asciiname":"Lakaja",
    "gn:country_code":"LT",
    "gn:dem":152,
    "gn:feature_class":"P",
    "gn:feature_code":"PPL",
    "gn:name":"Lakaja",
    "gn:population":0,
    "gn:timezone":"Europe/Vilnius",
    "iso:country":"LT",
    "name:eng_x_preferred":[
        "Lakaja"
    ],
    "name:rus_x_preferred":[
        "\u041b\u0430\u043a\u0430\u044f"
    ],
    "name:und_x_variant":[
        "Lakajos",
        "Lokaya",
        "Lakajai",
        "Lokaja"
    ],
    "wof:name":"Lakaja",
    "wof:placetype":"locality"
},
  "geometry": {"coordinates":[25.69584,55.18309],"type":"Point"}
}