{
  "type": "Feature",
  "properties": {
    "gn:admin1_code":"58.0",
    "gn:admin2_code":"88.0",
    "gn:asciiname":"Pagryniai",
    "gn:country_code":"LT",
    "gn:dem":3,
    "gn:feature_class":"P",
    "gn:feature_code":"PPL",
    "gn:name":"Pagryniai",
    "gn:population":0,
    "gn:timezone":"Europe/Vilnius",
    "iso:country":"LT",
    "name:und_x_variant":[
        "Pagrinyay",
        "Pagrinen",
        "Pagrinai",
        "Pagryniai"
    ],
    "wof:name":"Pagryniai",
    "wof:placetype":"locality"
},
  "geometry": {"coordinates":[21.4868,55.32714],"type":"Point"}
}