{
  "type": "Feature",
  "properties": {
    "gn:admin1_code":"60",
    "gn:admin2_code":"73.0",
    "gn:asciiname":"Deguciai I",
    "gn:country_code":"LT",
    "gn:dem":145,
    "gn:feature_class":"P",
    "gn:feature_code":"PPL",
    "gn:name":"Degu\u010diai I",
    "gn:population":0,
    "gn:timezone":"Europe/Vilnius",
    "iso:country":"LT",
    "name:lit_x_preferred":[
        "Degu\u010diai I"
    ],
    "wof:name":"Deguciai I",
    "wof:placetype":"locality"
},
  "geometry": {"coordinates":[25.84934,55.98286],"type":"Point"}
}