{
  "type": "Feature",
  "properties": {
    "gn:admin1_code":"65.0",
    "gn:admin2_code":"42.0",
    "gn:asciiname":"Kloniniai Jagelonys",
    "gn:country_code":"LT",
    "gn:dem":129,
    "gn:feature_class":"P",
    "gn:feature_code":"PPL",
    "gn:name":"Kloniniai Jag\u0117lonys",
    "gn:population":0,
    "gn:timezone":"Europe/Vilnius",
    "iso:country":"LT",
    "name:lit_x_preferred":[
        "Kloniniai Jag\u0117lonys"
    ],
    "name:und_x_variant":[
        "Yagelyany-Dol\u2019nyye",
        "Jag\u0117lonys Kloniniai",
        "Yagelyany-Gornyye",
        "Kalniniai",
        "Jag\u0117lonys Kalniniai"
    ],
    "wof:name":"Kloniniai Jagelonys",
    "wof:placetype":"locality"
},
  "geometry": {"coordinates":[24.55431,54.73541],"type":"Point"}
}