{
  "type": "Feature",
  "properties": {
    "gn:admin1_code":"65",
    "gn:admin2_code":"13.0",
    "gn:asciiname":"Skaliskes",
    "gn:country_code":"LT",
    "gn:dem":114,
    "gn:feature_class":"P",
    "gn:feature_code":"PPL",
    "gn:name":"Skali\u0161k\u0117s",
    "gn:population":0,
    "gn:timezone":"Europe/Vilnius",
    "iso:country":"LT",
    "name:lit_x_preferred":[
        "Skali\u0161k\u0117s"
    ],
    "wof:name":"Skaliskes",
    "wof:placetype":"locality"
},
  "geometry": {"coordinates":[25.58124,54.87468000000001],"type":"Point"}
}