{
  "type": "Feature",
  "properties": {
    "gn:admin1_code":"57.0",
    "gn:admin2_code":"46.0",
    "gn:asciiname":"Juskonys",
    "gn:country_code":"LT",
    "gn:dem":72,
    "gn:feature_class":"P",
    "gn:feature_code":"PPL",
    "gn:name":"Ju\u0161konys",
    "gn:population":0,
    "gn:timezone":"Europe/Vilnius",
    "iso:country":"LT",
    "name:ceb_x_preferred":[
        "Ju\u0161konys"
    ],
    "name:deu_x_preferred":[
        "Ju\u0161konys"
    ],
    "name:lit_x_preferred":[
        "Ju\u0161konys"
    ],
    "name:swe_x_preferred":[
        "Ju\u0161konys"
    ],
    "name:und_x_variant":[
        "Yushkonis",
        "Ju\u0161koniai",
        "Ju\u0161konys"
    ],
    "wof:name":"Juskonys",
    "wof:placetype":"locality"
},
  "geometry": {"coordinates":[24.2377,55.23904],"type":"Point"}
}