{
  "type": "Feature",
  "properties": {
    "gn:admin1_code":"64",
    "gn:admin2_code":"82.0",
    "gn:asciiname":"Seseliai",
    "gn:country_code":"LT",
    "gn:dem":165,
    "gn:feature_class":"P",
    "gn:feature_code":"PPL",
    "gn:name":"\u0160\u0117\u0161\u0117liai",
    "gn:population":0,
    "gn:timezone":"Europe/Vilnius",
    "iso:country":"LT",
    "name:lit_x_preferred":[
        "\u0160\u0117\u0161\u0117liai"
    ],
    "wof:name":"Seseliai",
    "wof:placetype":"locality"
},
  "geometry": {"coordinates":[25.73763,55.57598],"type":"Point"}
}