{
  "type": "Feature",
  "properties": {
    "gn:admin1_code":"57",
    "gn:admin2_code":"53.0",
    "gn:asciiname":"Linksmaviete",
    "gn:country_code":"LT",
    "gn:dem":68,
    "gn:feature_class":"P",
    "gn:feature_code":"PPL",
    "gn:name":"Linksmaviet\u0117",
    "gn:population":0,
    "gn:timezone":"Europe/Vilnius",
    "iso:country":"LT",
    "name:lit_x_preferred":[
        "Linksmaviet\u0117"
    ],
    "wof:name":"Linksmaviete",
    "wof:placetype":"locality"
},
  "geometry": {"coordinates":[24.29709,55.2954],"type":"Point"}
}