{
  "type": "Feature",
  "properties": {
    "gn:admin1_code":"65",
    "gn:admin2_code":"89.0",
    "gn:asciiname":"Zaltarunai",
    "gn:country_code":"LT",
    "gn:dem":130,
    "gn:feature_class":"P",
    "gn:feature_code":"PPL",
    "gn:name":"Zaltar\u016bnai",
    "gn:population":0,
    "gn:timezone":"Europe/Vilnius",
    "iso:country":"LT",
    "name:lit_x_preferred":[
        "Zaltar\u016bnai"
    ],
    "wof:name":"Zaltarunai",
    "wof:placetype":"locality"
},
  "geometry": {"coordinates":[24.86091,54.90301],"type":"Point"}
}