{
  "type": "Feature",
  "properties": {
    "gn:admin1_code":"62.0",
    "gn:admin2_code":"77.0",
    "gn:asciiname":"Kundrociai",
    "gn:country_code":"LT",
    "gn:dem":91,
    "gn:feature_class":"P",
    "gn:feature_code":"PPL",
    "gn:name":"Kundro\u010diai",
    "gn:population":0,
    "gn:timezone":"Europe/Vilnius",
    "iso:country":"LT",
    "name:und_x_variant":[
        "Kondraychay",
        "Kundro\u010diai"
    ],
    "wof:name":"Kundrociai",
    "wof:placetype":"locality"
},
  "geometry": {"coordinates":[22.56302,55.39847],"type":"Point"}
}