{
  "type": "Feature",
  "properties": {
    "gn:admin1_code":"59.0",
    "gn:admin2_code":"58.0",
    "gn:asciiname":"Skindeliske",
    "gn:country_code":"LT",
    "gn:dem":47,
    "gn:feature_class":"P",
    "gn:feature_code":"PPL",
    "gn:name":"Skindeli\u0161k\u0117",
    "gn:population":0,
    "gn:timezone":"Europe/Vilnius",
    "iso:country":"LT",
    "name:lit_x_preferred":[
        "Skindeli\u0161k\u0117"
    ],
    "name:und_x_variant":[
        "Skindelishki",
        "Skindeli\u0161ke"
    ],
    "wof:name":"Skindeliske",
    "wof:placetype":"locality"
},
  "geometry": {"coordinates":[23.35851,54.77981],"type":"Point"}
}