{
  "type": "Feature",
  "properties": {
    "gn:admin1_code":"57",
    "gn:admin2_code":"19.0",
    "gn:asciiname":"Bliovai",
    "gn:country_code":"LT",
    "gn:dem":77,
    "gn:feature_class":"P",
    "gn:feature_code":"PPL",
    "gn:name":"Bliovai",
    "gn:population":0,
    "gn:timezone":"Europe/Vilnius",
    "iso:country":"LT",
    "name:lit_x_preferred":[
        "Bliovai"
    ],
    "wof:name":"Bliovai",
    "wof:placetype":"locality"
},
  "geometry": {"coordinates":[23.71981,54.83837],"type":"Point"}
}