{
  "type": "Feature",
  "properties": {
    "gn:admin1_code":"60.0",
    "gn:admin2_code":"67.0",
    "gn:asciiname":"Berciunai",
    "gn:country_code":"LT",
    "gn:dem":55,
    "gn:feature_class":"P",
    "gn:feature_code":"PPL",
    "gn:name":"Ber\u010di\u016bnai",
    "gn:population":0,
    "gn:timezone":"Europe/Vilnius",
    "iso:country":"LT",
    "name:und_x_variant":[
        "Byarchyunay",
        "Berchiunai",
        "Berchyunay",
        "Bar\u010di\u016bnai",
        "Ber\u010di\u016bn\u0173",
        "Ber\u010di\u016bnai"
    ],
    "wof:name":"Berciunai",
    "wof:placetype":"locality"
},
  "geometry": {"coordinates":[24.65833,56.07964000000001],"type":"Point"}
}