{
  "type": "Feature",
  "properties": {
    "gn:admin1_code":"59",
    "gn:admin2_code":"39.0",
    "gn:asciiname":"Kupciskiai",
    "gn:country_code":"LT",
    "gn:dem":63,
    "gn:feature_class":"P",
    "gn:feature_code":"PPL",
    "gn:name":"Kup\u010di\u0161kiai",
    "gn:population":0,
    "gn:timezone":"Europe/Vilnius",
    "iso:country":"LT",
    "name:lit_x_preferred":[
        "Kup\u010di\u0161kiai"
    ],
    "wof:name":"Kupciskiai",
    "wof:placetype":"locality"
},
  "geometry": {"coordinates":[23.25297,54.65236],"type":"Point"}
}