{
  "type": "Feature",
  "properties": {
    "gn:admin1_code":"57",
    "gn:admin2_code":"49.0",
    "gn:asciiname":"Vaiguva",
    "gn:country_code":"LT",
    "gn:dem":89,
    "gn:feature_class":"P",
    "gn:feature_code":"PPL",
    "gn:name":"Vaiguva",
    "gn:population":0,
    "gn:timezone":"Europe/Vilnius",
    "iso:country":"LT",
    "name:lit_x_preferred":[
        "Vaiguva"
    ],
    "wof:name":"Vaiguva",
    "wof:placetype":"locality"
},
  "geometry": {"coordinates":[24.23359,54.78379],"type":"Point"}
}