{
  "type": "Feature",
  "properties": {
    "gn:admin1_code":"62.0",
    "gn:admin2_code":"94.0",
    "gn:asciiname":"Jovaliske",
    "gn:country_code":"LT",
    "gn:dem":63,
    "gn:feature_class":"P",
    "gn:feature_code":"PPL",
    "gn:name":"Jovali\u0161k\u0117",
    "gn:population":0,
    "gn:timezone":"Europe/Vilnius",
    "iso:country":"LT",
    "name:und_x_variant":[
        "Ivolishki",
        "Jovali\u0161k\u0117",
        "Ivolishkyay",
        "Jovali\u0161kiai"
    ],
    "wof:name":"Jovaliske",
    "wof:placetype":"locality"
},
  "geometry": {"coordinates":[23.07958,55.20126],"type":"Point"}
}