{
  "type": "Feature",
  "properties": {
    "gn:admin1_code":"65",
    "gn:admin2_code":"81.0",
    "gn:asciiname":"Gegznai",
    "gn:country_code":"LT",
    "gn:dem":134,
    "gn:feature_class":"P",
    "gn:feature_code":"PPL",
    "gn:name":"Geg\u017enai",
    "gn:population":0,
    "gn:timezone":"Europe/Vilnius",
    "iso:country":"LT",
    "name:lit_x_preferred":[
        "Geg\u017enai"
    ],
    "wof:name":"Gegznai",
    "wof:placetype":"locality"
},
  "geometry": {"coordinates":[24.81471,55.14497],"type":"Point"}
}