{
  "type": "Feature",
  "properties": {
    "gn:admin1_code":"65",
    "gn:admin2_code":"85.0",
    "gn:asciiname":"Kamiciunai",
    "gn:country_code":"LT",
    "gn:dem":159,
    "gn:feature_class":"P",
    "gn:feature_code":"PPL",
    "gn:name":"Kami\u010di\u016bnai",
    "gn:population":0,
    "gn:timezone":"Europe/Vilnius",
    "iso:country":"LT",
    "name:lit_x_preferred":[
        "Kami\u010di\u016bnai"
    ],
    "wof:name":"Kamiciunai",
    "wof:placetype":"locality"
},
  "geometry": {"coordinates":[24.94594,54.26183],"type":"Point"}
}