{
  "type": "Feature",
  "properties": {
    "gn:admin1_code":"65.0",
    "gn:admin2_code":"42.0",
    "gn:asciiname":"Naujosios Kietaviskes",
    "gn:country_code":"LT",
    "gn:dem":91,
    "gn:feature_class":"P",
    "gn:feature_code":"PPL",
    "gn:name":"Naujosios Kietavi\u0161k\u0117s",
    "gn:population":0,
    "gn:timezone":"Europe/Vilnius",
    "iso:country":"LT",
    "name:lit_x_preferred":[
        "Naujosios Kietavi\u0161k\u0117s"
    ],
    "wof:name":"Naujosios Kietaviskes",
    "wof:placetype":"locality"
},
  "geometry": {"coordinates":[24.60928,54.75819],"type":"Point"}
}