{
  "type": "Feature",
  "properties": {
    "gn:admin1_code":"62.0",
    "gn:admin2_code":"63.0",
    "gn:asciiname":"Vilkyskiai",
    "gn:country_code":"LT",
    "gn:dem":30,
    "gn:feature_class":"P",
    "gn:feature_code":"PPL",
    "gn:name":"Vilky\u0161kiai",
    "gn:population":0,
    "gn:timezone":"Europe/Vilnius",
    "iso:country":"LT",
    "name:ceb_x_preferred":[
        "Vilky\u0161kiai"
    ],
    "name:deu_x_preferred":[
        "Willkischken"
    ],
    "name:deu_x_variant":[
        "Vilky\u0161kiai"
    ],
    "name:eng_x_preferred":[
        "Vilky\u0161kiai"
    ],
    "name:est_x_preferred":[
        "Vilky\u0161kiai"
    ],
    "name:lit_x_preferred":[
        "Vilky\u0161kiai"
    ],
    "name:nld_x_preferred":[
        "Vilky\u0161kiai"
    ],
    "name:pol_x_preferred":[
        "Wilkiszki"
    ],
    "name:rus_x_preferred":[
        "\u0412\u0438\u043b\u044c\u043a\u0438\u0448\u043a\u044f\u0439"
    ],
    "name:swe_x_preferred":[
        "Vilky\u0161kiai"
    ],
    "name:und_x_variant":[
        "Vilki\u0161kiai",
        "Villkishken",
        "Vil\u2019kishkyay",
        "Vil\u2019kishkey",
        "Vilki\u0161ki\u0173",
        "Vilky\u0161kiai",
        "Willkischken"
    ],
    "wof:name":"Vilkyskiai",
    "wof:placetype":"locality"
},
  "geometry": {"coordinates":[22.1281,55.12145],"type":"Point"}
}