{
  "type": "Feature",
  "properties": {
    "gn:admin1_code":"65.0",
    "gn:admin2_code":"79.0",
    "gn:asciiname":"Taucionys",
    "gn:country_code":"LT",
    "gn:dem":147,
    "gn:feature_class":"P",
    "gn:feature_code":"PPL",
    "gn:name":"Tau\u010dionys",
    "gn:population":0,
    "gn:timezone":"Europe/Vilnius",
    "iso:country":"LT",
    "name:und_x_variant":[
        "Tovchany",
        "Tau\u010dioni\u0173",
        "Tau\u010dionys"
    ],
    "wof:name":"Taucionys",
    "wof:placetype":"locality"
},
  "geometry": {"coordinates":[24.60136,54.44904],"type":"Point"}
}