{
  "type": "Feature",
  "properties": {
    "gn:admin1_code":"65.0",
    "gn:admin2_code":"85.0",
    "gn:asciiname":"Didziosios Selos",
    "gn:country_code":"LT",
    "gn:dem":158,
    "gn:feature_class":"P",
    "gn:feature_code":"PPL",
    "gn:name":"Did\u017eiosios S\u0117los",
    "gn:population":0,
    "gn:timezone":"Europe/Vilnius",
    "iso:country":"LT",
    "name:lit_x_preferred":[
        "Did\u017eiosios S\u0117los"
    ],
    "name:und_x_variant":[
        "S\u0117l\u0117",
        "Sa\u0142ki Wielkie",
        "Bol\u2019shiye Salki"
    ],
    "wof:name":"Didziosios Selos",
    "wof:placetype":"locality"
},
  "geometry": {"coordinates":[25.2421,54.34173000000001],"type":"Point"}
}