{
  "type": "Feature",
  "properties": {
    "gn:admin1_code":"64",
    "gn:admin2_code":"43.0",
    "gn:asciiname":"Kamionka",
    "gn:country_code":"LT",
    "gn:dem":178,
    "gn:feature_class":"P",
    "gn:feature_code":"PPL",
    "gn:name":"Kamionka",
    "gn:population":0,
    "gn:timezone":"Europe/Vilnius",
    "iso:country":"LT",
    "name:ceb_x_preferred":[
        "Kamionka"
    ],
    "name:deu_x_preferred":[
        "Kamionka"
    ],
    "name:fra_x_preferred":[
        "Kamionka"
    ],
    "name:lit_x_preferred":[
        "Kamionka"
    ],
    "name:pol_x_preferred":[
        "Kamionka"
    ],
    "name:swe_x_preferred":[
        "Kamionka"
    ],
    "name:ukr_x_preferred":[
        "\u041a\u0430\u043c\u0439\u043e\u043d\u043a\u0430"
    ],
    "wof:name":"Kamionka",
    "wof:placetype":"locality"
},
  "geometry": {"coordinates":[25.94873,55.7175],"type":"Point"}
}