{
  "type": "Feature",
  "properties": {
    "gn:admin1_code":"65",
    "gn:admin2_code":"13.0",
    "gn:asciiname":"Rudokai",
    "gn:country_code":"LT",
    "gn:dem":155,
    "gn:feature_class":"P",
    "gn:feature_code":"PPL",
    "gn:name":"Rudokai",
    "gn:population":0,
    "gn:timezone":"Europe/Vilnius",
    "iso:country":"LT",
    "name:lit_x_preferred":[
        "Rudokai"
    ],
    "wof:name":"Rudokai",
    "wof:placetype":"locality"
},
  "geometry": {"coordinates":[25.28054,55.03903],"type":"Point"}
}