{
  "type": "Feature",
  "properties": {
    "gn:admin1_code":"61.0",
    "gn:admin2_code":"71.0",
    "gn:asciiname":"Aguriskes",
    "gn:country_code":"LT",
    "gn:dem":82,
    "gn:feature_class":"P",
    "gn:feature_code":"PPL",
    "gn:name":"Aguri\u0161k\u0117s",
    "gn:population":0,
    "gn:timezone":"Europe/Vilnius",
    "iso:country":"LT",
    "name:lit_x_preferred":[
        "Aguri\u0161k\u0117s"
    ],
    "wof:name":"Aguriskes",
    "wof:placetype":"locality"
},
  "geometry": {"coordinates":[23.86795,55.57804],"type":"Point"}
}