{
  "type": "Feature",
  "properties": {
    "gn:admin1_code":"58.0",
    "gn:admin2_code":"88.0",
    "gn:asciiname":"Metirkvieciai",
    "gn:country_code":"LT",
    "gn:dem":15,
    "gn:feature_class":"P",
    "gn:feature_code":"PPL",
    "gn:name":"Metirkvie\u010diai",
    "gn:population":0,
    "gn:timezone":"Europe/Vilnius",
    "iso:country":"LT",
    "name:lit_x_preferred":[
        "Metirkvie\u010diai"
    ],
    "name:und_x_variant":[
        "Myatrikvechyay",
        "Metrikvechay",
        "Metrikvie\u010diai"
    ],
    "wof:name":"Metirkvieciai",
    "wof:placetype":"locality"
},
  "geometry": {"coordinates":[21.63244,55.35749000000001],"type":"Point"}
}