{
  "type": "Feature",
  "properties": {
    "gn:admin1_code":"65",
    "gn:admin2_code":"86.0",
    "gn:asciiname":"Matakieniai",
    "gn:country_code":"LT",
    "gn:dem":141,
    "gn:feature_class":"P",
    "gn:feature_code":"PPL",
    "gn:name":"Matakieniai",
    "gn:population":0,
    "gn:timezone":"Europe/Vilnius",
    "iso:country":"LT",
    "name:lit_x_preferred":[
        "Matakieniai"
    ],
    "wof:name":"Matakieniai",
    "wof:placetype":"locality"
},
  "geometry": {"coordinates":[25.73395,55.01638000000001],"type":"Point"}
}