{
  "type": "Feature",
  "properties": {
    "gn:admin1_code":"65",
    "gn:admin2_code":"81.0",
    "gn:asciiname":"Palivarkas",
    "gn:country_code":"LT",
    "gn:dem":69,
    "gn:feature_class":"P",
    "gn:feature_code":"PPL",
    "gn:name":"Palivarkas",
    "gn:population":0,
    "gn:timezone":"Europe/Vilnius",
    "iso:country":"LT",
    "name:lit_x_preferred":[
        "Palivarkas"
    ],
    "wof:name":"Palivarkas",
    "wof:placetype":"locality"
},
  "geometry": {"coordinates":[24.78496,55.27437],"type":"Point"}
}