{
  "type": "Feature",
  "properties": {
    "gn:admin1_code":"58.0",
    "gn:admin2_code":"88.0",
    "gn:asciiname":"Jauniai",
    "gn:country_code":"LT",
    "gn:dem":31,
    "gn:feature_class":"P",
    "gn:feature_code":"PPL",
    "gn:name":"Jauniai",
    "gn:population":0,
    "gn:timezone":"Europe/Vilnius",
    "iso:country":"LT",
    "name:lit_x_preferred":[
        "Jauniai"
    ],
    "wof:name":"Jauniai",
    "wof:placetype":"locality"
},
  "geometry": {"coordinates":[21.60545,55.41096],"type":"Point"}
}