{
  "type": "Feature",
  "properties": {
    "gn:admin1_code":"61.0",
    "gn:admin2_code":"47.0",
    "gn:asciiname":"Reibiniai",
    "gn:country_code":"LT",
    "gn:dem":67,
    "gn:feature_class":"P",
    "gn:feature_code":"PPL",
    "gn:name":"Reibiniai",
    "gn:population":0,
    "gn:timezone":"Europe/Vilnius",
    "iso:country":"LT",
    "name:und_x_variant":[
        "Reybinyay",
        "Reibiniai"
    ],
    "wof:name":"Reibiniai",
    "wof:placetype":"locality"
},
  "geometry": {"coordinates":[23.37306,56.29023000000001],"type":"Point"}
}