{
  "type": "Feature",
  "properties": {
    "gn:admin1_code":"64",
    "gn:admin2_code":"82.0",
    "gn:asciiname":"Latviskes",
    "gn:country_code":"LT",
    "gn:dem":209,
    "gn:feature_class":"P",
    "gn:feature_code":"PPL",
    "gn:name":"Latvi\u0161k\u0117s",
    "gn:population":0,
    "gn:timezone":"Europe/Vilnius",
    "iso:country":"LT",
    "name:lit_x_preferred":[
        "Latvi\u0161k\u0117s"
    ],
    "wof:name":"Latviskes",
    "wof:placetype":"locality"
},
  "geometry": {"coordinates":[25.8335,55.5535],"type":"Point"}
}