{
  "type": "Feature",
  "properties": {
    "gn:admin1_code":"57",
    "gn:admin2_code":"53.0",
    "gn:asciiname":"Trakuciai",
    "gn:country_code":"LT",
    "gn:dem":55,
    "gn:feature_class":"P",
    "gn:feature_code":"PPL",
    "gn:name":"Traku\u010diai",
    "gn:population":0,
    "gn:timezone":"Europe/Vilnius",
    "iso:country":"LT",
    "name:lit_x_preferred":[
        "Traku\u010diai"
    ],
    "wof:name":"Trakuciai",
    "wof:placetype":"locality"
},
  "geometry": {"coordinates":[24.2055,55.2853],"type":"Point"}
}