{
  "type": "Feature",
  "properties": {
    "gn:admin1_code":"63",
    "gn:admin2_code":"78.0",
    "gn:asciiname":"Zalione",
    "gn:country_code":"LT",
    "gn:dem":114,
    "gn:feature_class":"P",
    "gn:feature_code":"PPL",
    "gn:name":"\u017dalion\u0117",
    "gn:population":0,
    "gn:timezone":"Europe/Vilnius",
    "iso:country":"LT",
    "name:lit_x_preferred":[
        "\u017dalion\u0117"
    ],
    "wof:name":"Zalione",
    "wof:placetype":"locality"
},
  "geometry": {"coordinates":[22.58912,55.94335],"type":"Point"}
}