{
  "type": "Feature",
  "properties": {
    "gn:admin1_code":"60",
    "gn:admin2_code":"27.0",
    "gn:asciiname":"Ozeliai",
    "gn:country_code":"LT",
    "gn:dem":52,
    "gn:feature_class":"P",
    "gn:feature_code":"PPL",
    "gn:name":"O\u017eeliai",
    "gn:population":0,
    "gn:timezone":"Europe/Vilnius",
    "iso:country":"LT",
    "name:lit_x_preferred":[
        "O\u017eeliai"
    ],
    "wof:name":"Ozeliai",
    "wof:placetype":"locality"
},
  "geometry": {"coordinates":[24.43063,55.73009],"type":"Point"}
}