{
  "type": "Feature",
  "properties": {
    "gn:admin1_code":"65",
    "gn:admin2_code":"81.0",
    "gn:asciiname":"Vaisgeliskis",
    "gn:country_code":"LT",
    "gn:dem":136,
    "gn:feature_class":"P",
    "gn:feature_code":"PPL",
    "gn:name":"Vaisg\u0117li\u0161kis",
    "gn:population":0,
    "gn:timezone":"Europe/Vilnius",
    "iso:country":"LT",
    "name:lit_x_preferred":[
        "Vaisg\u0117li\u0161kis"
    ],
    "wof:name":"Vaisgeliskis",
    "wof:placetype":"locality"
},
  "geometry": {"coordinates":[24.83685,55.21475],"type":"Point"}
}