{
  "type": "Feature",
  "properties": {
    "gn:admin1_code":"57.0",
    "gn:admin2_code":"72.0",
    "gn:asciiname":"Paltupiai",
    "gn:country_code":"LT",
    "gn:dem":103,
    "gn:feature_class":"P",
    "gn:feature_code":"PPL",
    "gn:name":"Paltupiai",
    "gn:population":0,
    "gn:timezone":"Europe/Vilnius",
    "iso:country":"LT",
    "name:lit_x_preferred":[
        "Paltupiai"
    ],
    "name:und_x_variant":[
        "Polutuni",
        "Palutupys"
    ],
    "wof:name":"Paltupiai",
    "wof:placetype":"locality"
},
  "geometry": {"coordinates":[23.08678,55.4987],"type":"Point"}
}