{
  "type": "Feature",
  "properties": {
    "gn:admin1_code":"56",
    "gn:admin2_code":"11.0",
    "gn:asciiname":"Varnagiriai",
    "gn:country_code":"LT",
    "gn:dem":116,
    "gn:feature_class":"P",
    "gn:feature_code":"PPL",
    "gn:name":"Varnagiriai",
    "gn:population":0,
    "gn:timezone":"Europe/Vilnius",
    "iso:country":"LT",
    "name:lit_x_preferred":[
        "Varnagiriai"
    ],
    "wof:name":"Varnagiriai",
    "wof:placetype":"locality"
},
  "geometry": {"coordinates":[23.784,54.37042],"type":"Point"}
}