{
  "type": "Feature",
  "properties": {
    "gn:admin1_code":"65",
    "gn:admin2_code":"86.0",
    "gn:asciiname":"Karpakelis",
    "gn:country_code":"LT",
    "gn:dem":147,
    "gn:feature_class":"P",
    "gn:feature_code":"PPL",
    "gn:name":"Karpak\u0117lis",
    "gn:population":0,
    "gn:timezone":"Europe/Vilnius",
    "iso:country":"LT",
    "name:lit_x_preferred":[
        "Karpak\u0117lis"
    ],
    "wof:name":"Karpakelis",
    "wof:placetype":"locality"
},
  "geometry": {"coordinates":[25.57645,55.01826],"type":"Point"}
}