{
  "type": "Feature",
  "properties": {
    "gn:admin1_code":"64.0",
    "gn:admin2_code":"62.0",
    "gn:asciiname":"Dapkuniskiai",
    "gn:country_code":"LT",
    "gn:dem":143,
    "gn:feature_class":"P",
    "gn:feature_code":"PPL",
    "gn:name":"Dapk\u016bni\u0161kiai",
    "gn:population":0,
    "gn:timezone":"Europe/Vilnius",
    "iso:country":"LT",
    "name:und_x_variant":[
        "Dabkunishki",
        "Dapkunishkyay",
        "Dapk\u016bni\u0161kiai"
    ],
    "wof:name":"Dapkuniskiai",
    "wof:placetype":"locality"
},
  "geometry": {"coordinates":[25.1227,55.35106],"type":"Point"}
}