{
  "type": "Feature",
  "properties": {
    "gn:admin1_code":"64",
    "gn:admin2_code":"62.0",
    "gn:asciiname":"Antapunte",
    "gn:country_code":"LT",
    "gn:dem":159,
    "gn:feature_class":"P",
    "gn:feature_code":"PPL",
    "gn:name":"Antapunt\u0117",
    "gn:population":0,
    "gn:timezone":"Europe/Vilnius",
    "iso:country":"LT",
    "name:lit_x_preferred":[
        "Antapunt\u0117"
    ],
    "wof:name":"Antapunte",
    "wof:placetype":"locality"
},
  "geometry": {"coordinates":[25.4092,55.17178000000001],"type":"Point"}
}