{
  "type": "Feature",
  "properties": {
    "gn:admin1_code":"65.0",
    "gn:admin2_code":"85.0",
    "gn:asciiname":"Smaguriai",
    "gn:country_code":"LT",
    "gn:dem":196,
    "gn:feature_class":"P",
    "gn:feature_code":"PPL",
    "gn:name":"Smaguriai",
    "gn:population":0,
    "gn:timezone":"Europe/Vilnius",
    "iso:country":"LT",
    "name:lit_x_preferred":[
        "Smaguriai"
    ],
    "wof:name":"Smaguriai",
    "wof:placetype":"locality"
},
  "geometry": {"coordinates":[25.48415,54.34751],"type":"Point"}
}