{
  "type": "Feature",
  "properties": {
    "gn:admin1_code":"59.0",
    "gn:admin2_code":"18.0",
    "gn:asciiname":"Pazelsviai",
    "gn:country_code":"LT",
    "gn:dem":112,
    "gn:feature_class":"P",
    "gn:feature_code":"PPL",
    "gn:name":"Pa\u017eelsviai",
    "gn:population":0,
    "gn:timezone":"Europe/Vilnius",
    "iso:country":"LT",
    "name:und_x_variant":[
        "Pa\u017eelsvi\u0173",
        "Pozhel\u2019stvo",
        "Pa\u017eelviai",
        "Pa\u017eelsviai"
    ],
    "wof:name":"Pazelsviai",
    "wof:placetype":"locality"
},
  "geometry": {"coordinates":[23.43273,54.41368000000001],"type":"Point"}
}