{
  "type": "Feature",
  "properties": {
    "gn:admin1_code":"65",
    "gn:admin2_code":"85.0",
    "gn:asciiname":"Katkuskes",
    "gn:country_code":"LT",
    "gn:dem":205,
    "gn:feature_class":"P",
    "gn:feature_code":"PPL",
    "gn:name":"Katku\u0161k\u0117s",
    "gn:population":0,
    "gn:timezone":"Europe/Vilnius",
    "iso:country":"LT",
    "name:lit_x_preferred":[
        "Katku\u0161k\u0117s"
    ],
    "wof:name":"Katkuskes",
    "wof:placetype":"locality"
},
  "geometry": {"coordinates":[25.58487,54.29893000000001],"type":"Point"}
}