{
  "type": "Feature",
  "properties": {
    "gn:admin1_code":"59.0",
    "gn:admin2_code":"39.0",
    "gn:asciiname":"Dambauka",
    "gn:country_code":"LT",
    "gn:dem":144,
    "gn:feature_class":"P",
    "gn:feature_code":"PPL",
    "gn:name":"Dambauka",
    "gn:population":0,
    "gn:timezone":"Europe/Vilnius",
    "iso:country":"LT",
    "name:und_x_variant":[
        "Dombalka",
        "Dambaukos",
        "Debovka",
        "Dambauka"
    ],
    "wof:name":"Dambauka",
    "wof:placetype":"locality"
},
  "geometry": {"coordinates":[22.97048,54.484],"type":"Point"}
}