{
  "type": "Feature",
  "properties": {
    "gn:admin1_code":"60.0",
    "gn:admin2_code":"27.0",
    "gn:asciiname":"Uzkalniai",
    "gn:country_code":"LT",
    "gn:dem":56,
    "gn:feature_class":"P",
    "gn:feature_code":"PPL",
    "gn:name":"U\u017ekalniai",
    "gn:population":0,
    "gn:timezone":"Europe/Vilnius",
    "iso:country":"LT",
    "name:und_x_variant":[
        "Uzhukol\u2019ke",
        "U\u017ekalniai"
    ],
    "wof:name":"Uzkalniai",
    "wof:placetype":"locality"
},
  "geometry": {"coordinates":[24.31727,55.56582],"type":"Point"}
}