{
  "type": "Feature",
  "properties": {
    "gn:admin1_code":"62.0",
    "gn:admin2_code":"77.0",
    "gn:asciiname":"Taurai",
    "gn:country_code":"LT",
    "gn:dem":27,
    "gn:feature_class":"P",
    "gn:feature_code":"PPL",
    "gn:name":"Taurai",
    "gn:population":0,
    "gn:timezone":"Europe/Vilnius",
    "iso:country":"LT",
    "name:eng_x_preferred":[
        "Taurai"
    ],
    "name:rus_x_preferred":[
        "\u0422\u0430\u0443\u0440\u0430\u0433\u0435"
    ],
    "name:und_x_variant":[
        "Taurogen"
    ],
    "wof:name":"Taurai",
    "wof:placetype":"locality"
},
  "geometry": {"coordinates":[22.25851,55.24163000000001],"type":"Point"}
}