{
  "type": "Feature",
  "properties": {
    "gn:admin1_code":"65",
    "gn:admin2_code":"85.0",
    "gn:asciiname":"Ragoziskes",
    "gn:country_code":"LT",
    "gn:dem":176,
    "gn:feature_class":"P",
    "gn:feature_code":"PPL",
    "gn:name":"Rago\u017ei\u0161k\u0117s",
    "gn:population":0,
    "gn:timezone":"Europe/Vilnius",
    "iso:country":"LT",
    "name:lit_x_preferred":[
        "Rago\u017ei\u0161k\u0117s"
    ],
    "wof:name":"Ragoziskes",
    "wof:placetype":"locality"
},
  "geometry": {"coordinates":[25.37954,54.38867],"type":"Point"}
}