{
  "type": "Feature",
  "properties": {
    "gn:admin1_code":"65.0",
    "gn:admin2_code":"79.0",
    "gn:asciiname":"Brazuole",
    "gn:country_code":"LT",
    "gn:dem":140,
    "gn:feature_class":"P",
    "gn:feature_code":"PPL",
    "gn:name":"Bra\u017euol\u0117",
    "gn:population":0,
    "gn:timezone":"Europe/Vilnius",
    "iso:country":"LT",
    "name:und_x_variant":[
        "Brazhola",
        "Bra\u017eola",
        "Bra\u017euola",
        "Bra\u017euol\u0117"
    ],
    "wof:name":"Brazuole",
    "wof:placetype":"locality"
},
  "geometry": {"coordinates":[24.9076,54.68331],"type":"Point"}
}