{
  "type": "Feature",
  "properties": {
    "gn:admin1_code":"64",
    "gn:admin2_code":"82.0",
    "gn:asciiname":"Siksniai",
    "gn:country_code":"LT",
    "gn:dem":146,
    "gn:feature_class":"P",
    "gn:feature_code":"PPL",
    "gn:name":"\u0160ik\u0161niai",
    "gn:population":0,
    "gn:timezone":"Europe/Vilnius",
    "iso:country":"LT",
    "name:lit_x_preferred":[
        "\u0160ik\u0161niai"
    ],
    "wof:name":"Siksniai",
    "wof:placetype":"locality"
},
  "geometry": {"coordinates":[25.72205,55.63169],"type":"Point"}
}