{
  "type": "Feature",
  "properties": {
    "gn:admin1_code":"60.0",
    "gn:admin2_code":"36.0",
    "gn:asciiname":"Bajoriskiai",
    "gn:country_code":"LT",
    "gn:dem":53,
    "gn:feature_class":"P",
    "gn:feature_code":"PPL",
    "gn:name":"Bajori\u0161kiai",
    "gn:population":0,
    "gn:timezone":"Europe/Vilnius",
    "iso:country":"LT",
    "name:und_x_variant":[
        "Bayorishkyay",
        "Bajori\u0161kiai"
    ],
    "wof:name":"Bajoriskiai",
    "wof:placetype":"locality"
},
  "geometry": {"coordinates":[24.65107,56.11079],"type":"Point"}
}