{
  "type": "Feature",
  "properties": {
    "gn:admin1_code":"63.0",
    "gn:admin2_code":"61.0",
    "gn:asciiname":"Cekai",
    "gn:country_code":"LT",
    "gn:dem":70,
    "gn:feature_class":"P",
    "gn:feature_code":"PPL",
    "gn:name":"\u010cekai",
    "gn:population":0,
    "gn:timezone":"Europe/Vilnius",
    "iso:country":"LT",
    "name:und_x_variant":[
        "\u010cek\u0173",
        "Czeki",
        "Cheki",
        "\u010cekai"
    ],
    "wof:name":"Cekai",
    "wof:placetype":"locality"
},
  "geometry": {"coordinates":[22.50487,56.22901],"type":"Point"}
}