{
  "type": "Feature",
  "properties": {
    "gn:admin1_code":"61",
    "gn:admin2_code":"47.0",
    "gn:asciiname":"Budraiciai",
    "gn:country_code":"LT",
    "gn:dem":56,
    "gn:feature_class":"P",
    "gn:feature_code":"PPL",
    "gn:name":"Budrai\u010diai",
    "gn:population":0,
    "gn:timezone":"Europe/Vilnius",
    "iso:country":"LT",
    "name:lit_x_preferred":[
        "Budrai\u010diai"
    ],
    "wof:name":"Budraiciai",
    "wof:placetype":"locality"
},
  "geometry": {"coordinates":[23.3842,56.31423],"type":"Point"}
}