{
  "type": "Feature",
  "properties": {
    "gn:admin1_code":"61",
    "gn:admin2_code":"47.0",
    "gn:asciiname":"Puodziunai",
    "gn:country_code":"LT",
    "gn:dem":50,
    "gn:feature_class":"P",
    "gn:feature_code":"PPL",
    "gn:name":"Puod\u017ei\u016bnai",
    "gn:population":0,
    "gn:timezone":"Europe/Vilnius",
    "iso:country":"LT",
    "name:lit_x_preferred":[
        "Puod\u017ei\u016bnai"
    ],
    "wof:name":"Puodziunai",
    "wof:placetype":"locality"
},
  "geometry": {"coordinates":[23.81482,56.18839000000001],"type":"Point"}
}