{
  "type": "Feature",
  "properties": {
    "gn:admin1_code":"61.0",
    "gn:admin2_code":"71.0",
    "gn:asciiname":"Nirtaiciai",
    "gn:country_code":"LT",
    "gn:dem":124,
    "gn:feature_class":"P",
    "gn:feature_code":"PPL",
    "gn:name":"Nirtai\u010diai",
    "gn:population":0,
    "gn:timezone":"Europe/Vilnius",
    "iso:country":"LT",
    "name:und_x_variant":[
        "Nortaychyay",
        "Nirtai\u010diai"
    ],
    "wof:name":"Nirtaiciai",
    "wof:placetype":"locality"
},
  "geometry": {"coordinates":[23.47437,55.72325],"type":"Point"}
}