{
  "type": "Feature",
  "properties": {
    "gn:admin1_code":"58.0",
    "gn:admin2_code":"88.0",
    "gn:asciiname":"Uta",
    "gn:country_code":"LT",
    "gn:dem":48,
    "gn:feature_class":"P",
    "gn:feature_code":"PPL",
    "gn:name":"\u016ata",
    "gn:population":0,
    "gn:timezone":"Europe/Vilnius",
    "iso:country":"LT",
    "name:und_x_variant":[
        "Guta",
        "\u016ata"
    ],
    "wof:name":"Uta",
    "wof:placetype":"locality"
},
  "geometry": {"coordinates":[21.73007,55.4478],"type":"Point"}
}