{
  "type": "Feature",
  "properties": {
    "gn:admin1_code":"58.0",
    "gn:admin2_code":"56.0",
    "gn:asciiname":"Baubliai",
    "gn:country_code":"LT",
    "gn:dem":60,
    "gn:feature_class":"P",
    "gn:feature_code":"PPL",
    "gn:name":"Baubliai",
    "gn:population":0,
    "gn:timezone":"Europe/Vilnius",
    "iso:country":"LT",
    "name:eng_x_preferred":[
        "Baubliai"
    ],
    "name:rus_x_preferred":[
        "\u0411\u0430\u0443\u0431\u043b\u044f\u0439"
    ],
    "name:und_x_variant":[
        "Baubli\u0173",
        "Baubley"
    ],
    "wof:name":"Baubliai",
    "wof:placetype":"locality"
},
  "geometry": {"coordinates":[21.40482,55.83204],"type":"Point"}
}