{
  "type": "Feature",
  "properties": {
    "gn:admin1_code":"56",
    "gn:admin2_code":"59.0",
    "gn:asciiname":"Smaliske",
    "gn:country_code":"LT",
    "gn:dem":128,
    "gn:feature_class":"P",
    "gn:feature_code":"PPL",
    "gn:name":"Smali\u0161k\u0117",
    "gn:population":0,
    "gn:timezone":"Europe/Vilnius",
    "iso:country":"LT",
    "name:lit_x_preferred":[
        "Smali\u0161k\u0117"
    ],
    "wof:name":"Smaliske",
    "wof:placetype":"locality"
},
  "geometry": {"coordinates":[23.79291,54.01792],"type":"Point"}
}