{
  "type": "Feature",
  "properties": {
    "gn:admin1_code":"64",
    "gn:admin2_code":"45.0",
    "gn:asciiname":"Siulgos",
    "gn:country_code":"LT",
    "gn:dem":163,
    "gn:feature_class":"P",
    "gn:feature_code":"PPL",
    "gn:name":"Siulgos",
    "gn:population":0,
    "gn:timezone":"Europe/Vilnius",
    "iso:country":"LT",
    "name:lit_x_preferred":[
        "Siulgos"
    ],
    "wof:name":"Siulgos",
    "wof:placetype":"locality"
},
  "geometry": {"coordinates":[26.46622,55.32062],"type":"Point"}
}