{
  "type": "Feature",
  "properties": {
    "gn:admin1_code":"64",
    "gn:admin2_code":"45.0",
    "gn:asciiname":"Kukoriske",
    "gn:country_code":"LT",
    "gn:dem":176,
    "gn:feature_class":"P",
    "gn:feature_code":"PPL",
    "gn:name":"Kukori\u0161k\u0117",
    "gn:population":0,
    "gn:timezone":"Europe/Vilnius",
    "iso:country":"LT",
    "name:lit_x_preferred":[
        "Kukori\u0161k\u0117"
    ],
    "wof:name":"Kukoriske",
    "wof:placetype":"locality"
},
  "geometry": {"coordinates":[26.23772,55.41662],"type":"Point"}
}