{
  "type": "Feature",
  "properties": {
    "gn:admin1_code":"65",
    "gn:admin2_code":"86.0",
    "gn:asciiname":"Liuline",
    "gn:country_code":"LT",
    "gn:dem":131,
    "gn:feature_class":"P",
    "gn:feature_code":"PPL",
    "gn:name":"Li\u016blin\u0117",
    "gn:population":0,
    "gn:timezone":"Europe/Vilnius",
    "iso:country":"LT",
    "name:lit_x_preferred":[
        "Li\u016blin\u0117"
    ],
    "wof:name":"Liuline",
    "wof:placetype":"locality"
},
  "geometry": {"coordinates":[25.94837,55.10207],"type":"Point"}
}