{
  "type": "Feature",
  "properties": {
    "gn:admin1_code":"61.0",
    "gn:admin2_code":"29.0",
    "gn:asciiname":"Mekiai",
    "gn:country_code":"LT",
    "gn:dem":129,
    "gn:feature_class":"P",
    "gn:feature_code":"PPL",
    "gn:name":"Mekiai",
    "gn:population":0,
    "gn:timezone":"Europe/Vilnius",
    "iso:country":"LT",
    "name:und_x_variant":[
        "Mekyay",
        "Mekiai"
    ],
    "wof:name":"Mekiai",
    "wof:placetype":"locality"
},
  "geometry": {"coordinates":[23.13089,55.79616],"type":"Point"}
}