{
  "type": "Feature",
  "properties": {
    "gn:admin1_code":"61.0",
    "gn:asciiname":"Akmeneliai",
    "gn:cc2":"LT",
    "gn:country_code":"LT",
    "gn:dem":45,
    "gn:feature_class":"P",
    "gn:feature_code":"PPL",
    "gn:name":"Akmen\u0117liai",
    "gn:population":0,
    "gn:timezone":"Europe/Vilnius",
    "iso:country":"LT",
    "name:und_x_variant":[
        "Akmyanyalyay",
        "Akmen\u0117liai"
    ],
    "wof:name":"Akmeneliai",
    "wof:placetype":"locality"
},
  "geometry": {"coordinates":[24.00306,56.25278],"type":"Point"}
}