{
  "type": "Feature",
  "properties": {
    "gn:admin1_code":"65.0",
    "gn:admin2_code":"89.0",
    "gn:asciiname":"Davonys",
    "gn:country_code":"LT",
    "gn:dem":101,
    "gn:feature_class":"P",
    "gn:feature_code":"PPL",
    "gn:name":"Davonys",
    "gn:population":0,
    "gn:timezone":"Europe/Vilnius",
    "iso:country":"LT",
    "name:und_x_variant":[
        "Davonis",
        "Davonys"
    ],
    "wof:name":"Davonys",
    "wof:placetype":"locality"
},
  "geometry": {"coordinates":[24.65865,55.01572],"type":"Point"}
}