{
  "type": "Feature",
  "properties": {
    "iso:country":"LT",
    "qs_pg:aaroncc":"LT",
    "qs_pg:name":"Traku Seniunija",
    "qs_pg:name_adm0":"Lietuva",
    "qs_pg:name_adm1":"Vilniaus Apskritis",
    "qs_pg:photos":2,
    "qs_pg:photos_1k":1,
    "qs_pg:photos_9k":17,
    "qs_pg:photos_9r":12,
    "qs_pg:photos_all":3753,
    "qs_pg:photos_sr":1,
    "qs_pg:pop_sr":0,
    "qs_pg:qs_pg_placetype":"localadmin",
    "qs_pg:qs_pg_placetype_gp":"LocalAdmin",
    "qs_pg:woe_adm0":23424875,
    "woe:adm0_id":23424875,
    "woe:name_adm0":"Lietuva",
    "woe:name_adm1":"Vilniaus Apskritis",
    "woe:placetype":"LocalAdmin",
    "wof:name":"Traku Seniunija",
    "wof:placetype":"localadmin"
},
  "geometry": {"coordinates":[24.9333,54.649455],"type":"Point"}
}