{
  "type": "Feature",
  "properties": {
    "gn:admin1_code":"61.0",
    "gn:admin2_code":"71.0",
    "gn:asciiname":"Margavoniai",
    "gn:country_code":"LT",
    "gn:dem":104,
    "gn:feature_class":"P",
    "gn:feature_code":"PPL",
    "gn:name":"Margavoniai",
    "gn:population":0,
    "gn:timezone":"Europe/Vilnius",
    "iso:country":"LT",
    "name:lit_x_preferred":[
        "Margavoniai"
    ],
    "wof:name":"Margavoniai",
    "wof:placetype":"locality"
},
  "geometry": {"coordinates":[23.73554,55.73962],"type":"Point"}
}