{
  "type": "Feature",
  "properties": {
    "gn:admin1_code":"65.0",
    "gn:admin2_code":"89.0",
    "gn:asciiname":"Drublionys",
    "gn:country_code":"LT",
    "gn:dem":120,
    "gn:feature_class":"P",
    "gn:feature_code":"PPL",
    "gn:name":"Drublionys",
    "gn:population":0,
    "gn:timezone":"Europe/Vilnius",
    "iso:country":"LT",
    "name:und_x_variant":[
        "Drublionis",
        "Drublioni\u0173",
        "Drublionys"
    ],
    "wof:name":"Drublionys",
    "wof:placetype":"locality"
},
  "geometry": {"coordinates":[24.94043,55.09226],"type":"Point"}
}