{
  "type": "Feature",
  "properties": {
    "gn:admin1_code":"61",
    "gn:admin2_code":"47.0",
    "gn:asciiname":"Dilbineliai",
    "gn:country_code":"LT",
    "gn:dem":87,
    "gn:feature_class":"P",
    "gn:feature_code":"PPL",
    "gn:name":"Dilbin\u0117liai",
    "gn:population":0,
    "gn:timezone":"Europe/Vilnius",
    "iso:country":"LT",
    "name:lit_x_preferred":[
        "Dilbin\u0117liai"
    ],
    "wof:name":"Dilbineliai",
    "wof:placetype":"locality"
},
  "geometry": {"coordinates":[23.18367000000001,56.30254],"type":"Point"}
}