{
  "type": "Feature",
  "properties": {
    "gn:admin1_code":"61.0",
    "gn:admin2_code":"71.0",
    "gn:asciiname":"Vainiunai",
    "gn:country_code":"LT",
    "gn:dem":91,
    "gn:feature_class":"P",
    "gn:feature_code":"PPL",
    "gn:name":"Vaini\u016bnai",
    "gn:population":0,
    "gn:timezone":"Europe/Vilnius",
    "iso:country":"LT",
    "name:lit_x_preferred":[
        "Vaini\u016bnai"
    ],
    "wof:name":"Vainiunai",
    "wof:placetype":"locality"
},
  "geometry": {"coordinates":[23.78419,55.65799000000001],"type":"Point"}
}