{
  "type": "Feature",
  "properties": {
    "gn:admin1_code":"60",
    "gn:admin2_code":"27.0",
    "gn:asciiname":"Kerava",
    "gn:country_code":"LT",
    "gn:dem":55,
    "gn:feature_class":"P",
    "gn:feature_code":"PPL",
    "gn:name":"Kerava",
    "gn:population":0,
    "gn:timezone":"Europe/Vilnius",
    "iso:country":"LT",
    "name:ara_x_preferred":[
        "\u0643\u064a\u0631\u0627\u0641\u0627"
    ],
    "name:bel_x_preferred":[
        "\u041a\u0435\u0440\u0430\u0432\u0430"
    ],
    "name:bul_x_preferred":[
        "\u041a\u0435\u0440\u0430\u0432\u0430"
    ],
    "name:cat_x_preferred":[
        "Kerava"
    ],
    "name:ceb_x_preferred":[
        "Kerava"
    ],
    "name:ces_x_preferred":[
        "Kerava"
    ],
    "name:deu_x_preferred":[
        "Kerava"
    ],
    "name:est_x_preferred":[
        "Kerava"
    ],
    "name:fas_x_preferred":[
        "\u06a9\u0631\u0627\u0648\u0627"
    ],
    "name:fin_x_preferred":[
        "Kerava"
    ],
    "name:fra_x_preferred":[
        "Kerava"
    ],
    "name:glg_x_preferred":[
        "Kerava"
    ],
    "name:ind_x_preferred":[
        "Kerava"
    ],
    "name:ita_x_preferred":[
        "Kerava"
    ],
    "name:jpn_x_preferred":[
        "\u30b1\u30e9\u30f4\u30a1"
    ],
    "name:kor_x_preferred":[
        "\ucf00\ub77c\ubc14"
    ],
    "name:lit_x_preferred":[
        "Kerava"
    ],
    "name:mrj_x_preferred":[
        "\u041a\u0435\u0440\u0430\u0432\u0430"
    ],
    "name:nau_x_preferred":[
        "Kerava"
    ],
    "name:nld_x_preferred":[
        "Kerava"
    ],
    "name:nno_x_preferred":[
        "Kervo"
    ],
    "name:nor_x_preferred":[
        "Kervo"
    ],
    "name:pol_x_preferred":[
        "Kerava"
    ],
    "name:ron_x_preferred":[
        "Kerava"
    ],
    "name:rus_x_preferred":[
        "\u041a\u0435\u0440\u0430\u0432\u0430"
    ],
    "name:sco_x_preferred":[
        "Kerava"
    ],
    "name:sme_x_preferred":[
        "Kerava"
    ],
    "name:spa_x_preferred":[
        "Kerava"
    ],
    "name:sqi_x_preferred":[
        "Kerava"
    ],
    "name:srp_x_preferred":[
        "\u041a\u0435\u0440\u0430\u0432\u0430"
    ],
    "name:swe_x_preferred":[
        "Kervo"
    ],
    "name:tur_x_preferred":[
        "Kerava"
    ],
    "name:ukr_x_preferred":[
        "\u041a\u0435\u0440\u0430\u0432\u0430"
    ],
    "name:urd_x_preferred":[
        "\u06a9\u06cc\u0631\u0627\u0648\u0627"
    ],
    "name:vep_x_preferred":[
        "Kerav"
    ],
    "name:vie_x_preferred":[
        "Kerava"
    ],
    "name:zho_x_preferred":[
        "\u51f1\u62c9\u74e6"
    ],
    "wof:name":"Kerava",
    "wof:placetype":"locality"
},
  "geometry": {"coordinates":[24.44135,55.67795],"type":"Point"}
}