{
  "type": "Feature",
  "properties": {
    "gn:admin1_code":"61.0",
    "gn:admin2_code":"54.0",
    "gn:asciiname":"Kirkuciai",
    "gn:country_code":"LT",
    "gn:dem":149,
    "gn:feature_class":"P",
    "gn:feature_code":"PPL",
    "gn:name":"Kirku\u010diai",
    "gn:population":0,
    "gn:timezone":"Europe/Vilnius",
    "iso:country":"LT",
    "name:und_x_variant":[
        "Kirkutse",
        "Kirku\u010diai"
    ],
    "wof:name":"Kirkuciai",
    "wof:placetype":"locality"
},
  "geometry": {"coordinates":[22.67364,55.64938000000001],"type":"Point"}
}