{
  "type": "Feature",
  "properties": {
    "gn:admin1_code":"61",
    "gn:admin2_code":"47.0",
    "gn:asciiname":"Indrisiunai",
    "gn:country_code":"LT",
    "gn:dem":41,
    "gn:feature_class":"P",
    "gn:feature_code":"PPL",
    "gn:name":"Indri\u0161i\u016bnai",
    "gn:population":0,
    "gn:timezone":"Europe/Vilnius",
    "iso:country":"LT",
    "name:lit_x_preferred":[
        "Indri\u0161i\u016bnai"
    ],
    "wof:name":"Indrisiunai",
    "wof:placetype":"locality"
},
  "geometry": {"coordinates":[23.89825,56.30517],"type":"Point"}
}