{
  "type": "Feature",
  "properties": {
    "gn:admin1_code":"64",
    "gn:admin2_code":"82.0",
    "gn:asciiname":"Ilciukai",
    "gn:country_code":"LT",
    "gn:dem":100,
    "gn:feature_class":"P",
    "gn:feature_code":"PPL",
    "gn:name":"Il\u010di\u016bkai",
    "gn:population":0,
    "gn:timezone":"Europe/Vilnius",
    "iso:country":"LT",
    "name:lit_x_preferred":[
        "Il\u010di\u016bkai"
    ],
    "wof:name":"Ilciukai",
    "wof:placetype":"locality"
},
  "geometry": {"coordinates":[25.663,55.67779],"type":"Point"}
}