{
  "type": "Feature",
  "properties": {
    "gn:admin1_code":"58.0",
    "gn:admin2_code":"21.0",
    "gn:asciiname":"Smilgynai",
    "gn:country_code":"LT",
    "gn:dem":34,
    "gn:feature_class":"P",
    "gn:feature_code":"PPL",
    "gn:name":"Smilgynai",
    "gn:population":0,
    "gn:timezone":"Europe/Vilnius",
    "iso:country":"LT",
    "name:und_x_variant":[
        "Shmilginen",
        "Smilgynai"
    ],
    "wof:name":"Smilgynai",
    "wof:placetype":"locality"
},
  "geometry": {"coordinates":[21.33027,55.76708000000001],"type":"Point"}
}