{
  "type": "Feature",
  "properties": {
    "gn:admin1_code":"56",
    "gn:admin2_code":"11.0",
    "gn:asciiname":"Laukintukai",
    "gn:country_code":"LT",
    "gn:dem":130,
    "gn:feature_class":"P",
    "gn:feature_code":"PPL",
    "gn:name":"Laukintukai",
    "gn:population":0,
    "gn:timezone":"Europe/Vilnius",
    "iso:country":"LT",
    "name:lit_x_preferred":[
        "Laukintukai"
    ],
    "wof:name":"Laukintukai",
    "wof:placetype":"locality"
},
  "geometry": {"coordinates":[23.87335,54.33816],"type":"Point"}
}