{
  "type": "Feature",
  "properties": {
    "gn:admin1_code":"59.0",
    "gn:admin2_code":"18.0",
    "gn:asciiname":"Mergasilis",
    "gn:country_code":"LT",
    "gn:dem":102,
    "gn:feature_class":"P",
    "gn:feature_code":"PPL",
    "gn:name":"Merga\u0161ilis",
    "gn:population":0,
    "gn:timezone":"Europe/Vilnius",
    "iso:country":"LT",
    "name:lit_x_preferred":[
        "Merga\u0161ilis"
    ],
    "wof:name":"Mergasilis",
    "wof:placetype":"locality"
},
  "geometry": {"coordinates":[23.57621,54.59806999999999],"type":"Point"}
}