{
  "type": "Feature",
  "properties": {
    "gn:admin1_code":"60",
    "gn:admin2_code":"27.0",
    "gn:asciiname":"Domaziskis",
    "gn:country_code":"LT",
    "gn:dem":70,
    "gn:feature_class":"P",
    "gn:feature_code":"PPL",
    "gn:name":"Doma\u017ei\u0161kis",
    "gn:population":0,
    "gn:timezone":"Europe/Vilnius",
    "iso:country":"LT",
    "name:lit_x_preferred":[
        "Doma\u017ei\u0161kis"
    ],
    "wof:name":"Domaziskis",
    "wof:placetype":"locality"
},
  "geometry": {"coordinates":[24.5828,55.60333000000001],"type":"Point"}
}