{
  "type": "Feature",
  "properties": {
    "gn:admin1_code":"62.0",
    "gn:admin2_code":"63.0",
    "gn:asciiname":"Barzunai",
    "gn:country_code":"LT",
    "gn:dem":35,
    "gn:feature_class":"P",
    "gn:feature_code":"PPL",
    "gn:name":"Barz\u016bnai",
    "gn:population":0,
    "gn:timezone":"Europe/Vilnius",
    "iso:country":"LT",
    "name:und_x_variant":[
        "Barzunay",
        "Barzunen",
        "Barz\u016bnai"
    ],
    "wof:name":"Barzunai",
    "wof:placetype":"locality"
},
  "geometry": {"coordinates":[22.13254,55.15872],"type":"Point"}
}