{
  "type": "Feature",
  "properties": {
    "gn:admin1_code":"60",
    "gn:admin2_code":"67.0",
    "gn:asciiname":"Zvirgzde",
    "gn:country_code":"LT",
    "gn:dem":54,
    "gn:feature_class":"P",
    "gn:feature_code":"PPL",
    "gn:name":"\u017dvirg\u017ed\u0117",
    "gn:population":0,
    "gn:timezone":"Europe/Vilnius",
    "iso:country":"LT",
    "name:lit_x_preferred":[
        "\u017dvirg\u017ed\u0117"
    ],
    "wof:name":"Zvirgzde",
    "wof:placetype":"locality"
},
  "geometry": {"coordinates":[24.59468,56.04883],"type":"Point"}
}