{
  "type": "Feature",
  "properties": {
    "gn:admin1_code":"64",
    "gn:admin2_code":"82.0",
    "gn:asciiname":"Ryliskes",
    "gn:country_code":"LT",
    "gn:dem":163,
    "gn:feature_class":"P",
    "gn:feature_code":"PPL",
    "gn:name":"Ryli\u0161k\u0117s",
    "gn:population":0,
    "gn:timezone":"Europe/Vilnius",
    "iso:country":"LT",
    "name:lit_x_preferred":[
        "Ryli\u0161k\u0117s"
    ],
    "wof:name":"Ryliskes",
    "wof:placetype":"locality"
},
  "geometry": {"coordinates":[25.77114,55.36979],"type":"Point"}
}