{
  "type": "Feature",
  "properties": {
    "gn:admin1_code":"61",
    "gn:admin2_code":"47.0",
    "gn:asciiname":"Zadeikiai",
    "gn:country_code":"LT",
    "gn:dem":71,
    "gn:feature_class":"P",
    "gn:feature_code":"PPL",
    "gn:name":"\u017dadeikiai",
    "gn:population":0,
    "gn:timezone":"Europe/Vilnius",
    "iso:country":"LT",
    "name:lit_x_preferred":[
        "\u017dadeikiai"
    ],
    "wof:name":"Zadeikiai",
    "wof:placetype":"locality"
},
  "geometry": {"coordinates":[23.26918,56.29356],"type":"Point"}
}