{
  "type": "Feature",
  "properties": {
    "gn:admin1_code":"65.0",
    "gn:admin2_code":"85.0",
    "gn:asciiname":"Kalesninkai",
    "gn:country_code":"LT",
    "gn:dem":170,
    "gn:feature_class":"P",
    "gn:feature_code":"PPL",
    "gn:name":"Kalesninkai",
    "gn:population":0,
    "gn:timezone":"Europe/Vilnius",
    "iso:country":"LT",
    "name:lit_x_preferred":[
        "Kalesninkai"
    ],
    "wof:name":"Kalesninkai",
    "wof:placetype":"locality"
},
  "geometry": {"coordinates":[24.84149,54.19114],"type":"Point"}
}