{
  "type": "Feature",
  "properties": {
    "gn:admin1_code":"57",
    "gn:admin2_code":"69.0",
    "gn:asciiname":"Gelionys",
    "gn:country_code":"LT",
    "gn:dem":243,
    "gn:feature_class":"P",
    "gn:feature_code":"PPL",
    "gn:name":"Gelionys",
    "gn:population":0,
    "gn:timezone":"Europe/Vilnius",
    "iso:country":"LT",
    "name:lit_x_preferred":[
        "Gelionys"
    ],
    "wof:name":"Gelionys",
    "wof:placetype":"locality"
},
  "geometry": {"coordinates":[24.47689,54.61023],"type":"Point"}
}