{
  "type": "Feature",
  "properties": {
    "gn:admin1_code":"59",
    "gn:admin2_code":"58.0",
    "gn:asciiname":"Pentupiai",
    "gn:country_code":"LT",
    "gn:dem":73,
    "gn:feature_class":"P",
    "gn:feature_code":"PPL",
    "gn:name":"Pentupiai",
    "gn:population":0,
    "gn:timezone":"Europe/Vilnius",
    "iso:country":"LT",
    "name:lit_x_preferred":[
        "Pentupiai"
    ],
    "wof:name":"Pentupiai",
    "wof:placetype":"locality"
},
  "geometry": {"coordinates":[23.58393,54.68185],"type":"Point"}
}