{
  "type": "Feature",
  "properties": {
    "gn:admin1_code":"59.0",
    "gn:admin2_code":"84.0",
    "gn:asciiname":"Dagiliai",
    "gn:country_code":"LT",
    "gn:dem":57,
    "gn:feature_class":"P",
    "gn:feature_code":"PPL",
    "gn:name":"Dagiliai",
    "gn:population":0,
    "gn:timezone":"Europe/Vilnius",
    "iso:country":"LT",
    "name:und_x_variant":[
        "Dagile",
        "Dagiliai"
    ],
    "wof:name":"Dagiliai",
    "wof:placetype":"locality"
},
  "geometry": {"coordinates":[23.14709,55.08022],"type":"Point"}
}