{
  "type": "Feature",
  "properties": {
    "gn:admin1_code":"65",
    "gn:admin2_code":"85.0",
    "gn:asciiname":"Pamerkys",
    "gn:country_code":"LT",
    "gn:dem":188,
    "gn:feature_class":"P",
    "gn:feature_code":"PPL",
    "gn:name":"Pamerkys",
    "gn:population":0,
    "gn:timezone":"Europe/Vilnius",
    "iso:country":"LT",
    "name:lit_x_preferred":[
        "Pamerkys"
    ],
    "wof:name":"Pamerkys",
    "wof:placetype":"locality"
},
  "geometry": {"coordinates":[25.55484,54.42609],"type":"Point"}
}