{
  "type": "Feature",
  "properties": {
    "gn:admin1_code":"59.0",
    "gn:admin2_code":"39.0",
    "gn:asciiname":"Stirnenai",
    "gn:country_code":"LT",
    "gn:dem":48,
    "gn:feature_class":"P",
    "gn:feature_code":"PPL",
    "gn:name":"Stirn\u0117nai",
    "gn:population":0,
    "gn:timezone":"Europe/Vilnius",
    "iso:country":"LT",
    "name:lit_x_preferred":[
        "Stirn\u0117nai"
    ],
    "wof:name":"Stirnenai",
    "wof:placetype":"locality"
},
  "geometry": {"coordinates":[23.11929,54.71724],"type":"Point"}
}