{
  "type": "Feature",
  "properties": {
    "gn:admin1_code":"59",
    "gn:admin2_code":"84.0",
    "gn:asciiname":"Meistai",
    "gn:country_code":"LT",
    "gn:dem":32,
    "gn:feature_class":"P",
    "gn:feature_code":"PPL",
    "gn:name":"Mei\u0161tai",
    "gn:population":0,
    "gn:timezone":"Europe/Vilnius",
    "iso:country":"LT",
    "name:lit_x_preferred":[
        "Mei\u0161tai"
    ],
    "wof:name":"Meistai",
    "wof:placetype":"locality"
},
  "geometry": {"coordinates":[22.88084,54.78545],"type":"Point"}
}