{
  "type": "Feature",
  "properties": {
    "gn:admin1_code":"61.0",
    "gn:admin2_code":"54.0",
    "gn:asciiname":"Budos",
    "gn:country_code":"LT",
    "gn:dem":137,
    "gn:feature_class":"P",
    "gn:feature_code":"PPL",
    "gn:name":"B\u016bdos",
    "gn:population":0,
    "gn:timezone":"Europe/Vilnius",
    "iso:country":"LT",
    "name:bug_x_preferred":[
        "Budos"
    ],
    "name:cat_x_preferred":[
        "Bud\u00f2s"
    ],
    "name:ceb_x_preferred":[
        "Budos"
    ],
    "name:deu_x_preferred":[
        "Budos"
    ],
    "name:eus_x_preferred":[
        "Bud\u00f2s"
    ],
    "name:fra_x_preferred":[
        "Budos"
    ],
    "name:hun_x_preferred":[
        "Budos"
    ],
    "name:ind_x_preferred":[
        "Budos"
    ],
    "name:ita_x_preferred":[
        "Budos"
    ],
    "name:kaz_x_preferred":[
        "\u0411\u044e\u0434\u043e\u0441"
    ],
    "name:lat_x_preferred":[
        "Budos"
    ],
    "name:mlg_x_preferred":[
        "Budos"
    ],
    "name:msa_x_preferred":[
        "Budos"
    ],
    "name:nld_x_preferred":[
        "Budos"
    ],
    "name:nor_x_preferred":[
        "Budos"
    ],
    "name:oci_x_preferred":[
        "Bud\u00f2s"
    ],
    "name:pms_x_preferred":[
        "Budos"
    ],
    "name:pol_x_preferred":[
        "Budos"
    ],
    "name:por_x_preferred":[
        "Budos"
    ],
    "name:ron_x_preferred":[
        "Budos"
    ],
    "name:slk_x_preferred":[
        "Budos"
    ],
    "name:spa_x_preferred":[
        "Budos"
    ],
    "name:srp_x_preferred":[
        "\u0411\u0438\u0434\u043e"
    ],
    "name:swe_x_preferred":[
        "Budos"
    ],
    "name:ukr_x_preferred":[
        "\u0411\u044e\u0434\u043e\u0441"
    ],
    "name:und_x_variant":[
        "Budy",
        "B\u016bdos"
    ],
    "name:uzb_x_preferred":[
        "Budos"
    ],
    "name:vie_x_preferred":[
        "Budos"
    ],
    "name:vol_x_preferred":[
        "Budos"
    ],
    "name:war_x_preferred":[
        "Budos"
    ],
    "wof:name":"Budos",
    "wof:placetype":"locality"
},
  "geometry": {"coordinates":[22.92865,55.50153],"type":"Point"}
}