{
  "type": "Feature",
  "properties": {
    "gn:admin1_code":"56",
    "gn:admin2_code":"11.0",
    "gn:asciiname":"Zivulciske",
    "gn:country_code":"LT",
    "gn:dem":68,
    "gn:feature_class":"P",
    "gn:feature_code":"PPL",
    "gn:name":"\u017divul\u010di\u0161k\u0117",
    "gn:population":0,
    "gn:timezone":"Europe/Vilnius",
    "iso:country":"LT",
    "name:lit_x_preferred":[
        "\u017divul\u010di\u0161k\u0117"
    ],
    "wof:name":"Zivulciske",
    "wof:placetype":"locality"
},
  "geometry": {"coordinates":[23.96896,54.18026],"type":"Point"}
}