{
  "type": "Feature",
  "properties": {
    "gn:admin1_code":"60",
    "gn:admin2_code":"27.0",
    "gn:asciiname":"Tautvilai",
    "gn:country_code":"LT",
    "gn:dem":67,
    "gn:feature_class":"P",
    "gn:feature_code":"PPL",
    "gn:name":"Tautvilai",
    "gn:population":0,
    "gn:timezone":"Europe/Vilnius",
    "iso:country":"LT",
    "name:lit_x_preferred":[
        "Tautvilai"
    ],
    "wof:name":"Tautvilai",
    "wof:placetype":"locality"
},
  "geometry": {"coordinates":[24.72511,55.84933],"type":"Point"}
}