{
  "type": "Feature",
  "properties": {
    "gn:admin1_code":"64",
    "gn:admin2_code":"62.0",
    "gn:asciiname":"Sikariskiai",
    "gn:country_code":"LT",
    "gn:dem":161,
    "gn:feature_class":"P",
    "gn:feature_code":"PPL",
    "gn:name":"Sikari\u0161kiai",
    "gn:population":0,
    "gn:timezone":"Europe/Vilnius",
    "iso:country":"LT",
    "name:lit_x_preferred":[
        "Sikari\u0161kiai"
    ],
    "wof:name":"Sikariskiai",
    "wof:placetype":"locality"
},
  "geometry": {"coordinates":[25.48272,55.17],"type":"Point"}
}