{
  "type": "Feature",
  "properties": {
    "gn:admin1_code":"62.0",
    "gn:admin2_code":"87.0",
    "gn:asciiname":"Gulbes",
    "gn:country_code":"LT",
    "gn:dem":168,
    "gn:feature_class":"P",
    "gn:feature_code":"PPL",
    "gn:name":"Gulb\u0117s",
    "gn:population":0,
    "gn:timezone":"Europe/Vilnius",
    "iso:country":"LT",
    "name:und_x_variant":[
        "Gul\u2019benay",
        "Gulb\u0117s"
    ],
    "wof:name":"Gulbes",
    "wof:placetype":"locality"
},
  "geometry": {"coordinates":[22.28046,55.61868000000001],"type":"Point"}
}