{
  "type": "Feature",
  "properties": {
    "gn:admin1_code":"59.0",
    "gn:admin2_code":"58.0",
    "gn:asciiname":"Kazliskiai",
    "gn:country_code":"LT",
    "gn:dem":64,
    "gn:feature_class":"P",
    "gn:feature_code":"PPL",
    "gn:name":"Kazli\u0161kiai",
    "gn:population":0,
    "gn:timezone":"Europe/Vilnius",
    "iso:country":"LT",
    "name:und_x_variant":[
        "Kazli\u0161ki\u0173",
        "Kozlishki",
        "Kazli\u0161kiai"
    ],
    "wof:name":"Kazliskiai",
    "wof:placetype":"locality"
},
  "geometry": {"coordinates":[23.54404,54.78748],"type":"Point"}
}