{
  "type": "Feature",
  "properties": {
    "gn:admin1_code":"61.0",
    "gn:admin2_code":"54.0",
    "gn:asciiname":"Zelviai",
    "gn:country_code":"LT",
    "gn:dem":124,
    "gn:feature_class":"P",
    "gn:feature_code":"PPL",
    "gn:name":"\u017delviai",
    "gn:population":0,
    "gn:timezone":"Europe/Vilnius",
    "iso:country":"LT",
    "name:und_x_variant":[
        "Zhelvyay",
        "\u017delviai"
    ],
    "wof:name":"Zelviai",
    "wof:placetype":"locality"
},
  "geometry": {"coordinates":[22.66551,55.76128000000001],"type":"Point"}
}