{
  "type": "Feature",
  "properties": {
    "gn:admin1_code":"62",
    "gn:admin2_code":"94.0",
    "gn:asciiname":"Antanava",
    "gn:country_code":"LT",
    "gn:dem":72,
    "gn:feature_class":"P",
    "gn:feature_code":"PPL",
    "gn:name":"Antanava",
    "gn:population":0,
    "gn:timezone":"Europe/Vilnius",
    "iso:country":"LT",
    "name:lit_x_preferred":[
        "Antanava"
    ],
    "wof:name":"Antanava",
    "wof:placetype":"locality"
},
  "geometry": {"coordinates":[23.09443,55.24352],"type":"Point"}
}