{
  "type": "Feature",
  "properties": {
    "gn:admin1_code":"61.0",
    "gn:admin2_code":"47.0",
    "gn:asciiname":"Martyniskiai",
    "gn:country_code":"LT",
    "gn:dem":84,
    "gn:feature_class":"P",
    "gn:feature_code":"PPL",
    "gn:name":"Martyni\u0161kiai",
    "gn:population":0,
    "gn:timezone":"Europe/Vilnius",
    "iso:country":"LT",
    "name:und_x_variant":[
        "Martinishkyay",
        "Martyni\u0161kiai"
    ],
    "wof:name":"Martyniskiai",
    "wof:placetype":"locality"
},
  "geometry": {"coordinates":[23.12031,56.30246],"type":"Point"}
}