{
  "type": "Feature",
  "properties": {
    "gn:admin1_code":"61",
    "gn:admin2_code":"54.0",
    "gn:asciiname":"Lauriske",
    "gn:country_code":"LT",
    "gn:dem":183,
    "gn:feature_class":"P",
    "gn:feature_code":"PPL",
    "gn:name":"Lauri\u0161k\u0117",
    "gn:population":0,
    "gn:timezone":"Europe/Vilnius",
    "iso:country":"LT",
    "name:lit_x_preferred":[
        "Lauri\u0161k\u0117"
    ],
    "wof:name":"Lauriske",
    "wof:placetype":"locality"
},
  "geometry": {"coordinates":[22.5678,55.74521],"type":"Point"}
}