{
  "type": "Feature",
  "properties": {
    "gn:admin1_code":"61",
    "gn:admin2_code":"65.0",
    "gn:asciiname":"Puodziskiai",
    "gn:country_code":"LT",
    "gn:dem":55,
    "gn:feature_class":"P",
    "gn:feature_code":"PPL",
    "gn:name":"Puod\u017ei\u0161kiai",
    "gn:population":0,
    "gn:timezone":"Europe/Vilnius",
    "iso:country":"LT",
    "name:lit_x_preferred":[
        "Puod\u017ei\u0161kiai"
    ],
    "wof:name":"Puodziskiai",
    "wof:placetype":"locality"
},
  "geometry": {"coordinates":[24.04815,55.91776],"type":"Point"}
}