{
  "type": "Feature",
  "properties": {
    "gn:admin1_code":"60.0",
    "gn:admin2_code":"36.0",
    "gn:asciiname":"Rinkuskiai",
    "gn:country_code":"LT",
    "gn:dem":51,
    "gn:feature_class":"P",
    "gn:feature_code":"PPL",
    "gn:name":"Rinku\u0161kiai",
    "gn:population":0,
    "gn:timezone":"Europe/Vilnius",
    "iso:country":"LT",
    "name:und_x_variant":[
        "Rimkushkyay",
        "Rimkushkiai",
        "Rinku\u0161kiai"
    ],
    "wof:name":"Rinkuskiai",
    "wof:placetype":"locality"
},
  "geometry": {"coordinates":[24.74254,56.2274],"type":"Point"}
}