{
  "type": "Feature",
  "properties": {
    "gn:admin1_code":"65.0",
    "gn:admin2_code":"86.0",
    "gn:asciiname":"Daumilai",
    "gn:country_code":"LT",
    "gn:dem":158,
    "gn:feature_class":"P",
    "gn:feature_code":"PPL",
    "gn:name":"Daumilai",
    "gn:population":0,
    "gn:timezone":"Europe/Vilnius",
    "iso:country":"LT",
    "name:eng_x_preferred":[
        "Daumilai"
    ],
    "name:rus_x_preferred":[
        "\u0414\u0430\u0443\u043c\u0438\u043b\u0430\u0439"
    ],
    "name:und_x_variant":[
        "Dovmily"
    ],
    "wof:name":"Daumilai",
    "wof:placetype":"locality"
},
  "geometry": {"coordinates":[26.06342,55.00796999999999],"type":"Point"}
}