{
  "type": "Feature",
  "properties": {
    "gn:admin1_code":"60.0",
    "gn:admin2_code":"67.0",
    "gn:asciiname":"Pazasai",
    "gn:country_code":"LT",
    "gn:dem":41,
    "gn:feature_class":"P",
    "gn:feature_code":"PPL",
    "gn:name":"Pa\u017e\u0105sai",
    "gn:population":0,
    "gn:timezone":"Europe/Vilnius",
    "iso:country":"LT",
    "name:lit_x_preferred":[
        "Pa\u017e\u0105sai"
    ],
    "name:und_x_variant":[
        "Pazhasyay",
        "Pa\u017easiai"
    ],
    "wof:name":"Pazasai",
    "wof:placetype":"locality"
},
  "geometry": {"coordinates":[24.28912,56.00784],"type":"Point"}
}