{
  "type": "Feature",
  "properties": {
    "gn:admin1_code":"64",
    "gn:admin2_code":"62.0",
    "gn:asciiname":"Raudonele",
    "gn:country_code":"LT",
    "gn:dem":161,
    "gn:feature_class":"P",
    "gn:feature_code":"PPL",
    "gn:name":"Raudon\u0117l\u0117",
    "gn:population":0,
    "gn:timezone":"Europe/Vilnius",
    "iso:country":"LT",
    "name:lit_x_preferred":[
        "Raudon\u0117l\u0117"
    ],
    "wof:name":"Raudonele",
    "wof:placetype":"locality"
},
  "geometry": {"coordinates":[25.53201,55.28868000000001],"type":"Point"}
}