{
  "type": "Feature",
  "properties": {
    "gn:admin1_code":"61.0",
    "gn:admin2_code":"54.0",
    "gn:asciiname":"Stulgiai",
    "gn:country_code":"LT",
    "gn:dem":151,
    "gn:feature_class":"P",
    "gn:feature_code":"PPL",
    "gn:name":"Stulgiai",
    "gn:population":0,
    "gn:timezone":"Europe/Vilnius",
    "iso:country":"LT",
    "name:eng_x_preferred":[
        "Stulgiai"
    ],
    "name:rus_x_preferred":[
        "\u0421\u0442\u0443\u043b\u044c\u0433\u044f\u0439"
    ],
    "name:und_x_variant":[
        "Stulgi\u0173",
        "Stul\u2019gyay",
        "Stulgiai"
    ],
    "wof:name":"Stulgiai",
    "wof:placetype":"locality"
},
  "geometry": {"coordinates":[22.67879,55.48683000000001],"type":"Point"}
}