{
  "type": "Feature",
  "properties": {
    "gn:admin1_code":"63.0",
    "gn:admin2_code":"61.0",
    "gn:asciiname":"Kapenai",
    "gn:country_code":"LT",
    "gn:dem":81,
    "gn:feature_class":"P",
    "gn:feature_code":"PPL",
    "gn:name":"Kap\u0117nai",
    "gn:population":0,
    "gn:timezone":"Europe/Vilnius",
    "iso:country":"LT",
    "name:lit_x_preferred":[
        "Kap\u0117nai"
    ],
    "wof:name":"Kapenai",
    "wof:placetype":"locality"
},
  "geometry": {"coordinates":[22.52757,56.15742],"type":"Point"}
}