{
  "type": "Feature",
  "properties": {
    "gn:admin1_code":"65.0",
    "gn:admin2_code":"42.0",
    "gn:asciiname":"Mackonys",
    "gn:country_code":"LT",
    "gn:dem":160,
    "gn:feature_class":"P",
    "gn:feature_code":"PPL",
    "gn:name":"Mackonys",
    "gn:population":0,
    "gn:timezone":"Europe/Vilnius",
    "iso:country":"LT",
    "name:und_x_variant":[
        "Matskany",
        "Mackonys"
    ],
    "wof:name":"Mackonys",
    "wof:placetype":"locality"
},
  "geometry": {"coordinates":[24.69415,54.68187],"type":"Point"}
}