{
  "type": "Feature",
  "properties": {
    "gn:admin1_code":"56",
    "gn:admin2_code":"38.0",
    "gn:asciiname":"Pagilsys",
    "gn:country_code":"LT",
    "gn:dem":109,
    "gn:feature_class":"P",
    "gn:feature_code":"PPL",
    "gn:name":"Pagil\u0161ys",
    "gn:population":0,
    "gn:timezone":"Europe/Vilnius",
    "iso:country":"LT",
    "name:lit_x_preferred":[
        "Pagil\u0161ys"
    ],
    "wof:name":"Pagilsys",
    "wof:placetype":"locality"
},
  "geometry": {"coordinates":[24.19992,54.20864],"type":"Point"}
}