{
  "type": "Feature",
  "properties": {
    "gn:admin1_code":"60",
    "gn:admin2_code":"73.0",
    "gn:asciiname":"Ilgalaukiai",
    "gn:country_code":"LT",
    "gn:dem":98,
    "gn:feature_class":"P",
    "gn:feature_code":"PPL",
    "gn:name":"Ilgalaukiai",
    "gn:population":0,
    "gn:timezone":"Europe/Vilnius",
    "iso:country":"LT",
    "name:lit_x_preferred":[
        "Ilgalaukiai"
    ],
    "wof:name":"Ilgalaukiai",
    "wof:placetype":"locality"
},
  "geometry": {"coordinates":[25.39878,55.97456999999999],"type":"Point"}
}