{
  "type": "Feature",
  "properties": {
    "gn:admin1_code":"60",
    "gn:admin2_code":"73.0",
    "gn:asciiname":"Pakluoniai",
    "gn:country_code":"LT",
    "gn:dem":146,
    "gn:feature_class":"P",
    "gn:feature_code":"PPL",
    "gn:name":"Pakluoniai",
    "gn:population":0,
    "gn:timezone":"Europe/Vilnius",
    "iso:country":"LT",
    "name:lit_x_preferred":[
        "Pakluoniai"
    ],
    "wof:name":"Pakluoniai",
    "wof:placetype":"locality"
},
  "geometry": {"coordinates":[25.60756,55.80895],"type":"Point"}
}