{
  "type": "Feature",
  "properties": {
    "gn:admin1_code":"0.0",
    "gn:asciiname":"Silenai",
    "gn:cc2":"LT",
    "gn:country_code":"LT",
    "gn:dem":66,
    "gn:feature_class":"P",
    "gn:feature_code":"PPL",
    "gn:name":"\u0160il\u0117nai",
    "gn:population":0,
    "gn:timezone":"Europe/Vilnius",
    "iso:country":"LT",
    "name:und_x_variant":[
        "Shilany",
        "\u0160il\u0117nai"
    ],
    "wof:name":"Silenai",
    "wof:placetype":"locality"
},
  "geometry": {"coordinates":[24.38333,54.81667],"type":"Point"}
}