{
  "type": "Feature",
  "properties": {
    "gn:admin1_code":"57",
    "gn:admin2_code":"53.0",
    "gn:asciiname":"Zemaiciai",
    "gn:country_code":"LT",
    "gn:dem":67,
    "gn:feature_class":"P",
    "gn:feature_code":"PPL",
    "gn:name":"\u017demai\u010diai",
    "gn:population":0,
    "gn:timezone":"Europe/Vilnius",
    "iso:country":"LT",
    "name:lit_x_preferred":[
        "\u017demai\u010diai"
    ],
    "wof:name":"Zemaiciai",
    "wof:placetype":"locality"
},
  "geometry": {"coordinates":[23.8312,55.38464000000001],"type":"Point"}
}