{
  "type": "Feature",
  "properties": {
    "gn:admin1_code":"63",
    "gn:admin2_code":"68.0",
    "gn:asciiname":"Glaudziai",
    "gn:country_code":"LT",
    "gn:dem":129,
    "gn:feature_class":"P",
    "gn:feature_code":"PPL",
    "gn:name":"Glaud\u017eiai",
    "gn:population":0,
    "gn:timezone":"Europe/Vilnius",
    "iso:country":"LT",
    "name:lit_x_preferred":[
        "Glaud\u017eiai"
    ],
    "wof:name":"Glaudziai",
    "wof:placetype":"locality"
},
  "geometry": {"coordinates":[21.9143,55.89932],"type":"Point"}
}