{
  "type": "Feature",
  "properties": {
    "gn:admin1_code":"56.0",
    "gn:admin2_code":"11.0",
    "gn:asciiname":"Rumbonys",
    "gn:country_code":"LT",
    "gn:dem":73,
    "gn:feature_class":"P",
    "gn:feature_code":"PPL",
    "gn:name":"Rumbonys",
    "gn:population":0,
    "gn:timezone":"Europe/Vilnius",
    "iso:country":"LT",
    "name:und_x_variant":[
        "Rumboviche",
        "Rumboni\u0173",
        "Rumbowicze",
        "Rumbonys"
    ],
    "wof:name":"Rumbonys",
    "wof:placetype":"locality"
},
  "geometry": {"coordinates":[24.05481,54.46704],"type":"Point"}
}