{
  "type": "Feature",
  "properties": {
    "gn:admin1_code":"59",
    "gn:admin2_code":"58.0",
    "gn:asciiname":"Kuciske",
    "gn:country_code":"LT",
    "gn:dem":49,
    "gn:feature_class":"P",
    "gn:feature_code":"PPL",
    "gn:name":"Ku\u010di\u0161k\u0117",
    "gn:population":0,
    "gn:timezone":"Europe/Vilnius",
    "iso:country":"LT",
    "name:lit_x_preferred":[
        "Ku\u010di\u0161k\u0117"
    ],
    "wof:name":"Kuciske",
    "wof:placetype":"locality"
},
  "geometry": {"coordinates":[23.32684,54.74129],"type":"Point"}
}