{
  "type": "Feature",
  "properties": {
    "gn:admin1_code":"61.0",
    "gn:admin2_code":"54.0",
    "gn:asciiname":"Lapkalnis",
    "gn:country_code":"LT",
    "gn:dem":136,
    "gn:feature_class":"P",
    "gn:feature_code":"PPL",
    "gn:name":"Lapkalnis",
    "gn:population":0,
    "gn:timezone":"Europe/Vilnius",
    "iso:country":"LT",
    "name:lit_x_preferred":[
        "Lapkalnis"
    ],
    "wof:name":"Lapkalnis",
    "wof:placetype":"locality"
},
  "geometry": {"coordinates":[22.97624,55.58843],"type":"Point"}
}