{
  "type": "Feature",
  "properties": {
    "gn:admin1_code":"56.0",
    "gn:admin2_code":"38.0",
    "gn:asciiname":"Giraite",
    "gn:country_code":"LT",
    "gn:dem":141,
    "gn:feature_class":"P",
    "gn:feature_code":"PPL",
    "gn:name":"Girait\u0117",
    "gn:population":0,
    "gn:timezone":"Europe/Vilnius",
    "iso:country":"LT",
    "name:lit_x_preferred":[
        "Girait\u0117"
    ],
    "name:und_x_variant":[
        "Girait\u0117",
        "Geraytsy",
        "Gerai\u010diai"
    ],
    "wof:name":"Giraite",
    "wof:placetype":"locality"
},
  "geometry": {"coordinates":[24.66326,54.26633],"type":"Point"}
}