{
  "type": "Feature",
  "properties": {
    "gn:admin1_code":"57",
    "gn:admin2_code":"53.0",
    "gn:asciiname":"Antusava",
    "gn:country_code":"LT",
    "gn:dem":98,
    "gn:feature_class":"P",
    "gn:feature_code":"PPL",
    "gn:name":"Antu\u0161ava",
    "gn:population":0,
    "gn:timezone":"Europe/Vilnius",
    "iso:country":"LT",
    "name:lit_x_preferred":[
        "Antu\u0161ava"
    ],
    "wof:name":"Antusava",
    "wof:placetype":"locality"
},
  "geometry": {"coordinates":[23.73498,55.48564],"type":"Point"}
}