{
  "type": "Feature",
  "properties": {
    "gn:admin1_code":"65",
    "gn:admin2_code":"13.0",
    "gn:asciiname":"Pauolia",
    "gn:country_code":"LT",
    "gn:dem":135,
    "gn:feature_class":"P",
    "gn:feature_code":"PPL",
    "gn:name":"Pauolia",
    "gn:population":0,
    "gn:timezone":"Europe/Vilnius",
    "iso:country":"LT",
    "name:lit_x_preferred":[
        "Pauolia"
    ],
    "wof:name":"Pauolia",
    "wof:placetype":"locality"
},
  "geometry": {"coordinates":[25.19779,55.0271],"type":"Point"}
}