{
  "type": "Feature",
  "properties": {
    "gn:admin1_code":"59.0",
    "gn:admin2_code":"18.0",
    "gn:asciiname":"Budvieciai",
    "gn:country_code":"LT",
    "gn:dem":50,
    "gn:feature_class":"P",
    "gn:feature_code":"PPL",
    "gn:name":"B\u016bdvie\u010diai",
    "gn:population":0,
    "gn:timezone":"Europe/Vilnius",
    "iso:country":"LT",
    "name:und_x_variant":[
        "Budvechay",
        "Budvetse",
        "B\u016bdvie\u010diai"
    ],
    "wof:name":"Budvieciai",
    "wof:placetype":"locality"
},
  "geometry": {"coordinates":[23.39652,54.6259],"type":"Point"}
}