{
  "type": "Feature",
  "properties": {
    "gn:admin1_code":"60.0",
    "gn:admin2_code":"67.0",
    "gn:asciiname":"Talackoniai",
    "gn:country_code":"LT",
    "gn:dem":35,
    "gn:feature_class":"P",
    "gn:feature_code":"PPL",
    "gn:name":"Tala\u010dkoniai",
    "gn:population":0,
    "gn:timezone":"Europe/Vilnius",
    "iso:country":"LT",
    "name:und_x_variant":[
        "Tala\u010dkoni\u0173",
        "Talachkonyay",
        "Tala\u010dkonis",
        "Tala\u010dkoniai"
    ],
    "wof:name":"Talackoniai",
    "wof:placetype":"locality"
},
  "geometry": {"coordinates":[24.36314,56.0262],"type":"Point"}
}