{
  "type": "Feature",
  "properties": {
    "gn:admin1_code":"64",
    "gn:admin2_code":"45.0",
    "gn:asciiname":"Pabaltys",
    "gn:country_code":"LT",
    "gn:dem":146,
    "gn:feature_class":"P",
    "gn:feature_code":"PPL",
    "gn:name":"Pabaltys",
    "gn:population":0,
    "gn:timezone":"Europe/Vilnius",
    "iso:country":"LT",
    "name:lit_x_preferred":[
        "Pabaltys"
    ],
    "wof:name":"Pabaltys",
    "wof:placetype":"locality"
},
  "geometry": {"coordinates":[26.0979,55.30291999999999],"type":"Point"}
}