{
  "type": "Feature",
  "properties": {
    "gn:admin1_code":"56",
    "gn:admin2_code":"11.0",
    "gn:asciiname":"Tarucionys",
    "gn:country_code":"LT",
    "gn:dem":135,
    "gn:feature_class":"P",
    "gn:feature_code":"PPL",
    "gn:name":"Taru\u010dionys",
    "gn:population":0,
    "gn:timezone":"Europe/Vilnius",
    "iso:country":"LT",
    "name:lit_x_preferred":[
        "Taru\u010dionys"
    ],
    "wof:name":"Tarucionys",
    "wof:placetype":"locality"
},
  "geometry": {"coordinates":[24.03206,54.22176999999999],"type":"Point"}
}