{
  "type": "Feature",
  "properties": {
    "gn:admin1_code":"60.0",
    "gn:admin2_code":"27.0",
    "gn:asciiname":"Kuciai",
    "gn:country_code":"LT",
    "gn:dem":60,
    "gn:feature_class":"P",
    "gn:feature_code":"PPL",
    "gn:name":"Ku\u010diai",
    "gn:population":0,
    "gn:timezone":"Europe/Vilnius",
    "iso:country":"LT",
    "name:und_x_variant":[
        "Kuche",
        "Ku\u010diai"
    ],
    "wof:name":"Kuciai",
    "wof:placetype":"locality"
},
  "geometry": {"coordinates":[24.37242,55.60599000000001],"type":"Point"}
}