{
  "type": "Feature",
  "properties": {
    "gn:admin1_code":"65",
    "gn:admin2_code":"86.0",
    "gn:asciiname":"Vajukiske",
    "gn:country_code":"LT",
    "gn:dem":148,
    "gn:feature_class":"P",
    "gn:feature_code":"PPL",
    "gn:name":"Vajuki\u0161k\u0117",
    "gn:population":0,
    "gn:timezone":"Europe/Vilnius",
    "iso:country":"LT",
    "name:lit_x_preferred":[
        "Vajuki\u0161k\u0117"
    ],
    "wof:name":"Vajukiske",
    "wof:placetype":"locality"
},
  "geometry": {"coordinates":[26.15279,55.24924],"type":"Point"}
}