{
  "type": "Feature",
  "properties": {
    "gn:admin1_code":"62",
    "gn:admin2_code":"87.0",
    "gn:asciiname":"Pailgotis",
    "gn:country_code":"LT",
    "gn:dem":88,
    "gn:feature_class":"P",
    "gn:feature_code":"PPL",
    "gn:name":"Pailgotis",
    "gn:population":0,
    "gn:timezone":"Europe/Vilnius",
    "iso:country":"LT",
    "name:lit_x_preferred":[
        "Pailgotis"
    ],
    "wof:name":"Pailgotis",
    "wof:placetype":"locality"
},
  "geometry": {"coordinates":[22.08018,55.46117],"type":"Point"}
}