{
  "type": "Feature",
  "properties": {
    "gn:admin1_code":"64.0",
    "gn:admin2_code":"30.0",
    "gn:asciiname":"Magunai",
    "gn:country_code":"LT",
    "gn:dem":166,
    "gn:feature_class":"P",
    "gn:feature_code":"PPL",
    "gn:name":"Mag\u016bnai",
    "gn:population":0,
    "gn:timezone":"Europe/Vilnius",
    "iso:country":"LT",
    "name:und_x_variant":[
        "Maguny",
        "Mag\u016bnai"
    ],
    "wof:name":"Magunai",
    "wof:placetype":"locality"
},
  "geometry": {"coordinates":[26.44301,55.56453000000001],"type":"Point"}
}