{
  "type": "Feature",
  "properties": {
    "gn:admin1_code":"65",
    "gn:admin2_code":"79.0",
    "gn:asciiname":"Paberze",
    "gn:country_code":"LT",
    "gn:dem":188,
    "gn:feature_class":"P",
    "gn:feature_code":"PPL",
    "gn:name":"Paber\u017e\u0117",
    "gn:population":0,
    "gn:timezone":"Europe/Vilnius",
    "iso:country":"LT",
    "name:lit_x_preferred":[
        "Paber\u017e\u0117"
    ],
    "wof:name":"Paberze",
    "wof:placetype":"locality"
},
  "geometry": {"coordinates":[24.50736,54.6389],"type":"Point"}
}