{
  "type": "Feature",
  "properties": {
    "gn:admin1_code":"63.0",
    "gn:admin2_code":"78.0",
    "gn:asciiname":"Jonaiciai",
    "gn:country_code":"LT",
    "gn:dem":147,
    "gn:feature_class":"P",
    "gn:feature_code":"PPL",
    "gn:name":"Jonai\u010diai",
    "gn:population":0,
    "gn:timezone":"Europe/Vilnius",
    "iso:country":"LT",
    "name:und_x_variant":[
        "Gonvichyay",
        "Jonai\u010diai"
    ],
    "wof:name":"Jonaiciai",
    "wof:placetype":"locality"
},
  "geometry": {"coordinates":[22.55366,55.91094],"type":"Point"}
}