{
  "type": "Feature",
  "properties": {
    "gn:admin1_code":"60",
    "gn:admin2_code":"57.0",
    "gn:asciiname":"Svedukalnis",
    "gn:country_code":"LT",
    "gn:dem":92,
    "gn:feature_class":"P",
    "gn:feature_code":"PPL",
    "gn:name":"\u0160vedukalnis",
    "gn:population":0,
    "gn:timezone":"Europe/Vilnius",
    "iso:country":"LT",
    "name:lit_x_preferred":[
        "\u0160vedukalnis"
    ],
    "wof:name":"Svedukalnis",
    "wof:placetype":"locality"
},
  "geometry": {"coordinates":[25.18,55.91719000000001],"type":"Point"}
}