{
  "type": "Feature",
  "properties": {
    "gn:admin1_code":"63",
    "gn:admin2_code":"61.0",
    "gn:asciiname":"Kuisiai",
    "gn:country_code":"LT",
    "gn:dem":131,
    "gn:feature_class":"P",
    "gn:feature_code":"PPL",
    "gn:name":"Kuisiai",
    "gn:population":0,
    "gn:timezone":"Europe/Vilnius",
    "iso:country":"LT",
    "name:lit_x_preferred":[
        "Kuisiai"
    ],
    "wof:name":"Kuisiai",
    "wof:placetype":"locality"
},
  "geometry": {"coordinates":[22.13491,56.1794],"type":"Point"}
}