{
  "type": "Feature",
  "properties": {
    "gn:admin1_code":"61.0",
    "gn:admin2_code":"29.0",
    "gn:asciiname":"Lingailiai",
    "gn:country_code":"LT",
    "gn:dem":129,
    "gn:feature_class":"P",
    "gn:feature_code":"PPL",
    "gn:name":"Lingailiai",
    "gn:population":0,
    "gn:timezone":"Europe/Vilnius",
    "iso:country":"LT",
    "name:und_x_variant":[
        "T\u016braki\u0161kiai",
        "Tolikishkis",
        "Lingailiai"
    ],
    "wof:name":"Lingailiai",
    "wof:placetype":"locality"
},
  "geometry": {"coordinates":[23.33084,55.84439],"type":"Point"}
}