{
  "type": "Feature",
  "properties": {
    "gn:admin1_code":"58",
    "gn:admin2_code":"21.0",
    "gn:asciiname":"Liaunai",
    "gn:country_code":"LT",
    "gn:dem":6,
    "gn:feature_class":"P",
    "gn:feature_code":"PPL",
    "gn:name":"Liaunai",
    "gn:population":0,
    "gn:timezone":"Europe/Vilnius",
    "iso:country":"LT",
    "name:lit_x_preferred":[
        "Liaunai"
    ],
    "wof:name":"Liaunai",
    "wof:placetype":"locality"
},
  "geometry": {"coordinates":[21.34144,55.52486999999999],"type":"Point"}
}