{
  "type": "Feature",
  "properties": {
    "gn:admin1_code":"65",
    "gn:admin2_code":"85.0",
    "gn:asciiname":"Zaliaklonis",
    "gn:country_code":"LT",
    "gn:dem":173,
    "gn:feature_class":"P",
    "gn:feature_code":"PPL",
    "gn:name":"\u017daliaklonis",
    "gn:population":0,
    "gn:timezone":"Europe/Vilnius",
    "iso:country":"LT",
    "name:lit_x_preferred":[
        "\u017daliaklonis"
    ],
    "wof:name":"Zaliaklonis",
    "wof:placetype":"locality"
},
  "geometry": {"coordinates":[25.29218,54.33088000000001],"type":"Point"}
}