{
  "type": "Feature",
  "properties": {
    "gn:admin1_code":"59.0",
    "gn:admin2_code":"39.0",
    "gn:asciiname":"Zyniai",
    "gn:country_code":"LT",
    "gn:dem":48,
    "gn:feature_class":"P",
    "gn:feature_code":"PPL",
    "gn:name":"\u017dyniai",
    "gn:population":0,
    "gn:timezone":"Europe/Vilnius",
    "iso:country":"LT",
    "name:und_x_variant":[
        "Zhine",
        "Zhinyay",
        "\u017dini\u0173",
        "\u017dyniai"
    ],
    "wof:name":"Zyniai",
    "wof:placetype":"locality"
},
  "geometry": {"coordinates":[22.98396,54.73799],"type":"Point"}
}