{
  "type": "Feature",
  "properties": {
    "gn:admin1_code":"65",
    "gn:admin2_code":"89.0",
    "gn:asciiname":"Meiliunai",
    "gn:country_code":"LT",
    "gn:dem":106,
    "gn:feature_class":"P",
    "gn:feature_code":"PPL",
    "gn:name":"Meili\u016bnai",
    "gn:population":0,
    "gn:timezone":"Europe/Vilnius",
    "iso:country":"LT",
    "name:lit_x_preferred":[
        "Meili\u016bnai"
    ],
    "wof:name":"Meiliunai",
    "wof:placetype":"locality"
},
  "geometry": {"coordinates":[24.91522,54.91702],"type":"Point"}
}