{
  "type": "Feature",
  "properties": {
    "gn:admin1_code":"57.0",
    "gn:admin2_code":"72.0",
    "gn:asciiname":"Paalsys",
    "gn:country_code":"LT",
    "gn:dem":57,
    "gn:feature_class":"P",
    "gn:feature_code":"PPL",
    "gn:name":"Paalsys",
    "gn:population":0,
    "gn:timezone":"Europe/Vilnius",
    "iso:country":"LT",
    "name:und_x_variant":[
        "Paal\u2019sis",
        "Paalsyay",
        "Paalsys"
    ],
    "wof:name":"Paalsys",
    "wof:placetype":"locality"
},
  "geometry": {"coordinates":[22.86449,55.34495],"type":"Point"}
}