{
  "type": "Feature",
  "properties": {
    "gn:admin1_code":"58.0",
    "gn:admin2_code":"88.0",
    "gn:asciiname":"Stemples",
    "gn:country_code":"LT",
    "gn:dem":60,
    "gn:feature_class":"P",
    "gn:feature_code":"PPL",
    "gn:name":"Stempl\u0117s",
    "gn:population":0,
    "gn:timezone":"Europe/Vilnius",
    "iso:country":"LT",
    "name:und_x_variant":[
        "Drebuliai",
        "Stempley",
        "Stempl\u0117s",
        "Stempli\u0173",
        "Stempliai"
    ],
    "wof:name":"Stemples",
    "wof:placetype":"locality"
},
  "geometry": {"coordinates":[21.79517,55.50655],"type":"Point"}
}