{
  "type": "Feature",
  "properties": {
    "gn:admin1_code":"60",
    "gn:admin2_code":"73.0",
    "gn:asciiname":"Kuodiskiai",
    "gn:country_code":"LT",
    "gn:dem":77,
    "gn:feature_class":"P",
    "gn:feature_code":"PPL",
    "gn:name":"Kuodi\u0161kiai",
    "gn:population":0,
    "gn:timezone":"Europe/Vilnius",
    "iso:country":"LT",
    "name:lit_x_preferred":[
        "Kuodi\u0161kiai"
    ],
    "wof:name":"Kuodiskiai",
    "wof:placetype":"locality"
},
  "geometry": {"coordinates":[25.28505,56.08306],"type":"Point"}
}