{
  "type": "Feature",
  "properties": {
    "gn:admin1_code":"56.0",
    "gn:admin2_code":"11.0",
    "gn:asciiname":"Pivasiunai",
    "gn:country_code":"LT",
    "gn:dem":153,
    "gn:feature_class":"P",
    "gn:feature_code":"PPL",
    "gn:name":"Piva\u0161i\u016bnai",
    "gn:population":0,
    "gn:timezone":"Europe/Vilnius",
    "iso:country":"LT",
    "name:eng_x_preferred":[
        "Piva\u0161i\u016bnai"
    ],
    "name:rus_x_preferred":[
        "\u041f\u0438\u0432\u0430\u0448\u044e\u043d\u0430\u0439"
    ],
    "name:und_x_variant":[
        "Piva\u0161i\u016bn\u0173",
        "Pivashyunay",
        "Pivoshuny"
    ],
    "wof:name":"Pivasiunai",
    "wof:placetype":"locality"
},
  "geometry": {"coordinates":[24.37486,54.4607],"type":"Point"}
}