{
  "type": "Feature",
  "properties": {
    "gn:admin1_code":"63.0",
    "gn:admin2_code":"68.0",
    "gn:asciiname":"Vainaiciai",
    "gn:country_code":"LT",
    "gn:dem":86,
    "gn:feature_class":"P",
    "gn:feature_code":"PPL",
    "gn:name":"Vainai\u010diai",
    "gn:population":0,
    "gn:timezone":"Europe/Vilnius",
    "iso:country":"LT",
    "name:und_x_variant":[
        "Vaynaychey",
        "Vainai\u010di\u0173",
        "Vainai\u010diai"
    ],
    "wof:name":"Vainaiciai",
    "wof:placetype":"locality"
},
  "geometry": {"coordinates":[21.88494,55.83351999999999],"type":"Point"}
}