{
  "type": "Feature",
  "properties": {
    "gn:admin1_code":"57",
    "gn:admin2_code":"72.0",
    "gn:asciiname":"Kasbaraiciai",
    "gn:country_code":"LT",
    "gn:dem":93,
    "gn:feature_class":"P",
    "gn:feature_code":"PPL",
    "gn:name":"Kasbarai\u010diai",
    "gn:population":0,
    "gn:timezone":"Europe/Vilnius",
    "iso:country":"LT",
    "name:lit_x_preferred":[
        "Kasbarai\u010diai"
    ],
    "wof:name":"Kasbaraiciai",
    "wof:placetype":"locality"
},
  "geometry": {"coordinates":[23.16283,55.34341],"type":"Point"}
}