{
  "type": "Feature",
  "properties": {
    "gn:admin1_code":"61.0",
    "gn:admin2_code":"65.0",
    "gn:asciiname":"Steigviliai",
    "gn:country_code":"LT",
    "gn:dem":53,
    "gn:feature_class":"P",
    "gn:feature_code":"PPL",
    "gn:name":"Steigviliai",
    "gn:population":0,
    "gn:timezone":"Europe/Vilnius",
    "iso:country":"LT",
    "name:lit_x_preferred":[
        "Steigviliai"
    ],
    "name:pol_x_preferred":[
        "Steigviliai"
    ],
    "name:und_x_variant":[
        "Steigvil\u0173",
        "Steygvilyay",
        "Steiguiliai"
    ],
    "wof:name":"Steigviliai",
    "wof:placetype":"locality"
},
  "geometry": {"coordinates":[24.00863,56.19011],"type":"Point"}
}