{
  "type": "Feature",
  "properties": {
    "gn:admin1_code":"57",
    "gn:admin2_code":"53.0",
    "gn:asciiname":"Jasnagurka",
    "gn:country_code":"LT",
    "gn:dem":43,
    "gn:feature_class":"P",
    "gn:feature_code":"PPL",
    "gn:name":"Jasnagurka",
    "gn:population":0,
    "gn:timezone":"Europe/Vilnius",
    "iso:country":"LT",
    "name:lit_x_preferred":[
        "Jasnagurka"
    ],
    "wof:name":"Jasnagurka",
    "wof:placetype":"locality"
},
  "geometry": {"coordinates":[23.84429,55.20412],"type":"Point"}
}