{
  "type": "Feature",
  "properties": {
    "gn:admin1_code":"65",
    "gn:admin2_code":"86.0",
    "gn:asciiname":"Vaiciukiske II",
    "gn:country_code":"LT",
    "gn:dem":160,
    "gn:feature_class":"P",
    "gn:feature_code":"PPL",
    "gn:name":"Vai\u010diuki\u0161k\u0117 II",
    "gn:population":0,
    "gn:timezone":"Europe/Vilnius",
    "iso:country":"LT",
    "name:lit_x_preferred":[
        "Vai\u010diuki\u0161k\u0117 II"
    ],
    "wof:name":"Vaiciukiske II",
    "wof:placetype":"locality"
},
  "geometry": {"coordinates":[26.16884,55.24882],"type":"Point"}
}