{
  "type": "Feature",
  "properties": {
    "gn:admin1_code":"58.0",
    "gn:admin2_code":"75.0",
    "gn:asciiname":"Medsedziai",
    "gn:country_code":"LT",
    "gn:dem":94,
    "gn:feature_class":"P",
    "gn:feature_code":"PPL",
    "gn:name":"Meds\u0117d\u017eiai",
    "gn:population":0,
    "gn:timezone":"Europe/Vilnius",
    "iso:country":"LT",
    "name:lit_x_preferred":[
        "Meds\u0117d\u017eiai"
    ],
    "wof:name":"Medsedziai",
    "wof:placetype":"locality"
},
  "geometry": {"coordinates":[21.84412,56.23118],"type":"Point"}
}