{
  "type": "Feature",
  "properties": {
    "gn:admin1_code":"63.0",
    "gn:admin2_code":"78.0",
    "gn:asciiname":"Ringaliai",
    "gn:country_code":"LT",
    "gn:dem":153,
    "gn:feature_class":"P",
    "gn:feature_code":"PPL",
    "gn:name":"Ringaliai",
    "gn:population":0,
    "gn:timezone":"Europe/Vilnius",
    "iso:country":"LT",
    "name:und_x_variant":[
        "Ryygayle",
        "Ringaliai"
    ],
    "wof:name":"Ringaliai",
    "wof:placetype":"locality"
},
  "geometry": {"coordinates":[22.38531,55.88042],"type":"Point"}
}