{
  "type": "Feature",
  "properties": {
    "gn:admin1_code":"65",
    "gn:admin2_code":"13.0",
    "gn:asciiname":"Zagariskes",
    "gn:country_code":"LT",
    "gn:dem":150,
    "gn:feature_class":"P",
    "gn:feature_code":"PPL",
    "gn:name":"\u017dagari\u0161k\u0117s",
    "gn:population":0,
    "gn:timezone":"Europe/Vilnius",
    "iso:country":"LT",
    "name:lit_x_preferred":[
        "\u017dagari\u0161k\u0117s"
    ],
    "wof:name":"Zagariskes",
    "wof:placetype":"locality"
},
  "geometry": {"coordinates":[25.58806,54.73528],"type":"Point"}
}