{
  "type": "Feature",
  "properties": {
    "gn:admin1_code":"60",
    "gn:admin2_code":"27.0",
    "gn:asciiname":"Birentiskis",
    "gn:country_code":"LT",
    "gn:dem":80,
    "gn:feature_class":"P",
    "gn:feature_code":"PPL",
    "gn:name":"Birenti\u0161kis",
    "gn:population":0,
    "gn:timezone":"Europe/Vilnius",
    "iso:country":"LT",
    "name:lit_x_preferred":[
        "Birenti\u0161kis"
    ],
    "wof:name":"Birentiskis",
    "wof:placetype":"locality"
},
  "geometry": {"coordinates":[24.6385,55.61406],"type":"Point"}
}