{
  "type": "Feature",
  "properties": {
    "gn:admin1_code":"63",
    "gn:admin2_code":"78.0",
    "gn:asciiname":"Bartlaukis",
    "gn:country_code":"LT",
    "gn:dem":157,
    "gn:feature_class":"P",
    "gn:feature_code":"PPL",
    "gn:name":"Bartlaukis",
    "gn:population":0,
    "gn:timezone":"Europe/Vilnius",
    "iso:country":"LT",
    "name:lit_x_preferred":[
        "Bartlaukis"
    ],
    "wof:name":"Bartlaukis",
    "wof:placetype":"locality"
},
  "geometry": {"coordinates":[22.39008,55.69508],"type":"Point"}
}