{
  "type": "Feature",
  "properties": {
    "gn:admin1_code":"59",
    "gn:admin2_code":"84.0",
    "gn:asciiname":"Leoniskiai",
    "gn:country_code":"LT",
    "gn:dem":61,
    "gn:feature_class":"P",
    "gn:feature_code":"PPL",
    "gn:name":"Leoni\u0161kiai",
    "gn:population":0,
    "gn:timezone":"Europe/Vilnius",
    "iso:country":"LT",
    "name:lit_x_preferred":[
        "Leoni\u0161kiai"
    ],
    "wof:name":"Leoniskiai",
    "wof:placetype":"locality"
},
  "geometry": {"coordinates":[23.42659,55.03093000000001],"type":"Point"}
}