{
  "type": "Feature",
  "properties": {
    "gn:admin1_code":"59.0",
    "gn:admin2_code":"39.0",
    "gn:asciiname":"Penkvalakiai",
    "gn:country_code":"LT",
    "gn:dem":55,
    "gn:feature_class":"P",
    "gn:feature_code":"PPL",
    "gn:name":"Penkvalakiai",
    "gn:population":0,
    "gn:timezone":"Europe/Vilnius",
    "iso:country":"LT",
    "name:und_x_variant":[
        "Penkvalaki",
        "Penkvalakiai"
    ],
    "wof:name":"Penkvalakiai",
    "wof:placetype":"locality"
},
  "geometry": {"coordinates":[23.21971,54.68123000000001],"type":"Point"}
}