{
  "type": "Feature",
  "properties": {
    "gn:admin1_code":"60.0",
    "gn:admin2_code":"57.0",
    "gn:asciiname":"Radziunai",
    "gn:country_code":"LT",
    "gn:dem":86,
    "gn:feature_class":"P",
    "gn:feature_code":"PPL",
    "gn:name":"Rad\u017ei\u016bnai",
    "gn:population":0,
    "gn:timezone":"Europe/Vilnius",
    "iso:country":"LT",
    "name:und_x_variant":[
        "Radzyuny",
        "Rad\u017ei\u016bnai"
    ],
    "wof:name":"Radziunai",
    "wof:placetype":"locality"
},
  "geometry": {"coordinates":[24.85244,55.77954],"type":"Point"}
}