{
  "type": "Feature",
  "properties": {
    "gn:admin1_code":"61",
    "gn:admin2_code":"71.0",
    "gn:asciiname":"Juodupiai",
    "gn:country_code":"LT",
    "gn:dem":94,
    "gn:feature_class":"P",
    "gn:feature_code":"PPL",
    "gn:name":"Juodupiai",
    "gn:population":0,
    "gn:timezone":"Europe/Vilnius",
    "iso:country":"LT",
    "name:lit_x_preferred":[
        "Juodupiai"
    ],
    "wof:name":"Juodupiai",
    "wof:placetype":"locality"
},
  "geometry": {"coordinates":[23.76353,55.81794],"type":"Point"}
}