{
  "type": "Feature",
  "properties": {
    "gn:admin1_code":"58",
    "gn:admin2_code":"88.0",
    "gn:asciiname":"Ulozai",
    "gn:country_code":"LT",
    "gn:dem":20,
    "gn:feature_class":"P",
    "gn:feature_code":"PPL",
    "gn:name":"Ulozai",
    "gn:population":0,
    "gn:timezone":"Europe/Vilnius",
    "iso:country":"LT",
    "name:lit_x_preferred":[
        "Ulozai"
    ],
    "wof:name":"Ulozai",
    "wof:placetype":"locality"
},
  "geometry": {"coordinates":[21.84556,55.25124],"type":"Point"}
}