{
  "type": "Feature",
  "properties": {
    "gn:admin1_code":"64",
    "gn:admin2_code":"34.0",
    "gn:asciiname":"Papsiai",
    "gn:country_code":"LT",
    "gn:dem":102,
    "gn:feature_class":"P",
    "gn:feature_code":"PPL",
    "gn:name":"Papsiai",
    "gn:population":0,
    "gn:timezone":"Europe/Vilnius",
    "iso:country":"LT",
    "name:lit_x_preferred":[
        "Papsiai"
    ],
    "wof:name":"Papsiai",
    "wof:placetype":"locality"
},
  "geometry": {"coordinates":[25.37535,55.59328000000001],"type":"Point"}
}