{
  "type": "Feature",
  "properties": {
    "gn:admin1_code":"57.0",
    "gn:admin2_code":"69.0",
    "gn:asciiname":"Rodomisle",
    "gn:country_code":"LT",
    "gn:dem":211,
    "gn:feature_class":"P",
    "gn:feature_code":"PPL",
    "gn:name":"Rodomisl\u0117",
    "gn:population":0,
    "gn:timezone":"Europe/Vilnius",
    "iso:country":"LT",
    "name:lit_x_preferred":[
        "Rodomisl\u0117"
    ],
    "wof:name":"Rodomisle",
    "wof:placetype":"locality"
},
  "geometry": {"coordinates":[24.44511,54.60502],"type":"Point"}
}