{
  "type": "Feature",
  "properties": {
    "gn:admin1_code":"56.0",
    "gn:admin2_code":"11.0",
    "gn:asciiname":"Eiciunai",
    "gn:country_code":"LT",
    "gn:dem":143,
    "gn:feature_class":"P",
    "gn:feature_code":"PPL",
    "gn:name":"Ei\u010di\u016bnai",
    "gn:population":0,
    "gn:timezone":"Europe/Vilnius",
    "iso:country":"LT",
    "name:und_x_variant":[
        "Aytsyuntsy",
        "Eychyunay",
        "Ei\u010di\u016bn\u0173",
        "Ei\u010di\u016bnai"
    ],
    "wof:name":"Eiciunai",
    "wof:placetype":"locality"
},
  "geometry": {"coordinates":[24.31538,54.50294],"type":"Point"}
}