{
  "type": "Feature",
  "properties": {
    "gn:admin1_code":"64.0",
    "gn:admin2_code":"62.0",
    "gn:asciiname":"Laukininkai",
    "gn:country_code":"LT",
    "gn:dem":148,
    "gn:feature_class":"P",
    "gn:feature_code":"PPL",
    "gn:name":"Laukininkai",
    "gn:population":0,
    "gn:timezone":"Europe/Vilnius",
    "iso:country":"LT",
    "name:und_x_variant":[
        "Laukinink\u0173",
        "Laukininkay",
        "Laukininkai"
    ],
    "wof:name":"Laukininkai",
    "wof:placetype":"locality"
},
  "geometry": {"coordinates":[25.62728,55.14723000000001],"type":"Point"}
}