{
  "type": "Feature",
  "properties": {
    "gn:admin1_code":"59.0",
    "gn:admin2_code":"39.0",
    "gn:asciiname":"Mazuciai",
    "gn:country_code":"LT",
    "gn:dem":116,
    "gn:feature_class":"P",
    "gn:feature_code":"PPL",
    "gn:name":"Ma\u017eu\u010diai",
    "gn:population":0,
    "gn:timezone":"Europe/Vilnius",
    "iso:country":"LT",
    "name:und_x_variant":[
        "Mazhuchay",
        "Ma\u017eu\u010di\u0173",
        "Ma\u017eu\u010diai"
    ],
    "wof:name":"Mazuciai",
    "wof:placetype":"locality"
},
  "geometry": {"coordinates":[22.87555,54.59915],"type":"Point"}
}