{
  "type": "Feature",
  "properties": {
    "gn:admin1_code":"65.0",
    "gn:admin2_code":"85.0",
    "gn:asciiname":"Sabaliunai",
    "gn:country_code":"LT",
    "gn:dem":185,
    "gn:feature_class":"P",
    "gn:feature_code":"PPL",
    "gn:name":"Sabali\u016bnai",
    "gn:population":0,
    "gn:timezone":"Europe/Vilnius",
    "iso:country":"LT",
    "name:und_x_variant":[
        "Sabali\u016bni",
        "Sobolyuny",
        "Sabali\u016bnai"
    ],
    "wof:name":"Sabaliunai",
    "wof:placetype":"locality"
},
  "geometry": {"coordinates":[25.74777000000001,54.21016],"type":"Point"}
}