{
  "type": "Feature",
  "properties": {
    "gn:admin1_code":"64",
    "gn:admin2_code":"45.0",
    "gn:asciiname":"Vilnokai",
    "gn:country_code":"LT",
    "gn:dem":148,
    "gn:feature_class":"P",
    "gn:feature_code":"PPL",
    "gn:name":"Vilnokai",
    "gn:population":0,
    "gn:timezone":"Europe/Vilnius",
    "iso:country":"LT",
    "name:lit_x_preferred":[
        "Vilnokai"
    ],
    "wof:name":"Vilnokai",
    "wof:placetype":"locality"
},
  "geometry": {"coordinates":[26.48119,55.49569],"type":"Point"}
}