{
  "type": "Feature",
  "properties": {
    "gn:admin1_code":"61",
    "gn:admin2_code":"54.0",
    "gn:asciiname":"Dailydiske",
    "gn:country_code":"LT",
    "gn:dem":159,
    "gn:feature_class":"P",
    "gn:feature_code":"PPL",
    "gn:name":"Dailydi\u0161k\u0117",
    "gn:population":0,
    "gn:timezone":"Europe/Vilnius",
    "iso:country":"LT",
    "name:lit_x_preferred":[
        "Dailydi\u0161k\u0117"
    ],
    "wof:name":"Dailydiske",
    "wof:placetype":"locality"
},
  "geometry": {"coordinates":[22.67772,55.57039],"type":"Point"}
}