{
  "type": "Feature",
  "properties": {
    "gn:admin1_code":"61",
    "gn:admin2_code":"54.0",
    "gn:asciiname":"Vileikiai",
    "gn:country_code":"LT",
    "gn:dem":142,
    "gn:feature_class":"P",
    "gn:feature_code":"PPL",
    "gn:name":"Vileikiai",
    "gn:population":0,
    "gn:timezone":"Europe/Vilnius",
    "iso:country":"LT",
    "name:lit_x_preferred":[
        "Vileikiai"
    ],
    "wof:name":"Vileikiai",
    "wof:placetype":"locality"
},
  "geometry": {"coordinates":[22.75472,55.55594],"type":"Point"}
}