{
  "type": "Feature",
  "properties": {
    "gn:admin1_code":"57.0",
    "gn:admin2_code":"69.0",
    "gn:asciiname":"Klebiskis",
    "gn:country_code":"LT",
    "gn:dem":107,
    "gn:feature_class":"P",
    "gn:feature_code":"PPL",
    "gn:name":"Klebi\u0161kis",
    "gn:population":0,
    "gn:timezone":"Europe/Vilnius",
    "iso:country":"LT",
    "name:und_x_variant":[
        "Klebishkis",
        "Klebi\u0161kio",
        "Klebi\u0161kis"
    ],
    "wof:name":"Klebiskis",
    "wof:placetype":"locality"
},
  "geometry": {"coordinates":[23.84035,54.66894],"type":"Point"}
}