{
  "type": "Feature",
  "properties": {
    "gn:admin1_code":"62.0",
    "gn:admin2_code":"77.0",
    "gn:asciiname":"Gilandvirsiai",
    "gn:country_code":"LT",
    "gn:dem":59,
    "gn:feature_class":"P",
    "gn:feature_code":"PPL",
    "gn:name":"Gilandvir\u0161iai",
    "gn:population":0,
    "gn:timezone":"Europe/Vilnius",
    "iso:country":"LT",
    "name:und_x_variant":[
        "Gillandvirzhen",
        "Gilandvir\u0161iai"
    ],
    "wof:name":"Gilandvirsiai",
    "wof:placetype":"locality"
},
  "geometry": {"coordinates":[22.07957,55.1629],"type":"Point"}
}