{
  "type": "Feature",
  "properties": {
    "gn:admin1_code":"61",
    "gn:admin2_code":"54.0",
    "gn:asciiname":"Kadagynas",
    "gn:country_code":"LT",
    "gn:dem":119,
    "gn:feature_class":"P",
    "gn:feature_code":"PPL",
    "gn:name":"Kadagynas",
    "gn:population":0,
    "gn:timezone":"Europe/Vilnius",
    "iso:country":"LT",
    "name:lit_x_preferred":[
        "Kadagynas"
    ],
    "wof:name":"Kadagynas",
    "wof:placetype":"locality"
},
  "geometry": {"coordinates":[22.71027,55.86159],"type":"Point"}
}