{
  "type": "Feature",
  "properties": {
    "gn:admin1_code":"64",
    "gn:admin2_code":"34.0",
    "gn:asciiname":"Juodzgalys",
    "gn:country_code":"LT",
    "gn:dem":110,
    "gn:feature_class":"P",
    "gn:feature_code":"PPL",
    "gn:name":"Juod\u017egalys",
    "gn:population":0,
    "gn:timezone":"Europe/Vilnius",
    "iso:country":"LT",
    "name:lit_x_preferred":[
        "Juod\u017egalys"
    ],
    "wof:name":"Juodzgalys",
    "wof:placetype":"locality"
},
  "geometry": {"coordinates":[24.99024,55.63591],"type":"Point"}
}