{
  "type": "Feature",
  "properties": {
    "gn:admin1_code":"56.0",
    "gn:admin2_code":"59.0",
    "gn:asciiname":"Teizininkai",
    "gn:country_code":"LT",
    "gn:dem":151,
    "gn:feature_class":"P",
    "gn:feature_code":"PPL",
    "gn:name":"Teizininkai",
    "gn:population":0,
    "gn:timezone":"Europe/Vilnius",
    "iso:country":"LT",
    "name:lit_x_preferred":[
        "Teizininkai"
    ],
    "wof:name":"Teizininkai",
    "wof:placetype":"locality"
},
  "geometry": {"coordinates":[23.62737000000001,54.29321],"type":"Point"}
}