{
  "type": "Feature",
  "properties": {
    "gn:admin1_code":"59.0",
    "gn:admin2_code":"39.0",
    "gn:asciiname":"Reciunai",
    "gn:country_code":"LT",
    "gn:dem":195,
    "gn:feature_class":"P",
    "gn:feature_code":"PPL",
    "gn:name":"R\u0117\u010di\u016bnai",
    "gn:population":0,
    "gn:timezone":"Europe/Vilnius",
    "iso:country":"LT",
    "name:und_x_variant":[
        "Rzhechuny",
        "Re\u010dioni\u0173",
        "Rechunay",
        "Re\u010di\u016bn\u0173",
        "R\u0117\u010di\u016bnai"
    ],
    "wof:name":"Reciunai",
    "wof:placetype":"locality"
},
  "geometry": {"coordinates":[22.71627,54.48813000000001],"type":"Point"}
}