{
  "type": "Feature",
  "properties": {
    "gn:admin1_code":"64",
    "gn:admin2_code":"62.0",
    "gn:asciiname":"Janonys",
    "gn:country_code":"LT",
    "gn:dem":122,
    "gn:feature_class":"P",
    "gn:feature_code":"PPL",
    "gn:name":"Janonys",
    "gn:population":0,
    "gn:timezone":"Europe/Vilnius",
    "iso:country":"LT",
    "name:lit_x_preferred":[
        "Janonys"
    ],
    "wof:name":"Janonys",
    "wof:placetype":"locality"
},
  "geometry": {"coordinates":[25.20291,55.38618],"type":"Point"}
}