{
  "type": "Feature",
  "properties": {
    "gn:admin1_code":"60.0",
    "gn:admin2_code":"67.0",
    "gn:asciiname":"Skilinpamusis",
    "gn:country_code":"LT",
    "gn:dem":27,
    "gn:feature_class":"P",
    "gn:feature_code":"PPL",
    "gn:name":"\u0160kilinpam\u016b\u0161is",
    "gn:population":0,
    "gn:timezone":"Europe/Vilnius",
    "iso:country":"LT",
    "name:lit_x_preferred":[
        "\u0160kilinpam\u016b\u0161is"
    ],
    "name:und_x_variant":[
        "\u0160kilnpamusis",
        "Shkilinpamushis",
        "\u0160kilinpamu\u0161is"
    ],
    "wof:name":"Skilinpamusis",
    "wof:placetype":"locality"
},
  "geometry": {"coordinates":[24.36639,56.26667],"type":"Point"}
}