{
  "type": "Feature",
  "properties": {
    "gn:admin1_code":"63.0",
    "gn:admin2_code":"61.0",
    "gn:asciiname":"Purvenai",
    "gn:country_code":"LT",
    "gn:dem":80,
    "gn:feature_class":"P",
    "gn:feature_code":"PPL",
    "gn:name":"Purv\u0117nai",
    "gn:population":0,
    "gn:timezone":"Europe/Vilnius",
    "iso:country":"LT",
    "name:und_x_variant":[
        "Sovai\u010diai",
        "Purv\u0117n\u0173",
        "Purv\u0117niai",
        "Purvenay",
        "Purv\u0117nai"
    ],
    "wof:name":"Purvenai",
    "wof:placetype":"locality"
},
  "geometry": {"coordinates":[22.53425,56.3128],"type":"Point"}
}