{
  "type": "Feature",
  "properties": {
    "gn:admin1_code":"65.0",
    "gn:admin2_code":"81.0",
    "gn:asciiname":"Varzgaliai",
    "gn:country_code":"LT",
    "gn:dem":79,
    "gn:feature_class":"P",
    "gn:feature_code":"PPL",
    "gn:name":"Var\u017egaliai",
    "gn:population":0,
    "gn:timezone":"Europe/Vilnius",
    "iso:country":"LT",
    "name:und_x_variant":[
        "Vorzhogoli",
        "Var\u017egaliai"
    ],
    "wof:name":"Varzgaliai",
    "wof:placetype":"locality"
},
  "geometry": {"coordinates":[24.71811,55.31826],"type":"Point"}
}