{
  "type": "Feature",
  "properties": {
    "gn:admin1_code":"65",
    "gn:admin2_code":"42.0",
    "gn:asciiname":"Senoji Buda",
    "gn:country_code":"LT",
    "gn:dem":201,
    "gn:feature_class":"P",
    "gn:feature_code":"PPL",
    "gn:name":"Senoji B\u016bda",
    "gn:population":0,
    "gn:timezone":"Europe/Vilnius",
    "iso:country":"LT",
    "name:lit_x_preferred":[
        "Senoji B\u016bda"
    ],
    "wof:name":"Senoji Buda",
    "wof:placetype":"locality"
},
  "geometry": {"coordinates":[24.74906,54.69325],"type":"Point"}
}