{
  "type": "Feature",
  "properties": {
    "gn:admin1_code":"57",
    "gn:admin2_code":"72.0",
    "gn:asciiname":"Ancakiai",
    "gn:country_code":"LT",
    "gn:dem":95,
    "gn:feature_class":"P",
    "gn:feature_code":"PPL",
    "gn:name":"An\u010dakiai",
    "gn:population":0,
    "gn:timezone":"Europe/Vilnius",
    "iso:country":"LT",
    "name:lit_x_preferred":[
        "An\u010dakiai"
    ],
    "wof:name":"Ancakiai",
    "wof:placetype":"locality"
},
  "geometry": {"coordinates":[23.10198,55.39555],"type":"Point"}
}