{
  "type": "Feature",
  "properties": {
    "gn:admin1_code":"0.0",
    "gn:asciiname":"Aleksandriske",
    "gn:cc2":"LT",
    "gn:country_code":"LT",
    "gn:dem":80,
    "gn:feature_class":"P",
    "gn:feature_code":"PPL",
    "gn:name":"Aleksandri\u0161k\u0117",
    "gn:population":0,
    "gn:timezone":"Europe/Vilnius",
    "iso:country":"LT",
    "name:und_x_variant":[
        "Aleksandrova",
        "Aleksandri\u0161k\u0117"
    ],
    "wof:name":"Aleksandriske",
    "wof:placetype":"locality"
},
  "geometry": {"coordinates":[21.63333,55.91667],"type":"Point"}
}