{
  "type": "Feature",
  "properties": {
    "gn:admin1_code":"59",
    "gn:admin2_code":"18.0",
    "gn:asciiname":"Bauboniskiai",
    "gn:country_code":"LT",
    "gn:dem":96,
    "gn:feature_class":"P",
    "gn:feature_code":"PPL",
    "gn:name":"Bauboni\u0161kiai",
    "gn:population":0,
    "gn:timezone":"Europe/Vilnius",
    "iso:country":"LT",
    "name:lit_x_preferred":[
        "Bauboni\u0161kiai"
    ],
    "wof:name":"Bauboniskiai",
    "wof:placetype":"locality"
},
  "geometry": {"coordinates":[23.6926,54.5066],"type":"Point"}
}