{
  "type": "Feature",
  "properties": {
    "gn:admin1_code":"56",
    "gn:admin2_code":"15.0",
    "gn:asciiname":"Kermusija",
    "gn:country_code":"LT",
    "gn:dem":114,
    "gn:feature_class":"P",
    "gn:feature_code":"PPL",
    "gn:name":"Kermu\u0161ija",
    "gn:population":0,
    "gn:timezone":"Europe/Vilnius",
    "iso:country":"LT",
    "name:lit_x_preferred":[
        "Kermu\u0161ija"
    ],
    "wof:name":"Kermusija",
    "wof:placetype":"locality"
},
  "geometry": {"coordinates":[24.10205,53.99671],"type":"Point"}
}