{
  "type": "Feature",
  "properties": {
    "gn:admin1_code":"62.0",
    "gn:admin2_code":"77.0",
    "gn:asciiname":"Akstinai",
    "gn:country_code":"LT",
    "gn:dem":57,
    "gn:feature_class":"P",
    "gn:feature_code":"PPL",
    "gn:name":"Akstinai",
    "gn:population":0,
    "gn:timezone":"Europe/Vilnius",
    "iso:country":"LT",
    "name:und_x_variant":[
        "Akstynyay",
        "Akstinai"
    ],
    "wof:name":"Akstinai",
    "wof:placetype":"locality"
},
  "geometry": {"coordinates":[22.48969,55.34822],"type":"Point"}
}