{
  "type": "Feature",
  "properties": {
    "gn:admin1_code":"60",
    "gn:admin2_code":"27.0",
    "gn:asciiname":"Naurasiliai",
    "gn:country_code":"LT",
    "gn:dem":58,
    "gn:feature_class":"P",
    "gn:feature_code":"PPL",
    "gn:name":"Naura\u0161iliai",
    "gn:population":0,
    "gn:timezone":"Europe/Vilnius",
    "iso:country":"LT",
    "name:lit_x_preferred":[
        "Naura\u0161iliai"
    ],
    "wof:name":"Naurasiliai",
    "wof:placetype":"locality"
},
  "geometry": {"coordinates":[24.06879,55.84887],"type":"Point"}
}