{
  "type": "Feature",
  "properties": {
    "gn:admin1_code":"64",
    "gn:admin2_code":"45.0",
    "gn:asciiname":"Pleniske",
    "gn:country_code":"LT",
    "gn:dem":186,
    "gn:feature_class":"P",
    "gn:feature_code":"PPL",
    "gn:name":"Pl\u0117ni\u0161k\u0117",
    "gn:population":0,
    "gn:timezone":"Europe/Vilnius",
    "iso:country":"LT",
    "name:lit_x_preferred":[
        "Pl\u0117ni\u0161k\u0117"
    ],
    "wof:name":"Pleniske",
    "wof:placetype":"locality"
},
  "geometry": {"coordinates":[26.34102,55.40176],"type":"Point"}
}