{
  "type": "Feature",
  "properties": {
    "gn:admin1_code":"62.0",
    "gn:admin2_code":"94.0",
    "gn:asciiname":"Dainiai",
    "gn:country_code":"LT",
    "gn:dem":38,
    "gn:feature_class":"P",
    "gn:feature_code":"PPL",
    "gn:name":"Dainiai",
    "gn:population":0,
    "gn:timezone":"Europe/Vilnius",
    "iso:country":"LT",
    "name:und_x_variant":[
        "Daini\u0173",
        "Dainiai",
        "Dainiai Pirmieji",
        "Doini",
        "Dainiai I"
    ],
    "wof:name":"Dainiai",
    "wof:placetype":"locality"
},
  "geometry": {"coordinates":[22.74342,55.09542],"type":"Point"}
}