{
  "type": "Feature",
  "properties": {
    "gn:admin1_code":"65.0",
    "gn:admin2_code":"81.0",
    "gn:asciiname":"Gailiunai",
    "gn:country_code":"LT",
    "gn:dem":143,
    "gn:feature_class":"P",
    "gn:feature_code":"PPL",
    "gn:name":"Gaili\u016bnai",
    "gn:population":0,
    "gn:timezone":"Europe/Vilnius",
    "iso:country":"LT",
    "name:und_x_variant":[
        "Gaylyunay",
        "Gaili\u016bnai"
    ],
    "wof:name":"Gailiunai",
    "wof:placetype":"locality"
},
  "geometry": {"coordinates":[24.79154,55.13399],"type":"Point"}
}