{
  "type": "Feature",
  "properties": {
    "gn:admin1_code":"61.0",
    "gn:admin2_code":"29.0",
    "gn:asciiname":"Berztvos",
    "gn:country_code":"LT",
    "gn:dem":104,
    "gn:feature_class":"P",
    "gn:feature_code":"PPL",
    "gn:name":"Ber\u017etvos",
    "gn:population":0,
    "gn:timezone":"Europe/Vilnius",
    "iso:country":"LT",
    "name:und_x_variant":[
        "Bershtay",
        "Ber\u017etvos"
    ],
    "wof:name":"Berztvos",
    "wof:placetype":"locality"
},
  "geometry": {"coordinates":[22.88511,55.9945],"type":"Point"}
}