{
  "type": "Feature",
  "properties": {
    "gn:admin1_code":"63",
    "gn:admin2_code":"78.0",
    "gn:asciiname":"Kilpiske",
    "gn:country_code":"LT",
    "gn:dem":112,
    "gn:feature_class":"P",
    "gn:feature_code":"PPL",
    "gn:name":"Kilpi\u0161k\u0117",
    "gn:population":0,
    "gn:timezone":"Europe/Vilnius",
    "iso:country":"LT",
    "name:lit_x_preferred":[
        "Kilpi\u0161k\u0117"
    ],
    "wof:name":"Kilpiske",
    "wof:placetype":"locality"
},
  "geometry": {"coordinates":[22.61286,56.0412],"type":"Point"}
}