{
  "type": "Feature",
  "properties": {
    "gn:admin1_code":"65",
    "gn:admin2_code":"89.0",
    "gn:asciiname":"Banisonys",
    "gn:country_code":"LT",
    "gn:dem":116,
    "gn:feature_class":"P",
    "gn:feature_code":"PPL",
    "gn:name":"Bani\u0161onys",
    "gn:population":0,
    "gn:timezone":"Europe/Vilnius",
    "iso:country":"LT",
    "name:lit_x_preferred":[
        "Bani\u0161onys"
    ],
    "wof:name":"Banisonys",
    "wof:placetype":"locality"
},
  "geometry": {"coordinates":[24.87822,55.06495],"type":"Point"}
}