{
  "type": "Feature",
  "properties": {
    "gn:admin1_code":"57",
    "gn:admin2_code":"53.0",
    "gn:asciiname":"Gaisai",
    "gn:country_code":"LT",
    "gn:dem":59,
    "gn:feature_class":"P",
    "gn:feature_code":"PPL",
    "gn:name":"Gaisai",
    "gn:population":0,
    "gn:timezone":"Europe/Vilnius",
    "iso:country":"LT",
    "name:lit_x_preferred":[
        "Gaisai"
    ],
    "wof:name":"Gaisai",
    "wof:placetype":"locality"
},
  "geometry": {"coordinates":[24.22173,55.40685],"type":"Point"}
}