{
  "type": "Feature",
  "properties": {
    "gn:admin1_code":"57.0",
    "gn:admin2_code":"12.0",
    "gn:asciiname":"Kernuves",
    "gn:country_code":"LT",
    "gn:dem":93,
    "gn:feature_class":"P",
    "gn:feature_code":"PPL",
    "gn:name":"Kernuv\u0117s",
    "gn:population":0,
    "gn:timezone":"Europe/Vilnius",
    "iso:country":"LT",
    "name:lit_x_preferred":[
        "Kernuv\u0117s"
    ],
    "wof:name":"Kernuves",
    "wof:placetype":"locality"
},
  "geometry": {"coordinates":[24.02199,54.5857],"type":"Point"}
}