{
  "type": "Feature",
  "properties": {
    "gn:admin1_code":"59",
    "gn:admin2_code":"58.0",
    "gn:asciiname":"Garanksciai",
    "gn:country_code":"LT",
    "gn:dem":66,
    "gn:feature_class":"P",
    "gn:feature_code":"PPL",
    "gn:name":"Garank\u0161\u010diai",
    "gn:population":0,
    "gn:timezone":"Europe/Vilnius",
    "iso:country":"LT",
    "name:lit_x_preferred":[
        "Garank\u0161\u010diai"
    ],
    "wof:name":"Garanksciai",
    "wof:placetype":"locality"
},
  "geometry": {"coordinates":[23.48117,54.8674],"type":"Point"}
}