{
  "type": "Feature",
  "properties": {
    "gn:admin1_code":"59.0",
    "gn:admin2_code":"48.0",
    "gn:asciiname":"Trakenai",
    "gn:country_code":"LT",
    "gn:dem":165,
    "gn:feature_class":"P",
    "gn:feature_code":"PPLL",
    "gn:name":"Trak\u0117nai",
    "gn:population":0,
    "gn:timezone":"Europe/Vilnius",
    "iso:country":"LT",
    "name:lit_x_preferred":[
        "Trak\u0117nai"
    ],
    "wof:name":"Trakenai",
    "wof:placetype":"locality"
},
  "geometry": {"coordinates":[23.18487,54.36163000000001],"type":"Point"}
}