{
  "type": "Feature",
  "properties": {
    "gn:admin1_code":"58.0",
    "gn:admin2_code":"21.0",
    "gn:asciiname":"Zvelsenai",
    "gn:country_code":"LT",
    "gn:dem":16,
    "gn:feature_class":"P",
    "gn:feature_code":"PPL",
    "gn:name":"\u017dvels\u0117nai",
    "gn:population":0,
    "gn:timezone":"Europe/Vilnius",
    "iso:country":"LT",
    "name:und_x_variant":[
        "Zhvel\u2019syany",
        "\u017dvels\u0117nai"
    ],
    "wof:name":"Zvelsenai",
    "wof:placetype":"locality"
},
  "geometry": {"coordinates":[21.43592,55.76396999999999],"type":"Point"}
}