{
  "type": "Feature",
  "properties": {
    "gn:admin1_code":"57.0",
    "gn:admin2_code":"53.0",
    "gn:asciiname":"Azuolaiciai",
    "gn:country_code":"LT",
    "gn:dem":60,
    "gn:feature_class":"P",
    "gn:feature_code":"PPL",
    "gn:name":"\u0104\u017euolai\u010diai",
    "gn:population":0,
    "gn:timezone":"Europe/Vilnius",
    "iso:country":"LT",
    "name:ceb_x_preferred":[
        "\u0104\u017euolai\u010diai"
    ],
    "name:lit_x_preferred":[
        "\u0104\u017euolai\u010diai"
    ],
    "name:swe_x_preferred":[
        "\u0104\u017euolai\u010diai"
    ],
    "name:und_x_variant":[
        "Dubiai"
    ],
    "wof:name":"Azuolaiciai",
    "wof:placetype":"locality"
},
  "geometry": {"coordinates":[23.85428,55.34441],"type":"Point"}
}