{
  "type": "Feature",
  "properties": {
    "gn:admin1_code":"60.0",
    "gn:admin2_code":"36.0",
    "gn:asciiname":"Satkunai",
    "gn:country_code":"LT",
    "gn:dem":70,
    "gn:feature_class":"P",
    "gn:feature_code":"PPL",
    "gn:name":"Satk\u016bnai",
    "gn:population":0,
    "gn:timezone":"Europe/Vilnius",
    "iso:country":"LT",
    "name:eng_x_preferred":[
        "Satk\u016bnai"
    ],
    "name:rus_x_preferred":[
        "\u0421\u0430\u0442\u043a\u0443\u043d\u0430\u0439"
    ],
    "name:und_x_variant":[
        "Satk\u016bn\u0173",
        "Satkunay"
    ],
    "wof:name":"Satkunai",
    "wof:placetype":"locality"
},
  "geometry": {"coordinates":[24.9293,56.0726],"type":"Point"}
}