{
  "type": "Feature",
  "properties": {
    "gn:admin1_code":"59.0",
    "gn:admin2_code":"18.0",
    "gn:asciiname":"Mokolai",
    "gn:country_code":"LT",
    "gn:dem":71,
    "gn:feature_class":"P",
    "gn:feature_code":"PPL",
    "gn:name":"Mokolai",
    "gn:population":0,
    "gn:timezone":"Europe/Vilnius",
    "iso:country":"LT",
    "name:und_x_variant":[
        "Mokol\u0173",
        "Mokolay",
        "Mokaly",
        "Mokolai"
    ],
    "wof:name":"Mokolai",
    "wof:placetype":"locality"
},
  "geometry": {"coordinates":[23.33963,54.5735],"type":"Point"}
}