{
  "type": "Feature",
  "properties": {
    "gn:admin1_code":"63.0",
    "gn:admin2_code":"78.0",
    "gn:asciiname":"Pavandene",
    "gn:country_code":"LT",
    "gn:dem":184,
    "gn:feature_class":"P",
    "gn:feature_code":"PPL",
    "gn:name":"Pavanden\u0117",
    "gn:population":0,
    "gn:timezone":"Europe/Vilnius",
    "iso:country":"LT",
    "name:ceb_x_preferred":[
        "Pavanden\u0117"
    ],
    "name:est_x_preferred":[
        "Pavanden\u0117"
    ],
    "name:lit_x_preferred":[
        "Pavanden\u0117"
    ],
    "name:nld_x_preferred":[
        "Pavanden\u0117"
    ],
    "name:pol_x_preferred":[
        "Powonde\u0144"
    ],
    "name:swe_x_preferred":[
        "Pavanden\u0117"
    ],
    "name:und_x_variant":[
        "Pavandenys",
        "Pavandenio",
        "Pavandenis",
        "Pavanden\u0117"
    ],
    "wof:name":"Pavandene",
    "wof:placetype":"locality"
},
  "geometry": {"coordinates":[22.48406,55.77099000000001],"type":"Point"}
}