{
  "type": "Feature",
  "properties": {
    "gn:admin1_code":"64",
    "gn:admin2_code":"43.0",
    "gn:asciiname":"Bartkiske I",
    "gn:country_code":"LT",
    "gn:dem":141,
    "gn:feature_class":"P",
    "gn:feature_code":"PPL",
    "gn:name":"Bartki\u0161k\u0117 I",
    "gn:population":0,
    "gn:timezone":"Europe/Vilnius",
    "iso:country":"LT",
    "name:lit_x_preferred":[
        "Bartki\u0161k\u0117 I"
    ],
    "wof:name":"Bartkiske I",
    "wof:placetype":"locality"
},
  "geometry": {"coordinates":[26.4534,55.68839000000001],"type":"Point"}
}