{
  "type": "Feature",
  "properties": {
    "gn:admin1_code":"64",
    "gn:admin2_code":"34.0",
    "gn:asciiname":"Maldeikiai",
    "gn:country_code":"LT",
    "gn:dem":97,
    "gn:feature_class":"P",
    "gn:feature_code":"PPL",
    "gn:name":"Maldeikiai",
    "gn:population":0,
    "gn:timezone":"Europe/Vilnius",
    "iso:country":"LT",
    "name:lit_x_preferred":[
        "Maldeikiai"
    ],
    "wof:name":"Maldeikiai",
    "wof:placetype":"locality"
},
  "geometry": {"coordinates":[24.94138,55.65498],"type":"Point"}
}