{
  "type": "Feature",
  "properties": {
    "gn:admin1_code":"60",
    "gn:admin2_code":"73.0",
    "gn:asciiname":"Gumbiskiai",
    "gn:country_code":"LT",
    "gn:dem":127,
    "gn:feature_class":"P",
    "gn:feature_code":"PPL",
    "gn:name":"Gumbi\u0161kiai",
    "gn:population":0,
    "gn:timezone":"Europe/Vilnius",
    "iso:country":"LT",
    "name:lit_x_preferred":[
        "Gumbi\u0161kiai"
    ],
    "wof:name":"Gumbiskiai",
    "wof:placetype":"locality"
},
  "geometry": {"coordinates":[25.81166,55.99462],"type":"Point"}
}