{
  "type": "Feature",
  "properties": {
    "gn:admin1_code":"60.0",
    "gn:admin2_code":"27.0",
    "gn:asciiname":"Dragonys",
    "gn:country_code":"LT",
    "gn:dem":51,
    "gn:feature_class":"P",
    "gn:feature_code":"PPL",
    "gn:name":"Dragonys",
    "gn:population":0,
    "gn:timezone":"Europe/Vilnius",
    "iso:country":"LT",
    "name:und_x_variant":[
        "Draganay",
        "Dragonys"
    ],
    "wof:name":"Dragonys",
    "wof:placetype":"locality"
},
  "geometry": {"coordinates":[24.18363,55.83268],"type":"Point"}
}