{
  "type": "Feature",
  "properties": {
    "gn:admin1_code":"62.0",
    "gn:admin2_code":"87.0",
    "gn:asciiname":"Kadzyga",
    "gn:country_code":"LT",
    "gn:dem":117,
    "gn:feature_class":"P",
    "gn:feature_code":"PPL",
    "gn:name":"Kad\u017eyga",
    "gn:population":0,
    "gn:timezone":"Europe/Vilnius",
    "iso:country":"LT",
    "name:und_x_variant":[
        "Kadzhigyay",
        "Kad\u017eyga"
    ],
    "wof:name":"Kadzyga",
    "wof:placetype":"locality"
},
  "geometry": {"coordinates":[22.14085,55.53161],"type":"Point"}
}