{
  "type": "Feature",
  "properties": {
    "gn:admin1_code":"60",
    "gn:admin2_code":"57.0",
    "gn:asciiname":"Iciunai",
    "gn:country_code":"LT",
    "gn:dem":82,
    "gn:feature_class":"P",
    "gn:feature_code":"PPL",
    "gn:name":"Ici\u016bnai",
    "gn:population":0,
    "gn:timezone":"Europe/Vilnius",
    "iso:country":"LT",
    "name:lit_x_preferred":[
        "Ici\u016bnai"
    ],
    "wof:name":"Iciunai",
    "wof:placetype":"locality"
},
  "geometry": {"coordinates":[25.01151,55.89723000000001],"type":"Point"}
}