{
  "type": "Feature",
  "properties": {
    "gn:admin1_code":"57",
    "gn:admin2_code":"72.0",
    "gn:asciiname":"Kriauksle",
    "gn:country_code":"LT",
    "gn:dem":64,
    "gn:feature_class":"P",
    "gn:feature_code":"PPL",
    "gn:name":"Kriauk\u0161l\u0117",
    "gn:population":0,
    "gn:timezone":"Europe/Vilnius",
    "iso:country":"LT",
    "name:lit_x_preferred":[
        "Kriauk\u0161l\u0117"
    ],
    "wof:name":"Kriauksle",
    "wof:placetype":"locality"
},
  "geometry": {"coordinates":[22.87758,55.3628],"type":"Point"}
}