{
  "type": "Feature",
  "properties": {
    "gn:admin1_code":"65",
    "gn:admin2_code":"85.0",
    "gn:asciiname":"Liudviniskes",
    "gn:country_code":"LT",
    "gn:dem":178,
    "gn:feature_class":"P",
    "gn:feature_code":"PPL",
    "gn:name":"Liudvini\u0161k\u0117s",
    "gn:population":0,
    "gn:timezone":"Europe/Vilnius",
    "iso:country":"LT",
    "name:lit_x_preferred":[
        "Liudvini\u0161k\u0117s"
    ],
    "wof:name":"Liudviniskes",
    "wof:placetype":"locality"
},
  "geometry": {"coordinates":[25.39441,54.44916],"type":"Point"}
}