{
  "type": "Feature",
  "properties": {
    "gn:admin1_code":"63.0",
    "gn:admin2_code":"68.0",
    "gn:asciiname":"Kaspariske",
    "gn:country_code":"LT",
    "gn:dem":121,
    "gn:feature_class":"P",
    "gn:feature_code":"PPL",
    "gn:name":"Kaspari\u0161k\u0117",
    "gn:population":0,
    "gn:timezone":"Europe/Vilnius",
    "iso:country":"LT",
    "name:lit_x_preferred":[
        "Kaspari\u0161k\u0117"
    ],
    "wof:name":"Kaspariske",
    "wof:placetype":"locality"
},
  "geometry": {"coordinates":[21.90075,55.91629],"type":"Point"}
}