{
  "type": "Feature",
  "properties": {
    "gn:admin1_code":"57",
    "gn:admin2_code":"53.0",
    "gn:asciiname":"Dvarcininkai",
    "gn:country_code":"LT",
    "gn:dem":46,
    "gn:feature_class":"P",
    "gn:feature_code":"PPL",
    "gn:name":"Dvar\u010dininkai",
    "gn:population":0,
    "gn:timezone":"Europe/Vilnius",
    "iso:country":"LT",
    "name:lit_x_preferred":[
        "Dvar\u010dininkai"
    ],
    "wof:name":"Dvarcininkai",
    "wof:placetype":"locality"
},
  "geometry": {"coordinates":[24.04981,55.29552],"type":"Point"}
}