{
  "type": "Feature",
  "properties": {
    "gn:admin1_code":"65.0",
    "gn:admin2_code":"81.0",
    "gn:asciiname":"Sargeliai",
    "gn:country_code":"LT",
    "gn:dem":109,
    "gn:feature_class":"P",
    "gn:feature_code":"PPL",
    "gn:name":"Sargeliai",
    "gn:population":0,
    "gn:timezone":"Europe/Vilnius",
    "iso:country":"LT",
    "name:und_x_variant":[
        "Sargelyay",
        "Sargeliai"
    ],
    "wof:name":"Sargeliai",
    "wof:placetype":"locality"
},
  "geometry": {"coordinates":[24.74341,55.19155],"type":"Point"}
}