{
  "type": "Feature",
  "properties": {
    "gn:admin1_code":"64",
    "gn:admin2_code":"43.0",
    "gn:asciiname":"Turaucizna",
    "gn:country_code":"LT",
    "gn:dem":147,
    "gn:feature_class":"P",
    "gn:feature_code":"PPL",
    "gn:name":"Turau\u010dizna",
    "gn:population":0,
    "gn:timezone":"Europe/Vilnius",
    "iso:country":"LT",
    "name:lit_x_preferred":[
        "Turau\u010dizna"
    ],
    "wof:name":"Turaucizna",
    "wof:placetype":"locality"
},
  "geometry": {"coordinates":[26.39707000000001,55.66365],"type":"Point"}
}