{
  "type": "Feature",
  "properties": {
    "gn:admin1_code":"0.0",
    "gn:asciiname":"Betegala",
    "gn:country_code":"LT",
    "gn:dem":33,
    "gn:feature_class":"P",
    "gn:feature_code":"PPL",
    "gn:name":"Bet\u0117gala",
    "gn:population":0,
    "gn:timezone":"Europe/Vilnius",
    "iso:country":"LT",
    "wof:name":"Betegala",
    "wof:placetype":"locality"
},
  "geometry": {"coordinates":[24.13333,55.05],"type":"Point"}
}