{
  "type": "Feature",
  "properties": {
    "iso:country":"LT",
    "name:deu_x_preferred":[
        "Antaviliai"
    ],
    "name:lit_x_preferred":[
        "Antaviliai"
    ],
    "wof:name":"Antaviliai",
    "wof:placetype":"neighbourhood"
},
  "geometry": {"coordinates":[25.39937068333413,54.79806885608251],"type":"Point"}
}