{
  "type": "Feature",
  "properties": {
    "gn:admin1_code":"65",
    "gn:admin2_code":"13.0",
    "gn:asciiname":"Naujadvaris",
    "gn:country_code":"LT",
    "gn:dem":196,
    "gn:feature_class":"P",
    "gn:feature_code":"PPL",
    "gn:name":"Naujadvaris",
    "gn:population":0,
    "gn:timezone":"Europe/Vilnius",
    "iso:country":"LT",
    "name:lit_x_preferred":[
        "Naujadvaris"
    ],
    "wof:name":"Naujadvaris",
    "wof:placetype":"locality"
},
  "geometry": {"coordinates":[25.53871,54.47051],"type":"Point"}
}