{
  "type": "Feature",
  "properties": {
    "gn:admin1_code":"64",
    "gn:admin2_code":"43.0",
    "gn:asciiname":"Voversiai",
    "gn:country_code":"LT",
    "gn:dem":156,
    "gn:feature_class":"P",
    "gn:feature_code":"PPL",
    "gn:name":"Voversiai",
    "gn:population":0,
    "gn:timezone":"Europe/Vilnius",
    "iso:country":"LT",
    "name:lit_x_preferred":[
        "Voversiai"
    ],
    "wof:name":"Voversiai",
    "wof:placetype":"locality"
},
  "geometry": {"coordinates":[25.88947000000001,55.73942],"type":"Point"}
}