{
  "type": "Feature",
  "properties": {
    "gn:admin1_code":"57",
    "gn:admin2_code":"19.0",
    "gn:asciiname":"Tumpai",
    "gn:country_code":"LT",
    "gn:dem":84,
    "gn:feature_class":"P",
    "gn:feature_code":"PPL",
    "gn:name":"Tumpai",
    "gn:population":0,
    "gn:timezone":"Europe/Vilnius",
    "iso:country":"LT",
    "name:lit_x_preferred":[
        "Tumpai"
    ],
    "wof:name":"Tumpai",
    "wof:placetype":"locality"
},
  "geometry": {"coordinates":[23.73267,54.82965],"type":"Point"}
}