{
  "type": "Feature",
  "properties": {
    "gn:admin1_code":"64",
    "gn:admin2_code":"45.0",
    "gn:asciiname":"Darzeliai",
    "gn:country_code":"LT",
    "gn:dem":166,
    "gn:feature_class":"P",
    "gn:feature_code":"PPL",
    "gn:name":"Dar\u017eeliai",
    "gn:population":0,
    "gn:timezone":"Europe/Vilnius",
    "iso:country":"LT",
    "name:lit_x_preferred":[
        "Dar\u017eeliai"
    ],
    "wof:name":"Darzeliai",
    "wof:placetype":"locality"
},
  "geometry": {"coordinates":[25.97629,55.33642],"type":"Point"}
}