{
  "type": "Feature",
  "properties": {
    "gn:asciiname":"Mardosu",
    "gn:country_code":"LT",
    "gn:dem":79,
    "gn:feature_class":"P",
    "gn:feature_code":"PPL",
    "gn:name":"Mardosu",
    "gn:population":0,
    "gn:timezone":"Europe/Vilnius",
    "iso:country":"LT",
    "wof:name":"Mardosu",
    "wof:placetype":"locality"
},
  "geometry": {"coordinates":[21.76083,55.88016999999999],"type":"Point"}
}