{
  "type": "Feature",
  "properties": {
    "gn:admin1_code":"64.0",
    "gn:admin2_code":"34.0",
    "gn:asciiname":"Vidugiriai",
    "gn:country_code":"LT",
    "gn:dem":93,
    "gn:feature_class":"P",
    "gn:feature_code":"PPL",
    "gn:name":"Vidugiriai",
    "gn:population":0,
    "gn:timezone":"Europe/Vilnius",
    "iso:country":"LT",
    "name:und_x_variant":[
        "Vidugirtsy",
        "Vidugirtsay",
        "Vidugiriai"
    ],
    "wof:name":"Vidugiriai",
    "wof:placetype":"locality"
},
  "geometry": {"coordinates":[24.91353,55.64934],"type":"Point"}
}