{
  "type": "Feature",
  "properties": {
    "gn:admin1_code":"60",
    "gn:admin2_code":"36.0",
    "gn:asciiname":"Smilgiskis",
    "gn:country_code":"LT",
    "gn:dem":61,
    "gn:feature_class":"P",
    "gn:feature_code":"PPL",
    "gn:name":"Smilgi\u0161kis",
    "gn:population":0,
    "gn:timezone":"Europe/Vilnius",
    "iso:country":"LT",
    "name:lit_x_preferred":[
        "Smilgi\u0161kis"
    ],
    "wof:name":"Smilgiskis",
    "wof:placetype":"locality"
},
  "geometry": {"coordinates":[24.78795,55.99569],"type":"Point"}
}