{
  "type": "Feature",
  "properties": {
    "gn:admin1_code":"61.0",
    "gn:asciiname":"Gailioniai",
    "gn:country_code":"LT",
    "gn:dem":49,
    "gn:feature_class":"P",
    "gn:feature_code":"PPL",
    "gn:name":"Gailioniai",
    "gn:population":0,
    "gn:timezone":"Europe/Vilnius",
    "iso:country":"LT",
    "name:und_x_variant":[
        "Gailioni\u0173",
        "Gayl\u00ebnyay",
        "Gaylionyay",
        "Gailioniai"
    ],
    "wof:name":"Gailioniai",
    "wof:placetype":"locality"
},
  "geometry": {"coordinates":[24.07529,56.05826],"type":"Point"}
}