{
  "type": "Feature",
  "properties": {
    "gn:admin1_code":"0.0",
    "gn:asciiname":"Berzvaitis",
    "gn:cc2":"LT",
    "gn:country_code":"LT",
    "gn:dem":120,
    "gn:feature_class":"P",
    "gn:feature_code":"PPL",
    "gn:name":"Ber\u017evaitis",
    "gn:population":0,
    "gn:timezone":"Europe/Vilnius",
    "iso:country":"LT",
    "name:und_x_variant":[
        "Berzhvaychyay",
        "Ber\u017evaitis"
    ],
    "wof:name":"Berzvaitis",
    "wof:placetype":"locality"
},
  "geometry": {"coordinates":[22.05,55.73333],"type":"Point"}
}