{
  "type": "Feature",
  "properties": {
    "gn:admin1_code":"62",
    "gn:admin2_code":"77.0",
    "gn:asciiname":"Dagiai",
    "gn:country_code":"LT",
    "gn:dem":33,
    "gn:feature_class":"P",
    "gn:feature_code":"PPL",
    "gn:name":"Dagiai",
    "gn:population":0,
    "gn:timezone":"Europe/Vilnius",
    "iso:country":"LT",
    "name:lit_x_preferred":[
        "Dagiai"
    ],
    "wof:name":"Dagiai",
    "wof:placetype":"locality"
},
  "geometry": {"coordinates":[22.20941,55.23921],"type":"Point"}
}