{
  "type": "Feature",
  "properties": {
    "gn:admin1_code":"59",
    "gn:admin2_code":"18.0",
    "gn:asciiname":"Pabukte",
    "gn:country_code":"LT",
    "gn:dem":109,
    "gn:feature_class":"P",
    "gn:feature_code":"PPL",
    "gn:name":"Pabukt\u0117",
    "gn:population":0,
    "gn:timezone":"Europe/Vilnius",
    "iso:country":"LT",
    "name:lit_x_preferred":[
        "Pabukt\u0117"
    ],
    "wof:name":"Pabukte",
    "wof:placetype":"locality"
},
  "geometry": {"coordinates":[23.39635,54.44135],"type":"Point"}
}