{
  "type": "Feature",
  "properties": {
    "gn:admin1_code":"65.0",
    "gn:admin2_code":"81.0",
    "gn:asciiname":"Jakutiskiai",
    "gn:country_code":"LT",
    "gn:dem":89,
    "gn:feature_class":"P",
    "gn:feature_code":"PPL",
    "gn:name":"Jakuti\u0161kiai",
    "gn:population":0,
    "gn:timezone":"Europe/Vilnius",
    "iso:country":"LT",
    "name:und_x_variant":[
        "Yakutishkyay",
        "Jakuti\u0161kiai"
    ],
    "wof:name":"Jakutiskiai",
    "wof:placetype":"locality"
},
  "geometry": {"coordinates":[24.58317000000001,55.22419],"type":"Point"}
}