{
  "type": "Feature",
  "properties": {
    "gn:admin1_code":"56",
    "gn:admin2_code":"11.0",
    "gn:asciiname":"Tamasava",
    "gn:country_code":"LT",
    "gn:dem":140,
    "gn:feature_class":"P",
    "gn:feature_code":"PPL",
    "gn:name":"Tama\u0161ava",
    "gn:population":0,
    "gn:timezone":"Europe/Vilnius",
    "iso:country":"LT",
    "name:lit_x_preferred":[
        "Tama\u0161ava"
    ],
    "wof:name":"Tamasava",
    "wof:placetype":"locality"
},
  "geometry": {"coordinates":[24.30521,54.40231],"type":"Point"}
}