{
  "type": "Feature",
  "properties": {
    "gn:admin1_code":"57.0",
    "gn:admin2_code":"72.0",
    "gn:asciiname":"Siauleliai",
    "gn:country_code":"LT",
    "gn:dem":126,
    "gn:feature_class":"P",
    "gn:feature_code":"PPL",
    "gn:name":"\u0160iauleliai",
    "gn:population":0,
    "gn:timezone":"Europe/Vilnius",
    "iso:country":"LT",
    "name:und_x_variant":[
        "Shaulelyay",
        "Shavleli",
        "\u0160iauleliai"
    ],
    "wof:name":"Siauleliai",
    "wof:placetype":"locality"
},
  "geometry": {"coordinates":[23.20455,55.50814],"type":"Point"}
}