{
  "type": "Feature",
  "properties": {
    "gn:admin1_code":"61",
    "gn:admin2_code":"54.0",
    "gn:asciiname":"Seskupis",
    "gn:country_code":"LT",
    "gn:dem":131,
    "gn:feature_class":"P",
    "gn:feature_code":"PPL",
    "gn:name":"\u0160e\u0161kupis",
    "gn:population":0,
    "gn:timezone":"Europe/Vilnius",
    "iso:country":"LT",
    "name:lit_x_preferred":[
        "\u0160e\u0161kupis"
    ],
    "wof:name":"Seskupis",
    "wof:placetype":"locality"
},
  "geometry": {"coordinates":[22.81675,55.79747],"type":"Point"}
}