{
  "type": "Feature",
  "properties": {
    "gn:admin1_code":"60.0",
    "gn:admin2_code":"27.0",
    "gn:asciiname":"Daniunai",
    "gn:country_code":"LT",
    "gn:dem":71,
    "gn:feature_class":"P",
    "gn:feature_code":"PPL",
    "gn:name":"Dani\u016bnai",
    "gn:population":0,
    "gn:timezone":"Europe/Vilnius",
    "iso:country":"LT",
    "name:lit_x_preferred":[
        "Dani\u016bnai"
    ],
    "name:und_x_variant":[
        "Danj\u016bnai"
    ],
    "wof:name":"Daniunai",
    "wof:placetype":"locality"
},
  "geometry": {"coordinates":[24.37998,55.46381],"type":"Point"}
}