{
  "type": "Feature",
  "properties": {
    "gn:admin1_code":"60",
    "gn:admin2_code":"73.0",
    "gn:asciiname":"Audronys II",
    "gn:country_code":"LT",
    "gn:dem":123,
    "gn:feature_class":"P",
    "gn:feature_code":"PPL",
    "gn:name":"Audronys II",
    "gn:population":0,
    "gn:timezone":"Europe/Vilnius",
    "iso:country":"LT",
    "name:lit_x_preferred":[
        "Audronys II"
    ],
    "wof:name":"Audronys II",
    "wof:placetype":"locality"
},
  "geometry": {"coordinates":[25.82084,55.96167],"type":"Point"}
}