{
  "type": "Feature",
  "properties": {
    "gn:admin1_code":"57",
    "gn:admin2_code":"49.0",
    "gn:asciiname":"Aleksiejuniskes",
    "gn:country_code":"LT",
    "gn:dem":140,
    "gn:feature_class":"P",
    "gn:feature_code":"PPL",
    "gn:name":"Aleksiej\u016bni\u0161k\u0117s",
    "gn:population":0,
    "gn:timezone":"Europe/Vilnius",
    "iso:country":"LT",
    "name:lit_x_preferred":[
        "Aleksiej\u016bni\u0161k\u0117s"
    ],
    "wof:name":"Aleksiejuniskes",
    "wof:placetype":"locality"
},
  "geometry": {"coordinates":[24.47226,54.7565],"type":"Point"}
}