{
  "type": "Feature",
  "properties": {
    "gn:admin1_code":"65",
    "gn:admin2_code":"86.0",
    "gn:asciiname":"Kaceniske",
    "gn:country_code":"LT",
    "gn:dem":174,
    "gn:feature_class":"P",
    "gn:feature_code":"PPL",
    "gn:name":"Ka\u010d\u0117ni\u0161k\u0117",
    "gn:population":0,
    "gn:timezone":"Europe/Vilnius",
    "iso:country":"LT",
    "name:lit_x_preferred":[
        "Ka\u010d\u0117ni\u0161k\u0117"
    ],
    "wof:name":"Kaceniske",
    "wof:placetype":"locality"
},
  "geometry": {"coordinates":[26.24053,55.22416],"type":"Point"}
}