{
  "type": "Feature",
  "properties": {
    "gn:admin1_code":"62.0",
    "gn:admin2_code":"87.0",
    "gn:asciiname":"Grazjuris",
    "gn:country_code":"LT",
    "gn:dem":99,
    "gn:feature_class":"P",
    "gn:feature_code":"PPL",
    "gn:name":"Gra\u017ej\u016bris",
    "gn:population":0,
    "gn:timezone":"Europe/Vilnius",
    "iso:country":"LT",
    "name:eng_x_preferred":[
        "Paj\u016br\u0117"
    ],
    "name:rus_x_preferred":[
        "\u041f\u0430\u044e\u0440\u0430\u043b\u0438\u0441"
    ],
    "name:und_x_variant":[
        "Gra\u017ej\u016bris",
        "Paj\u016br\u0117"
    ],
    "wof:name":"Grazjuris",
    "wof:placetype":"locality"
},
  "geometry": {"coordinates":[21.97685,55.55108000000001],"type":"Point"}
}