{
  "type": "Feature",
  "properties": {
    "gn:admin1_code":"57",
    "gn:admin2_code":"69.0",
    "gn:asciiname":"Mieleiskampis",
    "gn:country_code":"LT",
    "gn:dem":118,
    "gn:feature_class":"P",
    "gn:feature_code":"PPL",
    "gn:name":"Mielei\u0161kampis",
    "gn:population":0,
    "gn:timezone":"Europe/Vilnius",
    "iso:country":"LT",
    "name:lit_x_preferred":[
        "Mielei\u0161kampis"
    ],
    "wof:name":"Mieleiskampis",
    "wof:placetype":"locality"
},
  "geometry": {"coordinates":[23.77082,54.62954000000001],"type":"Point"}
}