{
  "type": "Feature",
  "properties": {
    "gn:admin1_code":"64.0",
    "gn:admin2_code":"43.0",
    "gn:asciiname":"Deguciai",
    "gn:country_code":"LT",
    "gn:dem":170,
    "gn:feature_class":"P",
    "gn:feature_code":"PPL",
    "gn:name":"Degu\u010diai",
    "gn:population":0,
    "gn:timezone":"Europe/Vilnius",
    "iso:country":"LT",
    "name:und_x_variant":[
        "Deguchyay",
        "Degu\u010di\u0173",
        "Degu\u010diai"
    ],
    "wof:name":"Deguciai",
    "wof:placetype":"locality"
},
  "geometry": {"coordinates":[26.05918,55.65883],"type":"Point"}
}