{
  "type": "Feature",
  "properties": {
    "gn:admin1_code":"58.0",
    "gn:admin2_code":"21.0",
    "gn:asciiname":"Girininkai",
    "gn:country_code":"LT",
    "gn:dem":64,
    "gn:feature_class":"P",
    "gn:feature_code":"PPL",
    "gn:name":"Girininkai",
    "gn:population":0,
    "gn:timezone":"Europe/Vilnius",
    "iso:country":"LT",
    "name:und_x_variant":[
        "Girinink\u0173",
        "Girininkay",
        "Girininkai"
    ],
    "wof:name":"Girininkai",
    "wof:placetype":"locality"
},
  "geometry": {"coordinates":[21.51209,55.68165],"type":"Point"}
}