{
  "type": "Feature",
  "properties": {
    "gn:admin1_code":"57.0",
    "gn:admin2_code":"19.0",
    "gn:asciiname":"Pociunai",
    "gn:country_code":"LT",
    "gn:dem":48,
    "gn:feature_class":"P",
    "gn:feature_code":"PPL",
    "gn:name":"Poci\u016bnai",
    "gn:population":0,
    "gn:timezone":"Europe/Vilnius",
    "iso:country":"LT",
    "name:lit_x_preferred":[
        "Poci\u016bnai"
    ],
    "name:und_x_variant":[
        "Pachunay",
        "Patsuny",
        "Poci\u016bnai-Pagyn\u0117s"
    ],
    "wof:name":"Pociunai",
    "wof:placetype":"locality"
},
  "geometry": {"coordinates":[23.87924,55.10666],"type":"Point"}
}