{
  "type": "Feature",
  "properties": {
    "gn:admin1_code":"65",
    "gn:admin2_code":"89.0",
    "gn:asciiname":"Kryziauka II",
    "gn:country_code":"LT",
    "gn:dem":122,
    "gn:feature_class":"P",
    "gn:feature_code":"PPL",
    "gn:name":"Kry\u017eiauka II",
    "gn:population":0,
    "gn:timezone":"Europe/Vilnius",
    "iso:country":"LT",
    "name:lit_x_preferred":[
        "Kry\u017eiauka II"
    ],
    "wof:name":"Kryziauka II",
    "wof:placetype":"locality"
},
  "geometry": {"coordinates":[24.87046,54.91426],"type":"Point"}
}