{
  "type": "Feature",
  "properties": {
    "gn:admin1_code":"62.0",
    "gn:admin2_code":"77.0",
    "gn:asciiname":"Antegluonis",
    "gn:country_code":"LT",
    "gn:dem":48,
    "gn:feature_class":"P",
    "gn:feature_code":"PPL",
    "gn:name":"Antegluonis",
    "gn:population":0,
    "gn:timezone":"Europe/Vilnius",
    "iso:country":"LT",
    "name:und_x_variant":[
        "Mitkshpaychyay",
        "Mink\u0161tpau\u010diai",
        "Antegluonis"
    ],
    "wof:name":"Antegluonis",
    "wof:placetype":"locality"
},
  "geometry": {"coordinates":[22.44936,55.34841],"type":"Point"}
}