{
  "type": "Feature",
  "properties": {
    "gn:admin1_code":"59",
    "gn:admin2_code":"84.0",
    "gn:asciiname":"Margauskai",
    "gn:country_code":"LT",
    "gn:dem":59,
    "gn:feature_class":"P",
    "gn:feature_code":"PPL",
    "gn:name":"Margauskai",
    "gn:population":0,
    "gn:timezone":"Europe/Vilnius",
    "iso:country":"LT",
    "name:lit_x_preferred":[
        "Margauskai"
    ],
    "wof:name":"Margauskai",
    "wof:placetype":"locality"
},
  "geometry": {"coordinates":[23.30295,54.88895],"type":"Point"}
}