{
  "type": "Feature",
  "properties": {
    "gn:admin1_code":"64",
    "gn:admin2_code":"62.0",
    "gn:asciiname":"Alkunai",
    "gn:country_code":"LT",
    "gn:dem":168,
    "gn:feature_class":"P",
    "gn:feature_code":"PPL",
    "gn:name":"Alk\u016bnai",
    "gn:population":0,
    "gn:timezone":"Europe/Vilnius",
    "iso:country":"LT",
    "name:lit_x_preferred":[
        "Alk\u016bnai"
    ],
    "wof:name":"Alkunai",
    "wof:placetype":"locality"
},
  "geometry": {"coordinates":[25.55044,55.13563000000001],"type":"Point"}
}