{
  "type": "Feature",
  "properties": {
    "gn:admin1_code":"64",
    "gn:admin2_code":"43.0",
    "gn:asciiname":"Meletiskes",
    "gn:country_code":"LT",
    "gn:dem":114,
    "gn:feature_class":"P",
    "gn:feature_code":"PPL",
    "gn:name":"Meleti\u0161k\u0117s",
    "gn:population":0,
    "gn:timezone":"Europe/Vilnius",
    "iso:country":"LT",
    "name:lit_x_preferred":[
        "Meleti\u0161k\u0117s"
    ],
    "wof:name":"Meletiskes",
    "wof:placetype":"locality"
},
  "geometry": {"coordinates":[25.88414,55.7981],"type":"Point"}
}