{
  "type": "Feature",
  "properties": {
    "gn:admin1_code":"65",
    "gn:admin2_code":"85.0",
    "gn:asciiname":"Albertina",
    "gn:country_code":"LT",
    "gn:dem":186,
    "gn:feature_class":"P",
    "gn:feature_code":"PPL",
    "gn:name":"Albertina",
    "gn:population":0,
    "gn:timezone":"Europe/Vilnius",
    "iso:country":"LT",
    "name:ara_x_preferred":[
        "\u0623\u0644\u0628\u0631\u062a\u064a\u0646\u0627"
    ],
    "name:arz_x_preferred":[
        "\u0627\u0644\u0628\u064a\u0631\u062a\u064a\u0646\u0627"
    ],
    "name:bel_x_preferred":[
        "\u0413\u0430\u043b\u0435\u0440\u044d\u044f \u0410\u043b\u044c\u0431\u0435\u0440\u0446\u0456\u043d\u0430"
    ],
    "name:bos_x_preferred":[
        "Albertina"
    ],
    "name:bul_x_preferred":[
        "\u0410\u043b\u0431\u0435\u0440\u0442\u0438\u043d\u0430"
    ],
    "name:cat_x_preferred":[
        "Albertina"
    ],
    "name:ces_x_preferred":[
        "Albertina"
    ],
    "name:dan_x_preferred":[
        "Albertina"
    ],
    "name:deu_x_preferred":[
        "Albertina"
    ],
    "name:epo_x_preferred":[
        "Muzeo Albertina"
    ],
    "name:fin_x_preferred":[
        "Albertina"
    ],
    "name:fra_x_preferred":[
        "Albertina"
    ],
    "name:heb_x_preferred":[
        "\u05de\u05d5\u05d6\u05d9\u05d0\u05d5\u05df \u05d0\u05dc\u05d1\u05e8\u05d8\u05d9\u05e0\u05d4"
    ],
    "name:hun_x_preferred":[
        "Albertina"
    ],
    "name:hye_x_preferred":[
        "\u0531\u056c\u0562\u0565\u0580\u057f\u056b\u0576\u0561 \u057a\u0561\u057f\u056f\u0565\u0580\u0561\u057d\u0580\u0561\u0570"
    ],
    "name:ita_x_preferred":[
        "Albertina"
    ],
    "name:jpn_x_preferred":[
        "\u30a2\u30eb\u30d9\u30eb\u30c6\u30a3\u30fc\u30ca"
    ],
    "name:lat_x_preferred":[
        "Albertina"
    ],
    "name:lit_x_preferred":[
        "Albertina"
    ],
    "name:mzn_x_preferred":[
        "\u0622\u0644\u0628\u0631\u062a\u06cc\u0646\u0627"
    ],
    "name:nld_x_preferred":[
        "Albertina"
    ],
    "name:nor_x_preferred":[
        "Albertina"
    ],
    "name:pol_x_preferred":[
        "Albertina"
    ],
    "name:por_x_preferred":[
        "Galeria Albertina"
    ],
    "name:ron_x_preferred":[
        "Muzeul Albertina"
    ],
    "name:rus_x_preferred":[
        "\u0413\u0430\u043b\u0435\u0440\u0435\u044f \u0410\u043b\u044c\u0431\u0435\u0440\u0442\u0438\u043d\u0430"
    ],
    "name:slk_x_preferred":[
        "Albertina"
    ],
    "name:slv_x_preferred":[
        "Albertina"
    ],
    "name:spa_x_preferred":[
        "Albertina"
    ],
    "name:srp_x_preferred":[
        "\u0410\u043b\u0431\u0435\u0440\u0442\u0438\u043d\u0430"
    ],
    "name:swe_x_preferred":[
        "Albertina"
    ],
    "name:tur_x_preferred":[
        "Albertina M\u00fczesi"
    ],
    "name:ukr_x_preferred":[
        "\u0410\u043b\u044c\u0431\u0435\u0440\u0442\u0456\u043d\u0430"
    ],
    "name:uzb_x_preferred":[
        "Albertina"
    ],
    "name:zho_x_preferred":[
        "\u963f\u5c14\u8d1d\u8482\u5a1c\u535a\u7269\u9986"
    ],
    "wof:name":"Albertina",
    "wof:placetype":"locality"
},
  "geometry": {"coordinates":[25.53463,54.18365],"type":"Point"}
}