{
  "type": "Feature",
  "properties": {
    "gn:admin1_code":"59.0",
    "gn:admin2_code":"18.0",
    "gn:asciiname":"Gudeliai",
    "gn:country_code":"LT",
    "gn:dem":105,
    "gn:feature_class":"P",
    "gn:feature_code":"PPL",
    "gn:name":"Gudeliai",
    "gn:population":0,
    "gn:timezone":"Europe/Vilnius",
    "iso:country":"LT",
    "name:ceb_x_preferred":[
        "Gudeliai"
    ],
    "name:eng_x_preferred":[
        "Gudeliai"
    ],
    "name:est_x_preferred":[
        "Gudeliai"
    ],
    "name:lit_x_preferred":[
        "Gudeliai"
    ],
    "name:nld_x_preferred":[
        "Gudeliai"
    ],
    "name:pol_x_preferred":[
        "Gudele"
    ],
    "name:rus_x_preferred":[
        "\u0413\u0443\u0434\u0435\u043b\u044f\u0439"
    ],
    "name:swe_x_preferred":[
        "Gudeliai"
    ],
    "name:und_x_variant":[
        "Gudeliai Antrieji",
        "Gudele",
        "Gudelyay",
        "Gudeli\u0173",
        "Gudeliai"
    ],
    "wof:name":"Gudeliai",
    "wof:placetype":"locality"
},
  "geometry": {"coordinates":[23.68908,54.52873],"type":"Point"}
}