{
  "type": "Feature",
  "properties": {
    "gn:admin1_code":"60.0",
    "gn:admin2_code":"27.0",
    "gn:asciiname":"Bernatoniai",
    "gn:country_code":"LT",
    "gn:dem":47,
    "gn:feature_class":"P",
    "gn:feature_code":"PPL",
    "gn:name":"Bernatoniai",
    "gn:population":0,
    "gn:timezone":"Europe/Vilnius",
    "iso:country":"LT",
    "name:lit_x_preferred":[
        "Bernatoniai"
    ],
    "wof:name":"Bernatoniai",
    "wof:placetype":"locality"
},
  "geometry": {"coordinates":[24.2908,55.78097],"type":"Point"}
}