{
  "type": "Feature",
  "properties": {
    "gn:admin1_code":"64",
    "gn:admin2_code":"62.0",
    "gn:asciiname":"Garneliskes",
    "gn:country_code":"LT",
    "gn:dem":164,
    "gn:feature_class":"P",
    "gn:feature_code":"PPL",
    "gn:name":"Garneli\u0161k\u0117s",
    "gn:population":0,
    "gn:timezone":"Europe/Vilnius",
    "iso:country":"LT",
    "name:lit_x_preferred":[
        "Garneli\u0161k\u0117s"
    ],
    "wof:name":"Garneliskes",
    "wof:placetype":"locality"
},
  "geometry": {"coordinates":[25.54946,55.26658000000001],"type":"Point"}
}