{
  "type": "Feature",
  "properties": {
    "gn:admin1_code":"65.0",
    "gn:admin2_code":"42.0",
    "gn:asciiname":"Abromiskes",
    "gn:country_code":"LT",
    "gn:dem":139,
    "gn:feature_class":"P",
    "gn:feature_code":"PPL",
    "gn:name":"Abromi\u0161k\u0117s",
    "gn:population":0,
    "gn:timezone":"Europe/Vilnius",
    "iso:country":"LT",
    "name:und_x_variant":[
        "Abramovsk",
        "Abromi\u0161k\u0117s"
    ],
    "wof:name":"Abromiskes",
    "wof:placetype":"locality"
},
  "geometry": {"coordinates":[24.7171,54.78291],"type":"Point"}
}