{
  "type": "Feature",
  "properties": {
    "gn:admin1_code":"56.0",
    "gn:admin2_code":"59.0",
    "gn:asciiname":"Nakruniske",
    "gn:country_code":"LT",
    "gn:dem":152,
    "gn:feature_class":"P",
    "gn:feature_code":"PPL",
    "gn:name":"Nakr\u016bni\u0161k\u0117",
    "gn:population":0,
    "gn:timezone":"Europe/Vilnius",
    "iso:country":"LT",
    "name:lit_x_preferred":[
        "Nakr\u016bni\u0161k\u0117"
    ],
    "wof:name":"Nakruniske",
    "wof:placetype":"locality"
},
  "geometry": {"coordinates":[23.7464,54.25877],"type":"Point"}
}