{
  "type": "Feature",
  "properties": {
    "gn:admin1_code":"59",
    "gn:admin2_code":"39.0",
    "gn:asciiname":"Drebuline",
    "gn:country_code":"LT",
    "gn:dem":47,
    "gn:feature_class":"P",
    "gn:feature_code":"PPL",
    "gn:name":"Drebulin\u0117",
    "gn:population":0,
    "gn:timezone":"Europe/Vilnius",
    "iso:country":"LT",
    "name:lit_x_preferred":[
        "Drebulin\u0117"
    ],
    "wof:name":"Drebuline",
    "wof:placetype":"locality"
},
  "geometry": {"coordinates":[22.93186,54.6858],"type":"Point"}
}