{
  "type": "Feature",
  "properties": {
    "gn:admin1_code":"61",
    "gn:admin2_code":"71.0",
    "gn:asciiname":"Mumsilis",
    "gn:country_code":"LT",
    "gn:dem":117,
    "gn:feature_class":"P",
    "gn:feature_code":"PPL",
    "gn:name":"Mum\u0161ilis",
    "gn:population":0,
    "gn:timezone":"Europe/Vilnius",
    "iso:country":"LT",
    "name:lit_x_preferred":[
        "Mum\u0161ilis"
    ],
    "wof:name":"Mumsilis",
    "wof:placetype":"locality"
},
  "geometry": {"coordinates":[23.52049,55.64643],"type":"Point"}
}