{
  "type": "Feature",
  "properties": {
    "gn:admin1_code":"64.0",
    "gn:admin2_code":"82.0",
    "gn:asciiname":"Kuktiskes",
    "gn:country_code":"LT",
    "gn:dem":172,
    "gn:feature_class":"P",
    "gn:feature_code":"PPL",
    "gn:name":"Kukti\u0161k\u0117s",
    "gn:population":0,
    "gn:timezone":"Europe/Vilnius",
    "iso:country":"LT",
    "name:ceb_x_preferred":[
        "Kukti\u0161k\u0117s"
    ],
    "name:eng_x_preferred":[
        "Kukti\u0161k\u0117s"
    ],
    "name:ita_x_preferred":[
        "Kukti\u0161k\u0117s"
    ],
    "name:lit_x_preferred":[
        "Kukti\u0161k\u0117s"
    ],
    "name:nld_x_preferred":[
        "Kukti\u0161k\u0117s"
    ],
    "name:pol_x_preferred":[
        "Kukuciszki"
    ],
    "name:rus_x_preferred":[
        "\u041a\u0443\u043a\u0442\u0438\u0448\u043a\u0435\u0441"
    ],
    "name:swe_x_preferred":[
        "Kukti\u0161k\u0117s"
    ],
    "name:und_x_variant":[
        "Kuktishkes",
        "Kukti\u0161ki\u0173",
        "Kukciszki",
        "Kukuzishki"
    ],
    "wof:name":"Kuktiskes",
    "wof:placetype":"locality"
},
  "geometry": {"coordinates":[25.67886,55.39462],"type":"Point"}
}