{
  "type": "Feature",
  "properties": {
    "gn:admin1_code":"61.0",
    "gn:admin2_code":"29.0",
    "gn:asciiname":"Repsiai",
    "gn:country_code":"LT",
    "gn:dem":127,
    "gn:feature_class":"P",
    "gn:feature_code":"PPL",
    "gn:name":"Rep\u0161iai",
    "gn:population":0,
    "gn:timezone":"Europe/Vilnius",
    "iso:country":"LT",
    "name:und_x_variant":[
        "Repshyay",
        "Rep\u0161iai"
    ],
    "wof:name":"Repsiai",
    "wof:placetype":"locality"
},
  "geometry": {"coordinates":[22.78745,55.94647],"type":"Point"}
}