{
  "type": "Feature",
  "properties": {
    "gn:admin1_code":"65",
    "gn:admin2_code":"13.0",
    "gn:asciiname":"Padvariai",
    "gn:country_code":"LT",
    "gn:dem":150,
    "gn:feature_class":"P",
    "gn:feature_code":"PPL",
    "gn:name":"Padvariai",
    "gn:population":0,
    "gn:timezone":"Europe/Vilnius",
    "iso:country":"LT",
    "name:lit_x_preferred":[
        "Padvariai"
    ],
    "wof:name":"Padvariai",
    "wof:placetype":"locality"
},
  "geometry": {"coordinates":[25.03362000000001,54.77399000000001],"type":"Point"}
}