{
  "type": "Feature",
  "properties": {
    "gn:admin1_code":"61",
    "gn:admin2_code":"71.0",
    "gn:asciiname":"Dirvoniskiai",
    "gn:country_code":"LT",
    "gn:dem":128,
    "gn:feature_class":"P",
    "gn:feature_code":"PPL",
    "gn:name":"Dirvoni\u0161kiai",
    "gn:population":0,
    "gn:timezone":"Europe/Vilnius",
    "iso:country":"LT",
    "name:lit_x_preferred":[
        "Dirvoni\u0161kiai"
    ],
    "wof:name":"Dirvoniskiai",
    "wof:placetype":"locality"
},
  "geometry": {"coordinates":[23.3623,55.67504],"type":"Point"}
}