{
  "type": "Feature",
  "properties": {
    "gn:admin1_code":"57",
    "gn:admin2_code":"69.0",
    "gn:asciiname":"Poliesis",
    "gn:country_code":"LT",
    "gn:dem":239,
    "gn:feature_class":"P",
    "gn:feature_code":"PPL",
    "gn:name":"Poliesis",
    "gn:population":0,
    "gn:timezone":"Europe/Vilnius",
    "iso:country":"LT",
    "name:lit_x_preferred":[
        "Poliesis"
    ],
    "wof:name":"Poliesis",
    "wof:placetype":"locality"
},
  "geometry": {"coordinates":[24.48213,54.60744],"type":"Point"}
}