{
  "type": "Feature",
  "properties": {
    "gn:admin1_code":"59.0",
    "gn:admin2_code":"48.0",
    "gn:asciiname":"Reketija",
    "gn:country_code":"LT",
    "gn:dem":156,
    "gn:feature_class":"P",
    "gn:feature_code":"PPL",
    "gn:name":"Reketija",
    "gn:population":0,
    "gn:timezone":"Europe/Vilnius",
    "iso:country":"LT",
    "name:und_x_variant":[
        "Rykaytseye",
        "Reketijos",
        "Reketija"
    ],
    "wof:name":"Reketija",
    "wof:placetype":"locality"
},
  "geometry": {"coordinates":[23.07953,54.32921],"type":"Point"}
}