{
  "type": "Feature",
  "properties": {
    "gn:admin1_code":"65",
    "gn:admin2_code":"86.0",
    "gn:asciiname":"Pasekstis",
    "gn:country_code":"LT",
    "gn:dem":148,
    "gn:feature_class":"P",
    "gn:feature_code":"PPL",
    "gn:name":"Pa\u0161ek\u0161tis",
    "gn:population":0,
    "gn:timezone":"Europe/Vilnius",
    "iso:country":"LT",
    "name:lit_x_preferred":[
        "Pa\u0161ek\u0161tis"
    ],
    "wof:name":"Pasekstis",
    "wof:placetype":"locality"
},
  "geometry": {"coordinates":[25.81314,55.23982],"type":"Point"}
}