{
  "type": "Feature",
  "properties": {
    "gn:admin1_code":"61.0",
    "gn:admin2_code":"47.0",
    "gn:asciiname":"Pociunai",
    "gn:country_code":"LT",
    "gn:dem":60,
    "gn:feature_class":"P",
    "gn:feature_code":"PPL",
    "gn:name":"Poci\u016bnai",
    "gn:population":0,
    "gn:timezone":"Europe/Vilnius",
    "iso:country":"LT",
    "name:und_x_variant":[
        "Po\u010diuneliai",
        "Potsyuny",
        "Poci\u016bnai"
    ],
    "wof:name":"Pociunai",
    "wof:placetype":"locality"
},
  "geometry": {"coordinates":[23.52994,56.23698],"type":"Point"}
}