{
  "type": "Feature",
  "properties": {
    "gn:admin1_code":"60",
    "gn:admin2_code":"27.0",
    "gn:asciiname":"Vainiskis",
    "gn:country_code":"LT",
    "gn:dem":73,
    "gn:feature_class":"P",
    "gn:feature_code":"PPL",
    "gn:name":"Vaini\u0161kis",
    "gn:population":0,
    "gn:timezone":"Europe/Vilnius",
    "iso:country":"LT",
    "name:lit_x_preferred":[
        "Vaini\u0161kis"
    ],
    "wof:name":"Vainiskis",
    "wof:placetype":"locality"
},
  "geometry": {"coordinates":[24.70554,55.70247],"type":"Point"}
}