{
  "type": "Feature",
  "properties": {
    "gn:admin1_code":"61.0",
    "gn:admin2_code":"47.0",
    "gn:asciiname":"Jauniunai",
    "gn:country_code":"LT",
    "gn:dem":76,
    "gn:feature_class":"P",
    "gn:feature_code":"PPL",
    "gn:name":"Jauni\u016bnai",
    "gn:population":0,
    "gn:timezone":"Europe/Vilnius",
    "iso:country":"LT",
    "name:und_x_variant":[
        "Yaunyunay",
        "Jauni\u016bn\u0173",
        "Yavnelyay",
        "Jauni\u016bnai"
    ],
    "wof:name":"Jauniunai",
    "wof:placetype":"locality"
},
  "geometry": {"coordinates":[23.4957,56.10542],"type":"Point"}
}