{
  "type": "Feature",
  "properties": {
    "gn:admin1_code":"62",
    "gn:admin2_code":"94.0",
    "gn:asciiname":"Naukaimis",
    "gn:country_code":"LT",
    "gn:dem":51,
    "gn:feature_class":"P",
    "gn:feature_code":"PPL",
    "gn:name":"Naukaimis",
    "gn:population":0,
    "gn:timezone":"Europe/Vilnius",
    "iso:country":"LT",
    "name:lit_x_preferred":[
        "Naukaimis"
    ],
    "wof:name":"Naukaimis",
    "wof:placetype":"locality"
},
  "geometry": {"coordinates":[22.92933,55.28545],"type":"Point"}
}