{
  "type": "Feature",
  "properties": {
    "gn:admin1_code":"65.0",
    "gn:admin2_code":"81.0",
    "gn:asciiname":"Kopusteliai",
    "gn:country_code":"LT",
    "gn:dem":92,
    "gn:feature_class":"P",
    "gn:feature_code":"PPL",
    "gn:name":"Kop\u016bst\u0117liai",
    "gn:population":0,
    "gn:timezone":"Europe/Vilnius",
    "iso:country":"LT",
    "name:und_x_variant":[
        "Kapusteli",
        "Kop\u016bst\u0117liai"
    ],
    "wof:name":"Kopusteliai",
    "wof:placetype":"locality"
},
  "geometry": {"coordinates":[24.91771,55.32975],"type":"Point"}
}