{
  "type": "Feature",
  "properties": {
    "gn:admin1_code":"61",
    "gn:admin2_code":"54.0",
    "gn:asciiname":"Gembutiske",
    "gn:country_code":"LT",
    "gn:dem":112,
    "gn:feature_class":"P",
    "gn:feature_code":"PPL",
    "gn:name":"Gembuti\u0161k\u0117",
    "gn:population":0,
    "gn:timezone":"Europe/Vilnius",
    "iso:country":"LT",
    "name:lit_x_preferred":[
        "Gembuti\u0161k\u0117"
    ],
    "wof:name":"Gembutiske",
    "wof:placetype":"locality"
},
  "geometry": {"coordinates":[23.08632,55.68124],"type":"Point"}
}