{
  "type": "Feature",
  "properties": {
    "gn:admin1_code":"65",
    "gn:admin2_code":"13.0",
    "gn:asciiname":"Gudeliu Plytine",
    "gn:country_code":"LT",
    "gn:dem":170,
    "gn:feature_class":"P",
    "gn:feature_code":"PPL",
    "gn:name":"Gudeli\u0173 Plytin\u0117",
    "gn:population":0,
    "gn:timezone":"Europe/Vilnius",
    "iso:country":"LT",
    "name:lit_x_preferred":[
        "Gudeli\u0173 Plytin\u0117"
    ],
    "wof:name":"Gudeliu Plytine",
    "wof:placetype":"locality"
},
  "geometry": {"coordinates":[25.18494,54.82211],"type":"Point"}
}