{
  "type": "Feature",
  "properties": {
    "gn:admin1_code":"59.0",
    "gn:admin2_code":"84.0",
    "gn:asciiname":"Degesiai",
    "gn:country_code":"LT",
    "gn:dem":40,
    "gn:feature_class":"P",
    "gn:feature_code":"PPL",
    "gn:name":"Deg\u0117siai",
    "gn:population":0,
    "gn:timezone":"Europe/Vilnius",
    "iso:country":"LT",
    "name:lit_x_preferred":[
        "Deg\u0117siai"
    ],
    "name:und_x_variant":[
        "Degese",
        "Degesiai"
    ],
    "wof:name":"Degesiai",
    "wof:placetype":"locality"
},
  "geometry": {"coordinates":[22.86159,55.01521],"type":"Point"}
}