{
  "type": "Feature",
  "properties": {
    "gn:admin1_code":"63.0",
    "gn:admin2_code":"78.0",
    "gn:asciiname":"Klaisiskiai",
    "gn:country_code":"LT",
    "gn:dem":169,
    "gn:feature_class":"P",
    "gn:feature_code":"PPL",
    "gn:name":"Klai\u0161i\u0161kiai",
    "gn:population":0,
    "gn:timezone":"Europe/Vilnius",
    "iso:country":"LT",
    "name:und_x_variant":[
        "Klayshishkyay",
        "Klai\u0161i\u0161kiai"
    ],
    "wof:name":"Klaisiskiai",
    "wof:placetype":"locality"
},
  "geometry": {"coordinates":[22.40657,55.70281],"type":"Point"}
}