{
  "type": "Feature",
  "properties": {
    "gn:admin1_code":"59.0",
    "gn:admin2_code":"39.0",
    "gn:asciiname":"Rimaviciai",
    "gn:country_code":"LT",
    "gn:dem":70,
    "gn:feature_class":"P",
    "gn:feature_code":"PPL",
    "gn:name":"Rimavi\u010diai",
    "gn:population":0,
    "gn:timezone":"Europe/Vilnius",
    "iso:country":"LT",
    "name:lit_x_preferred":[
        "Rimavi\u010diai"
    ],
    "name:und_x_variant":[
        "Ramoviet\u0117"
    ],
    "wof:name":"Rimaviciai",
    "wof:placetype":"locality"
},
  "geometry": {"coordinates":[23.25805,54.62647],"type":"Point"}
}