{
  "type": "Feature",
  "properties": {
    "gn:admin1_code":"60",
    "gn:admin2_code":"73.0",
    "gn:asciiname":"Lugariskis",
    "gn:country_code":"LT",
    "gn:dem":137,
    "gn:feature_class":"P",
    "gn:feature_code":"PPL",
    "gn:name":"Lugari\u0161kis",
    "gn:population":0,
    "gn:timezone":"Europe/Vilnius",
    "iso:country":"LT",
    "name:lit_x_preferred":[
        "Lugari\u0161kis"
    ],
    "wof:name":"Lugariskis",
    "wof:placetype":"locality"
},
  "geometry": {"coordinates":[26.02164,55.9444],"type":"Point"}
}