{
  "type": "Feature",
  "properties": {
    "gn:admin1_code":"65",
    "gn:admin2_code":"13.0",
    "gn:asciiname":"Barcialaukis",
    "gn:country_code":"LT",
    "gn:dem":137,
    "gn:feature_class":"P",
    "gn:feature_code":"PPL",
    "gn:name":"Bar\u010dialaukis",
    "gn:population":0,
    "gn:timezone":"Europe/Vilnius",
    "iso:country":"LT",
    "name:lit_x_preferred":[
        "Bar\u010dialaukis"
    ],
    "wof:name":"Barcialaukis",
    "wof:placetype":"locality"
},
  "geometry": {"coordinates":[25.37055,54.85842],"type":"Point"}
}