{
  "type": "Feature",
  "properties": {
    "gn:admin1_code":"64",
    "gn:admin2_code":"34.0",
    "gn:asciiname":"Stasiskiai",
    "gn:country_code":"LT",
    "gn:dem":114,
    "gn:feature_class":"P",
    "gn:feature_code":"PPL",
    "gn:name":"Stasi\u0161kiai",
    "gn:population":0,
    "gn:timezone":"Europe/Vilnius",
    "iso:country":"LT",
    "name:lit_x_preferred":[
        "Stasi\u0161kiai"
    ],
    "wof:name":"Stasiskiai",
    "wof:placetype":"locality"
},
  "geometry": {"coordinates":[25.40758,55.6169],"type":"Point"}
}