{
  "type": "Feature",
  "properties": {
    "gn:admin1_code":"63",
    "gn:admin2_code":"78.0",
    "gn:asciiname":"Sakaline",
    "gn:country_code":"LT",
    "gn:dem":155,
    "gn:feature_class":"P",
    "gn:feature_code":"PPL",
    "gn:name":"\u0160akalin\u0117",
    "gn:population":0,
    "gn:timezone":"Europe/Vilnius",
    "iso:country":"LT",
    "name:lit_x_preferred":[
        "\u0160akalin\u0117"
    ],
    "wof:name":"Sakaline",
    "wof:placetype":"locality"
},
  "geometry": {"coordinates":[22.44626,55.7561],"type":"Point"}
}