{
  "type": "Feature",
  "properties": {
    "gn:admin1_code":"60.0",
    "gn:admin2_code":"27.0",
    "gn:asciiname":"Puoriai",
    "gn:country_code":"LT",
    "gn:dem":49,
    "gn:feature_class":"P",
    "gn:feature_code":"PPL",
    "gn:name":"Puoriai",
    "gn:population":0,
    "gn:timezone":"Europe/Vilnius",
    "iso:country":"LT",
    "name:und_x_variant":[
        "Pory",
        "Puoriai"
    ],
    "wof:name":"Puoriai",
    "wof:placetype":"locality"
},
  "geometry": {"coordinates":[24.09597,55.65516],"type":"Point"}
}