{
  "type": "Feature",
  "properties": {
    "gn:admin1_code":"57.0",
    "gn:admin2_code":"49.0",
    "gn:asciiname":"Livintai",
    "gn:country_code":"LT",
    "gn:dem":81,
    "gn:feature_class":"P",
    "gn:feature_code":"PPL",
    "gn:name":"Livintai",
    "gn:population":0,
    "gn:timezone":"Europe/Vilnius",
    "iso:country":"LT",
    "name:und_x_variant":[
        "Levintai",
        "Livinyay",
        "Levinty",
        "Levintoy",
        "Livintai"
    ],
    "wof:name":"Livintai",
    "wof:placetype":"locality"
},
  "geometry": {"coordinates":[24.34094,54.93705],"type":"Point"}
}