{
  "type": "Feature",
  "properties": {
    "gn:admin1_code":"65.0",
    "gn:admin2_code":"85.0",
    "gn:asciiname":"Vaskeliai",
    "gn:country_code":"LT",
    "gn:dem":163,
    "gn:feature_class":"P",
    "gn:feature_code":"PPL",
    "gn:name":"Va\u0161keliai",
    "gn:population":0,
    "gn:timezone":"Europe/Vilnius",
    "iso:country":"LT",
    "name:lit_x_preferred":[
        "Va\u0161keliai"
    ],
    "wof:name":"Vaskeliai",
    "wof:placetype":"locality"
},
  "geometry": {"coordinates":[25.76272,54.17954],"type":"Point"}
}