{
  "type": "Feature",
  "properties": {
    "gn:admin1_code":"65",
    "gn:admin2_code":"79.0",
    "gn:asciiname":"Vidokiai",
    "gn:country_code":"LT",
    "gn:dem":188,
    "gn:feature_class":"P",
    "gn:feature_code":"PPL",
    "gn:name":"Vidokiai",
    "gn:population":0,
    "gn:timezone":"Europe/Vilnius",
    "iso:country":"LT",
    "name:lit_x_preferred":[
        "Vidokiai"
    ],
    "wof:name":"Vidokiai",
    "wof:placetype":"locality"
},
  "geometry": {"coordinates":[24.51869,54.65872],"type":"Point"}
}