{
  "type": "Feature",
  "properties": {
    "gn:admin1_code":"57",
    "gn:admin2_code":"46.0",
    "gn:asciiname":"Gedgaudai",
    "gn:country_code":"LT",
    "gn:dem":94,
    "gn:feature_class":"P",
    "gn:feature_code":"PPL",
    "gn:name":"Gedgaudai",
    "gn:population":0,
    "gn:timezone":"Europe/Vilnius",
    "iso:country":"LT",
    "name:lit_x_preferred":[
        "Gedgaudai"
    ],
    "wof:name":"Gedgaudai",
    "wof:placetype":"locality"
},
  "geometry": {"coordinates":[24.37852,55.17785],"type":"Point"}
}