{
  "type": "Feature",
  "properties": {
    "gn:admin1_code":"60",
    "gn:admin2_code":"57.0",
    "gn:asciiname":"Mirabelelis",
    "gn:country_code":"LT",
    "gn:dem":92,
    "gn:feature_class":"P",
    "gn:feature_code":"PPL",
    "gn:name":"Mirabel\u0117lis",
    "gn:population":0,
    "gn:timezone":"Europe/Vilnius",
    "iso:country":"LT",
    "name:lit_x_preferred":[
        "Mirabel\u0117lis"
    ],
    "wof:name":"Mirabelelis",
    "wof:placetype":"locality"
},
  "geometry": {"coordinates":[25.17935,55.87759000000001],"type":"Point"}
}