{
  "type": "Feature",
  "properties": {
    "gn:admin1_code":"63",
    "gn:admin2_code":"74.0",
    "gn:asciiname":"Budrikiai",
    "gn:country_code":"LT",
    "gn:dem":113,
    "gn:feature_class":"P",
    "gn:feature_code":"PPL",
    "gn:name":"Budrikiai",
    "gn:population":0,
    "gn:timezone":"Europe/Vilnius",
    "iso:country":"LT",
    "name:lit_x_preferred":[
        "Budrikiai"
    ],
    "wof:name":"Budrikiai",
    "wof:placetype":"locality"
},
  "geometry": {"coordinates":[21.91911,55.74899],"type":"Point"}
}