{
  "type": "Feature",
  "properties": {
    "gn:admin1_code":"58",
    "gn:admin2_code":"56.0",
    "gn:asciiname":"Rubiniske",
    "gn:country_code":"LT",
    "gn:dem":43,
    "gn:feature_class":"P",
    "gn:feature_code":"PPL",
    "gn:name":"Rubini\u0161k\u0117",
    "gn:population":0,
    "gn:timezone":"Europe/Vilnius",
    "iso:country":"LT",
    "name:lit_x_preferred":[
        "Rubini\u0161k\u0117"
    ],
    "wof:name":"Rubiniske",
    "wof:placetype":"locality"
},
  "geometry": {"coordinates":[21.37149,56.02361],"type":"Point"}
}