{
  "type": "Feature",
  "properties": {
    "gn:admin1_code":"62.0",
    "gn:admin2_code":"87.0",
    "gn:asciiname":"Ievoniskiai",
    "gn:country_code":"LT",
    "gn:dem":132,
    "gn:feature_class":"P",
    "gn:feature_code":"PPL",
    "gn:name":"Ievoni\u0161kiai",
    "gn:population":0,
    "gn:timezone":"Europe/Vilnius",
    "iso:country":"LT",
    "name:lit_x_preferred":[
        "Ievoni\u0161kiai"
    ],
    "name:und_x_variant":[
        "Ivoni\u0161kiai"
    ],
    "wof:name":"Ievoniskiai",
    "wof:placetype":"locality"
},
  "geometry": {"coordinates":[22.15681,55.60957],"type":"Point"}
}