{
  "type": "Feature",
  "properties": {
    "gn:admin1_code":"65",
    "gn:admin2_code":"81.0",
    "gn:asciiname":"Martyniskis",
    "gn:country_code":"LT",
    "gn:dem":91,
    "gn:feature_class":"P",
    "gn:feature_code":"PPL",
    "gn:name":"Martyni\u0161kis",
    "gn:population":0,
    "gn:timezone":"Europe/Vilnius",
    "iso:country":"LT",
    "name:lit_x_preferred":[
        "Martyni\u0161kis"
    ],
    "wof:name":"Martyniskis",
    "wof:placetype":"locality"
},
  "geometry": {"coordinates":[24.57787,55.18312],"type":"Point"}
}