{
  "type": "Feature",
  "properties": {
    "gn:admin1_code":"63.0",
    "gn:admin2_code":"74.0",
    "gn:asciiname":"Kyvaiciai",
    "gn:country_code":"LT",
    "gn:dem":178,
    "gn:feature_class":"P",
    "gn:feature_code":"PPL",
    "gn:name":"Kyvai\u010diai",
    "gn:population":0,
    "gn:timezone":"Europe/Vilnius",
    "iso:country":"LT",
    "name:und_x_variant":[
        "Kivaychyay",
        "Kyvai\u010diai"
    ],
    "wof:name":"Kyvaiciai",
    "wof:placetype":"locality"
},
  "geometry": {"coordinates":[22.20636,55.76722],"type":"Point"}
}