{
  "type": "Feature",
  "properties": {
    "gn:admin1_code":"58",
    "gn:admin2_code":"21.0",
    "gn:asciiname":"Perkunai",
    "gn:country_code":"LT",
    "gn:dem":71,
    "gn:feature_class":"P",
    "gn:feature_code":"PPL",
    "gn:name":"Perk\u016bnai",
    "gn:population":0,
    "gn:timezone":"Europe/Vilnius",
    "iso:country":"LT",
    "name:lit_x_preferred":[
        "Perk\u016bnai"
    ],
    "wof:name":"Perkunai",
    "wof:placetype":"locality"
},
  "geometry": {"coordinates":[21.50619,55.73873],"type":"Point"}
}