{
  "type": "Feature",
  "properties": {
    "gn:admin1_code":"65.0",
    "gn:admin2_code":"86.0",
    "gn:asciiname":"Vaiciukiske I",
    "gn:country_code":"LT",
    "gn:dem":150,
    "gn:feature_class":"P",
    "gn:feature_code":"PPL",
    "gn:name":"Vai\u010diuki\u0161k\u0117 I",
    "gn:population":0,
    "gn:timezone":"Europe/Vilnius",
    "iso:country":"LT",
    "name:lit_x_preferred":[
        "Vai\u010diuki\u0161k\u0117 I"
    ],
    "name:und_x_variant":[
        "Voyukishki",
        "Vai\u010diuki\u0161k\u0117"
    ],
    "wof:name":"Vaiciukiske I",
    "wof:placetype":"locality"
},
  "geometry": {"coordinates":[26.14862,55.23826],"type":"Point"}
}