{
  "type": "Feature",
  "properties": {
    "gn:admin1_code":"60.0",
    "gn:admin2_code":"27.0",
    "gn:asciiname":"Griniunai",
    "gn:country_code":"LT",
    "gn:dem":62,
    "gn:feature_class":"P",
    "gn:feature_code":"PPL",
    "gn:name":"Grini\u016bnai",
    "gn:population":0,
    "gn:timezone":"Europe/Vilnius",
    "iso:country":"LT",
    "name:und_x_variant":[
        "Grinyuny",
        "Grini\u016bnai"
    ],
    "wof:name":"Griniunai",
    "wof:placetype":"locality"
},
  "geometry": {"coordinates":[24.39054,55.55376],"type":"Point"}
}