{
  "type": "Feature",
  "properties": {
    "gn:admin1_code":"0.0",
    "gn:asciiname":"Teresdvaris",
    "gn:cc2":"LT",
    "gn:country_code":"LT",
    "gn:dem":57,
    "gn:feature_class":"P",
    "gn:feature_code":"PPL",
    "gn:name":"Teresdvaris",
    "gn:population":0,
    "gn:timezone":"Europe/Vilnius",
    "iso:country":"LT",
    "name:und_x_variant":[
        "Terezdvor",
        "Teresdvaris"
    ],
    "wof:name":"Teresdvaris",
    "wof:placetype":"locality"
},
  "geometry": {"coordinates":[24.65,55.78333000000001],"type":"Point"}
}