{
  "type": "Feature",
  "properties": {
    "gn:admin1_code":"61.0",
    "gn:admin2_code":"32.0",
    "gn:asciiname":"Juciai",
    "gn:country_code":"LT",
    "gn:dem":78,
    "gn:feature_class":"P",
    "gn:feature_code":"PPL",
    "gn:name":"Ju\u010diai",
    "gn:population":0,
    "gn:timezone":"Europe/Vilnius",
    "iso:country":"LT",
    "name:lit_x_preferred":[
        "Ju\u010diai"
    ],
    "wof:name":"Juciai",
    "wof:placetype":"locality"
},
  "geometry": {"coordinates":[22.64479,56.34818000000001],"type":"Point"}
}