{
  "type": "Feature",
  "properties": {
    "gn:admin1_code":"64.0",
    "gn:admin2_code":"43.0",
    "gn:asciiname":"Sauliai",
    "gn:country_code":"LT",
    "gn:dem":162,
    "gn:feature_class":"P",
    "gn:feature_code":"PPL",
    "gn:name":"\u0160auliai",
    "gn:population":0,
    "gn:timezone":"Europe/Vilnius",
    "iso:country":"LT",
    "name:und_x_variant":[
        "Siauliai",
        "\u0160auliai"
    ],
    "wof:name":"Sauliai",
    "wof:placetype":"locality"
},
  "geometry": {"coordinates":[26.26413,55.66409],"type":"Point"}
}