{
  "type": "Feature",
  "properties": {
    "gn:admin1_code":"59",
    "gn:admin2_code":"84.0",
    "gn:asciiname":"Baltkojai",
    "gn:country_code":"LT",
    "gn:dem":45,
    "gn:feature_class":"P",
    "gn:feature_code":"PPL",
    "gn:name":"Baltkojai",
    "gn:population":0,
    "gn:timezone":"Europe/Vilnius",
    "iso:country":"LT",
    "name:lit_x_preferred":[
        "Baltkojai"
    ],
    "wof:name":"Baltkojai",
    "wof:placetype":"locality"
},
  "geometry": {"coordinates":[22.93112,54.97322],"type":"Point"}
}