{
  "type": "Feature",
  "properties": {
    "gn:admin1_code":"65",
    "gn:admin2_code":"81.0",
    "gn:asciiname":"Sukusciai",
    "gn:country_code":"LT",
    "gn:dem":79,
    "gn:feature_class":"P",
    "gn:feature_code":"PPL",
    "gn:name":"Suk\u016bs\u010diai",
    "gn:population":0,
    "gn:timezone":"Europe/Vilnius",
    "iso:country":"LT",
    "name:lit_x_preferred":[
        "Suk\u016bs\u010diai"
    ],
    "wof:name":"Sukusciai",
    "wof:placetype":"locality"
},
  "geometry": {"coordinates":[24.73369,55.40623000000001],"type":"Point"}
}