{
  "type": "Feature",
  "properties": {
    "gn:admin1_code":"62",
    "gn:admin2_code":"87.0",
    "gn:asciiname":"Gedeikiai",
    "gn:country_code":"LT",
    "gn:dem":127,
    "gn:feature_class":"P",
    "gn:feature_code":"PPL",
    "gn:name":"Gedeikiai",
    "gn:population":0,
    "gn:timezone":"Europe/Vilnius",
    "iso:country":"LT",
    "name:lit_x_preferred":[
        "Gedeikiai"
    ],
    "wof:name":"Gedeikiai",
    "wof:placetype":"locality"
},
  "geometry": {"coordinates":[22.54866,55.46308000000001],"type":"Point"}
}