{
  "type": "Feature",
  "properties": {
    "gn:admin1_code":"60.0",
    "gn:admin2_code":"67.0",
    "gn:asciiname":"Jukoniai",
    "gn:country_code":"LT",
    "gn:dem":40,
    "gn:feature_class":"P",
    "gn:feature_code":"PPL",
    "gn:name":"Jukoniai",
    "gn:population":0,
    "gn:timezone":"Europe/Vilnius",
    "iso:country":"LT",
    "name:und_x_variant":[
        "Iokany",
        "Jukoniai"
    ],
    "wof:name":"Jukoniai",
    "wof:placetype":"locality"
},
  "geometry": {"coordinates":[24.26667,55.98398],"type":"Point"}
}