{
  "type": "Feature",
  "properties": {
    "gn:admin1_code":"59.0",
    "gn:admin2_code":"18.0",
    "gn:asciiname":"Islandziai",
    "gn:country_code":"LT",
    "gn:dem":125,
    "gn:feature_class":"P",
    "gn:feature_code":"PPL",
    "gn:name":"I\u0161land\u017eiai",
    "gn:population":0,
    "gn:timezone":"Europe/Vilnius",
    "iso:country":"LT",
    "name:und_x_variant":[
        "I\u0161land\u017ei\u0173",
        "Ishlondze",
        "I\u0161land\u017eiai"
    ],
    "wof:name":"Islandziai",
    "wof:placetype":"locality"
},
  "geometry": {"coordinates":[23.40907,54.37922],"type":"Point"}
}