{
  "type": "Feature",
  "properties": {
    "gn:admin1_code":"60.0",
    "gn:admin2_code":"36.0",
    "gn:asciiname":"Dirvonakiai",
    "gn:country_code":"LT",
    "gn:dem":59,
    "gn:feature_class":"P",
    "gn:feature_code":"PPL",
    "gn:name":"Dirvonakiai",
    "gn:population":0,
    "gn:timezone":"Europe/Vilnius",
    "iso:country":"LT",
    "name:und_x_variant":[
        "Dirvonakyay",
        "Dirvonakiai"
    ],
    "wof:name":"Dirvonakiai",
    "wof:placetype":"locality"
},
  "geometry": {"coordinates":[24.77707,56.15407],"type":"Point"}
}