{
  "type": "Feature",
  "properties": {
    "gn:admin1_code":"65",
    "gn:admin2_code":"89.0",
    "gn:asciiname":"Levainiai",
    "gn:country_code":"LT",
    "gn:dem":106,
    "gn:feature_class":"P",
    "gn:feature_code":"PPL",
    "gn:name":"Levainiai",
    "gn:population":0,
    "gn:timezone":"Europe/Vilnius",
    "iso:country":"LT",
    "name:lit_x_preferred":[
        "Levainiai"
    ],
    "wof:name":"Levainiai",
    "wof:placetype":"locality"
},
  "geometry": {"coordinates":[24.87522,55.01259],"type":"Point"}
}