{
  "type": "Feature",
  "properties": {
    "gn:admin1_code":"61",
    "gn:admin2_code":"29.0",
    "gn:asciiname":"Maldeniai",
    "gn:country_code":"LT",
    "gn:dem":105,
    "gn:feature_class":"P",
    "gn:feature_code":"PPL",
    "gn:name":"Maldeniai",
    "gn:population":0,
    "gn:timezone":"Europe/Vilnius",
    "iso:country":"LT",
    "name:lit_x_preferred":[
        "Maldeniai"
    ],
    "wof:name":"Maldeniai",
    "wof:placetype":"locality"
},
  "geometry": {"coordinates":[23.08248,56.08448000000001],"type":"Point"}
}