{
  "type": "Feature",
  "properties": {
    "gn:admin1_code":"64",
    "gn:admin2_code":"43.0",
    "gn:asciiname":"Pasvente",
    "gn:country_code":"LT",
    "gn:dem":183,
    "gn:feature_class":"P",
    "gn:feature_code":"PPL",
    "gn:name":"Pa\u0161vent\u0117",
    "gn:population":0,
    "gn:timezone":"Europe/Vilnius",
    "iso:country":"LT",
    "name:lit_x_preferred":[
        "Pa\u0161vent\u0117"
    ],
    "wof:name":"Pasvente",
    "wof:placetype":"locality"
},
  "geometry": {"coordinates":[26.30574,55.6258],"type":"Point"}
}