{
  "type": "Feature",
  "properties": {
    "gn:admin1_code":"59.0",
    "gn:admin2_code":"58.0",
    "gn:asciiname":"Kardokai",
    "gn:country_code":"LT",
    "gn:dem":67,
    "gn:feature_class":"P",
    "gn:feature_code":"PPL",
    "gn:name":"Kardokai",
    "gn:population":0,
    "gn:timezone":"Europe/Vilnius",
    "iso:country":"LT",
    "name:und_x_variant":[
        "Kordaki",
        "Kardokai"
    ],
    "wof:name":"Kardokai",
    "wof:placetype":"locality"
},
  "geometry": {"coordinates":[23.48765,54.85851],"type":"Point"}
}