{
  "type": "Feature",
  "properties": {
    "gn:admin1_code":"59",
    "gn:admin2_code":"39.0",
    "gn:asciiname":"Varpuciai",
    "gn:country_code":"LT",
    "gn:dem":50,
    "gn:feature_class":"P",
    "gn:feature_code":"PPL",
    "gn:name":"Varpu\u010diai",
    "gn:population":0,
    "gn:timezone":"Europe/Vilnius",
    "iso:country":"LT",
    "name:lit_x_preferred":[
        "Varpu\u010diai"
    ],
    "wof:name":"Varpuciai",
    "wof:placetype":"locality"
},
  "geometry": {"coordinates":[22.80377,54.66407],"type":"Point"}
}