{
  "type": "Feature",
  "properties": {
    "gn:admin1_code":"60",
    "gn:admin2_code":"73.0",
    "gn:asciiname":"Remeikiai",
    "gn:country_code":"LT",
    "gn:dem":160,
    "gn:feature_class":"P",
    "gn:feature_code":"PPL",
    "gn:name":"Remeikiai",
    "gn:population":0,
    "gn:timezone":"Europe/Vilnius",
    "iso:country":"LT",
    "name:lit_x_preferred":[
        "Remeikiai"
    ],
    "wof:name":"Remeikiai",
    "wof:placetype":"locality"
},
  "geometry": {"coordinates":[25.86694,55.93289],"type":"Point"}
}