{
  "type": "Feature",
  "properties": {
    "gn:admin1_code":"59",
    "gn:admin2_code":"48.0",
    "gn:asciiname":"Berzynai",
    "gn:country_code":"LT",
    "gn:dem":219,
    "gn:feature_class":"P",
    "gn:feature_code":"PPL",
    "gn:name":"Ber\u017eynai",
    "gn:population":0,
    "gn:timezone":"Europe/Vilnius",
    "iso:country":"LT",
    "name:lit_x_preferred":[
        "Ber\u017eynai"
    ],
    "wof:name":"Berzynai",
    "wof:placetype":"locality"
},
  "geometry": {"coordinates":[23.03194,54.40503],"type":"Point"}
}