{
  "type": "Feature",
  "properties": {
    "gn:admin1_code":"64",
    "gn:admin2_code":"82.0",
    "gn:asciiname":"Dryziai",
    "gn:country_code":"LT",
    "gn:dem":167,
    "gn:feature_class":"P",
    "gn:feature_code":"PPL",
    "gn:name":"Dry\u017eiai",
    "gn:population":0,
    "gn:timezone":"Europe/Vilnius",
    "iso:country":"LT",
    "name:lit_x_preferred":[
        "Dry\u017eiai"
    ],
    "wof:name":"Dryziai",
    "wof:placetype":"locality"
},
  "geometry": {"coordinates":[25.79169,55.36346],"type":"Point"}
}