{
  "type": "Feature",
  "properties": {
    "gn:admin1_code":"65",
    "gn:admin2_code":"13.0",
    "gn:asciiname":"Vyziskes",
    "gn:country_code":"LT",
    "gn:dem":182,
    "gn:feature_class":"P",
    "gn:feature_code":"PPL",
    "gn:name":"Vy\u017ei\u0161k\u0117s",
    "gn:population":0,
    "gn:timezone":"Europe/Vilnius",
    "iso:country":"LT",
    "name:lit_x_preferred":[
        "Vy\u017ei\u0161k\u0117s"
    ],
    "wof:name":"Vyziskes",
    "wof:placetype":"locality"
},
  "geometry": {"coordinates":[25.6702,54.76094000000001],"type":"Point"}
}