{
  "type": "Feature",
  "properties": {
    "gn:admin1_code":"0.0",
    "gn:asciiname":"Balninkai II",
    "gn:cc2":"LT",
    "gn:country_code":"LT",
    "gn:dem":133,
    "gn:feature_class":"P",
    "gn:feature_code":"PPL",
    "gn:name":"Balninkai II",
    "gn:population":0,
    "gn:timezone":"Europe/Vilnius",
    "iso:country":"LT",
    "name:und_x_variant":[
        "Balninkai",
        "Bal\u2019niki",
        "Balninkai Antrieji",
        "Balninkai II"
    ],
    "wof:name":"Balninkai II",
    "wof:placetype":"locality"
},
  "geometry": {"coordinates":[24.11667000000001,54.33333],"type":"Point"}
}