{
  "type": "Feature",
  "properties": {
    "gn:admin1_code":"65",
    "gn:admin2_code":"89.0",
    "gn:asciiname":"Paezerelis",
    "gn:country_code":"LT",
    "gn:dem":113,
    "gn:feature_class":"P",
    "gn:feature_code":"PPL",
    "gn:name":"Pae\u017eer\u0117lis",
    "gn:population":0,
    "gn:timezone":"Europe/Vilnius",
    "iso:country":"LT",
    "name:lit_x_preferred":[
        "Pae\u017eer\u0117lis"
    ],
    "wof:name":"Paezerelis",
    "wof:placetype":"locality"
},
  "geometry": {"coordinates":[24.88415,54.89844],"type":"Point"}
}