{
  "type": "Feature",
  "properties": {
    "gn:admin1_code":"0.0",
    "gn:asciiname":"Tolimenai",
    "gn:country_code":"LT",
    "gn:dem":181,
    "gn:feature_class":"P",
    "gn:feature_code":"PPL",
    "gn:name":"Tolim\u0117nai",
    "gn:population":0,
    "gn:timezone":"Europe/Vilnius",
    "iso:country":"LT",
    "name:lit_x_preferred":[
        "Tolim\u0117nai"
    ],
    "name:und_x_variant":[
        "Talimenay",
        "Talim\u0117nai"
    ],
    "wof:name":"Tolimenai",
    "wof:placetype":"locality"
},
  "geometry": {"coordinates":[26.06219,55.5206],"type":"Point"}
}