{
  "type": "Feature",
  "properties": {
    "gn:admin1_code":"65",
    "gn:admin2_code":"86.0",
    "gn:asciiname":"Degutiske",
    "gn:country_code":"LT",
    "gn:dem":215,
    "gn:feature_class":"P",
    "gn:feature_code":"PPL",
    "gn:name":"Deguti\u0161k\u0117",
    "gn:population":0,
    "gn:timezone":"Europe/Vilnius",
    "iso:country":"LT",
    "name:lit_x_preferred":[
        "Deguti\u0161k\u0117"
    ],
    "wof:name":"Degutiske",
    "wof:placetype":"locality"
},
  "geometry": {"coordinates":[26.29014,55.22309],"type":"Point"}
}