{
  "type": "Feature",
  "properties": {
    "gn:admin1_code":"58",
    "gn:admin2_code":"75.0",
    "gn:asciiname":"Milvydziai",
    "gn:country_code":"LT",
    "gn:dem":96,
    "gn:feature_class":"P",
    "gn:feature_code":"PPL",
    "gn:name":"Milvyd\u017eiai",
    "gn:population":0,
    "gn:timezone":"Europe/Vilnius",
    "iso:country":"LT",
    "name:lit_x_preferred":[
        "Milvyd\u017eiai"
    ],
    "wof:name":"Milvydziai",
    "wof:placetype":"locality"
},
  "geometry": {"coordinates":[21.82491,56.30889000000001],"type":"Point"}
}