{
  "type": "Feature",
  "properties": {
    "gn:admin1_code":"61",
    "gn:admin2_code":"54.0",
    "gn:asciiname":"Laitekiai",
    "gn:country_code":"LT",
    "gn:dem":144,
    "gn:feature_class":"P",
    "gn:feature_code":"PPL",
    "gn:name":"Laitekiai",
    "gn:population":0,
    "gn:timezone":"Europe/Vilnius",
    "iso:country":"LT",
    "name:lit_x_preferred":[
        "Laitekiai"
    ],
    "wof:name":"Laitekiai",
    "wof:placetype":"locality"
},
  "geometry": {"coordinates":[22.67931,55.48115],"type":"Point"}
}