{
  "type": "Feature",
  "properties": {
    "iso:country":"LT",
    "name:ceb_x_preferred":[
        "Pilait\u0117"
    ],
    "name:dan_x_preferred":[
        "Pilait\u0117"
    ],
    "name:deu_x_preferred":[
        "Pilait\u0117"
    ],
    "name:eng_x_preferred":[
        "Pilait\u0117 eldership"
    ],
    "name:lav_x_preferred":[
        "Pilaite"
    ],
    "name:lit_x_preferred":[
        "Pilait\u0117"
    ],
    "name:lit_x_variant":[
        "Pilait\u0117s seni\u016bnija"
    ],
    "name:pol_x_preferred":[
        "Zameczek"
    ],
    "name:rus_x_preferred":[
        "\u041f\u0438\u043b\u0430\u0439\u0442\u0435"
    ],
    "name:spa_x_preferred":[
        "Distrito municipal de Pilait\u0117"
    ],
    "name:swe_x_preferred":[
        "Pilait\u0117"
    ],
    "name:und_x_preferred":[
        "Pilaite"
    ],
    "name:unk_x_variant":[
        "Pilaite"
    ],
    "qs:gn_adm0_cc":"LT",
    "qs:gn_local":593116,
    "qs:local_max":12571,
    "qs:local_sum":23762,
    "qs:localhoods":20,
    "qs:name":"Pilaite",
    "qs:name_adm0":"Lietuva",
    "qs:name_adm1":"Vilniaus Apskritis",
    "qs:name_adm2":"Vilniaus Miesto Savivaldybe",
    "qs:name_lau":"Vilnius",
    "qs:name_local":"Vilnius",
    "qs:photo_max":69,
    "qs:photo_sum":106,
    "qs:placetype":"Suburb",
    "qs:quad_count":20,
    "qs:woe_adm0":23424875,
    "qs:woe_adm1":55848083,
    "qs:woe_adm2":2346097,
    "qs:woe_lau":56044000,
    "qs:woe_local":479616,
    "qs:woe_ver":"7.10.0",
    "wd:wordcount":153,
    "wof:lang":[
        "unk"
    ],
    "wof:name":"Pilaite",
    "wof:placetype":"neighbourhood"
},
  "geometry": {"coordinates":[25.182761,54.706948],"type":"Point"}
}