{
  "type": "Feature",
  "properties": {
    "gn:admin1_code":"60",
    "gn:admin2_code":"57.0",
    "gn:asciiname":"Pocauskai",
    "gn:country_code":"LT",
    "gn:dem":96,
    "gn:feature_class":"P",
    "gn:feature_code":"PPL",
    "gn:name":"Pocauskai",
    "gn:population":0,
    "gn:timezone":"Europe/Vilnius",
    "iso:country":"LT",
    "name:lit_x_preferred":[
        "Pocauskai"
    ],
    "wof:name":"Pocauskai",
    "wof:placetype":"locality"
},
  "geometry": {"coordinates":[25.2753,55.85112],"type":"Point"}
}