{
  "type": "Feature",
  "properties": {
    "gn:admin1_code":"60",
    "gn:admin2_code":"36.0",
    "gn:asciiname":"Skrebiskiai",
    "gn:country_code":"LT",
    "gn:dem":55,
    "gn:feature_class":"P",
    "gn:feature_code":"PPL",
    "gn:name":"Skrebi\u0161kiai",
    "gn:population":0,
    "gn:timezone":"Europe/Vilnius",
    "iso:country":"LT",
    "name:lit_x_preferred":[
        "Skrebi\u0161kiai"
    ],
    "wof:name":"Skrebiskiai",
    "wof:placetype":"locality"
},
  "geometry": {"coordinates":[24.80926,56.24112],"type":"Point"}
}