{
  "type": "Feature",
  "properties": {
    "gn:admin1_code":"61",
    "gn:admin2_code":"65.0",
    "gn:asciiname":"Lapyne",
    "gn:country_code":"LT",
    "gn:dem":89,
    "gn:feature_class":"P",
    "gn:feature_code":"PPL",
    "gn:name":"Lapyn\u0117",
    "gn:population":0,
    "gn:timezone":"Europe/Vilnius",
    "iso:country":"LT",
    "name:lit_x_preferred":[
        "Lapyn\u0117"
    ],
    "wof:name":"Lapyne",
    "wof:placetype":"locality"
},
  "geometry": {"coordinates":[23.58003,55.97629000000001],"type":"Point"}
}