{
  "type": "Feature",
  "properties": {
    "gn:admin1_code":"65",
    "gn:admin2_code":"86.0",
    "gn:asciiname":"Skritutiske",
    "gn:country_code":"LT",
    "gn:dem":189,
    "gn:feature_class":"P",
    "gn:feature_code":"PPL",
    "gn:name":"Skrituti\u0161k\u0117",
    "gn:population":0,
    "gn:timezone":"Europe/Vilnius",
    "iso:country":"LT",
    "name:lit_x_preferred":[
        "Skrituti\u0161k\u0117"
    ],
    "wof:name":"Skritutiske",
    "wof:placetype":"locality"
},
  "geometry": {"coordinates":[26.18852,55.06027],"type":"Point"}
}