{
  "type": "Feature",
  "properties": {
    "gn:admin1_code":"0.0",
    "gn:asciiname":"Singaliai",
    "gn:cc2":"LT",
    "gn:country_code":"LT",
    "gn:dem":49,
    "gn:feature_class":"P",
    "gn:feature_code":"PPL",
    "gn:name":"\u0160ingaliai",
    "gn:population":0,
    "gn:timezone":"Europe/Vilnius",
    "iso:country":"LT",
    "name:und_x_variant":[
        "Pa\u017eiemkelys"
    ],
    "wof:name":"Singaliai",
    "wof:placetype":"locality"
},
  "geometry": {"coordinates":[23.86667000000001,55.28333000000001],"type":"Point"}
}