{
  "type": "Feature",
  "properties": {
    "gn:admin1_code":"65",
    "gn:admin2_code":"89.0",
    "gn:asciiname":"Sasnuvka",
    "gn:country_code":"LT",
    "gn:dem":112,
    "gn:feature_class":"P",
    "gn:feature_code":"PPL",
    "gn:name":"Sasnuvka",
    "gn:population":0,
    "gn:timezone":"Europe/Vilnius",
    "iso:country":"LT",
    "name:lit_x_preferred":[
        "Sasnuvka"
    ],
    "wof:name":"Sasnuvka",
    "wof:placetype":"locality"
},
  "geometry": {"coordinates":[24.87333,54.92154],"type":"Point"}
}