{
  "type": "Feature",
  "properties": {
    "gn:admin1_code":"61",
    "gn:admin2_code":"65.0",
    "gn:asciiname":"Laiskoniai",
    "gn:country_code":"LT",
    "gn:dem":62,
    "gn:feature_class":"P",
    "gn:feature_code":"PPL",
    "gn:name":"Lai\u0161koniai",
    "gn:population":0,
    "gn:timezone":"Europe/Vilnius",
    "iso:country":"LT",
    "name:lit_x_preferred":[
        "Lai\u0161koniai"
    ],
    "wof:name":"Laiskoniai",
    "wof:placetype":"locality"
},
  "geometry": {"coordinates":[24.01334,56.08869],"type":"Point"}
}