{
  "type": "Feature",
  "properties": {
    "gn:admin1_code":"60",
    "gn:admin2_code":"57.0",
    "gn:asciiname":"Azuvadziai",
    "gn:country_code":"LT",
    "gn:dem":95,
    "gn:feature_class":"P",
    "gn:feature_code":"PPL",
    "gn:name":"A\u017euvad\u017eiai",
    "gn:population":0,
    "gn:timezone":"Europe/Vilnius",
    "iso:country":"LT",
    "name:lit_x_preferred":[
        "A\u017euvad\u017eiai"
    ],
    "wof:name":"Azuvadziai",
    "wof:placetype":"locality"
},
  "geometry": {"coordinates":[25.26964,55.84551],"type":"Point"}
}