{
  "type": "Feature",
  "properties": {
    "gn:admin1_code":"64",
    "gn:admin2_code":"62.0",
    "gn:asciiname":"Sniegiskiai",
    "gn:country_code":"LT",
    "gn:dem":191,
    "gn:feature_class":"P",
    "gn:feature_code":"PPL",
    "gn:name":"Sniegi\u0161kiai",
    "gn:population":0,
    "gn:timezone":"Europe/Vilnius",
    "iso:country":"LT",
    "name:lit_x_preferred":[
        "Sniegi\u0161kiai"
    ],
    "wof:name":"Sniegiskiai",
    "wof:placetype":"locality"
},
  "geometry": {"coordinates":[25.34856,55.04733],"type":"Point"}
}