{
  "type": "Feature",
  "properties": {
    "gn:admin1_code":"61.0",
    "gn:admin2_code":"54.0",
    "gn:asciiname":"Miezaiciai",
    "gn:country_code":"LT",
    "gn:dem":143,
    "gn:feature_class":"P",
    "gn:feature_code":"PPL",
    "gn:name":"Mie\u017eai\u010diai",
    "gn:population":0,
    "gn:timezone":"Europe/Vilnius",
    "iso:country":"LT",
    "name:und_x_variant":[
        "Mezhayteli",
        "Mie\u017eai\u010diai"
    ],
    "wof:name":"Miezaiciai",
    "wof:placetype":"locality"
},
  "geometry": {"coordinates":[22.8878,55.70573],"type":"Point"}
}