{
  "type": "Feature",
  "properties": {
    "gn:admin1_code":"61.0",
    "gn:admin2_code":"65.0",
    "gn:asciiname":"Rusliai",
    "gn:country_code":"LT",
    "gn:dem":83,
    "gn:feature_class":"P",
    "gn:feature_code":"PPL",
    "gn:name":"Rusliai",
    "gn:population":0,
    "gn:timezone":"Europe/Vilnius",
    "iso:country":"LT",
    "name:und_x_variant":[
        "Ruslale",
        "Rusliai"
    ],
    "wof:name":"Rusliai",
    "wof:placetype":"locality"
},
  "geometry": {"coordinates":[23.59466,55.99881],"type":"Point"}
}