{
  "type": "Feature",
  "properties": {
    "gn:admin1_code":"64",
    "gn:admin2_code":"82.0",
    "gn:asciiname":"Utnele",
    "gn:country_code":"LT",
    "gn:dem":151,
    "gn:feature_class":"P",
    "gn:feature_code":"PPL",
    "gn:name":"Utn\u0117l\u0117",
    "gn:population":0,
    "gn:timezone":"Europe/Vilnius",
    "iso:country":"LT",
    "name:lit_x_preferred":[
        "Utn\u0117l\u0117"
    ],
    "wof:name":"Utnele",
    "wof:placetype":"locality"
},
  "geometry": {"coordinates":[25.50658,55.45223000000001],"type":"Point"}
}