{
  "type": "Feature",
  "properties": {
    "gn:admin1_code":"64",
    "gn:admin2_code":"34.0",
    "gn:asciiname":"Uzuoraistis",
    "gn:country_code":"LT",
    "gn:dem":130,
    "gn:feature_class":"P",
    "gn:feature_code":"PPL",
    "gn:name":"U\u017euoraistis",
    "gn:population":0,
    "gn:timezone":"Europe/Vilnius",
    "iso:country":"LT",
    "name:lit_x_preferred":[
        "U\u017euoraistis"
    ],
    "wof:name":"Uzuoraistis",
    "wof:placetype":"locality"
},
  "geometry": {"coordinates":[25.18387,55.41067],"type":"Point"}
}