{
  "type": "Feature",
  "properties": {
    "gn:admin1_code":"58.0",
    "gn:admin2_code":"88.0",
    "gn:asciiname":"Norkaiciai",
    "gn:country_code":"LT",
    "gn:dem":12,
    "gn:feature_class":"P",
    "gn:feature_code":"PPL",
    "gn:name":"Norkai\u010diai",
    "gn:population":0,
    "gn:timezone":"Europe/Vilnius",
    "iso:country":"LT",
    "name:lit_x_preferred":[
        "Norkai\u010diai"
    ],
    "wof:name":"Norkaiciai",
    "wof:placetype":"locality"
},
  "geometry": {"coordinates":[21.52391,55.44981],"type":"Point"}
}