{
  "type": "Feature",
  "properties": {
    "gn:admin1_code":"58.0",
    "gn:admin2_code":"56.0",
    "gn:asciiname":"Barzdziu Madsedziai",
    "gn:country_code":"LT",
    "gn:dem":55,
    "gn:feature_class":"P",
    "gn:feature_code":"PPL",
    "gn:name":"Barzd\u017ei\u0173 Mads\u0117d\u017eiai",
    "gn:population":0,
    "gn:timezone":"Europe/Vilnius",
    "iso:country":"LT",
    "name:lit_x_preferred":[
        "Barzd\u017ei\u0173 Mads\u0117d\u017eiai"
    ],
    "name:und_x_variant":[
        "Bordzie Miedsiedy",
        "Barzdzhyu Medsedzhyay",
        "Barzd\u017ei\u0173",
        "Barzd\u017ei\u0173 Meds\u0117d\u017eiai"
    ],
    "wof:name":"Barzdziu Madsedziai",
    "wof:placetype":"locality"
},
  "geometry": {"coordinates":[21.52778,56.04589],"type":"Point"}
}