{
  "type": "Feature",
  "properties": {
    "gn:admin1_code":"65",
    "gn:admin2_code":"13.0",
    "gn:asciiname":"Mykoliskes",
    "gn:country_code":"LT",
    "gn:dem":158,
    "gn:feature_class":"P",
    "gn:feature_code":"PPL",
    "gn:name":"Mykoli\u0161k\u0117s",
    "gn:population":0,
    "gn:timezone":"Europe/Vilnius",
    "iso:country":"LT",
    "name:lit_x_preferred":[
        "Mykoli\u0161k\u0117s"
    ],
    "wof:name":"Mykoliskes",
    "wof:placetype":"locality"
},
  "geometry": {"coordinates":[25.24339,54.8557],"type":"Point"}
}