{
  "type": "Feature",
  "properties": {
    "gn:admin1_code":"63.0",
    "gn:admin2_code":"61.0",
    "gn:asciiname":"Svirkanciai",
    "gn:country_code":"LT",
    "gn:dem":77,
    "gn:feature_class":"P",
    "gn:feature_code":"PPL",
    "gn:name":"Svirkan\u010diai",
    "gn:population":0,
    "gn:timezone":"Europe/Vilnius",
    "iso:country":"LT",
    "name:und_x_variant":[
        "Swirkonce",
        "Svirkan\u010di\u0173",
        "Svikanchay",
        "Svirkan\u010diai"
    ],
    "wof:name":"Svirkanciai",
    "wof:placetype":"locality"
},
  "geometry": {"coordinates":[22.52256,56.18339],"type":"Point"}
}