{
  "type": "Feature",
  "properties": {
    "gn:admin1_code":"61.0",
    "gn:admin2_code":"71.0",
    "gn:asciiname":"Liaudiskiai",
    "gn:country_code":"LT",
    "gn:dem":129,
    "gn:feature_class":"P",
    "gn:feature_code":"PPL",
    "gn:name":"Liaudi\u0161kiai",
    "gn:population":0,
    "gn:timezone":"Europe/Vilnius",
    "iso:country":"LT",
    "name:und_x_variant":[
        "Lyaudyshkyay",
        "Liaudi\u0161kiai"
    ],
    "wof:name":"Liaudiskiai",
    "wof:placetype":"locality"
},
  "geometry": {"coordinates":[23.69325,55.69969],"type":"Point"}
}