{
  "type": "Feature",
  "properties": {
    "gn:admin1_code":"62.0",
    "gn:admin2_code":"87.0",
    "gn:asciiname":"Guvainiai",
    "gn:country_code":"LT",
    "gn:dem":92,
    "gn:feature_class":"P",
    "gn:feature_code":"PPL",
    "gn:name":"G\u016bvainiai",
    "gn:population":0,
    "gn:timezone":"Europe/Vilnius",
    "iso:country":"LT",
    "name:lit_x_preferred":[
        "G\u016bvainiai"
    ],
    "name:und_x_variant":[
        "Guvayne",
        "Guvainiai"
    ],
    "wof:name":"Guvainiai",
    "wof:placetype":"locality"
},
  "geometry": {"coordinates":[22.04163,55.50484],"type":"Point"}
}