{
  "type": "Feature",
  "properties": {
    "gn:admin1_code":"61.0",
    "gn:admin2_code":"54.0",
    "gn:asciiname":"Padubysis",
    "gn:country_code":"LT",
    "gn:dem":73,
    "gn:feature_class":"P",
    "gn:feature_code":"PPL",
    "gn:name":"Padubysis",
    "gn:population":0,
    "gn:timezone":"Europe/Vilnius",
    "iso:country":"LT",
    "name:fra_x_preferred":[
        "Padubysis"
    ],
    "name:lit_x_preferred":[
        "Padubysis"
    ],
    "name:pol_x_preferred":[
        "Padubysis"
    ],
    "name:und_x_variant":[
        "Podubis\u2019",
        "Padubis",
        "Padubysis"
    ],
    "wof:name":"Padubysis",
    "wof:placetype":"locality"
},
  "geometry": {"coordinates":[23.07332,55.56388000000001],"type":"Point"}
}