{
  "type": "Feature",
  "properties": {
    "gn:admin1_code":"60",
    "gn:admin2_code":"36.0",
    "gn:asciiname":"Pakalnieciai",
    "gn:country_code":"LT",
    "gn:dem":31,
    "gn:feature_class":"P",
    "gn:feature_code":"PPL",
    "gn:name":"Pakalnie\u010diai",
    "gn:population":0,
    "gn:timezone":"Europe/Riga",
    "iso:country":"LT",
    "name:lit_x_preferred":[
        "Pakalnie\u010diai"
    ],
    "wof:name":"Pakalnieciai",
    "wof:placetype":"locality"
},
  "geometry": {"coordinates":[24.61445,56.3391],"type":"Point"}
}