{
  "type": "Feature",
  "properties": {
    "gn:admin1_code":"65.0",
    "gn:asciiname":"Sakiskes",
    "gn:country_code":"LT",
    "gn:dem":181,
    "gn:feature_class":"P",
    "gn:feature_code":"PPL",
    "gn:name":"Saki\u0161k\u0117s",
    "gn:population":0,
    "gn:timezone":"Europe/Vilnius",
    "iso:country":"LT",
    "wof:name":"Sakiskes",
    "wof:placetype":"locality"
},
  "geometry": {"coordinates":[25.372,54.952],"type":"Point"}
}