{
  "type": "Feature",
  "properties": {
    "gn:admin1_code":"65",
    "gn:admin2_code":"79.0",
    "gn:asciiname":"Vytautava",
    "gn:country_code":"LT",
    "gn:dem":175,
    "gn:feature_class":"P",
    "gn:feature_code":"PPL",
    "gn:name":"Vytautava",
    "gn:population":0,
    "gn:timezone":"Europe/Vilnius",
    "iso:country":"LT",
    "name:lit_x_preferred":[
        "Vytautava"
    ],
    "wof:name":"Vytautava",
    "wof:placetype":"locality"
},
  "geometry": {"coordinates":[24.71454,54.54581],"type":"Point"}
}