{
  "type": "Feature",
  "properties": {
    "gn:country":"LT",
    "gn:fcode":"PPL",
    "gn:population":0,
    "iso:country":"LT",
    "name:und_x_variant":[
        "Sausinink\u0173"
    ],
    "qs_pg:aaroncc":"LT",
    "qs_pg:gn_country":"LT",
    "qs_pg:gn_fcode":"PPL",
    "qs_pg:gn_pop":0,
    "qs_pg:name":"Sausininkai",
    "qs_pg:name_adm0":"Lietuva",
    "qs_pg:name_adm1":"Marijampol\u00ecs Apskritis",
    "qs_pg:photos":6,
    "qs_pg:photos_1k":1,
    "qs_pg:photos_9k":1,
    "qs_pg:photos_9r":1,
    "qs_pg:photos_all":6,
    "qs_pg:photos_sr":1,
    "qs_pg:pop_sr":0,
    "qs_pg:qs_pg_placetype":"locality",
    "qs_pg:qs_pg_placetype_gp":"Town",
    "qs_pg:woe_adm0":23424875,
    "woe:adm0_id":23424875,
    "woe:name_adm0":"Lietuva",
    "woe:name_adm1":"Marijampol\u00ecs Apskritis",
    "woe:placetype":"Town",
    "wof:name":"Sausininkai",
    "wof:placetype":"locality"
},
  "geometry": {"coordinates":[22.95611,54.51889],"type":"Point"}
}