{
  "type": "Feature",
  "properties": {
    "gn:admin1_code":"58.0",
    "gn:admin2_code":"88.0",
    "gn:asciiname":"Sysgiriai",
    "gn:country_code":"LT",
    "gn:dem":0,
    "gn:feature_class":"P",
    "gn:feature_code":"PPL",
    "gn:name":"\u0160y\u0161giriai",
    "gn:population":0,
    "gn:timezone":"Europe/Vilnius",
    "iso:country":"LT",
    "name:und_x_variant":[
        "Shishgiryay",
        "Shishgire",
        "\u0160y\u0161giriai"
    ],
    "wof:name":"Sysgiriai",
    "wof:placetype":"locality"
},
  "geometry": {"coordinates":[21.40462,55.34685],"type":"Point"}
}