{
  "type": "Feature",
  "properties": {
    "gn:admin1_code":"61.0",
    "gn:admin2_code":"54.0",
    "gn:asciiname":"Aukstiskiai",
    "gn:country_code":"LT",
    "gn:dem":133,
    "gn:feature_class":"P",
    "gn:feature_code":"PPL",
    "gn:name":"Auk\u0161ti\u0161kiai",
    "gn:population":0,
    "gn:timezone":"Europe/Vilnius",
    "iso:country":"LT",
    "name:eng_x_preferred":[
        "Auk\u0161ti\u0161kiai"
    ],
    "name:rus_x_preferred":[
        "\u0410\u0443\u043a\u0448\u0442\u0438\u0448\u043a\u044f\u0439"
    ],
    "name:und_x_variant":[
        "Aukshtishkyay",
        "Aukshtyshki",
        "Auk\u0161ti\u0161kiai"
    ],
    "wof:name":"Aukstiskiai",
    "wof:placetype":"locality"
},
  "geometry": {"coordinates":[23.22453,55.64529],"type":"Point"}
}