{
  "type": "Feature",
  "properties": {
    "gn:gn_country":"LT",
    "gn:gn_fcode":"PPL",
    "gn:gn_pop":0,
    "iso:country":"LT",
    "name:eng_x_preferred":[
        "\u017duvintai"
    ],
    "name:lit_x_preferred":[
        "\u017duvintai"
    ],
    "name:unk_x_variant":[
        "Zhuvinty"
    ],
    "qs_pg:aaroncc":"LT",
    "qs_pg:gn_country":"LT",
    "qs_pg:gn_fcode":"PPL",
    "qs_pg:gn_pop":0,
    "qs_pg:name":"\u017duvintai",
    "qs_pg:name_adm0":"Lietuva",
    "qs_pg:name_adm1":"Alytaus Apskritis",
    "qs_pg:photos":2,
    "qs_pg:photos_1k":1,
    "qs_pg:photos_9k":1,
    "qs_pg:photos_9r":1,
    "qs_pg:photos_all":2,
    "qs_pg:photos_sr":1,
    "qs_pg:pop_sr":0,
    "qs_pg:qs_pg_placetype":"locality",
    "qs_pg:qs_pg_placetype_gp":"Town",
    "qs_pg:woe_adm0":23424875,
    "woe:adm0_id":23424875,
    "woe:name_adm0":"Lietuva",
    "woe:name_adm1":"Alytaus Apskritis",
    "woe:placetype":"Town",
    "wof:name":"\u017duvintai",
    "wof:placetype":"locality"
},
  "geometry": {"coordinates":[23.61667,54.45],"type":"Point"}
}