{
  "type": "Feature",
  "properties": {
    "gn:admin1_code":"56",
    "gn:admin2_code":"11.0",
    "gn:asciiname":"Milastonys",
    "gn:country_code":"LT",
    "gn:dem":143,
    "gn:feature_class":"P",
    "gn:feature_code":"PPL",
    "gn:name":"Milastonys",
    "gn:population":0,
    "gn:timezone":"Europe/Vilnius",
    "iso:country":"LT",
    "name:lit_x_preferred":[
        "Milastonys"
    ],
    "wof:name":"Milastonys",
    "wof:placetype":"locality"
},
  "geometry": {"coordinates":[23.87088,54.28726],"type":"Point"}
}