{
  "type": "Feature",
  "properties": {
    "gn:admin1_code":"61",
    "gn:admin2_code":"54.0",
    "gn:asciiname":"Seveliske",
    "gn:country_code":"LT",
    "gn:dem":136,
    "gn:feature_class":"P",
    "gn:feature_code":"PPL",
    "gn:name":"\u0160eveli\u0161k\u0117",
    "gn:population":0,
    "gn:timezone":"Europe/Vilnius",
    "iso:country":"LT",
    "name:lit_x_preferred":[
        "\u0160eveli\u0161k\u0117"
    ],
    "wof:name":"Seveliske",
    "wof:placetype":"locality"
},
  "geometry": {"coordinates":[22.85956,55.70981999999999],"type":"Point"}
}