{
  "type": "Feature",
  "properties": {
    "gn:admin1_code":"65",
    "gn:admin2_code":"86.0",
    "gn:asciiname":"Akmenyne",
    "gn:country_code":"LT",
    "gn:dem":200,
    "gn:feature_class":"P",
    "gn:feature_code":"PPL",
    "gn:name":"Akmenyn\u0117",
    "gn:population":0,
    "gn:timezone":"Europe/Vilnius",
    "iso:country":"LT",
    "name:lit_x_preferred":[
        "Akmenyn\u0117"
    ],
    "wof:name":"Akmenyne",
    "wof:placetype":"locality"
},
  "geometry": {"coordinates":[26.19349,55.16193000000001],"type":"Point"}
}