{
  "type": "Feature",
  "properties": {
    "gn:admin1_code":"64",
    "gn:admin2_code":"43.0",
    "gn:asciiname":"Zirnajai",
    "gn:country_code":"LT",
    "gn:dem":123,
    "gn:feature_class":"P",
    "gn:feature_code":"PPL",
    "gn:name":"Zirnajai",
    "gn:population":0,
    "gn:timezone":"Europe/Vilnius",
    "iso:country":"LT",
    "name:lit_x_preferred":[
        "Zirnajai"
    ],
    "wof:name":"Zirnajai",
    "wof:placetype":"locality"
},
  "geometry": {"coordinates":[25.93715,55.8582],"type":"Point"}
}