{
  "type": "Feature",
  "properties": {
    "gn:admin1_code":"62.0",
    "gn:admin2_code":"77.0",
    "gn:asciiname":"Pavartis",
    "gn:country_code":"LT",
    "gn:dem":103,
    "gn:feature_class":"P",
    "gn:feature_code":"PPL",
    "gn:name":"Pavartis",
    "gn:population":0,
    "gn:timezone":"Europe/Vilnius",
    "iso:country":"LT",
    "name:und_x_variant":[
        "Pavart\u0117",
        "Pavart\u0117s",
        "Pavartis"
    ],
    "wof:name":"Pavartis",
    "wof:placetype":"locality"
},
  "geometry": {"coordinates":[22.49621,55.40991999999999],"type":"Point"}
}