{
  "type": "Feature",
  "properties": {
    "gn:admin1_code":"58.0",
    "gn:admin2_code":"21.0",
    "gn:asciiname":"Zvirbliai",
    "gn:country_code":"LT",
    "gn:dem":47,
    "gn:feature_class":"P",
    "gn:feature_code":"PPL",
    "gn:name":"\u017dvirbliai",
    "gn:population":0,
    "gn:timezone":"Europe/Vilnius",
    "iso:country":"LT",
    "name:und_x_variant":[
        "Zhvirbley",
        "\u017dvirbliai"
    ],
    "wof:name":"Zvirbliai",
    "wof:placetype":"locality"
},
  "geometry": {"coordinates":[21.35936,55.80011999999999],"type":"Point"}
}