{
  "type": "Feature",
  "properties": {
    "gn:admin1_code":"62.0",
    "gn:admin2_code":"87.0",
    "gn:asciiname":"Dargiai",
    "gn:country_code":"LT",
    "gn:dem":164,
    "gn:feature_class":"P",
    "gn:feature_code":"PPL",
    "gn:name":"Dargiai",
    "gn:population":0,
    "gn:timezone":"Europe/Vilnius",
    "iso:country":"LT",
    "name:und_x_variant":[
        "Podvernikay-Darzho",
        "Dargiai"
    ],
    "wof:name":"Dargiai",
    "wof:placetype":"locality"
},
  "geometry": {"coordinates":[22.31759,55.65416],"type":"Point"}
}