{
  "type": "Feature",
  "properties": {
    "gn:admin1_code":"60",
    "gn:admin2_code":"57.0",
    "gn:asciiname":"Simiskiai",
    "gn:country_code":"LT",
    "gn:dem":94,
    "gn:feature_class":"P",
    "gn:feature_code":"PPL",
    "gn:name":"\u0160imi\u0161kiai",
    "gn:population":0,
    "gn:timezone":"Europe/Vilnius",
    "iso:country":"LT",
    "name:lit_x_preferred":[
        "\u0160imi\u0161kiai"
    ],
    "wof:name":"Simiskiai",
    "wof:placetype":"locality"
},
  "geometry": {"coordinates":[25.19912,55.86919],"type":"Point"}
}