{
  "type": "Feature",
  "properties": {
    "gn:admin1_code":"61.0",
    "gn:admin2_code":"65.0",
    "gn:asciiname":"Dulkiskiai",
    "gn:country_code":"LT",
    "gn:dem":74,
    "gn:feature_class":"P",
    "gn:feature_code":"PPL",
    "gn:name":"Dulki\u0161kiai",
    "gn:population":0,
    "gn:timezone":"Europe/Vilnius",
    "iso:country":"LT",
    "name:und_x_variant":[
        "Dul\u2019kishkyay",
        "Dulki\u0161kiai"
    ],
    "wof:name":"Dulkiskiai",
    "wof:placetype":"locality"
},
  "geometry": {"coordinates":[23.84947,55.89097],"type":"Point"}
}