{
  "type": "Feature",
  "properties": {
    "gn:admin1_code":"58",
    "gn:admin2_code":"56.0",
    "gn:asciiname":"Salynas",
    "gn:country_code":"LT",
    "gn:dem":58,
    "gn:feature_class":"P",
    "gn:feature_code":"PPL",
    "gn:name":"\u0160alynas",
    "gn:population":0,
    "gn:timezone":"Europe/Vilnius",
    "iso:country":"LT",
    "name:lit_x_preferred":[
        "\u0160alynas"
    ],
    "wof:name":"Salynas",
    "wof:placetype":"locality"
},
  "geometry": {"coordinates":[21.51133,56.00469],"type":"Point"}
}