{
  "type": "Feature",
  "properties": {
    "gn:admin1_code":"65",
    "gn:admin2_code":"81.0",
    "gn:asciiname":"Daubariskiai",
    "gn:country_code":"LT",
    "gn:dem":145,
    "gn:feature_class":"P",
    "gn:feature_code":"PPL",
    "gn:name":"Daubari\u0161kiai",
    "gn:population":0,
    "gn:timezone":"Europe/Vilnius",
    "iso:country":"LT",
    "name:lit_x_preferred":[
        "Daubari\u0161kiai"
    ],
    "wof:name":"Daubariskiai",
    "wof:placetype":"locality"
},
  "geometry": {"coordinates":[25.15251,55.24884],"type":"Point"}
}