{
  "type": "Feature",
  "properties": {
    "gn:admin1_code":"64",
    "gn:admin2_code":"43.0",
    "gn:asciiname":"Raudondvaris",
    "gn:country_code":"LT",
    "gn:dem":175,
    "gn:feature_class":"P",
    "gn:feature_code":"PPL",
    "gn:name":"Raudondvaris",
    "gn:population":0,
    "gn:timezone":"Europe/Vilnius",
    "iso:country":"LT",
    "name:bel_x_preferred":[
        "\u0420\u0430\u045e\u0434\u043e\u043d\u0434\u0432\u0430\u0440\u044b\u0441"
    ],
    "name:deu_x_preferred":[
        "Raudondvaris"
    ],
    "name:est_x_preferred":[
        "Raudondvaris"
    ],
    "name:fin_x_preferred":[
        "Raudondvaris"
    ],
    "name:lit_x_preferred":[
        "Raudondvaris"
    ],
    "name:nld_x_preferred":[
        "Raudondvaris"
    ],
    "name:pol_x_preferred":[
        "Czerwony Dw\u00f3r"
    ],
    "name:rus_x_preferred":[
        "\u0420\u0430\u0443\u0434\u043e\u043d\u0434\u0432\u0430\u0440\u0438\u0441"
    ],
    "wof:name":"Raudondvaris",
    "wof:placetype":"locality"
},
  "geometry": {"coordinates":[26.26264,55.7561],"type":"Point"}
}