{
  "type": "Feature",
  "properties": {
    "gn:admin1_code":"60",
    "gn:admin2_code":"27.0",
    "gn:asciiname":"Savitiskis",
    "gn:country_code":"LT",
    "gn:dem":66,
    "gn:feature_class":"P",
    "gn:feature_code":"PPL",
    "gn:name":"Saviti\u0161kis",
    "gn:population":0,
    "gn:timezone":"Europe/Vilnius",
    "iso:country":"LT",
    "name:lit_x_preferred":[
        "Saviti\u0161kis"
    ],
    "wof:name":"Savitiskis",
    "wof:placetype":"locality"
},
  "geometry": {"coordinates":[23.97981,55.80218000000001],"type":"Point"}
}