{
  "type": "Feature",
  "properties": {
    "gn:admin1_code":"65",
    "gn:admin2_code":"85.0",
    "gn:asciiname":"Bruknyne",
    "gn:country_code":"LT",
    "gn:dem":183,
    "gn:feature_class":"P",
    "gn:feature_code":"PPL",
    "gn:name":"Bruknyn\u0117",
    "gn:population":0,
    "gn:timezone":"Europe/Vilnius",
    "iso:country":"LT",
    "name:lit_x_preferred":[
        "Bruknyn\u0117"
    ],
    "wof:name":"Bruknyne",
    "wof:placetype":"locality"
},
  "geometry": {"coordinates":[25.37407,54.35621999999999],"type":"Point"}
}