{
  "type": "Feature",
  "properties": {
    "gn:admin1_code":"57",
    "gn:admin2_code":"69.0",
    "gn:asciiname":"Obeline",
    "gn:country_code":"LT",
    "gn:dem":90,
    "gn:feature_class":"P",
    "gn:feature_code":"PPL",
    "gn:name":"Obelin\u0117",
    "gn:population":0,
    "gn:timezone":"Europe/Vilnius",
    "iso:country":"LT",
    "name:lit_x_preferred":[
        "Obelin\u0117"
    ],
    "wof:name":"Obeline",
    "wof:placetype":"locality"
},
  "geometry": {"coordinates":[23.67938,54.67205],"type":"Point"}
}