{
  "type": "Feature",
  "properties": {
    "gn:admin1_code":"64",
    "gn:admin2_code":"45.0",
    "gn:asciiname":"Saltiniai",
    "gn:country_code":"LT",
    "gn:dem":186,
    "gn:feature_class":"P",
    "gn:feature_code":"PPL",
    "gn:name":"\u0160altiniai",
    "gn:population":0,
    "gn:timezone":"Europe/Vilnius",
    "iso:country":"LT",
    "name:lit_x_preferred":[
        "\u0160altiniai"
    ],
    "wof:name":"Saltiniai",
    "wof:placetype":"locality"
},
  "geometry": {"coordinates":[26.38016,55.56339000000001],"type":"Point"}
}