{
  "type": "Feature",
  "properties": {
    "gn:admin1_code":"65",
    "gn:admin2_code":"13.0",
    "gn:asciiname":"Vaira",
    "gn:country_code":"LT",
    "gn:dem":133,
    "gn:feature_class":"P",
    "gn:feature_code":"PPL",
    "gn:name":"Vaira",
    "gn:population":0,
    "gn:timezone":"Europe/Vilnius",
    "iso:country":"LT",
    "name:lit_x_preferred":[
        "Vaira"
    ],
    "wof:name":"Vaira",
    "wof:placetype":"locality"
},
  "geometry": {"coordinates":[25.14486,54.47617],"type":"Point"}
}