{
  "type": "Feature",
  "properties": {
    "gn:admin1_code":"65.0",
    "gn:admin2_code":"85.0",
    "gn:asciiname":"Ciuronys",
    "gn:country_code":"LT",
    "gn:dem":147,
    "gn:feature_class":"P",
    "gn:feature_code":"PPL",
    "gn:name":"\u010ciuronys",
    "gn:population":0,
    "gn:timezone":"Europe/Vilnius",
    "iso:country":"LT",
    "name:lit_x_preferred":[
        "\u010ciuronys"
    ],
    "wof:name":"Ciuronys",
    "wof:placetype":"locality"
},
  "geometry": {"coordinates":[25.11613,54.28821],"type":"Point"}
}