{
  "type": "Feature",
  "properties": {
    "gn:admin1_code":"58",
    "gn:admin2_code":"21.0",
    "gn:asciiname":"Vistiskiai",
    "gn:country_code":"LT",
    "gn:dem":71,
    "gn:feature_class":"P",
    "gn:feature_code":"PPL",
    "gn:name":"Vi\u0161ti\u0161kiai",
    "gn:population":0,
    "gn:timezone":"Europe/Vilnius",
    "iso:country":"LT",
    "name:lit_x_preferred":[
        "Vi\u0161ti\u0161kiai"
    ],
    "wof:name":"Vistiskiai",
    "wof:placetype":"locality"
},
  "geometry": {"coordinates":[21.62227,55.62481999999999],"type":"Point"}
}