{
  "type": "Feature",
  "properties": {
    "gn:admin1_code":"64",
    "gn:admin2_code":"34.0",
    "gn:asciiname":"Pasusienys",
    "gn:country_code":"LT",
    "gn:dem":85,
    "gn:feature_class":"P",
    "gn:feature_code":"PPL",
    "gn:name":"Pasusienys",
    "gn:population":0,
    "gn:timezone":"Europe/Vilnius",
    "iso:country":"LT",
    "name:lit_x_preferred":[
        "Pasusienys"
    ],
    "wof:name":"Pasusienys",
    "wof:placetype":"locality"
},
  "geometry": {"coordinates":[24.98463,55.46849],"type":"Point"}
}