{
  "type": "Feature",
  "properties": {
    "gn:admin1_code":"64.0",
    "gn:admin2_code":"45.0",
    "gn:asciiname":"Siulenai",
    "gn:country_code":"LT",
    "gn:dem":178,
    "gn:feature_class":"P",
    "gn:feature_code":"PPL",
    "gn:name":"\u0160i\u016bl\u0117nai",
    "gn:population":0,
    "gn:timezone":"Europe/Vilnius",
    "iso:country":"LT",
    "name:lit_x_preferred":[
        "\u0160i\u016bl\u0117nai"
    ],
    "name:lit_x_variant":[
        "Siul\u0117nai"
    ],
    "wof:name":"Siulenai",
    "wof:placetype":"locality"
},
  "geometry": {"coordinates":[26.40152,55.33917],"type":"Point"}
}