{
  "type": "Feature",
  "properties": {
    "gn:admin1_code":"58.0",
    "gn:admin2_code":"75.0",
    "gn:asciiname":"Vindeikiai",
    "gn:country_code":"LT",
    "gn:dem":79,
    "gn:feature_class":"P",
    "gn:feature_code":"PPL",
    "gn:name":"Vindeikiai",
    "gn:population":0,
    "gn:timezone":"Europe/Vilnius",
    "iso:country":"LT",
    "name:und_x_variant":[
        "Vindeiki\u0173",
        "Windejki",
        "Vindeykyay",
        "Vindeikiai"
    ],
    "wof:name":"Vindeikiai",
    "wof:placetype":"locality"
},
  "geometry": {"coordinates":[21.6987,56.1322],"type":"Point"}
}