{
  "type": "Feature",
  "properties": {
    "gn:admin1_code":"56.0",
    "gn:admin2_code":"11.0",
    "gn:asciiname":"Laukinciai",
    "gn:country_code":"LT",
    "gn:dem":134,
    "gn:feature_class":"P",
    "gn:feature_code":"PPL",
    "gn:name":"Laukin\u010diai",
    "gn:population":0,
    "gn:timezone":"Europe/Vilnius",
    "iso:country":"LT",
    "name:und_x_variant":[
        "Lovkintany",
        "Laukin\u010di\u0173",
        "Laukinchyay",
        "Laukin\u010diai"
    ],
    "wof:name":"Laukinciai",
    "wof:placetype":"locality"
},
  "geometry": {"coordinates":[23.85801,54.35157],"type":"Point"}
}