{
  "type": "Feature",
  "properties": {
    "gn:admin1_code":"63",
    "gn:admin2_code":"74.0",
    "gn:asciiname":"Avizaiciai",
    "gn:country_code":"LT",
    "gn:dem":169,
    "gn:feature_class":"P",
    "gn:feature_code":"PPL",
    "gn:name":"Avi\u017eai\u010diai",
    "gn:population":0,
    "gn:timezone":"Europe/Vilnius",
    "iso:country":"LT",
    "name:lit_x_preferred":[
        "Avi\u017eai\u010diai"
    ],
    "wof:name":"Avizaiciai",
    "wof:placetype":"locality"
},
  "geometry": {"coordinates":[22.17877,55.79756999999999],"type":"Point"}
}