{
  "type": "Feature",
  "properties": {
    "gn:admin1_code":"65.0",
    "gn:admin2_code":"81.0",
    "gn:asciiname":"Savidonys",
    "gn:country_code":"LT",
    "gn:dem":91,
    "gn:feature_class":"P",
    "gn:feature_code":"PPL",
    "gn:name":"Savidonys",
    "gn:population":0,
    "gn:timezone":"Europe/Vilnius",
    "iso:country":"LT",
    "name:und_x_variant":[
        "Savidoni\u0173",
        "Savidonis",
        "Savidonys"
    ],
    "wof:name":"Savidonys",
    "wof:placetype":"locality"
},
  "geometry": {"coordinates":[24.69084,55.16734],"type":"Point"}
}