{
  "type": "Feature",
  "properties": {
    "gn:admin1_code":"57.0",
    "gn:admin2_code":"69.0",
    "gn:asciiname":"Alsininkai",
    "gn:country_code":"LT",
    "gn:dem":104,
    "gn:feature_class":"P",
    "gn:feature_code":"PPL",
    "gn:name":"Al\u0161ininkai",
    "gn:population":0,
    "gn:timezone":"Europe/Vilnius",
    "iso:country":"LT",
    "name:und_x_variant":[
        "Ol\u2019sheniki",
        "Al\u0161ininkai"
    ],
    "wof:name":"Alsininkai",
    "wof:placetype":"locality"
},
  "geometry": {"coordinates":[24.30989,54.65348],"type":"Point"}
}