{
  "type": "Feature",
  "properties": {
    "gn:admin1_code":"64",
    "gn:admin2_code":"82.0",
    "gn:asciiname":"Kavoliskis",
    "gn:country_code":"LT",
    "gn:dem":137,
    "gn:feature_class":"P",
    "gn:feature_code":"PPL",
    "gn:name":"Kavoli\u0161kis",
    "gn:population":0,
    "gn:timezone":"Europe/Vilnius",
    "iso:country":"LT",
    "name:lit_x_preferred":[
        "Kavoli\u0161kis"
    ],
    "wof:name":"Kavoliskis",
    "wof:placetype":"locality"
},
  "geometry": {"coordinates":[25.62938,55.55059],"type":"Point"}
}