{
  "type": "Feature",
  "properties": {
    "gn:admin1_code":"57",
    "gn:admin2_code":"72.0",
    "gn:asciiname":"Daugeliskiai",
    "gn:country_code":"LT",
    "gn:dem":72,
    "gn:feature_class":"P",
    "gn:feature_code":"PPL",
    "gn:name":"Daug\u0117li\u0161kiai",
    "gn:population":0,
    "gn:timezone":"Europe/Vilnius",
    "iso:country":"LT",
    "name:lit_x_preferred":[
        "Daug\u0117li\u0161kiai"
    ],
    "wof:name":"Daugeliskiai",
    "wof:placetype":"locality"
},
  "geometry": {"coordinates":[23.53263,55.22383000000001],"type":"Point"}
}