{
  "type": "Feature",
  "properties": {
    "gn:admin1_code":"0.0",
    "gn:asciiname":"Krantai",
    "gn:cc2":"LT",
    "gn:country_code":"LT",
    "gn:dem":109,
    "gn:feature_class":"P",
    "gn:feature_code":"PPL",
    "gn:name":"Krantai",
    "gn:population":0,
    "gn:timezone":"Europe/Vilnius",
    "iso:country":"LT",
    "name:und_x_variant":[
        "Krentaguray",
        "Krantagura",
        "Krentagura",
        "Krantai"
    ],
    "wof:name":"Krantai",
    "wof:placetype":"locality"
},
  "geometry": {"coordinates":[23.05,55.51667],"type":"Point"}
}