{
  "type": "Feature",
  "properties": {
    "gn:admin1_code":"57",
    "gn:admin2_code":"72.0",
    "gn:asciiname":"Smulkines",
    "gn:country_code":"LT",
    "gn:dem":114,
    "gn:feature_class":"P",
    "gn:feature_code":"PPL",
    "gn:name":"Smulkin\u0117s",
    "gn:population":0,
    "gn:timezone":"Europe/Vilnius",
    "iso:country":"LT",
    "name:lit_x_preferred":[
        "Smulkin\u0117s"
    ],
    "wof:name":"Smulkines",
    "wof:placetype":"locality"
},
  "geometry": {"coordinates":[22.82633,55.4712],"type":"Point"}
}