{
  "type": "Feature",
  "properties": {
    "gn:admin1_code":"62.0",
    "gn:admin2_code":"77.0",
    "gn:asciiname":"Lengveniai",
    "gn:country_code":"LT",
    "gn:dem":43,
    "gn:feature_class":"P",
    "gn:feature_code":"PPL",
    "gn:name":"Lengveniai",
    "gn:population":0,
    "gn:timezone":"Europe/Vilnius",
    "iso:country":"LT",
    "name:lit_x_preferred":[
        "Lengveniai"
    ],
    "name:und_x_variant":[
        "Lenaveniai"
    ],
    "wof:name":"Lengveniai",
    "wof:placetype":"locality"
},
  "geometry": {"coordinates":[22.23318,55.29534],"type":"Point"}
}