{
  "type": "Feature",
  "properties": {
    "gn:admin1_code":"0.0",
    "gn:asciiname":"Pagramdiskiai",
    "gn:cc2":"LT",
    "gn:country_code":"LT",
    "gn:dem":56,
    "gn:feature_class":"P",
    "gn:feature_code":"PPL",
    "gn:name":"Pagramdi\u0161kiai",
    "gn:population":0,
    "gn:timezone":"Europe/Vilnius",
    "iso:country":"LT",
    "name:und_x_variant":[
        "Pagramdishkes",
        "Pagramdi\u0161kiai"
    ],
    "wof:name":"Pagramdiskiai",
    "wof:placetype":"locality"
},
  "geometry": {"coordinates":[23.08333,54.66667],"type":"Point"}
}