{
  "type": "Feature",
  "properties": {
    "gn:admin1_code":"65.0",
    "gn:admin2_code":"85.0",
    "gn:asciiname":"Juskiai",
    "gn:country_code":"LT",
    "gn:dem":211,
    "gn:feature_class":"P",
    "gn:feature_code":"PPL",
    "gn:name":"Ju\u0161kiai",
    "gn:population":0,
    "gn:timezone":"Europe/Vilnius",
    "iso:country":"LT",
    "name:lit_x_preferred":[
        "Ju\u0161kiai"
    ],
    "wof:name":"Juskiai",
    "wof:placetype":"locality"
},
  "geometry": {"coordinates":[25.58239,54.45472],"type":"Point"}
}