{
  "type": "Feature",
  "properties": {
    "gn:admin1_code":"61",
    "gn:admin2_code":"32.0",
    "gn:asciiname":"Pagame",
    "gn:country_code":"LT",
    "gn:dem":97,
    "gn:feature_class":"P",
    "gn:feature_code":"PPL",
    "gn:name":"Pagam\u0117",
    "gn:population":0,
    "gn:timezone":"Europe/Vilnius",
    "iso:country":"LT",
    "name:lit_x_preferred":[
        "Pagam\u0117"
    ],
    "wof:name":"Pagame",
    "wof:placetype":"locality"
},
  "geometry": {"coordinates":[22.85896,56.12566999999999],"type":"Point"}
}