{
  "type": "Feature",
  "properties": {
    "gn:admin1_code":"57.0",
    "gn:admin2_code":"53.0",
    "gn:asciiname":"Paobelys",
    "gn:country_code":"LT",
    "gn:dem":30,
    "gn:feature_class":"P",
    "gn:feature_code":"PPL",
    "gn:name":"Paobelys",
    "gn:population":0,
    "gn:timezone":"Europe/Vilnius",
    "iso:country":"LT",
    "name:und_x_variant":[
        "Paobyalis",
        "Paobelys"
    ],
    "wof:name":"Paobelys",
    "wof:placetype":"locality"
},
  "geometry": {"coordinates":[23.96885,55.26421],"type":"Point"}
}