{
  "type": "Feature",
  "properties": {
    "gn:admin1_code":"61",
    "gn:admin2_code":"65.0",
    "gn:asciiname":"Lasmenpamusis",
    "gn:country_code":"LT",
    "gn:dem":51,
    "gn:feature_class":"P",
    "gn:feature_code":"PPL",
    "gn:name":"La\u0161menpam\u016b\u0161is",
    "gn:population":0,
    "gn:timezone":"Europe/Vilnius",
    "iso:country":"LT",
    "name:lit_x_preferred":[
        "La\u0161menpam\u016b\u0161is"
    ],
    "wof:name":"Lasmenpamusis",
    "wof:placetype":"locality"
},
  "geometry": {"coordinates":[23.98477,56.02903000000001],"type":"Point"}
}