{
  "type": "Feature",
  "properties": {
    "gn:admin1_code":"64.0",
    "gn:admin2_code":"43.0",
    "gn:asciiname":"Raistiniskes",
    "gn:country_code":"LT",
    "gn:dem":161,
    "gn:feature_class":"P",
    "gn:feature_code":"PPL",
    "gn:name":"Raistini\u0161k\u0117s",
    "gn:population":0,
    "gn:timezone":"Europe/Vilnius",
    "iso:country":"LT",
    "name:und_x_variant":[
        "Raystinishkes",
        "Raistini\u0161ki\u0173",
        "Raistini\u0161k\u0117s"
    ],
    "wof:name":"Raistiniskes",
    "wof:placetype":"locality"
},
  "geometry": {"coordinates":[26.07844,55.67777],"type":"Point"}
}