{
  "type": "Feature",
  "properties": {
    "gn:admin1_code":"64.0",
    "gn:admin2_code":"45.0",
    "gn:asciiname":"Didziasalis",
    "gn:country_code":"LT",
    "gn:dem":137,
    "gn:feature_class":"P",
    "gn:feature_code":"PPL",
    "gn:name":"Did\u017eiasalis",
    "gn:population":0,
    "gn:timezone":"Europe/Vilnius",
    "iso:country":"LT",
    "name:und_x_variant":[
        "Vel\u2019ka Ves\u2019",
        "Didzhyasalis",
        "Did\u017eiasalis"
    ],
    "wof:name":"Didziasalis",
    "wof:placetype":"locality"
},
  "geometry": {"coordinates":[26.67469,55.31861],"type":"Point"}
}