{
  "type": "Feature",
  "properties": {
    "gn:admin1_code":"64.0",
    "gn:admin2_code":"45.0",
    "gn:asciiname":"Didziasalis",
    "gn:country_code":"LT",
    "gn:dem":137,
    "gn:feature_class":"P",
    "gn:feature_code":"PPL",
    "gn:name":"Did\u017eiasalis",
    "gn:population":0,
    "gn:timezone":"Europe/Vilnius",
    "iso:country":"LT",
    "name:bel_x_preferred":[
        "\u0414\u0437\u0456\u0434\u0436\u0430\u0441\u0430\u043b\u0456\u0441"
    ],
    "name:ceb_x_preferred":[
        "Did\u017eiasalis"
    ],
    "name:ita_x_preferred":[
        "Did\u017eiasalis"
    ],
    "name:lit_x_preferred":[
        "Did\u017eiasalis"
    ],
    "name:pol_x_preferred":[
        "Wielka Wie\u015b"
    ],
    "name:rus_x_preferred":[
        "\u0414\u0438\u0434\u0436\u044f\u0441\u0430\u043b\u0438\u0441"
    ],
    "name:swe_x_preferred":[
        "Did\u017eiasalis"
    ],
    "name:und_x_variant":[
        "Vel\u2019ka Ves\u2019",
        "Didzhyasalis"
    ],
    "wof:name":"Didziasalis",
    "wof:placetype":"locality"
},
  "geometry": {"coordinates":[26.67469,55.31861],"type":"Point"}
}