{
  "type": "Feature",
  "properties": {
    "gn:admin1_code":"57",
    "gn:admin2_code":"72.0",
    "gn:asciiname":"Papusynys",
    "gn:country_code":"LT",
    "gn:dem":126,
    "gn:feature_class":"P",
    "gn:feature_code":"PPL",
    "gn:name":"Papu\u0161ynys",
    "gn:population":0,
    "gn:timezone":"Europe/Vilnius",
    "iso:country":"LT",
    "name:lit_x_preferred":[
        "Papu\u0161ynys"
    ],
    "wof:name":"Papusynys",
    "wof:placetype":"locality"
},
  "geometry": {"coordinates":[23.43674,55.47609],"type":"Point"}
}