{
  "type": "Feature",
  "properties": {
    "gn:admin1_code":"57.0",
    "gn:admin2_code":"49.0",
    "gn:asciiname":"Pasuliai",
    "gn:country_code":"LT",
    "gn:dem":81,
    "gn:feature_class":"P",
    "gn:feature_code":"PPL",
    "gn:name":"Pa\u0161uliai",
    "gn:population":0,
    "gn:timezone":"Europe/Vilnius",
    "iso:country":"LT",
    "name:und_x_variant":[
        "Poshule",
        "Pa\u0161uliai"
    ],
    "wof:name":"Pasuliai",
    "wof:placetype":"locality"
},
  "geometry": {"coordinates":[24.30892,54.91784000000001],"type":"Point"}
}