{
  "type": "Feature",
  "properties": {
    "gn:admin1_code":"64",
    "gn:admin2_code":"34.0",
    "gn:asciiname":"Azupieciai",
    "gn:country_code":"LT",
    "gn:dem":103,
    "gn:feature_class":"P",
    "gn:feature_code":"PPL",
    "gn:name":"A\u017eupie\u010diai",
    "gn:population":0,
    "gn:timezone":"Europe/Vilnius",
    "iso:country":"LT",
    "name:lit_x_preferred":[
        "A\u017eupie\u010diai"
    ],
    "wof:name":"Azupieciai",
    "wof:placetype":"locality"
},
  "geometry": {"coordinates":[25.07519,55.55692],"type":"Point"}
}