{
  "type": "Feature",
  "properties": {
    "gn:admin1_code":"61.0",
    "gn:admin2_code":"54.0",
    "gn:asciiname":"Maldagine",
    "gn:country_code":"LT",
    "gn:dem":146,
    "gn:feature_class":"P",
    "gn:feature_code":"PPL",
    "gn:name":"Maldagin\u0117",
    "gn:population":0,
    "gn:timezone":"Europe/Vilnius",
    "iso:country":"LT",
    "name:lit_x_preferred":[
        "Maldagin\u0117"
    ],
    "wof:name":"Maldagine",
    "wof:placetype":"locality"
},
  "geometry": {"coordinates":[22.68902000000001,55.66513000000001],"type":"Point"}
}