{
  "type": "Feature",
  "properties": {
    "gn:admin1_code":"64.0",
    "gn:admin2_code":"34.0",
    "gn:asciiname":"Piktagalys",
    "gn:country_code":"LT",
    "gn:dem":98,
    "gn:feature_class":"P",
    "gn:feature_code":"PPL",
    "gn:name":"Piktagalys",
    "gn:population":0,
    "gn:timezone":"Europe/Vilnius",
    "iso:country":"LT",
    "name:und_x_variant":[
        "Piktagalio",
        "Piktagalis",
        "Piktagalys"
    ],
    "wof:name":"Piktagalys",
    "wof:placetype":"locality"
},
  "geometry": {"coordinates":[25.01223,55.53817],"type":"Point"}
}