{
  "type": "Feature",
  "properties": {
    "gn:admin1_code":"57",
    "gn:admin2_code":"69.0",
    "gn:asciiname":"Naujasis Mikaliskis",
    "gn:country_code":"LT",
    "gn:dem":112,
    "gn:feature_class":"P",
    "gn:feature_code":"PPL",
    "gn:name":"Naujasis Mikali\u0161kis",
    "gn:population":0,
    "gn:timezone":"Europe/Vilnius",
    "iso:country":"LT",
    "name:lit_x_preferred":[
        "Naujasis Mikali\u0161kis"
    ],
    "wof:name":"Naujasis Mikaliskis",
    "wof:placetype":"locality"
},
  "geometry": {"coordinates":[23.68332,54.62441999999999],"type":"Point"}
}