{
  "type": "Feature",
  "properties": {
    "gn:admin1_code":"56",
    "gn:admin2_code":"59.0",
    "gn:asciiname":"Nasutai",
    "gn:country_code":"LT",
    "gn:dem":126,
    "gn:feature_class":"P",
    "gn:feature_code":"PPL",
    "gn:name":"Nas\u016btai",
    "gn:population":0,
    "gn:timezone":"Europe/Vilnius",
    "iso:country":"LT",
    "name:lit_x_preferred":[
        "Nas\u016btai"
    ],
    "wof:name":"Nasutai",
    "wof:placetype":"locality"
},
  "geometry": {"coordinates":[23.62295,54.02518000000001],"type":"Point"}
}