{
  "type": "Feature",
  "properties": {
    "gn:admin1_code":"65",
    "gn:admin2_code":"85.0",
    "gn:asciiname":"Misiucenai",
    "gn:country_code":"LT",
    "gn:dem":177,
    "gn:feature_class":"P",
    "gn:feature_code":"PPL",
    "gn:name":"Misiu\u010d\u0117nai",
    "gn:population":0,
    "gn:timezone":"Europe/Vilnius",
    "iso:country":"LT",
    "name:lit_x_preferred":[
        "Misiu\u010d\u0117nai"
    ],
    "wof:name":"Misiucenai",
    "wof:placetype":"locality"
},
  "geometry": {"coordinates":[25.4758,54.4742],"type":"Point"}
}