{
  "type": "Feature",
  "properties": {
    "gn:admin1_code":"60",
    "gn:admin2_code":"73.0",
    "gn:asciiname":"Bernotiskis",
    "gn:country_code":"LT",
    "gn:dem":126,
    "gn:feature_class":"P",
    "gn:feature_code":"PPL",
    "gn:name":"Bernoti\u0161kis",
    "gn:population":0,
    "gn:timezone":"Europe/Vilnius",
    "iso:country":"LT",
    "name:lit_x_preferred":[
        "Bernoti\u0161kis"
    ],
    "wof:name":"Bernotiskis",
    "wof:placetype":"locality"
},
  "geometry": {"coordinates":[25.51799,55.90389],"type":"Point"}
}