{
  "type": "Feature",
  "properties": {
    "gn:admin1_code":"63",
    "gn:admin2_code":"78.0",
    "gn:asciiname":"Sodale",
    "gn:country_code":"LT",
    "gn:dem":171,
    "gn:feature_class":"P",
    "gn:feature_code":"PPL",
    "gn:name":"Sodal\u0117",
    "gn:population":0,
    "gn:timezone":"Europe/Vilnius",
    "iso:country":"LT",
    "name:lit_x_preferred":[
        "Sodal\u0117"
    ],
    "wof:name":"Sodale",
    "wof:placetype":"locality"
},
  "geometry": {"coordinates":[22.25546,55.90039],"type":"Point"}
}