{
  "type": "Feature",
  "properties": {
    "gn:admin1_code":"60",
    "gn:admin2_code":"57.0",
    "gn:asciiname":"Daukuteliai",
    "gn:country_code":"LT",
    "gn:dem":86,
    "gn:feature_class":"P",
    "gn:feature_code":"PPL",
    "gn:name":"Daukut\u0117liai",
    "gn:population":0,
    "gn:timezone":"Europe/Vilnius",
    "iso:country":"LT",
    "name:lit_x_preferred":[
        "Daukut\u0117liai"
    ],
    "wof:name":"Daukuteliai",
    "wof:placetype":"locality"
},
  "geometry": {"coordinates":[24.971,55.90444],"type":"Point"}
}