{
  "type": "Feature",
  "properties": {
    "gn:admin1_code":"56",
    "gn:admin2_code":"11.0",
    "gn:asciiname":"Liesionys",
    "gn:country_code":"LT",
    "gn:dem":159,
    "gn:feature_class":"P",
    "gn:feature_code":"PPL",
    "gn:name":"Liesionys",
    "gn:population":0,
    "gn:timezone":"Europe/Vilnius",
    "iso:country":"LT",
    "name:lit_x_preferred":[
        "Liesionys"
    ],
    "wof:name":"Liesionys",
    "wof:placetype":"locality"
},
  "geometry": {"coordinates":[24.37079,54.47668],"type":"Point"}
}