{
  "type": "Feature",
  "properties": {
    "gn:admin1_code":"59",
    "gn:admin2_code":"58.0",
    "gn:asciiname":"Bundziskes",
    "gn:country_code":"LT",
    "gn:dem":74,
    "gn:feature_class":"P",
    "gn:feature_code":"PPL",
    "gn:name":"Bundzi\u0161k\u0117s",
    "gn:population":0,
    "gn:timezone":"Europe/Vilnius",
    "iso:country":"LT",
    "name:lit_x_preferred":[
        "Bundzi\u0161k\u0117s"
    ],
    "wof:name":"Bundziskes",
    "wof:placetype":"locality"
},
  "geometry": {"coordinates":[23.62217,54.73578000000001],"type":"Point"}
}