{
  "type": "Feature",
  "properties": {
    "gn:admin1_code":"65.0",
    "gn:admin2_code":"86.0",
    "gn:asciiname":"Rakauskai",
    "gn:country_code":"LT",
    "gn:dem":164,
    "gn:feature_class":"P",
    "gn:feature_code":"PPL",
    "gn:name":"Rakauskai",
    "gn:population":0,
    "gn:timezone":"Europe/Vilnius",
    "iso:country":"LT",
    "name:lit_x_preferred":[
        "Rakauskai"
    ],
    "wof:name":"Rakauskai",
    "wof:placetype":"locality"
},
  "geometry": {"coordinates":[26.48896,55.19929000000001],"type":"Point"}
}