{
  "type": "Feature",
  "properties": {
    "gn:admin1_code":"64",
    "gn:admin2_code":"34.0",
    "gn:asciiname":"Zerkiskiai",
    "gn:country_code":"LT",
    "gn:dem":82,
    "gn:feature_class":"P",
    "gn:feature_code":"PPL",
    "gn:name":"\u017derki\u0161kiai",
    "gn:population":0,
    "gn:timezone":"Europe/Vilnius",
    "iso:country":"LT",
    "name:lit_x_preferred":[
        "\u017derki\u0161kiai"
    ],
    "wof:name":"Zerkiskiai",
    "wof:placetype":"locality"
},
  "geometry": {"coordinates":[24.7797,55.53327],"type":"Point"}
}