{
  "type": "Feature",
  "properties": {
    "gn:admin1_code":"0.0",
    "gn:asciiname":"Slabada",
    "gn:country_code":"LT",
    "gn:dem":69,
    "gn:feature_class":"P",
    "gn:feature_code":"PPL",
    "gn:name":"Slabada",
    "gn:population":0,
    "gn:timezone":"Europe/Vilnius",
    "iso:country":"LT",
    "wof:name":"Slabada",
    "wof:placetype":"locality"
},
  "geometry": {"coordinates":[24.58333,55.14],"type":"Point"}
}