{
  "type": "Feature",
  "properties": {
    "gn:admin1_code":"65",
    "gn:admin2_code":"13.0",
    "gn:asciiname":"Liepalotai",
    "gn:country_code":"LT",
    "gn:dem":146,
    "gn:feature_class":"P",
    "gn:feature_code":"PPL",
    "gn:name":"Liepalotai",
    "gn:population":0,
    "gn:timezone":"Europe/Vilnius",
    "iso:country":"LT",
    "name:lit_x_preferred":[
        "Liepalotai"
    ],
    "wof:name":"Liepalotai",
    "wof:placetype":"locality"
},
  "geometry": {"coordinates":[25.44063,54.84453000000001],"type":"Point"}
}