{
  "type": "Feature",
  "properties": {
    "gn:admin1_code":"61.0",
    "gn:admin2_code":"71.0",
    "gn:asciiname":"Pociunai",
    "gn:country_code":"LT",
    "gn:dem":71,
    "gn:feature_class":"P",
    "gn:feature_code":"PPL",
    "gn:name":"Poci\u016bnai",
    "gn:population":0,
    "gn:timezone":"Europe/Vilnius",
    "iso:country":"LT",
    "name:lit_x_preferred":[
        "Poci\u016bnai"
    ],
    "name:pol_x_preferred":[
        "Poci\u016bnai"
    ],
    "name:und_x_variant":[
        "Poci\u016bnai"
    ],
    "wof:name":"Pociunai",
    "wof:placetype":"locality"
},
  "geometry": {"coordinates":[23.94354,55.78682],"type":"Point"}
}