{
  "type": "Feature",
  "properties": {
    "gn:admin1_code":"65",
    "gn:admin2_code":"85.0",
    "gn:asciiname":"Azumedis",
    "gn:country_code":"LT",
    "gn:dem":229,
    "gn:feature_class":"P",
    "gn:feature_code":"PPL",
    "gn:name":"A\u017eumedis",
    "gn:population":0,
    "gn:timezone":"Europe/Vilnius",
    "iso:country":"LT",
    "name:lit_x_preferred":[
        "A\u017eumedis"
    ],
    "wof:name":"Azumedis",
    "wof:placetype":"locality"
},
  "geometry": {"coordinates":[25.60669,54.30164],"type":"Point"}
}