{
  "type": "Feature",
  "properties": {
    "gn:admin1_code":"60",
    "gn:admin2_code":"73.0",
    "gn:asciiname":"Ruksiai",
    "gn:country_code":"LT",
    "gn:dem":105,
    "gn:feature_class":"P",
    "gn:feature_code":"PPL",
    "gn:name":"Ruk\u0161iai",
    "gn:population":0,
    "gn:timezone":"Europe/Vilnius",
    "iso:country":"LT",
    "name:lit_x_preferred":[
        "Ruk\u0161iai"
    ],
    "wof:name":"Ruksiai",
    "wof:placetype":"locality"
},
  "geometry": {"coordinates":[25.40864,55.8856],"type":"Point"}
}