{
  "type": "Feature",
  "properties": {
    "gn:admin1_code":"62.0",
    "gn:admin2_code":"87.0",
    "gn:asciiname":"Drobuksciai",
    "gn:country_code":"LT",
    "gn:dem":105,
    "gn:feature_class":"P",
    "gn:feature_code":"PPL",
    "gn:name":"Drob\u016bk\u0161\u010diai",
    "gn:population":0,
    "gn:timezone":"Europe/Vilnius",
    "iso:country":"LT",
    "name:und_x_variant":[
        "Drobukshchyay",
        "Drob\u016bkstaliai",
        "Drobukshnay",
        "Drobuk\u0161\u010di\u0173",
        "Drob\u016bk\u0161\u010diai"
    ],
    "wof:name":"Drobuksciai",
    "wof:placetype":"locality"
},
  "geometry": {"coordinates":[22.03698,55.52578000000001],"type":"Point"}
}