{
  "type": "Feature",
  "properties": {
    "gn:admin1_code":"57.0",
    "gn:admin2_code":"49.0",
    "gn:asciiname":"Sepijoniskes",
    "gn:country_code":"LT",
    "gn:dem":179,
    "gn:feature_class":"P",
    "gn:feature_code":"PPL",
    "gn:name":"Sepijoni\u0161k\u0117s",
    "gn:population":0,
    "gn:timezone":"Europe/Vilnius",
    "iso:country":"LT",
    "name:lit_x_preferred":[
        "Sepijoni\u0161k\u0117s"
    ],
    "wof:name":"Sepijoniskes",
    "wof:placetype":"locality"
},
  "geometry": {"coordinates":[24.41148,54.65583],"type":"Point"}
}