{
  "type": "Feature",
  "properties": {
    "gn:admin1_code":"61",
    "gn:admin2_code":"32.0",
    "gn:asciiname":"Skretiske",
    "gn:country_code":"LT",
    "gn:dem":72,
    "gn:feature_class":"P",
    "gn:feature_code":"PPL",
    "gn:name":"Skreti\u0161k\u0117",
    "gn:population":0,
    "gn:timezone":"Europe/Vilnius",
    "iso:country":"LT",
    "name:lit_x_preferred":[
        "Skreti\u0161k\u0117"
    ],
    "wof:name":"Skretiske",
    "wof:placetype":"locality"
},
  "geometry": {"coordinates":[22.69241,56.22815],"type":"Point"}
}