{
  "type": "Feature",
  "properties": {
    "gn:admin1_code":"65",
    "gn:admin2_code":"13.0",
    "gn:asciiname":"Klimoniskes",
    "gn:country_code":"LT",
    "gn:dem":120,
    "gn:feature_class":"P",
    "gn:feature_code":"PPL",
    "gn:name":"Klimoni\u0161k\u0117s",
    "gn:population":0,
    "gn:timezone":"Europe/Vilnius",
    "iso:country":"LT",
    "name:lit_x_preferred":[
        "Klimoni\u0161k\u0117s"
    ],
    "wof:name":"Klimoniskes",
    "wof:placetype":"locality"
},
  "geometry": {"coordinates":[24.98014,54.80373],"type":"Point"}
}