{
  "type": "Feature",
  "properties": {
    "gn:admin1_code":"60",
    "gn:admin2_code":"36.0",
    "gn:asciiname":"Jasiuliskiai",
    "gn:country_code":"LT",
    "gn:dem":59,
    "gn:feature_class":"P",
    "gn:feature_code":"PPL",
    "gn:name":"Jasiuli\u0161kiai",
    "gn:population":0,
    "gn:timezone":"Europe/Vilnius",
    "iso:country":"LT",
    "name:lit_x_preferred":[
        "Jasiuli\u0161kiai"
    ],
    "wof:name":"Jasiuliskiai",
    "wof:placetype":"locality"
},
  "geometry": {"coordinates":[24.70726,56.02923000000001],"type":"Point"}
}