{
  "type": "Feature",
  "properties": {
    "gn:admin1_code":"64",
    "gn:admin2_code":"34.0",
    "gn:asciiname":"Saviciunai",
    "gn:country_code":"LT",
    "gn:dem":136,
    "gn:feature_class":"P",
    "gn:feature_code":"PPL",
    "gn:name":"Savi\u010di\u016bnai",
    "gn:population":0,
    "gn:timezone":"Europe/Vilnius",
    "iso:country":"LT",
    "name:lit_x_preferred":[
        "Savi\u010di\u016bnai"
    ],
    "wof:name":"Saviciunai",
    "wof:placetype":"locality"
},
  "geometry": {"coordinates":[25.44623,55.7102],"type":"Point"}
}