{
  "type": "Feature",
  "properties": {
    "gn:admin1_code":"65",
    "gn:admin2_code":"86.0",
    "gn:asciiname":"Velianka",
    "gn:country_code":"LT",
    "gn:dem":164,
    "gn:feature_class":"P",
    "gn:feature_code":"PPL",
    "gn:name":"Velianka",
    "gn:population":0,
    "gn:timezone":"Europe/Vilnius",
    "iso:country":"LT",
    "name:lit_x_preferred":[
        "Velianka"
    ],
    "wof:name":"Velianka",
    "wof:placetype":"locality"
},
  "geometry": {"coordinates":[25.58254,55.01631999999999],"type":"Point"}
}