{
  "type": "Feature",
  "properties": {
    "gn:admin1_code":"60.0",
    "gn:admin2_code":"73.0",
    "gn:asciiname":"Buivenai",
    "gn:country_code":"LT",
    "gn:dem":96,
    "gn:feature_class":"P",
    "gn:feature_code":"PPL",
    "gn:name":"Buiv\u0117nai",
    "gn:population":0,
    "gn:timezone":"Europe/Vilnius",
    "iso:country":"LT",
    "name:lit_x_preferred":[
        "Buiv\u0117nai"
    ],
    "wof:name":"Buivenai",
    "wof:placetype":"locality"
},
  "geometry": {"coordinates":[25.18039,56.01514],"type":"Point"}
}