{
  "type": "Feature",
  "properties": {
    "gn:admin1_code":"64",
    "gn:admin2_code":"62.0",
    "gn:asciiname":"Likiskis",
    "gn:country_code":"LT",
    "gn:dem":156,
    "gn:feature_class":"P",
    "gn:feature_code":"PPL",
    "gn:name":"Liki\u0161kis",
    "gn:population":0,
    "gn:timezone":"Europe/Vilnius",
    "iso:country":"LT",
    "name:lit_x_preferred":[
        "Liki\u0161kis"
    ],
    "wof:name":"Likiskis",
    "wof:placetype":"locality"
},
  "geometry": {"coordinates":[25.56863,55.23438],"type":"Point"}
}