{
  "type": "Feature",
  "properties": {
    "gn:admin1_code":"62",
    "gn:admin2_code":"77.0",
    "gn:asciiname":"Girzadai",
    "gn:country_code":"LT",
    "gn:dem":103,
    "gn:feature_class":"P",
    "gn:feature_code":"PPL",
    "gn:name":"Gir\u017eadai",
    "gn:population":0,
    "gn:timezone":"Europe/Vilnius",
    "iso:country":"LT",
    "name:lit_x_preferred":[
        "Gir\u017eadai"
    ],
    "wof:name":"Girzadai",
    "wof:placetype":"locality"
},
  "geometry": {"coordinates":[22.62582,55.40338000000001],"type":"Point"}
}