{
  "type": "Feature",
  "properties": {
    "gn:admin1_code":"64",
    "gn:admin2_code":"34.0",
    "gn:asciiname":"Sestokiskiai",
    "gn:country_code":"LT",
    "gn:dem":83,
    "gn:feature_class":"P",
    "gn:feature_code":"PPL",
    "gn:name":"\u0160e\u0161toki\u0161kiai",
    "gn:population":0,
    "gn:timezone":"Europe/Vilnius",
    "iso:country":"LT",
    "name:lit_x_preferred":[
        "\u0160e\u0161toki\u0161kiai"
    ],
    "wof:name":"Sestokiskiai",
    "wof:placetype":"locality"
},
  "geometry": {"coordinates":[24.98227,55.45766],"type":"Point"}
}