{
  "type": "Feature",
  "properties": {
    "gn:admin1_code":"60",
    "gn:admin2_code":"73.0",
    "gn:asciiname":"Juozapava",
    "gn:country_code":"LT",
    "gn:dem":140,
    "gn:feature_class":"P",
    "gn:feature_code":"PPL",
    "gn:name":"Juozapava",
    "gn:population":0,
    "gn:timezone":"Europe/Vilnius",
    "iso:country":"LT",
    "name:lit_x_preferred":[
        "Juozapava"
    ],
    "wof:name":"Juozapava",
    "wof:placetype":"locality"
},
  "geometry": {"coordinates":[25.63837,55.9869],"type":"Point"}
}