{
  "type": "Feature",
  "properties": {
    "gn:admin1_code":"63",
    "gn:admin2_code":"78.0",
    "gn:asciiname":"Skliausciai",
    "gn:country_code":"LT",
    "gn:dem":133,
    "gn:feature_class":"P",
    "gn:feature_code":"PPL",
    "gn:name":"Skliaus\u010diai",
    "gn:population":0,
    "gn:timezone":"Europe/Vilnius",
    "iso:country":"LT",
    "name:lit_x_preferred":[
        "Skliaus\u010diai"
    ],
    "wof:name":"Skliausciai",
    "wof:placetype":"locality"
},
  "geometry": {"coordinates":[22.41957,55.86731999999999],"type":"Point"}
}