{
  "type": "Feature",
  "properties": {
    "gn:admin1_code":"65.0",
    "gn:admin2_code":"13.0",
    "gn:asciiname":"Lankeliai",
    "gn:country_code":"LT",
    "gn:dem":215,
    "gn:feature_class":"P",
    "gn:feature_code":"PPL",
    "gn:name":"Lankeliai",
    "gn:population":0,
    "gn:timezone":"Europe/Vilnius",
    "iso:country":"LT",
    "name:lit_x_preferred":[
        "Lankeliai"
    ],
    "wof:name":"Lankeliai",
    "wof:placetype":"locality"
},
  "geometry": {"coordinates":[25.56796,54.56818000000001],"type":"Point"}
}