{
  "type": "Feature",
  "properties": {
    "gn:admin1_code":"64",
    "gn:admin2_code":"45.0",
    "gn:asciiname":"Antakmene",
    "gn:country_code":"LT",
    "gn:dem":177,
    "gn:feature_class":"P",
    "gn:feature_code":"PPL",
    "gn:name":"Antakmen\u0117",
    "gn:population":0,
    "gn:timezone":"Europe/Vilnius",
    "iso:country":"LT",
    "name:lit_x_preferred":[
        "Antakmen\u0117"
    ],
    "wof:name":"Antakmene",
    "wof:placetype":"locality"
},
  "geometry": {"coordinates":[26.25064,55.44058],"type":"Point"}
}