{
  "type": "Feature",
  "properties": {
    "gn:admin1_code":"58.0",
    "gn:admin2_code":"21.0",
    "gn:asciiname":"Azpurviai",
    "gn:country_code":"LT",
    "gn:dem":20,
    "gn:feature_class":"P",
    "gn:feature_code":"PPL",
    "gn:name":"A\u017epurviai",
    "gn:population":0,
    "gn:timezone":"Europe/Vilnius",
    "iso:country":"LT",
    "name:lit_x_preferred":[
        "A\u017epurviai"
    ],
    "name:und_x_variant":[
        "Ashpurven",
        "A\u0161purviai"
    ],
    "wof:name":"Azpurviai",
    "wof:placetype":"locality"
},
  "geometry": {"coordinates":[21.44865,55.57556999999999],"type":"Point"}
}