{
  "type": "Feature",
  "properties": {
    "gn:admin1_code":"65.0",
    "gn:admin2_code":"81.0",
    "gn:asciiname":"Baleliai",
    "gn:country_code":"LT",
    "gn:dem":85,
    "gn:feature_class":"P",
    "gn:feature_code":"PPL",
    "gn:name":"Baleliai",
    "gn:population":0,
    "gn:timezone":"Europe/Vilnius",
    "iso:country":"LT",
    "name:und_x_variant":[
        "Balelyay",
        "Boleli",
        "Baleliai Pirmieji",
        "Baleliai"
    ],
    "wof:name":"Baleliai",
    "wof:placetype":"locality"
},
  "geometry": {"coordinates":[24.7134,55.45814],"type":"Point"}
}