{
  "type": "Feature",
  "properties": {
    "gn:admin1_code":"56.0",
    "gn:admin2_code":"15.0",
    "gn:asciiname":"Naujasode",
    "gn:country_code":"LT",
    "gn:dem":102,
    "gn:feature_class":"P",
    "gn:feature_code":"PPL",
    "gn:name":"Naujasod\u0117",
    "gn:population":0,
    "gn:timezone":"Europe/Vilnius",
    "iso:country":"LT",
    "name:lit_x_preferred":[
        "Naujasod\u0117"
    ],
    "name:und_x_variant":[
        "Naujasodis"
    ],
    "wof:name":"Naujasode",
    "wof:placetype":"locality"
},
  "geometry": {"coordinates":[24.0415,53.98996],"type":"Point"}
}