{
  "type": "Feature",
  "properties": {
    "gn:admin1_code":"56",
    "gn:admin2_code":"59.0",
    "gn:asciiname":"Janciuliai",
    "gn:country_code":"LT",
    "gn:dem":112,
    "gn:feature_class":"P",
    "gn:feature_code":"PPL",
    "gn:name":"Jan\u010diuliai",
    "gn:population":0,
    "gn:timezone":"Europe/Vilnius",
    "iso:country":"LT",
    "name:lit_x_preferred":[
        "Jan\u010diuliai"
    ],
    "wof:name":"Janciuliai",
    "wof:placetype":"locality"
},
  "geometry": {"coordinates":[23.68837000000001,54.00071],"type":"Point"}
}