{
  "type": "Feature",
  "properties": {
    "gn:admin1_code":"60.0",
    "gn:admin2_code":"36.0",
    "gn:asciiname":"Valiuliskiai",
    "gn:country_code":"LT",
    "gn:dem":85,
    "gn:feature_class":"P",
    "gn:feature_code":"PPL",
    "gn:name":"Valiuli\u0161kiai",
    "gn:population":0,
    "gn:timezone":"Europe/Vilnius",
    "iso:country":"LT",
    "name:und_x_variant":[
        "Valyulishkyay",
        "Valiuli\u0161ki\u0173",
        "Valiuli\u0161kiai"
    ],
    "wof:name":"Valiuliskiai",
    "wof:placetype":"locality"
},
  "geometry": {"coordinates":[25.07632000000001,56.02437],"type":"Point"}
}