{
  "type": "Feature",
  "properties": {
    "gn:admin1_code":"60.0",
    "gn:admin2_code":"36.0",
    "gn:asciiname":"Kupreliskis",
    "gn:country_code":"LT",
    "gn:dem":78,
    "gn:feature_class":"P",
    "gn:feature_code":"PPL",
    "gn:name":"Kupreli\u0161kis",
    "gn:population":0,
    "gn:timezone":"Europe/Vilnius",
    "iso:country":"LT",
    "name:ceb_x_preferred":[
        "Kupreli\u0161kis"
    ],
    "name:eng_x_preferred":[
        "Kupreli\u0161kis"
    ],
    "name:est_x_preferred":[
        "Kupreli\u0161kis"
    ],
    "name:lit_x_preferred":[
        "Kupreli\u0161kis"
    ],
    "name:nld_x_preferred":[
        "Kupreli\u0161kis"
    ],
    "name:pol_x_preferred":[
        "Kupreliszki"
    ],
    "name:rus_x_preferred":[
        "\u041a\u0443\u043f\u0440\u044f\u043b\u0438\u0448\u043a\u0438\u0441"
    ],
    "name:swe_x_preferred":[
        "Kupreli\u0161kis"
    ],
    "name:und_x_variant":[
        "Kuprelishkis",
        "Kupreli\u0161kio",
        "Kupryalishkis"
    ],
    "wof:name":"Kupreliskis",
    "wof:placetype":"locality"
},
  "geometry": {"coordinates":[24.96358,56.04123000000001],"type":"Point"}
}