{
  "type": "Feature",
  "properties": {
    "gn:admin1_code":"63",
    "gn:admin2_code":"68.0",
    "gn:asciiname":"Lekeme",
    "gn:country_code":"LT",
    "gn:dem":118,
    "gn:feature_class":"P",
    "gn:feature_code":"PPL",
    "gn:name":"Lekem\u0117",
    "gn:population":0,
    "gn:timezone":"Europe/Vilnius",
    "iso:country":"LT",
    "name:lit_x_preferred":[
        "Lekem\u0117"
    ],
    "wof:name":"Lekeme",
    "wof:placetype":"locality"
},
  "geometry": {"coordinates":[21.85894,55.85466],"type":"Point"}
}