{
  "type": "Feature",
  "properties": {
    "gn:admin1_code":"64",
    "gn:admin2_code":"45.0",
    "gn:asciiname":"Vaitiske",
    "gn:country_code":"LT",
    "gn:dem":153,
    "gn:feature_class":"P",
    "gn:feature_code":"PPL",
    "gn:name":"Vaitisk\u0117",
    "gn:population":0,
    "gn:timezone":"Europe/Vilnius",
    "iso:country":"LT",
    "name:lit_x_preferred":[
        "Vaitisk\u0117"
    ],
    "wof:name":"Vaitiske",
    "wof:placetype":"locality"
},
  "geometry": {"coordinates":[26.54065,55.44945],"type":"Point"}
}