{
  "type": "Feature",
  "properties": {
    "gn:admin1_code":"57",
    "gn:admin2_code":"69.0",
    "gn:asciiname":"Buntiskes",
    "gn:country_code":"LT",
    "gn:dem":164,
    "gn:feature_class":"P",
    "gn:feature_code":"PPL",
    "gn:name":"Bunti\u0161k\u0117s",
    "gn:population":0,
    "gn:timezone":"Europe/Vilnius",
    "iso:country":"LT",
    "name:lit_x_preferred":[
        "Bunti\u0161k\u0117s"
    ],
    "wof:name":"Buntiskes",
    "wof:placetype":"locality"
},
  "geometry": {"coordinates":[24.3861,54.64222],"type":"Point"}
}