{
  "type": "Feature",
  "properties": {
    "gn:admin1_code":"61",
    "gn:admin2_code":"47.0",
    "gn:asciiname":"Kulpiai",
    "gn:country_code":"LT",
    "gn:dem":37,
    "gn:feature_class":"P",
    "gn:feature_code":"PPL",
    "gn:name":"Kulpiai",
    "gn:population":0,
    "gn:timezone":"Europe/Vilnius",
    "iso:country":"LT",
    "name:lit_x_preferred":[
        "Kulpiai"
    ],
    "wof:name":"Kulpiai",
    "wof:placetype":"locality"
},
  "geometry": {"coordinates":[23.69929,56.36365],"type":"Point"}
}