{
  "type": "Feature",
  "properties": {
    "gn:admin1_code":"64",
    "gn:admin2_code":"43.0",
    "gn:asciiname":"Klabutka",
    "gn:country_code":"LT",
    "gn:dem":135,
    "gn:feature_class":"P",
    "gn:feature_code":"PPL",
    "gn:name":"Klabutka",
    "gn:population":0,
    "gn:timezone":"Europe/Riga",
    "iso:country":"LT",
    "name:lit_x_preferred":[
        "Klabutka"
    ],
    "wof:name":"Klabutka",
    "wof:placetype":"locality"
},
  "geometry": {"coordinates":[26.51509,55.67817],"type":"Point"}
}