{
  "type": "Feature",
  "properties": {
    "gn:admin1_code":"65",
    "gn:admin2_code":"85.0",
    "gn:asciiname":"Maciunai",
    "gn:country_code":"LT",
    "gn:dem":170,
    "gn:feature_class":"P",
    "gn:feature_code":"PPL",
    "gn:name":"Maci\u016bnai",
    "gn:population":0,
    "gn:timezone":"Europe/Vilnius",
    "iso:country":"LT",
    "name:lit_x_preferred":[
        "Maci\u016bnai"
    ],
    "wof:name":"Maciunai",
    "wof:placetype":"locality"
},
  "geometry": {"coordinates":[25.16086,54.23267],"type":"Point"}
}