{
  "type": "Feature",
  "properties": {
    "gn:admin1_code":"57.0",
    "gn:admin2_code":"53.0",
    "gn:asciiname":"Dotnuvos Gelezinkelo Stotis",
    "gn:country_code":"LT",
    "gn:dem":66,
    "gn:feature_class":"P",
    "gn:feature_code":"PPL",
    "gn:name":"Dotnuvos Gele\u017einkelo Stotis",
    "gn:population":0,
    "gn:timezone":"Europe/Vilnius",
    "iso:country":"LT",
    "name:lit_x_preferred":[
        "Dotnuvos Gele\u017einkelo Stotis"
    ],
    "name:lit_x_variant":[
        "Gele\u017einkelo Stotis Dotnuva"
    ],
    "name:und_x_variant":[
        "Stantsiya Datnovo",
        "Stotis Dotnuva",
        "Dotnuva"
    ],
    "wof:name":"Dotnuvos Gelezinkelo Stotis",
    "wof:placetype":"locality"
},
  "geometry": {"coordinates":[23.87593,55.40633],"type":"Point"}
}