{
  "type": "Feature",
  "properties": {
    "gn:admin1_code":"57",
    "gn:admin2_code":"12.0",
    "gn:asciiname":"Zvirgzdenai",
    "gn:country_code":"LT",
    "gn:dem":88,
    "gn:feature_class":"P",
    "gn:feature_code":"PPL",
    "gn:name":"\u017dvirg\u017ed\u0117nai",
    "gn:population":0,
    "gn:timezone":"Europe/Vilnius",
    "iso:country":"LT",
    "name:lit_x_preferred":[
        "\u017dvirg\u017ed\u0117nai"
    ],
    "wof:name":"Zvirgzdenai",
    "wof:placetype":"locality"
},
  "geometry": {"coordinates":[24.08965,54.57898],"type":"Point"}
}