{
  "type": "Feature",
  "properties": {
    "gn:country":"LT",
    "gn:fcode":"PPL",
    "gn:population":0,
    "iso:country":"LT",
    "name:eng_x_preferred":[
        "Paupiai"
    ],
    "name:lit_x_preferred":[
        "Paupiai"
    ],
    "name:nld_x_preferred":[
        "Paupiai"
    ],
    "name:sgs_x_preferred":[
        "Paop\u0113"
    ],
    "qs_pg:aaroncc":"LT",
    "qs_pg:gn_country":"LT",
    "qs_pg:gn_fcode":"PPL",
    "qs_pg:gn_pop":0,
    "qs_pg:name":"Paupiai",
    "qs_pg:name_adm0":"Lietuva",
    "qs_pg:name_adm1":"Klaip\u00ecdos Apskritis",
    "qs_pg:photos":19,
    "qs_pg:photos_1k":4,
    "qs_pg:photos_9k":1,
    "qs_pg:photos_9r":1,
    "qs_pg:photos_all":19,
    "qs_pg:photos_sr":1,
    "qs_pg:pop_sr":0,
    "qs_pg:qs_pg_placetype":"locality",
    "qs_pg:qs_pg_placetype_gp":"Town",
    "qs_pg:woe_adm0":23424875,
    "woe:adm0_id":23424875,
    "woe:name_adm0":"Lietuva",
    "woe:name_adm1":"Klaip\u00ecdos Apskritis",
    "woe:placetype":"Town",
    "wof:name":"Paupiai",
    "wof:placetype":"locality"
},
  "geometry": {"coordinates":[21.13333,55.71667],"type":"Point"}
}