{
  "type": "Feature",
  "properties": {
    "gn:admin1_code":"57.0",
    "gn:admin2_code":"49.0",
    "gn:asciiname":"Navasodai",
    "gn:country_code":"LT",
    "gn:dem":109,
    "gn:feature_class":"P",
    "gn:feature_code":"PPL",
    "gn:name":"Navasodai",
    "gn:population":0,
    "gn:timezone":"Europe/Vilnius",
    "iso:country":"LT",
    "name:lit_x_preferred":[
        "Navasodai"
    ],
    "name:und_x_variant":[
        "Nauyasodis",
        "Novosady",
        "Naujasodis"
    ],
    "wof:name":"Navasodai",
    "wof:placetype":"locality"
},
  "geometry": {"coordinates":[24.52225,54.88612],"type":"Point"}
}