{
  "type": "Feature",
  "properties": {
    "gn:admin1_code":"64.0",
    "gn:admin2_code":"34.0",
    "gn:asciiname":"Rudzionys",
    "gn:country_code":"LT",
    "gn:dem":100,
    "gn:feature_class":"P",
    "gn:feature_code":"PPL",
    "gn:name":"Rud\u017eionys",
    "gn:population":0,
    "gn:timezone":"Europe/Vilnius",
    "iso:country":"LT",
    "name:und_x_variant":[
        "Rudzhenyay",
        "Rud\u017eioniai",
        "Rudzyany",
        "Rud\u017eionys"
    ],
    "wof:name":"Rudzionys",
    "wof:placetype":"locality"
},
  "geometry": {"coordinates":[24.968,55.58748000000001],"type":"Point"}
}