{
  "type": "Feature",
  "properties": {
    "gn:admin1_code":"59.0",
    "gn:admin2_code":"39.0",
    "gn:asciiname":"Budvieciai",
    "gn:country_code":"LT",
    "gn:dem":112,
    "gn:feature_class":"P",
    "gn:feature_code":"PPL",
    "gn:name":"B\u016bdvie\u010diai",
    "gn:population":0,
    "gn:timezone":"Europe/Vilnius",
    "iso:country":"LT",
    "name:und_x_variant":[
        "Budvetse",
        "B\u016bdvie\u010di\u0173",
        "B\u016bdvie\u010diai"
    ],
    "wof:name":"Budvieciai",
    "wof:placetype":"locality"
},
  "geometry": {"coordinates":[23.12109,54.53218],"type":"Point"}
}