{
  "type": "Feature",
  "properties": {
    "gn:admin1_code":"64",
    "gn:admin2_code":"43.0",
    "gn:asciiname":"Matuliskes",
    "gn:country_code":"LT",
    "gn:dem":137,
    "gn:feature_class":"P",
    "gn:feature_code":"PPL",
    "gn:name":"Matuli\u0161k\u0117s",
    "gn:population":0,
    "gn:timezone":"Europe/Vilnius",
    "iso:country":"LT",
    "name:lit_x_preferred":[
        "Matuli\u0161k\u0117s"
    ],
    "wof:name":"Matuliskes",
    "wof:placetype":"locality"
},
  "geometry": {"coordinates":[26.29912,55.72668],"type":"Point"}
}