{
  "type": "Feature",
  "properties": {
    "gn:admin1_code":"62.0",
    "gn:admin2_code":"94.0",
    "gn:asciiname":"Zubrickai",
    "gn:country_code":"LT",
    "gn:dem":69,
    "gn:feature_class":"P",
    "gn:feature_code":"PPL",
    "gn:name":"Zubrickai",
    "gn:population":0,
    "gn:timezone":"Europe/Vilnius",
    "iso:country":"LT",
    "name:und_x_variant":[
        "Zubriai"
    ],
    "wof:name":"Zubrickai",
    "wof:placetype":"locality"
},
  "geometry": {"coordinates":[23.25605,55.17954],"type":"Point"}
}