{
  "type": "Feature",
  "properties": {
    "iso:country":"LT",
    "name:dan_x_preferred":[
        "Paneriai"
    ],
    "name:deu_x_preferred":[
        "Auk\u0161tieji Paneriai"
    ],
    "name:deu_x_variant":[
        "Paneriai"
    ],
    "name:eng_x_preferred":[
        "Paneriai"
    ],
    "name:est_x_preferred":[
        "Paneriai"
    ],
    "name:fra_x_preferred":[
        "Paneriai"
    ],
    "name:heb_x_preferred":[
        "\u05e4\u05d5\u05e0\u05d0\u05e8"
    ],
    "name:hye_x_preferred":[
        "\u0531\u0578\u0582\u056f\u0577\u057f\u0565\u0575\u056b \u054a\u0561\u0576\u0575\u0561\u0580\u0575\u0561\u0575"
    ],
    "name:jpn_x_preferred":[
        "\u30d1\u30cd\u30ea\u30a2\u30a4"
    ],
    "name:lav_x_preferred":[
        "Paneri"
    ],
    "name:lit_x_preferred":[
        "Auk\u0161tieji Paneriai"
    ],
    "name:lit_x_variant":[
        "Paneriai",
        "Paneri\u0173 seni\u016bnija"
    ],
    "name:nld_x_preferred":[
        "Paneriai"
    ],
    "name:pol_x_preferred":[
        "Ponary"
    ],
    "name:rus_x_preferred":[
        "\u0410\u0443\u043a\u0448\u0442\u0435\u0439\u0438-\u041f\u0430\u043d\u044f\u0440\u044f\u0439"
    ],
    "name:rus_x_variant":[
        "\u041f\u0430\u043d\u0435\u0440\u044f\u0439"
    ],
    "name:swe_x_preferred":[
        "Paneriai"
    ],
    "name:und_x_preferred":[
        "Paneriai"
    ],
    "name:unk_x_variant":[
        "Dvaras Paneriai",
        "Paneriai"
    ],
    "name:yid_x_preferred":[
        "\u05e4\u05d0\u05e0\u05d0\u05e8"
    ],
    "qs:gn_adm0_cc":"LT",
    "qs:gn_fcode":"PPL",
    "qs:gn_local":593116,
    "qs:gn_namadm1":"00",
    "qs:gn_name":"Paneriai",
    "qs:local_max":12571,
    "qs:local_sum":23762,
    "qs:localhoods":20,
    "qs:name":"Paneriai",
    "qs:name_adm0":"Lietuva",
    "qs:name_adm1":"Vilniaus Apskritis",
    "qs:name_adm2":"Vilniaus Miesto Savivaldybe",
    "qs:name_lau":"Vilnius",
    "qs:name_local":"Vilnius",
    "qs:photo_max":41,
    "qs:photo_sum":164,
    "qs:placetype":"Suburb",
    "qs:quad_count":25,
    "qs:woe_adm0":23424875,
    "qs:woe_adm1":55848083,
    "qs:woe_adm2":2346097,
    "qs:woe_lau":56044000,
    "qs:woe_local":479616,
    "qs:woe_ver":"7.10.0",
    "wd:wordcount":558,
    "wof:lang":[
        "unk"
    ],
    "wof:name":"Aukstieji Paneriai",
    "wof:placetype":"neighbourhood"
},
  "geometry": {"coordinates":[25.174049,54.629101],"type":"Point"}
}