{
  "type": "Feature",
  "properties": {
    "gn:admin1_code":"0.0",
    "gn:asciiname":"Pilioniai",
    "gn:country_code":"LT",
    "gn:dem":81,
    "gn:feature_class":"P",
    "gn:feature_code":"PPL",
    "gn:name":"Pilioniai",
    "gn:population":0,
    "gn:timezone":"Europe/Vilnius",
    "iso:country":"LT",
    "name:lit_x_preferred":[
        "Pilioniai"
    ],
    "name:und_x_variant":[
        "Pilioni\u0173",
        "Pilyany",
        "Pilionai"
    ],
    "wof:name":"Pilioniai",
    "wof:placetype":"locality"
},
  "geometry": {"coordinates":[23.79685,55.47911],"type":"Point"}
}