{
  "type": "Feature",
  "properties": {
    "gn:admin1_code":"64",
    "gn:admin2_code":"45.0",
    "gn:asciiname":"Simoniskis I",
    "gn:country_code":"LT",
    "gn:dem":149,
    "gn:feature_class":"P",
    "gn:feature_code":"PPL",
    "gn:name":"Simoni\u0161kis I",
    "gn:population":0,
    "gn:timezone":"Europe/Vilnius",
    "iso:country":"LT",
    "name:lit_x_preferred":[
        "Simoni\u0161kis I"
    ],
    "wof:name":"Simoniskis I",
    "wof:placetype":"locality"
},
  "geometry": {"coordinates":[26.00961,55.30291999999999],"type":"Point"}
}