{
  "type": "Feature",
  "properties": {
    "gn:admin1_code":"61.0",
    "gn:admin2_code":"29.0",
    "gn:asciiname":"Pakarciunai",
    "gn:country_code":"LT",
    "gn:dem":112,
    "gn:feature_class":"P",
    "gn:feature_code":"PPL",
    "gn:name":"Pakar\u010di\u016bnai",
    "gn:population":0,
    "gn:timezone":"Europe/Vilnius",
    "iso:country":"LT",
    "name:und_x_variant":[
        "Pokarne",
        "Pakar\u010di\u016bnai"
    ],
    "wof:name":"Pakarciunai",
    "wof:placetype":"locality"
},
  "geometry": {"coordinates":[23.31003,55.98417],"type":"Point"}
}