{
  "type": "Feature",
  "properties": {
    "gn:admin1_code":"58",
    "gn:admin2_code":"88.0",
    "gn:asciiname":"Stirpeikos",
    "gn:country_code":"LT",
    "gn:dem":38,
    "gn:feature_class":"P",
    "gn:feature_code":"PPL",
    "gn:name":"Stirpeikos",
    "gn:population":0,
    "gn:timezone":"Europe/Vilnius",
    "iso:country":"LT",
    "name:lit_x_preferred":[
        "Stirpeikos"
    ],
    "wof:name":"Stirpeikos",
    "wof:placetype":"locality"
},
  "geometry": {"coordinates":[21.59217,55.53205],"type":"Point"}
}