{
  "type": "Feature",
  "properties": {
    "gn:admin1_code":"60",
    "gn:admin2_code":"57.0",
    "gn:asciiname":"Mantvydai",
    "gn:country_code":"LT",
    "gn:dem":83,
    "gn:feature_class":"P",
    "gn:feature_code":"PPL",
    "gn:name":"Mantvydai",
    "gn:population":0,
    "gn:timezone":"Europe/Vilnius",
    "iso:country":"LT",
    "name:lit_x_preferred":[
        "Mantvydai"
    ],
    "wof:name":"Mantvydai",
    "wof:placetype":"locality"
},
  "geometry": {"coordinates":[25.01175,56.01707],"type":"Point"}
}