{
  "type": "Feature",
  "properties": {
    "gn:admin1_code":"58",
    "gn:admin2_code":"75.0",
    "gn:asciiname":"Ivoniske",
    "gn:country_code":"LT",
    "gn:dem":104,
    "gn:feature_class":"P",
    "gn:feature_code":"PPL",
    "gn:name":"Ivonisk\u0117",
    "gn:population":0,
    "gn:timezone":"Europe/Vilnius",
    "iso:country":"LT",
    "name:lit_x_preferred":[
        "Ivonisk\u0117"
    ],
    "wof:name":"Ivoniske",
    "wof:placetype":"locality"
},
  "geometry": {"coordinates":[21.98099,56.20806],"type":"Point"}
}