{
  "type": "Feature",
  "properties": {
    "gn:admin1_code":"61",
    "gn:admin2_code":"54.0",
    "gn:asciiname":"Rezgalis",
    "gn:country_code":"LT",
    "gn:dem":158,
    "gn:feature_class":"P",
    "gn:feature_code":"PPL",
    "gn:name":"R\u0117\u017egalis",
    "gn:population":0,
    "gn:timezone":"Europe/Vilnius",
    "iso:country":"LT",
    "name:lit_x_preferred":[
        "R\u0117\u017egalis"
    ],
    "wof:name":"Rezgalis",
    "wof:placetype":"locality"
},
  "geometry": {"coordinates":[22.64642000000001,55.76871],"type":"Point"}
}