{
  "type": "Feature",
  "properties": {
    "gn:admin1_code":"60",
    "gn:admin2_code":"73.0",
    "gn:asciiname":"Gireisiai",
    "gn:country_code":"LT",
    "gn:dem":112,
    "gn:feature_class":"P",
    "gn:feature_code":"PPL",
    "gn:name":"Girei\u0161iai",
    "gn:population":0,
    "gn:timezone":"Europe/Vilnius",
    "iso:country":"LT",
    "name:lit_x_preferred":[
        "Girei\u0161iai"
    ],
    "wof:name":"Gireisiai",
    "wof:placetype":"locality"
},
  "geometry": {"coordinates":[25.43684,55.89884],"type":"Point"}
}