{
  "type": "Feature",
  "properties": {
    "gn:admin1_code":"60.0",
    "gn:admin2_code":"36.0",
    "gn:asciiname":"Smaltiskiai",
    "gn:country_code":"LT",
    "gn:dem":65,
    "gn:feature_class":"P",
    "gn:feature_code":"PPL",
    "gn:name":"Smalti\u0161kiai",
    "gn:population":0,
    "gn:timezone":"Europe/Vilnius",
    "iso:country":"LT",
    "name:und_x_variant":[
        "Smal\u2019tishkyay",
        "Smalti\u0161kiai"
    ],
    "wof:name":"Smaltiskiai",
    "wof:placetype":"locality"
},
  "geometry": {"coordinates":[24.98894,56.30237],"type":"Point"}
}