{
  "type": "Feature",
  "properties": {
    "gn:admin1_code":"57.0",
    "gn:admin2_code":"72.0",
    "gn:asciiname":"Seimyniskiai",
    "gn:country_code":"LT",
    "gn:dem":78,
    "gn:feature_class":"P",
    "gn:feature_code":"PPL",
    "gn:name":"\u0160eimyni\u0161kiai",
    "gn:population":0,
    "gn:timezone":"Europe/Vilnius",
    "iso:country":"LT",
    "name:und_x_variant":[
        "Semenishki",
        "\u0160eimyni\u0161kiai"
    ],
    "wof:name":"Seimyniskiai",
    "wof:placetype":"locality"
},
  "geometry": {"coordinates":[23.16549,55.31851],"type":"Point"}
}