{
  "type": "Feature",
  "properties": {
    "gn:admin1_code":"65",
    "gn:admin2_code":"13.0",
    "gn:asciiname":"Mikulionys",
    "gn:country_code":"LT",
    "gn:dem":167,
    "gn:feature_class":"P",
    "gn:feature_code":"PPL",
    "gn:name":"Mikulionys",
    "gn:population":0,
    "gn:timezone":"Europe/Vilnius",
    "iso:country":"LT",
    "name:lit_x_preferred":[
        "Mikulionys"
    ],
    "wof:name":"Mikulionys",
    "wof:placetype":"locality"
},
  "geometry": {"coordinates":[25.23489,54.86743000000001],"type":"Point"}
}