{
  "type": "Feature",
  "properties": {
    "gn:admin1_code":"61.0",
    "gn:admin2_code":"71.0",
    "gn:asciiname":"Jaugelai",
    "gn:country_code":"LT",
    "gn:dem":119,
    "gn:feature_class":"P",
    "gn:feature_code":"PPL",
    "gn:name":"Jaug\u0117lai",
    "gn:population":0,
    "gn:timezone":"Europe/Vilnius",
    "iso:country":"LT",
    "name:und_x_variant":[
        "Yagelaychyay",
        "Jaug\u0117lai"
    ],
    "wof:name":"Jaugelai",
    "wof:placetype":"locality"
},
  "geometry": {"coordinates":[23.5131,55.76858000000001],"type":"Point"}
}