{
  "type": "Feature",
  "properties": {
    "gn:admin1_code":"64",
    "gn:admin2_code":"34.0",
    "gn:asciiname":"Gudonys",
    "gn:country_code":"LT",
    "gn:dem":106,
    "gn:feature_class":"P",
    "gn:feature_code":"PPL",
    "gn:name":"Gudonys",
    "gn:population":0,
    "gn:timezone":"Europe/Vilnius",
    "iso:country":"LT",
    "name:lit_x_preferred":[
        "Gudonys"
    ],
    "wof:name":"Gudonys",
    "wof:placetype":"locality"
},
  "geometry": {"coordinates":[25.0021,55.4057],"type":"Point"}
}