{
  "type": "Feature",
  "properties": {
    "gn:admin1_code":"65",
    "gn:admin2_code":"81.0",
    "gn:asciiname":"Pamusis",
    "gn:country_code":"LT",
    "gn:dem":68,
    "gn:feature_class":"P",
    "gn:feature_code":"PPL",
    "gn:name":"Pam\u016b\u0161is",
    "gn:population":0,
    "gn:timezone":"Europe/Vilnius",
    "iso:country":"LT",
    "name:lit_x_preferred":[
        "Pam\u016b\u0161is"
    ],
    "wof:name":"Pamusis",
    "wof:placetype":"locality"
},
  "geometry": {"coordinates":[24.795,55.35576],"type":"Point"}
}