{
  "type": "Feature",
  "properties": {
    "gn:admin1_code":"63.0",
    "gn:admin2_code":"61.0",
    "gn:asciiname":"Dagiai",
    "gn:country_code":"LT",
    "gn:dem":145,
    "gn:feature_class":"P",
    "gn:feature_code":"PPL",
    "gn:name":"Dagiai",
    "gn:population":0,
    "gn:timezone":"Europe/Vilnius",
    "iso:country":"LT",
    "name:und_x_variant":[
        "Dagi",
        "Dagi\u0173",
        "Dagyay",
        "Dagiai"
    ],
    "wof:name":"Dagiai",
    "wof:placetype":"locality"
},
  "geometry": {"coordinates":[22.00138,56.16584],"type":"Point"}
}