{
  "type": "Feature",
  "properties": {
    "gn:admin1_code":"63.0",
    "gn:admin2_code":"78.0",
    "gn:asciiname":"Kaunatava",
    "gn:country_code":"LT",
    "gn:dem":109,
    "gn:feature_class":"P",
    "gn:feature_code":"PPL",
    "gn:name":"Kaunatava",
    "gn:population":0,
    "gn:timezone":"Europe/Vilnius",
    "iso:country":"LT",
    "name:und_x_variant":[
        "Kaunatavas",
        "Kaunotavo",
        "Kaunetavo",
        "Kaunatava"
    ],
    "wof:name":"Kaunatava",
    "wof:placetype":"locality"
},
  "geometry": {"coordinates":[22.57003,55.96961999999999],"type":"Point"}
}