{
  "type": "Feature",
  "properties": {
    "gn:admin1_code":"64",
    "gn:admin2_code":"34.0",
    "gn:asciiname":"Jankaviskis",
    "gn:country_code":"LT",
    "gn:dem":119,
    "gn:feature_class":"P",
    "gn:feature_code":"PPL",
    "gn:name":"Jankavi\u0161kis",
    "gn:population":0,
    "gn:timezone":"Europe/Vilnius",
    "iso:country":"LT",
    "name:lit_x_preferred":[
        "Jankavi\u0161kis"
    ],
    "wof:name":"Jankaviskis",
    "wof:placetype":"locality"
},
  "geometry": {"coordinates":[25.27168,55.59051],"type":"Point"}
}