{
  "type": "Feature",
  "properties": {
    "gn:admin1_code":"65",
    "gn:admin2_code":"13.0",
    "gn:asciiname":"Rimsiskes",
    "gn:country_code":"LT",
    "gn:dem":180,
    "gn:feature_class":"P",
    "gn:feature_code":"PPL",
    "gn:name":"Rim\u0161i\u0161k\u0117s",
    "gn:population":0,
    "gn:timezone":"Europe/Vilnius",
    "iso:country":"LT",
    "name:lit_x_preferred":[
        "Rim\u0161i\u0161k\u0117s"
    ],
    "wof:name":"Rimsiskes",
    "wof:placetype":"locality"
},
  "geometry": {"coordinates":[25.48953,54.96939],"type":"Point"}
}