{
  "type": "Feature",
  "properties": {
    "gn:admin1_code":"57.0",
    "gn:admin2_code":"53.0",
    "gn:asciiname":"Rudziai",
    "gn:country_code":"LT",
    "gn:dem":52,
    "gn:feature_class":"P",
    "gn:feature_code":"PPL",
    "gn:name":"Rud\u017eiai",
    "gn:population":0,
    "gn:timezone":"Europe/Vilnius",
    "iso:country":"LT",
    "name:eng_x_preferred":[
        "Rud\u017eiai"
    ],
    "name:rus_x_preferred":[
        "\u0420\u0443\u0434\u0436\u044f\u0439"
    ],
    "name:und_x_variant":[
        "Rvd\u017eiai",
        "R\u016bd\u017ei\u0173",
        "Rudzhyay"
    ],
    "wof:name":"Rudziai",
    "wof:placetype":"locality"
},
  "geometry": {"coordinates":[24.11802,55.35689],"type":"Point"}
}