{
  "type": "Feature",
  "properties": {
    "gn:admin1_code":"64",
    "gn:admin2_code":"45.0",
    "gn:asciiname":"Andrikavas",
    "gn:country_code":"LT",
    "gn:dem":194,
    "gn:feature_class":"P",
    "gn:feature_code":"PPL",
    "gn:name":"Andrikavas",
    "gn:population":0,
    "gn:timezone":"Europe/Vilnius",
    "iso:country":"LT",
    "name:lit_x_preferred":[
        "Andrikavas"
    ],
    "wof:name":"Andrikavas",
    "wof:placetype":"locality"
},
  "geometry": {"coordinates":[26.27892,55.35442],"type":"Point"}
}