{
  "type": "Feature",
  "properties": {
    "gn:admin1_code":"60",
    "gn:admin2_code":"73.0",
    "gn:asciiname":"Azubaliai",
    "gn:country_code":"LT",
    "gn:dem":113,
    "gn:feature_class":"P",
    "gn:feature_code":"PPL",
    "gn:name":"A\u017eubaliai",
    "gn:population":0,
    "gn:timezone":"Europe/Vilnius",
    "iso:country":"LT",
    "name:lit_x_preferred":[
        "A\u017eubaliai"
    ],
    "wof:name":"Azubaliai",
    "wof:placetype":"locality"
},
  "geometry": {"coordinates":[25.42701,55.76169],"type":"Point"}
}