{
  "type": "Feature",
  "properties": {
    "gn:admin1_code":"64",
    "gn:admin2_code":"43.0",
    "gn:asciiname":"Navikai",
    "gn:country_code":"LT",
    "gn:dem":165,
    "gn:feature_class":"P",
    "gn:feature_code":"PPL",
    "gn:name":"Navikai",
    "gn:population":0,
    "gn:timezone":"Europe/Vilnius",
    "iso:country":"LT",
    "name:bel_x_preferred":[
        "\u041d\u0430\u0432\u0456\u043a\u0430\u0439"
    ],
    "name:lit_x_preferred":[
        "Navikai"
    ],
    "wof:name":"Navikai",
    "wof:placetype":"locality"
},
  "geometry": {"coordinates":[26.14694,55.74256999999999],"type":"Point"}
}