{
  "type": "Feature",
  "properties": {
    "gn:admin1_code":"58.0",
    "gn:admin2_code":"56.0",
    "gn:asciiname":"Dimitravas",
    "gn:country_code":"LT",
    "gn:dem":28,
    "gn:feature_class":"P",
    "gn:feature_code":"PPL",
    "gn:name":"Dimitravas",
    "gn:population":0,
    "gn:timezone":"Europe/Vilnius",
    "iso:country":"LT",
    "name:und_x_variant":[
        "Tarvydai",
        "Dimitravas"
    ],
    "wof:name":"Dimitravas",
    "wof:placetype":"locality"
},
  "geometry": {"coordinates":[21.23136,55.96909],"type":"Point"}
}