{
  "type": "Feature",
  "properties": {
    "gn:admin1_code":"63",
    "gn:admin2_code":"68.0",
    "gn:asciiname":"Yliai",
    "gn:country_code":"LT",
    "gn:dem":145,
    "gn:feature_class":"P",
    "gn:feature_code":"PPL",
    "gn:name":"Yliai",
    "gn:population":0,
    "gn:timezone":"Europe/Vilnius",
    "iso:country":"LT",
    "name:lit_x_preferred":[
        "Yliai"
    ],
    "wof:name":"Yliai",
    "wof:placetype":"locality"
},
  "geometry": {"coordinates":[22.04907,56.05033],"type":"Point"}
}