{
  "type": "Feature",
  "properties": {
    "gn:admin1_code":"64",
    "gn:admin2_code":"82.0",
    "gn:asciiname":"Gatakiemis",
    "gn:country_code":"LT",
    "gn:dem":160,
    "gn:feature_class":"P",
    "gn:feature_code":"PPL",
    "gn:name":"Gatakiemis",
    "gn:population":0,
    "gn:timezone":"Europe/Vilnius",
    "iso:country":"LT",
    "name:lit_x_preferred":[
        "Gatakiemis"
    ],
    "wof:name":"Gatakiemis",
    "wof:placetype":"locality"
},
  "geometry": {"coordinates":[25.78762,55.31566],"type":"Point"}
}