{
  "type": "Feature",
  "properties": {
    "gn:admin1_code":"62.0",
    "gn:admin2_code":"63.0",
    "gn:asciiname":"Zukai",
    "gn:country_code":"LT",
    "gn:dem":16,
    "gn:feature_class":"P",
    "gn:feature_code":"PPL",
    "gn:name":"\u017dukai",
    "gn:population":0,
    "gn:timezone":"Europe/Vilnius",
    "iso:country":"LT",
    "name:eng_x_preferred":[
        "\u017dukai"
    ],
    "name:rus_x_preferred":[
        "\u0416\u0443\u043a\u0430\u0439"
    ],
    "name:und_x_variant":[
        "Szugken",
        "Zhukay",
        "Zhugken",
        "\u017duk\u0173"
    ],
    "wof:name":"Zukai",
    "wof:placetype":"locality"
},
  "geometry": {"coordinates":[22.25978,55.11396],"type":"Point"}
}