{
  "type": "Feature",
  "properties": {
    "gn:admin1_code":"63.0",
    "gn:admin2_code":"78.0",
    "gn:asciiname":"Mizikai",
    "gn:country_code":"LT",
    "gn:dem":128,
    "gn:feature_class":"P",
    "gn:feature_code":"PPL",
    "gn:name":"Mi\u017eikai",
    "gn:population":0,
    "gn:timezone":"Europe/Vilnius",
    "iso:country":"LT",
    "name:und_x_variant":[
        "Mizhikyay",
        "Mi\u017eikai",
        "Bargainiai"
    ],
    "wof:name":"Mizikai",
    "wof:placetype":"locality"
},
  "geometry": {"coordinates":[22.4899,55.93514],"type":"Point"}
}