{
  "type": "Feature",
  "properties": {
    "gn:admin1_code":"64.0",
    "gn:admin2_code":"45.0",
    "gn:asciiname":"Bajorai II",
    "gn:country_code":"LT",
    "gn:dem":160,
    "gn:feature_class":"P",
    "gn:feature_code":"PPL",
    "gn:name":"Bajorai II",
    "gn:population":0,
    "gn:timezone":"Europe/Vilnius",
    "iso:country":"LT",
    "name:lit_x_preferred":[
        "Bajorai II"
    ],
    "name:lit_x_variant":[
        "Bajorai"
    ],
    "wof:name":"Bajorai II",
    "wof:placetype":"locality"
},
  "geometry": {"coordinates":[26.22934,55.44808],"type":"Point"}
}