{
  "type": "Feature",
  "properties": {
    "gn:admin1_code":"63",
    "gn:admin2_code":"78.0",
    "gn:asciiname":"Jausaiciai",
    "gn:country_code":"LT",
    "gn:dem":167,
    "gn:feature_class":"P",
    "gn:feature_code":"PPL",
    "gn:name":"Jausai\u010diai",
    "gn:population":0,
    "gn:timezone":"Europe/Vilnius",
    "iso:country":"LT",
    "name:lit_x_preferred":[
        "Jausai\u010diai"
    ],
    "wof:name":"Jausaiciai",
    "wof:placetype":"locality"
},
  "geometry": {"coordinates":[22.26597000000001,55.7266],"type":"Point"}
}