{
  "type": "Feature",
  "properties": {
    "gn:admin1_code":"65",
    "gn:admin2_code":"79.0",
    "gn:asciiname":"Samuauka",
    "gn:country_code":"LT",
    "gn:dem":130,
    "gn:feature_class":"P",
    "gn:feature_code":"PPL",
    "gn:name":"Samuauka",
    "gn:population":0,
    "gn:timezone":"Europe/Vilnius",
    "iso:country":"LT",
    "name:lit_x_preferred":[
        "Samuauka"
    ],
    "wof:name":"Samuauka",
    "wof:placetype":"locality"
},
  "geometry": {"coordinates":[24.49042,54.52848],"type":"Point"}
}