{
  "type": "Feature",
  "properties": {
    "gn:admin1_code":"61",
    "gn:admin2_code":"29.0",
    "gn:asciiname":"Pilkalnis",
    "gn:country_code":"LT",
    "gn:dem":100,
    "gn:feature_class":"P",
    "gn:feature_code":"PPL",
    "gn:name":"Pilkalnis",
    "gn:population":0,
    "gn:timezone":"Europe/Vilnius",
    "iso:country":"LT",
    "name:lit_x_preferred":[
        "Pilkalnis"
    ],
    "wof:name":"Pilkalnis",
    "wof:placetype":"locality"
},
  "geometry": {"coordinates":[23.00884,56.07174000000001],"type":"Point"}
}