{
  "type": "Feature",
  "properties": {
    "gn:admin1_code":"64",
    "gn:admin2_code":"62.0",
    "gn:asciiname":"Brazdoniskiai",
    "gn:country_code":"LT",
    "gn:dem":179,
    "gn:feature_class":"P",
    "gn:feature_code":"PPL",
    "gn:name":"Brazdoni\u0161kiai",
    "gn:population":0,
    "gn:timezone":"Europe/Vilnius",
    "iso:country":"LT",
    "name:lit_x_preferred":[
        "Brazdoni\u0161kiai"
    ],
    "wof:name":"Brazdoniskiai",
    "wof:placetype":"locality"
},
  "geometry": {"coordinates":[25.36616,55.07519],"type":"Point"}
}