{
  "type": "Feature",
  "properties": {
    "gn:admin1_code":"65",
    "gn:admin2_code":"13.0",
    "gn:asciiname":"Juodalaukis",
    "gn:country_code":"LT",
    "gn:dem":176,
    "gn:feature_class":"P",
    "gn:feature_code":"PPL",
    "gn:name":"Juodalaukis",
    "gn:population":0,
    "gn:timezone":"Europe/Vilnius",
    "iso:country":"LT",
    "name:lit_x_preferred":[
        "Juodalaukis"
    ],
    "wof:name":"Juodalaukis",
    "wof:placetype":"locality"
},
  "geometry": {"coordinates":[25.49231,54.64504],"type":"Point"}
}