{
  "type": "Feature",
  "properties": {
    "gn:admin1_code":"61.0",
    "gn:admin2_code":"54.0",
    "gn:asciiname":"Baldegiai",
    "gn:country_code":"LT",
    "gn:dem":141,
    "gn:feature_class":"P",
    "gn:feature_code":"PPL",
    "gn:name":"Baldegiai",
    "gn:population":0,
    "gn:timezone":"Europe/Vilnius",
    "iso:country":"LT",
    "name:und_x_variant":[
        "Bal\u2019degyay",
        "Baldegiai"
    ],
    "wof:name":"Baldegiai",
    "wof:placetype":"locality"
},
  "geometry": {"coordinates":[22.96821,55.50722],"type":"Point"}
}