{
  "type": "Feature",
  "properties": {
    "gn:admin1_code":"57",
    "gn:admin2_code":"72.0",
    "gn:asciiname":"Pociunai",
    "gn:country_code":"LT",
    "gn:dem":95,
    "gn:feature_class":"P",
    "gn:feature_code":"PPL",
    "gn:name":"Poci\u016bnai",
    "gn:population":0,
    "gn:timezone":"Europe/Vilnius",
    "iso:country":"LT",
    "name:lit_x_preferred":[
        "Poci\u016bnai"
    ],
    "wof:name":"Pociunai",
    "wof:placetype":"locality"
},
  "geometry": {"coordinates":[23.3443,55.27857],"type":"Point"}
}