{
  "type": "Feature",
  "properties": {
    "gn:admin1_code":"57.0",
    "gn:admin2_code":"49.0",
    "gn:asciiname":"Zibaviciai",
    "gn:country_code":"LT",
    "gn:dem":121,
    "gn:feature_class":"P",
    "gn:feature_code":"PPL",
    "gn:name":"\u017dibavi\u010diai",
    "gn:population":0,
    "gn:timezone":"Europe/Vilnius",
    "iso:country":"LT",
    "name:lit_x_preferred":[
        "\u017dibavi\u010diai"
    ],
    "name:und_x_variant":[
        "\u017dibavie\u010diai",
        "Karsakai Antrieji",
        "Korsaki Vtoroye",
        "Karsakai II"
    ],
    "wof:name":"Zibaviciai",
    "wof:placetype":"locality"
},
  "geometry": {"coordinates":[24.65204,54.87974000000001],"type":"Point"}
}