{
  "type": "Feature",
  "properties": {
    "gn:admin1_code":"56.0",
    "gn:admin2_code":"11.0",
    "gn:asciiname":"Griskonys",
    "gn:country_code":"LT",
    "gn:dem":113,
    "gn:feature_class":"P",
    "gn:feature_code":"PPL",
    "gn:name":"Gri\u0161konys",
    "gn:population":0,
    "gn:timezone":"Europe/Vilnius",
    "iso:country":"LT",
    "name:und_x_variant":[
        "Grishkantsy",
        "Gri\u0161konys"
    ],
    "wof:name":"Griskonys",
    "wof:placetype":"locality"
},
  "geometry": {"coordinates":[24.2098,54.51016],"type":"Point"}
}