{
  "type": "Feature",
  "properties": {
    "gn:admin1_code":"58.0",
    "gn:admin2_code":"88.0",
    "gn:asciiname":"Uzlauke",
    "gn:country_code":"LT",
    "gn:dem":32,
    "gn:feature_class":"P",
    "gn:feature_code":"PPL",
    "gn:name":"U\u017elauk\u0117",
    "gn:population":0,
    "gn:timezone":"Europe/Vilnius",
    "iso:country":"LT",
    "name:und_x_variant":[
        "Uzhlaukey",
        "Uzhlauke",
        "U\u017elauk\u0117"
    ],
    "wof:name":"Uzlauke",
    "wof:placetype":"locality"
},
  "geometry": {"coordinates":[21.66559,55.39355],"type":"Point"}
}