{
  "type": "Feature",
  "properties": {
    "gn:admin1_code":"59",
    "gn:admin2_code":"39.0",
    "gn:asciiname":"Uzbaliai",
    "gn:country_code":"LT",
    "gn:dem":96,
    "gn:feature_class":"P",
    "gn:feature_code":"PPL",
    "gn:name":"U\u017ebaliai",
    "gn:population":0,
    "gn:timezone":"Europe/Vilnius",
    "iso:country":"LT",
    "name:lit_x_preferred":[
        "U\u017ebaliai"
    ],
    "wof:name":"Uzbaliai",
    "wof:placetype":"locality"
},
  "geometry": {"coordinates":[22.91945,54.52804],"type":"Point"}
}