{
  "type": "Feature",
  "properties": {
    "gn:admin1_code":"62.0",
    "gn:admin2_code":"94.0",
    "gn:asciiname":"Ausgirys",
    "gn:country_code":"LT",
    "gn:dem":73,
    "gn:feature_class":"P",
    "gn:feature_code":"PPL",
    "gn:name":"Au\u0161girys",
    "gn:population":0,
    "gn:timezone":"Europe/Vilnius",
    "iso:country":"LT",
    "name:und_x_variant":[
        "Auzhgiry",
        "Au\u0161girys"
    ],
    "wof:name":"Ausgirys",
    "wof:placetype":"locality"
},
  "geometry": {"coordinates":[23.12362000000001,55.24786999999999],"type":"Point"}
}