{
  "type": "Feature",
  "properties": {
    "gn:admin1_code":"62",
    "gn:admin2_code":"77.0",
    "gn:asciiname":"Sakiai",
    "gn:country_code":"LT",
    "gn:dem":21,
    "gn:feature_class":"P",
    "gn:feature_code":"PPL",
    "gn:name":"\u0160akiai",
    "gn:population":0,
    "gn:timezone":"Europe/Vilnius",
    "iso:country":"LT",
    "name:lit_x_preferred":[
        "\u0160akiai"
    ],
    "wof:name":"Sakiai",
    "wof:placetype":"locality"
},
  "geometry": {"coordinates":[22.35662,55.23368000000001],"type":"Point"}
}