{
  "type": "Feature",
  "properties": {
    "gn:admin1_code":"60",
    "gn:admin2_code":"27.0",
    "gn:asciiname":"Zariskiai",
    "gn:country_code":"LT",
    "gn:dem":69,
    "gn:feature_class":"P",
    "gn:feature_code":"PPL",
    "gn:name":"\u017dari\u0161kiai",
    "gn:population":0,
    "gn:timezone":"Europe/Vilnius",
    "iso:country":"LT",
    "name:lit_x_preferred":[
        "\u017dari\u0161kiai"
    ],
    "wof:name":"Zariskiai",
    "wof:placetype":"locality"
},
  "geometry": {"coordinates":[24.69104,55.73787],"type":"Point"}
}