{
  "type": "Feature",
  "properties": {
    "gn:admin1_code":"57.0",
    "gn:admin2_code":"49.0",
    "gn:asciiname":"Vilkakiemis",
    "gn:country_code":"LT",
    "gn:dem":101,
    "gn:feature_class":"P",
    "gn:feature_code":"PPL",
    "gn:name":"Vilkakiemis",
    "gn:population":0,
    "gn:timezone":"Europe/Vilnius",
    "iso:country":"LT",
    "name:und_x_variant":[
        "Volgokeny",
        "Vilkakiemis"
    ],
    "wof:name":"Vilkakiemis",
    "wof:placetype":"locality"
},
  "geometry": {"coordinates":[24.61965,54.93046],"type":"Point"}
}