{
  "type": "Feature",
  "properties": {
    "gn:admin1_code":"61.0",
    "gn:admin2_code":"47.0",
    "gn:asciiname":"Staneliai",
    "gn:country_code":"LT",
    "gn:dem":86,
    "gn:feature_class":"P",
    "gn:feature_code":"PPL",
    "gn:name":"Staneliai",
    "gn:population":0,
    "gn:timezone":"Europe/Vilnius",
    "iso:country":"LT",
    "name:und_x_variant":[
        "Stanyalyay",
        "Staneliai"
    ],
    "wof:name":"Staneliai",
    "wof:placetype":"locality"
},
  "geometry": {"coordinates":[23.4112,56.16328000000001],"type":"Point"}
}