{
  "type": "Feature",
  "properties": {
    "gn:admin1_code":"62.0",
    "gn:admin2_code":"63.0",
    "gn:asciiname":"Kentriai",
    "gn:country_code":"LT",
    "gn:dem":26,
    "gn:feature_class":"P",
    "gn:feature_code":"PPL",
    "gn:name":"Kentriai",
    "gn:population":0,
    "gn:timezone":"Europe/Vilnius",
    "iso:country":"LT",
    "name:und_x_variant":[
        "Kyantryay",
        "Kullmen Zharden",
        "Kentriai"
    ],
    "wof:name":"Kentriai",
    "wof:placetype":"locality"
},
  "geometry": {"coordinates":[21.99428,55.19694000000001],"type":"Point"}
}