{
  "type": "Feature",
  "properties": {
    "gn:admin1_code":"64",
    "gn:admin2_code":"43.0",
    "gn:asciiname":"Pagrauze",
    "gn:country_code":"LT",
    "gn:dem":154,
    "gn:feature_class":"P",
    "gn:feature_code":"PPL",
    "gn:name":"Pagrau\u017e\u0117",
    "gn:population":0,
    "gn:timezone":"Europe/Vilnius",
    "iso:country":"LT",
    "name:lit_x_preferred":[
        "Pagrau\u017e\u0117"
    ],
    "wof:name":"Pagrauze",
    "wof:placetype":"locality"
},
  "geometry": {"coordinates":[26.22875,55.65716],"type":"Point"}
}