{
  "type": "Feature",
  "properties": {
    "gn:admin1_code":"65.0",
    "gn:admin2_code":"42.0",
    "gn:asciiname":"Aleksandrava",
    "gn:country_code":"LT",
    "gn:dem":107,
    "gn:feature_class":"P",
    "gn:feature_code":"PPL",
    "gn:name":"Aleksandrava",
    "gn:population":0,
    "gn:timezone":"Europe/Vilnius",
    "iso:country":"LT",
    "name:lit_x_preferred":[
        "Aleksandrava"
    ],
    "name:und_x_variant":[
        "Aleksandrauka",
        "Aleksandraukos",
        "Gad\u0117na"
    ],
    "wof:name":"Aleksandrava",
    "wof:placetype":"locality"
},
  "geometry": {"coordinates":[24.64914,54.68118000000001],"type":"Point"}
}