{
  "type": "Feature",
  "properties": {
    "gn:admin1_code":"59.0",
    "gn:admin2_code":"39.0",
    "gn:asciiname":"Bobiai",
    "gn:country_code":"LT",
    "gn:dem":48,
    "gn:feature_class":"P",
    "gn:feature_code":"PPL",
    "gn:name":"Bobiai",
    "gn:population":0,
    "gn:timezone":"Europe/Vilnius",
    "iso:country":"LT",
    "name:und_x_variant":[
        "Bobe",
        "Bobi\u0173",
        "Bobiai"
    ],
    "wof:name":"Bobiai",
    "wof:placetype":"locality"
},
  "geometry": {"coordinates":[23.03672000000001,54.74178000000001],"type":"Point"}
}