{
  "type": "Feature",
  "properties": {
    "gn:admin1_code":"58",
    "gn:admin2_code":"88.0",
    "gn:asciiname":"Zasyciai",
    "gn:country_code":"LT",
    "gn:dem":60,
    "gn:feature_class":"P",
    "gn:feature_code":"PPL",
    "gn:name":"\u017d\u0105sy\u010diai",
    "gn:population":0,
    "gn:timezone":"Europe/Vilnius",
    "iso:country":"LT",
    "name:lit_x_preferred":[
        "\u017d\u0105sy\u010diai"
    ],
    "wof:name":"Zasyciai",
    "wof:placetype":"locality"
},
  "geometry": {"coordinates":[21.75468,55.49964],"type":"Point"}
}