{
  "type": "Feature",
  "properties": {
    "gn:admin1_code":"60",
    "gn:admin2_code":"27.0",
    "gn:asciiname":"Puskonys",
    "gn:country_code":"LT",
    "gn:dem":45,
    "gn:feature_class":"P",
    "gn:feature_code":"PPL",
    "gn:name":"Pu\u0161konys",
    "gn:population":0,
    "gn:timezone":"Europe/Vilnius",
    "iso:country":"LT",
    "name:lit_x_preferred":[
        "Pu\u0161konys"
    ],
    "wof:name":"Puskonys",
    "wof:placetype":"locality"
},
  "geometry": {"coordinates":[24.1884,55.69579],"type":"Point"}
}