{
  "type": "Feature",
  "properties": {
    "gn:admin1_code":"60.0",
    "gn:admin2_code":"57.0",
    "gn:asciiname":"Varniskiai",
    "gn:country_code":"LT",
    "gn:dem":85,
    "gn:feature_class":"P",
    "gn:feature_code":"PPL",
    "gn:name":"Varni\u0161kiai",
    "gn:population":0,
    "gn:timezone":"Europe/Vilnius",
    "iso:country":"LT",
    "name:und_x_variant":[
        "Varnishki",
        "Varni\u0161kiai"
    ],
    "wof:name":"Varniskiai",
    "wof:placetype":"locality"
},
  "geometry": {"coordinates":[24.84221,55.84363000000001],"type":"Point"}
}