{
  "type": "Feature",
  "properties": {
    "gn:admin1_code":"60.0",
    "gn:admin2_code":"66.0",
    "gn:asciiname":"Smilgiai",
    "gn:cc2":"LT",
    "gn:country_code":"LT",
    "gn:dem":66,
    "gn:feature_class":"P",
    "gn:feature_code":"PPL",
    "gn:name":"Smilgiai",
    "gn:population":0,
    "gn:timezone":"Europe/Vilnius",
    "iso:country":"LT",
    "name:ceb_x_preferred":[
        "Smilgiai"
    ],
    "name:deu_x_preferred":[
        "Smilgiai"
    ],
    "name:est_x_preferred":[
        "Smilgiai"
    ],
    "name:lit_x_preferred":[
        "Smilgiai"
    ],
    "name:nld_x_preferred":[
        "Smilgiai"
    ],
    "name:pol_x_preferred":[
        "Smilgie"
    ],
    "name:swe_x_preferred":[
        "Smilgiai"
    ],
    "name:und_x_variant":[
        "Smilgi\u0173",
        "Smil\u2019ge"
    ],
    "wof:name":"Smilgiai",
    "wof:placetype":"locality"
},
  "geometry": {"coordinates":[24.013,55.803],"type":"Point"}
}