{
  "type": "Feature",
  "properties": {
    "gn:admin1_code":"64",
    "gn:admin2_code":"62.0",
    "gn:asciiname":"Antadure",
    "gn:country_code":"LT",
    "gn:dem":150,
    "gn:feature_class":"P",
    "gn:feature_code":"PPL",
    "gn:name":"Antad\u016br\u0117",
    "gn:population":0,
    "gn:timezone":"Europe/Vilnius",
    "iso:country":"LT",
    "name:lit_x_preferred":[
        "Antad\u016br\u0117"
    ],
    "wof:name":"Antadure",
    "wof:placetype":"locality"
},
  "geometry": {"coordinates":[25.44006,55.25716],"type":"Point"}
}