{
  "type": "Feature",
  "properties": {
    "gn:admin1_code":"60",
    "gn:admin2_code":"36.0",
    "gn:asciiname":"Mikalaitiskiai",
    "gn:country_code":"LT",
    "gn:dem":74,
    "gn:feature_class":"P",
    "gn:feature_code":"PPL",
    "gn:name":"Mikalaiti\u0161kiai",
    "gn:population":0,
    "gn:timezone":"Europe/Vilnius",
    "iso:country":"LT",
    "name:lit_x_preferred":[
        "Mikalaiti\u0161kiai"
    ],
    "wof:name":"Mikalaitiskiai",
    "wof:placetype":"locality"
},
  "geometry": {"coordinates":[24.94454,56.02743],"type":"Point"}
}