{
  "type": "Feature",
  "properties": {
    "gn:admin1_code":"56",
    "gn:admin2_code":"11.0",
    "gn:asciiname":"Paskuniskes",
    "gn:country_code":"LT",
    "gn:dem":160,
    "gn:feature_class":"P",
    "gn:feature_code":"PPL",
    "gn:name":"Pa\u0161k\u016bni\u0161k\u0117s",
    "gn:population":0,
    "gn:timezone":"Europe/Vilnius",
    "iso:country":"LT",
    "name:lit_x_preferred":[
        "Pa\u0161k\u016bni\u0161k\u0117s"
    ],
    "wof:name":"Paskuniskes",
    "wof:placetype":"locality"
},
  "geometry": {"coordinates":[24.33843,54.47214],"type":"Point"}
}