{
  "type": "Feature",
  "properties": {
    "gn:admin1_code":"60.0",
    "gn:admin2_code":"27.0",
    "gn:asciiname":"Tumagalys",
    "gn:country_code":"LT",
    "gn:dem":73,
    "gn:feature_class":"P",
    "gn:feature_code":"PPL",
    "gn:name":"Tumagalys",
    "gn:population":0,
    "gn:timezone":"Europe/Vilnius",
    "iso:country":"LT",
    "name:und_x_variant":[
        "Tumagoli",
        "Tumagalys"
    ],
    "wof:name":"Tumagalys",
    "wof:placetype":"locality"
},
  "geometry": {"coordinates":[24.64389,55.63595],"type":"Point"}
}