{
  "type": "Feature",
  "properties": {
    "gn:admin1_code":"61.0",
    "gn:admin2_code":"29.0",
    "gn:asciiname":"Raizgiai",
    "gn:country_code":"LT",
    "gn:dem":121,
    "gn:feature_class":"P",
    "gn:feature_code":"PPL",
    "gn:name":"Raizgiai",
    "gn:population":0,
    "gn:timezone":"Europe/Vilnius",
    "iso:country":"LT",
    "name:und_x_variant":[
        "Reyzchyay",
        "Raizgiai"
    ],
    "wof:name":"Raizgiai",
    "wof:placetype":"locality"
},
  "geometry": {"coordinates":[23.18857,55.88985],"type":"Point"}
}