{
  "type": "Feature",
  "properties": {
    "gn:admin1_code":"64",
    "gn:admin2_code":"62.0",
    "gn:asciiname":"Gaveikiai",
    "gn:country_code":"LT",
    "gn:dem":161,
    "gn:feature_class":"P",
    "gn:feature_code":"PPL",
    "gn:name":"Gaveikiai",
    "gn:population":0,
    "gn:timezone":"Europe/Vilnius",
    "iso:country":"LT",
    "name:lit_x_preferred":[
        "Gaveikiai"
    ],
    "wof:name":"Gaveikiai",
    "wof:placetype":"locality"
},
  "geometry": {"coordinates":[25.39659,55.04221999999999],"type":"Point"}
}