{
  "type": "Feature",
  "properties": {
    "gn:admin1_code":"65",
    "gn:admin2_code":"79.0",
    "gn:asciiname":"Babromiskes",
    "gn:country_code":"LT",
    "gn:dem":175,
    "gn:feature_class":"P",
    "gn:feature_code":"PPL",
    "gn:name":"Babromisk\u0117s",
    "gn:population":0,
    "gn:timezone":"Europe/Vilnius",
    "iso:country":"LT",
    "name:lit_x_preferred":[
        "Babromisk\u0117s"
    ],
    "wof:name":"Babromiskes",
    "wof:placetype":"locality"
},
  "geometry": {"coordinates":[24.45235,54.58212],"type":"Point"}
}