{
  "type": "Feature",
  "properties": {
    "gn:admin1_code":"57.0",
    "gn:admin2_code":"69.0",
    "gn:asciiname":"Vosiskes",
    "gn:country_code":"LT",
    "gn:dem":93,
    "gn:feature_class":"P",
    "gn:feature_code":"PPL",
    "gn:name":"Vo\u0161i\u0161k\u0117s",
    "gn:population":0,
    "gn:timezone":"Europe/Vilnius",
    "iso:country":"LT",
    "name:lit_x_preferred":[
        "Vo\u0161i\u0161k\u0117s"
    ],
    "name:und_x_variant":[
        "Vosiski\u0173",
        "Vasishki",
        "Vosi\u0161k\u0117s"
    ],
    "wof:name":"Vosiskes",
    "wof:placetype":"locality"
},
  "geometry": {"coordinates":[24.17753,54.68256],"type":"Point"}
}