{
  "type": "Feature",
  "properties": {
    "gn:admin1_code":"62.0",
    "gn:admin2_code":"94.0",
    "gn:asciiname":"Kalniskiai",
    "gn:country_code":"LT",
    "gn:dem":53,
    "gn:feature_class":"P",
    "gn:feature_code":"PPL",
    "gn:name":"Kalni\u0161kiai",
    "gn:population":0,
    "gn:timezone":"Europe/Vilnius",
    "iso:country":"LT",
    "name:und_x_variant":[
        "Kal\u2019nishki",
        "Kalni\u0161kiai"
    ],
    "wof:name":"Kalniskiai",
    "wof:placetype":"locality"
},
  "geometry": {"coordinates":[22.88912,55.27775],"type":"Point"}
}