{
  "type": "Feature",
  "properties": {
    "gn:admin1_code":"57",
    "gn:admin2_code":"72.0",
    "gn:asciiname":"Paberzis",
    "gn:country_code":"LT",
    "gn:dem":96,
    "gn:feature_class":"P",
    "gn:feature_code":"PPL",
    "gn:name":"Paber\u017eis",
    "gn:population":0,
    "gn:timezone":"Europe/Vilnius",
    "iso:country":"LT",
    "name:lit_x_preferred":[
        "Paber\u017eis"
    ],
    "wof:name":"Paberzis",
    "wof:placetype":"locality"
},
  "geometry": {"coordinates":[22.85766,55.42571],"type":"Point"}
}