{
  "type": "Feature",
  "properties": {
    "gn:admin1_code":"56.0",
    "gn:admin2_code":"59.0",
    "gn:asciiname":"Budvietis",
    "gn:country_code":"LT",
    "gn:dem":133,
    "gn:feature_class":"P",
    "gn:feature_code":"PPL",
    "gn:name":"B\u016bdvietis",
    "gn:population":0,
    "gn:timezone":"Europe/Vilnius",
    "iso:country":"LT",
    "name:eng_x_preferred":[
        "B\u016bdvietis"
    ],
    "name:rus_x_preferred":[
        "\u0411\u0443\u0434\u0432\u0435\u0442\u0438\u0441"
    ],
    "name:und_x_variant":[
        "Budviet\u0117s",
        "Budvetis",
        "Budvetse",
        "Budvie\u010dio",
        "B\u016bdvietis"
    ],
    "wof:name":"Budvietis",
    "wof:placetype":"locality"
},
  "geometry": {"coordinates":[23.32616,54.29059],"type":"Point"}
}