{
  "type": "Feature",
  "properties": {
    "gn:admin1_code":"61.0",
    "gn:admin2_code":"54.0",
    "gn:asciiname":"Kolainiukai",
    "gn:country_code":"LT",
    "gn:dem":188,
    "gn:feature_class":"P",
    "gn:feature_code":"PPL",
    "gn:name":"Kolainiukai",
    "gn:population":0,
    "gn:timezone":"Europe/Vilnius",
    "iso:country":"LT",
    "name:lit_x_preferred":[
        "Kolainiukai"
    ],
    "wof:name":"Kolainiukai",
    "wof:placetype":"locality"
},
  "geometry": {"coordinates":[22.56201,55.74494],"type":"Point"}
}