{
  "type": "Feature",
  "properties": {
    "gn:admin1_code":"57",
    "gn:admin2_code":"53.0",
    "gn:asciiname":"Kezai",
    "gn:country_code":"LT",
    "gn:dem":76,
    "gn:feature_class":"P",
    "gn:feature_code":"PPL",
    "gn:name":"Kezai",
    "gn:population":0,
    "gn:timezone":"Europe/Vilnius",
    "iso:country":"LT",
    "name:lit_x_preferred":[
        "Kezai"
    ],
    "wof:name":"Kezai",
    "wof:placetype":"locality"
},
  "geometry": {"coordinates":[24.39013,55.33596],"type":"Point"}
}