{
  "type": "Feature",
  "properties": {
    "gn:admin1_code":"60.0",
    "gn:admin2_code":"36.0",
    "gn:asciiname":"Smilgiai",
    "gn:country_code":"LT",
    "gn:dem":39,
    "gn:feature_class":"P",
    "gn:feature_code":"PPL",
    "gn:name":"Smilgiai",
    "gn:population":0,
    "gn:timezone":"Europe/Vilnius",
    "iso:country":"LT",
    "name:ceb_x_preferred":[
        "Smilgiai"
    ],
    "name:deu_x_preferred":[
        "Smilgiai"
    ],
    "name:est_x_preferred":[
        "Smilgiai"
    ],
    "name:lit_x_preferred":[
        "Smilgiai"
    ],
    "name:nld_x_preferred":[
        "Smilgiai"
    ],
    "name:pol_x_preferred":[
        "Smilgie"
    ],
    "name:swe_x_preferred":[
        "Smilgiai"
    ],
    "name:und_x_variant":[
        "Smil\u2019gyay",
        "Smilgay",
        "Smilgi\u0173",
        "Smilgiai"
    ],
    "wof:name":"Smilgiai",
    "wof:placetype":"locality"
},
  "geometry": {"coordinates":[24.54461,56.25315],"type":"Point"}
}