{
  "type": "Feature",
  "properties": {
    "gn:admin1_code":"65",
    "gn:admin2_code":"86.0",
    "gn:asciiname":"Svencianka",
    "gn:country_code":"LT",
    "gn:dem":205,
    "gn:feature_class":"P",
    "gn:feature_code":"PPL",
    "gn:name":"Sven\u010dianka",
    "gn:population":0,
    "gn:timezone":"Europe/Vilnius",
    "iso:country":"LT",
    "name:lit_x_preferred":[
        "Sven\u010dianka"
    ],
    "wof:name":"Svencianka",
    "wof:placetype":"locality"
},
  "geometry": {"coordinates":[26.17993,55.09285],"type":"Point"}
}