{
  "type": "Feature",
  "properties": {
    "gn:admin1_code":"59.0",
    "gn:admin2_code":"84.0",
    "gn:asciiname":"Tirmenai",
    "gn:country_code":"LT",
    "gn:dem":56,
    "gn:feature_class":"P",
    "gn:feature_code":"PPL",
    "gn:name":"Tirm\u0117nai",
    "gn:population":0,
    "gn:timezone":"Europe/Vilnius",
    "iso:country":"LT",
    "name:und_x_variant":[
        "Tyrmyany",
        "Turmenai",
        "Tirm\u0117nai"
    ],
    "wof:name":"Tirmenai",
    "wof:placetype":"locality"
},
  "geometry": {"coordinates":[23.55185,55.01688000000001],"type":"Point"}
}