{
  "type": "Feature",
  "properties": {
    "gn:admin1_code":"61",
    "gn:admin2_code":"54.0",
    "gn:asciiname":"Kamariskiai",
    "gn:country_code":"LT",
    "gn:dem":139,
    "gn:feature_class":"P",
    "gn:feature_code":"PPL",
    "gn:name":"Kamari\u0161kiai",
    "gn:population":0,
    "gn:timezone":"Europe/Vilnius",
    "iso:country":"LT",
    "name:lit_x_preferred":[
        "Kamari\u0161kiai"
    ],
    "wof:name":"Kamariskiai",
    "wof:placetype":"locality"
},
  "geometry": {"coordinates":[22.71013,55.60071],"type":"Point"}
}