{
  "type": "Feature",
  "properties": {
    "gn:admin1_code":"65.0",
    "gn:admin2_code":"13.0",
    "gn:asciiname":"Gauriliskes",
    "gn:country_code":"LT",
    "gn:dem":162,
    "gn:feature_class":"P",
    "gn:feature_code":"PPL",
    "gn:name":"Gaurili\u0161k\u0117s",
    "gn:population":0,
    "gn:timezone":"Europe/Vilnius",
    "iso:country":"LT",
    "name:lit_x_preferred":[
        "Gaurili\u0161k\u0117s"
    ],
    "name:und_x_variant":[
        "Tavrilishki"
    ],
    "wof:name":"Gauriliskes",
    "wof:placetype":"locality"
},
  "geometry": {"coordinates":[25.17307000000001,54.9174],"type":"Point"}
}