{
  "type": "Feature",
  "properties": {
    "gn:admin1_code":"65",
    "gn:admin2_code":"42.0",
    "gn:asciiname":"Aleksandriskes",
    "gn:country_code":"LT",
    "gn:dem":119,
    "gn:feature_class":"P",
    "gn:feature_code":"PPL",
    "gn:name":"Aleksandri\u0161k\u0117s",
    "gn:population":0,
    "gn:timezone":"Europe/Vilnius",
    "iso:country":"LT",
    "name:lit_x_preferred":[
        "Aleksandri\u0161k\u0117s"
    ],
    "wof:name":"Aleksandriskes",
    "wof:placetype":"locality"
},
  "geometry": {"coordinates":[24.83318,54.85802],"type":"Point"}
}