{
  "type": "Feature",
  "properties": {
    "gn:admin1_code":"57",
    "gn:admin2_code":"72.0",
    "gn:asciiname":"Zacharovka",
    "gn:country_code":"LT",
    "gn:dem":125,
    "gn:feature_class":"P",
    "gn:feature_code":"PPL",
    "gn:name":"Zacharovka",
    "gn:population":0,
    "gn:timezone":"Europe/Vilnius",
    "iso:country":"LT",
    "name:lit_x_preferred":[
        "Zacharovka"
    ],
    "wof:name":"Zacharovka",
    "wof:placetype":"locality"
},
  "geometry": {"coordinates":[23.27836,55.50722],"type":"Point"}
}