{
  "type": "Feature",
  "properties": {
    "gn:admin1_code":"59",
    "gn:admin2_code":"39.0",
    "gn:asciiname":"Pakalniai",
    "gn:country_code":"LT",
    "gn:dem":213,
    "gn:feature_class":"P",
    "gn:feature_code":"PPL",
    "gn:name":"Pakalniai",
    "gn:population":0,
    "gn:timezone":"Europe/Vilnius",
    "iso:country":"LT",
    "name:lit_x_preferred":[
        "Pakalniai"
    ],
    "wof:name":"Pakalniai",
    "wof:placetype":"locality"
},
  "geometry": {"coordinates":[22.78841,54.39395],"type":"Point"}
}