{
  "type": "Feature",
  "properties": {
    "gn:admin1_code":"64",
    "gn:admin2_code":"45.0",
    "gn:asciiname":"Tripuckai",
    "gn:country_code":"LT",
    "gn:dem":162,
    "gn:feature_class":"P",
    "gn:feature_code":"PPL",
    "gn:name":"Tripuckai",
    "gn:population":0,
    "gn:timezone":"Europe/Vilnius",
    "iso:country":"LT",
    "name:lit_x_preferred":[
        "Tripuckai"
    ],
    "wof:name":"Tripuckai",
    "wof:placetype":"locality"
},
  "geometry": {"coordinates":[26.49252000000001,55.55582],"type":"Point"}
}