{
  "type": "Feature",
  "properties": {
    "gn:admin1_code":"61.0",
    "gn:admin2_code":"47.0",
    "gn:asciiname":"Simkunai",
    "gn:country_code":"LT",
    "gn:dem":78,
    "gn:feature_class":"P",
    "gn:feature_code":"PPL",
    "gn:name":"\u0160imk\u016bnai",
    "gn:population":0,
    "gn:timezone":"Europe/Vilnius",
    "iso:country":"LT",
    "name:und_x_variant":[
        "Zinyunay",
        "Shimkunay",
        "\u0160imkun\u0173",
        "\u0160imk\u016bnai"
    ],
    "wof:name":"Simkunai",
    "wof:placetype":"locality"
},
  "geometry": {"coordinates":[23.43732,56.18206],"type":"Point"}
}