{
  "type": "Feature",
  "properties": {
    "gn:admin1_code":"57",
    "gn:admin2_code":"19.0",
    "gn:asciiname":"Geranoniai",
    "gn:country_code":"LT",
    "gn:dem":65,
    "gn:feature_class":"P",
    "gn:feature_code":"PPL",
    "gn:name":"Geranoniai",
    "gn:population":0,
    "gn:timezone":"Europe/Vilnius",
    "iso:country":"LT",
    "name:lit_x_preferred":[
        "Geranoniai"
    ],
    "wof:name":"Geranoniai",
    "wof:placetype":"locality"
},
  "geometry": {"coordinates":[23.96067,55.05566999999999],"type":"Point"}
}