{
  "type": "Feature",
  "properties": {
    "gn:admin1_code":"60",
    "gn:admin2_code":"27.0",
    "gn:asciiname":"Vilkeliai",
    "gn:country_code":"LT",
    "gn:dem":46,
    "gn:feature_class":"P",
    "gn:feature_code":"PPL",
    "gn:name":"Vilkeliai",
    "gn:population":0,
    "gn:timezone":"Europe/Vilnius",
    "iso:country":"LT",
    "name:lit_x_preferred":[
        "Vilkeliai"
    ],
    "wof:name":"Vilkeliai",
    "wof:placetype":"locality"
},
  "geometry": {"coordinates":[24.22393,55.68118000000001],"type":"Point"}
}