{
  "type": "Feature",
  "properties": {
    "gn:admin1_code":"62",
    "gn:admin2_code":"94.0",
    "gn:asciiname":"Pagatupys",
    "gn:country_code":"LT",
    "gn:dem":70,
    "gn:feature_class":"P",
    "gn:feature_code":"PPL",
    "gn:name":"Pagatupys",
    "gn:population":0,
    "gn:timezone":"Europe/Vilnius",
    "iso:country":"LT",
    "name:lit_x_preferred":[
        "Pagatupys"
    ],
    "wof:name":"Pagatupys",
    "wof:placetype":"locality"
},
  "geometry": {"coordinates":[22.74633,55.38695],"type":"Point"}
}