{
  "type": "Feature",
  "properties": {
    "gn:admin1_code":"57",
    "gn:admin2_code":"53.0",
    "gn:asciiname":"Valkaiciai",
    "gn:country_code":"LT",
    "gn:dem":51,
    "gn:feature_class":"P",
    "gn:feature_code":"PPL",
    "gn:name":"Valkai\u010diai",
    "gn:population":0,
    "gn:timezone":"Europe/Vilnius",
    "iso:country":"LT",
    "name:lit_x_preferred":[
        "Valkai\u010diai"
    ],
    "wof:name":"Valkaiciai",
    "wof:placetype":"locality"
},
  "geometry": {"coordinates":[24.12307,55.27008000000001],"type":"Point"}
}