{
  "type": "Feature",
  "properties": {
    "gn:admin1_code":"57.0",
    "gn:admin2_code":"49.0",
    "gn:asciiname":"Pajautiskes",
    "gn:country_code":"LT",
    "gn:dem":124,
    "gn:feature_class":"P",
    "gn:feature_code":"PPL",
    "gn:name":"Pajauti\u0161k\u0117s",
    "gn:population":0,
    "gn:timezone":"Europe/Vilnius",
    "iso:country":"LT",
    "name:und_x_variant":[
        "Pajauti\u0161k\u0117s",
        "Pajauci\u0161ki\u0173",
        "Payautishkyay",
        "Pajauti\u0161kiai"
    ],
    "wof:name":"Pajautiskes",
    "wof:placetype":"locality"
},
  "geometry": {"coordinates":[24.56763,54.82279000000001],"type":"Point"}
}