{
  "type": "Feature",
  "properties": {
    "gn:admin1_code":"60.0",
    "gn:admin2_code":"67.0",
    "gn:asciiname":"Liciunai",
    "gn:country_code":"LT",
    "gn:dem":46,
    "gn:feature_class":"P",
    "gn:feature_code":"PPL",
    "gn:name":"Li\u010di\u016bnai",
    "gn:population":0,
    "gn:timezone":"Europe/Vilnius",
    "iso:country":"LT",
    "name:und_x_variant":[
        "Li\u010di\u016bn\u0173",
        "Lichunay",
        "Lichyunay",
        "Li\u010di\u016bnai"
    ],
    "wof:name":"Liciunai",
    "wof:placetype":"locality"
},
  "geometry": {"coordinates":[24.51923,56.06047],"type":"Point"}
}