{
  "type": "Feature",
  "properties": {
    "gn:admin1_code":"65",
    "gn:admin2_code":"85.0",
    "gn:asciiname":"Zalabiskes",
    "gn:country_code":"LT",
    "gn:dem":167,
    "gn:feature_class":"P",
    "gn:feature_code":"PPL",
    "gn:name":"\u017dalabi\u0161k\u0117s",
    "gn:population":0,
    "gn:timezone":"Europe/Vilnius",
    "iso:country":"LT",
    "name:lit_x_preferred":[
        "\u017dalabi\u0161k\u0117s"
    ],
    "wof:name":"Zalabiskes",
    "wof:placetype":"locality"
},
  "geometry": {"coordinates":[25.05814,54.27674],"type":"Point"}
}