{
  "type": "Feature",
  "properties": {
    "gn:admin1_code":"60",
    "gn:admin2_code":"57.0",
    "gn:asciiname":"Vilviskiai",
    "gn:country_code":"LT",
    "gn:dem":110,
    "gn:feature_class":"P",
    "gn:feature_code":"PPL",
    "gn:name":"Vilvi\u0161kiai",
    "gn:population":0,
    "gn:timezone":"Europe/Vilnius",
    "iso:country":"LT",
    "name:lit_x_preferred":[
        "Vilvi\u0161kiai"
    ],
    "wof:name":"Vilviskiai",
    "wof:placetype":"locality"
},
  "geometry": {"coordinates":[24.99743,55.75109000000001],"type":"Point"}
}