{
  "type": "Feature",
  "properties": {
    "gn:admin1_code":"58.0",
    "gn:admin2_code":"88.0",
    "gn:asciiname":"Versmininkai",
    "gn:country_code":"LT",
    "gn:dem":36,
    "gn:feature_class":"P",
    "gn:feature_code":"PPL",
    "gn:name":"Versmininkai",
    "gn:population":0,
    "gn:timezone":"Europe/Vilnius",
    "iso:country":"LT",
    "name:lit_x_preferred":[
        "Versmininkai"
    ],
    "name:und_x_variant":[
        "Versmeningken",
        "Vyarsmininkay",
        "Versm\u0117ninkai"
    ],
    "wof:name":"Versmininkai",
    "wof:placetype":"locality"
},
  "geometry": {"coordinates":[21.80686,55.30209],"type":"Point"}
}