{
  "type": "Feature",
  "properties": {
    "gn:admin1_code":"61",
    "gn:admin2_code":"71.0",
    "gn:asciiname":"Bloskiai",
    "gn:country_code":"LT",
    "gn:dem":121,
    "gn:feature_class":"P",
    "gn:feature_code":"PPL",
    "gn:name":"Blo\u0161kiai",
    "gn:population":0,
    "gn:timezone":"Europe/Vilnius",
    "iso:country":"LT",
    "name:lit_x_preferred":[
        "Blo\u0161kiai"
    ],
    "wof:name":"Bloskiai",
    "wof:placetype":"locality"
},
  "geometry": {"coordinates":[23.36322,55.70877],"type":"Point"}
}