{
  "type": "Feature",
  "properties": {
    "gn:admin1_code":"62.0",
    "gn:admin2_code":"63.0",
    "gn:asciiname":"Sodenai",
    "gn:country_code":"LT",
    "gn:dem":20,
    "gn:feature_class":"P",
    "gn:feature_code":"PPL",
    "gn:name":"Sod\u0117nai",
    "gn:population":0,
    "gn:timezone":"Europe/Vilnius",
    "iso:country":"LT",
    "name:und_x_variant":[
        "Zodenen",
        "Sod\u0117nai"
    ],
    "wof:name":"Sodenai",
    "wof:placetype":"locality"
},
  "geometry": {"coordinates":[22.06047,55.14841],"type":"Point"}
}