{
  "type": "Feature",
  "properties": {
    "gn:admin1_code":"59",
    "gn:admin2_code":"84.0",
    "gn:asciiname":"Zubriai",
    "gn:country_code":"LT",
    "gn:dem":41,
    "gn:feature_class":"P",
    "gn:feature_code":"PPL",
    "gn:name":"Zubriai",
    "gn:population":0,
    "gn:timezone":"Europe/Vilnius",
    "iso:country":"LT",
    "name:lit_x_preferred":[
        "Zubriai"
    ],
    "wof:name":"Zubriai",
    "wof:placetype":"locality"
},
  "geometry": {"coordinates":[22.87713,54.9512],"type":"Point"}
}