{
  "type": "Feature",
  "properties": {
    "gn:admin1_code":"63",
    "gn:admin2_code":"68.0",
    "gn:asciiname":"Vaistarai",
    "gn:country_code":"LT",
    "gn:dem":174,
    "gn:feature_class":"P",
    "gn:feature_code":"PPL",
    "gn:name":"Vai\u0161tarai",
    "gn:population":0,
    "gn:timezone":"Europe/Vilnius",
    "iso:country":"LT",
    "name:lit_x_preferred":[
        "Vai\u0161tarai"
    ],
    "wof:name":"Vaistarai",
    "wof:placetype":"locality"
},
  "geometry": {"coordinates":[22.04482,55.96199],"type":"Point"}
}