{
  "type": "Feature",
  "properties": {
    "gn:admin1_code":"64",
    "gn:admin2_code":"82.0",
    "gn:asciiname":"Skrebule",
    "gn:country_code":"LT",
    "gn:dem":155,
    "gn:feature_class":"P",
    "gn:feature_code":"PPL",
    "gn:name":"Skrebul\u0117",
    "gn:population":0,
    "gn:timezone":"Europe/Vilnius",
    "iso:country":"LT",
    "name:lit_x_preferred":[
        "Skrebul\u0117"
    ],
    "wof:name":"Skrebule",
    "wof:placetype":"locality"
},
  "geometry": {"coordinates":[25.68617,55.56671],"type":"Point"}
}