{
  "type": "Feature",
  "properties": {
    "gn:admin1_code":"64",
    "gn:admin2_code":"43.0",
    "gn:asciiname":"Lengveniskes",
    "gn:country_code":"LT",
    "gn:dem":156,
    "gn:feature_class":"P",
    "gn:feature_code":"PPL",
    "gn:name":"Lengveni\u0161k\u0117s",
    "gn:population":0,
    "gn:timezone":"Europe/Vilnius",
    "iso:country":"LT",
    "name:lit_x_preferred":[
        "Lengveni\u0161k\u0117s"
    ],
    "wof:name":"Lengveniskes",
    "wof:placetype":"locality"
},
  "geometry": {"coordinates":[26.24349,55.6828],"type":"Point"}
}