{
  "type": "Feature",
  "properties": {
    "gn:admin1_code":"64",
    "gn:admin2_code":"34.0",
    "gn:asciiname":"Pelyseles I",
    "gn:country_code":"LT",
    "gn:dem":89,
    "gn:feature_class":"P",
    "gn:feature_code":"PPL",
    "gn:name":"Pely\u0161\u0117l\u0117s I",
    "gn:population":0,
    "gn:timezone":"Europe/Vilnius",
    "iso:country":"LT",
    "name:lit_x_preferred":[
        "Pely\u0161\u0117l\u0117s I"
    ],
    "wof:name":"Pelyseles I",
    "wof:placetype":"locality"
},
  "geometry": {"coordinates":[24.83791,55.69565],"type":"Point"}
}