{
  "type": "Feature",
  "properties": {
    "gn:admin1_code":"65",
    "gn:admin2_code":"81.0",
    "gn:asciiname":"Vyliaudziai",
    "gn:country_code":"LT",
    "gn:dem":111,
    "gn:feature_class":"P",
    "gn:feature_code":"PPL",
    "gn:name":"Vyliaud\u017eiai",
    "gn:population":0,
    "gn:timezone":"Europe/Vilnius",
    "iso:country":"LT",
    "name:lit_x_preferred":[
        "Vyliaud\u017eiai"
    ],
    "wof:name":"Vyliaudziai",
    "wof:placetype":"locality"
},
  "geometry": {"coordinates":[24.86121,55.25583],"type":"Point"}
}