{
  "type": "Feature",
  "properties": {
    "gn:admin1_code":"62",
    "gn:admin2_code":"94.0",
    "gn:asciiname":"Uzakmeniai",
    "gn:country_code":"LT",
    "gn:dem":42,
    "gn:feature_class":"P",
    "gn:feature_code":"PPL",
    "gn:name":"U\u017eakmeniai",
    "gn:population":0,
    "gn:timezone":"Europe/Vilnius",
    "iso:country":"LT",
    "name:lit_x_preferred":[
        "U\u017eakmeniai"
    ],
    "wof:name":"Uzakmeniai",
    "wof:placetype":"locality"
},
  "geometry": {"coordinates":[22.73577,55.2591],"type":"Point"}
}