{
  "type": "Feature",
  "properties": {
    "gn:admin1_code":"64",
    "gn:admin2_code":"62.0",
    "gn:asciiname":"Adomaitiskiai",
    "gn:country_code":"LT",
    "gn:dem":183,
    "gn:feature_class":"P",
    "gn:feature_code":"PPL",
    "gn:name":"Adomaiti\u0161kiai",
    "gn:population":0,
    "gn:timezone":"Europe/Vilnius",
    "iso:country":"LT",
    "name:lit_x_preferred":[
        "Adomaiti\u0161kiai"
    ],
    "wof:name":"Adomaitiskiai",
    "wof:placetype":"locality"
},
  "geometry": {"coordinates":[25.41023,55.14234],"type":"Point"}
}