{
  "type": "Feature",
  "properties": {
    "gn:admin1_code":"57.0",
    "gn:admin2_code":"53.0",
    "gn:asciiname":"Deveikiskeliai",
    "gn:country_code":"LT",
    "gn:dem":73,
    "gn:feature_class":"P",
    "gn:feature_code":"PPL",
    "gn:name":"Deveiki\u0161k\u0117liai",
    "gn:population":0,
    "gn:timezone":"Europe/Vilnius",
    "iso:country":"LT",
    "name:und_x_variant":[
        "Doveykishki",
        "Deveiki\u0161k\u0117liai"
    ],
    "wof:name":"Deveikiskeliai",
    "wof:placetype":"locality"
},
  "geometry": {"coordinates":[23.72063,55.33546],"type":"Point"}
}