{
  "type": "Feature",
  "properties": {
    "gn:admin1_code":"61.0",
    "gn:admin2_code":"71.0",
    "gn:asciiname":"Zardeliai",
    "gn:country_code":"LT",
    "gn:dem":90,
    "gn:feature_class":"P",
    "gn:feature_code":"PPL",
    "gn:name":"\u017dardeliai",
    "gn:population":0,
    "gn:timezone":"Europe/Vilnius",
    "iso:country":"LT",
    "name:und_x_variant":[
        "Zhardelyay",
        "\u017dardeliai"
    ],
    "wof:name":"Zardeliai",
    "wof:placetype":"locality"
},
  "geometry": {"coordinates":[23.74172,55.8623],"type":"Point"}
}