{
  "type": "Feature",
  "properties": {
    "gn:admin1_code":"60",
    "gn:admin2_code":"57.0",
    "gn:asciiname":"Jurkstai",
    "gn:country_code":"LT",
    "gn:dem":116,
    "gn:feature_class":"P",
    "gn:feature_code":"PPL",
    "gn:name":"Jurk\u0161tai",
    "gn:population":0,
    "gn:timezone":"Europe/Vilnius",
    "iso:country":"LT",
    "name:lit_x_preferred":[
        "Jurk\u0161tai"
    ],
    "wof:name":"Jurkstai",
    "wof:placetype":"locality"
},
  "geometry": {"coordinates":[25.16635,55.75264],"type":"Point"}
}