{
  "type": "Feature",
  "properties": {
    "gn:admin1_code":"61.0",
    "gn:admin2_code":"54.0",
    "gn:asciiname":"Drupstai",
    "gn:country_code":"LT",
    "gn:dem":154,
    "gn:feature_class":"P",
    "gn:feature_code":"PPL",
    "gn:name":"Drupstai",
    "gn:population":0,
    "gn:timezone":"Europe/Vilnius",
    "iso:country":"LT",
    "name:und_x_variant":[
        "Drubotay",
        "Drupstai"
    ],
    "wof:name":"Drupstai",
    "wof:placetype":"locality"
},
  "geometry": {"coordinates":[22.90826,55.54042],"type":"Point"}
}