{
  "type": "Feature",
  "properties": {
    "gn:admin1_code":"60",
    "gn:admin2_code":"67.0",
    "gn:asciiname":"Stasiukai",
    "gn:country_code":"LT",
    "gn:dem":49,
    "gn:feature_class":"P",
    "gn:feature_code":"PPL",
    "gn:name":"Stasiukai",
    "gn:population":0,
    "gn:timezone":"Europe/Vilnius",
    "iso:country":"LT",
    "name:lit_x_preferred":[
        "Stasiukai"
    ],
    "wof:name":"Stasiukai",
    "wof:placetype":"locality"
},
  "geometry": {"coordinates":[24.16026,55.99409],"type":"Point"}
}