{
  "type": "Feature",
  "properties": {
    "gn:admin1_code":"0.0",
    "gn:asciiname":"Davilonys",
    "gn:cc2":"LT",
    "gn:country_code":"LT",
    "gn:dem":209,
    "gn:feature_class":"P",
    "gn:feature_code":"PPL",
    "gn:name":"Davilonys",
    "gn:population":0,
    "gn:timezone":"Europe/Vilnius",
    "iso:country":"LT",
    "name:und_x_variant":[
        "Dz\u2019vilany",
        "Davilonys"
    ],
    "wof:name":"Davilonys",
    "wof:placetype":"locality"
},
  "geometry": {"coordinates":[26.18333,55.08333],"type":"Point"}
}