{
  "type": "Feature",
  "properties": {
    "gn:admin1_code":"61.0",
    "gn:admin2_code":"47.0",
    "gn:asciiname":"Niuraiciai",
    "gn:country_code":"LT",
    "gn:dem":71,
    "gn:feature_class":"P",
    "gn:feature_code":"PPL",
    "gn:name":"Ni\u016brai\u010diai",
    "gn:population":0,
    "gn:timezone":"Europe/Vilnius",
    "iso:country":"LT",
    "name:und_x_variant":[
        "Nurai\u010diai",
        "Nurai\u010di\u0173",
        "Nyuraychyay",
        "Nuraychay",
        "Ni\u016brai\u010diai"
    ],
    "wof:name":"Niuraiciai",
    "wof:placetype":"locality"
},
  "geometry": {"coordinates":[23.55696,56.16803],"type":"Point"}
}