{
  "type": "Feature",
  "properties": {
    "gn:admin1_code":"64",
    "gn:admin2_code":"34.0",
    "gn:asciiname":"Rasciagalys",
    "gn:country_code":"LT",
    "gn:dem":93,
    "gn:feature_class":"P",
    "gn:feature_code":"PPL",
    "gn:name":"Ra\u0161\u010diagalys",
    "gn:population":0,
    "gn:timezone":"Europe/Vilnius",
    "iso:country":"LT",
    "name:lit_x_preferred":[
        "Ra\u0161\u010diagalys"
    ],
    "wof:name":"Rasciagalys",
    "wof:placetype":"locality"
},
  "geometry": {"coordinates":[24.84834,55.43379],"type":"Point"}
}