{
  "type": "Feature",
  "properties": {
    "gn:admin1_code":"63",
    "gn:admin2_code":"78.0",
    "gn:asciiname":"Zylaiciai",
    "gn:country_code":"LT",
    "gn:dem":155,
    "gn:feature_class":"P",
    "gn:feature_code":"PPL",
    "gn:name":"Zylaiciai",
    "gn:population":0,
    "gn:timezone":"Europe/Vilnius",
    "iso:country":"LT",
    "name:lit_x_preferred":[
        "Zylaiciai"
    ],
    "wof:name":"Zylaiciai",
    "wof:placetype":"locality"
},
  "geometry": {"coordinates":[22.35438,55.82514000000001],"type":"Point"}
}