{
  "type": "Feature",
  "properties": {
    "gn:admin1_code":"62",
    "gn:admin2_code":"87.0",
    "gn:asciiname":"Lasiske",
    "gn:country_code":"LT",
    "gn:dem":108,
    "gn:feature_class":"P",
    "gn:feature_code":"PPL",
    "gn:name":"La\u0161i\u0161k\u0117",
    "gn:population":0,
    "gn:timezone":"Europe/Vilnius",
    "iso:country":"LT",
    "name:lit_x_preferred":[
        "La\u0161i\u0161k\u0117"
    ],
    "wof:name":"Lasiske",
    "wof:placetype":"locality"
},
  "geometry": {"coordinates":[22.26611,55.44152],"type":"Point"}
}