{
  "type": "Feature",
  "properties": {
    "gn:admin1_code":"57",
    "gn:admin2_code":"49.0",
    "gn:asciiname":"Sarkiskes",
    "gn:country_code":"LT",
    "gn:dem":131,
    "gn:feature_class":"P",
    "gn:feature_code":"PPL",
    "gn:name":"\u0160arki\u0161k\u0117s",
    "gn:population":0,
    "gn:timezone":"Europe/Vilnius",
    "iso:country":"LT",
    "name:lit_x_preferred":[
        "\u0160arki\u0161k\u0117s"
    ],
    "wof:name":"Sarkiskes",
    "wof:placetype":"locality"
},
  "geometry": {"coordinates":[24.51591,54.75935],"type":"Point"}
}