{
  "type": "Feature",
  "properties": {
    "gn:admin1_code":"61.0",
    "gn:admin2_code":"29.0",
    "gn:asciiname":"Marmai",
    "gn:country_code":"LT",
    "gn:dem":106,
    "gn:feature_class":"P",
    "gn:feature_code":"PPL",
    "gn:name":"Marmai",
    "gn:population":0,
    "gn:timezone":"Europe/Vilnius",
    "iso:country":"LT",
    "name:und_x_variant":[
        "U\u017esieniai"
    ],
    "wof:name":"Marmai",
    "wof:placetype":"locality"
},
  "geometry": {"coordinates":[23.05002,55.95591],"type":"Point"}
}