{
  "type": "Feature",
  "properties": {
    "gn:admin1_code":"65",
    "gn:admin2_code":"86.0",
    "gn:asciiname":"Lugiai",
    "gn:country_code":"LT",
    "gn:dem":174,
    "gn:feature_class":"P",
    "gn:feature_code":"PPL",
    "gn:name":"Lugiai",
    "gn:population":0,
    "gn:timezone":"Europe/Vilnius",
    "iso:country":"LT",
    "name:lit_x_preferred":[
        "Lugiai"
    ],
    "wof:name":"Lugiai",
    "wof:placetype":"locality"
},
  "geometry": {"coordinates":[26.1684,54.99622],"type":"Point"}
}