{
  "type": "Feature",
  "properties": {
    "gn:admin1_code":"61.0",
    "gn:admin2_code":"71.0",
    "gn:asciiname":"Abrieskai",
    "gn:country_code":"LT",
    "gn:dem":120,
    "gn:feature_class":"P",
    "gn:feature_code":"PPL",
    "gn:name":"Abrieskai",
    "gn:population":0,
    "gn:timezone":"Europe/Vilnius",
    "iso:country":"LT",
    "name:und_x_variant":[
        "Obrzhesky",
        "Obrzheskyay",
        "Abrieskai"
    ],
    "wof:name":"Abrieskai",
    "wof:placetype":"locality"
},
  "geometry": {"coordinates":[23.47364,55.63192],"type":"Point"}
}