{
  "type": "Feature",
  "properties": {
    "gn:admin1_code":"63.0",
    "gn:admin2_code":"74.0",
    "gn:asciiname":"Patyris",
    "gn:country_code":"LT",
    "gn:dem":110,
    "gn:feature_class":"P",
    "gn:feature_code":"PPL",
    "gn:name":"Patyris",
    "gn:population":0,
    "gn:timezone":"Europe/Vilnius",
    "iso:country":"LT",
    "name:und_x_variant":[
        "Potiryay",
        "Patyris"
    ],
    "wof:name":"Patyris",
    "wof:placetype":"locality"
},
  "geometry": {"coordinates":[22.02173,55.78611],"type":"Point"}
}