{
  "type": "Feature",
  "properties": {
    "gn:admin1_code":"64",
    "gn:admin2_code":"34.0",
    "gn:asciiname":"Ragaisiai",
    "gn:country_code":"LT",
    "gn:dem":93,
    "gn:feature_class":"P",
    "gn:feature_code":"PPL",
    "gn:name":"Ragaisiai",
    "gn:population":0,
    "gn:timezone":"Europe/Vilnius",
    "iso:country":"LT",
    "name:lit_x_preferred":[
        "Ragaisiai"
    ],
    "wof:name":"Ragaisiai",
    "wof:placetype":"locality"
},
  "geometry": {"coordinates":[25.27434,55.64169],"type":"Point"}
}