{
  "type": "Feature",
  "properties": {
    "gn:admin1_code":"0.0",
    "gn:asciiname":"Padube",
    "gn:cc2":"LT",
    "gn:country_code":"LT",
    "gn:dem":168,
    "gn:feature_class":"P",
    "gn:feature_code":"PPL",
    "gn:name":"Padub\u0117",
    "gn:population":0,
    "gn:timezone":"Europe/Vilnius",
    "iso:country":"LT",
    "name:und_x_variant":[
        "Podembe",
        "Padub\u0117"
    ],
    "wof:name":"Padube",
    "wof:placetype":"locality"
},
  "geometry": {"coordinates":[25.18333,54.91667],"type":"Point"}
}