{
  "type": "Feature",
  "properties": {
    "gn:admin1_code":"57.0",
    "gn:admin2_code":"72.0",
    "gn:asciiname":"Sliuziai",
    "gn:country_code":"LT",
    "gn:dem":75,
    "gn:feature_class":"P",
    "gn:feature_code":"PPL",
    "gn:name":"\u0160liu\u017eiai",
    "gn:population":0,
    "gn:timezone":"Europe/Vilnius",
    "iso:country":"LT",
    "name:und_x_variant":[
        "Shlyuzhyay",
        "\u0160liu\u017ei\u0173 Pagyn\u0117vys",
        "\u0160liu\u017eiai"
    ],
    "wof:name":"Sliuziai",
    "wof:placetype":"locality"
},
  "geometry": {"coordinates":[23.57736,55.28213],"type":"Point"}
}