{
  "type": "Feature",
  "properties": {
    "gn:admin1_code":"60",
    "gn:admin2_code":"27.0",
    "gn:asciiname":"Dluzniava",
    "gn:country_code":"LT",
    "gn:dem":51,
    "gn:feature_class":"P",
    "gn:feature_code":"PPL",
    "gn:name":"Dlu\u017eniava",
    "gn:population":0,
    "gn:timezone":"Europe/Vilnius",
    "iso:country":"LT",
    "name:lit_x_preferred":[
        "Dlu\u017eniava"
    ],
    "wof:name":"Dluzniava",
    "wof:placetype":"locality"
},
  "geometry": {"coordinates":[24.19123,55.52029],"type":"Point"}
}