{
  "type": "Feature",
  "properties": {
    "gn:admin1_code":"62",
    "gn:admin2_code":"77.0",
    "gn:asciiname":"Pamiliusiai",
    "gn:country_code":"LT",
    "gn:dem":26,
    "gn:feature_class":"P",
    "gn:feature_code":"PPL",
    "gn:name":"Pamiliu\u0161iai",
    "gn:population":0,
    "gn:timezone":"Europe/Vilnius",
    "iso:country":"LT",
    "name:lit_x_preferred":[
        "Pamiliu\u0161iai"
    ],
    "wof:name":"Pamiliusiai",
    "wof:placetype":"locality"
},
  "geometry": {"coordinates":[22.38811,55.24861],"type":"Point"}
}