{
  "type": "Feature",
  "properties": {
    "gn:admin1_code":"62.0",
    "gn:admin2_code":"77.0",
    "gn:asciiname":"Dirvenai",
    "gn:country_code":"LT",
    "gn:dem":67,
    "gn:feature_class":"P",
    "gn:feature_code":"PPL",
    "gn:name":"Dirv\u0117nai",
    "gn:population":0,
    "gn:timezone":"Europe/Vilnius",
    "iso:country":"LT",
    "name:und_x_variant":[
        "Dirv\u0117nai",
        "Starklaukis"
    ],
    "wof:name":"Dirvenai",
    "wof:placetype":"locality"
},
  "geometry": {"coordinates":[22.00898,55.34522],"type":"Point"}
}