{
  "type": "Feature",
  "properties": {
    "gn:admin1_code":"65",
    "gn:admin2_code":"85.0",
    "gn:asciiname":"Vidnapolis",
    "gn:country_code":"LT",
    "gn:dem":189,
    "gn:feature_class":"P",
    "gn:feature_code":"PPL",
    "gn:name":"Vidnapolis",
    "gn:population":0,
    "gn:timezone":"Europe/Vilnius",
    "iso:country":"LT",
    "name:lit_x_preferred":[
        "Vidnapolis"
    ],
    "wof:name":"Vidnapolis",
    "wof:placetype":"locality"
},
  "geometry": {"coordinates":[25.36363,54.45273],"type":"Point"}
}