{
  "type": "Feature",
  "properties": {
    "gn:admin1_code":"65",
    "gn:admin2_code":"13.0",
    "gn:asciiname":"Juskonys",
    "gn:country_code":"LT",
    "gn:dem":177,
    "gn:feature_class":"P",
    "gn:feature_code":"PPL",
    "gn:name":"Ju\u0161konys",
    "gn:population":0,
    "gn:timezone":"Europe/Vilnius",
    "iso:country":"LT",
    "name:lit_x_preferred":[
        "Ju\u0161konys"
    ],
    "wof:name":"Juskonys",
    "wof:placetype":"locality"
},
  "geometry": {"coordinates":[25.17593,54.89392],"type":"Point"}
}