{
  "type": "Feature",
  "properties": {
    "gn:admin1_code":"57.0",
    "gn:admin2_code":"49.0",
    "gn:asciiname":"Karsakai",
    "gn:country_code":"LT",
    "gn:dem":120,
    "gn:feature_class":"P",
    "gn:feature_code":"PPL",
    "gn:name":"Karsakai",
    "gn:population":0,
    "gn:timezone":"Europe/Vilnius",
    "iso:country":"LT",
    "name:und_x_variant":[
        "Karsakai Pirmieji",
        "Karsakai",
        "Korsaki Pervoye",
        "Karsakai I"
    ],
    "wof:name":"Karsakai",
    "wof:placetype":"locality"
},
  "geometry": {"coordinates":[24.64873,54.87399],"type":"Point"}
}