{
  "type": "Feature",
  "properties": {
    "gn:admin1_code":"61",
    "gn:admin2_code":"71.0",
    "gn:asciiname":"Rinktineliai",
    "gn:country_code":"LT",
    "gn:dem":78,
    "gn:feature_class":"P",
    "gn:feature_code":"PPL",
    "gn:name":"Rinktin\u0117liai",
    "gn:population":0,
    "gn:timezone":"Europe/Vilnius",
    "iso:country":"LT",
    "name:lit_x_preferred":[
        "Rinktin\u0117liai"
    ],
    "wof:name":"Rinktineliai",
    "wof:placetype":"locality"
},
  "geometry": {"coordinates":[23.88146,55.5799],"type":"Point"}
}