{
  "type": "Feature",
  "properties": {
    "gn:admin1_code":"64.0",
    "gn:admin2_code":"45.0",
    "gn:asciiname":"Gaide",
    "gn:country_code":"LT",
    "gn:dem":157,
    "gn:feature_class":"P",
    "gn:feature_code":"PPL",
    "gn:name":"Gaid\u0117",
    "gn:population":0,
    "gn:timezone":"Europe/Vilnius",
    "iso:country":"LT",
    "name:und_x_variant":[
        "Gaydy",
        "Gajdy",
        "Gaid\u0117"
    ],
    "wof:name":"Gaide",
    "wof:placetype":"locality"
},
  "geometry": {"coordinates":[26.55356,55.55933],"type":"Point"}
}