{
  "type": "Feature",
  "properties": {
    "gn:admin1_code":"59",
    "gn:admin2_code":"58.0",
    "gn:asciiname":"Sernine",
    "gn:country_code":"LT",
    "gn:dem":62,
    "gn:feature_class":"P",
    "gn:feature_code":"PPL",
    "gn:name":"\u0160ernin\u0117",
    "gn:population":0,
    "gn:timezone":"Europe/Vilnius",
    "iso:country":"LT",
    "name:lit_x_preferred":[
        "\u0160ernin\u0117"
    ],
    "wof:name":"Sernine",
    "wof:placetype":"locality"
},
  "geometry": {"coordinates":[23.58372,54.70276],"type":"Point"}
}