{
  "type": "Feature",
  "properties": {
    "gn:admin1_code":"62.0",
    "gn:admin2_code":"87.0",
    "gn:asciiname":"Kliukiai",
    "gn:country_code":"LT",
    "gn:dem":147,
    "gn:feature_class":"P",
    "gn:feature_code":"PPL",
    "gn:name":"Kli\u016bkiai",
    "gn:population":0,
    "gn:timezone":"Europe/Vilnius",
    "iso:country":"LT",
    "name:und_x_variant":[
        "Klukyay",
        "Kli\u016bkiai"
    ],
    "wof:name":"Kliukiai",
    "wof:placetype":"locality"
},
  "geometry": {"coordinates":[22.41134,55.47508000000001],"type":"Point"}
}