{
  "type": "Feature",
  "properties": {
    "gn:admin1_code":"64.0",
    "gn:admin2_code":"34.0",
    "gn:asciiname":"Mikieriai",
    "gn:country_code":"LT",
    "gn:dem":90,
    "gn:feature_class":"P",
    "gn:feature_code":"PPL",
    "gn:name":"Mikieriai",
    "gn:population":0,
    "gn:timezone":"Europe/Vilnius",
    "iso:country":"LT",
    "name:und_x_variant":[
        "Mikery",
        "Mikieriai",
        "Mikeryay",
        "Mikeriai"
    ],
    "wof:name":"Mikieriai",
    "wof:placetype":"locality"
},
  "geometry": {"coordinates":[25.17504,55.66451],"type":"Point"}
}