{
  "type": "Feature",
  "properties": {
    "gn:admin1_code":"64",
    "gn:admin2_code":"34.0",
    "gn:asciiname":"Zibuciai",
    "gn:country_code":"LT",
    "gn:dem":91,
    "gn:feature_class":"P",
    "gn:feature_code":"PPL",
    "gn:name":"\u017dibu\u010diai",
    "gn:population":0,
    "gn:timezone":"Europe/Vilnius",
    "iso:country":"LT",
    "name:lit_x_preferred":[
        "\u017dibu\u010diai"
    ],
    "wof:name":"Zibuciai",
    "wof:placetype":"locality"
},
  "geometry": {"coordinates":[24.83387,55.40638000000001],"type":"Point"}
}