{
  "type": "Feature",
  "properties": {
    "gn:admin1_code":"57.0",
    "gn:admin2_code":"46.0",
    "gn:asciiname":"Kryziauka",
    "gn:country_code":"LT",
    "gn:dem":73,
    "gn:feature_class":"P",
    "gn:feature_code":"PPL",
    "gn:name":"Kry\u017eiauka",
    "gn:population":0,
    "gn:timezone":"Europe/Vilnius",
    "iso:country":"LT",
    "name:und_x_variant":[
        "Krizhyauka",
        "Kry\u017eiauka"
    ],
    "wof:name":"Kryziauka",
    "wof:placetype":"locality"
},
  "geometry": {"coordinates":[24.45892000000001,55.13542],"type":"Point"}
}