{
  "type": "Feature",
  "properties": {
    "gn:admin1_code":"58.0",
    "gn:admin2_code":"25.0",
    "gn:asciiname":"Paliepgiriai",
    "gn:country_code":"LT",
    "gn:dem":11,
    "gn:feature_class":"P",
    "gn:feature_code":"PPL",
    "gn:name":"Paliepgiriai",
    "gn:population":0,
    "gn:timezone":"Europe/Vilnius",
    "iso:country":"LT",
    "name:und_x_variant":[
        "Paliepgirai",
        "Pal\u2019epgirey",
        "Paliepgiri\u0173",
        "Paliepgiriai"
    ],
    "wof:name":"Paliepgiriai",
    "wof:placetype":"locality"
},
  "geometry": {"coordinates":[21.09793,55.96701],"type":"Point"}
}