{
  "type": "Feature",
  "properties": {
    "gn:admin1_code":"59.0",
    "gn:admin2_code":"84.0",
    "gn:asciiname":"Stalioriai",
    "gn:country_code":"LT",
    "gn:dem":65,
    "gn:feature_class":"P",
    "gn:feature_code":"PPL",
    "gn:name":"Stalioriai",
    "gn:population":0,
    "gn:timezone":"Europe/Vilnius",
    "iso:country":"LT",
    "name:und_x_variant":[
        "Prie Staliorai",
        "Stolarishki",
        "Stalioriai"
    ],
    "wof:name":"Stalioriai",
    "wof:placetype":"locality"
},
  "geometry": {"coordinates":[23.28813,54.94151],"type":"Point"}
}