{
  "type": "Feature",
  "properties": {
    "gn:admin1_code":"62.0",
    "gn:admin2_code":"94.0",
    "gn:asciiname":"Gedziai",
    "gn:country_code":"LT",
    "gn:dem":35,
    "gn:feature_class":"P",
    "gn:feature_code":"PPL",
    "gn:name":"Ged\u017eiai",
    "gn:population":0,
    "gn:timezone":"Europe/Vilnius",
    "iso:country":"LT",
    "name:und_x_variant":[
        "Gedzi",
        "Ged\u017eiai"
    ],
    "wof:name":"Gedziai",
    "wof:placetype":"locality"
},
  "geometry": {"coordinates":[22.72983,55.14551],"type":"Point"}
}