{
  "type": "Feature",
  "properties": {
    "gn:admin1_code":"60.0",
    "gn:admin2_code":"27.0",
    "gn:asciiname":"Tautkunai",
    "gn:country_code":"LT",
    "gn:dem":57,
    "gn:feature_class":"P",
    "gn:feature_code":"PPL",
    "gn:name":"Tautk\u016bnai",
    "gn:population":0,
    "gn:timezone":"Europe/Vilnius",
    "iso:country":"LT",
    "name:und_x_variant":[
        "Tautkuny",
        "Tautk\u016bnai"
    ],
    "wof:name":"Tautkunai",
    "wof:placetype":"locality"
},
  "geometry": {"coordinates":[24.46598,55.68273000000001],"type":"Point"}
}