{
  "type": "Feature",
  "properties": {
    "gn:admin1_code":"0.0",
    "gn:asciiname":"Motiejunai",
    "gn:cc2":"LT",
    "gn:country_code":"LT",
    "gn:dem":116,
    "gn:feature_class":"P",
    "gn:feature_code":"PPL",
    "gn:name":"Motiej\u016bnai",
    "gn:population":0,
    "gn:timezone":"Europe/Vilnius",
    "iso:country":"LT",
    "name:und_x_variant":[
        "Matseyun\u2019tse",
        "Motiej\u016bn\u0173",
        "Moteyunay",
        "Motiej\u016bnai"
    ],
    "wof:name":"Motiejunai",
    "wof:placetype":"locality"
},
  "geometry": {"coordinates":[25.01667,55.03333000000001],"type":"Point"}
}