{
  "type": "Feature",
  "properties": {
    "gn:admin1_code":"64",
    "gn:admin2_code":"82.0",
    "gn:asciiname":"Karciupys",
    "gn:country_code":"LT",
    "gn:dem":169,
    "gn:feature_class":"P",
    "gn:feature_code":"PPL",
    "gn:name":"Kar\u010diupys",
    "gn:population":0,
    "gn:timezone":"Europe/Vilnius",
    "iso:country":"LT",
    "name:lit_x_preferred":[
        "Kar\u010diupys"
    ],
    "wof:name":"Karciupys",
    "wof:placetype":"locality"
},
  "geometry": {"coordinates":[25.45991,55.51488000000001],"type":"Point"}
}