{
  "type": "Feature",
  "properties": {
    "gn:admin1_code":"56.0",
    "gn:admin2_code":"11.0",
    "gn:asciiname":"Pupasodis",
    "gn:country_code":"LT",
    "gn:dem":132,
    "gn:feature_class":"P",
    "gn:feature_code":"PPL",
    "gn:name":"Pupasodis",
    "gn:population":0,
    "gn:timezone":"Europe/Vilnius",
    "iso:country":"LT",
    "name:und_x_variant":[
        "Pupasodis Pirmieji",
        "Poposadze",
        "Pupasod\u017ei\u0173",
        "Pupasodis"
    ],
    "wof:name":"Pupasodis",
    "wof:placetype":"locality"
},
  "geometry": {"coordinates":[23.93677000000001,54.30367],"type":"Point"}
}