{
  "type": "Feature",
  "properties": {
    "gn:admin1_code":"60",
    "gn:admin2_code":"57.0",
    "gn:asciiname":"Bagdoniskiai",
    "gn:country_code":"LT",
    "gn:dem":71,
    "gn:feature_class":"P",
    "gn:feature_code":"PPL",
    "gn:name":"Bagdoni\u0161kiai",
    "gn:population":0,
    "gn:timezone":"Europe/Vilnius",
    "iso:country":"LT",
    "name:lit_x_preferred":[
        "Bagdoni\u0161kiai"
    ],
    "wof:name":"Bagdoniskiai",
    "wof:placetype":"locality"
},
  "geometry": {"coordinates":[24.74035,55.80505],"type":"Point"}
}