{
  "type": "Feature",
  "properties": {
    "gn:admin1_code":"64",
    "gn:admin2_code":"43.0",
    "gn:asciiname":"Butiskes",
    "gn:country_code":"LT",
    "gn:dem":154,
    "gn:feature_class":"P",
    "gn:feature_code":"PPL",
    "gn:name":"Buti\u0161k\u0117s",
    "gn:population":0,
    "gn:timezone":"Europe/Vilnius",
    "iso:country":"LT",
    "name:lit_x_preferred":[
        "Buti\u0161k\u0117s"
    ],
    "wof:name":"Butiskes",
    "wof:placetype":"locality"
},
  "geometry": {"coordinates":[25.96474,55.82355],"type":"Point"}
}