{
  "type": "Feature",
  "properties": {
    "gn:admin1_code":"61.0",
    "gn:admin2_code":"47.0",
    "gn:asciiname":"Berzininkai",
    "gn:country_code":"LT",
    "gn:dem":47,
    "gn:feature_class":"P",
    "gn:feature_code":"PPL",
    "gn:name":"Ber\u017eininkai",
    "gn:population":0,
    "gn:timezone":"Europe/Vilnius",
    "iso:country":"LT",
    "name:und_x_variant":[
        "Berzhininkay",
        "Ber\u017eininkai"
    ],
    "wof:name":"Berzininkai",
    "wof:placetype":"locality"
},
  "geometry": {"coordinates":[23.64351,56.22368],"type":"Point"}
}