{
  "type": "Feature",
  "properties": {
    "gn:admin1_code":"61",
    "gn:admin2_code":"65.0",
    "gn:asciiname":"Liesai",
    "gn:country_code":"LT",
    "gn:dem":48,
    "gn:feature_class":"P",
    "gn:feature_code":"PPL",
    "gn:name":"Liesai",
    "gn:population":0,
    "gn:timezone":"Europe/Vilnius",
    "iso:country":"LT",
    "name:lit_x_preferred":[
        "Liesai"
    ],
    "wof:name":"Liesai",
    "wof:placetype":"locality"
},
  "geometry": {"coordinates":[23.89825,56.23264],"type":"Point"}
}