{
  "type": "Feature",
  "properties": {
    "gn:admin1_code":"57",
    "gn:admin2_code":"19.0",
    "gn:asciiname":"Azuolynas",
    "gn:country_code":"LT",
    "gn:dem":63,
    "gn:feature_class":"P",
    "gn:feature_code":"PPL",
    "gn:name":"A\u017euolynas",
    "gn:population":0,
    "gn:timezone":"Europe/Vilnius",
    "iso:country":"LT",
    "name:lit_x_preferred":[
        "A\u017euolynas"
    ],
    "wof:name":"Azuolynas",
    "wof:placetype":"locality"
},
  "geometry": {"coordinates":[23.93301,55.01936],"type":"Point"}
}