{
  "type": "Feature",
  "properties": {
    "gn:admin1_code":"58",
    "gn:admin2_code":"75.0",
    "gn:asciiname":"Visgaudziai",
    "gn:country_code":"LT",
    "gn:dem":111,
    "gn:feature_class":"P",
    "gn:feature_code":"PPL",
    "gn:name":"Visgaud\u017eiai",
    "gn:population":0,
    "gn:timezone":"Europe/Vilnius",
    "iso:country":"LT",
    "name:lit_x_preferred":[
        "Visgaud\u017eiai"
    ],
    "wof:name":"Visgaudziai",
    "wof:placetype":"locality"
},
  "geometry": {"coordinates":[21.90632,56.31599],"type":"Point"}
}