{
  "type": "Feature",
  "properties": {
    "gn:admin1_code":"56",
    "gn:admin2_code":"38.0",
    "gn:asciiname":"Tetervine",
    "gn:country_code":"LT",
    "gn:dem":130,
    "gn:feature_class":"P",
    "gn:feature_code":"PPL",
    "gn:name":"Tetervin\u0117",
    "gn:population":0,
    "gn:timezone":"Europe/Vilnius",
    "iso:country":"LT",
    "name:lit_x_preferred":[
        "Tetervin\u0117"
    ],
    "wof:name":"Tetervine",
    "wof:placetype":"locality"
},
  "geometry": {"coordinates":[24.06605,54.09989],"type":"Point"}
}