{
  "type": "Feature",
  "properties": {
    "gn:admin1_code":"60.0",
    "gn:asciiname":"Puciakalne",
    "gn:cc2":"LT",
    "gn:country_code":"LT",
    "gn:dem":71,
    "gn:feature_class":"P",
    "gn:feature_code":"PPL",
    "gn:name":"Pu\u010diakaln\u0117",
    "gn:population":0,
    "gn:timezone":"Europe/Vilnius",
    "iso:country":"LT",
    "name:und_x_variant":[
        "Pu\u010diakin\u0117",
        "Puchekal\u2019ne",
        "Puchekalnis",
        "Puchyakal\u2019ne",
        "Pu\u010diakaln\u0117"
    ],
    "wof:name":"Puciakalne",
    "wof:placetype":"locality"
},
  "geometry": {"coordinates":[24.89,56.41222],"type":"Point"}
}