{
  "type": "Feature",
  "properties": {
    "gn:admin1_code":"57",
    "gn:admin2_code":"46.0",
    "gn:asciiname":"Petryne",
    "gn:country_code":"LT",
    "gn:dem":71,
    "gn:feature_class":"P",
    "gn:feature_code":"PPL",
    "gn:name":"Petryn\u0117",
    "gn:population":0,
    "gn:timezone":"Europe/Vilnius",
    "iso:country":"LT",
    "name:lit_x_preferred":[
        "Petryn\u0117"
    ],
    "wof:name":"Petryne",
    "wof:placetype":"locality"
},
  "geometry": {"coordinates":[24.256,55.02898],"type":"Point"}
}