{
  "type": "Feature",
  "properties": {
    "gn:admin1_code":"60",
    "gn:admin2_code":"73.0",
    "gn:asciiname":"Uvainiai",
    "gn:country_code":"LT",
    "gn:dem":93,
    "gn:feature_class":"P",
    "gn:feature_code":"PPL",
    "gn:name":"Uvainiai",
    "gn:population":0,
    "gn:timezone":"Europe/Vilnius",
    "iso:country":"LT",
    "name:lit_x_preferred":[
        "Uvainiai"
    ],
    "wof:name":"Uvainiai",
    "wof:placetype":"locality"
},
  "geometry": {"coordinates":[25.36965,55.96045],"type":"Point"}
}