{
  "type": "Feature",
  "properties": {
    "gn:admin1_code":"58.0",
    "gn:admin2_code":"88.0",
    "gn:asciiname":"Uzkamoniai",
    "gn:country_code":"LT",
    "gn:dem":19,
    "gn:feature_class":"P",
    "gn:feature_code":"PPL",
    "gn:name":"U\u017ekamoniai",
    "gn:population":0,
    "gn:timezone":"Europe/Vilnius",
    "iso:country":"LT",
    "name:lit_x_preferred":[
        "U\u017ekamoniai"
    ],
    "name:und_x_variant":[
        "Uzhkamonyay",
        "Uzhkamonen",
        "U\u017ekamun\u0117"
    ],
    "wof:name":"Uzkamoniai",
    "wof:placetype":"locality"
},
  "geometry": {"coordinates":[21.81887,55.21776],"type":"Point"}
}