{
  "type": "Feature",
  "properties": {
    "gn:admin1_code":"65",
    "gn:admin2_code":"13.0",
    "gn:asciiname":"Raksonys",
    "gn:country_code":"LT",
    "gn:dem":171,
    "gn:feature_class":"P",
    "gn:feature_code":"PPL",
    "gn:name":"Rak\u0161onys",
    "gn:population":0,
    "gn:timezone":"Europe/Vilnius",
    "iso:country":"LT",
    "name:lit_x_preferred":[
        "Rak\u0161onys"
    ],
    "wof:name":"Raksonys",
    "wof:placetype":"locality"
},
  "geometry": {"coordinates":[25.46964,54.99432],"type":"Point"}
}