{
  "type": "Feature",
  "properties": {
    "gn:admin1_code":"59",
    "gn:admin2_code":"48.0",
    "gn:asciiname":"Sarkiai",
    "gn:country_code":"LT",
    "gn:dem":135,
    "gn:feature_class":"P",
    "gn:feature_code":"PPL",
    "gn:name":"\u0160arkiai",
    "gn:population":0,
    "gn:timezone":"Europe/Vilnius",
    "iso:country":"LT",
    "name:lit_x_preferred":[
        "\u0160arkiai"
    ],
    "wof:name":"Sarkiai",
    "wof:placetype":"locality"
},
  "geometry": {"coordinates":[23.33429,54.40764],"type":"Point"}
}