{
  "type": "Feature",
  "properties": {
    "gn:admin1_code":"60.0",
    "gn:admin2_code":"67.0",
    "gn:asciiname":"Siukstoniai",
    "gn:country_code":"LT",
    "gn:dem":45,
    "gn:feature_class":"P",
    "gn:feature_code":"PPL",
    "gn:name":"\u0160iuk\u0161toniai",
    "gn:population":0,
    "gn:timezone":"Europe/Vilnius",
    "iso:country":"LT",
    "name:und_x_variant":[
        "\u0160yk\u0161toniai",
        "Shikstonyay",
        "Shikshtonyay",
        "\u0160iuk\u0161toniai"
    ],
    "wof:name":"Siukstoniai",
    "wof:placetype":"locality"
},
  "geometry": {"coordinates":[24.16776,56.07473],"type":"Point"}
}