{
  "type": "Feature",
  "properties": {
    "gn:admin1_code":"65.0",
    "gn:admin2_code":"13.0",
    "gn:asciiname":"Asmenele",
    "gn:country_code":"LT",
    "gn:dem":168,
    "gn:feature_class":"P",
    "gn:feature_code":"PPL",
    "gn:name":"A\u0161men\u0117l\u0117",
    "gn:population":0,
    "gn:timezone":"Europe/Vilnius",
    "iso:country":"LT",
    "name:lit_x_preferred":[
        "A\u0161men\u0117l\u0117"
    ],
    "name:lit_x_variant":[
        "A\u0161menel\u0117"
    ],
    "wof:name":"Asmenele",
    "wof:placetype":"locality"
},
  "geometry": {"coordinates":[25.53389,54.62667],"type":"Point"}
}