{
  "type": "Feature",
  "properties": {
    "gn:admin1_code":"65",
    "gn:admin2_code":"89.0",
    "gn:asciiname":"Dirzioniskes",
    "gn:country_code":"LT",
    "gn:dem":149,
    "gn:feature_class":"P",
    "gn:feature_code":"PPL",
    "gn:name":"Dir\u017eioni\u0161k\u0117s",
    "gn:population":0,
    "gn:timezone":"Europe/Vilnius",
    "iso:country":"LT",
    "name:lit_x_preferred":[
        "Dir\u017eioni\u0161k\u0117s"
    ],
    "wof:name":"Dirzioniskes",
    "wof:placetype":"locality"
},
  "geometry": {"coordinates":[25.03671,54.88921],"type":"Point"}
}