{
  "type": "Feature",
  "properties": {
    "gn:admin1_code":"65",
    "gn:admin2_code":"13.0",
    "gn:asciiname":"Buiniskes",
    "gn:country_code":"LT",
    "gn:dem":177,
    "gn:feature_class":"P",
    "gn:feature_code":"PPL",
    "gn:name":"Buini\u0161k\u0117s",
    "gn:population":0,
    "gn:timezone":"Europe/Vilnius",
    "iso:country":"LT",
    "name:lit_x_preferred":[
        "Buini\u0161k\u0117s"
    ],
    "wof:name":"Buiniskes",
    "wof:placetype":"locality"
},
  "geometry": {"coordinates":[25.07413,54.76131],"type":"Point"}
}