{
  "type": "Feature",
  "properties": {
    "gn:admin1_code":"61.0",
    "gn:admin2_code":"54.0",
    "gn:asciiname":"Linkauciai",
    "gn:country_code":"LT",
    "gn:dem":148,
    "gn:feature_class":"P",
    "gn:feature_code":"PPL",
    "gn:name":"Linkau\u010diai",
    "gn:population":0,
    "gn:timezone":"Europe/Vilnius",
    "iso:country":"LT",
    "name:und_x_variant":[
        "Linkau\u010dius",
        "Linkau\u010diai",
        "Linkava",
        "Linkai\u010diai"
    ],
    "wof:name":"Linkauciai",
    "wof:placetype":"locality"
},
  "geometry": {"coordinates":[22.65954,55.63181],"type":"Point"}
}