{
  "type": "Feature",
  "properties": {
    "gn:admin1_code":"64",
    "gn:admin2_code":"43.0",
    "gn:asciiname":"Ulytele",
    "gn:country_code":"LT",
    "gn:dem":149,
    "gn:feature_class":"P",
    "gn:feature_code":"PPL",
    "gn:name":"Ulyt\u0117l\u0117",
    "gn:population":0,
    "gn:timezone":"Europe/Vilnius",
    "iso:country":"LT",
    "name:lit_x_preferred":[
        "Ulyt\u0117l\u0117"
    ],
    "wof:name":"Ulytele",
    "wof:placetype":"locality"
},
  "geometry": {"coordinates":[26.04199,55.92921],"type":"Point"}
}