{
  "type": "Feature",
  "properties": {
    "gn:admin1_code":"65.0",
    "gn:admin2_code":"86.0",
    "gn:asciiname":"Vaiskunai",
    "gn:country_code":"LT",
    "gn:dem":197,
    "gn:feature_class":"P",
    "gn:feature_code":"PPL",
    "gn:name":"Vai\u0161k\u016bnai",
    "gn:population":0,
    "gn:timezone":"Europe/Vilnius",
    "iso:country":"LT",
    "name:und_x_variant":[
        "Voyshkuny",
        "Vai\u0161k\u016bnai"
    ],
    "wof:name":"Vaiskunai",
    "wof:placetype":"locality"
},
  "geometry": {"coordinates":[26.09658,55.12564],"type":"Point"}
}