{
  "type": "Feature",
  "properties": {
    "gn:admin1_code":"64",
    "gn:admin2_code":"62.0",
    "gn:asciiname":"Gabrieliskis",
    "gn:country_code":"LT",
    "gn:dem":129,
    "gn:feature_class":"P",
    "gn:feature_code":"PPL",
    "gn:name":"Gabrieli\u0161kis",
    "gn:population":0,
    "gn:timezone":"Europe/Vilnius",
    "iso:country":"LT",
    "name:lit_x_preferred":[
        "Gabrieli\u0161kis"
    ],
    "wof:name":"Gabrieliskis",
    "wof:placetype":"locality"
},
  "geometry": {"coordinates":[25.20756,55.36648],"type":"Point"}
}