{
  "type": "Feature",
  "properties": {
    "gn:admin1_code":"62.0",
    "gn:admin2_code":"94.0",
    "gn:asciiname":"Paantvardys",
    "gn:country_code":"LT",
    "gn:dem":46,
    "gn:feature_class":"P",
    "gn:feature_code":"PPL",
    "gn:name":"Paantvardys",
    "gn:population":0,
    "gn:timezone":"Europe/Vilnius",
    "iso:country":"LT",
    "name:lit_x_preferred":[
        "Paantvardys"
    ],
    "name:und_x_variant":[
        "Poantvardze",
        "Pantvardys Pirmasis",
        "Pantvardis",
        "Pantvardys I"
    ],
    "wof:name":"Paantvardys",
    "wof:placetype":"locality"
},
  "geometry": {"coordinates":[22.84942,55.13977],"type":"Point"}
}