{
  "type": "Feature",
  "properties": {
    "gn:admin1_code":"62.0",
    "gn:admin2_code":"77.0",
    "gn:asciiname":"Alanga",
    "gn:country_code":"LT",
    "gn:dem":45,
    "gn:feature_class":"P",
    "gn:feature_code":"PPL",
    "gn:name":"Alanga",
    "gn:population":0,
    "gn:timezone":"Europe/Vilnius",
    "iso:country":"LT",
    "name:und_x_variant":[
        "Alangi",
        "Alanga"
    ],
    "wof:name":"Alanga",
    "wof:placetype":"locality"
},
  "geometry": {"coordinates":[22.20801,55.30283000000001],"type":"Point"}
}