{
  "type": "Feature",
  "properties": {
    "gn:admin1_code":"57",
    "gn:admin2_code":"69.0",
    "gn:asciiname":"Ruda",
    "gn:country_code":"LT",
    "gn:dem":71,
    "gn:feature_class":"P",
    "gn:feature_code":"PPL",
    "gn:name":"R\u016bda",
    "gn:population":0,
    "gn:timezone":"Europe/Vilnius",
    "iso:country":"LT",
    "name:bos_x_preferred":[
        "Ruda"
    ],
    "name:ceb_x_preferred":[
        "Ruda"
    ],
    "name:ces_x_preferred":[
        "Ruda"
    ],
    "name:deu_x_preferred":[
        "Ruda"
    ],
    "name:epo_x_preferred":[
        "Ruda"
    ],
    "name:fra_x_preferred":[
        "Ruda"
    ],
    "name:glg_x_preferred":[
        "Ruda"
    ],
    "name:hrv_x_preferred":[
        "Ruda"
    ],
    "name:hun_x_preferred":[
        "Ruda"
    ],
    "name:ita_x_preferred":[
        "Ruda"
    ],
    "name:lit_x_preferred":[
        "R\u016bda"
    ],
    "name:lit_x_variant":[
        "Ruda"
    ],
    "name:nld_x_preferred":[
        "Ruda"
    ],
    "name:oci_x_preferred":[
        "Ruda"
    ],
    "name:pol_x_preferred":[
        "Ruda"
    ],
    "name:ron_x_preferred":[
        "Ruda"
    ],
    "name:slk_x_preferred":[
        "Ruda"
    ],
    "name:slv_x_preferred":[
        "Ruda"
    ],
    "name:spa_x_preferred":[
        "Ruda"
    ],
    "name:swe_x_preferred":[
        "Ruda"
    ],
    "name:uzb_x_preferred":[
        "Ruda"
    ],
    "wof:name":"Ruda",
    "wof:placetype":"locality"
},
  "geometry": {"coordinates":[23.74538,54.67704000000001],"type":"Point"}
}