{
  "type": "Feature",
  "properties": {
    "gn:admin1_code":"59.0",
    "gn:admin2_code":"58.0",
    "gn:asciiname":"Antanavas",
    "gn:country_code":"LT",
    "gn:dem":44,
    "gn:feature_class":"P",
    "gn:feature_code":"PPL",
    "gn:name":"Antanavas",
    "gn:population":0,
    "gn:timezone":"Europe/Vilnius",
    "iso:country":"LT",
    "name:und_x_variant":[
        "Antonovo",
        "Antanavas",
        "Antanava"
    ],
    "wof:name":"Antanavas",
    "wof:placetype":"locality"
},
  "geometry": {"coordinates":[23.30612,54.70451],"type":"Point"}
}